Workbook
Name Fraction_coal: [1]About!$C$50
Name GDP_per_capita_ratio: #REF!
Name INR: [2]Conversions!$E$105
Name Percent_rural: [1]About!$A$77
Name Percent_urban: [1]About!$A$76
Name Preferences.moneyunits: [2]Preferences!$C$9
Name quadrillion: [1]About!$B$79
Name Table4: '[1]AEO Table 4'!$C$34:$AI$72
Name Table5: '[1]AEO Table 5'!$C$31:$AI$58

Sheet About
A1: ICpUEfEBE Incremental Cost per Unit Energy for Electrified Building Equipment
A3: Sources: | B3: Cost of technologies except commerial heat pumps | D3: Commercial heating and water heating heat pump costs
B4: EIA | D4: NREL
B5: 2018 | D5: 2018
B6: Updated Buildings Sector Appliance and Equipment Costs and Efficiencies | D6: Electrification Futures Study Technology Report Figure Data
B7: https://www.eia.gov/analysis/studies/buildings/equipcosts/pdf/full.pdf | D7: https://data.nrel.gov/system/files/93/EFS_70485_figure_data.xlsx
B8: p. 9, 12, 29, 46, 51, 54, 58, 90, 92, 120, 123 | D8: Tables 22 and 23
B10: GDP Per Capita | D10: Commercial building equipment load factors
B11: The World Bank | D11: NREL
B12: 2021 | D12: 2018
B13: "GDP per capita (current US$) | D13: Electrification Futures Study: End-Use Electric Technology Cost and Performance Projections through 2050
B14: https://data.worldbank.org/indicator/NY.GDP.PCAP.CD | D14: https://www.nrel.gov/docs/fy18osti/70485.pdf
D15: P.90
B16: Residential Cooking Fuel Use and Costs
B17: NITI Aayog | D17: Residential building equipment stock and average annual energy consumption
B18: 2023 | D18: EIA
B19: India Energy Security Scenarios | D19: 20222023
B20: http://indiaenergy.gov.in/iess/docs/IESS_Version3.xlsx | D20: AEO 2022, AEO 2023
B21: Table XIII.a | D21: https://www.eia.gov/outlooks/aeo/tables_side.php
D22: Tables 4 and 21
A24: Notes:
A25: All policy-driven electrification in the EPS is assumed to rely on heat pumps,
A26: not electric resistance heating
A28: Methodology:
A29: For India, there is no fossil fuel use in the heating or other categories, so only the appliance tabs are
A30: used here.
A32: The primary driver of residential appliance energy consumption in India is cooking. We calculate the
A33: average energy used by equipment of different types, which allows us to find a $/BTU value. We then estimate
A34: the cost of switching to heat pump equipment based on the data from EIA
A35: and annual energy consumption.
A37: For commercial buildings, we use US data with a GDP per capita adjustment for India.
A39: US Notes:
... A57: other fuels based on the above mapping, with biomass mapped to petroleum.
B58: 54.77
A59: 2017 to 2012 USD
A60: 0.9366596
A61: 2016 to 2012 USD
A62: 0.95661377
A64: Ruppees per dollar
A65: 2012

Sheet EIA Costs
A1: Residential Gas Fired Furnaces
A2: DATA | B2: 2009 | C2: 2015 | D2: 2017 | H2: 2020 | J2: 2030 | L2: 2040 | N2: 2050
B3: Installed Base | C3: Installed Base | D3: Current Standard | E3: Typical | F3: ENERGY STAR (South) | G3: High | H3: Typical | I3: High | J3: Typical | K3: High | L3: Typical | M3: High | N3: Typical | O3: High
A4: Typical Input Capacity (kBtu/h) | B4: 80 | C4: 80 | D4: 80 | E4: 80 | F4: 80 | G4: 80 | H4: 80 | I4: 80 | J4: 80 | K4: 80 | L4: 80 | M4: 80 | N4: 80 | O4: 80
A5: AFUE (%) | B5: 80 | C5: 80 | D5: 80 | E5: 80 | F5: 90 | G5: 99 | H5: 80 | I5: 99 | J5: 80 | K5: 99 | L5: 80 | M5: 99 | N5: 80 | O5: 99
A6: Electric Consumption (kWh/yr)* | B6: 548 | C6: 522 | D6: 470 | E6: 470 | F6: 408 | G6: 418 | H6: 329 | I6: 334 | J6: 329 | K6: 334 | L6: 329 | M6: 334 | N6: 329 | O6: 334
A7: Average Life (yrs)** | B7: 16 | C7: 16 | D7: 16 | E7: 16 | F7: 16 | G7: 16 | H7: 16 | I7: 16 | J7: 16 | K7: 16 | L7: 16 | M7: 16 | N7: 16 | O7: 16
B8: 27 | C8: 27 | D8: 27 | E8: 27 | F8: 27 | G8: 27 | H8: 27 | I8: 27 | J8: 27 | K8: 27 | L8: 27 | M8: 27 | N8: 27 | O8: 27
A9: Retail Equipment Cost (2017$) | B9: 840 | C9: 860 | D9: 890 | E9: 890 | F9: 1150 | G9: 1620 | H9: 1080 | I9: 1620 | J9: 1080 | K9: 1620 | L9: 1080 | M9: 1620 | N9: 1080 | O9: 1620
A10: Total Installed Cost (2017$) | B10: 2000 | C10: 2020 | D10: 2050 | E10: 2050 | F10: 2560 | G10: 3040 | H10: 2240 | I10: 3040 | J10: 2240 | K10: 3040 | L10: 2240 | M10: 3040 | N10: 2240 | O10: 3040
A11: Annual Maintenance Cost (2017$) | B11: 40 | C11: 40 | D11: 40 | E11: 40 | F11: 40 | G11: 40 | H11: 40 | I11: 40 | J11: 40 | K11: 40 | L11: 40 | M11: 40 | N11: 40 | O11: 40
A13: Residential Oil Fired Furnaces
A14: DATA | B14: 2009 | C14: 2015 | D14: 2017 | H14: 2020 | J14: 2030 | L14: 2040 | N14: 2050
B15: Installed Base | C15: Installed Base | D15: Current Standard | E15: Typical | F15: ENERGY STAR | G15: High | H15: Typical | I15: High Typical | K15: High | L15: Typical | M15: High | N15: Typical | O15: High
A16: Typical Input Capacity (kBtu/h) | B16: 105 | C16: 105 | D16: 105 | E16: 105 | F16: 105 | G16: 105 | H16: 105 | I16: 105 | J16: 105 | K16: 105 | L16: 105 | M16: 105 | N16: 105 | O16: 105
A17: AFUE (%) | B17: 80 | C17: 83 | D17: 83 | E17: 83 | F17: 85 | G17: 97 | H17: 83 | I17: 97 | J17: 84 | K17: 97 | L17: 84 | M17: 97 | N17: 84 | O17: 97
A18: Electric Consumption (kWh/yr)* | B18: 490 | C18: 477 | D18: 477 | E18: 477 | F18: 466 | G18: 410 | H18: 477 | I18: 410 | J18: 472 | K18: 410 | L18: 472 | M18: 410 | N18: 472 | O18: 410
A19: Average Life (yrs)** | B19: 20 | C19: 20 | D19: 20 | E19: 20 | F19: 20 | G19: 20 | H19: 20 | I19: 20 | J19: 20 | K19: 20 | L19: 20 | M19: 20 | N19: 20 | O19: 20
B20: 33 | C20: 33 | D20: 33 | E20: 33 | F20: 33 | G20: 33 | H20: 33 | I20: 33 | J20: 33 | K20: 33 | L20: 33 | M20: 33 | N20: 33 | O20: 33
A21: Retail Equipment Cost (2017$) | B21: 2150 | C21: 2200 | D21: 2200 | E21: 2200 | F21: 2250 | G21: 2700 | H21: 2200 | I21: 2700 | J21: 2250 | K21: 2700 | L21: 2250 | M21: 2700 | N21: 2250 | O21: 2700
B22: 2350 | C22: 2900 | D22: 2900 | E22: 2900 | F22: 2950 | G22: 3450 | H22: 2900 | I22: 3450 | J22: 2950 | K22: 3450 | L22: 2950 | M22: 3450 | N22: 2950 | O22: 3450
A23: Total Installed Cost (2017$) | B23: 2700 | C23: 2750 | D23: 2750 | E23: 2750 | F23: 2950 | G23: 4350 | H23: 2750 | I23: 4350 | J23: 2750 | K23: 4350 | L23: 2750 | M23: 4350 | N23: 2750 | O23: 4350
B24: 3400 | C24: 5500 | D24: 5500 | E24: 5500 | F24: 5750 | G24: 8550 | H24: 5500 | I24: 8550 | J24: 5700 | K24: 8550 | L24: 5700 | M24: 8550 | N24: 5700 | O24: 8550
A25: Annual Maintenance Cost (2017$) | B25: 70 | C25: 70 | D25: 70 | E25: 70 | F25: 70 | G25: 200 | H25: 70 | I25: 200 | J25: 70 | K25: 200 | L25: 70 | M25: 200 | N25: 70 | O25: 200
A27: Residential Wood Pellet Stoves
A28: DATA | B28: 2009 | C28: 2015 | D28: 2017 | F28: 2020 | H28: 2030 | J28: 2040 | L28: 2050
B29: Installed Base | C29: Installed Base | D29: Typical | E29: High | F29: Typical | G29: High | H29: Typical | I29: High | J29: Typical | K29: High | L29: Typical | M29: High
A30: Typical Capacity (kBtu/h) | B30: 50 | C30: 50 | D30: 50 | E30: 50 | F30: 50 | G30: 50 | H30: 50 | I30: 50 | J30: 50 | K30: 50 | L30: 50 | M30: 50
A31: Efficiency (HHV) | B31: 65 | C31: 70 | D31: 76 | E31: 87 | F31: 76 | G31: 87 | H31: 77 | I31: 87 | J31: 78 | K31: 88 | L31: 79 | M31: 89
A32: Annual Electricity Consumption (kWh) | B32: 600 | C32: 600 | D32: 600 | E32: 600 | F32: 600 | G32: 600 | H32: 600 | I32: 600 | J32: 600 | K32: 600 | L32: 600 | M32: 600
A33: Average Life (yrs) | B33: 12 | C33: 12 | D33: 12 | E33: 12 | F33: 12 | G33: 12 | H33: 12 | I33: 12 | J33: 12 | K33: 12 | L33: 12 | M33: 12
B34: 25 | C34: 25 | D34: 25 | E34: 25 | F34: 25 | G34: 25 | H34: 25 | I34: 25 | J34: 25 | K34: 25 | L34: 25 | M34: 25
A35: Retail Equipment Cost (2017$) | B35: 3300 | C35: 3300 | D35: 3300 | E35: 4000 | F35: 3300 | G35: 4000 | H35: 3400 | I35: 4000 | J35: 3500 | K35: 4100 | L35: 3600 | M35: 4200
A36: Total Installed Cost (2017$) | B36: 4700 | C36: 4700 | D36: 4700 | E36: 5400 | F36: 4700 | G36: 5400 | H36: 4800 | I36: 5400 | J36: 4900 | K36: 5500 | L36: 5000 | M36: 5600
A37: Annual Maintenance Cost (2017$) | B37: 260 | C37: 260 | D37: 260 | E37: 260 | F37: 260 | G37: 260 | H37: 260 | I37: 260 | J37: 260 | K37: 260 | L37: 260 | M37: 260
A39: Residential Air Source Heat Pumps
A40: DATA | B40: 2009 | C40: 2015 | D40: 2017 | H40: 2020 | J40: 2030** | L40: 2040 | N40: 2050
B41: Installed Base | C41: Installed Base | D41: Current Standard | E41: Typical | F41: ENERGY STAR | G41: High | H41: Typical | I41: High | J41: Typical | K41: High | L41: Typical | M41: High | N41: Typical | O41: High
A42: Typical Capacity (kBtu/h) | B42: 36 | C42: 36 | D42: 36 | E42: 36 | F42: 36 | G42: 36 | H42: 36 | I42: 36 | J42: 36 | K42: 36 | L42: 36 | M42: 36 | N42: 36 | O42: 36
A43: SEER (Cooling)* | B43: 12 | C43: 13.1 | D43: 14 | E43: 15.3 | F43: 15 | G43: 19 | H43: 15.3 | I43: 19 | J43: 15.8 | K43: 19 | L43: 15.8 | M43: 19 | N43: 15.8 | O43: 19
A44: HSPF (Heating)* | B44: 7 .0 | C44: 7.9 | D44: 8.2 | E44: 8.6 | F44: 8.5 | G44: 9 | H44: 8.6 | I44: 9 | J44: 8.8 | K44: 9 | L44: 8.8 | M44: 9 | N44: 8.8 | O44: 9
A45: Average Life (yrs) | B45: 9 | C45: 9 | D45: 9 | E45: 9 | F45: 9 | G45: 9 | H45: 9 | I45: 9 | J45: 9 | K45: 9 | L45: 9 | M45: 9 | N45: 9 | O45: 9
B46: 22 | C46: 22 | D46: 22 | E46: 22 | F46: 22 | G46: 22 | H46: 22 | I46: 22 | J46: 22 | K46: 22 | L46: 22 | M46: 22 | N46: 22 | O46: 22
A47: Retail Equipment Cost (2017$)* | B47: 2550 | C47: 2800 | D47: 3350 | E47: 3600 | F47: 3500 | G47: 4550 | H47: 3600 | I47: 4550 | J47: 3700 | K47: 4550 | L47: 3700 | M47: 4550 | N47: 3700 | O47: 4550
A48: Total Installed Cost (2017$)* | B48: 3000 | C48: 3250 | D48: 4850 | E48: 5100 | F48: 4950 | G48: 6100 | H48: 5100 | I48: 6100 | J48: 5150 | K48: 6100 | L48: 5150 | M48: 6100 | N48: 5150 | O48: 6100
A49: Annual Maintenance Cost (2017$) | B49: 20 | C49: 20 | D49: 20 | E49: 20 | F49: 20 | G49: 20 | H49: 20 | I49: 20 | J49: 20 | K49: 20 | L49: 20 | M49: 20 | N49: 20 | O49: 20
B50: 125 | C50: 125 | D50: 125 | E50: 125 | F50: 125 | G50: 125 | H50: 125 | I50: 125 | J50: 125 | K50: 125 | L50: 125 | M50: 125 | N50: 125 | O50: 125
A52: Residential Gas Water Heater
B53: 2009 | C53: 2015 | D53: 2017 | H53: 2020 | J53: 2030 | L53: 2040 | N53: 2050
B54: Installed Base | C54: Installed Base | D54: Current Standard | E54: Typical | F54: ENERGY STAR | G54: High | H54: Typical | I54: High | J54: Typical | K54: High | L54: Typical | M54: High | N54: Typical | O54: High
A55: Typical Capacity (gal) | B55: 40 | C55: 40 | D55: 40 | E55: 40 | F55: 40 | G55: 40 | H55: 40 | I55: 40 | J55: 40 | K55: 40 | L55: 40 | M55: 40 | N55: 40 | O55: 40
A56: Uniform Energy Factor (UEF)* | B56: 0.58 | C56: 0.58 | D56: 0.61 | E56: 0.63 | F56: 0.66 | G56: 0.81 | H56: 0.63 | I56: 0.81 | J56: 0.63 | K56: 0.81 | L56: 0.63 | M56: 0.81 | N56: 0.63 | O56: 0.81
A57: Average Life (yrs) | B57: 6 | C57: 6 | D57: 6 | E57: 6 | F57: 6 | G57: 6 | H57: 6 | I57: 6 | J57: 6 | K57: 6 | L57: 6 | M57: 6 | N57: 6 | O57: 6
B58: 20 | C58: 20 | D58: 20 | E58: 20 | F58: 20 | G58: 20 | H58: 20 | I58: 20 | J58: 20 | K58: 20 | L58: 20 | M58: 20 | N58: 20 | O58: 20
A59: Retail Equipment Cost (2017$) | B59: 500 | C59: 500 | D59: 700 | E59: 750 | F59: 800 | G59: 1850 | H59: 750 | I59: 1850 | J59: 750 | K59: 1850 | L59: 750 | M59: 1850 | N59: 750 | O59: 1850
B60: 550 | C60: 550 | D60: 1000 | E60: 1200 | F60: 1350 | G60: 2100 | H60: 1200 | I60: 2100 | J60: 1200 | K60: 2100 | L60: 1200 | M60: 2100 | N60: 1200 | O60: 2100
A61: Total Installed Cost (2017$)** | B61: 1050 | C61: 1050 | D61: 1350 | E61: 1400 | F61: 1500 | G61: 2450 | H61: 1400 | I61: 2450 | J61: 1400 | K61: 2450 | L61: 1400 | M61: 2450 | N61: 1400 | O61: 2450
B62: 1050 | C62: 1050 | D62: 2300 | E62: 2450 | F62: 2550 | G62: 3700 | H62: 2450 | I62: 3700 | J62: 2450 | K62: 3700 | L62: 2450 | M62: 3700 | N62: 2450 | O62: 3700
A63: Annual Maintenance Cost (2017$)*** | B63: - | C63: - | D63: - | E63: - | F63: - | G63: - | H63: - | I63: - | J63: - | K63: - | L63: - | M63: - | N63: - | O63: -
A66: Residential Oil Water Heater
A67: DATA | B67: 2009 | C67: 2015 | E67: 2017 | G67: 2020 | I67: 2030 | K67: 2040 | M67: 2050
B68: Installed Base | C68: =AVERAGE('[3]EIA Costs'!D136:D137) -> 5225 | D68: Current Standard | E68: Typical | F68: High | G68: Typical | H68: High | I68: Typical | J68: High | K68: Typical | L68: High | M68: Typical | N68: High
A69: Typical Capacity (gal) | B69: 30 | C69: 32 | D69: 32 | E69: 32 | F69: 32 | G69: 32 | H69: 32 | I69: 32 | J69: 32 | K69: 32 | L69: 32 | M69: 32 | N69: 32
A70: Uniform Energy Factor (UEF)* | B70: 0.51 | C70: 0.51 | D70: 0.64 | E70: 0.67 | F70: 0.69 | G70: 0.67 | H70: 0.69 | I70: 0.67 | J70: 0.69 | K70: 0.67 | L70: 0.69 | M70: 0.67 | N70: 0.69
A71: Average Life (yrs) | B71: 6 | C71: 6 | D71: 6 | E71: 6 | F71: 6 | G71: 6 | H71: 6 | I71: 6 | J71: 6 | K71: 6 | L71: 6 | M71: 6 | N71: 6
B72: 20 | C72: 20 | D72: 20 | E72: 20 | F72: 20 | G72: 20 | H72: 20 | I72: 20 | J72: 20 | K72: 20 | L72: 20 | M72: 20 | N72: 20
A73: Retail Equipment Cost (2017$) | B73: 1350 | C73: 1350 | D73: 1500 | E73: 1600 | F73: 1600 | G73: 1600 | H73: 1600 | I73: 1600 | J73: 1600 | K73: 1600 | L73: 1600 | M73: 1600 | N73: 1600
B74: 1450 | C74: 1450 | D74: 1900 | E74: 2050 | F74: 2050 | G74: 2050 | H74: 2050 | I74: 2050 | J74: 2050 | K74: 2050 | L74: 2050 | M74: 2050 | N74: 2050
A75: Total Installed Cost (2017$) | B75: 2000 | C75: 2000 | D75: 2100 | E75: 2250 | F75: 2200 | G75: 2250 | H75: 2200 | I75: 2250 | J75: 2200 | K75: 2250 | L75: 2200 | M75: 2250 | N75: 2200
B76: 2100 | C76: 2100 | D76: 2700 | E76: 2850 | F76: 2850 | G76: 2850 | H76: 2850 | I76: 2850 | J76: 2850 | K76: 2850 | L76: 2850 | M76: 2850 | N76: 2850
A77: Annual Maintenance Cost (2017$) | B77: 180 | C77: 180 | D77: 180 | E77: 180 | F77: 180 | G77: 180 | H77: 180 | I77: 180 | J77: 180 | K77: 180 | L77: 180 | M77: 180 | N77: 180
A79: Residential Heat Pump Water Heater
A80: DATA | B80: 2009 | C80: 2015 | E80: 2017 | G80: 2020 | I80: 2030 | K80: 2040 | M80: 2050
B81: Installed Base | C81: Installed Base | D81: Typical | E81: ENERGY STAR | F81: High | G81: Typical | H81: High | I81: Typical | J81: High | K81: Typical | L81: High | M81: Typical | N81: High
A82: Typical Capacity (gal) | B82: 50 | C82: 50 | D82: 50 | E82: 50 | F82: 50 | G82: 50 | H82: 50 | I82: 50 | J82: 50 | K82: 50 | L82: 50 | M82: 50 | N82: 50
A83: Uniform Energy Factor (UEF)* | B83: 2.05 | C83: 2.05 | D83: 3.28 | E83: 2 | F83: 3.55 | G83: 3.28 | H83: 3.55 | I83: 3.28 | J83: 3.55 | K83: 3.28 | L83: 3.55 | M83: 3.28 | N83: 3.55
A84: Average Life (yrs) | B84: 6 | C84: 6 | D84: 6 | E84: 6 | F84: 6 | G84: 6 | H84: 6 | I84: 6 | J84: 6 | K84: 6 | L84: 6 | M84: 6 | N84: 6
B85: 20 | C85: 20 | D85: 20 | E85: 20 | F85: 20 | G85: 20 | H85: 20 | I85: 20 | J85: 20 | K85: 20 | L85: 20 | M85: 20 | N85: 20
A86: Retail Equipment Cost (2017$) | B86: 1550 | C86: 1100 | D86: 1200 | E86: 1050 | F86: 1200 | G86: 1200 | H86: 1200 | I86: 1200 | J86: 1200 | K86: 1200 | L86: 1200 | M86: 1200 | N86: 1200
B87: 1900 | C87: 1400 | D87: 1500 | E87: 1350 | F87: 2300 | G87: 1500 | H87: 2300 | I87: 1500 | J87: 2300 | K87: 1500 | L87: 2300 | M87: 1500 | N87: 2300
A88: Total Installed Cost (2017$) | B88: 1700 | C88: 1450 | D88: 1600 | E88: 1400 | F88: 1600 | G88: 1600 | H88: 1600 | I88: 1600 | J88: 1600 | K88: 1600 | L88: 1600 | M88: 1600 | N88: 1600
B89: 2450 | C89: 2500 | D89: 2550 | E89: 2400 | F89: 3350 | G89: 2550 | H89: 3350 | I89: 2550 | J89: 3350 | K89: 2550 | L89: 3350 | M89: 2550 | N89: 3350
A90: Annual Maintenance Cost (2017$) | B90: 20 | C90: 20 | D90: 20 | E90: 20 | F90: 20 | G90: 20 | H90: 20 | I90: 20 | J90: 20 | K90: 20 | L90: 20 | M90: 20 | N90: 20
A93: Commercial Gas Furnace
A94: DATA | B94: 2012 | D94: 2017 | F94: 2020 | H94: 2030 | J94: 2040 | L94: 2050
B95: Installed Base | C95: Current Standard | D95: Typical | E95: High | F95: Typical | G95: High | H95: Typical | I95: High | J95: Typical | K95: High | L95: Typical | M95: High
A96: Typical Input Capacity (kBtu/h) | B96: 400 | C96: 400 | D96: 400 | E96: 400 | F96: 400 | G96: 400 | H96: 400 | I96: 400 | J96: 400 | K96: 400 | L96: 400 | M96: 400
A97: Thermal Efficiency (%)* | B97: 80 | C97: 80 | D97: 80 | E97: 95 | F97: 80 | G97: 95 | H97: 81 | I97: 95 | J97: 81 | K97: 95 | L97: 81 | M97: 95
A98: Average Life (yrs) | B98: 23 | C98: 23 | D98: 23 | E98: 23 | F98: 23 | G98: 23 | H98: 23 | I98: 23 | J98: 23 | K98: 23 | L98: 23 | M98: 23
A99: Retail Equipment Cost (2017$) | B99: 1050 | C99: 1050 | D99: 1050 | E99: 2450 | F99: 1050 | G99: 2450 | H99: 1050 | I99: 2450 | J99: 1050 | K99: 2450 | L99: 1050 | M99: 2450
A100: Total Installed Cost (2017$) | B100: 2150 | C100: 2150 | D100: 2150 | E100: 3950 | F100: 2150 | G100: 3950 | H100: 2200 | I100: 3950 | J100: 2200 | K100: 3950 | L100: 2200 | M100: 3950
A101: Annual Maintenance Cost (2017$)** | B101: 170 | C101: 170 | D101: 170 | E101: 180 | F101: 170 | G101: 180 | H101: 170 | I101: 180 | J101: 170 | K101: 180 | L101: 170 | M101: 180
A104: Commercial Oil Furnace
A105: DATA | B105: 2012 | C105: 2017 | F105: 2020 | G105: 2030** | H105: 2040 | I105: 2050
B106: Installed Base | C106: Current Standard | D106: Typical | E106: High | F106: Typical | G106: Typical | H106: Typical | I106: Typical
A107: Typical Input Capacity (kBtu/h) | B107: 400 | C107: 400 | D107: 400 | E107: 400 | F107: 400 | G107: 400 | H107: 400 | I107: 400
A108: Thermal Efficiency (%)* | B108: 81 | C108: 81 | D108: 82 | E108: 85 | F108: 82 | G108: 82 | H108: 82 | I108: 82
A109: Average Life (yrs) | B109: 23 | C109: 23 | D109: 23 | E109: 23 | F109: 23 | G109: 23 | H109: 23 | I109: 23
A110: Retail Equipment Cost (2017$) | B110: 4650 | C110: 4650 | D110: 4700 | E110: 5050 | F110: 4700 | G110: 4700 | H110: 4700 | I110: 4700
A111: Total Installed Cost (2017$) | B111: 6550 | C111: 6550 | D111: 6600 | E111: 6750 | F111: 6600 | G111: 6600 | H111: 6600 | I111: 6600
...

Sheet EIA AEO Table 4
B1: ref2023.d020623a | C1: 2022 | D1: 2023 | E1: 2024 | F1: 2025 | G1: 2026 | H1: 2027 | I1: 2028 | J1: 2029 | K1: 2030 | L1: 2031 | M1: 2032 | N1: 2033 | O1: 2034 | P1: 2035 | Q1: 2036 | R1: 2037 | S1: 2038 | T1: 2039 | U1: 2040 | V1: 2041 | W1: 2042 | X1: 2043 | Y1: 2044 | Z1: 2045 | AA1: 2046 | AB1: 2047 | AC1: 2048 | AD1: 2049 | AE1: 2050
C3: Report | D3: Annual Energy Outlook 2023
C4: Scenario | D4: ref2023 | G4: Reference
C5: Datekey | D5: d020623a
C6: Release Date | E6: March 2023
A10: RKI000 | B10: 4. Residential Sector Key Indicators and Consumption | AF10: Average
B11: (quadrillion Btu, unless otherwise noted) | AF11: Annual
AF12: Change | AI12: 2019-
B13: Key Indicators and Consumption | C13: 2022 | D13: 2023 | E13: 2024 | F13: 2025 | G13: 2026 | H13: 2027 | I13: 2028 | J13: 2029 | K13: 2030 | L13: 2031 | M13: 2032 | N13: 2033 | O13: 2034 | P13: 2035 | Q13: 2036 | R13: 2037 | S13: 2038 | T13: 2039 | U13: 2040 | V13: 2041 | W13: 2042 | X13: 2043 | Y13: 2044 | Z13: 2045 | AA13: 2046 | AB13: 2047 | AC13: 2048 | AD13: 2049 | AE13: 2050 | AF13: 2022–2050 | AI13: 2050
B15: Key Indicators
B16: Households (millions)
A17: RKI000:ba_Single-Family | B17: Single-Family | C17: 86.924255 | D17: 87.748611 | E17: 88.618675 | F17: 89.519981 | G17: 90.411308 | H17: 91.302132 | I17: 92.198265 | J17: 93.091507 | K17: 93.970619 | L17: 94.836555 | M17: 95.694557 | N17: 96.533203 | O17: 97.347885 | P17: 98.154381 | Q17: 98.959145 | R17: 99.75724 | S17: 100.55006 | T17: 101.33466 | U17: 102.12499 | V17: 102.91761 | W17: 103.69783 | X17: 104.47331 | Y17: 105.24597 | Z17: 106.01605 | AA17: 106.78051 | AB17: 107.53815 | AC17: 108.28622 | AD17: 109.02242 | AE17: 109.74868 | AF17: 0.008362 | AI17: 0.007038
A18: RKI000:ba_Multifamily | B18: Multifamily | C18: 32.842152 | D18: 33.209229 | E18: 33.535469 | F18: 33.85815 | G18: 34.181629 | H18: 34.507633 | I18: 34.834255 | J18: 35.155056 | K18: 35.46513 | L18: 35.769081 | M18: 36.0718 | N18: 36.366608 | O18: 36.650593 | P18: 36.930111 | Q18: 37.212017 | R18: 37.496159 | S18: 37.783924 | T18: 38.073307 | U18: 38.36647 | V18: 38.656506 | W18: 38.941956 | X18: 39.223991 | Y18: 39.501945 | Z18: 39.776779 | AA18: 40.048443 | AB18: 40.322777 | AC18: 40.595905 | AD18: 40.869537 | AE18: 41.144089 | AF18: 0.008081 | AI18: 0.005591
A19: RKI000:ba_MobileHomes | B19: Mobile Homes | C19: 6.648376 | D19: 6.654435 | E19: 6.657747 | F19: 6.660283 | G19: 6.66859 | H19: 6.680898 | I19: 6.695705 | J19: 6.709839 | K19: 6.717811 | L19: 6.722091 | M19: 6.727011 | N19: 6.734098 | O19: 6.740673 | P19: 6.744905 | Q19: 6.74995 | R19: 6.752422 | S19: 6.751948 | T19: 6.750166 | U19: 6.750861 | V19: 6.753187 | W19: 6.756266 | X19: 6.759341 | Y19: 6.761881 | Z19: 6.763837 | AA19: 6.764435 | AB19: 6.765501 | AC19: 6.766449 | AD19: 6.766767 | AE19: 6.767235 | AF19: 0.000633 | AI19: -0.011866
A20: RKI000:ba_Total | B20: Total | C20: 126.41478 | D20: 127.61227 | E20: 128.81189 | F20: 130.03841 | G20: 131.26154 | H20: 132.49066 | I20: 133.72823 | J20: 134.95641 | K20: 136.15355 | L20: 137.32773 | M20: 138.49336 | N20: 139.63391 | O20: 140.73915 | P20: 141.82939 | Q20: 142.92111 | R20: 144.00583 | S20: 145.08594 | T20: 146.15813 | U20: 147.24231 | V20: 148.3273 | W20: 149.39606 | X20: 150.45664 | Y20: 151.50981 | Z20: 152.55667 | AA20: 153.59338 | AB20: 154.62643 | AC20: 155.64857 | AD20: 156.65874 | AE20: 157.66 | AF20: 0.00792 | AI20: 0.005904
A22: RKI000:ca_AverageHouseS | B22: Average House Square Footage | C22: 1798.9158 | D22: 1803.5209 | E22: 1808.4264 | F22: 1813.3185 | G22: 1818.0804 | H22: 1822.7229 | I22: 1827.2777 | J22: 1831.8 | K22: 1836.3394 | L22: 1840.8495 | M22: 1845.2855 | N22: 1849.6774 | O22: 1854.0608 | P22: 1858.4113 | Q22: 1862.6759 | R22: 1866.8663 | S22: 1870.9755 | T22: 1875.0114 | U22: 1878.9578 | V22: 1882.8684 | W22: 1886.7397 | X22: 1890.5779 | Y22: 1894.3921 | Z22: 1898.1798 | AA22: 1901.9388 | AB22: 1905.6209 | AC22: 1909.2523 | AD22: 1912.8229 | AE22: 1916.3303 | AF22: 0.002261 | AI22: 0.003435
B24: Energy Intensity
B25: (million Btu per household)
A26: RKI000:da_DeliveredEner | B26: Gross End-use Consumption 1/ | C26: 93.909477 | D26: 92.769119 | E26: 89.479935 | F26: 89.052956 | G26: 88.647408 | H26: 88.231392 | I26: 87.719673 | J26: 87.082458 | K26: 86.372932 | L26: 85.637901 | M26: 84.930008 | N26: 84.330368 | O26: 83.726021 | P26: 83.229088 | Q26: 82.803543 | R26: 82.42997 | S26: 82.039726 | T26: 81.693481 | U26: 81.360573 | V26: 81.06002 | W26: 80.817673 | X26: 80.633194 | Y26: 80.500008 | Z26: 80.389549 | AA26: 80.279945 | AB26: 80.223389 | AC26: 80.211197 | AD26: 80.229492 | AE26: 80.285049 | AF26: -0.005583 | AI26: -0.006009
A27: RKI000:da_TotalEnergyCo | B27: Delivered Energy Consumption | C27: 93.023323 | D27: 91.801674 | E27: 88.420021 | F27: 87.901169 | G27: 87.405548 | H27: 86.898582 | I27: 86.294922 | J27: 85.563858 | K27: 84.758438 | L27: 83.924873 | M27: 83.114105 | N27: 82.411514 | O27: 81.703484 | P27: 81.117577 | Q27: 80.600105 | R27: 80.131668 | S27: 79.641068 | T27: 79.188065 | U27: 78.743118 | V27: 78.324791 | W27: 77.958664 | X27: 77.644554 | Y27: 77.377632 | Z27: 77.127983 | AA27: 76.87487 | AB27: 76.670601 | AC27: 76.504471 | AD27: 76.365883 | AE27: 76.260414 | AF27: -0.007071 | AI27: -0.006295
B28: (thousand Btu per square foot)
A29: RKI000:ea_DeliveredEner | B29: Gross End-use Consumption 1/ | C29: 52.203377 | D29: 51.437782 | E29: 49.479443 | F29: 49.110489 | G29: 48.758793 | H29: 48.406364 | I29: 48.005661 | J29: 47.539284 | K29: 47.035389 | L29: 46.520859 | M29: 46.025402 | N29: 45.591934 | O29: 45.158184 | P29: 44.785076 | Q29: 44.454079 | R29: 44.15419 | S29: 43.848637 | T29: 43.569595 | U29: 43.300903 | V29: 43.051346 | W29: 42.83456 | X29: 42.650024 | Y29: 42.493847 | Z29: 42.350861 | AA29: 42.209534 | AB29: 42.098293 | AC29: 42.011837 | AD29: 41.942982 | AE29: 41.895203 | AF29: -0.007825 | AI29: -0.009412
A30: RKI000:ea_TotalEnergyCo | B30: Delivered Energy Consumption | C30: 51.710773 | D30: 50.901363 | E30: 48.893349 | F30: 48.475307 | G30: 48.075733 | H30: 47.675148 | I30: 47.225948 | J30: 46.710258 | K30: 46.156193 | L30: 45.590298 | M30: 45.041325 | N30: 44.554535 | O30: 44.067314 | P30: 43.648884 | Q30: 43.271141 | R30: 42.923088 | S30: 42.566601 | T30: 42.233379 | U30: 41.907867 | V30: 41.598656 | W30: 41.319248 | X30: 41.069218 | Y30: 40.845627 | Z30: 40.632603 | AA30: 40.419212 | AB30: 40.233921 | AC30: 40.070381 | AD30: 39.923134 | AE30: 39.795025 | AF30: -0.009311 | AI30: -0.009696
B32: Energy Consumption by Fuel
B33: Electricity 1/
A34: RKI000:fa_SpaceHeating | B34: Space Heating | C34: 0.74562 | D34: 0.744025 | E34: 0.657572 | F34: 0.656949 | G34: 0.655732 | H34: 0.653215 | I34: 0.649408 | J34: 0.644338 | K34: 0.637851 | L34: 0.630493 | M34: 0.623023 | N34: 0.615132 | O34: 0.606908 | P34: 0.599838 | Q34: 0.593122 | R34: 0.586547 | S34: 0.579423 | T34: 0.572275 | U34: 0.565611 | V34: 0.559325 | W34: 0.553414 | X34: 0.54783 | Y34: 0.542214 | Z34: 0.536676 | AA34: 0.531381 | AB34: 0.526393 | AC34: 0.521432 | AD34: 0.516688 | AE34: 0.512384 | AF34: -0.013309 | AI34: -0.009756
A35: RKI000:fa_SpaceCooling | B35: Space Cooling | C35: 0.853587 | D35: 0.735192 | E35: 0.890909 | F35: 0.91105 | G35: 0.930181 | H35: 0.950142 | I35: 0.969709 | J35: 0.988224 | K35: 1.004471 | L35: 1.019774 | M35: 1.036202 | N35: 1.052583 | O35: 1.069291 | P35: 1.088333 | Q35: 1.109122 | R35: 1.130924 | S35: 1.152515 | T35: 1.174549 | U35: 1.196908 | V35: 1.219416 | W35: 1.242558 | X35: 1.266365 | Y35: 1.29112 | Z35: 1.3168 | AA35: 1.344624 | AB35: 1.373569 | AC35: 1.403082 | AD35: 1.432529 | AE35: 1.463148 | AF35: 0.019433 | AI35: 0.016141
A36: RKI000:fa_WaterHeating | B36: Water Heating | C36: 0.599797 | D36: 0.598845 | E36: 0.598786 | F36: 0.599582 | G36: 0.599536 | H36: 0.599125 | I36: 0.59802 | J36: 0.596113 | K36: 0.593223 | L36: 0.589911 | M36: 0.586847 | N36: 0.586124 | O36: 0.586146 | P36: 0.588552 | Q36: 0.591464 | R36: 0.594365 | S36: 0.596931 | T36: 0.599321 | U36: 0.601795 | V36: 0.604464 | W36: 0.607404 | X36: 0.610584 | Y36: 0.613738 | Z36: 0.616835 | AA36: 0.620251 | AB36: 0.623921 | AC36: 0.627667 | AD36: 0.631618 | AE36: 0.63608 | AF36: 0.0021 | AI36: 0.001207
A37: RKI000:fa_Refrigeration | B37: Refrigeration | C37: 0.295558 | D37: 0.293987 | E37: 0.292668 | F37: 0.29163 | G37: 0.290783 | H37: 0.290158 | I37: 0.289778 | J37: 0.289615 | K37: 0.289659 | L37: 0.289986 | M37: 0.29063 | N37: 0.29157 | O37: 0.292795 | P37: 0.294343 | Q37: 0.296242 | R37: 0.298447 | S37: 0.30096 | T37: 0.303745 | U37: 0.306848 | V37: 0.310249 | W37: 0.313888 | X37: 0.317482 | Y37: 0.321024 | Z37: 0.324507 | AA37: 0.327915 | AB37: 0.33125 | AC37: 0.334496 | AD37: 0.337645 | AE37: 0.340702 | AF37: 0.00509 | AI37: 0.002205
A38: RKI000:fa_Cooking | B38: Cooking | C38: 0.055863 | D38: 0.056202 | E38: 0.056536 | F38: 0.056875 | G38: 0.057205 | H38: 0.05753 | I38: 0.057848 | J38: 0.058138 | K38: 0.058391 | L38: 0.058604 | M38: 0.058781 | N38: 0.058966 | O38: 0.05917 | P38: 0.059404 | Q38: 0.05968 | R38: 0.059996 | S38: 0.060304 | T38: 0.060601 | U38: 0.060895 | V38: 0.061182 | W38: 0.061454 | X38: 0.061714 | Y38: 0.061964 | Z38: 0.062203 | AA38: 0.062434 | AB38: 0.062659 | AC38: 0.06288 | AD38: 0.063098 | AE38: 0.063319 | AF38: 0.004485 | AI38: 0.002445
A39: RKI000:fa_ClothesDryers | B39: Clothes Dryers | C39: 0.222467 | D39: 0.227024 | E39: 0.231891 | F39: 0.237295 | G39: 0.242448 | H39: 0.247266 | I39: 0.251793 | J39: 0.25596 | K39: 0.259671 | L39: 0.263071 | M39: 0.266436 | N39: 0.269392 | O39: 0.272342 | P39: 0.275723 | Q39: 0.279342 | R39: 0.282799 | S39: 0.285963 | T39: 0.289075 | U39: 0.292206 | V39: 0.295411 | W39: 0.298723 | X39: 0.30216 | Y39: 0.305635 | Z39: 0.309109 | AA39: 0.31273 | AB39: 0.31651 | AC39: 0.320307 | AD39: 0.324172 | AE39: 0.328278 | AF39: 0.013993 | AI39: 0.011783
A40: RKI000:fa_Freezers | B40: Freezers | C40: 0.069007 | D40: 0.06885 | E40: 0.068687 | F40: 0.068516 | G40: 0.068318 | H40: 0.068105 | I40: 0.067922 | J40: 0.067761 | K40: 0.067615 | L40: 0.067486 | M40: 0.067377 | N40: 0.067287 | O40: 0.067216 | P40: 0.067169 | Q40: 0.067159 | R40: 0.067178 | S40: 0.067229 | T40: 0.067311 | U40: 0.067431 | V40: 0.067596 | W40: 0.067794 | X40: 0.068036 | Y40: 0.068326 | Z40: 0.068666 | AA40: 0.069053 | AB40: 0.069481 | AC40: 0.069904 | AD40: 0.070319 | AE40: 0.070729 | AF40: 0.000881 | AI40: -0.00151
A41: RKI000:fa_Lighting | B41: Lighting | C41: 0.22927 | D41: 0.21316 | E41: 0.206794 | F41: 0.205129 | G41: 0.2052 | H41: 0.206404 | I41: 0.20833 | J41: 0.210226 | K41: 0.209704 | L41: 0.209164 | M41: 0.208855 | N41: 0.208568 | O41: 0.208536 | P41: 0.209016 | Q41: 0.209627 | R41: 0.210178 | S41: 0.210558 | T41: 0.210954 | U41: 0.207703 | V41: 0.205012 | W41: 0.202911 | X41: 0.201467 | Y41: 0.200848 | Z41: 0.20064 | AA41: 0.200592 | AB41: 0.20073 | AC41: 0.200991 | AD41: 0.201423 | AE41: 0.202056 | AF41: -0.004503 | AI41: -0.010524
A42: RKI000:fa_ClothesWasher | B42: Clothes Washers 2/ | C42: 0.037489 | D42: 0.037813 | E42: 0.038144 | F42: 0.038486 | G42: 0.038827 | H42: 0.039168 | I42: 0.039519 | J42: 0.039875 | K42: 0.040246 | L42: 0.040617 | M42: 0.040992 | N42: 0.041365 | O42: 0.041733 | P42: 0.042099 | Q42: 0.042465 | R42: 0.042828 | S42: 0.043187 | T42: 0.043542 | U42: 0.043898 | V42: 0.044252 | W42: 0.044599 | X42: 0.044942 | Y42: 0.045282 | Z42: 0.045619 | AA42: 0.045952 | AB42: 0.046283 | AC42: 0.046611 | AD42: 0.046936 | AE42: 0.047258 | AF42: 0.008305 | AI42: 0.006674
A43: RKI000:fa_Dishwashers | B43: Dishwashers 2/ | C43: 0.027618 | D43: 0.028064 | E43: 0.028506 | F43: 0.028945 | G43: 0.02937 | H43: 0.029782 | I43: 0.030233 | J43: 0.030722 | K43: 0.031242 | L43: 0.031797 | M43: 0.032392 | N43: 0.033027 | O43: 0.033702 | P43: 0.034373 | Q43: 0.035043 | R43: 0.03571 | S43: 0.036375 | T43: 0.037036 | U43: 0.037698 | V43: 0.038359 | W43: 0.039015 | X43: 0.039667 | Y43: 0.040316 | Z43: 0.040962 | AA43: 0.041605 | AB43: 0.042245 | AC43: 0.042882 | AD43: 0.043514 | AE43: 0.044143 | AF43: 0.01689 | AI43: 0.014947
A44: RKI000:fa_ColorTelevisi | B44: Televisions and Related Equipment 3/ | C44: 0.185092 | D44: 0.181559 | E44: 0.178365 | F44: 0.175692 | G44: 0.172951 | H44: 0.170143 | I44: 0.167198 | J44: 0.164139 | K44: 0.160987 | L44: 0.157867 | M44: 0.154866 | N44: 0.151867 | O44: 0.148998 | P44: 0.146585 | Q44: 0.144473 | R44: 0.142566 | S44: 0.14076 | T44: 0.139189 | U44: 0.13791 | V44: 0.136911 | W44: 0.136207 | X44: 0.135755 | Y44: 0.135537 | Z44: 0.135552 | AA44: 0.135802 | AB44: 0.136265 | AC44: 0.13685 | AD44: 0.137593 | AE44: 0.138527 | AF44: -0.010296 | AI44: 0.007737
A45: RKI000:fa_PersonalCompu | B45: Computers and Related Equipment 4/ | C45: 0.120106 | D45: 0.118562 | E45: 0.116931 | F45: 0.115363 | G45: 0.113493 | H45: 0.111328 | I45: 0.108857 | J45: 0.106117 | K45: 0.103168 | L45: 0.100088 | M45: 0.09698 | N45: 0.093786 | O45: 0.09061 | P45: 0.087647 | Q45: 0.084848 | R45: 0.082133 | S45: 0.079493 | T45: 0.077008 | U45: 0.074726 | V45: 0.072652 | W45: 0.070825 | X45: 0.069227 | Y45: 0.067875 | Z45: 0.066753 | AA45: 0.065956 | AB45: 0.065417 | AC45: 0.065087 | AD45: 0.064993 | AE45: 0.065107 | AF45: -0.021632 | AI45: -0.026585
... A48: RKI000:fa_DeliveredEner | B48: Electricity Subtotal | C48: 5.259642 | D48: 5.170129 | E48: 5.25044 | F48: 5.307276 | G48: 5.362642 | H48: 5.422232 | I48: 5.47432 | J48: 5.518295 | K48: 5.554088 | L48: 5.587194 | M48: 5.622504 | N48: 5.659284 | O48: 5.694947 | P48: 5.742076 | Q48: 5.795343 | R48: 5.852389 | S48: 5.907059 | T48: 5.963454 | U48: 6.0203 | V48: 6.08025 | W48: 6.145656 | X48: 6.215189 | Y48: 6.288645 | Z48: 6.365698 | AA48: 6.448222 | AB48: 6.53561 | AC48: 6.625218 | AD48: 6.717607 | AE48: 6.816999 | AF48: 0.009306 | AI48: 0.006181
B49: On-site Generation for Own Use | C49: 0.112023 | D49: 0.123458 | E49: 0.136529 | F49: 0.149777 | G49: 0.163009 | H49: 0.176585 | I49: 0.19053 | J49: 0.204945 | K49: 0.21982 | L49: 0.235246 | M49: 0.25149 | N49: 0.267937 | O49: 0.28465 | P49: 0.299474 | Q49: 0.314918 | R49: 0.330968 | S49: 0.348012 | T49: 0.366187 | U49: 0.3854 | V49: 0.405709 | W49: 0.427124 | X49: 0.44966 | Y49: 0.473071 | Z49: 0.497574 | AA49: 0.522997 | AB49: 0.549355 | AC49: 0.576946 | AD49: 0.605268 | AE49: 0.634524 | AF49: 0.063893
B50: Purchased Electricity | C50: 5.147618 | D50: 5.046671 | E50: 5.113911 | F50: 5.157499 | G50: 5.199634 | H50: 5.245647 | I50: 5.28379 | J50: 5.31335 | K50: 5.334268 | L50: 5.351949 | M50: 5.371014 | N50: 5.391346 | O50: 5.410297 | P50: 5.442602 | Q50: 5.480425 | R50: 5.521421 | S50: 5.559047 | T50: 5.597267 | U50: 5.6349 | V50: 5.674541 | W50: 5.718532 | X50: 5.765529 | Y50: 5.815574 | Z50: 5.868124 | AA50: 5.925225 | AB50: 5.986255 | AC50: 6.048272 | AD50: 6.112339 | AE50: 6.182475 | AF50: 0.006564
A51: RKI000:ga_SpaceHeating | AI51: -0.006376
A52: RKI000:ga_SpaceCooling | B52: Natural Gas | AI52: -0.003157
A53: RKI000:ga_WaterHeating | B53: Space Heating | C53: 3.73693 | D53: 3.786134 | E53: 3.524206 | F53: 3.534772 | G53: 3.540792 | H53: 3.53828 | I53: 3.529304 | J53: 3.510945 | K53: 3.487897 | L53: 3.462235 | M53: 3.436536 | N53: 3.41919 | O53: 3.398954 | P53: 3.379413 | Q53: 3.362053 | R53: 3.346112 | S53: 3.329438 | T53: 3.314799 | U53: 3.301509 | V53: 3.288682 | W53: 3.276622 | X53: 3.266367 | Y53: 3.257648 | Z53: 3.247816 | AA53: 3.234627 | AB53: 3.222775 | AC53: 3.212637 | AD53: 3.202551 | AE53: 3.191122 | AF53: -0.005623 | AI53: 0.005355
A54: RKI000:ga_Cooking | B54: Space Cooling | C54: 0.058888 | D54: 0.05053 | E54: 0.059461 | F54: 0.059824 | G54: 0.060086 | H54: 0.060237 | I54: 0.060283 | J54: 0.060235 | K54: 0.060099 | L54: 0.05989 | M54: 0.059666 | N54: 0.05942 | O54: 0.059215 | P54: 0.059099 | Q54: 0.059116 | R54: 0.059266 | S54: 0.059431 | T54: 0.059636 | U54: 0.059841 | V54: 0.060023 | W54: 0.060231 | X54: 0.060454 | Y54: 0.060706 | Z54: 0.060936 | AA54: 0.061137 | AB54: 0.06134 | AC54: 0.061597 | AD54: 0.06187 | AE54: 0.062122 | AF54: 0.001911 | AI54: 0.004044
A55: RKI000:ga_ClothesDryers | B55: Water Heating | C55: 0.982988 | D55: 0.980209 | E55: 0.989771 | F55: 1.005515 | G55: 1.022239 | H55: 1.038243 | I55: 1.053751 | J55: 1.066705 | K55: 1.078192 | L55: 1.087593 | M55: 1.096298 | N55: 1.104917 | O55: 1.113101 | P55: 1.121259 | Q55: 1.129493 | R55: 1.13727 | S55: 1.144052 | T55: 1.151144 | U55: 1.158029 | V55: 1.164591 | W55: 1.171285 | X55: 1.178668 | Y55: 1.186804 | Z55: 1.194551 | AA55: 1.199459 | AB55: 1.205508 | AC55: 1.213089 | AD55: 1.221263 | AE55: 1.228967 | AF55: 0.008008 | AI55: 0.012555
A56: RKI000:ga_OtherNatGas | B56: Cooking | C56: 0.103539 | D56: 0.103721 | E56: 0.10393 | F56: 0.104173 | G56: 0.104412 | H56: 0.10465 | I56: 0.10492 | J56: 0.105265 | K56: 0.105678 | L56: 0.106176 | M56: 0.106773 | N56: 0.107469 | O56: 0.108208 | P56: 0.109004 | Q56: 0.109852 | R56: 0.110743 | S56: 0.111655 | T56: 0.112587 | U56: 0.113552 | V56: 0.114545 | W56: 0.115558 | X56: 0.116595 | Y56: 0.117656 | Z56: 0.118736 | AA56: 0.119822 | AB56: 0.120911 | AC56: 0.121992 | AD56: 0.123053 | AE56: 0.12409 | AF56: 0.006487 | AI56: -0.004016
A57: RKI000:ga_DeliveredEner | B57: Clothes Dryers | C57: 0.039713 | D57: 0.040031 | E57: 0.040827 | F57: 0.041872 | G57: 0.042965 | H57: 0.044042 | I57: 0.04506 | J57: 0.045927 | K57: 0.046698 | L57: 0.047413 | M57: 0.048116 | N57: 0.04879 | O57: 0.049444 | P57: 0.05008 | Q57: 0.050721 | R57: 0.051386 | S57: 0.052048 | T57: 0.052755 | U57: 0.053475 | V57: 0.054198 | W57: 0.054938 | X57: 0.055711 | Y57: 0.056512 | Z57: 0.057282 | AA57: 0.057895 | AB57: 0.058551 | AC57: 0.059274 | AD57: 0.060025 | AE57: 0.06075 | AF57: 0.015298 | AI57: -0.003266
B58: Other Uses 6/ | C58: 0.227335 | D58: 0.225826 | E58: 0.226278 | F58: 0.227805 | G58: 0.22943 | H58: 0.230812 | I58: 0.231871 | J58: 0.232141 | K58: 0.231911 | L58: 0.231396 | M58: 0.230831 | N58: 0.230173 | O58: 0.229503 | P58: 0.228858 | Q58: 0.228335 | R58: 0.227843 | S58: 0.227266 | T58: 0.226819 | U58: 0.226353 | V58: 0.225855 | W58: 0.225413 | X58: 0.225093 | Y58: 0.224878 | Z58: 0.224557 | AA58: 0.223546 | AB58: 0.222772 | AC58: 0.222338 | AD58: 0.222088 | AE58: 0.221789 | AF58: -0.000882
B59: Delivered Energy | C59: 5.149392 | D59: 5.186451 | E59: 4.944474 | F59: 4.973961 | G59: 4.999925 | H59: 5.016266 | I59: 5.025189 | J59: 5.021217 | K59: 5.010476 | L59: 4.994703 | M59: 4.978221 | N59: 4.969959 | O59: 4.958426 | P59: 4.947713 | Q59: 4.93957 | R59: 4.932621 | S59: 4.923891 | T59: 4.91774 | U59: 4.912759 | V59: 4.907895 | W59: 4.904047 | X59: 4.902888 | Y59: 4.904204 | Z59: 4.903876 | AA59: 4.896485 | AB59: 4.891857 | AC59: 4.890927 | AD59: 4.890851 | AE59: 4.888841 | AF59: -0.001853
A60: RKI000:ha_SpaceHeating | AI60: -0.023495
A61: RKI000:ha_WaterHeating | B61: Distillate Fuel Oil 7/ | AI61: -0.024363
A62: RKI000:Other_ha_ha | B62: Space Heating | C62: 0.381925 | D62: 0.383536 | E62: 0.32749 | F62: 0.323264 | G62: 0.318155 | H62: 0.312652 | I62: 0.306879 | J62: 0.300867 | K62: 0.29494 | L62: 0.289076 | M62: 0.283366 | N62: 0.278218 | O62: 0.273003 | P62: 0.267846 | Q62: 0.262899 | R62: 0.258123 | S62: 0.253507 | T62: 0.249017 | U62: 0.244715 | V62: 0.240453 | W62: 0.236259 | X62: 0.232016 | Y62: 0.22792 | Z62: 0.223829 | AA62: 0.219666 | AB62: 0.215518 | AC62: 0.211458 | AD62: 0.20742 | AE62: 0.203485 | AF62: -0.022236 | AI62: -0.00612
A63: RKI000:ha_DeliveredEner | B63: Water Heating | C63: 0.043041 | D63: 0.040315 | E63: 0.038573 | F63: 0.037466 | G63: 0.036442 | H63: 0.035552 | I63: 0.03481 | J63: 0.034219 | K63: 0.033803 | L63: 0.033317 | M63: 0.032805 | N63: 0.03227 | O63: 0.031735 | P63: 0.031182 | Q63: 0.030637 | R63: 0.030092 | S63: 0.029556 | T63: 0.029034 | U63: 0.028531 | V63: 0.028038 | W63: 0.027574 | X63: 0.027129 | Y63: 0.026715 | Z63: 0.026321 | AA63: 0.025933 | AB63: 0.025563 | AC63: 0.025213 | AD63: 0.024871 | AE63: 0.024542 | AF63: -0.019863 | AI63: -0.023188
B64: Other Uses 8/ | C64: 0.007531 | D64: 0.007367 | E64: 0.00733 | F64: 0.007369 | G64: 0.007389 | H64: 0.007397 | I64: 0.007396 | J64: 0.007385 | K64: 0.00737 | L64: 0.00735 | M64: 0.007331 | N64: 0.007312 | O64: 0.007293 | P64: 0.007275 | Q64: 0.007257 | R64: 0.007239 | S64: 0.007222 | T64: 0.007205 | U64: 0.007189 | V64: 0.007171 | W64: 0.007155 | X64: 0.007139 | Y64: 0.007125 | Z64: 0.007111 | AA64: 0.007093 | AB64: 0.007076 | AC64: 0.007061 | AD64: 0.007047 | AE64: 0.007033 | AF64: -0.002442
B65: Delivered Energy | C65: 0.432497 | D65: 0.431217 | E65: 0.373393 | F65: 0.368099 | G65: 0.361986 | H65: 0.355601 | I65: 0.349085 | J65: 0.342471 | K65: 0.336113 | L65: 0.329744 | M65: 0.323502 | N65: 0.317799 | O65: 0.312032 | P65: 0.306303 | Q65: 0.300794 | R65: 0.295454 | S65: 0.290284 | T65: 0.285256 | U65: 0.280434 | V65: 0.275663 | W65: 0.270988 | X65: 0.266283 | Y65: 0.26176 | Z65: 0.257261 | AA65: 0.252692 | AB65: 0.248185 | AC65: 0.24379 | AD65: 0.239424 | AE65: 0.235174 | AF65: -0.021524
A66: RKI000:ia_SpaceHeating | AI66: -0.016118
A67: RKI000:ia_WaterHeating | B67: Propane | AI67: -0.026517
A68: RKI000:ia_Cooking | B68: Space Heating | C68: 0.340393 | D68: 0.328603 | E68: 0.298348 | F68: 0.294508 | G68: 0.291721 | H68: 0.289288 | I68: 0.286684 | J68: 0.283808 | K68: 0.280645 | L68: 0.277305 | M68: 0.27385 | N68: 0.270671 | O68: 0.267416 | P68: 0.264355 | Q68: 0.261527 | R68: 0.258915 | S68: 0.25637 | T68: 0.253968 | U68: 0.251703 | V68: 0.249546 | W68: 0.247417 | X68: 0.245385 | Y68: 0.243459 | Z68: 0.241594 | AA68: 0.239707 | AB68: 0.237884 | AC68: 0.236081 | AD68: 0.234328 | AE68: 0.232634 | AF68: -0.013502 | AI68: -0.01258
A69: RKI000:ia_OtherUses | B69: Water Heating | C69: 0.060221 | D69: 0.057039 | E69: 0.054758 | F69: 0.053262 | G69: 0.052171 | H69: 0.051295 | I69: 0.050536 | J69: 0.04987 | K69: 0.049293 | L69: 0.048556 | M69: 0.047707 | N69: 0.046804 | O69: 0.045866 | P69: 0.044928 | Q69: 0.044022 | R69: 0.043145 | S69: 0.042286 | T69: 0.041473 | U69: 0.040704 | V69: 0.039977 | W69: 0.0393 | X69: 0.038685 | Y69: 0.038131 | Z69: 0.037623 | AA69: 0.03713 | AB69: 0.036677 | AC69: 0.036256 | AD69: 0.035863 | AE69: 0.035496 | AF69: -0.018702 | AI69: 0.016822
A70: RKI000:ia_DeliveredEner | B70: Cooking | C70: 0.016931 | D70: 0.016749 | E70: 0.016561 | F70: 0.016368 | G70: 0.016165 | H70: 0.015948 | I70: 0.015723 | J70: 0.015489 | K70: 0.015245 | L70: 0.014994 | M70: 0.014737 | N70: 0.014521 | O70: 0.014345 | P70: 0.01421 | Q70: 0.014119 | R70: 0.014071 | S70: 0.014016 | T70: 0.013956 | U70: 0.01389 | V70: 0.013818 | W70: 0.013741 | X70: 0.013661 | Y70: 0.013581 | Z70: 0.013502 | AA70: 0.013427 | AB70: 0.013357 | AC70: 0.013293 | AD70: 0.013233 | AE70: 0.013175 | AF70: -0.008917 | AI70: -0.009641
B71: Other Uses 9/ | C71: 0.07354 | D71: 0.073881 | E71: 0.075038 | F71: 0.076967 | G71: 0.079218 | H71: 0.081565 | I71: 0.083859 | J71: 0.086047 | K71: 0.088106 | L71: 0.090054 | M71: 0.091918 | N71: 0.093709 | O71: 0.095459 | P71: 0.097231 | Q71: 0.099066 | R71: 0.100945 | S71: 0.102823 | T71: 0.104744 | U71: 0.106688 | V71: 0.108645 | W71: 0.110621 | X71: 0.112653 | Y71: 0.114748 | Z71: 0.116869 | AA71: 0.118934 | AB71: 0.121035 | AC71: 0.123162 | AD71: 0.125322 | AE71: 0.127509 | AF71: 0.01985
A72: RKI000:ja_MarketedRenew | B72: Delivered Energy | C72: 0.491085 | D72: 0.476272 | E72: 0.444705 | F72: 0.441105 | G72: 0.439275 | H72: 0.438096 | I72: 0.436801 | J72: 0.435214 | K72: 0.433289 | L72: 0.430909 | M72: 0.428213 | N72: 0.425705 | O72: 0.423085 | P72: 0.420724 | Q72: 0.418734 | R72: 0.417076 | S72: 0.415495 | T72: 0.414142 | U72: 0.412984 | V72: 0.411986 | W72: 0.41108 | X72: 0.410385 | Y72: 0.409919 | Z72: 0.409588 | AA72: 0.409198 | AB72: 0.408952 | AC72: 0.408792 | AD72: 0.408746 | AE72: 0.408814 | AF72: -0.006527 | AI72: -0.0176
B74: Marketed Renewables (wood) 10/ | C74: 0.538932 | D74: 0.57441 | E74: 0.513068 | F74: 0.489864 | G74: 0.472164 | H74: 0.45764 | I74: 0.4452 | J74: 0.435137 | K74: 0.426017 | L74: 0.417909 | M74: 0.409804 | N74: 0.402631 | O74: 0.395039 | P74: 0.387514 | Q74: 0.379935 | R74: 0.372857 | S74: 0.366083 | T74: 0.359575 | U74: 0.353241 | V74: 0.347622 | W74: 0.342071 | X74: 0.337054 | Y74: 0.332011 | Z74: 0.327538 | AA74: 0.323872 | AB74: 0.320083 | AC74: 0.316089 | AD74: 0.312111 | AE74: 0.308024 | AF74: -0.019781
A75: RKI000:ka_SpaceHeating | AI75: -0.009142
A76: RKI000:ka_SpaceCooling | B76: Energy Consumption by End Use 1/ | AI76: 0.015056
A77: RKI000:ka_WaterHeating | B77: Space Heating | C77: 5.743799 | D77: 5.816709 | E77: 5.320683 | F77: 5.299356 | G77: 5.278564 | H77: 5.251076 | I77: 5.217474 | J77: 5.175095 | K77: 5.127351 | L77: 5.077018 | M77: 5.02658 | N77: 4.985841 | O77: 4.94132 | P77: 4.898966 | Q77: 4.859536 | R77: 4.822555 | S77: 4.784821 | T77: 4.749634 | U77: 4.716778 | V77: 4.685628 | W77: 4.655783 | X77: 4.628654 | Y77: 4.603252 | Z77: 4.577453 | AA77: 4.549252 | AB77: 4.522653 | AC77: 4.497698 | AD77: 4.473098 | AE77: 4.447649 | AF77: -0.009092 | AI77: 0.002531
A78: RKI000:ka_Refrigeration | B78: Space Cooling | C78: 0.912475 | D78: 0.785722 | E78: 0.95037 | F78: 0.970874 | G78: 0.990268 | H78: 1.010379 | I78: 1.029992 | J78: 1.048459 | K78: 1.064569 | L78: 1.079664 | M78: 1.095868 | N78: 1.112003 | O78: 1.128507 | P78: 1.147432 | Q78: 1.168238 | R78: 1.19019 | S78: 1.211945 | T78: 1.234185 | U78: 1.256749 | V78: 1.279439 | W78: 1.302789 | X78: 1.326819 | Y78: 1.351826 | Z78: 1.377735 | AA78: 1.405762 | AB78: 1.434909 | AC78: 1.464679 | AD78: 1.494399 | AE78: 1.52527 | AF78: 0.018518 | AI78: 0.002205
A79: RKI000:ka_Cooking | B79: Water Heating | C79: 1.686047 | D79: 1.676408 | E79: 1.681888 | F79: 1.695826 | G79: 1.710388 | H79: 1.724215 | I79: 1.737117 | J79: 1.746907 | K79: 1.75451 | L79: 1.759377 | M79: 1.763657 | N79: 1.770115 | O79: 1.776848 | P79: 1.785921 | Q79: 1.795616 | R79: 1.804871 | S79: 1.812825 | T79: 1.820973 | U79: 1.829057 | V79: 1.837071 | W79: 1.845563 | X79: 1.855066 | Y79: 1.865388 | Z79: 1.87533 | AA79: 1.882772 | AB79: 1.891669 | AC79: 1.902225 | AD79: 1.913615 | AE79: 1.925086 | AF79: 0.004746 | AI79: 0.002236
A80: RKI000:ka_ClothesDryers | B80: Refrigeration | C80: 0.295558 | D80: 0.293987 | E80: 0.292668 | F80: 0.29163 | G80: 0.290783 | H80: 0.290158 | I80: 0.289778 | J80: 0.289615 | K80: 0.289659 | L80: 0.289986 | M80: 0.29063 | N80: 0.29157 | O80: 0.292795 | P80: 0.294343 | Q80: 0.296242 | R80: 0.298447 | S80: 0.30096 | T80: 0.303745 | U80: 0.306848 | V80: 0.310249 | W80: 0.313888 | X80: 0.317482 | Y80: 0.321024 | Z80: 0.324507 | AA80: 0.327915 | AB80: 0.33125 | AC80: 0.334496 | AD80: 0.337645 | AE80: 0.340702 | AF80: 0.00509 | AI80: 0.011904
A81: RKI000:ka_Freezers | B81: Cooking | C81: 0.176332 | D81: 0.176672 | E81: 0.177028 | F81: 0.177417 | G81: 0.177783 | H81: 0.178128 | I81: 0.17849 | J81: 0.178893 | K81: 0.179315 | L81: 0.179774 | M81: 0.180291 | N81: 0.180956 | O81: 0.181724 | P81: 0.182619 | Q81: 0.183652 | R81: 0.18481 | S81: 0.185975 | T81: 0.187144 | U81: 0.188336 | V81: 0.189544 | W81: 0.190752 | X81: 0.191971 | Y81: 0.193201 | Z81: 0.194441 | AA81: 0.195682 | AB81: 0.196927 | AC81: 0.198164 | AD81: 0.199384 | AE81: 0.200584 | AF81: 0.004613 | AI81: -0.00151
A82: RKI000:ka_Lighting | B82: Clothes Dryers | C82: 0.262179 | D82: 0.267055 | E82: 0.272718 | F82: 0.279166 | G82: 0.285413 | H82: 0.291308 | I82: 0.296853 | J82: 0.301887 | K82: 0.306369 | L82: 0.310484 | M82: 0.314552 | N82: 0.318182 | O82: 0.321786 | P82: 0.325803 | Q82: 0.330063 | R82: 0.334185 | S82: 0.338012 | T82: 0.341829 | U82: 0.345681 | V82: 0.349609 | W82: 0.353661 | X82: 0.357871 | Y82: 0.362147 | Z82: 0.366391 | AA82: 0.370625 | AB82: 0.375061 | AC82: 0.379581 | AD82: 0.384197 | AE82: 0.389028 | AF82: 0.014194 | AI82: -0.010524
A83: RKI000:ka_ClothesWasher | B83: Freezers | C83: 0.069007 | D83: 0.06885 | E83: 0.068687 | F83: 0.068516 | G83: 0.068318 | H83: 0.068105 | I83: 0.067922 | J83: 0.067761 | K83: 0.067615 | L83: 0.067486 | M83: 0.067377 | N83: 0.067287 | O83: 0.067216 | P83: 0.067169 | Q83: 0.067159 | R83: 0.067178 | S83: 0.067229 | T83: 0.067311 | U83: 0.067431 | V83: 0.067596 | W83: 0.067794 | X83: 0.068036 | Y83: 0.068326 | Z83: 0.068666 | AA83: 0.069053 | AB83: 0.069481 | AC83: 0.069904 | AD83: 0.070319 | AE83: 0.070729 | AF83: 0.000881 | AI83: 0.006674
A84: RKI000:ka_Dishwashers | B84: Lighting | C84: 0.22927 | D84: 0.21316 | E84: 0.206794 | F84: 0.205129 | G84: 0.2052 | H84: 0.206404 | I84: 0.20833 | J84: 0.210226 | K84: 0.209704 | L84: 0.209164 | M84: 0.208855 | N84: 0.208568 | O84: 0.208536 | P84: 0.209016 | Q84: 0.209627 | R84: 0.210178 | S84: 0.210558 | T84: 0.210954 | U84: 0.207703 | V84: 0.205012 | W84: 0.202911 | X84: 0.201467 | Y84: 0.200848 | Z84: 0.20064 | AA84: 0.200592 | AB84: 0.20073 | AC84: 0.200991 | AD84: 0.201423 | AE84: 0.202056 | AF84: -0.004503 | AI84: 0.014947
A85: RKI000:ka_ColorTelevisi | B85: Clothes Washers 2/ | C85: 0.037489 | D85: 0.037813 | E85: 0.038144 | F85: 0.038486 | G85: 0.038827 | H85: 0.039168 | I85: 0.039519 | J85: 0.039875 | K85: 0.040246 | L85: 0.040617 | M85: 0.040992 | N85: 0.041365 | O85: 0.041733 | P85: 0.042099 | Q85: 0.042465 | R85: 0.042828 | S85: 0.043187 | T85: 0.043542 | U85: 0.043898 | V85: 0.044252 | W85: 0.044599 | X85: 0.044942 | Y85: 0.045282 | Z85: 0.045619 | AA85: 0.045952 | AB85: 0.046283 | AC85: 0.046611 | AD85: 0.046936 | AE85: 0.047258 | AF85: 0.008305 | AI85: 0.007737
A86: RKI000:ka_PersonalCompu | B86: Dishwashers 2/ | C86: 0.027618 | D86: 0.028064 | E86: 0.028506 | F86: 0.028945 | G86: 0.02937 | H86: 0.029782 | I86: 0.030233 | J86: 0.030722 | K86: 0.031242 | L86: 0.031797 | M86: 0.032392 | N86: 0.033027 | O86: 0.033702 | P86: 0.034373 | Q86: 0.035043 | R86: 0.03571 | S86: 0.036375 | T86: 0.037036 | U86: 0.037698 | V86: 0.038359 | W86: 0.039015 | X86: 0.039667 | Y86: 0.040316 | Z86: 0.040962 | AA86: 0.041605 | AB86: 0.042245 | AC86: 0.042882 | AD86: 0.043514 | AE86: 0.044143 | AF86: 0.01689 | AI86: -0.026585
A87: RKI000:ka_FurnaceFans | B87: Televisions and Related Equipment 3/ | C87: 0.185092 | D87: 0.181559 | E87: 0.178365 | F87: 0.175692 | G87: 0.172951 | H87: 0.170143 | I87: 0.167198 | J87: 0.164139 | K87: 0.160987 | L87: 0.157867 | M87: 0.154866 | N87: 0.151867 | O87: 0.148998 | P87: 0.146585 | Q87: 0.144473 | R87: 0.142566 | S87: 0.14076 | T87: 0.139189 | U87: 0.13791 | V87: 0.136911 | W87: 0.136207 | X87: 0.135755 | Y87: 0.135537 | Z87: 0.135552 | AA87: 0.135802 | AB87: 0.136265 | AC87: 0.13685 | AD87: 0.137593 | AE87: 0.138527 | AF87: -0.010296 | AI87: -0.00951
A88: RKI000:ka_OtherUses | B88: Computers and Related Equipment 4/ | C88: 0.120106 | D88: 0.118562 | E88: 0.116931 | F88: 0.115363 | G88: 0.113493 | H88: 0.111328 | I88: 0.108857 | J88: 0.106117 | K88: 0.103168 | L88: 0.100088 | M88: 0.09698 | N88: 0.093786 | O88: 0.09061 | P88: 0.087647 | Q88: 0.084848 | R88: 0.082133 | S88: 0.079493 | T88: 0.077008 | U88: 0.074726 | V88: 0.072652 | W88: 0.070825 | X88: 0.069227 | Y88: 0.067875 | Z88: 0.066753 | AA88: 0.065956 | AB88: 0.065417 | AC88: 0.065087 | AD88: 0.064993 | AE88: 0.065107 | AF88: -0.021632 | AI88: 0.010208
A89: RKI000:ka_DeliveredEner | B89: Furnace Fans and Boiler Circulation Pumps | C89: 0.089175 | D89: 0.08825 | E89: 0.079128 | F89: 0.080094 | G89: 0.08098 | H89: 0.08173 | I89: 0.08228 | J89: 0.08254 | K89: 0.082562 | L89: 0.082343 | M89: 0.081924 | N89: 0.081309 | O89: 0.080431 | P89: 0.07939 | Q89: 0.078254 | R89: 0.077045 | S89: 0.075694 | T89: 0.074349 | U89: 0.07305 | V89: 0.071817 | W89: 0.07064 | X89: 0.069588 | Y89: 0.068662 | Z89: 0.067823 | AA89: 0.067006 | AB89: 0.066321 | AC89: 0.065775 | AD89: 0.065344 | AE89: 0.064997 | AF89: -0.011231 | AI89: -0.000141
B90: Other Uses 11/ | C90: 2.037398 | D90: 2.085668 | E90: 2.114172 | F90: 2.15381 | G90: 2.193656 | H90: 2.237911 | I90: 2.276552 | J90: 2.310099 | K90: 2.342685 | L90: 2.374795 | M90: 2.40728 | N90: 2.439503 | O90: 2.469323 | P90: 2.502968 | Q90: 2.539162 | R90: 2.577702 | S90: 2.614976 | T90: 2.653268 | U90: 2.693851 | V90: 2.735276 | W90: 2.779413 | X90: 2.825256 | Y90: 2.872853 | Z90: 2.92209 | AA90: 2.972497 | AB90: 3.025447 | AC90: 3.079815 | AD90: 3.136191 | AE90: 3.196599 | AF90: 0.016216
A91: RKI000:la_ElectricityRe | B91: Gross End-use Consumption | C91: 11.871545 | D91: 11.838481 | E91: 11.526081 | F91: 11.580305 | G91: 11.635993 | H91: 11.689837 | I91: 11.730596 | J91: 11.752335 | K91: 11.759981 | L91: 11.76046 | M91: 11.762243 | N91: 11.775377 | O91: 11.783529 | P91: 11.804331 | Q91: 11.834376 | R91: 11.870398 | S91: 11.902811 | T91: 11.940166 | U91: 11.979717 | V91: 12.023415 | W91: 12.073841 | X91: 12.131802 | Y91: 12.196539 | Z91: 12.263962 | AA91: 12.330469 | AB91: 12.404661 | AC91: 12.484758 | AD91: 12.568653 | AE91: 12.657738 | AF91: 0.002293 | AI91: -0.000786
B92: On-site Generation for Own Use | C92: 0.112023 | D92: 0.123458 | E92: 0.136529 | F92: 0.149777 | G92: 0.163009 | H92: 0.176585 | I92: 0.19053 | J92: 0.204945 | K92: 0.21982 | L92: 0.235246 | M92: 0.25149 | N92: 0.267937 | O92: 0.28465 | P92: 0.299474 | Q92: 0.314918 | R92: 0.330968 | S92: 0.348012 | T92: 0.366187 | U92: 0.3854 | V92: 0.405709 | W92: 0.427124 | X92: 0.44966 | Y92: 0.473071 | Z92: 0.497574 | AA92: 0.522997 | AB92: 0.549355 | AC92: 0.576946 | AD92: 0.605268 | AE92: 0.634524 | AF92: 0.063893
B93: Delivered Energy | C93: 11.759521 | D93: 11.715023 | E93: 11.389552 | F93: 11.430529 | G93: 11.472984 | H93: 11.513251 | I93: 11.540066 | J93: 11.547389 | K93: 11.540161 | L93: 11.525214 | M93: 11.510754 | N93: 11.50744 | O93: 11.498879 | P93: 11.504856 | Q93: 11.519459 | R93: 11.539429 | S93: 11.554799 | T93: 11.573979 | U93: 11.594316 | V93: 11.617705 | W93: 11.646717 | X93: 11.682141 | Y93: 11.723468 | Z93: 11.766388 | AA93: 11.807472 | AB93: 11.855307 | AC93: 11.907812 | AD93: 11.963385 | AE93: 12.023213 | AF93: 0.000792
A94: RKI000:ma_SpaceHeating | AI94: -0.010452
A95: RKI000:ma_SpaceCooling | B95: Electricity Related Losses | C95: 9.431884 | D95: 9.061446 | E95: 9.215983 | F95: 9.27758 | G95: 9.264794 | H95: 9.248041 | I95: 9.204556 | J95: 9.16187 | K95: 9.133 | L95: 9.153221 | M95: 9.218598 | N95: 9.2463 | O95: 9.313498 | P95: 9.377416 | Q95: 9.447539 | R95: 9.487012 | S95: 9.491396 | T95: 9.49157 | U95: 9.514772 | V95: 9.557769 | W95: 9.643615 | X95: 9.717905 | Y95: 9.805035 | Z95: 9.906764 | AA95: 9.974902 | AB95: 10.062102 | AC95: 10.154728 | AD95: 10.235389 | AE95: 10.336385 | AF95: 0.003276 | AI95: 0.01137
A96: RKI000:ma_WaterHeating | AI96: -0.000529
A97: RKI000:ma_Refrigeration | B97: Total Energy Consumption by End Use 1/ | AI97: -0.002189
A98: RKI000:ma_Cooking | B98: Space Heating | C98: 7.110015 | D98: 7.152661 | E98: 6.505752 | F98: 6.481146 | G98: 6.446995 | H98: 6.402728 | I98: 6.348807 | J98: 6.286177 | K98: 6.219484 | L98: 6.155372 | M98: 6.095963 | N98: 6.04086 | O98: 5.986131 | P98: 5.932523 | Q98: 5.882059 | R98: 5.830431 | S98: 5.774178 | T98: 5.720133 | U98: 5.671903 | V98: 5.62778 | W98: 5.589119 | X98: 5.552104 | Y98: 5.517498 | Z98: 5.483564 | AA98: 5.443891 | AB98: 5.407531 | AC98: 5.373238 | AD98: 5.338401 | AE98: 5.304385 | AF98: -0.010409 | AI98: -0.000126
A99: RKI000:ma_ClothesDryers | B99: Space Cooling | C99: 2.47652 | D99: 2.105813 | E99: 2.555955 | F99: 2.609767 | G99: 2.647732 | H99: 2.685529 | I99: 2.71932 | J99: 2.752531 | K99: 2.784432 | L99: 2.823819 | M99: 2.874449 | N99: 2.917299 | O99: 2.969324 | P99: 3.022695 | Q99: 3.080329 | R99: 3.133481 | S99: 3.179847 | T99: 3.226057 | U99: 3.277918 | V99: 3.333478 | W99: 3.398369 | X99: 3.461468 | Y99: 3.528827 | Z99: 3.600989 | AA99: 3.669588 | AB99: 3.743907 | AC99: 3.820605 | AD99: 3.893471 | AE99: 3.971736 | AF99: 0.017013 | AI99: 0.007679
A100: RKI000:ma_Freezers | B100: Water Heating | C100: 2.785069 | D100: 2.751679 | E100: 2.761014 | F100: 2.774418 | G100: 2.778686 | H100: 2.780505 | I100: 2.778927 | J100: 2.774831 | K100: 2.770231 | L100: 2.768322 | M100: 2.770947 | N100: 2.775383 | O100: 2.785916 | P100: 2.800031 | Q100: 2.815281 | R100: 2.82618 | S100: 2.832077 | T100: 2.837339 | U100: 2.845284 | V100: 2.855257 | W100: 2.869954 | X100: 2.884296 | Y100: 2.900232 | Z100: 2.91678 | AA100: 2.927033 | AB100: 2.940495 | AC100: 2.956146 | AD100: 2.971393 | AE100: 2.988648 | AF100: 0.002523 | AI100: -0.005888
A101: RKI000:ma_Lighting | B101: Refrigeration | C101: 0.837116 | D101: 0.821863 | E101: 0.82011 | F101: 0.816244 | G101: 0.80892 | H101: 0.801723 | I101: 0.794599 | J101: 0.789021 | K101: 0.785615 | L101: 0.785959 | M101: 0.78948 | N101: 0.791646 | O101: 0.796851 | P101: 0.801514 | Q101: 0.806954 | R101: 0.811274 | S101: 0.814845 | T101: 0.818855 | U101: 0.825009 | V101: 0.832846 | W101: 0.843261 | X101: 0.852645 | Y101: 0.862313 | Z101: 0.872397 | AA101: 0.879996 | AB101: 0.888089 | AC101: 0.896151 | AD101: 0.903103 | AE101: 0.910376 | AF101: 0.003001 | AI101: -0.014863
A102: RKI000:ma_ClothesWasher | B102: Cooking | C102: 0.278691 | D102: 0.277586 | E102: 0.278916 | F102: 0.279729 | G102: 0.279715 | H102: 0.279556 | I102: 0.279267 | J102: 0.279145 | K102: 0.279292 | L102: 0.280007 | M102: 0.281185 | N102: 0.282089 | O102: 0.283588 | P102: 0.284976 | Q102: 0.286538 | R102: 0.287902 | S102: 0.288942 | T102: 0.289914 | U102: 0.291167 | V102: 0.292601 | W102: 0.294395 | X102: 0.296 | Y102: 0.29768 | Z102: 0.299464 | AA102: 0.300796 | AB102: 0.302258 | AC102: 0.303746 | AD102: 0.305056 | AE102: 0.306457 | AF102: 0.003398 | AI102: 0.00226
A103: RKI000:ma_Dishwashers | B103: Clothes Dryers | C103: 0.66981 | D103: 0.674694 | E103: 0.690628 | F103: 0.706037 | G103: 0.717424 | H103: 0.727251 | I103: 0.735502 | J103: 0.743259 | K103: 0.75098 | L103: 0.760422 | M103: 0.771873 | N103: 0.780219 | O103: 0.79063 | P103: 0.80089 | Q103: 0.811639 | R103: 0.820126 | S103: 0.82629 | T103: 0.83206 | U103: 0.839117 | V103: 0.847212 | W103: 0.857459 | X103: 0.867207 | Y103: 0.877489 | Z103: 0.888283 | AA103: 0.897141 | AB103: 0.907121 | AC103: 0.917411 | AD103: 0.927091 | AE103: 0.937927 | AF103: 0.012097 | AI103: 0.010497
A104: RKI000:ma_ColorTelevisi | B104: Freezers | C104: 0.195449 | D104: 0.192474 | E104: 0.192473 | F104: 0.191769 | G104: 0.190053 | H104: 0.188178 | I104: 0.186248 | J104: 0.184606 | K104: 0.183387 | L104: 0.182909 | M104: 0.183025 | N104: 0.182693 | O104: 0.182931 | P104: 0.182904 | Q104: 0.182938 | R104: 0.18261 | S104: 0.182022 | T104: 0.18146 | U104: 0.181299 | V104: 0.181458 | W104: 0.182129 | X104: 0.18272 | Y104: 0.183532 | Z104: 0.184599 | AA104: 0.185312 | AB104: 0.186281 | AC104: 0.18728 | AD104: 0.188084 | AE104: 0.188993 | AF104: -0.001199 | AI104: 0.003318
A105: RKI000:ma_PersonalCompu | B105: Lighting | C105: 0.649367 | D105: 0.595905 | E105: 0.579474 | F105: 0.574137 | G105: 0.570839 | H105: 0.570306 | I105: 0.57126 | J105: 0.572736 | K105: 0.56876 | L105: 0.566906 | M105: 0.567342 | N105: 0.566285 | O105: 0.567537 | P105: 0.569162 | Q105: 0.571018 | R105: 0.571332 | S105: 0.570084 | T105: 0.568703 | U105: 0.558443 | V105: 0.550342 | W105: 0.545122 | X105: 0.54107 | Y105: 0.539506 | Z105: 0.539396 | AA105: 0.538311 | AB105: 0.538162 | AC105: 0.538476 | AD105: 0.538749 | AE105: 0.539906 | AF105: -0.006571 | AI105: -0.030853
A106: RKI000:ma_FurnaceFans | B106: Clothes Washers 2/ | C106: 0.106182 | D106: 0.105708 | E106: 0.106885 | F106: 0.107719 | G106: 0.108011 | H106: 0.108223 | I106: 0.108365 | J106: 0.108634 | K106: 0.109156 | L106: 0.110086 | M106: 0.111352 | N106: 0.11231 | O106: 0.113578 | P106: 0.114638 | Q106: 0.115674 | R106: 0.11642 | S106: 0.116929 | T106: 0.117383 | U106: 0.118026 | V106: 0.118792 | W106: 0.119816 | X106: 0.1207 | Y106: 0.121634 | Z106: 0.12264 | AA106: 0.123317 | AB106: 0.124087 | AC106: 0.124877 | AD106: 0.12554 | AE106: 0.126277 | AF106: 0.006209 | AI106: -0.013853
A107: RKI000:ma_OtherUses | B107: Dishwashers 2/ | C107: 0.078223 | D107: 0.078456 | E107: 0.079879 | F107: 0.081015 | G107: 0.081704 | H107: 0.082288 | I107: 0.082902 | J107: 0.083698 | K107: 0.084734 | L107: 0.086179 | M107: 0.087991 | N107: 0.089672 | O107: 0.091722 | P107: 0.0936 | Q107: 0.095456 | R107: 0.097072 | S107: 0.098484 | T107: 0.099843 | U107: 0.101357 | V107: 0.102973 | W107: 0.104813 | X107: 0.106531 | Y107: 0.108293 | Z107: 0.110121 | AA107: 0.111651 | AB107: 0.11326 | AC107: 0.114884 | AD107: 0.116387 | AE107: 0.117952 | AF107: 0.014777 | AI107: 0.006925
A108: RKI000:ma_Total | B108: Televisions and Related Equipment 3/ | C108: 0.524241 | D108: 0.50756 | E108: 0.499812 | F108: 0.491745 | G108: 0.481127 | H108: 0.470115 | I108: 0.458474 | J108: 0.447178 | K108: 0.43663 | L108: 0.427872 | M108: 0.420683 | N108: 0.412336 | O108: 0.405502 | P108: 0.39916 | Q108: 0.393541 | R108: 0.387539 | S108: 0.381106 | T108: 0.375235 | U108: 0.370793 | V108: 0.36753 | W108: 0.36592 | X108: 0.36459 | Y108: 0.364071 | Z108: 0.364416 | AA108: 0.364439 | AB108: 0.36533 | AC108: 0.366635 | AD108: 0.368021 | AE108: 0.370152 | AF108: -0.012353 | AI108: -0.000429
B109: Computers and Related Equipment 4/ | C109: 0.340178 | D109: 0.33145 | E109: 0.327662 | F109: 0.322891 | G109: 0.315723 | H109: 0.307605 | I109: 0.298498 | J109: 0.289104 | K109: 0.279812 | L109: 0.271273 | M109: 0.263439 | N109: 0.25464 | O109: 0.246597 | P109: 0.238668 | Q109: 0.231122 | R109: 0.223264 | S109: 0.215225 | T109: 0.207604 | U109: 0.200912 | V109: 0.195029 | W109: 0.190272 | X109: 0.18592 | Y109: 0.182322 | Z109: 0.179457 | AA109: 0.177 | AB109: 0.175386 | AC109: 0.174376 | AD109: 0.173838 | AE109: 0.17397 | AF109: -0.023665
B110: Furnace Fans and Boiler Circulation Pumps | C110: 0.252573 | D110: 0.24671 | E110: 0.221731 | F110: 0.224176 | G110: 0.225276 | H110: 0.225825 | I110: 0.225621 | J110: 0.224869 | K110: 0.223926 | L110: 0.223178 | M110: 0.222542 | N110: 0.220762 | O110: 0.218897 | P110: 0.216183 | Q110: 0.213162 | R110: 0.209433 | S110: 0.20494 | T110: 0.200434 | U110: 0.196406 | V110: 0.192789 | W110: 0.189775 | X110: 0.18689 | Y110: 0.184436 | Z110: 0.182334 | AA110: 0.179819 | AB110: 0.177807 | AC110: 0.176219 | AD110: 0.174776 | AE110: 0.173677 | AF110: -0.013286
A111: RKI000:na_GeothermalHea | B111: Other Uses 11/ | C111: 5.205466 | D111: 5.279265 | E111: 5.368068 | F111: 5.466795 | G111: 5.539333 | H111: 5.619686 | I111: 5.679614 | J111: 5.732172 | K111: 5.793295 | L111: 5.87413 | M111: 5.972672 | N111: 6.055487 | O111: 6.148349 | P111: 6.241326 | Q111: 6.339656 | R111: 6.429622 | S111: 6.504057 | T111: 6.57834 | U111: 6.668315 | V111: 6.76717 | W111: 6.888118 | X111: 7.006293 | Y111: 7.132197 | Z111: 7.267217 | AA111: 7.388483 | AB111: 7.521447 | AC111: 7.659168 | AD111: 7.794793 | AE111: 7.945688 | AF111: 0.015219 | AI111: 0.04523
...

Sheet EIA AEO Table 21
B1: Table 21. Residential Sector Equipment Stock and Efficiency, and Distributed Generation
B2: https://www.eia.gov/outlooks/aeo/data/browser/#/?id=30-AEO2022&cases=lowmacro&sourcekey=0
B3: Thu Apr 13 2023 14:53:57 GMT-0400 (Eastern Daylight Time)
B4: Source: U.S. Energy Information Administration
C5: full name | D5: api key | E5: units | F5: 2020 | G5: 2021 | H5: 2022 | I5: 2023 | J5: 2024 | K5: 2025 | L5: 2026 | M5: 2027 | N5: 2028 | O5: 2029 | P5: 2030 | Q5: 2031 | R5: 2032 | S5: 2033 | T5: 2034 | U5: 2035 | V5: 2036 | W5: 2037 | X5: 2038 | Y5: 2039 | Z5: 2040 | AA5: 2041 | AB5: 2042 | AC5: 2043 | AD5: 2044 | AE5: 2045 | AF5: 2046 | AG5: 2047 | AH5: 2048 | AI5: 2049 | AJ5: 2050 | AK5: Growth (2021-2050)
B6: Equipment Stock (million units)
B7: Main Space Heaters
B8: Electric Heat Pumps | C8: Residential Equipment: Equipment Stock: Main Space Heaters: Electric Heat Pumps: Low economic growth | D8: AEO.2022.LOWMACRO.EQNR_STK_RESD_MSHR_EHP_NA_NA_MILL.A | E8: millions | G8: 12.939867 | H8: 13.152194 | I8: 13.342212 | J8: 13.532937 | K8: 13.721616 | L8: 13.903946 | M8: 14.084397 | N8: 14.269409 | O8: 14.454908 | P8: 14.636997 | Q8: 14.814411 | R8: 14.999154 | S8: 15.181839 | T8: 15.3564 | U8: 15.527476 | V8: 15.696768 | W8: 15.868364 | X8: 16.039974 | Y8: 16.212418 | Z8: 16.385061 | AA8: 16.555988 | AB8: 16.72423 | AC8: 16.890961 | AD8: 17.056513 | AE8: 17.22121 | AF8: 17.385036 | AG8: 17.548895 | AH8: 17.710915 | AI8: 17.872004 | AJ8: 18.031734 | AK8: 0.012
B9: Electric Other | C9: Residential Equipment: Equipment Stock: Main Space Heaters: Electric Other: Low economic growth | D9: AEO.2022.LOWMACRO.EQNR_STK_RESD_MSHR_ELO_NA_NA_MILL.A | E9: millions | G9: 30.553938 | H9: 30.675936 | I9: 30.782753 | J9: 30.885431 | K9: 30.986736 | L9: 31.084375 | M9: 31.182482 | N9: 31.286263 | O9: 31.391994 | P9: 31.495815 | Q9: 31.596684 | R9: 31.703642 | S9: 31.809694 | T9: 31.908785 | U9: 32.005138 | V9: 32.098763 | W9: 32.194691 | X9: 32.291416 | Y9: 32.390797 | Z9: 32.491833 | AA9: 32.590778 | AB9: 32.687199 | AC9: 32.782112 | AD9: 32.876045 | AE9: 32.970554 | AF9: 33.064606 | AG9: 33.159756 | AH9: 33.253029 | AI9: 33.345913 | AJ9: 33.438988 | AK9: 0.003
A10: RST000 | B10: Natural Gas Heat Pumps | C10: Residential Equipment: Equipment Stock: Main Space Heaters: Natural Gas Heat Pumps: Low economic growth | D10: AEO.2022.LOWMACRO.EQNR_STK_RESD_MSHR_NHU_NA_NA_MILL.A | E10: millions | G10: 1.316486 | H10: 1.314569 | I10: 1.312659 | J10: 1.310759 | K10: 1.308866 | L10: 1.30698 | M10: 1.305104 | N10: 1.303233 | O10: 1.301371 | P10: 1.299515 | Q10: 1.297667 | R10: 1.295827 | S10: 1.293993 | T10: 1.292167 | U10: 1.290347 | V10: 1.288535 | W10: 1.286729 | X10: 1.28493 | Y10: 1.283138 | Z10: 1.281352 | AA10: 1.279573 | AB10: 1.2778 | AC10: 1.276034 | AD10: 1.274273 | AE10: 1.272519 | AF10: 1.270772 | AG10: 1.26903 | AH10: 1.267294 | AI10: 1.265564 | AJ10: 1.263841 | AK10: -0.001
B11: Natural Gas Other | C11: Residential Equipment: Equipment Stock: Main Space Heaters: Natural Gas Other: Low economic growth | D11: AEO.2022.LOWMACRO.EQNR_STK_RESD_MSHR_NGO_NA_NA_MILL.A | E11: millions | G11: 61.33672 | H11: 62.030872 | I11: 62.670055 | J11: 63.315552 | K11: 63.953545 | L11: 64.569389 | M11: 65.174591 | N11: 65.787827 | O11: 66.398575 | P11: 66.995453 | Q11: 67.574905 | R11: 68.175156 | S11: 68.765228 | T11: 69.327278 | U11: 69.872078 | V11: 70.404388 | W11: 70.934273 | X11: 71.465973 | Y11: 71.999748 | Z11: 72.535378 | AA11: 73.065193 | AB11: 73.586014 | AC11: 74.100395 | AD11: 74.608742 | AE11: 75.111382 | AF11: 75.607239 | AG11: 76.097046 | AH11: 76.576889 | AI11: 77.048859 | AJ11: 77.510254 | AK11: 0.008
B12: Distillate Fuel Oil | C12: Residential Equipment: Equipment Stock: Main Space Heaters: Distillate Fuel Oil: Low economic growth | D12: AEO.2022.LOWMACRO.EQNR_STK_RESD_MSHR_DFO_NA_NA_MILL.A | E12: millions | G12: 5.503068 | H12: 5.452685 | I12: 5.403224 | J12: 5.35462 | K12: 5.306357 | L12: 5.258382 | M12: 5.212059 | N12: 5.167742 | O12: 5.125732 | P12: 5.086065 | Q12: 5.047999 | R12: 5.01172 | S12: 4.976817 | T12: 4.942926 | U12: 4.909963 | V12: 4.877693 | W12: 4.846786 | X12: 4.816997 | Y12: 4.788019 | Z12: 4.759813 | AA12: 4.731733 | AB12: 4.702106 | AC12: 4.671 | AD12: 4.638635 | AE12: 4.60528 | AF12: 4.571091 | AG12: 4.535478 | AH12: 4.498829 | AI12: 4.461558 | AJ12: 4.424065 | AK12: -0.007
B13: Propane | C13: Residential Equipment: Equipment Stock: Main Space Heaters: Propane: Low economic growth | D13: AEO.2022.LOWMACRO.EQNR_STK_RESD_MSHR_PROP_NA_NA_MILL.A | E13: millions | G13: 5.245557 | H13: 5.245455 | I13: 5.243608 | J13: 5.240382 | K13: 5.236936 | L13: 5.233324 | M13: 5.229367 | N13: 5.225949 | O13: 5.223021 | P13: 5.219841 | Q13: 5.216552 | R13: 5.214471 | S13: 5.212708 | T13: 5.210732 | U13: 5.208905 | V13: 5.206887 | W13: 5.204187 | X13: 5.20069 | Y13: 5.19686 | Z13: 5.192907 | AA13: 5.188683 | AB13: 5.18278 | AC13: 5.175326 | AD13: 5.166907 | AE13: 5.158232 | AF13: 5.149588 | AG13: 5.1413 | AH13: 5.133091 | AI13: 5.125126 | AJ13: 5.117575 | AK13: -0.001
B14: Kerosene | C14: Residential Equipment: Equipment Stock: Main Space Heaters: Kerosene: Low economic growth | D14: AEO.2022.LOWMACRO.EQNR_STK_RESD_MSHR_KRS_NA_NA_MILL.A | E14: millions | G14: 0.003345 | H14: 0.006042 | I14: 0.008499 | J14: 0.010799 | K14: 0.013122 | L14: 0.015544 | M14: 0.017829 | N14: 0.020044 | O14: 0.022209 | P14: 0.024266 | Q14: 0.02626 | R14: 0.028255 | S14: 0.030243 | T14: 0.032189 | U14: 0.034111 | V14: 0.035971 | W14: 0.037734 | X14: 0.039376 | Y14: 0.040966 | Z14: 0.042535 | AA14: 0.044012 | AB14: 0.045418 | AC14: 0.046763 | AD14: 0.048074 | AE14: 0.049373 | AF14: 0.050627 | AG14: 0.051852 | AH14: 0.053008 | AI14: 0.054102 | AJ14: 0.05515 | AK14: 0.101
B15: Wood Stoves | C15: Residential Equipment: Equipment Stock: Main Space Heaters: Wood Stoves: Low economic growth | D15: AEO.2022.LOWMACRO.EQNR_STK_RESD_MSHR_WDS_NA_NA_MILL.A | E15: millions | G15: 3.324872 | H15: 3.296432 | I15: 3.269913 | J15: 3.244488 | K15: 3.219946 | L15: 3.196247 | M15: 3.172873 | N15: 3.149143 | O15: 3.124991 | P15: 3.100666 | Q15: 3.075778 | R15: 3.049958 | S15: 3.023234 | T15: 2.995832 | U15: 2.967745 | V15: 2.939001 | W15: 2.911176 | X15: 2.884129 | Y15: 2.857822 | Z15: 2.831723 | AA15: 2.806644 | AB15: 2.783075 | AC15: 2.760905 | AD15: 2.740153 | AE15: 2.7209 | AF15: 2.702927 | AG15: 2.684836 | AH15: 2.666614 | AI15: 2.648213 | AJ15: 2.629575 | AK15: -0.008
B16: Geothermal Heat Pumps | C16: Residential Equipment: Equipment Stock: Main Space Heaters: Geothermal Heat Pumps: Low economic growth | D16: AEO.2022.LOWMACRO.EQNR_STK_RESD_MSHR_GEHP_NA_NA_MILL.A | E16: millions | G16: 0.691816 | H16: 0.748202 | I16: 0.800437 | J16: 0.852791 | K16: 0.903986 | L16: 0.953071 | M16: 1.001114 | N16: 1.050052 | O16: 1.099535 | P16: 1.148657 | Q16: 1.197588 | R16: 1.24913 | S16: 1.301267 | T16: 1.352828 | U16: 1.404353 | V16: 1.456145 | W16: 1.50693 | X16: 1.557102 | Y16: 1.606632 | Z16: 1.656135 | AA16: 1.704539 | AB16: 1.75091 | AC16: 1.7955 | AD16: 1.838362 | AE16: 1.879344 | AF16: 1.918721 | AG16: 1.957791 | AH16: 1.99649 | AI16: 2.034937 | AJ16: 2.072986 | AK16: 0.039
A17: RST000:ba_ElectricHeatP | B17: Total | C17: Residential Equipment: Equipment Stock: Main Space Heaters: Total: Low economic growth | D17: AEO.2022.LOWMACRO.EQNR_STK_RESD_MSHR_TOT_NA_NA_MILL.A | E17: millions | G17: 120.91567 | H17: 121.92238 | I17: 122.83336 | J17: 123.74776 | K17: 124.65112 | L17: 125.52125 | M17: 126.37982 | N17: 127.25966 | O17: 128.14233 | P17: 129.00728 | Q17: 129.84784 | R17: 130.72731 | S17: 131.59502 | T17: 132.41914 | U17: 133.22011 | V17: 134.00415 | W17: 134.79088 | X17: 135.58058 | Y17: 136.37639 | Z17: 137.17673 | AA17: 137.96715 | AB17: 138.73956 | AC17: 139.49901 | AD17: 140.24771 | AE17: 140.98881 | AF17: 141.7206 | AG17: 142.44597 | AH17: 143.15616 | AI17: 143.85629 | AJ17: 144.54416 | AK17: 0.006
A18: RST000:ba_ElectricOther | B18: Space Cooling (million units)
A19: RST000:ba_NaturalGasHea | B19: Electric Heat Pumps | C19: Residential Equipment: Equipment Stock: Space Cooling: Electric Heat Pumps: Low economic growth | D19: AEO.2022.LOWMACRO.EQNR_STK_RESD_SPC_EHP_NA_NA_MILL.A | E19: millions | G19: 12.939865 | H19: 13.152193 | I19: 13.342216 | J19: 13.53294 | K19: 13.721614 | L19: 13.903946 | M19: 14.0844 | N19: 14.269408 | O19: 14.454908 | P19: 14.637002 | Q19: 14.814411 | R19: 14.999156 | S19: 15.181841 | T19: 15.356396 | U19: 15.527485 | V19: 15.69677 | W19: 15.868359 | X19: 16.039976 | Y19: 16.21242 | Z19: 16.385063 | AA19: 16.555988 | AB19: 16.72423 | AC19: 16.890959 | AD19: 17.056513 | AE19: 17.221212 | AF19: 17.38504 | AG19: 17.548897 | AH19: 17.710917 | AI19: 17.872009 | AJ19: 18.031742 | AK19: 0.012
A20: RST000:ba_NaturalGasOth | B20: Natural Gas Heat Pumps | C20: Residential Equipment: Equipment Stock: Space Cooling: Natural Gas Heat Pumps: Low economic growth | D20: AEO.2022.LOWMACRO.EQNR_STK_RESD_SPC_NHU_NA_NA_MILL.A | E20: millions | G20: 1.316486 | H20: 1.314569 | I20: 1.31266 | J20: 1.310759 | K20: 1.308866 | L20: 1.306981 | M20: 1.305103 | N20: 1.303233 | O20: 1.301371 | P20: 1.299515 | Q20: 1.297668 | R20: 1.295827 | S20: 1.293994 | T20: 1.292167 | U20: 1.290348 | V20: 1.288535 | W20: 1.286729 | X20: 1.28493 | Y20: 1.283138 | Z20: 1.281352 | AA20: 1.279573 | AB20: 1.2778 | AC20: 1.276034 | AD20: 1.274274 | AE20: 1.272519 | AF20: 1.270772 | AG20: 1.26903 | AH20: 1.267294 | AI20: 1.265564 | AJ20: 1.263841 | AK20: -0.001
A21: RST000:ba_Distillate | B21: Geothermal Heat Pumps | C21: Residential Equipment: Equipment Stock: Space Cooling: Geothermal Heat Pumps: Low economic growth | D21: AEO.2022.LOWMACRO.EQNR_STK_RESD_SPC_GEHP_NA_NA_MILL.A | E21: millions | G21: 0.691816 | H21: 0.748202 | I21: 0.800437 | J21: 0.852791 | K21: 0.903986 | L21: 0.953071 | M21: 1.001115 | N21: 1.050052 | O21: 1.099534 | P21: 1.148657 | Q21: 1.197588 | R21: 1.249131 | S21: 1.301267 | T21: 1.352828 | U21: 1.404353 | V21: 1.456146 | W21: 1.50693 | X21: 1.557102 | Y21: 1.606632 | Z21: 1.656135 | AA21: 1.70454 | AB21: 1.75091 | AC21: 1.795501 | AD21: 1.838362 | AE21: 1.879344 | AF21: 1.918721 | AG21: 1.957791 | AH21: 1.99649 | AI21: 2.034937 | AJ21: 2.072986 | AK21: 0.039
A22: RST000:ba_LiquefiedPetr | B22: Central Air Conditioners | C22: Residential Equipment: Equipment Stock: Space Cooling: Central Air Conditioners: Low economic growth | D22: AEO.2022.LOWMACRO.EQNR_STK_RESD_SPC_CAC_NA_NA_MILL.A | E22: millions | G22: 64.167404 | H22: 65.628075 | I22: 67.026932 | J22: 68.427589 | K22: 69.819656 | L22: 71.188896 | M22: 72.548157 | N22: 73.918556 | O22: 75.288826 | P22: 76.645782 | Q22: 77.985336 | R22: 79.348358 | S22: 80.702156 | T22: 82.026726 | U22: 83.334877 | V22: 84.630608 | W22: 85.925674 | X22: 87.220566 | Y22: 88.517242 | Z22: 89.814919 | AA22: 91.104797 | AB22: 92.381447 | AC22: 93.64814 | AD22: 94.906357 | AE22: 96.157784 | AF22: 97.401619 | AG22: 98.639374 | AH22: 99.865723 | AI22: 101.08376 | AJ22: 102.29199 | AK22: 0.016
A23: RST000:ba_Kerosene | B23: Room Air Conditioners | C23: Residential Equipment: Equipment Stock: Space Cooling: Room Air Conditioners: Low economic growth | D23: AEO.2022.LOWMACRO.EQNR_STK_RESD_SPC_RAC_NA_NA_MILL.A | E23: millions | G23: 58.043907 | H23: 58.031307 | I23: 58.008541 | J23: 57.986195 | K23: 57.964832 | L23: 57.943119 | M23: 57.920296 | N23: 57.900295 | O23: 57.881512 | P23: 57.861092 | Q23: 57.838936 | R23: 57.822067 | S23: 57.805351 | T23: 57.785152 | U23: 57.763771 | V23: 57.741295 | W23: 57.719055 | X23: 57.696808 | Y23: 57.67569 | Z23: 57.655998 | AA23: 57.635544 | AB23: 57.613773 | AC23: 57.591301 | AD23: 57.568768 | AE23: 57.546726 | AF23: 57.524544 | AG23: 57.502636 | AH23: 57.479496 | AI23: 57.455704 | AJ23: 57.431248 | AK23: 0
A24: RST000:ba_WoodStoves | B24: Total | C24: Residential Equipment: Equipment Stock: Space Cooling: Total: Low economic growth | D24: AEO.2022.LOWMACRO.EQNR_STK_RESD_SPC_TOT_NA_NA_MILL.A | E24: millions | G24: 137.15948 | H24: 138.87434 | I24: 140.49078 | J24: 142.11028 | K24: 143.71895 | L24: 145.29601 | M24: 146.85907 | N24: 148.44154 | O24: 150.02615 | P24: 151.59204 | Q24: 153.13394 | R24: 154.71454 | S24: 156.28461 | T24: 157.81326 | U24: 159.32083 | V24: 160.81335 | W24: 162.30675 | X24: 163.79938 | Y24: 165.29512 | Z24: 166.79346 | AA24: 168.28044 | AB24: 169.74815 | AC24: 171.20193 | AD24: 172.64427 | AE24: 174.07759 | AF24: 175.5007 | AG24: 176.91772 | AH24: 178.31992 | AI24: 179.71197 | AJ24: 181.09181 | AK24: 0.01
A25: RST000:ba_GeothermalHea | B25: Water Heaters (million units)
A26: RST000:ba_Total | B26: Electric | C26: Residential Equipment: Equipment Stock: Water Heaters: Electric: Low economic growth | D26: AEO.2022.LOWMACRO.EQNR_STK_RESD_WHT_ELE_NA_NA_MILL.A | E26: millions | G26: 59.829865 | H26: 60.213783 | I26: 60.580872 | J26: 61.03635 | K26: 61.449547 | L26: 61.813381 | M26: 62.155468 | N26: 62.490932 | O26: 62.81295 | P26: 63.113571 | Q26: 63.422279 | R26: 63.766239 | S26: 64.118187 | T26: 64.462593 | U26: 64.813332 | V26: 65.166489 | W26: 65.528687 | X26: 65.899277 | Y26: 66.268959 | Z26: 66.632172 | AA26: 66.986679 | AB26: 67.326195 | AC26: 67.657356 | AD26: 67.981659 | AE26: 68.299133 | AF26: 68.614403 | AG26: 68.928024 | AH26: 69.236954 | AI26: 69.544441 | AJ26: 69.853416 | AK26: 0.005
B27: Natural Gas | C27: Residential Equipment: Equipment Stock: Water Heaters: Natural Gas: Low economic growth | D27: AEO.2022.LOWMACRO.EQNR_STK_RESD_WHT_NG_NA_NA_MILL.A | E27: millions | G27: 60.704216 | H27: 61.224213 | I27: 61.727146 | J27: 62.283768 | K27: 62.85593 | L27: 63.432217 | M27: 64.010368 | N27: 64.605728 | O27: 65.206589 | P27: 65.80072 | Q27: 66.369591 | R27: 66.945938 | S27: 67.506172 | T27: 68.033279 | U27: 68.533333 | V27: 69.014732 | W27: 69.489388 | X27: 69.957626 | Y27: 70.43013 | Z27: 70.910095 | AA27: 71.386017 | AB27: 71.855698 | AC27: 72.318619 | AD27: 72.775093 | AE27: 73.227837 | AF27: 73.671577 | AG27: 74.108505 | AH27: 74.53334 | AI27: 74.948402 | AJ27: 75.348824 | AK27: 0.007
B28: Distillate Fuel Oil | C28: Residential Equipment: Equipment Stock: Water Heaters: Distillate Fuel Oil: Low economic growth | D28: AEO.2022.LOWMACRO.EQNR_STK_RESD_WHT_DFO_NA_NA_MILL.A | E28: millions | G28: 2.602572 | H28: 2.554386 | I28: 2.510953 | J28: 2.468833 | K28: 2.429554 | L28: 2.393059 | M28: 2.359057 | N28: 2.328569 | O28: 2.301511 | P28: 2.27756 | Q28: 2.251528 | R28: 2.224324 | S28: 2.196179 | T28: 2.167443 | U28: 2.137812 | V28: 2.107999 | W28: 2.078641 | X28: 2.049778 | Y28: 2.021623 | Z28: 1.994376 | AA28: 1.967958 | AB28: 1.942628 | AC28: 1.917783 | AD28: 1.893621 | AE28: 1.87028 | AF28: 1.84734 | AG28: 1.82491 | AH28: 1.802973 | AI28: 1.781409 | AJ28: 1.760126 | AK28: -0.013
A29: RST000:ca_ElectricHeatP | B29: Propane | C29: Residential Equipment: Equipment Stock: Water Heaters: Propane: Low economic growth | D29: AEO.2022.LOWMACRO.EQNR_STK_RESD_WHT_PROP_NA_NA_MILL.A | E29: millions | G29: 3.998682 | H29: 3.897122 | I29: 3.804604 | J29: 3.72221 | K29: 3.649823 | L29: 3.586324 | M29: 3.529158 | N29: 3.4795 | O29: 3.437484 | P29: 3.40298 | Q29: 3.363295 | R29: 3.320493 | S29: 3.274979 | T29: 3.227235 | U29: 3.178444 | V29: 3.129654 | W29: 3.081452 | X29: 3.034334 | Y29: 2.989191 | Z29: 2.946535 | AA29: 2.905906 | AB29: 2.867353 | AC29: 2.830608 | AD29: 2.795922 | AE29: 2.763403 | AF29: 2.732625 | AG29: 2.703559 | AH29: 2.67561 | AI29: 2.6487 | AJ29: 2.622729 | AK29: -0.014
A30: RST000:ca_NaturalGasHea | B30: Solar Thermal | C30: Residential Equipment: Equipment Stock: Water Heaters: Solar Thermal: Low economic growth | D30: AEO.2022.LOWMACRO.EQNR_STK_RESD_WHT_SLR_THERM_NA_MILL.A | E30: millions | G30: 1.873337 | H30: 2.106847 | I30: 2.264974 | J30: 2.272993 | K30: 2.28405 | L30: 2.295635 | M30: 2.306829 | N30: 2.317815 | O30: 2.328661 | P30: 2.339389 | Q30: 2.350307 | R30: 2.361829 | S30: 2.373521 | T30: 2.385176 | U30: 2.396525 | V30: 2.407451 | W30: 2.417866 | X30: 2.427773 | Y30: 2.437905 | Z30: 2.448268 | AA30: 2.458755 | AB30: 2.469354 | AC30: 2.479919 | AD30: 2.490493 | AE30: 2.501091 | AF30: 2.511559 | AG30: 2.522038 | AH30: 2.532417 | AI30: 2.542718 | AJ30: 2.552892 | AK30: 0.011
A31: RST000:ca_GeothermalHea | B31: Total | C31: Residential Equipment: Equipment Stock: Water Heaters: Total: Low economic growth | D31: AEO.2022.LOWMACRO.EQNR_STK_RESD_WHT_TOT_NA_NA_MILL.A | E31: millions | G31: 129.00867 | H31: 129.99635 | I31: 130.88855 | J31: 131.78415 | K31: 132.66891 | L31: 133.52061 | M31: 134.36087 | N31: 135.22253 | O31: 136.08719 | P31: 136.93422 | Q31: 137.757 | R31: 138.61882 | S31: 139.46904 | T31: 140.27574 | U31: 141.05946 | V31: 141.82632 | W31: 142.59602 | X31: 143.36879 | Y31: 144.14783 | Z31: 144.93144 | AA31: 145.70531 | AB31: 146.46123 | AC31: 147.2043 | AD31: 147.93678 | AE31: 148.66176 | AF31: 149.3775 | AG31: 150.08702 | AH31: 150.7813 | AI31: 151.46567 | AJ31: 152.13798 | AK31: 0.006
A32: RST000:ca_CentralAirCon | B32: Cooking Equipment (million units)
A33: RST000:ca_RoomAirCondit | B33: Electric | C33: Residential Equipment: Equipment Stock: Cooking Equipment: Electric: Low economic growth | D33: AEO.2022.LOWMACRO.EQNR_STK_RESD_CER_ELE_NA_NA_MILL.A | E33: millions | G33: 97.282806 | H33: 97.787354 | I33: 98.215042 | J33: 98.632729 | K33: 99.032143 | L33: 99.396202 | M33: 99.739357 | N33: 100.08295 | O33: 100.38844 | P33: 100.63934 | Q33: 100.82276 | R33: 100.97788 | S33: 101.15427 | T33: 101.35497 | U33: 101.59816 | V33: 101.89742 | W33: 102.27224 | X33: 102.63831 | Y33: 102.99777 | Z33: 103.34814 | AA33: 103.67843 | AB33: 103.98253 | AC33: 104.2638 | AD33: 104.52412 | AE33: 104.76753 | AF33: 104.99548 | AG33: 105.21425 | AH33: 105.42191 | AI33: 105.62772 | AJ33: 105.8353 | AK33: 0.003
A34: RST000:ca_Total | B34: Natural Gas | C34: Residential Equipment: Equipment Stock: Cooking Equipment: Natural Gas: Low economic growth | D34: AEO.2022.LOWMACRO.EQNR_STK_RESD_CER_NG_NA_NA_MILL.A | E34: millions | G34: 48.396942 | H34: 48.864845 | I34: 49.317436 | J34: 49.785069 | K34: 50.261314 | L34: 50.742012 | M34: 51.236866 | N34: 51.756042 | O34: 52.320065 | P34: 52.924976 | Q34: 53.576504 | R34: 54.296326 | S34: 54.979057 | T34: 55.590328 | U34: 56.132183 | V34: 56.597126 | W34: 56.98587 | X34: 57.389172 | Y34: 57.807804 | Z34: 58.242535 | AA34: 58.690311 | AB34: 59.148796 | AC34: 59.618919 | AD34: 60.099831 | AE34: 60.589512 | AF34: 61.083973 | AG34: 61.579159 | AH34: 62.068329 | AI34: 62.547977 | AJ34: 63.01305 | AK34: 0.009
B35: Propane | C35: Residential Equipment: Equipment Stock: Cooking Equipment: Propane: Low economic growth | D35: AEO.2022.LOWMACRO.EQNR_STK_RESD_CER_PROP_NA_NA_MILL.A | E35: millions | G35: 7.215937 | H35: 7.198987 | I35: 7.178784 | J35: 7.157144 | K35: 7.134501 | L35: 7.109806 | M35: 7.080655 | N35: 7.048186 | O35: 7.012279 | P35: 6.972398 | Q35: 6.929494 | R35: 6.885695 | S35: 6.846237 | T35: 6.810504 | U35: 6.778969 | V35: 6.751493 | W35: 6.727694 | X35: 6.701273 | Y35: 6.672495 | Z35: 6.641469 | AA35: 6.607776 | AB35: 6.571814 | AC35: 6.534314 | AD35: 6.496439 | AE35: 6.459413 | AF35: 6.423977 | AG35: 6.390821 | AH35: 6.359664 | AI35: 6.330132 | AJ35: 6.301469 | AK35: -0.005
B36: Total | C36: Residential Equipment: Equipment Stock: Cooking Equipment: Total: Low economic growth | D36: AEO.2022.LOWMACRO.EQNR_STK_RESD_CER_TOT_NA_NA_MILL.A | E36: millions | G36: 152.89569 | H36: 153.85118 | I36: 154.71126 | J36: 155.57495 | K36: 156.42796 | L36: 157.24802 | M36: 158.05688 | N36: 158.88718 | O36: 159.7208 | P36: 160.53671 | Q36: 161.32875 | R36: 162.1599 | S36: 162.97957 | T36: 163.7558 | U36: 164.50931 | V36: 165.24605 | W36: 165.98581 | X36: 166.72876 | Y36: 167.47807 | Z36: 168.23213 | AA36: 168.97652 | AB36: 169.70312 | AC36: 170.41704 | AD36: 171.12041 | AE36: 171.81645 | AF36: 172.50343 | AG36: 173.18424 | AH36: 173.8499 | AI36: 174.50583 | AJ36: 175.14983 | AK36: 0.005
A37: RST000:da_Electric | B37: Clothes Dryers (million units)
A38: RST000:da_NaturalGas | B38: Electric | C38: Residential Equipment: Equipment Stock: Clothes Dryers: Electric: Low economic growth | D38: AEO.2022.LOWMACRO.EQNR_STK_RESD_CDR_ELE_NA_NA_MILL.A | E38: millions | G38: 84.74617 | H38: 86.235474 | I38: 87.634346 | J38: 89.025757 | K38: 90.409912 | L38: 91.740776 | M38: 93.044624 | N38: 94.368134 | O38: 95.694359 | P38: 97.005806 | Q38: 98.296959 | R38: 99.628151 | S38: 100.95462 | T38: 102.28601 | U38: 103.60919 | V38: 104.9316 | W38: 106.24234 | X38: 107.54414 | Y38: 108.84335 | Z38: 110.13705 | AA38: 111.41454 | AB38: 112.66832 | AC38: 113.90573 | AD38: 115.13056 | AE38: 116.3458 | AF38: 117.55255 | AG38: 118.75244 | AH38: 119.93816 | AI38: 121.11373 | AJ38: 122.27639 | AK38: 0.013
A39: RST000:da_Distillate | B39: Natural Gas | C39: Residential Equipment: Equipment Stock: Clothes Dryers: Natural Gas: Low economic growth | D39: AEO.2022.LOWMACRO.EQNR_STK_RESD_CDR_NG_NA_NA_MILL.A | E39: millions | G39: 19.709597 | H39: 20.023542 | I39: 20.33856 | J39: 20.669289 | K39: 21.015242 | L39: 21.379358 | M39: 21.76585 | N39: 22.150591 | O39: 22.533482 | P39: 22.910875 | Q39: 23.281893 | R39: 23.653246 | S39: 24.01589 | T39: 24.363272 | U39: 24.692194 | V39: 25.002323 | W39: 25.322683 | X39: 25.652546 | Y39: 25.990679 | Z39: 26.336733 | AA39: 26.687059 | AB39: 27.039303 | AC39: 27.391558 | AD39: 27.742498 | AE39: 28.091402 | AF39: 28.436264 | AG39: 28.777365 | AH39: 29.113682 | AI39: 29.446186 | AJ39: 29.77441 | AK39: 0.014
A40: RST000:da_LiquefiedPetr | B40: Total | C40: Residential Equipment: Equipment Stock: Clothes Dryers: Total: Low economic growth | D40: AEO.2022.LOWMACRO.EQNR_STK_RESD_CDR_TOT_NA_NA_MILL.A | E40: millions | G40: 104.45576 | H40: 106.25902 | I40: 107.97291 | J40: 109.69504 | K40: 111.42516 | L40: 113.12013 | M40: 114.81047 | N40: 116.51872 | O40: 118.22784 | P40: 119.91668 | Q40: 121.57885 | R40: 123.2814 | S40: 124.97051 | T40: 126.64928 | U40: 128.30139 | V40: 129.93393 | W40: 131.56502 | X40: 133.19669 | Y40: 134.83403 | Z40: 136.47378 | AA40: 138.10161 | AB40: 139.70763 | AC40: 141.29729 | AD40: 142.87306 | AE40: 144.43721 | AF40: 145.98881 | AG40: 147.5298 | AH40: 149.05183 | AI40: 150.55992 | AJ40: 152.0508 | AK40: 0.013
A41: RST000:da_SolarThermal | B41: Other Appliances (million units)
A42: RST000:da_Total | B42: Refrigerators | C42: Residential Equipment: Equipment Stock: Other Appliances: Refrigerators: Low economic growth | D42: AEO.2022.LOWMACRO.EQNR_STK_RESD_OTAR_RFG_NA_NA_MILL.A | E42: millions | G42: 170.63339 | H42: 172.10457 | I42: 173.44502 | J42: 174.80096 | K42: 176.1425 | L42: 177.43581 | M42: 178.7077 | N42: 180.00755 | O42: 181.31125 | P42: 182.58859 | Q42: 183.83032 | R42: 185.13275 | S42: 186.41869 | T42: 187.64331 | U42: 188.83479 | V42: 190.0029 | W42: 191.17137 | X42: 192.34315 | Y42: 193.52161 | Z42: 194.70668 | AA42: 195.87918 | AB42: 197.02565 | AC42: 198.15324 | AD42: 199.26564 | AE42: 200.36551 | AF42: 201.45138 | AG42: 202.52565 | AH42: 203.57718 | AI42: 204.61255 | AJ42: 205.62712 | AK42: 0.006
B43: Freezers | C43: Residential Equipment: Equipment Stock: Other Appliances: Freezers: Low economic growth | D43: AEO.2022.LOWMACRO.EQNR_STK_RESD_OTAR_FRZ_NA_NA_MILL.A | E43: millions | G43: 44.947987 | H43: 45.289402 | I43: 45.602821 | J43: 45.922535 | K43: 46.241211 | L43: 46.551991 | M43: 46.85471 | N43: 47.162128 | O43: 47.470245 | P43: 47.771069 | Q43: 48.063629 | R43: 48.37204 | S43: 48.677734 | T43: 48.970444 | U43: 49.256191 | V43: 49.536831 | W43: 49.814934 | X43: 50.091827 | Y43: 50.368973 | Z43: 50.647869 | AA43: 50.923866 | AB43: 51.193691 | AC43: 51.459049 | AD43: 51.721455 | AE43: 51.981228 | AF43: 52.237854 | AG43: 52.491165 | AH43: 52.738609 | AI43: 52.981316 | AJ43: 53.217987 | AK43: 0.006
B44: Stock Average Equipment Efficiency
A45: RST000:ea_Electric | B45: Main Space Heaters
A46: RST000:ea_NaturalGas | B46: Electric Heat Pumps (HSPF) | C46: Residential Equipment: Stock Average Efficiency: Main Space Heaters: Electric Heat Pumps: Low economic growth | D46: AEO.2022.LOWMACRO.EFI_STK_RESD_SPHR_EHP_NA_NA_HSPF.A | E46: HSPF | G46: 8.152074 | H46: 8.196118 | I46: 8.287066 | J46: 8.369968 | K46: 8.448981 | L46: 8.523767 | M46: 8.59485 | N46: 8.662163 | O46: 8.725883 | P46: 8.785576 | Q46: 8.841197 | R46: 8.892589 | S46: 8.939072 | T46: 8.980197 | U46: 9.015215 | V46: 9.042925 | W46: 9.062171 | X46: 9.079855 | Y46: 9.095611 | Z46: 9.109237 | AA46: 9.120657 | AB46: 9.12994 | AC46: 9.137234 | AD46: 9.142768 | AE46: 9.146824 | AF46: 9.149684 | AG46: 9.151633 | AH46: 9.152927 | AI46: 9.153751 | AJ46: 9.154268 | AK46: 0.004
A47: RST000:ea_LiquefiedPetr | B47: Natural Gas Heat Pumps (GCOP) | C47: Residential Equipment: Stock Average Efficiency: Main Space Heaters: Natural Gas Heat Pumps: Low economic growth | D47: AEO.2022.LOWMACRO.EFI_STK_RESD_SPHR_NHU_NA_NA_GCOP.A | E47: GCOP | G47: 1.3 | H47: 1.3 | I47: 1.3 | J47: 1.3 | K47: 1.3 | L47: 1.3 | M47: 1.3 | N47: 1.3 | O47: 1.3 | P47: 1.3 | Q47: 1.3 | R47: 1.3 | S47: 1.3 | T47: 1.3 | U47: 1.3 | V47: 1.3 | W47: 1.3 | X47: 1.3 | Y47: 1.3 | Z47: 1.3 | AA47: 1.3 | AB47: 1.3 | AC47: 1.3 | AD47: 1.3 | AE47: 1.3 | AF47: 1.3 | AG47: 1.3 | AH47: 1.3 | AI47: 1.3 | AJ47: 1.3 | AK47: 0
A48: RST000:ea_Total | B48: Geothermal Heat Pumps (COP) | C48: Residential Equipment: Stock Average Efficiency: Main Space Heaters: Geothermal Heat Pumps: Low economic growth | D48: AEO.2022.LOWMACRO.EFI_STK_RESD_SPHR_GEHP_NA_NA_COP.A | E48: COP | G48: 3.45279 | H48: 3.501445 | I48: 3.541777 | J48: 3.559523 | K48: 3.574398 | L48: 3.588524 | M48: 3.600637 | N48: 3.610833 | O48: 3.619402 | P48: 3.62658 | Q48: 3.632766 | R48: 3.637919 | S48: 3.642429 | T48: 3.646606 | U48: 3.650417 | V48: 3.653776 | W48: 3.65681 | X48: 3.659426 | Y48: 3.661763 | Z48: 3.663834 | AA48: 3.665688 | AB48: 3.667331 | AC48: 3.668621 | AD48: 3.669614 | AE48: 3.670264 | AF48: 3.670482 | AG48: 3.670837 | AH48: 3.671264 | AI48: 3.671724 | AJ48: 3.672159 | AK48: 0.002
B49: Natural Gas Furnace (AFUE) | C49: Residential Equipment: Stock Average Efficiency: Main Space Heaters: Natural Gas Furnace: Low economic growth | D49: AEO.2022.LOWMACRO.EFI_STK_RESD_SPHR_NFR_NA_NA_AFUE.A | E49: AFUE | G49: 0.825728 | H49: 0.829944 | I49: 0.834061 | J49: 0.838133 | K49: 0.84218 | L49: 0.846256 | M49: 0.850016 | N49: 0.853493 | O49: 0.85666 | P49: 0.859499 | Q49: 0.862051 | R49: 0.864296 | S49: 0.866252 | T49: 0.867912 | U49: 0.869281 | V49: 0.870351 | W49: 0.871148 | X49: 0.871663 | Y49: 0.871901 | Z49: 0.871858 | AA49: 0.871554 | AB49: 0.871274 | AC49: 0.871014 | AD49: 0.870778 | AE49: 0.870565 | AF49: 0.870378 | AG49: 0.870216 | AH49: 0.87008 | AI49: 0.869967 | AJ49: 0.869874 | AK49: 0.002
B50: Distillate Furnace (AFUE) | C50: Residential Equipment: Stock Average Efficiency: Main Space Heaters: Distillate Furnace: Low economic growth | D50: AEO.2022.LOWMACRO.EFI_STK_RESD_SPHR_DFR_NA_NA_AFUE.A | E50: AFUE | G50: 0.834686 | H50: 0.835597 | I50: 0.836411 | J50: 0.837252 | K50: 0.838107 | L50: 0.838979 | M50: 0.839828 | N50: 0.840618 | O50: 0.841345 | P50: 0.841995 | Q50: 0.842588 | R50: 0.843113 | S50: 0.843579 | T50: 0.843984 | U50: 0.844329 | V50: 0.844616 | W50: 0.844847 | X50: 0.84502 | Y50: 0.845131 | Z50: 0.84518 | AA50: 0.845174 | AB50: 0.845165 | AC50: 0.845155 | AD50: 0.845141 | AE50: 0.84512 | AF50: 0.845094 | AG50: 0.845057 | AH50: 0.84501 | AI50: 0.844953 | AJ50: 0.844885 | AK50: 0
A51: RST000:fa_Electric | B51: Space Cooling
A52: RST000:fa_NaturalGas | B52: Electric Heat Pumps (SEER) | C52: Residential Equipment: Stock Average Efficiency: Space Cooling: Electric Heat Pumps: Low economic growth | D52: AEO.2022.LOWMACRO.EFI_STK_RESD_SPC_EHP_NA_NA_SEER.A | E52: SEER | G52: 13.942868 | H52: 14.079188 | I52: 14.315822 | J52: 14.532186 | K52: 14.73676 | L52: 14.928681 | M52: 15.109222 | N52: 15.278121 | O52: 15.435934 | P52: 15.581635 | Q52: 15.715282 | R52: 15.836614 | S52: 15.944226 | T52: 16.037289 | U52: 16.114223 | V52: 16.172186 | W52: 16.20854 | X52: 16.241852 | Y52: 16.271374 | Z52: 16.296741 | AA52: 16.317814 | AB52: 16.33474 | AC52: 16.347799 | AD52: 16.357452 | AE52: 16.364264 | AF52: 16.368788 | AG52: 16.371586 | AH52: 16.373158 | AI52: 16.373884 | AJ52: 16.374081 | AK52: 0.006
A53: RST000:fa_Total | B53: Natural Gas Heat Pumps (GCOP) | C53: Residential Equipment: Stock Average Efficiency: Space Cooling: Natural Gas Heat Pumps: Low economic growth | D53: AEO.2022.LOWMACRO.EFI_STK_RESD_SPC_NHU_NA_NA_GCOP.A | E53: GCOP | G53: 0.611393 | H53: 0.617321 | I53: 0.623879 | J53: 0.630243 | K53: 0.636405 | L53: 0.642344 | M53: 0.648128 | N53: 0.653823 | O53: 0.659591 | P53: 0.665547 | Q53: 0.671792 | R53: 0.678266 | S53: 0.68466 | T53: 0.690462 | U53: 0.69508 | V53: 0.698063 | W53: 0.69929 | X53: 0.699813 | Y53: 0.699968 | Z53: 0.699997 | AA53: 0.7 | AB53: 0.7 | AC53: 0.7 | AD53: 0.7 | AE53: 0.7 | AF53: 0.7 | AG53: 0.7 | AH53: 0.7 | AI53: 0.7 | AJ53: 0.7 | AK53: 0.005
B54: Geothermal Heat Pumps (EER) | C54: Residential Equipment: Stock Average Efficiency: Space Cooling: Geothermal Heat Pumps: Low economic growth | D54: AEO.2022.LOWMACRO.EFI_STK_RESD_SPC_GEHP_NA_NA_EER.A | E54: EER | G54: 15.699868 | H54: 16.037779 | I54: 16.317791 | J54: 16.439041 | K54: 16.536537 | L54: 16.630522 | M54: 16.71191 | N54: 16.780962 | O54: 16.839209 | P54: 16.888083 | Q54: 16.930128 | R54: 16.96526 | S54: 16.995779 | T54: 17.023705 | U54: 17.048967 | V54: 17.071047 | W54: 17.090841 | X54: 17.107815 | Y54: 17.122906 | Z54: 17.136196 | AA54: 17.148056 | AB54: 17.158499 | AC54: 17.166634 | AD54: 17.172842 | AE54: 17.176811 | AF54: 17.177925 | AG54: 17.179966 | AH54: 17.18247 | AI54: 17.185184 | AJ54: 17.187729 | AK54: 0.003
B55: Central Air Conditioners (SEER) | C55: Residential Equipment: Stock Average Efficiency: Space Cooling: Central Air Conditioners: Low economic growth | D55: AEO.2022.LOWMACRO.EFI_STK_RESD_SPC_CAC_NA_NA_SEER.A | E55: SEER | G55: 13.350917 | H55: 13.482215 | I55: 13.698519 | J55: 13.900108 | K55: 14.087223 | L55: 14.259071 | M55: 14.416427 | N55: 14.559613 | O55: 14.690548 | P55: 14.808434 | Q55: 14.913205 | R55: 15.006129 | S55: 15.08869 | T55: 15.160207 | U55: 15.22127 | V55: 15.270899 | W55: 15.307234 | X55: 15.343105 | Y55: 15.377698 | Z55: 15.410213 | AA55: 15.439958 | AB55: 15.466483 | AC55: 15.489461 | AD55: 15.508827 | AE55: 15.524755 | AF55: 15.537507 | AG55: 15.547526 | AH55: 15.555306 | AI55: 15.561322 | AJ55: 15.565972 | AK55: 0.005
A56: RST000:ga_Refrigerators | B56: Room Air Conditioners (EER) | C56: Residential Equipment: Stock Average Efficiency: Space Cooling: Room Air Conditioners: Low economic growth | D56: AEO.2022.LOWMACRO.EFI_STK_RESD_SPC_RAC_NA_NA_EER.A | E56: EER | G56: 11.214135 | H56: 11.293177 | I56: 11.378103 | J56: 11.469821 | K56: 11.55479 | L56: 11.630031 | M56: 11.695104 | N56: 11.751246 | O56: 11.797316 | P56: 11.850436 | Q56: 11.887785 | R56: 11.909636 | S56: 11.931602 | T56: 11.953343 | U56: 11.974455 | V56: 11.99447 | W56: 12.012794 | X56: 12.028731 | Y56: 12.041742 | Z56: 12.06344 | AA56: 12.081763 | AB56: 12.097495 | AC56: 12.1113 | AD56: 12.123844 | AE56: 12.135592 | AF56: 12.146557 | AG56: 12.156595 | AH56: 12.165377 | AI56: 12.17261 | AJ56: 12.178071 | AK56: 0.003
A57: RST000:ga_Freezers | B57: Water Heaters
B58: Electric (EF) | C58: Residential Equipment: Stock Average Efficiency: Water Heaters: Electric: Low economic growth | D58: AEO.2022.LOWMACRO.EFI_STK_RESD_WHT_ELE_NA_NA_EF.A | E58: EF | G58: 0.923471 | H58: 0.929527 | I58: 0.934797 | J58: 0.940422 | K58: 0.946173 | L58: 0.952004 | M58: 0.957348 | N58: 0.962212 | O58: 0.966561 | P58: 0.970409 | Q58: 0.973755 | R58: 0.9766 | S58: 0.978957 | T58: 0.980819 | U58: 0.982189 | V58: 0.983085 | W58: 0.983491 | X58: 0.983428 | Y58: 0.983376 | Z58: 0.983335 | AA58: 0.983303 | AB58: 0.983279 | AC58: 0.98326 | AD58: 0.983247 | AE58: 0.983237 | AF58: 0.983229 | AG58: 0.983224 | AH58: 0.98322 | AI58: 0.983217 | AJ58: 0.983214 | AK58: 0.002
B59: Natural Gas (EF) | C59: Residential Equipment: Stock Average Efficiency: Water Heaters: Natural Gas: Low economic growth | D59: AEO.2022.LOWMACRO.EFI_STK_RESD_WHT_NG_NA_NA_EF.A | E59: EF | G59: 0.615744 | H59: 0.618895 | I59: 0.621485 | J59: 0.623566 | K59: 0.625148 | L59: 0.62624 | M59: 0.626865 | N59: 0.626999 | O59: 0.626681 | P59: 0.625972 | Q59: 0.625264 | R59: 0.624574 | S59: 0.623918 | T59: 0.623309 | U59: 0.622756 | V59: 0.622266 | W59: 0.621842 | X59: 0.621485 | Y59: 0.621192 | Z59: 0.620958 | AA59: 0.620777 | AB59: 0.620642 | AC59: 0.620543 | AD59: 0.620472 | AE59: 0.620425 | AF59: 0.620394 | AG59: 0.620375 | AH59: 0.620364 | AI59: 0.620359 | AJ59: 0.620357 | AK59: 0
B60: Distillate Fuel Oil (EF) | C60: Residential Equipment: Stock Average Efficiency: Water Heaters: Distillate Fuel Oil: Low economic growth | D60: AEO.2022.LOWMACRO.EFI_STK_RESD_WHT_DFO_NA_NA_EF.A | E60: EF | G60: 0.597978 | H60: 0.612125 | I60: 0.62499 | J60: 0.636196 | K60: 0.645649 | L60: 0.653421 | M60: 0.65938 | N60: 0.663449 | O60: 0.665525 | P60: 0.665556 | Q60: 0.66559 | R60: 0.665626 | S60: 0.665664 | T60: 0.665702 | U60: 0.66574 | V60: 0.665776 | W60: 0.665811 | X60: 0.665845 | Y60: 0.665876 | Z60: 0.665906 | AA60: 0.665935 | AB60: 0.665961 | AC60: 0.665986 | AD60: 0.666012 | AE60: 0.666035 | AF60: 0.666057 | AG60: 0.666077 | AH60: 0.666095 | AI60: 0.666112 | AJ60: 0.666126 | AK60: 0.004
A61: RST000:ha_ElectricHeatP | B61: Propane (EF) | C61: Residential Equipment: Stock Average Efficiency: Water Heaters: Propane: Low economic growth | D61: AEO.2022.LOWMACRO.EFI_STK_RESD_WHT_PROP_NA_NA_EF.A | E61: EF | G61: 0.603391 | H61: 0.606443 | I61: 0.609177 | J61: 0.611531 | K61: 0.613499 | L61: 0.615082 | M61: 0.616264 | N61: 0.617017 | O61: 0.61733 | P61: 0.61719 | Q61: 0.617051 | R61: 0.616921 | S61: 0.616799 | T61: 0.61669 | U61: 0.616592 | V61: 0.616509 | W61: 0.616441 | X61: 0.61639 | Y61: 0.616355 | Z61: 0.616336 | AA61: 0.616332 | AB61: 0.616341 | AC61: 0.61636 | AD61: 0.616389 | AE61: 0.616422 | AF61: 0.616456 | AG61: 0.616489 | AH61: 0.616519 | AI61: 0.616548 | AJ61: 0.616573 | AK61: 0.001
A62: RST000:ha_NaturalGasHea | B62: Other Appliances (kilowatthours per year)
A63: RST000:ha_GeothermalHea | B63: Refrigerators | C63: Residential Equipment: Stock Average Efficiency: Other Appliances: Refrigerators: Low economic growth | D63: AEO.2022.LOWMACRO.EFI_STK_RESD_OTAR_RFG_NA_NA_KWH.A | E63: kWh | G63: 611.68988 | H63: 602.07062 | I63: 592.40869 | J63: 583.24225 | K63: 574.59338 | L63: 566.45447 | M63: 558.79932 | N63: 551.60077 | O63: 544.85504 | P63: 538.59955 | Q63: 532.91553 | R63: 527.75848 | S63: 523.14087 | T63: 519.06561 | U63: 515.50519 | V63: 512.45703 | W63: 509.89145 | X63: 507.83685 | Y63: 506.26801 | Z63: 505.20886 | AA63: 504.68805 | AB63: 504.69116 | AC63: 504.69424 | AD63: 504.69714 | AE63: 504.6987 | AF63: 504.70248 | AG63: 504.70706 | AH63: 504.71304 | AI63: 504.72058 | AJ63: 504.7312 | AK63: -0.007
A64: RST000:ha_NaturalGasFur | B64: Freezers | C64: Residential Equipment: Stock Average Efficiency: Other Appliances: Freezers: Low economic growth | D64: AEO.2022.LOWMACRO.EFI_STK_RESD_OTAR_FRZ_NA_NA_KWH.A | E64: kWh | G64: 453.33017 | H64: 448.66418 | I64: 443.98053 | J64: 439.19278 | K64: 434.32385 | L64: 429.37357 | M64: 424.38077 | N64: 419.61008 | O64: 415.06067 | P64: 410.75241 | Q64: 406.66867 | R64: 402.77826 | S64: 399.11786 | T64: 395.70456 | U64: 392.51959 | V64: 389.60083 | W64: 386.92304 | X64: 384.49777 | Y64: 382.31036 | Z64: 380.34644 | AA64: 378.65359 | AB64: 377.2085 | AC64: 376.04828 | AD64: 375.19199 | AE64: 374.64114 | AF64: 374.39032 | AG64: 374.39163 | AH64: 374.39301 | AI64: 374.39414 | AJ64: 374.39569 | AK64: -0.007
A65: RST000:ha_DistillateFur | B65: Building Shell Efficiency Index
B66: Space Heating
B67: Pre-2015 Homes | C67: Residential Equipment: Building Shell Efficiency Index: Space Heating: Pre-2015 Homes: Low economic growth | D67: AEO.2022.LOWMACRO.EFI_BSE_RESD_SPH_OLD_NA_NA_Y15EQ1.A | E67: 2015=1.00 | G67: 0.960074 | H67: 0.952097 | I67: 0.945333 | J67: 0.93951 | K67: 0.933794 | L67: 0.927669 | M67: 0.921273 | N67: 0.914467 | O67: 0.907379 | P67: 0.900281 | Q67: 0.89324 | R67: 0.885931 | S67: 0.878659 | T67: 0.871608 | U67: 0.864869 | V67: 0.858314 | W67: 0.85174 | X67: 0.845103 | Y67: 0.83844 | Z67: 0.831738 | AA67: 0.824987 | AB67: 0.81829 | AC67: 0.811716 | AD67: 0.80518 | AE67: 0.798646 | AF67: 0.792145 | AG67: 0.785603 | AH67: 0.77906 | AI67: 0.772481 | AJ67: 0.765934 | AK67: -0.008
A68: RST000:ia_ElectricHeatP | B68: New Construction | C68: Residential Equipment: Building Shell Efficiency Index: Space Heating: New Construction: Low economic growth | D68: AEO.2022.LOWMACRO.EFI_BSE_RESD_SPH_NCO_NA_NA_Y15EQ1.A | E68: 2015=1.00 | G68: 0.847376 | H68: 0.88884 | I68: 0.874386 | J68: 0.870592 | K68: 0.868825 | L68: 0.867276 | M68: 0.870184 | N68: 0.87128 | O68: 0.870576 | P68: 0.870458 | Q68: 0.869662 | R68: 0.865661 | S68: 0.863842 | T68: 0.861375 | U68: 0.860073 | V68: 0.858327 | W68: 0.860181 | X68: 0.860184 | Y68: 0.860694 | Z68: 0.859456 | AA68: 0.85729 | AB68: 0.856289 | AC68: 0.855514 | AD68: 0.854292 | AE68: 0.854167 | AF68: 0.853711 | AG68: 0.854482 | AH68: 0.854203 | AI68: 0.854742 | AJ68: 0.856398 | AK68: 0
A69: RST000:ia_NaturalGasHea | B69: All Homes | C69: Residential Equipment: Building Shell Efficiency Index: Space Heating: All Homes: Low economic growth | D69: AEO.2022.LOWMACRO.EFI_BSE_RESD_SPH_AHM_NA_NA_Y15EQ1.A | E69: 2015=1.00 | G69: 0.953071 | H69: 0.94504 | I69: 0.938177 | J69: 0.932256 | K69: 0.926528 | L69: 0.920543 | M69: 0.914454 | N69: 0.908119 | O69: 0.901644 | P69: 0.895278 | Q69: 0.889065 | R69: 0.882694 | S69: 0.876447 | T69: 0.870471 | U69: 0.864839 | V69: 0.859432 | W69: 0.854107 | X69: 0.848815 | Y69: 0.843589 | Z69: 0.838405 | AA69: 0.833242 | AB69: 0.82819 | AC69: 0.823298 | AD69: 0.818496 | AE69: 0.813761 | AF69: 0.809113 | AG69: 0.804503 | AH69: 0.799948 | AI69: 0.795428 | AJ69: 0.791 | AK69: -0.006
A70: RST000:ia_GeothermalHea | B70: Space Cooling
A71: RST000:ia_Cent.AirCondi | B71: Pre-2015 Homes | C71: Residential Equipment: Building Shell Efficiency Index: Space Cooling: Pre-2015 Homes: Low economic growth | D71: AEO.2022.LOWMACRO.EFI_BSE_RESD_SPC_OLD_NA_NA_Y15EQ1.A | E71: 2015=1.00 | G71: 0.986008 | H71: 0.983193 | I71: 0.980836 | J71: 0.978775 | K71: 0.976729 | L71: 0.974527 | M71: 0.97223 | N71: 0.969784 | O71: 0.967245 | P71: 0.964714 | Q71: 0.962191 | R71: 0.959559 | S71: 0.95693 | T71: 0.95438 | U71: 0.95195 | V71: 0.949579 | W71: 0.947179 | X71: 0.944754 | Y71: 0.942322 | Z71: 0.939871 | AA71: 0.93739 | AB71: 0.934931 | AC71: 0.932514 | AD71: 0.930109 | AE71: 0.927703 | AF71: 0.925295 | AG71: 0.922882 | AH71: 0.920466 | AI71: 0.918031 | AJ71: 0.91561 | AK71: -0.003
A72: RST000:ia_RoomAirCondit | B72: New Construction | C72: Residential Equipment: Building Shell Efficiency Index: Space Cooling: New Construction: Low economic growth | D72: AEO.2022.LOWMACRO.EFI_BSE_RESD_SPC_NCO_NA_NA_Y15EQ1.A | E72: 2015=1.00 | G72: 0.975003 | H72: 0.998662 | I72: 0.993724 | J72: 0.990626 | K72: 0.990066 | L72: 0.990329 | M72: 0.991837 | N72: 0.992271 | O72: 0.991972 | P72: 0.991932 | Q72: 0.991776 | R72: 0.989402 | S72: 0.988868 | T72: 0.988115 | U72: 0.987928 | V72: 0.987207 | W72: 0.988169 | X72: 0.987974 | Y72: 0.988434 | Z72: 0.988046 | AA72: 0.98692 | AB72: 0.986684 | AC72: 0.986511 | AD72: 0.986236 | AE72: 0.986746 | AF72: 0.986846 | AG72: 0.987809 | AH72: 0.987948 | AI72: 0.988563 | AJ72: 0.990008 | AK72: 0.001
B73: All Homes | C73: Residential Equipment: Building Shell Efficiency Index: Space Cooling: All Homes: Low economic growth | D73: AEO.2022.LOWMACRO.EFI_BSE_RESD_SPC_AHM_NA_NA_Y15EQ1.A | E73: 2015=1.00 | G73: 0.986182 | H73: 0.983653 | I73: 0.981536 | J73: 0.979697 | K73: 0.977892 | L73: 0.975968 | M73: 0.973995 | N73: 0.971919 | O73: 0.969784 | P73: 0.967679 | Q73: 0.965602 | R73: 0.963442 | S73: 0.961305 | T73: 0.959247 | U73: 0.957307 | V73: 0.955429 | W73: 0.953551 | X73: 0.951669 | Y73: 0.949803 | Z73: 0.947937 | AA73: 0.946053 | AB73: 0.944199 | AC73: 0.942391 | AD73: 0.940602 | AE73: 0.938829 | AF73: 0.937066 | AG73: 0.935315 | AH73: 0.93357 | AI73: 0.931823 | AJ73: 0.930103 | AK73: -0.002
B74: Distributed Generation and
A75: RST000:ja_Electric(EF) | B75: Combined Heat and Power
A76: RST000:ja_NaturalGas(EF | B76: Generating Capacity (gigawatts)
A77: RST000:ja_Distillate(EF | B77: Natural Gas Fuel Cells | C77: Residential: Combined Heat and Power: Generating Capacity: Fuel Cells: Low economic growth | D77: AEO.2022.LOWMACRO.CAP_NA_COMM_CHP_FCL_NA_NA_MW.A | E77: GW | G77: 0 | H77: 0 | I77: 0 | J77: 0 | K77: 0 | L77: 0 | M77: 0 | N77: 0 | O77: 0 | P77: 0 | Q77: 0 | R77: 0 | S77: 0 | T77: 2e-06 | U77: 5e-06 | V77: 1e-05 | W77: 2.1e-05 | X77: 4.1e-05 | Y77: 7.8e-05 | Z77: 0.000146 | AA77: 0.000271 | AB77: 0.000395 | AC77: 0.00052 | AD77: 0.000645 | AE77: 0.00077 | AF77: 0.000896 | AG77: 0.001022 | AH77: 0.001147 | AI77: 0.001273 | AJ77: 0.001399 | AK77: - -
A78: RST000:ja_LiquefiedPetr | B78: Solar Photovoltaic | C78: Residential: Combined Heat and Power: Generating Capacity: Solar Photovoltaic: Low economic growth | D78: AEO.2022.LOWMACRO.CAP_NA_RESD_CHP_SLR_PHTVL_NA_MW.A | E78: GW | G78: 21.272516 | H78: 23.21953 | I78: 25.164965 | J78: 26.557243 | K78: 27.860468 | L78: 29.152689 | M78: 30.454779 | N78: 31.826214 | O78: 33.259167 | P78: 34.706844 | Q78: 36.238861 | R78: 37.829205 | S78: 39.584492 | T78: 41.482212 | U78: 43.369297 | V78: 45.266972 | W78: 47.348141 | X78: 49.414562 | Y78: 51.598206 | Z78: 53.9884 | AA78: 56.450306 | AB78: 59.155888 | AC78: 62.009609 | AD78: 64.908005 | AE78: 68.013458 | AF78: 71.232567 | AG78: 74.634651 | AH78: 78.220139 | AI78: 81.992233 | AJ78: 85.854904 | AK78: 0.049
B79: Wind | C79: Residential: Combined Heat and Power: Generating Capacity: Wind: Low economic growth | D79: AEO.2022.LOWMACRO.CAP_NA_RESD_CHP_WND_NA_NA_MW.A | E79: GW | G79: 0.014232 | H79: 0.014232 | I79: 0.014232 | J79: 0.014232 | K79: 0.014232 | L79: 0.014232 | M79: 0.014232 | N79: 0.014232 | O79: 0.014232 | P79: 0.014232 | Q79: 0.014232 | R79: 0.014233 | S79: 0.014233 | T79: 0.014236 | U79: 0.014242 | V79: 0.014253 | W79: 0.014274 | X79: 0.014314 | Y79: 0.014388 | Z79: 0.014525 | AA79: 0.014773 | AB79: 0.015022 | AC79: 0.015272 | AD79: 0.015522 | AE79: 0.015773 | AF79: 0.016024 | AG79: 0.016275 | AH79: 0.016527 | AI79: 0.016779 | AJ79: 0.017031 | AK79: 0.006
B80: Total | C80: Residential: Combined Heat and Power: Generating Capacity: Total: Low economic growth | D80: AEO.2022.LOWMACRO.CAP_NA_RESD_CHP_TOT_NA_NA_MW.A | E80: GW | G80: 21.286749 | H80: 23.233763 | I80: 25.179197 | J80: 26.571476 | K80: 27.874701 | L80: 29.166922 | M80: 30.469011 | N80: 31.840446 | O80: 33.273399 | P80: 34.721077 | Q80: 36.253094 | R80: 37.843437 | S80: 39.598724 | T80: 41.496449 | U80: 43.383541 | V80: 45.281235 | W80: 47.362434 | X80: 49.428917 | Y80: 51.612671 | Z80: 54.003071 | AA80: 56.465351 | AB80: 59.171307 | AC80: 62.025398 | AD80: 64.924179 | AE80: 68.029999 | AF80: 71.249481 | AG80: 74.651947 | AH80: 78.237808 | AI80: 82.010284 | AJ80: 85.873329 | AK80: 0.049
A81: RST000:ka_Refrigerators | B81: Net Generation (billion kilowatthours)
A82: RST000:ka_Freezers | B82: Natural Gas Fuel Cells | C82: Residential: Combined Heat and Power: Net Generation: Fuel Cells: Low economic growth | D82: AEO.2022.LOWMACRO.GEN_NA_COMM_CHP_FCL_NA_NA_MILLKWH.A | E82: billion kWh | G82: 0 | H82: 0 | I82: 0 | J82: 0 | K82: 0 | L82: 0 | M82: 0 | N82: 0 | O82: 0 | P82: 0 | Q82: 0 | R82: 0 | S82: 1e-06 | T82: 5e-06 | U82: 1.3e-05 | V82: 2.9e-05 | W82: 5.8e-05 | X82: 0.000115 | Y82: 0.000217 | Z82: 0.000408 | AA82: 0.000755 | AB82: 0.001102 | AC82: 0.001451 | AD82: 0.0018 | AE82: 0.002149 | AF82: 0.002499 | AG82: 0.00285 | AH82: 0.003201 | AI82: 0.003553 | AJ82: 0.003904 | AK82: - -
B83: Solar Photovoltaic | C83: Residential: Combined Heat and Power: Net Generation: Solar Photovoltaic: Low economic growth | D83: AEO.2022.LOWMACRO.GEN_NA_COMM_CHP_SLR_PHTVL_NA_MILLKWH.A | E83: billion kWh | G83: 33.568367 | H83: 37.323689 | I83: 41.078842 | J83: 43.92907 | K83: 46.637699 | L83: 49.32835 | M83: 52.035904 | N83: 54.856461 | O83: 57.778942 | P83: 60.727287 | Q83: 63.814194 | R83: 66.997108 | S83: 70.448288 | T83: 74.131058 | U83: 77.799164 | V83: 81.486954 | W83: 85.473923 | X83: 89.439262 | Y83: 93.596977 | Z83: 98.090248 | AA83: 102.70145 | AB83: 107.70828 | AC83: 112.95686 | AD83: 118.27981 | AE83: 123.94126 | AF83: 129.78888 | AG83: 135.93684 | AH83: 142.38464 | AI83: 149.13727 | AJ83: 156.04033 | AK83: 0.054
B84: Wind | C84: Residential: Combined Heat and Power: Net Generation: Wind: Low economic growth | D84: AEO.2022.LOWMACRO.GEN_NA_COMM_CHP_WND_NA_NA_MILLKWH.A | E84: billion kWh | G84: 0.018546 | H84: 0.018546 | I84: 0.018546 | J84: 0.018546 | K84: 0.018546 | L84: 0.018546 | M84: 0.018546 | N84: 0.018546 | O84: 0.018546 | P84: 0.018546 | Q84: 0.018546 | R84: 0.018546 | S84: 0.018547 | T84: 0.018549 | U84: 0.018555 | V84: 0.018567 | W84: 0.018588 | X84: 0.01863 | Y84: 0.018705 | Z84: 0.018846 | AA84: 0.019101 | AB84: 0.019356 | AC84: 0.019612 | AD84: 0.019868 | AE84: 0.020125 | AF84: 0.020381 | AG84: 0.020638 | AH84: 0.020896 | AI84: 0.021153 | AJ84: 0.02141 | AK84: 0.005
B85: Total | C85: Residential: Combined Heat and Power: Net Generation: Total: Low economic growth | D85: AEO.2022.LOWMACRO.GEN_NA_COMM_CHP_TOT_NA_NA_MILLKWH.A | E85: billion kWh | G85: 33.586914 | H85: 37.342236 | I85: 41.097389 | J85: 43.947617 | K85: 46.656246 | L85: 49.346897 | M85: 52.054451 | N85: 54.875008 | O85: 57.797489 | P85: 60.745834 | Q85: 63.832741 | R85: 67.015656 | S85: 70.466835 | T85: 74.149612 | U85: 77.817734 | V85: 81.505554 | W85: 85.492569 | X85: 89.458008 | Y85: 93.615898 | Z85: 98.109497 | AA85: 102.72131 | AB85: 107.72873 | AC85: 112.97792 | AD85: 118.30148 | AE85: 123.96354 | AF85: 129.81177 | AG85: 135.96034 | AH85: 142.40874 | AI85: 149.16197 | AJ85: 156.06564 | AK85: 0.054
A86: RST000:la_Pre-1998Homes | B86: Disposition
A87: RST000:la_NewConstructi | B87: Sales to the Grid | C87: Residential: Combined Heat and Power: Net Generation: Sales to the Grid: Low economic growth | D87: AEO.2022.LOWMACRO.GEN_NA_COMM_CHP_STG_NA_NA_MILLKWH.A | E87: billion kWh | G87: 5.224064 | H87: 5.967855 | I87: 6.699723 | J87: 7.254611 | K87: 7.770401 | L87: 8.296711 | M87: 8.840633 | N87: 9.403831 | O87: 9.998558 | P87: 10.589752 | Q87: 11.223314 | R87: 11.871784 | S87: 12.597094 | T87: 13.369761 | U87: 14.142963 | V87: 14.904646 | W87: 15.74896 | X87: 16.568188 | Y87: 17.441166 | Z87: 18.38599 | AA87: 19.343506 | AB87: 20.412245 | AC87: 21.525923 | AD87: 22.638149 | AE87: 23.848207 | AF87: 25.083582 | AG87: 26.401922 | AH87: 27.772264 | AI87: 29.193533 | AJ87: 30.651522 | AK87: 0.063
A88: RST000:la_AllHomes | B88: Generation for Own Use | C88: Residential: Combined Heat and Power: Net Generation: Generation for Own Use: Low economic growth | D88: AEO.2022.LOWMACRO.GEN_NA_COMM_CHP_GFO_NA_NA_MILLKWH.A | E88: billion kWh | G88: 28.362848 | H88: 31.374378 | I88: 34.397667 | J88: 36.693005 | K88: 38.885845 | L88: 41.050186 | M88: 43.213814 | N88: 45.471176 | O88: 47.798931 | P88: 50.156082 | Q88: 52.609425 | R88: 55.143871 | S88: 57.86974 | T88: 60.779846 | U88: 63.67477 | V88: 66.600899 | W88: 69.743607 | X88: 72.889824 | Y88: 76.174736 | Z88: 79.723518 | AA88: 83.377792 | AB88: 87.31649 | AC88: 91.452003 | AD88: 95.663322 | AE88: 100.11533 | AF88: 104.72818 | AG88: 109.5584 | AH88: 114.63648 | AI88: 119.96843 | AJ88: 125.41412 | AK88: 0.053
B89: Energy Input (trillion Btu)
B90: Natural Gas Fuel Cells | C90: Residential: Combined Heat and Power: Energy Input: Fuel Cells: Low economic growth | D90: AEO.2022.LOWMACRO.CNSM_NA_COMM_CHP_FCL_NA_NA_TRLBTU.A | E90: trillion Btu | G90: 0 | H90: 0 | I90: 0 | J90: 0 | K90: 0 | L90: 0 | M90: 0 | N90: 0 | O90: 0 | P90: 0 | Q90: 0 | R90: 3e-06 | S90: 9e-06 | T90: 3.9e-05 | U90: 0.0001 | V90: 0.00022 | W90: 0.000446 | X90: 0.000875 | Y90: 0.001655 | Z90: 0.003101 | AA90: 0.005725 | AB90: 0.008347 | AC90: 0.010971 | AD90: 0.013594 | AE90: 0.016216 | AF90: 0.018834 | AG90: 0.021455 | AH90: 0.024071 | AI90: 0.026683 | AJ90: 0.029288 | AK90: - -
A91: RST000:ma_Pre-1998Homes | B91: Solar Photovoltaic | C91: Residential: Combined Heat and Power: Energy Input: Solar Photovoltaic: Low economic growth | D91: AEO.2022.LOWMACRO.CNSM_NA_COMM_CHP_SLR_PHTVL_NA_TRLBTU.A | E91: trillion Btu | G91: 277.5553 | H91: 308.05719 | I91: 336.70551 | J91: 357.55841 | K91: 378.3233 | L91: 394.63434 | M91: 415.04358 | N91: 436.20337 | O91: 458.1474 | P91: 479.54761 | Q91: 502.21405 | R91: 528.19928 | S91: 554.21283 | T91: 580.63434 | U91: 606.95343 | V91: 634.33252 | W91: 664.0047 | X91: 696.08276 | Y91: 729.50317 | Z91: 764.87933 | AA91: 800.34558 | AB91: 838.4093 | AC91: 880.90863 | AD91: 920.92273 | AE91: 965.40332 | AF91: 1012.1259 | AG91: 1058.214 | AH91: 1113.6364 | AI91: 1164.7744 | AJ91: 1219.8955 | AK91: 0.052
A92: RST000:ma_NewConstructi | B92: Wind | C92: Residential: Combined Heat and Power: Energy Input: Wind: Low economic growth | D92: AEO.2022.LOWMACRO.CNSM_NA_COMM_CHP_WND_NA_NA_TRLBTU.A | E92: trillion Btu | G92: 0.172248 | H92: 0.172009 | I92: 0.169952 | J92: 0.168357 | K92: 0.167438 | L92: 0.165436 | M92: 0.164201 | N92: 0.163529 | O92: 0.162485 | P92: 0.162315 | Q92: 0.162004 | R92: 0.161729 | S92: 0.161494 | T92: 0.161033 | U92: 0.160486 | V92: 0.160208 | W92: 0.159728 | X92: 0.159928 | Y92: 0.16044 | Z92: 0.161586 | AA92: 0.163318 | AB92: 0.165319 | AC92: 0.167114 | AD92: 0.169115 | AE92: 0.170756 | AF92: 0.172466 | AG92: 0.17432 | AH92: 0.17643 | AI92: 0.178361 | AJ92: 0.180448 | AK92: 0.002
A93: RST000:ma_AllHomes | B93: Total | C93: Residential: Combined Heat and Power: Energy Input: Total: Low economic growth | D93: AEO.2022.LOWMACRO.CNSM_NA_COMM_CHP_TOT_NA_NA_TRLBTU.A | E93: trillion Btu | G93: 277.72754 | H93: 308.22919 | I93: 336.87546 | J93: 357.72678 | K93: 378.49075 | L93: 394.79977 | M93: 415.20779 | N93: 436.36691 | O93: 458.30987 | P93: 479.70993 | Q93: 502.37607 | R93: 528.36102 | S93: 554.37433 | T93: 580.79541 | U93: 607.11401 | V93: 634.49298 | W93: 664.16486 | X93: 696.24353 | Y93: 729.66528 | Z93: 765.04401 | AA93: 800.51465 | AB93: 838.58301 | AC93: 881.08673 | AD93: 921.10547 | AE93: 965.59033 | AF93: 1012.3173 | AG93: 1058.4098 | AH93: 1113.8368 | AI93: 1164.9795 | AJ93: 1220.1052 | AK93: 0.052
A98: RST000:dgc_FuelsCells
A99: RST000:dgc_SolarPhoto
A100: RST000:dgc_WindHuffHuff
A101: RST000:dgc_TotalCap
A103: RST000:dgg_FuelCells
A104: RST000:dgg_SolarPhoto
A105: RST000:dgg_WindHuffHuff
...

Sheet NREL EF Table 22
A1: Figure 22. Installed unit costs (left) and performance projections (right) for commercial air-source heat pumps
A2: Figure Notes: | B2: Installed costs include both capital and installation costs.
A4: Year | B4: Technology | C4: EFS Case | D4: Installed Cost ($/kBtu/hr) | E4: Efficiency (COP)
A5: 2015 | B5: Air Source Heat Pump | C5: Moderate Advancement | D5: 96 | E5: 3.3
A6: 2015 | B6: Air Source Heat Pump | C6: Rapid Advancement | D6: 96 | E6: 3.3
A7: 2015 | B7: Air Source Heat Pump | C7: Slow Advancement | D7: 96 | E7: 3.3
A8: 2015 | B8: Cold Climate Air Source Heat Pump | C8: Moderate Advancement | D8: 96 | E8: 1.5
A9: 2015 | B9: Cold Climate Air Source Heat Pump | C9: Rapid Advancement | D9: 96 | E9: 1.5
A10: 2015 | B10: Cold Climate Air Source Heat Pump | C10: Slow Advancement | D10: 96 | E10: 1.5
A11: 2020 | B11: Air Source Heat Pump | C11: Moderate Advancement | D11: 85 | E11: 3.75
A12: 2020 | B12: Air Source Heat Pump | C12: Rapid Advancement | D12: 80 | E12: 4
A13: 2020 | B13: Air Source Heat Pump | C13: Slow Advancement | D13: 92.873543 | E13: 3.4
A14: 2020 | B14: Cold Climate Air Source Heat Pump | C14: Moderate Advancement | D14: 85 | E14: 2
A15: 2020 | B15: Cold Climate Air Source Heat Pump | C15: Rapid Advancement | D15: 80 | E15: 2.5
A16: 2020 | B16: Cold Climate Air Source Heat Pump | C16: Slow Advancement | D16: 92.873543 | E16: 1.75
... A34: 2050 | B34: Cold Climate Air Source Heat Pump | C34: Slow Advancement | D34: 76.140668 | E34: 2.75

Sheet NREL EF Table 23
A1: Figure 23. Installed costs (left) and performance projections (right) for commercial HPWHs
A2: Figure Notes: | B2: Installed costs include both capital and installation costs.
A4: Year | B4: Technology | C4: EFS Case | D4: Installed Cost ($/kBtu/hr) | E4: Efficiency (COP)
A5: 2015 | B5: Heat Pump Water Heater | C5: Moderate Advancement | D5: 310 | E5: 2.45
A6: 2015 | B6: Heat Pump Water Heater | C6: Rapid Advancement | D6: 310 | E6: 2.45
A7: 2015 | B7: Heat Pump Water Heater | C7: Slow Advancement | D7: 310 | E7: 2.45
A8: 2020 | B8: Heat Pump Water Heater | C8: Moderate Advancement | D8: 287.51781 | E8: 3
A9: 2020 | B9: Heat Pump Water Heater | C9: Rapid Advancement | D9: 281.0389 | E9: 3
A10: 2020 | B10: Heat Pump Water Heater | C10: Slow Advancement | D10: 302.85283 | E10: 3
A11: 2030 | B11: Heat Pump Water Heater | C11: Moderate Advancement | D11: 247.32663 | E11: 3.25
A12: 2030 | B12: Heat Pump Water Heater | C12: Rapid Advancement | D12: 219.56945 | E12: 3.6
A13: 2030 | B13: Heat Pump Water Heater | C13: Slow Advancement | D13: 289.04903 | E13: 3
A14: 2040 | B14: Heat Pump Water Heater | C14: Moderate Advancement | D14: 212.75364 | E14: 3.35
A15: 2040 | B15: Heat Pump Water Heater | C15: Rapid Advancement | D15: 180 | E15: 3.85
A16: 2040 | B16: Heat Pump Water Heater | C16: Slow Advancement | D16: 275.8744 | E16: 3
... A19: 2050 | B19: Heat Pump Water Heater | C19: Slow Advancement | D19: 263.5 | E19: 3

Sheet Calculations
A1: Residential Equipment
A2: Appliances (cooking)
A3: Appliances Energy Consumption per Unit per Year by Fuel (btu/household) | B3: 2019 | C3: 2020 | D3: 2021 | E3: 2022 | F3: 2023 | G3: 2024 | H3: 2025 | I3: 2026 | J3: 2027 | K3: 2028 | L3: 2029 | M3: 2030 | N3: 2031 | O3: 2032 | P3: 2033 | Q3: 2034 | R3: 2035 | S3: 2036 | T3: 2037 | U3: 2038 | V3: 2039 | W3: 2040 | X3: 2041 | Y3: 2042 | Z3: 2043 | AA3: 2044 | AB3: 2045 | AC3: 2046 | AD3: 2047 | AE3: 2048 | AF3: 2049 | AG3: 2050
A4: traditional biomass | B4: ='IESS Residential'!$B$10*'IESS Residential'!$B$14 -> 4243675 | C4: ='IESS Residential'!$B$10*'IESS Residential'!$B$14 -> 4243675 | D4: ='IESS Residential'!$B$10*'IESS Residential'!$B$14 -> 4243675 | E4: ='IESS Residential'!$B$10*'IESS Residential'!$B$14 -> 4243675 | F4: ='IESS Residential'!$B$10*'IESS Residential'!$B$14 -> 4243675 | G4: ='IESS Residential'!$B$10*'IESS Residential'!$B$14 -> 4243675 | H4: ='IESS Residential'!$B$10*'IESS Residential'!$B$14 -> 4243675 | I4: ='IESS Residential'!$B$10*'IESS Residential'!$B$14 -> 4243675 | ... AG4: ='IESS Residential'!$B$10*'IESS Residential'!$B$14 -> 4243675
A5: LPG | B5: ='IESS Residential'!$B$4*'IESS Residential'!$B$14 -> 4811393.9 | C5: ='IESS Residential'!$B$4*'IESS Residential'!$B$14 -> 4811393.9 | D5: ='IESS Residential'!$B$4*'IESS Residential'!$B$14 -> 4811393.9 | E5: ='IESS Residential'!$B$4*'IESS Residential'!$B$14 -> 4811393.9 | F5: ='IESS Residential'!$B$4*'IESS Residential'!$B$14 -> 4811393.9 | G5: ='IESS Residential'!$B$4*'IESS Residential'!$B$14 -> 4811393.9 | H5: ='IESS Residential'!$B$4*'IESS Residential'!$B$14 -> 4811393.9 | I5: ='IESS Residential'!$B$4*'IESS Residential'!$B$14 -> 4811393.9 | ... AG5: ='IESS Residential'!$B$4*'IESS Residential'!$B$14 -> 4811393.9
A7: Annualized Incremental Equipment Cost | B7: 2019 | C7: 2020 | D7: 2021 | E7: 2022 | F7: 2023 | G7: 2024 | H7: 2025 | I7: 2026 | J7: 2027 | K7: 2028 | L7: 2029 | M7: 2030 | N7: 2031 | O7: 2032 | P7: 2033 | Q7: 2034 | R7: 2035 | S7: 2036 | T7: 2037 | U7: 2038 | V7: 2039 | W7: 2040 | X7: 2041 | Y7: 2042 | Z7: 2043 | AA7: 2044 | AB7: 2045 | AC7: 2046 | AD7: 2047 | AE7: 2048 | AF7: 2049 | AG7: 2050
A8: traditional biomass (trillion Rs) | B8: ='IESS Residential'!M56+'IESS Residential'!H21*'IESS Residential'!F21-'IESS Residential'!M78 -> 7.0337685e-09 | C8: ='IESS Residential'!N56+'IESS Residential'!I21*'IESS Residential'!G21-'IESS Residential'!N78 -> 8.8725e-20 | D8: ='IESS Residential'!O56+'IESS Residential'!J21*'IESS Residential'!H21-'IESS Residential'!O78 -> 0 | E8: ='IESS Residential'!P56+'IESS Residential'!K21*'IESS Residential'!I21-'IESS Residential'!P78 -> 0.136 | F8: ='IESS Residential'!Q56+'IESS Residential'!L21*'IESS Residential'!J21-'IESS Residential'!Q78 -> 0.142 | G8: ='IESS Residential'!R56+'IESS Residential'!M21*'IESS Residential'!K21-'IESS Residential'!R78 -> 0.1585 | H8: ='IESS Residential'!S56+'IESS Residential'!N21*'IESS Residential'!L21-'IESS Residential'!S78 -> 0.175 | I8: ='IESS Residential'!T56+'IESS Residential'!O21*'IESS Residential'!M21-'IESS Residential'!T78 -> 0.1915 | ... AD8: ='IESS Residential'!AO56+'IESS Residential'!AJ21*'IESS Residential'!AH21-'IESS Residential'!AO78 -> 0.735667 | AE8: =AD8 -> 0.735667 | AF8: =AE8 -> 0.735667 | AG8: =AF8 -> 0.735667
A9: LPG (trillion Rs) | B9: =('IESS Residential'!M56+'IESS Residential'!H21*'IESS Residential'!F21)-('IESS Residential'!M34+'IESS Residential'!H20*'IESS Residential'!F20) -> 2.2e-09 | C9: =('IESS Residential'!N56+'IESS Residential'!I21*'IESS Residential'!G21)-('IESS Residential'!N34+'IESS Residential'!I20*'IESS Residential'!G20) -> 7.6437e-20 | D9: =('IESS Residential'!O56+'IESS Residential'!J21*'IESS Residential'!H21)-('IESS Residential'!O34+'IESS Residential'!J20*'IESS Residential'!H20) -> 0 | E9: =('IESS Residential'!P56+'IESS Residential'!K21*'IESS Residential'!I21)-('IESS Residential'!P34+'IESS Residential'!K20*'IESS Residential'!I20) -> 0.374 | F9: =('IESS Residential'!Q56+'IESS Residential'!L21*'IESS Residential'!J21)-('IESS Residential'!Q34+'IESS Residential'!L20*'IESS Residential'!J20) -> 0.0425 | G9: =('IESS Residential'!R56+'IESS Residential'!M21*'IESS Residential'!K21)-('IESS Residential'!R34+'IESS Residential'!M20*'IESS Residential'!K20) -> -0.289 | H9: =('IESS Residential'!S56+'IESS Residential'!N21*'IESS Residential'!L21)-('IESS Residential'!S34+'IESS Residential'!N20*'IESS Residential'!L20) -> -0.6205 | I9: =('IESS Residential'!T56+'IESS Residential'!O21*'IESS Residential'!M21)-('IESS Residential'!T34+'IESS Residential'!O20*'IESS Residential'!M20) -> -0.952 | ... AD9: =('IESS Residential'!AO56+'IESS Residential'!AJ21*'IESS Residential'!AH21)-('IESS Residential'!AO34+'IESS Residential'!AJ20*'IESS Residential'!AH20) -> 0.193334 | AE9: =AD9 -> 0.193334 | AF9: =AE9 -> 0.193334 | AG9: =AF9 -> 0.193334
A11: Annualized Incremental Equipment Cost | B11: 2019 | C11: 2020 | D11: 2021 | E11: 2022 | F11: 2023 | G11: 2024 | H11: 2025 | I11: 2026 | J11: 2027 | K11: 2028 | L11: 2029 | M11: 2030 | N11: 2031 | O11: 2032 | P11: 2033 | Q11: 2034 | R11: 2035 | S11: 2036 | T11: 2037 | U11: 2038 | V11: 2039 | W11: 2040 | X11: 2041 | Y11: 2042 | Z11: 2043 | AA11: 2044 | AB11: 2045 | AC11: 2046 | AD11: 2047 | AE11: 2048 | AF11: 2049 | AG11: 2050
A12: traditional biomass (2012 USD) | B12: =B8*1000000000000/About!$B$58 -> 128.42374 | C12: =C8*1000000000000/About!$B$58 -> 1.6199562e-09 | D12: =D8*1000000000000/About!$B$58 -> 0 | E12: =E8*1000000000000/About!$B$58 -> 2.4831112e+09 | F12: =F8*1000000000000/About!$B$58 -> 2.5926602e+09 | G12: =G8*1000000000000/About!$B$58 -> 2.89392e+09 | H12: =H8*1000000000000/About!$B$58 -> 3.1951798e+09 | I12: =I8*1000000000000/About!$B$58 -> 3.4964397e+09 | ... AG12: =AG8*1000000000000/About!$B$58 -> 1.3431934e+10
A13: LPG (2012 USD) | B13: =B9*1000000000000/About!$B$58 -> 40.167975 | C13: =C9*1000000000000/About!$B$58 -> 1.3955998e-09 | D13: =D9*1000000000000/About!$B$58 -> 0 | E13: =E9*1000000000000/About!$B$58 -> 6.8285558e+09 | F13: =F9*1000000000000/About!$B$58 -> 7.7597225e+08 | G13: =G9*1000000000000/About!$B$58 -> -5.2766113e+09 | H13: =H9*1000000000000/About!$B$58 -> -1.1329195e+10 | I13: =I9*1000000000000/About!$B$58 -> -1.7381778e+10 | ... AG13: =AG9*1000000000000/About!$B$58 -> 3.5299251e+09
A15: Annualized Incremental Cost per BTU Shifted | B15: 2019 | C15: 2020 | D15: 2021 | E15: 2022 | F15: 2023 | G15: 2024 | H15: 2025 | I15: 2026 | J15: 2027 | K15: 2028 | L15: 2029 | M15: 2030 | N15: 2031 | O15: 2032 | P15: 2033 | Q15: 2034 | R15: 2035 | S15: 2036 | T15: 2037 | U15: 2038 | V15: 2039 | W15: 2040 | X15: 2041 | Y15: 2042 | Z15: 2043 | AA15: 2044 | AB15: 2045 | AC15: 2046 | AD15: 2047 | AE15: 2048 | AF15: 2049 | AG15: 2050
A16: traditional biomass | B16: =B12/B4 -> 3.0262389e-05 | C16: =C12/C4 -> 3.8173427e-16 | D16: =D12/D4 -> 0 | E16: =E12/E4 -> 585.13227 | F16: =F12/F4 -> 610.94693 | G16: =G12/G4 -> 681.93724 | H16: =H12/H4 -> 752.92756 | I16: =I12/I4 -> 823.91787 | ... AG16: =AG12/AG4 -> 3165.1655
A17: LPG | B17: =B13/B5 -> 8.3485111e-06 | C17: =C13/C5 -> 2.9006143e-16 | D17: =D13/D5 -> 0 | E17: =E13/E5 -> 1419.2469 | F17: =F13/F5 -> 161.27805 | G17: =G13/G5 -> -1096.6908 | H17: =H13/H5 -> -2354.6596 | I17: =I13/I5 -> -3612.6284 | ... AG17: =AG13/AG5 -> 733.65956
A19: Commercial Equipment
A20: Appliances (water heaters)
A21: Utilization Assumption
A22: space heating | B22: 0.08
A23: water heating | B23: 0.25
A26: Installed Cost ($/kBTU/hr) | B26: 2015 | C26: 2017 | D26: 2020 | E26: 2030 | F26: 2040 | G26: 2050
A27: natural gas (2017 USD) | C27: =AVERAGE('EIA Costs'!D134:D135)/'EIA Costs'!D131 -> 19.472362 | D27: =AVERAGE('EIA Costs'!G134:G135)/'EIA Costs'!G131 -> 19.472362 | E27: =AVERAGE('EIA Costs'!I134:I135)/'EIA Costs'!I131 -> 19.472362 | F27: =AVERAGE('EIA Costs'!K134:K135)/'EIA Costs'!K131 -> 19.472362 | G27: =AVERAGE('EIA Costs'!M134:M135)/'EIA Costs'!M131 -> 19.472362
A28: oil (2017 USD) | C28: ='EIA Costs'!D148/'EIA Costs'!D144 -> 17.333333 | D28: ='EIA Costs'!F148/'EIA Costs'!F144 -> 17.333333 | E28: ='EIA Costs'!H148/'EIA Costs'!H144 -> 17.333333 | F28: ='EIA Costs'!J148/'EIA Costs'!J144 -> 17.333333 | G28: ='EIA Costs'!L148/'EIA Costs'!L144 -> 17.333333
A29: ASHP (2016 USD) | B29: ='NREL EF Table 23'!D5 -> 310 | D29: ='NREL EF Table 23'!D8 -> 287.51781 | E29: ='NREL EF Table 23'!D11 -> 247.32663 | F29: ='NREL EF Table 23'!D14 -> 212.75364 | G29: ='NREL EF Table 23'!D17 -> 184.45
A31: Annualized Installed Cost ($/kBTU/hr) | B31: 2019 | C31: 2020 | D31: 2021 | E31: 2022 | F31: 2023 | G31: 2024 | H31: 2025 | I31: 2026 | J31: 2027 | K31: 2028 | L31: 2029 | M31: 2030 | N31: 2031 | O31: 2032 | P31: 2033 | Q31: 2034 | R31: 2035 | S31: 2036 | T31: 2037 | U31: 2038 | V31: 2039 | W31: 2040 | X31: 2041 | Y31: 2042 | Z31: 2043 | AA31: 2044 | AB31: 2045 | AC31: 2046 | AD31: 2047 | AE31: 2048 | AF31: 2049 | AG31: 2050
A32: natural gas (2012 USD) | B32: =(TREND($C$27:$D$27,$C$26:$D$26,B$11))*(About!$A$60) -> 18.238975 | C32: =(TREND($C$27:$D$27,$C$26:$D$26,C$11))*(About!$A$60) -> 18.238975 | D32: =(TREND($D$27:$E$27,$D$26:$E$26,D$11))*(About!$A$60) -> 18.238975 | E32: =(TREND($D$27:$E$27,$D$26:$E$26,E$11))*(About!$A$60) -> 18.238975 | F32: =(TREND($D$27:$E$27,$D$26:$E$26,F$11))*(About!$A$60) -> 18.238975 | G32: =(TREND($D$27:$E$27,$D$26:$E$26,G$11))*(About!$A$60) -> 18.238975 | H32: =(TREND($D$27:$E$27,$D$26:$E$26,H$11))*(About!$A$60) -> 18.238975 | I32: =(TREND($D$27:$E$27,$D$26:$E$26,I$11))*(About!$A$60) -> 18.238975 | J32: =(TREND($D$27:$E$27,$D$26:$E$26,J$11))*(About!$A$60) -> 18.238975 | K32: =(TREND($D$27:$E$27,$D$26:$E$26,K$11))*(About!$A$60) -> 18.238975 | ... M32: =(TREND($D$27:$E$27,$D$26:$E$26,M$11))*(About!$A$60) -> 18.238975 | N32: =(TREND($E$27:$G$27,$E$26:$G$26,N$11))*(About!$A$60) -> 18.238975 | O32: =(TREND($E$27:$G$27,$E$26:$G$26,O$11))*(About!$A$60) -> 18.238975 | P32: =(TREND($E$27:$G$27,$E$26:$G$26,P$11))*(About!$A$60) -> 18.238975 | Q32: =(TREND($E$27:$G$27,$E$26:$G$26,Q$11))*(About!$A$60) -> 18.238975 | R32: =(TREND($E$27:$G$27,$E$26:$G$26,R$11))*(About!$A$60) -> 18.238975 | S32: =(TREND($E$27:$G$27,$E$26:$G$26,S$11))*(About!$A$60) -> 18.238975 | T32: =(TREND($E$27:$G$27,$E$26:$G$26,T$11))*(About!$A$60) -> 18.238975 | U32: =(TREND($E$27:$G$27,$E$26:$G$26,U$11))*(About!$A$60) -> 18.238975 | ... AG32: =(TREND($E$27:$G$27,$E$26:$G$26,AG$11))*(About!$A$60) -> 18.238975
A33: oil (2012 USD) | B33: =(TREND($C$28:$D$28,$C$26:$D$26,B$11))*(About!$A$60) -> 16.235433 | C33: =(TREND($C$28:$D$28,$C$26:$D$26,C$11))*(About!$A$60) -> 16.235433 | D33: =(TREND($D$28:$E$28,$D$26:$E$26,D$11))*(About!$A$60) -> 16.235433 | E33: =(TREND($D$28:$E$28,$D$26:$E$26,E$11))*(About!$A$60) -> 16.235433 | F33: =(TREND($D$28:$E$28,$D$26:$E$26,F$11))*(About!$A$60) -> 16.235433 | G33: =(TREND($D$28:$E$28,$D$26:$E$26,G$11))*(About!$A$60) -> 16.235433 | H33: =(TREND($D$28:$E$28,$D$26:$E$26,H$11))*(About!$A$60) -> 16.235433 | I33: =(TREND($D$28:$E$28,$D$26:$E$26,I$11))*(About!$A$60) -> 16.235433 | J33: =(TREND($D$28:$E$28,$D$26:$E$26,J$11))*(About!$A$60) -> 16.235433 | K33: =(TREND($D$28:$E$28,$D$26:$E$26,K$11))*(About!$A$60) -> 16.235433 | ... M33: =(TREND($D$28:$E$28,$D$26:$E$26,M$11))*(About!$A$60) -> 16.235433 | N33: =(TREND($E$28:$G$28,$E$26:$G$26,N$11))*(About!$A$60) -> 16.235433 | O33: =(TREND($E$28:$G$28,$E$26:$G$26,O$11))*(About!$A$60) -> 16.235433 | P33: =(TREND($E$28:$G$28,$E$26:$G$26,P$11))*(About!$A$60) -> 16.235433 | Q33: =(TREND($E$28:$G$28,$E$26:$G$26,Q$11))*(About!$A$60) -> 16.235433 | R33: =(TREND($E$28:$G$28,$E$26:$G$26,R$11))*(About!$A$60) -> 16.235433 | S33: =(TREND($E$28:$G$28,$E$26:$G$26,S$11))*(About!$A$60) -> 16.235433 | T33: =(TREND($E$28:$G$28,$E$26:$G$26,T$11))*(About!$A$60) -> 16.235433 | U33: =(TREND($E$28:$G$28,$E$26:$G$26,U$11))*(About!$A$60) -> 16.235433 | ... AG33: =(TREND($E$28:$G$28,$E$26:$G$26,AG$11))*(About!$A$60) -> 16.235433
A34: ASHP (2012 USD) | B34: =((B29-D29)/(B26-D26)*(B31-C31))*(About!$A$62)+C34 -> 279.34485 | C34: =(TREND($D$29:$E$29,$D$26:$E$26,C$11))*(About!$A$62) -> 275.0435 | D34: =(TREND($D$29:$E$29,$D$26:$E$26,D$11))*(About!$A$62) -> 271.19875 | E34: =(TREND($D$29:$E$29,$D$26:$E$26,E$11))*(About!$A$62) -> 267.35401 | F34: =(TREND($D$29:$E$29,$D$26:$E$26,F$11))*(About!$A$62) -> 263.50926 | G34: =(TREND($D$29:$E$29,$D$26:$E$26,G$11))*(About!$A$62) -> 259.66452 | H34: =(TREND($D$29:$E$29,$D$26:$E$26,H$11))*(About!$A$62) -> 255.81978 | I34: =(TREND($D$29:$E$29,$D$26:$E$26,I$11))*(About!$A$62) -> 251.97503 | J34: =(TREND($D$29:$E$29,$D$26:$E$26,J$11))*(About!$A$62) -> 248.13029 | ... M34: =(TREND($D$29:$E$29,$D$26:$E$26,M$11))*(About!$A$62) -> 236.59606 | N34: =(TREND($E$29:$G$29,$E$26:$G$26,N$11))*(About!$A$62) -> 232.58907 | O34: =(TREND($E$29:$G$29,$E$26:$G$26,O$11))*(About!$A$62) -> 229.58163 | P34: =(TREND($E$29:$G$29,$E$26:$G$26,P$11))*(About!$A$62) -> 226.5742 | Q34: =(TREND($E$29:$G$29,$E$26:$G$26,Q$11))*(About!$A$62) -> 223.56677 | R34: =(TREND($E$29:$G$29,$E$26:$G$26,R$11))*(About!$A$62) -> 220.55934 | S34: =(TREND($E$29:$G$29,$E$26:$G$26,S$11))*(About!$A$62) -> 217.5519 | T34: =(TREND($E$29:$G$29,$E$26:$G$26,T$11))*(About!$A$62) -> 214.54447 | U34: =(TREND($E$29:$G$29,$E$26:$G$26,U$11))*(About!$A$62) -> 211.53704 | ... AG34: =(TREND($E$29:$G$29,$E$26:$G$26,AG$11))*(About!$A$62) -> 175.44785
A36: Annualized Incremental Capital Cost per BTU Shifted | B36: 2019 | C36: 2020 | D36: 2021 | E36: 2022 | F36: 2023 | G36: 2024 | H36: 2025 | I36: 2026 | J36: 2027 | K36: 2028 | L36: 2029 | M36: 2030 | N36: 2031 | O36: 2032 | P36: 2033 | Q36: 2034 | R36: 2035 | S36: 2036 | T36: 2037 | U36: 2038 | V36: 2039 | W36: 2040 | X36: 2041 | Y36: 2042 | Z36: 2043 | AA36: 2044 | AB36: 2045 | AC36: 2046 | AD36: 2047 | AE36: 2048 | AF36: 2049 | AG36: 2050
A37: natural gas | B37: =(B34-B32)/(8760*10^3*$B$23) -> 0.00011922643 | C37: =(C34-C32)/(8760*10^3*$B$23) -> 0.00011726234 | D37: =(D34-D32)/(8760*10^3*$B$23) -> 0.00011550675 | E37: =(E34-E32)/(8760*10^3*$B$23) -> 0.00011375116 | F37: =(F34-F32)/(8760*10^3*$B$23) -> 0.00011199557 | G37: =(G34-G32)/(8760*10^3*$B$23) -> 0.00011023998 | H37: =(H34-H32)/(8760*10^3*$B$23) -> 0.00010848438 | I37: =(I34-I32)/(8760*10^3*$B$23) -> 0.00010672879 | ... AG37: =(AG34-AG32)/(8760*10^3*$B$23) -> 7.1784875e-05
A38: oil | B38: =(B34-B33)/(8760*10^3*$B$23) -> 0.00012014129 | C38: =(C34-C33)/(8760*10^3*$B$23) -> 0.0001181772 | D38: =(D34-D33)/(8760*10^3*$B$23) -> 0.00011642161 | E38: =(E34-E33)/(8760*10^3*$B$23) -> 0.00011466602 | F38: =(F34-F33)/(8760*10^3*$B$23) -> 0.00011291043 | G38: =(G34-G33)/(8760*10^3*$B$23) -> 0.00011115483 | H38: =(H34-H33)/(8760*10^3*$B$23) -> 0.00010939924 | I38: =(I34-I33)/(8760*10^3*$B$23) -> 0.00010764365 | ... AG38: =(AG34-AG33)/(8760*10^3*$B$23) -> 7.2699734e-05

Sheet IESS Residential
A1: Household Annual Fuel Consumption
A3: Assumption | B3: Per hh consumption Annual | C3: Unit | D3: Life Cycle( Years)
A4: LPG | B4: 1.4101389e-06 | C4: TWh | D4: 15
A5: Electricity | B5: 1.022e-06 | C5: TWh | D5: 10
A6: PNG | B6: 1.6027222e-06 | C6: TWh | D6: 15
A7: Improved Biomass | B7: 1.7506667e-06 | C7: TWh | D7: 3
A8: Coal | B8: 2.1152444e-06 | C8: TWh | D8: 3
A9: Kerosene | B9: 8.2244513e-07 | C9: TWh | D9: 5
A10: Biogas | B10: 1.24375e-06 | C10: TWh | D10: 15
A11: Traditional Biomass | B11: 4.0415556e-06 | C11: TWh | D11: 1
A12: Efficiency of a Traditional Biomass Chulha | D12: 0.13
A14: TWh to BTU | B14: 3412000000000
A17: Infrastructure costs for fuels
A18: Source | B18: Connection costs per unit of cook stove (fuel switching) | E18: Network replacement and O&M cost per year | F18: Lifespan of asset (years) | G18: Cost of Network Augmention/ annum in INR Trillion
B19: High | C19: Point | D19: Low | G19: High | H19: Point | I19: Low
A20: LPG | B20: 1.6e-09 | C20: 1.4e-09 | D20: 1.2e-09 | E20: 0.06 | F20: 50 | G20: 1.28e-10 | H20: 1.12e-10 | I20: 9.6e-11
A21: Electricity | B21: 3.5e-09 | C21: 3e-09 | D21: 1.5e-09 | E21: 0.08 | F21: 20 | G21: 4.55e-10 | H21: 3.9e-10 | I21: 1.95e-10
A22: PNG | B22: 6e-09 | C22: 4.5e-09 | D22: 3e-09 | E22: 0.1 | F22: 15 | G22: 1e-09 | H22: 7.5e-10 | I22: 5e-10
A23: Improved Biomass (only cookstove cost ) | B23: 0 | C23: 0 | D23: 0 | E23: 0 | F23: N/A | G23: 0 | H23: 0 | I23: 0
A24: Traditional Biomass | B24: 0 | C24: 0 | D24: 0 | E24: 0 | F24: N/A | G24: 0 | H24: 0 | I24: 0
A25: Coal | B25: 0 | C25: 0 | D25: 0 | E25: 0 | F25: N/A | G25: 0 | H25: 0 | I25: 0
A26: Kerosene | B26: 0 | C26: 0 | D26: 0 | E26: 0 | F26: N/A | G26: 0 | H26: 0 | I26: 0
A27: Biogas | B27: 2.5e-08 | C27: 2.2e-08 | D27: 1.7e-08 | E27: 0.12 | F27: 10 | G27: 5.5e-09 | H27: 4.84e-09 | I27: 3.74e-09
A29: 1 | B29: LPG
B30: Capital cost per unit of Cookstove | N30: INR Trillion/unit of cookstove
D32: Delta | F32: 2012 | G32: 2013 | H32: 2014 | I32: 2015 | J32: 2016 | K32: 2017 | L32: 2018 | M32: 2020 | N32: 2021 | O32: 2022 | P32: 2023 | Q32: 2024 | R32: 2025 | S32: 2026 | T32: 2027 | U32: 2028 | V32: 2029 | W32: 2030 | X32: 2031 | Y32: 2032 | Z32: 2033 | AA32: 2034 | AB32: 2035 | AC32: 2036 | AD32: 2037 | AE32: 2038 | AF32: 2039 | AG32: 2040 | AH32: 2041 | AI32: 2042 | AJ32: 2043 | AK32: 2044 | AL32: 2045 | AM32: 2046 | AN32: 2047 | AO32: 2048 | AP32: 2049 | AQ32: 2050 | AR32: 2051 | AS32: 2052 | AT32: 2053 | AU32: 2054 | AV32: 2055 | AW32: 2056 | AX32: 2057 | AY32: 2058 | AZ32: 2059 | BA32: 2060 | BB32: 2061 | BC32: 2062 | BD32: 2063 | BE32: 2064 | BF32: 2065 | BG32: 2066 | BH32: 2067 | BI32: 2068 | BJ32: 2069 | BK32: 2070
B33: High estimate | F33: 2.75e-09 | G33: 2.79204e-09 | H33: 2.8340801e-09 | I33: 2.8761201e-09 | J33: 2.9181601e-09 | K33: 2.9602002e-09 | L33: 3.0022402e-09 | M33: 3.0442802e-09 | N33: 3.0863203e-09 | O33: 3.1283603e-09 | P33: 3.1704003e-09 | Q33: 3.2124403e-09 | R33: 3.2544804e-09 | S33: 3.2965204e-09 | T33: 3.3385604e-09 | U33: 3.3806005e-09 | V33: 3.4226405e-09 | W33: 3.4646805e-09 | X33: 3.5067206e-09 | Y33: 3.5487606e-09 | Z33: 3.5908006e-09 | AA33: 3.6328407e-09 | AB33: 3.6748807e-09 | AC33: 3.7169207e-09 | AD33: 3.7589608e-09 | AE33: 3.8010008e-09 | AF33: 3.8430408e-09 | AG33: 3.8850809e-09 | AH33: 3.9271209e-09 | AI33: 3.9691609e-09 | AJ33: 4.011201e-09 | AK33: 4.053241e-09 | AL33: 4.095281e-09 | AM33: 4.137321e-09 | AN33: 4.1793611e-09 | AO33: 4.2214011e-09
B34: Point estimate | F34: 2.75e-09 | G34: 2.754349e-09 | H34: 2.7586979e-09 | I34: 2.7630469e-09 | J34: 2.7673958e-09 | K34: 2.7717448e-09 | L34: 2.7760937e-09 | M34: 0 | N34: 0 | O34: 0 | P34: -0.238 | Q34: 0.1105 | R34: 0.459 | S34: 0.8075 | T34: 1.156 | U34: 1.1598 | V34: 1.1636 | W34: 1.1674 | X34: 1.1712 | Y34: 1.175 | Z34: 1.1764 | AA34: 1.1778 | AB34: 1.1792 | AC34: 1.1806 | AD34: 1.168 | AE34: 1.16 | AF34: 1.12064 | AG34: 1.045376 | AH34: 0.952115 | AI34: 1.128 | AJ34: 1.0616 | AK34: 0.9952 | AL34: 0.9288 | AM34: 0.8624 | AN34: 0.796 | AO34: 0.569333 | AP34: 0.342667 | AQ34: 0.116 | AR34: 0.1092 | AS34: 0.1024 | AT34: 0.0956 | AU34: 0.0888 | AV34: 0.082 | AW34: 0.0514 | AX34: 0.0208 | AY34: -0.0098 | AZ34: -0.0404 | BA34: -0.071 | BB34: -0.102 | BC34: -0.133 | BD34: -0.164 | BE34: -0.195 | BF34: -0.226 | BG34: -0.257 | BH34: -0.288 | BI34: -0.319 | BJ34: -0.35 | BK34: -0.381
B35: Low estimate | F35: 2.75e-09 | G35: 2.7166579e-09 | H35: 2.6833157e-09 | I35: 2.6499736e-09 | J35: 2.6166315e-09 | K35: 2.5832893e-09 | L35: 2.5499472e-09 | M35: 2.5166051e-09 | N35: 2.483263e-09 | O35: 2.4499208e-09 | P35: 2.4165787e-09 | Q35: 2.3832366e-09 | R35: 2.3498944e-09 | S35: 2.3165523e-09 | T35: 2.2832102e-09 | U35: 2.249868e-09 | V35: 2.2165259e-09 | W35: 2.1831838e-09 | X35: 2.1498416e-09 | Y35: 2.1164995e-09 | Z35: 2.0831574e-09 | AA35: 2.0498153e-09 | AB35: 2.0164731e-09 | AC35: 1.983131e-09 | AD35: 1.9497889e-09 | AE35: 1.9164467e-09 | AF35: 1.8831046e-09 | AG35: 1.8497625e-09 | AH35: 1.8164203e-09 | AI35: 1.7830782e-09 | AJ35: 1.7497361e-09 | AK35: 1.7163939e-09 | AL35: 1.6830518e-09 | AM35: 1.6497097e-09 | AN35: 1.6163675e-09 | AO35: 1.5830254e-09
B37: Operating cost per unit of Cookstove | N37: INR Trillion/unit of cookstove
D39: Delta | F39: 2012 | G39: 2013 | H39: 2014 | I39: 2015 | J39: 2016 | K39: 2017 | L39: 2018 | M39: 2019 | N39: 2020 | O39: 2021 | P39: 2022 | Q39: 2023 | R39: 2024 | S39: 2025 | T39: 2026 | U39: 2027 | V39: 2028 | W39: 2029 | X39: 2030 | Y39: 2031 | Z39: 2032 | AA39: 2033 | AB39: 2034 | AC39: 2035 | AD39: 2036 | AE39: 2037 | AF39: 2038 | AG39: 2039 | AH39: 2040 | AI39: 2041 | AJ39: 2042 | AK39: 2043 | AL39: 2044 | AM39: 2045 | AN39: 2046 | AO39: 2047
B40: High estimate | F40: 2.75e-11 | G40: 2.79204e-11 | H40: 2.8340801e-11 | I40: 2.8761201e-11 | J40: 2.9181601e-11 | K40: 2.9602002e-11 | L40: 3.0022402e-11 | M40: 3.0442802e-11 | N40: 3.0863203e-11 | O40: 3.1283603e-11 | P40: 3.1704003e-11 | Q40: 3.2124403e-11 | R40: 3.2544804e-11 | S40: 3.2965204e-11 | T40: 3.3385604e-11 | U40: 3.3806005e-11 | V40: 3.4226405e-11 | W40: 3.4646805e-11 | X40: 3.5067206e-11 | Y40: 3.5487606e-11 | Z40: 3.5908006e-11 | AA40: 3.6328407e-11 | AB40: 3.6748807e-11 | AC40: 3.7169207e-11 | AD40: 3.7589608e-11 | AE40: 3.8010008e-11 | AF40: 3.8430408e-11 | AG40: 3.8850809e-11 | AH40: 3.9271209e-11 | AI40: 3.9691609e-11 | AJ40: 4.011201e-11 | AK40: 4.053241e-11 | AL40: 4.095281e-11 | AM40: 4.137321e-11 | AN40: 4.1793611e-11 | AO40: 4.2214011e-11
B41: Point estimate | F41: 2.75e-11 | G41: 2.754349e-11 | H41: 2.7586979e-11 | I41: 2.7630469e-11 | J41: 2.7673958e-11 | K41: 2.7717448e-11 | L41: 2.7760937e-11 | M41: 2.7804427e-11 | N41: 2.7847916e-11 | O41: 2.7891406e-11 | P41: 2.7934895e-11 | Q41: 2.7978385e-11 | R41: 2.8021874e-11 | S41: 2.8065364e-11 | T41: 2.8108853e-11 | U41: 2.8152343e-11 | V41: 2.8195832e-11 | W41: 2.8239322e-11 | X41: 2.8282811e-11 | Y41: 2.8326301e-11 | Z41: 2.836979e-11 | AA41: 2.841328e-11 | AB41: 2.8456769e-11 | AC41: 2.8500259e-11 | AD41: 2.8543748e-11 | AE41: 2.8587238e-11 | AF41: 2.8630727e-11 | AG41: 2.8674217e-11 | AH41: 2.8717706e-11 | AI41: 2.8761196e-11 | AJ41: 2.8804685e-11 | AK41: 2.8848175e-11 | AL41: 2.8891664e-11 | AM41: 2.8935154e-11 | AN41: 2.8978643e-11 | AO41: 2.9022133e-11
B42: Low estimate | F42: 2.75e-11 | G42: 2.7166579e-11 | H42: 2.6833157e-11 | I42: 2.6499736e-11 | J42: 2.6166315e-11 | K42: 2.5832893e-11 | L42: 2.5499472e-11 | M42: 2.5166051e-11 | N42: 2.483263e-11 | O42: 2.4499208e-11 | P42: 2.4165787e-11 | Q42: 2.3832366e-11 | R42: 2.3498944e-11 | S42: 2.3165523e-11 | T42: 2.2832102e-11 | U42: 2.249868e-11 | V42: 2.2165259e-11 | W42: 2.1831838e-11 | X42: 2.1498416e-11 | Y42: 2.1164995e-11 | Z42: 2.0831574e-11 | AA42: 2.0498153e-11 | AB42: 2.0164731e-11 | AC42: 1.983131e-11 | AD42: 1.9497889e-11 | AE42: 1.9164467e-11 | AF42: 1.8831046e-11 | AG42: 1.8497625e-11 | AH42: 1.8164203e-11 | AI42: 1.7830782e-11 | AJ42: 1.7497361e-11 | AK42: 1.7163939e-11 | AL42: 1.6830518e-11 | AM42: 1.6497097e-11 | AN42: 1.6163675e-11 | AO42: 1.5830254e-11
B44: Infrastructure cost per unit of Cookstove | N44: INR Trillion/unit of cookstove
D46: Delta | F46: 2012 | G46: 2013 | H46: 2014 | I46: 2015 | J46: 2016 | K46: 2017 | L46: 2018 | M46: 2019 | N46: 2020 | O46: 2021 | P46: 2022 | Q46: 2023 | R46: 2024 | S46: 2025 | T46: 2026 | U46: 2027 | V46: 2028 | W46: 2029 | X46: 2030 | Y46: 2031 | Z46: 2032 | AA46: 2033 | AB46: 2034 | AC46: 2035 | AD46: 2036 | AE46: 2037 | AF46: 2038 | AG46: 2039 | AH46: 2040 | AI46: 2041 | AJ46: 2042 | AK46: 2043 | AL46: 2044 | AM46: 2045 | AN46: 2046 | AO46: 2047
B47: High estimate | F47: 1.28e-10 | G47: 1.28e-10 | H47: 1.28e-10 | I47: 1.28e-10 | J47: 1.28e-10 | K47: 1.28e-10 | L47: 1.28e-10 | M47: 1.28e-10 | N47: 1.28e-10 | O47: 1.28e-10 | P47: 1.28e-10 | Q47: 1.28e-10 | R47: 1.28e-10 | S47: 1.28e-10 | T47: 1.28e-10 | U47: 1.28e-10 | V47: 1.28e-10 | W47: 1.28e-10 | X47: 1.28e-10 | Y47: 1.28e-10 | Z47: 1.28e-10 | AA47: 1.28e-10 | AB47: 1.28e-10 | AC47: 1.28e-10 | AD47: 1.28e-10 | AE47: 1.28e-10 | AF47: 1.28e-10 | AG47: 1.28e-10 | AH47: 1.28e-10 | AI47: 1.28e-10 | AJ47: 1.28e-10 | AK47: 1.28e-10 | AL47: 1.28e-10 | AM47: 1.28e-10 | AN47: 1.28e-10 | AO47: 1.28e-10
B48: Point estimate | F48: 1.12e-10 | G48: 1.12e-10 | H48: 1.12e-10 | I48: 1.12e-10 | J48: 1.12e-10 | K48: 1.12e-10 | L48: 1.12e-10 | M48: 1.12e-10 | N48: 1.12e-10 | O48: 1.12e-10 | P48: 1.12e-10 | Q48: 1.12e-10 | R48: 1.12e-10 | S48: 1.12e-10 | T48: 1.12e-10 | U48: 1.12e-10 | V48: 1.12e-10 | W48: 1.12e-10 | X48: 1.12e-10 | Y48: 1.12e-10 | Z48: 1.12e-10 | AA48: 1.12e-10 | AB48: 1.12e-10 | AC48: 1.12e-10 | AD48: 1.12e-10 | AE48: 1.12e-10 | AF48: 1.12e-10 | AG48: 1.12e-10 | AH48: 1.12e-10 | AI48: 1.12e-10 | AJ48: 1.12e-10 | AK48: 1.12e-10 | AL48: 1.12e-10 | AM48: 1.12e-10 | AN48: 1.12e-10 | AO48: 1.12e-10
B49: Low estimate | F49: 9.6e-11 | G49: 9.6e-11 | H49: 9.6e-11 | I49: 9.6e-11 | J49: 9.6e-11 | K49: 9.6e-11 | L49: 9.6e-11 | M49: 9.6e-11 | N49: 9.6e-11 | O49: 9.6e-11 | P49: 9.6e-11 | Q49: 9.6e-11 | R49: 9.6e-11 | S49: 9.6e-11 | T49: 9.6e-11 | U49: 9.6e-11 | V49: 9.6e-11 | W49: 9.6e-11 | X49: 9.6e-11 | Y49: 9.6e-11 | Z49: 9.6e-11 | AA49: 9.6e-11 | AB49: 9.6e-11 | AC49: 9.6e-11 | AD49: 9.6e-11 | AE49: 9.6e-11 | AF49: 9.6e-11 | AG49: 9.6e-11 | AH49: 9.6e-11 | AI49: 9.6e-11 | AJ49: 9.6e-11 | AK49: 9.6e-11 | AL49: 9.6e-11 | AM49: 9.6e-11 | AN49: 9.6e-11 | AO49: 9.6e-11
A51: 3 | B51: Electric | F51: 1.0040161e-12
B52: Capital cost per unit of Cookstove | N52: INR Trillion/unit of cookstove
D54: Delta | F54: 2012 | G54: 2013 | H54: 2014 | I54: 2015 | J54: 2016 | K54: 2017 | L54: 2018 | M54: 2020 | N54: 2021 | O54: 2022 | P54: 2023 | Q54: 2024 | R54: 2025 | S54: 2026 | T54: 2027 | U54: 2028 | V54: 2029 | W54: 2030 | X54: 2031 | Y54: 2032 | Z54: 2033 | AA54: 2034 | AB54: 2035 | AC54: 2036 | AD54: 2037 | AE54: 2038 | AF54: 2039 | AG54: 2040 | AH54: 2041 | AI54: 2042 | AJ54: 2043 | AK54: 2044 | AL54: 2045 | AM54: 2046 | AN54: 2047 | AO54: 2048 | AP54: 2049 | AQ54: 2050 | AR54: 2051 | AS54: 2052 | AT54: 2053 | AU54: 2054 | AV54: 2055 | AW54: 2056 | AX54: 2057 | AY54: 2058 | AZ54: 2059 | BA54: 2060 | BB54: 2061 | BC54: 2062 | BD54: 2063 | BE54: 2064 | BF54: 2065 | BG54: 2066 | BH54: 2067 | BI54: 2068 | BJ54: 2069 | BK54: 2070
B55: Low estimate | F55: 2.95e-09 | G55: 2.9230047e-09 | H55: 2.8960095e-09 | I55: 2.8690142e-09 | J55: 2.8420189e-09 | K55: 2.8150236e-09 | L55: 2.7880284e-09 | M55: 2.7610331e-09 | N55: 2.7340378e-09 | O55: 2.7070426e-09 | P55: 2.6800473e-09 | Q55: 2.653052e-09 | R55: 2.6260568e-09 | S55: 2.5990615e-09 | T55: 2.5720662e-09 | U55: 2.5450709e-09 | V55: 2.5180757e-09 | W55: 2.4910804e-09 | X55: 2.4640851e-09 | Y55: 2.4370899e-09 | Z55: 2.4100946e-09 | AA55: 2.3830993e-09 | AB55: 2.356104e-09 | AC55: 2.3291088e-09 | AD55: 2.3021135e-09 | AE55: 2.2751182e-09 | AF55: 2.248123e-09 | AG55: 2.2211277e-09 | AH55: 2.1941324e-09 | AI55: 2.1671372e-09 | AJ55: 2.1401419e-09 | AK55: 2.1131466e-09 | AL55: 2.0861513e-09 | AM55: 2.0591561e-09 | AN55: 2.0321608e-09 | AO55: 2.0051655e-09
B56: Point estimate | F56: 2.95e-09 | G56: 2.9546652e-09 | H56: 2.9593305e-09 | I56: 2.9639957e-09 | J56: 2.968661e-09 | K56: 2.9733262e-09 | L56: 2.9779914e-09 | M56: 0 | N56: 0 | O56: 0 | P56: 0.136 | Q56: 0.153 | R56: 0.17 | S56: 0.187 | T56: 0.204 | U56: 0.242 | V56: 0.28 | W56: 0.318 | X56: 0.356 | Y56: 0.394 | Z56: 0.42 | AA56: 0.446 | AB56: 0.472 | AC56: 0.498 | AD56: 0.524 | AE56: 0.5528 | AF56: 0.5816 | AG56: 0.6104 | AH56: 0.6392 | AI56: 0.668 | AJ56: 0.7092 | AK56: 0.7504 | AL56: 0.7916 | AM56: 0.8328 | AN56: 0.874 | AO56: 0.762667 | AP56: 0.651333 | AQ56: 0.54 | AR56: 0.6292 | AS56: 0.7184 | AT56: 0.8076 | AU56: 0.8968 | AV56: 0.986 | AW56: 1.0126 | AX56: 1.0392 | AY56: 1.0658 | AZ56: 1.0924 | BA56: 1.119 | BB56: 1.146 | BC56: 1.173 | BD56: 1.2 | BE56: 1.227 | BF56: 1.254 | BG56: 1.9538 | BH56: 2.6536 | BI56: 3.3534 | BJ56: 4.0532 | BK56: 4.753
B57: High estimate | F57: 2.95e-09 | G57: 2.9863257e-09 | H57: 3.0226515e-09 | I57: 3.0589772e-09 | J57: 3.095303e-09 | K57: 3.1316287e-09 | L57: 3.1679545e-09 | M57: 3.2042802e-09 | N57: 3.240606e-09 | O57: 3.2769317e-09 | P57: 3.3132575e-09 | Q57: 3.3495832e-09 | R57: 3.385909e-09 | S57: 3.4222347e-09 | T57: 3.4585604e-09 | U57: 3.4948862e-09 | V57: 3.5312119e-09 | W57: 3.5675377e-09 | X57: 3.6038634e-09 | Y57: 3.6401892e-09 | Z57: 3.6765149e-09 | AA57: 3.7128407e-09 | AB57: 3.7491664e-09 | AC57: 3.7854922e-09 | AD57: 3.8218179e-09 | AE57: 3.8581437e-09 | AF57: 3.8944694e-09 | AG57: 3.9307951e-09 | AH57: 3.9671209e-09 | AI57: 4.0034466e-09 | AJ57: 4.0397724e-09 | AK57: 4.0760981e-09 | AL57: 4.1124239e-09 | AM57: 4.1487496e-09 | AN57: 4.1850754e-09 | AO57: 4.2214011e-09
B59: Operating cost per unit of Cookstove | N59: INR Trillion/unit of cookstove
D61: Delta | F61: 2012 | G61: 2013 | H61: 2014 | I61: 2015 | J61: 2016 | K61: 2017 | L61: 2018 | M61: 2019 | N61: 2020 | O61: 2021 | P61: 2022 | Q61: 2023 | R61: 2024 | S61: 2025 | T61: 2026 | U61: 2027 | V61: 2028 | W61: 2029 | X61: 2030 | Y61: 2031 | Z61: 2032 | AA61: 2033 | AB61: 2034 | AC61: 2035 | AD61: 2036 | AE61: 2037 | AF61: 2038 | AG61: 2039 | AH61: 2040 | AI61: 2041 | AJ61: 2042 | AK61: 2043 | AL61: 2044 | AM61: 2045 | AN61: 2046 | AO61: 2047
B62: Low estimate | F62: 1.475e-11 | G62: 1.4615024e-11 | H62: 1.4480047e-11 | I62: 1.4345071e-11 | J62: 1.4210095e-11 | K62: 1.4075118e-11 | L62: 1.3940142e-11 | M62: 1.3805166e-11 | N62: 1.3670189e-11 | O62: 1.3535213e-11 | P62: 1.3400236e-11 | Q62: 1.326526e-11 | R62: 1.3130284e-11 | S62: 1.2995307e-11 | T62: 1.2860331e-11 | U62: 1.2725355e-11 | V62: 1.2590378e-11 | W62: 1.2455402e-11 | X62: 1.2320426e-11 | Y62: 1.2185449e-11 | Z62: 1.2050473e-11 | AA62: 1.1915497e-11 | AB62: 1.178052e-11 | AC62: 1.1645544e-11 | AD62: 1.1510568e-11 | AE62: 1.1375591e-11 | AF62: 1.1240615e-11 | AG62: 1.1105638e-11 | AH62: 1.0970662e-11 | AI62: 1.0835686e-11 | AJ62: 1.0700709e-11 | AK62: 1.0565733e-11 | AL62: 1.0430757e-11 | AM62: 1.029578e-11 | AN62: 1.0160804e-11 | AO62: 1.0025828e-11
B63: Point estimate | F63: 1.475e-11 | G63: 1.4773326e-11 | H63: 1.4796652e-11 | I63: 1.4819979e-11 | J63: 1.4843305e-11 | K63: 1.4866631e-11 | L63: 1.4889957e-11 | M63: 1.4913283e-11 | N63: 1.493661e-11 | O63: 1.4959936e-11 | P63: 1.4983262e-11 | Q63: 1.5006588e-11 | R63: 1.5029914e-11 | S63: 1.505324e-11 | T63: 1.5076567e-11 | U63: 1.5099893e-11 | V63: 1.5123219e-11 | W63: 1.5146545e-11 | X63: 1.5169871e-11 | Y63: 1.5193198e-11 | Z63: 1.5216524e-11 | AA63: 1.523985e-11 | AB63: 1.5263176e-11 | AC63: 1.5286502e-11 | AD63: 1.5309829e-11 | AE63: 1.5333155e-11 | AF63: 1.5356481e-11 | AG63: 1.5379807e-11 | AH63: 1.5403133e-11 | AI63: 1.5426459e-11 | AJ63: 1.5449786e-11 | AK63: 1.5473112e-11 | AL63: 1.5496438e-11 | AM63: 1.5519764e-11 | AN63: 1.554309e-11 | AO63: 1.5566417e-11
B64: High estimate | F64: 1.475e-11 | G64: 1.4931629e-11 | H64: 1.5113257e-11 | I64: 1.5294886e-11 | J64: 1.5476515e-11 | K64: 1.5658144e-11 | L64: 1.5839772e-11 | M64: 1.6021401e-11 | N64: 1.620303e-11 | O64: 1.6384659e-11 | P64: 1.6566287e-11 | Q64: 1.6747916e-11 | R64: 1.6929545e-11 | S64: 1.7111173e-11 | T64: 1.7292802e-11 | U64: 1.7474431e-11 | V64: 1.765606e-11 | W64: 1.7837688e-11 | X64: 1.8019317e-11 | Y64: 1.8200946e-11 | Z64: 1.8382575e-11 | AA64: 1.8564203e-11 | AB64: 1.8745832e-11 | AC64: 1.8927461e-11 | AD64: 1.910909e-11 | AE64: 1.9290718e-11 | AF64: 1.9472347e-11 | AG64: 1.9653976e-11 | AH64: 1.9835604e-11 | AI64: 2.0017233e-11 | AJ64: 2.0198862e-11 | AK64: 2.0380491e-11 | AL64: 2.0562119e-11 | AM64: 2.0743748e-11 | AN64: 2.0925377e-11 | AO64: 2.1107006e-11
B66: Infrastructure cost per unit of Cookstove | N66: INR Trillion/unit of cookstove
D68: Delta | F68: 2012 | G68: 2013 | H68: 2014 | I68: 2015 | J68: 2016 | K68: 2017 | L68: 2018 | M68: 2019 | N68: 2020 | O68: 2021 | P68: 2022 | Q68: 2023 | R68: 2024 | S68: 2025 | T68: 2026 | U68: 2027 | V68: 2028 | W68: 2029 | X68: 2030 | Y68: 2031 | Z68: 2032 | AA68: 2033 | AB68: 2034 | AC68: 2035 | AD68: 2036 | AE68: 2037 | AF68: 2038 | AG68: 2039 | AH68: 2040 | AI68: 2041 | AJ68: 2042 | AK68: 2043 | AL68: 2044 | AM68: 2045 | AN68: 2046 | AO68: 2047
B69: High estimate | F69: 4.55e-10 | G69: 4.55e-10 | H69: 4.55e-10 | I69: 4.55e-10 | J69: 4.55e-10 | K69: 4.55e-10 | L69: 4.55e-10 | M69: 4.55e-10 | N69: 4.55e-10 | O69: 4.55e-10 | P69: 4.55e-10 | Q69: 4.55e-10 | R69: 4.55e-10 | S69: 4.55e-10 | T69: 4.55e-10 | U69: 4.55e-10 | V69: 4.55e-10 | W69: 4.55e-10 | X69: 4.55e-10 | Y69: 4.55e-10 | Z69: 4.55e-10 | AA69: 4.55e-10 | AB69: 4.55e-10 | AC69: 4.55e-10 | AD69: 4.55e-10 | AE69: 4.55e-10 | AF69: 4.55e-10 | AG69: 4.55e-10 | AH69: 4.55e-10 | AI69: 4.55e-10 | AJ69: 4.55e-10 | AK69: 4.55e-10 | AL69: 4.55e-10 | AM69: 4.55e-10 | AN69: 4.55e-10 | AO69: 4.55e-10
B70: Point estimate | F70: 3.9e-10 | G70: 3.9e-10 | H70: 3.9e-10 | I70: 3.9e-10 | J70: 3.9e-10 | K70: 3.9e-10 | L70: 3.9e-10 | M70: 3.9e-10 | N70: 3.9e-10 | O70: 3.9e-10 | P70: 3.9e-10 | Q70: 3.9e-10 | R70: 3.9e-10 | S70: 3.9e-10 | T70: 3.9e-10 | U70: 3.9e-10 | V70: 3.9e-10 | W70: 3.9e-10 | X70: 3.9e-10 | Y70: 3.9e-10 | Z70: 3.9e-10 | AA70: 3.9e-10 | AB70: 3.9e-10 | AC70: 3.9e-10 | AD70: 3.9e-10 | AE70: 3.9e-10 | AF70: 3.9e-10 | AG70: 3.9e-10 | AH70: 3.9e-10 | AI70: 3.9e-10 | AJ70: 3.9e-10 | AK70: 3.9e-10 | AL70: 3.9e-10 | AM70: 3.9e-10 | AN70: 3.9e-10 | AO70: 3.9e-10
B71: Low estimate | F71: 1.95e-10 | G71: 1.95e-10 | H71: 1.95e-10 | I71: 1.95e-10 | J71: 1.95e-10 | K71: 1.95e-10 | L71: 1.95e-10 | M71: 1.95e-10 | N71: 1.95e-10 | O71: 1.95e-10 | P71: 1.95e-10 | Q71: 1.95e-10 | R71: 1.95e-10 | S71: 1.95e-10 | T71: 1.95e-10 | U71: 1.95e-10 | V71: 1.95e-10 | W71: 1.95e-10 | X71: 1.95e-10 | Y71: 1.95e-10 | Z71: 1.95e-10 | AA71: 1.95e-10 | AB71: 1.95e-10 | AC71: 1.95e-10 | AD71: 1.95e-10 | AE71: 1.95e-10 | AF71: 1.95e-10 | AG71: 1.95e-10 | AH71: 1.95e-10 | AI71: 1.95e-10 | AJ71: 1.95e-10 | AK71: 1.95e-10 | AL71: 1.95e-10 | AM71: 1.95e-10 | AN71: 1.95e-10 | AO71: 1.95e-10
A73: 8 | B73: Traditional Biomass Cookstove | F73: 1.0040161e-12
B74: Capital cost per unit of Cookstove | N74: INR Trillion/unit of cookstove
D76: Delta | F76: 2012 | G76: 2013 | H76: 2014 | I76: 2015 | J76: 2016 | K76: 2017 | L76: 2018 | M76: 2019 | N76: 2020 | O76: 2021 | P76: 2022 | Q76: 2023 | R76: 2024 | S76: 2025 | T76: 2026 | U76: 2027 | V76: 2028 | W76: 2029 | X76: 2030 | Y76: 2031 | Z76: 2032 | AA76: 2033 | AB76: 2034 | AC76: 2035 | AD76: 2036 | AE76: 2037 | AF76: 2038 | AG76: 2039 | AH76: 2040 | AI76: 2041 | AJ76: 2042 | AK76: 2043 | AL76: 2044 | AM76: 2045 | AN76: 2046 | AO76: 2047 | AP76: 2048 | AQ76: 2049 | AR76: 2050 | AS76: 2051 | AT76: 2052 | AU76: 2053 | AV76: 2054 | AW76: 2055 | AX76: 2056 | AY76: 2057 | AZ76: 2058 | BA76: 2059 | BB76: 2060 | BC76: 2061 | BD76: 2062 | BE76: 2063 | BF76: 2064 | BG76: 2065 | BH76: 2066 | BI76: 2067 | BJ76: 2068 | BK76: 2069 | BL76: 2070
B77: High estimate | F77: 6.5e-10 | G77: 6.9430885e-10 | H77: 7.386177e-10 | I77: 7.8292655e-10 | J77: 8.2723539e-10 | K77: 8.7154424e-10 | L77: 9.1585309e-10 | M77: 9.6016194e-10 | N77: 1.0044708e-09 | O77: 1.0487796e-09 | P77: 1.0930885e-09 | Q77: 1.1373973e-09 | R77: 1.1817062e-09 | S77: 1.226015e-09 | T77: 1.2703239e-09 | U77: 1.3146327e-09 | V77: 1.3589416e-09 | W77: 1.4032504e-09 | X77: 1.4475593e-09 | Y77: 1.4918681e-09 | Z77: 1.536177e-09 | AA77: 1.5804858e-09 | AB77: 1.6247947e-09 | AC77: 1.6691035e-09 | AD77: 1.7134124e-09 | AE77: 1.7577212e-09 | AF77: 1.8020301e-09 | AG77: 1.8463389e-09 | AH77: 1.8906478e-09 | AI77: 1.9349566e-09 | AJ77: 1.9792655e-09 | AK77: 2.0235743e-09 | AL77: 2.0678832e-09 | AM77: 2.112192e-09 | AN77: 2.1565009e-09 | AO77: 2.2008097e-09
B78: Point estimate | F78: 6.5e-10 | G78: 6.6660451e-10 | H78: 6.8320901e-10 | I78: 6.9981352e-10 | J78: 7.1641802e-10 | K78: 7.3302253e-10 | L78: 7.4962703e-10 | M78: 7.6623154e-10 | N78: 0 | O78: 0 | P78: 0 | Q78: 0.011 | R78: 0.0115 | S78: 0.012 | T78: 0.0125 | U78: 0.013 | V78: 0.0152 | W78: 0.0174 | X78: 0.0196 | Y78: 0.0218 | Z78: 0.024 | AA78: 0.0246 | AB78: 0.0252 | AC78: 0.0258 | AD78: 0.0264 | AE78: 0.027 | AF78: 0.027 | AG78: 0.027 | AH78: 0.027 | AI78: 0.027 | AJ78: 0.027 | AK78: 0.027 | AL78: 0.027 | AM78: 0.027 | AN78: 0.027 | AO78: 0.027 | AP78: 0.022 | AQ78: 0.017 | AR78: 0.012 | AS78: 0.0122 | AT78: 0.0124 | AU78: 0.0126 | AV78: 0.0128 | AW78: 0.013 | AX78: 0.0114 | AY78: 0.0098 | AZ78: 0.0082 | BA78: 0.0066 | BB78: 0.005 | BC78: 0.0034 | BD78: 0.0018 | BE78: 0.0002 | BF78: -0.0014 | BG78: -0.003 | BH78: -0.0048 | BI78: -0.0066 | BJ78: -0.0084 | BK78: -0.0102 | BL78: -0.012
B79: Low estimate | F79: 6.5e-10 | G79: 6.3890016e-10 | H79: 6.2780032e-10 | I79: 6.1670049e-10 | J79: 6.0560065e-10 | K79: 5.9450081e-10 | L79: 5.8340097e-10 | M79: 5.7230113e-10 | N79: 5.6120129e-10 | O79: 5.5010146e-10 | P79: 5.3900162e-10 | Q79: 5.2790178e-10 | R79: 5.1680194e-10 | S79: 5.057021e-10 | T79: 4.9460227e-10 | U79: 4.8350243e-10 | V79: 4.7240259e-10 | W79: 4.6130275e-10 | X79: 4.5020291e-10 | Y79: 4.3910307e-10 | Z79: 4.2800324e-10 | AA79: 4.169034e-10 | AB79: 4.0580356e-10 | AC79: 3.9470372e-10 | AD79: 3.8360388e-10 | AE79: 3.7250404e-10 | AF79: 3.6140421e-10 | AG79: 3.5030437e-10 | AH79: 3.3920453e-10 | AI79: 3.2810469e-10 | AJ79: 3.1700485e-10 | AK79: 3.0590502e-10 | AL79: 2.9480518e-10 | AM79: 2.8370534e-10 | AN79: 2.726055e-10 | AO79: 2.6150566e-10
B81: Operating cost per unit of Cookstove | N81: INR Trillion/unit of cookstove
D83: Delta | F83: 2012 | G83: 2013 | H83: 2014 | I83: 2015 | J83: 2016 | K83: 2017 | L83: 2018 | M83: 2019 | N83: 2020 | O83: 2021 | P83: 2022 | Q83: 2023 | R83: 2024 | S83: 2025 | T83: 2026 | U83: 2027 | V83: 2028 | W83: 2029 | X83: 2030 | Y83: 2031 | Z83: 2032 | AA83: 2033 | AB83: 2034 | AC83: 2035 | AD83: 2036 | AE83: 2037 | AF83: 2038 | AG83: 2039 | AH83: 2040 | AI83: 2041 | AJ83: 2042 | AK83: 2043 | AL83: 2044 | AM83: 2045 | AN83: 2046 | AO83: 2047
B84: High estimate | F84: 6.5e-12 | G84: 6.9430885e-12 | H84: 7.386177e-12 | I84: 7.8292655e-12 | J84: 8.2723539e-12 | K84: 8.7154424e-12 | L84: 9.1585309e-12 | M84: 9.6016194e-12 | N84: 1.0044708e-11 | O84: 1.0487796e-11 | P84: 1.0930885e-11 | Q84: 1.1373973e-11 | R84: 1.1817062e-11 | S84: 1.226015e-11 | T84: 1.2703239e-11 | U84: 1.3146327e-11 | V84: 1.3589416e-11 | W84: 1.4032504e-11 | X84: 1.4475593e-11 | Y84: 1.4918681e-11 | Z84: 1.536177e-11 | AA84: 1.5804858e-11 | AB84: 1.6247947e-11 | AC84: 1.6691035e-11 | AD84: 1.7134124e-11 | AE84: 1.7577212e-11 | AF84: 1.8020301e-11 | AG84: 1.8463389e-11 | AH84: 1.8906478e-11 | AI84: 1.9349566e-11 | AJ84: 1.9792655e-11 | AK84: 2.0235743e-11 | AL84: 2.0678832e-11 | AM84: 2.112192e-11 | AN84: 2.1565009e-11 | AO84: 2.2008097e-11
B85: Point estimate | F85: 6.5e-12 | G85: 6.6660451e-12 | H85: 6.8320901e-12 | I85: 6.9981352e-12 | J85: 7.1641802e-12 | K85: 7.3302253e-12 | L85: 7.4962703e-12 | M85: 7.6623154e-12 | N85: 7.8283604e-12 | O85: 7.9944055e-12 | P85: 8.1604505e-12 | Q85: 8.3264956e-12 | R85: 8.4925406e-12 | S85: 8.6585857e-12 | T85: 8.8246307e-12 | U85: 8.9906758e-12 | V85: 9.1567208e-12 | W85: 9.3227659e-12 | X85: 9.4888109e-12 | Y85: 9.654856e-12 | Z85: 9.820901e-12 | AA85: 9.9869461e-12 | AB85: 1.0152991e-11 | AC85: 1.0319036e-11 | AD85: 1.0485081e-11 | AE85: 1.0651126e-11 | AF85: 1.0817171e-11 | AG85: 1.0983216e-11 | AH85: 1.1149261e-11 | AI85: 1.1315307e-11 | AJ85: 1.1481352e-11 | AK85: 1.1647397e-11 | AL85: 1.1813442e-11 | AM85: 1.1979487e-11 | AN85: 1.2145532e-11 | AO85: 1.2311577e-11
B86: Low estimate | F86: 6.5e-12 | G86: 6.3890016e-12 | H86: 6.2780032e-12 | I86: 6.1670049e-12 | J86: 6.0560065e-12 | K86: 5.9450081e-12 | L86: 5.8340097e-12 | M86: 5.7230113e-12 | N86: 5.6120129e-12 | O86: 5.5010146e-12 | P86: 5.3900162e-12 | Q86: 5.2790178e-12 | R86: 5.1680194e-12 | S86: 5.057021e-12 | T86: 4.9460227e-12 | U86: 4.8350243e-12 | V86: 4.7240259e-12 | W86: 4.6130275e-12 | X86: 4.5020291e-12 | Y86: 4.3910307e-12 | Z86: 4.2800324e-12 | AA86: 4.169034e-12 | AB86: 4.0580356e-12 | AC86: 3.9470372e-12 | AD86: 3.8360388e-12 | AE86: 3.7250404e-12 | AF86: 3.6140421e-12 | AG86: 3.5030437e-12 | AH86: 3.3920453e-12 | AI86: 3.2810469e-12 | AJ86: 3.1700485e-12 | AK86: 3.0590502e-12 | AL86: 2.9480518e-12 | AM86: 2.8370534e-12 | AN86: 2.726055e-12 | AO86: 2.6150566e-12
B88: Infrastructure cost per unit of Cookstove | N88: INR Trillion/unit of cookstove
D90: Delta | F90: 2012 | G90: 2013 | H90: 2014 | I90: 2015 | J90: 2016 | K90: 2017 | L90: 2018 | M90: 2019 | N90: 2020 | O90: 2021 | P90: 2022 | Q90: 2023 | R90: 2024 | S90: 2025 | T90: 2026 | U90: 2027 | V90: 2028 | W90: 2029 | X90: 2030 | Y90: 2031 | Z90: 2032 | AA90: 2033 | AB90: 2034 | AC90: 2035 | AD90: 2036 | AE90: 2037 | AF90: 2038 | AG90: 2039 | AH90: 2040 | AI90: 2041 | AJ90: 2042 | AK90: 2043 | AL90: 2044 | AM90: 2045 | AN90: 2046 | AO90: 2047
B91: High estimate | F91: 0 | G91: 0 | H91: 0 | I91: 0 | J91: 0 | K91: 0 | L91: 0 | M91: 0 | N91: 0 | O91: 0 | P91: 0 | Q91: 0 | R91: 0 | S91: 0 | T91: 0 | U91: 0 | V91: 0 | W91: 0 | X91: 0 | Y91: 0 | Z91: 0 | AA91: 0 | AB91: 0 | AC91: 0 | AD91: 0 | AE91: 0 | AF91: 0 | AG91: 0 | AH91: 0 | AI91: 0 | AJ91: 0 | AK91: 0 | AL91: 0 | AM91: 0 | AN91: 0 | AO91: 0
B92: Point estimate | F92: 0 | G92: 0 | H92: 0 | I92: 0 | J92: 0 | K92: 0 | L92: 0 | M92: 0 | N92: 0 | O92: 0 | P92: 0 | Q92: 0 | R92: 0 | S92: 0 | T92: 0 | U92: 0 | V92: 0 | W92: 0 | X92: 0 | Y92: 0 | Z92: 0 | AA92: 0 | AB92: 0 | AC92: 0 | AD92: 0 | AE92: 0 | AF92: 0 | AG92: 0 | AH92: 0 | AI92: 0 | AJ92: 0 | AK92: 0 | AL92: 0 | AM92: 0 | AN92: 0 | AO92: 0
B93: Low estimate | F93: 0 | G93: 0 | H93: 0 | I93: 0 | J93: 0 | K93: 0 | L93: 0 | M93: 0 | N93: 0 | O93: 0 | P93: 0 | Q93: 0 | R93: 0 | S93: 0 | T93: 0 | U93: 0 | V93: 0 | W93: 0 | X93: 0 | Y93: 0 | Z93: 0 | AA93: 0 | AB93: 0 | AC93: 0 | AD93: 0 | AE93: 0 | AF93: 0 | AG93: 0 | AH93: 0 | AI93: 0 | AJ93: 0 | AK93: 0 | AL93: 0 | AM93: 0 | AN93: 0 | AO93: 0

Sheet GDP per capita
A1: Data Source | B1: World Development Indicators
A2: Last Updated Date | B2: 44013
A4: Country Name | B4: Country Code | C4: Indicator Name | D4: Indicator Code | E4: 1960 | F4: 1961 | G4: 1962 | H4: 1963 | I4: 1964 | J4: 1965 | K4: 1966 | L4: 1967 | M4: 1968 | N4: 1969 | O4: 1970 | P4: 1971 | Q4: 1972 | R4: 1973 | S4: 1974 | T4: 1975 | U4: 1976 | V4: 1977 | W4: 1978 | X4: 1979 | Y4: 1980 | Z4: 1981 | AA4: 1982 | AB4: 1983 | AC4: 1984 | AD4: 1985 | AE4: 1986 | AF4: 1987 | AG4: 1988 | AH4: 1989 | AI4: 1990 | AJ4: 1991 | AK4: 1992 | AL4: 1993 | AM4: 1994 | AN4: 1995 | AO4: 1996 | AP4: 1997 | AQ4: 1998 | AR4: 1999 | AS4: 2000 | AT4: 2001 | AU4: 2002 | AV4: 2003 | AW4: 2004 | AX4: 2005 | AY4: 2006 | AZ4: 2007 | BA4: 2008 | BB4: 2009 | BC4: 2010 | BD4: 2011 | BE4: 2012 | BF4: 2013 | BG4: 2014 | BH4: 2015 | BI4: 2016 | BJ4: 2017 | BK4: 2018 | BL4: 2021
A5: Aruba | B5: ABW | C5: GDP per capita (current US$) | D5: NY.GDP.PCAP.CD | AE5: 6472.502 | AF5: 7885.7965 | AG5: 9764.79 | AH5: 11392.456 | AI5: 12307.312 | AJ5: 13496.003 | AK5: 14046.504 | AL5: 14936.827 | AM5: 16241.047 | AN5: 16439.356 | AO5: 16586.068 | AP5: 17927.75 | AQ5: 19078.343 | AR5: 19356.203 | AS5: 20620.701 | AT5: 20669.032 | AU5: 20436.887 | AV5: 20833.762 | AW5: 22569.975 | AX5: 23300.04 | AY5: 24045.272 | AZ5: 25835.133 | BA5: 27084.704 | BB5: 24630.454 | BC5: 23512.603 | BD5: 24985.993 | BE5: 24713.698 | BF5: 26189.436 | BG5: 26647.938 | BH5: 27980.881 | BI5: 28281.35 | BJ5: 29007.693
A6: Afghanistan | B6: AFG | C6: GDP per capita (current US$) | D6: NY.GDP.PCAP.CD | E6: 59.773194 | F6: 59.860874 | G6: 58.458015 | H6: 78.706388 | I6: 82.095231 | J6: 101.1083 | K6: 137.59435 | L6: 160.89859 | M6: 129.10832 | N6: 129.32971 | O6: 156.51894 | P6: 159.56758 | Q6: 135.31731 | R6: 143.14465 | S6: 173.65376 | T6: 186.5109 | U6: 197.44551 | V6: 224.2248 | W6: 247.35411 | X6: 275.7382 | Y6: 272.65529 | Z6: 264.11132 | AU6: 179.42661 | AV6: 190.68381 | AW6: 211.38212 | AX6: 242.03128 | AY6: 263.73369 | AZ6: 359.69324 | BA6: 364.66074 | BB6: 438.07603 | BC6: 543.30304 | BD6: 591.16276 | BE6: 641.87148 | BF6: 637.16552 | BG6: 613.85669 | BH6: 578.46635 | BI6: 547.22811 | BJ6: 556.302 | BK6: 524.16288 | BL6: 502.11549
A7: Angola | B7: AGO | C7: GDP per capita (current US$) | D7: NY.GDP.PCAP.CD | Y7: 710.98165 | Z7: 642.38386 | AA7: 619.96136 | AB7: 623.44058 | AC7: 637.71523 | AD7: 758.23758 | AE7: 685.27009 | AF7: 756.26185 | AG7: 792.30312 | AH7: 890.55414 | AI7: 947.70418 | AJ7: 865.69273 | AK7: 656.36176 | AL7: 441.20067 | AM7: 328.67329 | AN7: 397.17945 | AO7: 522.64381 | AP7: 514.29522 | AQ7: 423.59366 | AR7: 387.78432 | AS7: 556.83632 | AT7: 527.33353 | AU7: 872.49449 | AV7: 982.9609 | AW7: 1255.564 | AX7: 1902.4223 | AY7: 2599.5665 | AZ7: 3121.9956 | BA7: 4080.9414 | BB7: 3122.7808 | BC7: 3587.8838 | BD7: 4615.468 | BE7: 5100.0958 | BF7: 5254.8823 | BG7: 5408.4105 | BH7: 4166.9797 | BI7: 3506.0729 | BJ7: 4095.8129 | BK7: 3289.6467 | BL7: 2973.5912
A8: Albania | B8: ALB | C8: GDP per capita (current US$) | D8: NY.GDP.PCAP.CD | AC8: 639.48474 | AD8: 639.86591 | AE8: 693.87347 | AF8: 674.79338 | AG8: 652.77432 | AH8: 697.9956 | AI8: 617.23044 | AJ8: 336.58699 | AK8: 200.85222 | AL8: 367.27923 | AM8: 586.41634 | AN8: 750.60445 | AO8: 1009.9777 | AP8: 717.38057 | AQ8: 813.79026 | AR8: 1033.2417 | AS8: 1126.6833 | AT8: 1281.6594 | AU8: 1425.1248 | AV8: 1846.1188 | AW8: 2373.5798 | AX8: 2673.7873 | AY8: 2972.7433 | AZ8: 3595.0372 | BA8: 4370.5401 | BB8: 4114.1401 | BC8: 4094.3503 | BD8: 4437.1429 | BE8: 4247.63 | BF8: 4413.0609 | BG8: 4578.632 | BH8: 3952.8012 | BI8: 4124.0557 | BJ8: 4531.0208 | BK8: 5284.3802 | BL8: 5352.8574
A9: Andorra | B9: AND | C9: GDP per capita (current US$) | D9: NY.GDP.PCAP.CD | O9: 3238.5568 | P9: 3498.1737 | Q9: 4217.1736 | R9: 5342.1686 | S9: 6319.739 | T9: 7169.101 | U9: 7152.3751 | V9: 7751.3702 | W9: 9129.7062 | X9: 11820.849 | Y9: 12377.412 | Z9: 10372.233 | AA9: 9610.2663 | AB9: 8022.6548 | AC9: 7728.9067 | AD9: 7774.3938 | AE9: 10361.816 | AF9: 12616.168 | AG9: 14304.357 | AH9: 15166.438 | AI9: 18878.506 | AJ9: 19532.54 | AK9: 20547.712 | AL9: 16516.471 | AM9: 16234.809 | AN9: 18461.065 | AO9: 19017.175 | AP9: 18353.06 | AQ9: 18894.521 | AR9: 19261.711 | AS9: 21854.247 | AT9: 22971.536 | AU9: 25066.882 | AV9: 32271.964 | AW9: 37969.175 | AX9: 40066.257 | AY9: 42675.813 | AZ9: 47803.694 | BA9: 48718.497 | BB9: 43503.186 | BC9: 40852.667 | BD9: 43335.329 | BE9: 38686.461 | BF9: 39538.767 | BG9: 41303.929 | BH9: 35762.523 | BI9: 37474.665 | BJ9: 38962.88 | BK9: 41793.055 | BL9: 40886.391
A10: Arab World | B10: ARB | C10: GDP per capita (current US$) | D10: NY.GDP.PCAP.CD | M10: 224.87868 | N10: 240.03624 | O10: 262.86742 | P10: 295.97173 | Q10: 343.56731 | R10: 423.13549 | S10: 777.56257 | T10: 836.21081 | U10: 1007.1433 | V10: 1123.1456 | W10: 1193.7481 | X10: 1563.7073 | Y10: 2052.9615 | Z10: 2050.7747 | AA10: 1864.8757 | AB10: 1699.2197 | AC10: 1672.2829 | AD10: 1606.7598 | AE10: 1489.8437 | AF10: 1543.5169 | AG10: 1476.0447 | AH10: 1505.5092 | AI10: 2009.4203 | AJ10: 1929.6184 | AK10: 2028.1917 | AL10: 1997.2783 | AM10: 1989.8406 | AN10: 2073.1421 | AO10: 2236.3287 | AP10: 2319.4103 | AQ10: 2189.6811 | AR10: 2332.7981 | AS10: 2606.0766 | AT10: 2510.2619 | AU10: 2476.696 | AV10: 2736.4821 | AW10: 3134.6735 | AX10: 3765.8205 | AY10: 4359.808 | AZ10: 4963.5415 | BA10: 6146.3917 | BB10: 5176.5283 | BC10: 5934.2907 | BD10: 6867.692 | BE10: 7465.1517 | BF10: 7519.8083 | BG10: 7457.4611 | BH10: 6387.6606 | BI10: 6097.239 | BJ10: 6102.2111 | BK10: 6603.3512 | BL10: 6580.0563
A11: United Arab Emirates | B11: ARE | C11: GDP per capita (current US$) | D11: NY.GDP.PCAP.CD | T11: 26847.794 | U11: 30118.138 | V11: 33823.32 | W11: 28456.737 | X11: 33512.741 | Y11: 42764.457 | Z11: 44987.21 | AA11: 40026.166 | AB11: 34843.103 | AC11: 32309.808 | AD11: 29720.919 | AE11: 23467.977 | AF11: 23726.152 | AG11: 22295.146 | AH11: 24028.193 | AI11: 27729.466 | AJ11: 26612.336 | AK11: 26420.873 | AL11: 25596.692 | AM11: 25847.926 | AN11: 27222.036 | AO11: 28975.023 | AP11: 29512.664 | AQ11: 26899.602 | AR11: 28470.838 | AS11: 33291.419 | AT11: 31280.784 | AU11: 31567.474 | AV11: 33499.094 | AW11: 36333.25 | AX11: 39365.434 | AY11: 41907.406 | AZ11: 41809.516 | BA11: 44498.934 | BB11: 32024.182 | BC11: 33893.304 | BD11: 39194.677 | BE11: 40976.5 | BF11: 42412.63 | BG11: 43751.839 | BH11: 38663.384 | BI11: 38141.847 | BJ11: 40644.804 | BK11: 43839.356 | BL11: 43103.323
A12: Argentina | B12: ARG | C12: GDP per capita (current US$) | D12: NY.GDP.PCAP.CD | G12: 1155.8902 | H12: 850.30474 | I12: 1173.2382 | J12: 1279.1134 | K12: 1272.803 | L12: 1062.5436 | M12: 1141.0805 | N12: 1329.0587 | O12: 1322.5908 | P12: 1372.3743 | Q12: 1408.8652 | R12: 2097.0226 | S12: 2844.8636 | T12: 2027.3371 | U12: 1948.2247 | V12: 2129.7083 | W12: 2146.3645 | X12: 2520.9216 | Y12: 2758.8352 | Z12: 2776.322 | AA12: 2927.8976 | AB12: 3553.3778 | AC12: 2659.7086 | AD12: 2926.127 | AE12: 3613.6217 | AF12: 3562.8756 | AG12: 3985.1912 | AH12: 2383.8677 | AI12: 4333.483 | AJ12: 5735.3603 | AK12: 6823.5376 | AL12: 6969.1181 | AM12: 7483.1397 | AN12: 7408.7082 | AO12: 7721.3545 | AP12: 8213.1272 | AQ12: 8289.5057 | AR12: 7774.7362 | AS12: 7708.101 | AT12: 7208.3716 | AU12: 2593.4042 | AV12: 3349.8061 | AW12: 4277.7214 | AX12: 5109.8513 | AY12: 5919.012 | AZ12: 7245.4483 | BA12: 9020.8731 | BB12: 8225.1372 | BC12: 10385.964 | BD12: 12848.864 | BE12: 13082.664 | BF12: 13080.255 | BG12: 12334.798 | BH12: 13789.06 | BI12: 12790.242 | BJ12: 14591.863 | BK12: 11683.95 | BL12: 10006.149
A13: Armenia | B13: ARM | C13: GDP per capita (current US$) | D13: NY.GDP.PCAP.CD | AI13: 637.85466 | AJ13: 590.12105 | AK13: 369.63262 | AL13: 357.20328 | AM13: 400.51524 | AN13: 456.37505 | AO13: 504.05856 | AP13: 523.28307 | AQ13: 609.17244 | AR13: 597.43251 | AS13: 622.74214 | AT13: 694.42323 | AU13: 783.2407 | AV13: 930.12732 | AW13: 1191.919 | AX13: 1643.753 | AY13: 2158.1437 | AZ13: 3139.2775 | BA13: 4010.8572 | BB13: 2994.3425 | BC13: 3218.3727 | BD13: 3525.8047 | BE13: 3681.8575 | BF13: 3838.1858 | BG13: 3986.2316 | BH13: 3607.2967 | BI13: 3591.8293 | BJ13: 3914.5013 | BK13: 4220.4903 | BL13: 4622.7335
A14: American Samoa | B14: ASM | C14: GDP per capita (current US$) | D14: NY.GDP.PCAP.CD | AU14: 8700.0677 | AV14: 8856.5475 | AW14: 8578.9447 | AX14: 8444.9817 | AY14: 8391.5611 | AZ14: 8909.4492 | BA14: 9792.6668 | BB14: 11961.258 | BC14: 10271.225 | BD14: 10294.302 | BE14: 11568.793 | BF14: 11505.394 | BG14: 11507.232 | BH14: 11843.331 | BI14: 11696.956 | BJ14: 10823.445 | BK14: 11466.691
A15: Antigua and Barbuda | B15: ATG | C15: GDP per capita (current US$) | D15: NY.GDP.PCAP.CD | V15: 1246.7503 | W15: 1416.5862 | X15: 1760.7176 | Y15: 2124.4812 | Z15: 2392.2611 | AA15: 2660.6012 | AB15: 2947.9355 | AC15: 3372.4929 | AD15: 3899.3287 | AE15: 4703.1794 | AF15: 5463.2413 | AG15: 6453.477 | AH15: 7076.4222 | AI15: 7348.2129 | AJ15: 7601.8485 | AK15: 7744.2749 | AL15: 8136.1688 | AM15: 8770.7516 | AN15: 8406.593 | AO15: 9030.9753 | AP15: 9492.0383 | AQ15: 9940.1916 | AR15: 10260.585 | AS15: 10920.843 | AT15: 10370.671 | AU15: 10404.436 | AV15: 10789.951 | AW15: 11446.638 | AX15: 12547.613 | AY15: 13989.716 | AZ15: 15607.09 | BA15: 16024.346 | BB15: 14113.077 | BC15: 13049.257 | BD15: 12746.205 | BE15: 13272.441 | BF15: 12909.744 | BG15: 13501.581 | BH15: 14286.093 | BI15: 15197.617 | BJ15: 15383.415 | BK15: 16726.981 | BL15: 17790.309
A16: Australia | B16: AUS | C16: GDP per capita (current US$) | D16: NY.GDP.PCAP.CD | E16: 1807.7857 | F16: 1874.7321 | G16: 1851.8419 | H16: 1964.1505 | I16: 2128.0684 | J16: 2277.5584 | K16: 2340.4387 | L16: 2576.2845 | M16: 2720.0826 | N16: 2986.9495 | O16: 3299.8432 | P16: 3489.9523 | Q16: 3943.7876 | R16: 4763.6284 | S16: 6473.1652 | T16: 6994.2099 | U16: 7476.7487 | V16: 7765.0705 | W16: 8241.9973 | X16: 9281.5234 | Y16: 10194.319 | Z16: 11833.743 | AA16: 12766.522 | AB16: 11518.669 | AC16: 12431.946 | AD16: 11437.664 | AE16: 11364.239 | AF16: 11624.54 | AG16: 14254.558 | AH16: 17798.314 | AI16: 18211.275 | AJ16: 18821.477 | AK16: 18569.813 | AL16: 17634.256 | AM16: 18046.02 | AN16: 20319.631 | AO16: 21861.326 | AP16: 23468.597 | AQ16: 21318.964 | AR16: 20533.035 | AS16: 21679.248 | AT16: 19490.861 | AU16: 20082.483 | AV16: 23447.031 | AW16: 30430.676 | AX16: 33999.243 | AY16: 36044.923 | AZ16: 40960.054 | BA16: 49601.657 | BB16: 42772.359 | BC16: 52022.126 | BD16: 62517.834 | BE16: 68012.148 | BF16: 68150.107 | BG16: 62510.791 | BH16: 56755.722 | BI16: 49971.131 | BJ16: 54066.471 | BK16: 57395.919 | BL16: 54907.102
A17: Austria | B17: AUT | C17: GDP per capita (current US$) | D17: NY.GDP.PCAP.CD | E17: 935.46043 | F17: 1031.815 | G17: 1087.8342 | H17: 1167.0005 | I17: 1269.4126 | J17: 1374.5321 | K17: 1486.9686 | L17: 1569.6672 | M17: 1677.6735 | N17: 1825.3861 | O17: 2058.7691 | P17: 2380.9784 | Q17: 2924.0489 | R17: 3890.7225 | S17: 4630.7572 | T17: 5285.6207 | U17: 5678.3866 | V17: 6810.6277 | W17: 8205.4689 | X17: 9793.7653 | Y17: 10869.546 | Z17: 9385.249 | AA17: 9410.3472 | AB17: 9537.4074 | AC17: 8991.0651 | AD17: 9172.0968 | AE17: 13083.073 | AF17: 16392.77 | AG17: 17578.619 | AH17: 17468.946 | AI17: 21680.99 | AJ17: 22410.912 | AK17: 24880.164 | AL17: 24081.528 | AM17: 25646.701 | AN17: 30325.85 | AO17: 29809.077 | AP17: 26705.479 | AQ17: 27361.875 | AR17: 27174.297 | AS17: 24564.458 | AT17: 24537.514 | AU17: 26401.745 | AV17: 32222.897 | AW17: 36821.521 | AX17: 38403.134 | AY17: 40635.282 | AZ17: 46855.772 | BA17: 51708.766 | BB17: 47963.179 | BC17: 46858.043 | BD17: 51374.958 | BE17: 48567.695 | BF17: 50716.709 | BG17: 51717.496 | BH17: 44178.047 | BI17: 45237.805 | BJ17: 47549.079 | BK17: 51525.046 | BL17: 50277.275
A18: Azerbaijan | B18: AZE | C18: GDP per capita (current US$) | D18: NY.GDP.PCAP.CD | AI18: 1237.3245 | AJ18: 1209.2375 | AK18: 676.15151 | AL18: 529.81366 | AM18: 436.21687 | AN18: 397.19812 | AO18: 409.21076 | AP18: 505.56377 | AQ18: 561.90704 | AR18: 573.8933 | AS18: 655.09743 | AT18: 703.68384 | AU18: 763.08064 | AV18: 883.644 | AW18: 1045.0094 | AX18: 1578.4024 | AY18: 2473.0818 | AZ18: 3851.4379 | BA18: 5574.6038 | BB18: 4950.2948 | BC18: 5842.8058 | BD18: 7189.6912 | BE18: 7496.2946 | BF18: 7875.757 | BG18: 7891.3131 | BH18: 5500.3104 | BI18: 3880.7387 | BJ18: 4147.0897 | BK18: 4739.8417 | BL18: 4793.587
A19: Burundi | B19: BDI | C19: GDP per capita (current US$) | D19: NY.GDP.PCAP.CD | E19: 70.051735 | F19: 71.167188 | G19: 73.435306 | H19: 78.514329 | I19: 86.161606 | J19: 51.381865 | K19: 52.18265 | L19: 54.806393 | M19: 54.900811 | N19: 55.715016 | O19: 69.769304 | P19: 71.626771 | Q19: 69.139402 | R19: 84.418642 | S19: 94.685322 | T19: 113.75313 | U19: 118.9149 | V19: 142.05302 | W19: 154.5162 | X19: 193.1502 | Y19: 221.23184 | Z19: 227.12812 | AA19: 231.34385 | AB19: 240.78229 | AC19: 213.61652 | AD19: 242.05825 | AE19: 245.91543 | AF19: 225.0717 | AG19: 209.41506 | AH19: 209.89441 | AI19: 208.14676 | AJ19: 209.7779 | AK19: 190.48901 | AL19: 161.88755 | AM19: 156.8123 | AN19: 167.09892 | AO19: 143.4023 | AP19: 158.91467 | AQ19: 144.49306 | AR19: 128.93908 | AS19: 136.46397 | AT19: 134.36345 | AU19: 123.11763 | AV19: 113.56737 | AW19: 128.33661 | AX19: 151.68146 | AY19: 167.37648 | AZ19: 172.49586 | BA19: 198.3529 | BB19: 212.13688 | BC19: 234.23565 | BD19: 249.57798 | BE19: 252.35898 | BF19: 256.976 | BG19: 274.85795 | BH19: 305.54977 | BI19: 282.19313 | BJ19: 292.99763 | BK19: 271.75204 | BL19: 261.24747
A20: Belgium | B20: BEL | C20: GDP per capita (current US$) | D20: NY.GDP.PCAP.CD | E20: 1273.6917 | F20: 1350.1977 | G20: 1438.5232 | H20: 1535.0237 | I20: 1701.8463 | J20: 1835.5948 | K20: 1957.6261 | L20: 2086.636 | M20: 2222.3615 | N20: 2458.0818 | O20: 2765.891 | P20: 3082.928 | Q20: 3831.6319 | R20: 4900.9622 | S20: 5733.7982 | T20: 6701.3773 | U20: 7243.0474 | V20: 8426.9469 | W20: 10289.768 | X20: 11810.616 | Y20: 12864.003 | Z20: 10622.802 | AA20: 9343.8611 | AB20: 8846.2343 | AC20: 8457.2688 | AD20: 8750.8185 | AE20: 12170.041 | AF20: 15135.852 | AG20: 16391.094 | AH20: 16525.062 | AI20: 20600.375 | AJ20: 21041.661 | AK20: 23372.619 | AL20: 22283.936 | AM20: 24208.555 | AN20: 28413.826 | AO20: 27489.555 | AP20: 24820.938 | AQ20: 25338.443 | AR20: 25244.275 | AS20: 23041.535 | AT20: 22995.158 | AU20: 24887.561 | AV20: 30587.668 | AW20: 35364.375 | AX20: 36795.977 | AY20: 38672.706 | AZ20: 44262.896 | BA20: 48106.893 | BB20: 44583.545 | BC20: 44141.878 | BD20: 47348.525 | BE20: 44673.116 | BF20: 46744.663 | BG20: 47700.54 | BH20: 40991.808 | BI20: 41998.336 | BJ20: 44288.508 | BK20: 47491.323 | BL20: 46116.699
A21: Benin | B21: BEN | C21: GDP per capita (current US$) | D21: NY.GDP.PCAP.CD | E21: 93.022509 | F21: 95.572155 | G21: 94.464535 | H21: 99.859114 | I21: 104.33977 | J21: 110.13279 | K21: 112.94084 | L21: 111.9516 | M21: 116.89507 | N21: 116.02509 | O21: 114.5566 | P21: 112.57009 | Q21: 134.81941 | R21: 161.98737 | S21: 174.01415 | T21: 207.30044 | U21: 208.65615 | V21: 218.45437 | W21: 263.58106 | X21: 327.82168 | Y21: 378.0439 | Z21: 337.97819 | AA21: 322.7777 | AB21: 271.12924 | AC21: 252.86979 | AD21: 244.411 | AE21: 303.3489 | AF21: 344.50307 | AG21: 346.73604 | AH21: 311.6783 | AI21: 393.68621 | AJ21: 385.75362 | AK21: 317.96286 | AL21: 411.92603 | AM21: 279.6665 | AN21: 367.38734 | AO21: 387.43292 | AP21: 361.10027 | AQ21: 379.44235 | AR21: 551.61939 | AS21: 511.40023 | AT21: 517.61423 | AU21: 572.2288 | AV21: 709.69053 | AW21: 797.31268 | AX21: 822.45783 | AY21: 855.29404 | AZ21: 964.92694 | BA21: 1120.8883 | BB21: 1084.3939 | BC21: 1036.534 | BD21: 1130.2731 | BE21: 1145.1408 | BF21: 1251.2105 | BG21: 1291.4098 | BH21: 1076.7977 | BI21: 1087.2878 | BJ21: 1136.5928 | BK21: 1240.8295 | BL21: 1219.4327
A22: Burkina Faso | B22: BFA | C22: GDP per capita (current US$) | D22: NY.GDP.PCAP.CD | E22: 68.424749 | F22: 71.55818 | G22: 76.520611 | H22: 78.372072 | I22: 80.472767 | J22: 81.725115 | K22: 82.545637 | L22: 84.363165 | M22: 84.733049 | N22: 86.520211 | O22: 81.499899 | P22: 84.287815 | Q22: 99.326764 | R22: 113.78058 | S22: 124.35903 | T22: 152.72822 | U22: 155.649 | V22: 176.78337 | W22: 225.94165 | X22: 262.07601 | Y22: 282.68574 | Z22: 254.23078 | AA22: 245.0947 | AB22: 217.99475 | AC22: 193.84324 | AD22: 200.89442 | AE22: 256.76232 | AF22: 291.13196 | AG22: 313.06189 | AH22: 304.85344 | AI22: 351.97932 | AJ22: 346.41067 | AK22: 240.96348 | AL22: 244.12707 | AM22: 193.07024 | AN22: 235.8322 | AO22: 249.36029 | AP22: 229.49312 | AQ22: 255.71823 | AR22: 298.22817 | AS22: 254.71753 | AT22: 266.86416 | AU22: 293.28075 | AV22: 373.78763 | AW22: 417.62706 | AX22: 457.75155 | AY22: 473.02918 | AZ22: 534.35589 | BA22: 640.81088 | BB22: 621.6731 | BC22: 647.83585 | BD22: 751.17296 | BE22: 758.0007 | BF22: 787.47018 | BG22: 792.84678 | BH22: 653.32698 | BI22: 687.67017 | BJ22: 738.27416 | BK22: 820.16079 | BL22: 774.83969
A23: Bangladesh | B23: BGD | C23: GDP per capita (current US$) | D23: NY.GDP.PCAP.CD | E23: 89.035241 | F23: 97.595274 | G23: 100.12212 | H23: 101.90141 | I23: 100.22111 | J23: 106.64665 | K23: 112.66536 | L23: 122.87063 | M23: 122.84759 | N23: 135.14738 | O23: 140.00271 | P23: 133.55142 | Q23: 94.381678 | R23: 119.55974 | S23: 182.01999 | T23: 277.57064 | U23: 141.19717 | V23: 131.37324 | W23: 176.03395 | X23: 200.76966 | Y23: 227.75195 | Z23: 247.64962 | AA23: 220.71881 | AB23: 204.41768 | AC23: 213.99666 | AD23: 245.4539 | AE23: 233.65805 | AF23: 253.97446 | AG23: 270.6996 | AH23: 285.82921 | AI23: 306.2687 | AJ23: 293.16042 | AK23: 293.645 | AL23: 300.55575 | AM23: 299.53304 | AN23: 329.42408 | AO23: 394.71748 | AP23: 401.49869 | AQ23: 407.42919 | AR23: 409.5432 | AS23: 418.06897 | AT23: 415.03443 | AU23: 413.08025 | AV23: 446.31066 | AW23: 475.29192 | AX23: 499.46194 | AY23: 509.64014 | AZ23: 558.05186 | BA23: 634.98706 | BB23: 702.26441 | BC23: 781.15359 | BD23: 861.75844 | BE23: 883.105 | BF23: 981.83988 | BG23: 1118.8537 | BH23: 1248.4534 | BI23: 1401.6205 | BJ23: 1563.9139 | BK23: 1698.3504 | BL23: 1855.7398
A24: Bulgaria | B24: BGR | C24: GDP per capita (current US$) | D24: NY.GDP.PCAP.CD | Y24: 2238.803 | Z24: 2234.8148 | AA24: 2169.004 | AB24: 1852.8134 | AC24: 1963.5727 | AD24: 1914.5506 | AE24: 2260.4273 | AF24: 3132.3014 | AG24: 2511.3931 | AH24: 2477.0208 | AI24: 2366.5298 | AJ24: 1267.7344 | AK24: 1211.9809 | AL24: 1278.2472 | AM24: 1148.4944 | AN24: 2258.286 | AO24: 1470.1037 | AP24: 1361.3924 | AQ24: 1820.4051 | AR24: 1659.7183 | AS24: 1621.243 | AT24: 1770.9135 | AU24: 2092.9577 | AV24: 2719.4977 | AW24: 3389.707 | AX24: 3899.9076 | AY24: 4523.0508 | AZ24: 5885.1043 | BA24: 7265.7355 | BB24: 6984.966 | BC24: 6809.899 | BD24: 7806.3487 | BE24: 7393.1892 | BF24: 7651.8179 | BG24: 7874.2609 | BH24: 7053.6037 | BI24: 7545.7903 | BJ24: 8331.058 | BK24: 9423.5586 | BL24: 9737.6014
A25: Bahrain | B25: BHR | C25: GDP per capita (current US$) | D25: NY.GDP.PCAP.CD | Y25: 8537.9294 | Z25: 9269.2696 | AA25: 9446.158 | AB25: 9421.2857 | AC25: 9590.7302 | AD25: 8706.7666 | AE25: 7041.602 | AF25: 7555.1005 | AG25: 7958.7479 | AH25: 8030.9047 | AI25: 8528.9833 | AJ25: 9055.6799 | AK25: 9082.7585 | AL25: 9698.1891 | AM25: 10130.505 | AN25: 10376.972 | AO25: 10544.704 | AP25: 10672.166 | AQ25: 10076.221 | AR25: 10401.546 | AS25: 13636.396 | AT25: 12868.269 | AU25: 13049.803 | AV25: 14222.037 | AW25: 15846.544 | AX25: 17959.255 | AY25: 19307.61 | AZ25: 20976.544 | BA25: 23066.534 | BB25: 19355.905 | BC25: 20722.137 | BD25: 22514.238 | BE25: 23654.351 | BF25: 24744.297 | BG25: 24989.4 | BH25: 22688.944 | BI25: 22619.117 | BJ25: 23709.43 | BK25: 23991.057 | BL25: 23503.977
A26: Bahamas, The | B26: BHS | C26: GDP per capita (current US$) | D26: NY.GDP.PCAP.CD | E26: 1550.2394 | F26: 1651.289 | G26: 1752.8545 | H26: 1867.025 | I26: 1994.3808 | J26: 2144.7544 | K26: 2322.6899 | L26: 2556.651 | M26: 2804.3339 | N26: 3215.0952 | O26: 3178.8446 | P26: 3297.5059 | Q26: 3322.1639 | R26: 3696.0725 | S26: 3416.1625 | T26: 3156.2341 | U26: 3328.5124 | V26: 3617.4347 | W26: 4131.4684 | X26: 5533.44 | Y26: 6340.7268 | Z26: 6624.8386 | AA26: 7168.0958 | AB26: 7698.4592 | AC26: 8877.3198 | AD26: 9893.0842 | AE26: 10344.452 | AF26: 11156.282 | AG26: 11387.709 | AH26: 12163.681 | AI26: 12356.424 | AJ26: 11919.788 | AK26: 11686.696 | AL26: 11406.69 | AM26: 11814.563 | AN26: 12238.386 | AO26: 12708.731 | AP26: 22036.484 | AQ26: 23514.42 | AR26: 26130.102 | AS26: 27097.611 | AT26: 27486.237 | AU26: 28866.801 | AV26: 28327.271 | AW26: 28395.925 | AX26: 30278.367 | AY26: 30713.705 | AZ26: 31472.099 | BA26: 30627.239 | BB26: 28552.19 | BC26: 28443.408 | BD26: 28006.38 | BE26: 29485.621 | BF26: 28768.03 | BG26: 29445.031 | BH26: 31405.964 | BI26: 31588.835 | BJ26: 31827.243 | BK26: 32217.872 | BL26: 32933.486
A27: Bosnia and Herzegovina | B27: BIH | C27: GDP per capita (current US$) | D27: NY.GDP.PCAP.CD | AM27: 319.01304 | AN27: 487.47678 | AO27: 740.09851 | AP27: 982.80185 | AQ27: 1102.391 | AR27: 1251.7473 | AS27: 1467.7765 | AT27: 1530.8148 | AU27: 1769.1998 | AV27: 2224.7459 | AW27: 2814.9999 | AX27: 2980.6021 | AY27: 3416.5106 | AZ27: 4193.3737 | BA27: 5090.9323 | BB27: 4714.7025 | BC27: 4635.5178 | BD27: 5092.5519 | BE27: 4778.6361 | BF27: 5131.3945 | BG27: 5329.635 | BH27: 4727.2775 | BI27: 4994.6831 | BJ27: 5394.5912 | BK27: 6072.181 | BL27: 6073.2652
A28: Belarus | B28: BLR | C28: GDP per capita (current US$) | D28: NY.GDP.PCAP.CD | AI28: 2124.8405 | AJ28: 1765.7446 | AK28: 1667.6818 | AL28: 1590.0959 | AM28: 1460.0591 | AN28: 1370.6766 | AO28: 1452.4455 | AP28: 1396.5018 | AQ28: 1511.7701 | AR28: 1210.6117 | AS28: 1276.288 | AT28: 1244.3732 | AU28: 1479.3146 | AV28: 1819.7661 | AW28: 2378.6233 | AX28: 3125.8105 | AY28: 3847.4341 | AZ28: 4735.6576 | BA28: 6377.3697 | BB28: 5351.3554 | BC28: 6029.3968 | BD28: 6519.2302 | BE28: 6940.1593 | BF28: 7978.8726 | BG28: 8318.5127 | BH28: 5949.1063 | BI28: 5022.6266 | BJ28: 5761.7471 | BK28: 6330.0752 | BL28: 6663.2953
A29: Belize | B29: BLZ | C29: GDP per capita (current US$) | D29: NY.GDP.PCAP.CD | E29: 304.91711 | F29: 316.40361 | G29: 327.12687 | H29: 336.94147 | I29: 351.16113 | J29: 377.59431 | K29: 406.09797 | L29: 420.43189 | M29: 386.95324 | N29: 396.65431 | O29: 435.69047 | P29: 474.44422 | Q29: 519.56351 | R29: 605.93344 | S29: 786.06909 | T29: 885.98453 | U29: 717.04018 | V29: 858.82808 | W29: 980.82251 | X29: 1074.272 | Y29: 1373.093 | Z29: 1328.8281 | AA29: 1202.682 | AB29: 1232.8374 | AC29: 1336.9876 | AD29: 1289.3673 | AE29: 1366.0497 | AF29: 1612.4516 | AG29: 1787.9514 | AH29: 2011.9687 | AI29: 2197.185 | AJ29: 2326.8216 | AK29: 2666.8816 | AL29: 2832.9753 | AM29: 2880.1254 | AN29: 2996.3829 | AO29: 3001.8337 | AP29: 2952.9486 | AQ29: 2992.4448 | AR29: 3065.9797 | AS29: 3364.3329 | AT29: 3404.453 | AU29: 3525.6386 | AV29: 3650.3665 | AW29: 3802.2958 | AX29: 3883.1924 | AY29: 4153.8947 | AZ29: 4252.4873 | BA29: 4404.3308 | BB29: 4186.49 | BC29: 4270.8643 | BD29: 4423.4898 | BE29: 4505.6213 | BF29: 4568.503 | BG29: 4705.6027 | BH29: 4775.9556 | BI29: 4818.4039 | BJ29: 4887.5772 | BK29: 4884.7342 | BL29: 4815.1637
A30: Bermuda | B30: BMU | C30: GDP per capita (current US$) | D30: NY.GDP.PCAP.CD | E30: 1902.4021 | F30: 1961.5382 | G30: 2020.386 | H30: 2020.2652 | I30: 2199.727 | J30: 2282.2165 | K30: 2630.8505 | L30: 2982.7497 | M30: 2830.1887 | N30: 3053.7037 | O30: 3387.2727 | P30: 3866.3004 | Q30: 4343.1734 | R30: 5009.2937 | S30: 5853.9326 | T30: 6509.434 | U30: 7261.2782 | V30: 8370.7865 | W30: 8876.8657 | X30: 9613.3829 | Y30: 11218.218 | Z30: 13425.977 | AA30: 14166.171 | AB30: 15902.02 | AC30: 17469.826 | AD30: 18269.536 | AE30: 20450.665 | AF30: 22411.796 | AG30: 24253.176 | AH30: 25517.922 | AI30: 26841.52 | AJ30: 27700.31 | AK30: 28669.682 | AL30: 30900.695 | AM30: 31476.063 | AN30: 33989.722 | AO30: 44826.789 | AP30: 48478.883 | AQ30: 51371.741 | AR30: 54245.46 | AS30: 56284.169 | AT30: 58883.959 | AU30: 62583.1 | AV30: 66111.725 | AW30: 70359.319 | AX30: 75882.034 | AY30: 83912.698 | AZ30: 90849.587 | BA30: 93605.748 | BB30: 88463.313 | BC30: 88207.328 | BD30: 85973.158 | BE30: 85458.456 | BF30: 85748.065
A31: Bolivia | B31: BOL | C31: GDP per capita (current US$) | D31: NY.GDP.PCAP.CD | E31: 102.23789 | F31: 109.06101 | G31: 116.92515 | H31: 123.42931 | I31: 136.31243 | J31: 149.64007 | K31: 162.32605 | L31: 179.58334 | M31: 199.6298 | N31: 211.79711 | O31: 226.80697 | P31: 239.12813 | Q31: 268.58413 | R31: 263.89236 | S31: 429.29765 | T31: 480.80308 | U31: 534.27349 | V31: 617.30695 | W31: 703.13635 | X31: 809.41129 | Y31: 811.28486 | Z31: 1030.8334 | AA31: 960.98361 | AB31: 913.97516 | AC31: 1019.0578 | AD31: 870.18565 | AE31: 627.39853 | AF31: 671.07513 | AG31: 698.69264 | AH31: 701.66615 | AI31: 709.05967 | AJ31: 762.07803 | AK31: 788.15199 | AL31: 784.19174 | AM31: 801.04603 | AN31: 880.99222 | AO31: 950.85651 | AP31: 998.51532 | AQ31: 1049.4994 | AR31: 1003.3922 | AS31: 997.58246 | AT31: 948.87121 | AU31: 904.22663 | AV31: 907.53711 | AW31: 967.40699 | AX31: 1034.3112 | AY31: 1218.8745 | AZ31: 1372.6282 | BA31: 1715.2089 | BB31: 1754.2111 | BC31: 1955.4616 | BD31: 2346.3372 | BE31: 2609.8808 | BF31: 2908.2001 | BG31: 3081.8788 | BH31: 3035.9722 | BI31: 3076.6589 | BJ31: 3351.124 | BK31: 3548.5902 | BL31: 3552.0688
A32: Brazil | B32: BRA | C32: GDP per capita (current US$) | D32: NY.GDP.PCAP.CD | E32: 210.1099 | F32: 205.04077 | G32: 260.42565 | H32: 292.25214 | I32: 261.66662 | J32: 261.35435 | K32: 315.7972 | L32: 347.49306 | M32: 374.78678 | N32: 403.88427 | O32: 445.0231 | P32: 504.74952 | Q32: 586.2144 | R32: 775.2733 | S32: 1004.1049 | T32: 1153.831 | U32: 1390.625 | V32: 1567.0062 | W32: 1744.2571 | X32: 1908.4876 | Y32: 1947.2764 | Z32: 2132.8833 | AA32: 2226.7673 | AB32: 1570.5397 | AC32: 1578.9264 | AD32: 1648.0821 | AE32: 1941.4911 | AF32: 2087.3076 | AG32: 2300.3768 | AH32: 2908.4962 | AI32: 3100.2805 | AJ32: 3975.3901 | AK32: 2596.9199 | AL32: 2791.2091 | AM32: 3500.6115 | AN32: 4748.2155 | AO32: 5166.1637 | AP32: 5282.0088 | AQ32: 5087.1522 | AR32: 3478.3727 | AS32: 3749.7532 | AT32: 3156.7987 | AU32: 2829.2832 | AV32: 3070.9105 | AW32: 3637.4624 | AX32: 4790.4371 | AY32: 5886.4636 | AZ32: 7348.0308 | BA32: 8831.0231 | BB32: 8597.9154 | BC32: 11286.243 | BD32: 13245.612 | BE32: 12370.024 | BF32: 12300.325 | BG32: 12112.588 | BH32: 8814.001 | BI32: 8710.0967 | BJ32: 9925.3862 | BK32: 9001.2342 | BL32: 8717.1863
A33: Barbados | B33: BRB | C33: GDP per capita (current US$) | D33: NY.GDP.PCAP.CD | S33: 1274.5432 | T33: 1633.8496 | U33: 1760.6672 | V33: 1988.8473 | W33: 2209.7405 | X33: 2667.0371 | Y33: 4010.7158 | Z33: 4398.7901 | AA33: 4580.8984 | AB33: 4851.1567 | AC33: 5271.6473 | AD33: 5500.3497 | AE33: 6019.8874 | AF33: 6605.6 | AG33: 6999.6869 | AH33: 7717.2962 | AI33: 7711.2068 | AJ33: 7714.9489 | AK33: 7444.2914 | AL33: 7819.4218 | AM33: 8121.5619 | AN33: 8335.8993 | AO33: 8850.9802 | AP33: 9315.8286 | AQ33: 10459.365 | AR33: 10914.444 | AS33: 11268.254 | AT33: 11209.174 | AU33: 11361.434 | AV33: 11699.456 | AW33: 12512.533 | AX33: 13822.592 | AY33: 15199.458 | AZ33: 16770.721 | BA33: 17092.582 | BB33: 15885.58 | BC33: 16056.371 | BD33: 16458.353 | BE33: 16249.559 | BF33: 16451.164 | BG33: 16489.072 | BH33: 16525.073 | BI33: 16900.167 | BJ33: 17391.426 | BK33: 17745.193 | BL33: 18148.245
A34: Brunei Darussalam | B34: BRN | C34: GDP per capita (current US$) | D34: NY.GDP.PCAP.CD | J34: 1113.8266 | K34: 1237.5636 | L34: 1236.3977 | M34: 1364.0544 | N34: 1304.2985 | O34: 1382.5483 | P34: 1455.8983 | Q34: 1906.8775 | R34: 2916.2088 | S34: 6923.0879 | T34: 7228.4429 | U34: 8461.4871 | V34: 9917.4718 | W34: 10714.94 | X34: 14945.204 | Y34: 25422.17 | Z34: 21828.777 | AA34: 20693.724 | AB34: 18128.987 | AC34: 17337.106 | AD34: 15698.945 | AE34: 10214.117 | AF34: 11594.665 | AG34: 11009.302 | AH34: 11872.631 | AI34: 13607.522 | AJ34: 13905.064 | AK34: 15274.445 | AL34: 14575.73 | AM34: 14120.855 | AN34: 15933.346 | AO34: 16793.281 | AP34: 16660.361 | AQ34: 12693.791 | AR34: 14101.346 | AS34: 18012.556 | AT34: 16472.149 | AU34: 16850.151 | AV34: 18560.609 | AW34: 21902.088 | AX34: 26105.279 | AY34: 30979.879 | AZ34: 32663.567 | BA34: 37934.377 | BB34: 27955.714 | BC34: 35269.553 | BD34: 47055.841 | BE34: 47740.515 | BF34: 44740.085 | BG34: 41726.784 | BH34: 31164.562 | BI34: 27157.823 | BJ34: 28572.147 | BK34: 31628.329 | BL34: 31086.751
A35: Bhutan | B35: BTN | C35: GDP per capita (current US$) | D35: NY.GDP.PCAP.CD | Y35: 333.40288 | Z35: 350.12626 | AA35: 347.2197 | AB35: 376.48399 | AC35: 374.9147 | AD35: 370.94576 | AE35: 420.67911 | AF35: 512.1916 | AG35: 557.08253 | AH35: 528.45842 | AI35: 564.77961 | AJ35: 467.69711 | AK35: 469.19898 | AL35: 441.68482 | AM35: 509.12407 | AN35: 566.8577 | AO35: 584.37916 | AP35: 663.32886 | AQ35: 667.91362 | AR35: 725.12474 | AS35: 718.18783 | AT35: 764.43661 | AU35: 845.51028 | AV35: 962.0969 | AW35: 1068.4218 | AX35: 1228.4418 | AY35: 1330.9653 | AZ35: 1757.1826 | BA35: 1828.1492 | BB35: 1819.2134 | BC35: 2258.1831 | BD35: 2563.2575 | BE35: 2538.9459 | BF35: 2472.7143 | BG35: 2652.2146 | BH35: 2752.6642 | BI35: 2930.563 | BJ35: 3286.5747 | BK35: 3243.2311
A36: Botswana | B36: BWA | C36: GDP per capita (current US$) | D36: NY.GDP.PCAP.CD | E36: 60.492514 | F36: 64.176515 | G36: 68.050219 | H36: 71.107368 | I36: 75.955503 | J36: 81.770286 | K36: 89.978452 | L36: 100.40617 | M36: 110.97846 | N36: 126.54493 | O36: 153.32613 | P36: 196.42312 | Q36: 247.72909 | R36: 353.8554 | S36: 428.19184 | T36: 479.08548 | U36: 483.1432 | V36: 564.13113 | W36: 709.18934 | X36: 947.75285 | Y36: 1181.6033 | Z36: 1154.1835 | AA36: 1054.0384 | AB36: 1176.8124 | AC36: 1202.976 | AD36: 1042.2427 | AE36: 1253.561 | AF36: 1701.6752 | AG36: 2203.6576 | AH36: 2477.9754 | AI36: 2945.832 | AJ36: 2972.7267 | AK36: 3040.9604 | AL36: 2973.3804 | AM36: 2970.1226 | AN36: 3219.9121 | AO36: 3221.6762 | AP36: 3258.9803 | AQ36: 3039.9707 | AR36: 3405.8126 | AS36: 3522.3087 | AT36: 3278.0082 | AU36: 3190.6155 | AV36: 4330.9449 | AW36: 5073.5376 | AX36: 5520.1247 | AY36: 5516.0392 | AZ36: 5832.7339 | BA36: 5713.535 | BB36: 5255.7685 | BC36: 6434.8157 | BD36: 7617.3251 | BE36: 7070.3766 | BF36: 7224.9652 | BG36: 7780.6384 | BH36: 6799.8752 | BI36: 7243.853 | BJ36: 7893.2101 | BK36: 8279.6014 | BL36: 7961.3381
A37: Central African Republic | B37: CAF | C37: GDP per capita (current US$) | D37: NY.GDP.PCAP.CD | E37: 74.687347 | F37: 80.687588 | G37: 80.212608 | H37: 81.918169 | I37: 88.290226 | J37: 91.830375 | K37: 94.398236 | L37: 95.896708 | M37: 109.94616 | N37: 105.70764 | O37: 104.41277 | P37: 109.4533 | Q37: 123.31092 | R37: 143.11562 | S37: 146.22762 | T37: 193.35498 | U37: 225.91351 | V37: 248.68542 | W37: 292.46987 | X37: 327.34138 | Y37: 362.40064 | Z37: 306.8321 | AA37: 320.43066 | AB37: 273.50195 | AC37: 257.35364 | AD37: 340.20152 | AE37: 432.01242 | AF37: 453.74553 | AG37: 469.52934 | AH37: 449.39906 | AI37: 513.30528 | AJ37: 478.50294 | AK37: 477.12232 | AL37: 419.80257 | AM37: 271.50567 | AN37: 346.10884 | AO37: 304.63126 | AP37: 276.42127 | AQ37: 278.33134 | AR37: 280.90882 | AS37: 251.20688 | AT37: 250.35701 | AU37: 260.74553 | AV37: 293.66185 | AW37: 320.73746 | AX37: 331.16292 | AY37: 354.67138 | AZ37: 404.37396 | BA37: 464.56142 | BB37: 474.70541 | BC37: 488.4214 | BD37: 551.7501 | BE37: 565.8007 | BF37: 380.29817 | BG37: 424.44875 | BH37: 377.423 | BI37: 402.19129 | BJ37: 450.90024 | BK37: 475.95361 | BL37: 467.90744
A38: Canada | B38: CAN | C38: GDP per capita (current US$) | D38: NY.GDP.PCAP.CD | E38: 2259.2943 | F38: 2240.433 | G38: 2268.5853 | H38: 2374.4984 | I38: 2555.1111 | J38: 2770.3618 | K38: 3047.1061 | L38: 3217.1593 | M38: 3462.6789 | N38: 3763.9534 | O38: 4121.9328 | P38: 4520.1629 | Q38: 5089.5879 | R38: 5838.6609 | S38: 7033.011 | T38: 7511.2113 | U38: 8809.2646 | V38: 8919.0575 | W38: 9123.6913 | X38: 10043.661 | Y38: 11170.564 | Z38: 12337.466 | AA38: 12481.875 | AB38: 13425.122 | AC38: 13877.917 | AD38: 14114.808 | AE38: 14461.069 | AF38: 16308.967 | AG38: 18936.964 | AH38: 20715.631 | AI38: 21448.362 | AJ38: 21768.343 | AK38: 20879.848 | AL38: 20121.161 | AM38: 19935.381 | AN38: 20613.788 | AO38: 21227.348 | AP38: 21829.233 | AQ38: 20952.069 | AR38: 22238.665 | AS38: 24190.25 | AT38: 23738.181 | AU38: 24169.285 | AV38: 28200.658 | AW38: 32034.308 | AX38: 36266.187 | AY38: 40385.87 | AZ38: 44543.041 | BA38: 46594.451 | BB38: 40773.062 | BC38: 47448.013 | BD38: 52087.446 | BE38: 52678.39 | BF38: 52652.594 | BG38: 50893.447 | BH38: 43585.512 | BI38: 42322.485 | BJ38: 45148.553 | BK38: 46313.171 | BL38: 46194.725
A39: Central Europe and the Baltics | B39: CEB | C39: GDP per capita (current US$) | D39: NY.GDP.PCAP.CD | AI39: 2370.2223 | AJ39: 2202.7518 | AK39: 2355.4567 | AL39: 2479.3119 | AM39: 2808.6703 | AN39: 3572.6475 | AO39: 3786.3073 | AP39: 3739.6335 | AQ39: 4099.5827 | AR39: 3979.9473 | AS39: 3942.4382 | AT39: 4347.2763 | AU39: 4929.7605 | AV39: 5936.2096 | AW39: 7164.8033 | AX39: 8347.8228 | AY39: 9468.426 | AZ39: 12004.032 | BA39: 14576.991 | BB39: 12293.392 | BC39: 12576.042 | BD39: 13889.386 | BE39: 13015.829 | BF39: 13718.098 | BG39: 14161.907 | BH39: 12493.714 | BI39: 12792.514 | BJ39: 14198.13 | BK39: 15966.668 | BL39: 16184.332
A40: Switzerland | B40: CHE | C40: GDP per capita (current US$) | D40: NY.GDP.PCAP.CD | E40: 1787.3603 | F40: 1971.3163 | G40: 2131.3917 | H40: 2294.1828 | I40: 2501.2932 | J40: 2620.4755 | K40: 2784.7335 | L40: 2960.7226 | M40: 3121.889 | N40: 3344.7836 | O40: 3927.2865 | P40: 4694.7172 | Q40: 5714.3409 | R40: 7628.3965 | S40: 8743.9927 | T40: 10028.987 | U40: 10550.301 | V40: 11306.424 | W40: 15810.63 | X40: 17736.553 | Y40: 18832.197 | Z40: 17153.401 | AA40: 17478.656 | AB40: 17341.995 | AC40: 16499.147 | AD40: 16655.337 | AE40: 23751.45 | AF40: 29558.895 | AG40: 31743.653 | AH40: 30401.892 | AI40: 38428.386 | AJ40: 38399.211 | AK40: 39534.542 | AL40: 38100.737 | AM40: 41843.757 | AN40: 48662.44 | AO40: 46676.851 | AP40: 40417.962 | AQ40: 41497.203 | AR40: 40581.307 | AS40: 37868.323 | AT40: 38538.99 | AU40: 41376.394 | AV40: 48087.583 | AW40: 53340.148 | AX40: 54952.674 | AY40: 57579.502 | AZ40: 63555.237 | BA40: 72487.846 | BB40: 69927.469 | BC40: 74605.721 | BD40: 88415.628 | BE40: 83538.23 | BF40: 85112.464 | BG40: 86605.563 | BH40: 82081.597 | BI40: 80172.232 | BJ40: 80449.995 | BK40: 82818.108 | BL40: 81993.727
A41: Channel Islands | B41: CHI | C41: GDP per capita (current US$) | D41: NY.GDP.PCAP.CD | AQ41: 40585.383 | AR41: 42443.432 | AS41: 43381.658 | AT41: 41804.371 | AU41: 44544.433 | AV41: 48859.483 | AW41: 56753.386 | AX41: 58197.449 | AY41: 63239.654 | AZ41: 74462.647
A42: Chile | B42: CHL | C42: GDP per capita (current US$) | D42: NY.GDP.PCAP.CD | E42: 505.3492 | F42: 555.13393 | G42: 638.94521 | H42: 655.25248 | I42: 678.12788 | J42: 670.39464 | K42: 772.72605 | L42: 753.12763 | M42: 756.91248 | N42: 870.31912 | O42: 932.86157 | P42: 1094.681 | Q42: 1173.2185 | R42: 1640.0294 | S42: 1554.3885 | T42: 719.59936 | U42: 961.42443 | V42: 1278.3279 | W42: 1441.9421 | X42: 1937.2666 | Y42: 2542.7643 | Z42: 2979.6094 | AA42: 2156.5127 | AB42: 1709.4414 | AC42: 1624.6322 | AD42: 1444.2804 | AE42: 1517.8626 | AF42: 1760.3054 | AG42: 2026.8385 | AH42: 2288.5549 | AI42: 2494.5257 | AJ42: 2803.5621 | AK42: 3350.2138 | AL42: 3535.1736 | AM42: 4024.2169 | AN42: 5107.2768 | AO42: 5349.8041 | AP42: 5745.3738 | AQ42: 5446.5806 | AR42: 4957.7779 | AS42: 5074.9016 | AT42: 4574.5944 | AU42: 4446.2505 | AV42: 4772.5628 | AW42: 6194.8531 | AX42: 7598.5251 | AY42: 9464.5502 | AZ42: 10502.355 | BA42: 10751.48 | BB42: 10208.907 | BC42: 12808.035 | BD42: 14637.24 | BE42: 15351.551 | BF42: 15842.941 | BG42: 14670.997 | BH42: 13574.172 | BI42: 13753.594 | BJ42: 14999.37 | BK42: 15924.794 | BL42: 14896.454
A43: China | B43: CHN | C43: GDP per capita (current US$) | D43: NY.GDP.PCAP.CD | E43: 89.520542 | F43: 75.805838 | G43: 70.909412 | H43: 74.313643 | I43: 85.498555 | J43: 98.486778 | K43: 104.32457 | L43: 96.589532 | M43: 91.472718 | N43: 100.1299 | O43: 113.16299 | P43: 118.65458 | Q43: 131.88356 | R43: 157.09037 | S43: 160.14009 | T43: 178.34182 | U43: 165.40554 | V43: 185.42283 | W43: 156.39639 | X43: 183.98315 | Y43: 194.80472 | Z43: 197.07147 | AA43: 203.33492 | AB43: 225.43193 | AC43: 250.71397 | AD43: 294.45885 | AE43: 281.92812 | AF43: 251.81196 | AG43: 283.5377 | AH43: 310.88191 | AI43: 317.88467 | AJ43: 333.14215 | AK43: 366.46069 | AL43: 377.38984 | AM43: 473.49228 | AN43: 609.65668 | AO43: 709.41376 | AP43: 781.74416 | AQ43: 828.58048 | AR43: 873.28706 | AS43: 959.37248 | AT43: 1053.1082 | AU43: 1148.5083 | AV43: 1288.6433 | AW43: 1508.6681 | AX43: 1753.4178 | AY43: 2099.2294 | AZ43: 2693.9698 | BA43: 3468.3045 | BB43: 3832.236 | BC43: 4550.4536 | BD43: 5618.1325 | BE43: 6316.9189 | BF43: 7050.6459 | BG43: 7678.5994 | BH43: 8066.9424 | BI43: 8147.9381 | BJ43: 8879.4381 | BK43: 9976.6768 | BL43: 10261.679
A44: Cote d'Ivoire | B44: CIV | C44: GDP per capita (current US$) | D44: NY.GDP.PCAP.CD | E44: 155.8999 | F44: 170.24277 | G44: 171.12819 | H44: 194.21263 | I44: 226.22704 | J44: 217.60239 | K44: 233.61464 | L44: 238.3107 | M44: 271.85329 | N44: 277.97201 | O44: 285.27337 | P44: 297.27986 | Q44: 331.6693 | R44: 429.41345 | S44: 501.5535 | T44: 607.23557 | U44: 694.38314 | V44: 891.63473 | W44: 1074.8619 | X44: 1189.5698 | Y44: 1266.6242 | Z44: 1004.6341 | AA44: 863.33363 | AB44: 747.75692 | AC44: 717.89737 | AD44: 703.52008 | AE44: 888.52746 | AF44: 942.93048 | AG44: 924.32658 | AH44: 848.28984 | AI44: 905.32172 | AJ44: 848.75291 | AK44: 870.48118 | AL44: 832.28275 | AM44: 605.26359 | AN44: 774.67121 | AO44: 827.76201 | AP44: 774.72763 | AQ44: 809.01269 | AR44: 771.96841 | AS44: 651.30591 | AT44: 664.12767 | AU44: 716.53027 | AV44: 869.7126 | AW44: 921.20127 | AX44: 930.82982 | AY44: 949.13183 | AZ44: 1061.154 | BA44: 1235.6134 | BB44: 1210.2954 | BC44: 1213.1126 | BD44: 1208.583 | BE44: 1243.2735 | BF44: 1415.8718 | BG44: 1561.4637 | BH44: 1972.5461 | BI44: 2013.3825 | BJ44: 2111.0271 | BK44: 2302.613 | BL44: 2286.1628
A45: Cameroon | B45: CMR | C45: GDP per capita (current US$) | D45: NY.GDP.PCAP.CD | E45: 119.51918 | F45: 124.42673 | G45: 129.54414 | H45: 131.13641 | I45: 138.64603 | J45: 141.01217 | K45: 144.38 | L45: 154.3315 | M45: 169.81245 | N45: 181.28077 | O45: 177.92095 | P45: 184.4624 | Q45: 208.37545 | R45: 249.36411 | S45: 311.21949 | T45: 369.4472 | U45: 401.41303 | V45: 426.79468 | W45: 543.02118 | X45: 694.68628 | Y45: 781.86279 | Z45: 859.12311 | AA45: 798.85039 | AB45: 780.61222 | AC45: 799.54765 | AD45: 809.09349 | AE45: 1021.7093 | AF45: 1146.4354 | AG45: 1128.019 | AH45: 974.99128 | AI45: 946.64641 | AJ45: 1024.4241 | AK45: 911.74142 | AL45: 1204.763 | AM45: 801.1617 | AN45: 709.11483 | AO45: 752.5251 | AP45: 755.23971 | AQ45: 720.79697 | AR45: 740.99656 | AS45: 649.99185 | AT45: 651.10091 | AU45: 707.88757 | AV45: 865.95814 | AW45: 1009.9431 | AX45: 1011.8801 | AY45: 1062.1374 | AZ45: 1194.0699 | BA45: 1371.7467 | BB45: 1314.706 | BC45: 1286.5156 | BD45: 1405.0944 | BE45: 1354.5456 | BF45: 1465.6388 | BG45: 1542.6203 | BH45: 1327.503 | BI45: 1364.3301 | BJ45: 1425.1078 | BK45: 1534.4913 | BL45: 1497.9092
A46: Congo, Dem. Rep. | B46: COD | C46: GDP per capita (current US$) | D46: NY.GDP.PCAP.CD | E46: 220.31406 | F46: 197.39137 | G46: 235.63348 | H46: 377.42983 | I46: 170.46699 | J46: 232.81111 | K46: 253.75925 | L46: 184.13039 | M46: 206.71491 | N46: 258.6065 | O46: 243.74974 | P46: 272.06536 | Q46: 292.29708 | R46: 362.84365 | S46: 430.70198 | T46: 446.97566 | U46: 409.52433 | V46: 509.06671 | W46: 615.97896 | X46: 587.15172 | Y46: 546.11244 | Z46: 463.67129 | AA46: 492.53253 | AB46: 387.50776 | AC46: 269.84263 | AD46: 240.78804 | AE46: 263.83137 | AF46: 243.00474 | AG46: 273.12784 | AH46: 269.59289 | AI46: 270.13054 | AJ46: 268.05646 | AK46: 220.37186 | AL46: 275.82197 | AM46: 144.59508 | AN46: 135.73715 | AO46: 134.98192 | AP46: 138.97405 | AQ46: 138.58631 | AR46: 102.59798 | AS46: 405.21625 | AT46: 153.59101 | AU46: 175.00997 | AV46: 173.79614 | AW46: 194.03996 | AX46: 218.38619 | AY46: 255.43308 | AZ46: 286.33049 | BA46: 327.56372 | BB46: 298.61968 | BC46: 334.02157 | BD46: 387.08247 | BE46: 424.60039 | BF46: 457.96373 | BG46: 486.78708 | BH46: 497.31696 | BI46: 471.31884 | BJ46: 467.07424 | BK46: 557.06442 | BL46: 545.21621
A47: Congo, Rep. | B47: COG | C47: GDP per capita (current US$) | D47: NY.GDP.PCAP.CD | E47: 129.37046 | F47: 145.4064 | G47: 155.73824 | H47: 157.05587 | I47: 165.00946 | J47: 171.6457 | K47: 185.89179 | L47: 194.66129 | M47: 200.39518 | N47: 205.53355 | O47: 207.22271 | P47: 235.8359 | Q47: 291.975 | R47: 374.12641 | S47: 392.32108 | T47: 499.20326 | U47: 476.85138 | V47: 469.69053 | W47: 523.91045 | X47: 694.17642 | Y47: 959.42642 | Z47: 1088.9749 | AA47: 1146.3044 | AB47: 1080.8224 | AC47: 1098.4411 | AD47: 1051.8716 | AE47: 875.45084 | AF47: 1058.2284 | AG47: 991.51737 | AH47: 1042.0497 | AI47: 1187.5513 | AJ47: 1124.9011 | AK47: 1178.0238 | AL47: 749.63486 | AM47: 672.16319 | AN47: 781.52357 | AO47: 912.01399 | AP47: 810.07749 | AQ47: 660.47237 | AR47: 774.71169 | AS47: 1029.577 | AT47: 868.33995 | AU47: 912.27815 | AV47: 1026.1077 | AW47: 1324.2191 | AX47: 1680.2046 | AY47: 2064.3445 | AZ47: 2165.7458 | BA47: 2956.2644 | BB47: 2314.266 | BC47: 2812.436 | BD47: 3286.6945 | BE47: 3032.4939 | BF47: 3047.9308 | BG47: 2996.918 | BH47: 1762.032 | BI47: 1815.2958 | BJ47: 1767.8945 | BK47: 2223.8545 | BL47: 2011.0724
A48: Colombia | B48: COL | C48: GDP per capita (current US$) | D48: NY.GDP.PCAP.CD | E48: 251.04137 | F48: 274.05236 | G48: 289.91796 | H48: 274.31494 | I48: 328.65507 | J48: 307.64681 | K48: 281.56596 | L48: 293.64423 | M48: 292.25757 | N48: 307.99517 | O48: 335.11819 | P48: 355.40757 | Q48: 385.11259 | R48: 448.03372 | S48: 525.52582 | T48: 544.29079 | U48: 623.42869 | V48: 773.74578 | W48: 904.01055 | X48: 1061.8484 | Y48: 1241.6397 | Z48: 1323.3761 | AA48: 1386.6732 | AB48: 1348.8043 | AC48: 1304.1768 | AD48: 1165.0421 | AE48: 1142.9394 | AF48: 1165.9825 | AG48: 1232.2262 | AH48: 1218.2109 | AI48: 1445.3284 | AJ48: 1456.694 | AK48: 1697.1129 | AL48: 1893.5421 | AM48: 2284.8387 | AN48: 2539.9129 | AO48: 2620.5388 | AP48: 2827.3798 | AQ48: 2566.0241 | AR48: 2209.9315 | AS48: 2520.4809 | AT48: 2439.6818 | AU48: 2396.6273 | AV48: 2281.402 | AW48: 2782.6231 | AX48: 3414.4658 | AY48: 3741.0932 | AZ48: 4714.0725 | BA48: 5472.5361 | BB48: 5193.2415 | BC48: 6336.7092 | BD48: 7335.1105 | BE48: 8050.0584 | BF48: 8218.034 | BG48: 8114.0841 | BH48: 6175.8761 | BI48: 5871.2236 | BJ48: 6377.8514 | BK48: 6718.5853 | BL48: 6432.3876
A49: Comoros | B49: COM | C49: GDP per capita (current US$) | D49: NY.GDP.PCAP.CD | Y49: 689.40297 | Z49: 618.2187 | AA49: 562.81158 | AB49: 570.14055 | AC49: 534.63209 | AD49: 553.6324 | AE49: 763.33579 | AF49: 896.11652 | AG49: 918.90213 | AH49: 854.47803 | AI49: 1043.8008 | AJ49: 1000.5587 | AK49: 1047.9796 | AL49: 1008.0295 | AM49: 690.47173 | AN49: 838.17168 | AO49: 810.54423 | AP49: 726.05521 | AQ49: 718.11709 | AR49: 723.18509 | AS49: 645.81869 | AT49: 680.31854 | AU49: 744.47517 | AV49: 935.61152 | AW49: 1059.1769 | AX49: 1068.6003 | AY49: 1113.9578 | AZ49: 1238.4615 | BA49: 1387.5946 | BB49: 1339.3372 | BC49: 1316.4988 | BD49: 1447.9636 | BE49: 1403.3486 | BF49: 1505.3495 | BG49: 1513.8304 | BH49: 1242.6032 | BI49: 1273.059 | BJ49: 1323.8116 | BK49: 1415.9553 | BL49: 1393.5224
A50: Cabo Verde | B50: CPV | C50: GDP per capita (current US$) | D50: NY.GDP.PCAP.CD | Y50: 501.13926 | Z50: 483.1286 | AA50: 477.92301 | AB50: 461.23385 | AC50: 431.24319 | AD50: 441.89245 | AE50: 602.15279 | AF50: 732.56784 | AG50: 811.39336 | AH50: 807.56483 | AI50: 908.09619 | AJ50: 923.74161 | AK50: 1003.9465 | AL50: 1339.7442 | AM50: 1080.1623 | AN50: 1261.1162 | AO50: 1269.1206 | AP50: 1213.5998 | AQ50: 1265.1948 | AR50: 1408.9996 | AS50: 1259.3237 | AT50: 1292.2028 | AU50: 1401.9037 | AV50: 1809.0899 | AW50: 2024.2752 | AX50: 2099.1575 | AY50: 2361.3851 | AZ50: 3186.8269 | BA50: 3721.2509 | BB50: 3517.4012 | BC50: 3378.2549 | BD50: 3740.3891 | BE50: 3447.524 | BF50: 3615.979 | BG50: 3588.6741 | BH50: 3043.014 | BI50: 3130.9634 | BJ50: 3292.6458 | BK50: 3617.3275 | BL50: 3603.7818
