Workbook
Name IQ_CH: 110000
Name IQ_CQ: 5000
Name IQ_CY: 10000
Name IQ_DAILY: 500000
Name IQ_FH: 100000
Name IQ_FQ: 500
Name IQ_FY: 1000
Name IQ_LTM: 2000
Name IQ_MONTH: 15000
Name IQ_NTM: 6000
Name IQ_WEEK: 50000
Name IQ_YTD: 3000
Name Net_Generation_by_State__Type_1: #REF!
Name Net_Generation_by_State__Type_of_Producer__Energy_Source: #REF!
Name Net_Generation_by_State__Type_of_Producer__Energy_Source: #REF!

Sheet About
A1: BRPSDbS BAU Renewable Portfolio Std Percentage by Subregion
A2: BRPSDbS BAU Electricity Shares by Subregion
A4: Sources: | B4: RPO targets and Compliance by state
B5: Ministry of Power, Govt of India
B6: 2023
B7: Rajya Sabha report
B8: AS122.pdf (sansad.in)
B9: Annexure 1 and Annexure 2
B10: RPO Compliance by state, 2023
B11: EIA
B12: 2023
B13: EIA-923 Power Plant Operations Report
B14: https://www.eia.gov/electricity/data/state/
B15: Net Generation by State by Type of Producer by Energy Source (EIA-906, EIA-920, and EIA-923)
B17: State's share of generation
B18: Press Information Bureau
B19: 2023
B20: The State-wise power supply position for the year 2021-22 and current year 2022-23
B21: https://pib.gov.in/PressReleaseIframePage.aspx?PRID=1909932
B22: Annexure 1 Table
B24: Actual share of RE
B25: CEA
B26: 2024
B27: All India Electricity Statistics
B28: https://cea.nic.in/wp-content/uploads/general/2024/General_Review_2024_2.pdf
B29: Page 19
A30: Note:
A31: The purpose of this variable is to specify the renewable portfolio standard requirement that must be met in the BAU case (which the user may increase
A32: via a policy lever, affecting the policy case).
A35: Notes on Output Data Formatting
A36: Note that the blue output tab "BRPSDbS-RPS-percentages" is populating the "Future Year" subscript. It is not a normal time-series variable.
A37: Therefore, it must include a value for every year that exists in the Future Year subscript (and no other years should be present).
A38: It is designed this way for compatibility with the RPS foresight option (enabled via a control setting).
A40: The blue output tab "BRPSDbS-electricity-shares" contains the share of electricity sales in each subregion.
A41: The data in this tab must sum to 1.
A44: NOtes for India
A45: Although India has RPS as a policy instrument, it has been subject to consistent non-compliance by across states. Therefore, we set an RPO mandate of 30% by 2030 which is slightly more than the actual share of generation by states.
A46: This is assumed to remain constant from 2030
A47: States are assumed to comply have the same RPS targets in each year

Sheet India Data
B2: pib.gov.in/PressReleaseIframePage.aspx?PRID=1909932 | K2: Source: | L2: AS122.pdf (sansad.in)
B15: YEar | C15: MoP's RPO Target
B16: 2023 | C16: 24.61
B17: 2024 | C17: 27.08
B18: 2025 | C18: 29.91
B19: 2026 | C19: 33.01
B20: 2027 | C20: 35.95
B21: 2028 | C21: 38.81
B22: 2029 | C22: 41.36
B23: 2030 | C23: 43.33

Sheet India's generation numbers
A1: Column1 | B1: Column2 | C1: Column3 | D1: Column4 | E1: Column5 | F1: Column6
A2: State/ System/Region | B2: April, 2022 - February, 2023 | C2: April, 2022 - February, 2023 | D2: April, 2022 - February, 2023 | E2: April, 2022 - February, 2023 | F2: State's share of energy supplied
B3: Energy requirement | C3: Energy supplied | D3: Energy not supplied | E3: Energy not supplied
B4: ( MU ) | C4: ( MU ) | D4: ( MU ) | E4: ( % )
A5: Chandigarh | B5: 1,687 | C5: 1,687 | D5: 0 | E5: 0.0 | F5: =Table_2[[#This Row],[Column3]]/C46 -> #VALUE!
A6: Delhi | B6: 33,012 | C6: 33,002 | D6: 10 | E6: 0.0
A7: Haryana | B7: 57,564 | C7: 57,061 | D7: 503 | E7: 0.9
A8: Himachal Pradesh | B8: 11,601 | C8: 11,497 | D8: 104 | E8: 0.9
A9: UT of J&K and Ladakh | B9: 17,914 | C9: 17,604 | D9: 309 | E9: 1.7
A10: Punjab | B10: 65,282 | C10: 64,996 | D10: 286 | E10: 0.4
A11: Rajasthan | B11: 94,270 | C11: 92,557 | D11: 1,712 | E11: 1.8
A12: Uttar Pradesh | B12: 1,34,645 | C12: 1,33,449 | D12: 1,196 | E12: 0.9
A13: Uttarakhand | B13: 14,496 | C13: 14,247 | D13: 249 | E13: 1.7
A14: Northern Region | B14: 4,31,544 | C14: 4,27,175 | D14: 4,369 | E14: 1.0
A15: Chhattisgarh | B15: 35,450 | C15: 35,381 | D15: 69 | E15: 0.2
A16: Gujarat | B16: 1,26,657 | C16: 1,26,613 | D16: 44 | E16: 0.0
A17: Madhya Pradesh | B17: 84,434 | C17: 84,105 | D17: 329 | E17: 0.4
... A49: Note: Power Supply Position Report has been compiled based on the data furnished by State Utilities/Electricity Departments. The MU figures have been rounded off to nearest unit place. | B49: Note: Power Supply Position Report has been compiled based on the data furnished by State Utilities/Electricity Departments. The MU figures have been rounded off to nearest unit place. | C49: Note: Power Supply Position Report has been compiled based on the data furnished by State Utilities/Electricity Departments. The MU figures have been rounded off to nearest unit place. | D49: Note: Power Supply Position Report has been compiled based on the data furnished by State Utilities/Electricity Departments. The MU figures have been rounded off to nearest unit place. | E49: Note: Power Supply Position Report has been compiled based on the data furnished by State Utilities/Electricity Departments. The MU figures have been rounded off to nearest unit place.
A52: Chandigarh | B52: 1687 | C52: 1687 | D52: 0 | E52: 0.0
A53: Delhi | B53: 33012 | C53: 33002 | D53: 10 | E53: 0.0 | F53: =C53/$C$94 -> 0.024081229
A54: Haryana | B54: 57564 | C54: 57061 | D54: 503 | E54: 0.9 | F54: =C54/$C$94 -> 0.041636841
A55: Himachal Pradesh | B55: 11601 | C55: 11497 | D55: 104 | E55: 0.9 | F55: =C55/$C$94 -> 0.0083892458
A56: UT of J&K and Ladakh | B56: 17914 | C56: 17604 | D56: 309 | E56: 1.7 | F56: =C56/$C$94 -> 0.012845463
A57: Punjab | B57: 65282 | C57: 64996 | D57: 286 | E57: 0.4 | F57: =C57/$C$94 -> 0.047426931
A58: Rajasthan | B58: 94270 | C58: 92557 | D58: 1,712 | E58: 1.8 | F58: =C58/$C$94 -> 0.067537917
A59: Uttar Pradesh | B59: 134645 | C59: 133449 | D59: 1,196 | E59: 0.9 | F59: =C59/$C$94 -> 0.0973764
A60: Uttarakhand | B60: 14496 | C60: 14247 | D60: 249 | E60: 1.7 | F60: =C60/$C$94 -> 0.010395893
A61: Northern Region | B61: 431544 | D61: 4,369 | E61: 1.0 | F61: =C61/$C$94 -> 0
A62: Chhattisgarh | B62: 35450 | C62: 35381 | D62: 69 | E62: 0.2 | F62: =C62/$C$94 -> 0.025817162
A63: Gujarat | B63: 126657 | C63: 126613 | D63: 44 | E63: 0.0 | F63: =C63/$C$94 -> 0.092388239
A64: Madhya Pradesh | B64: 84434 | C64: 84105 | D64: 329 | E64: 0.4 | F64: =C64/$C$94 -> 0.061370577
A65: Maharashtra | B65: 169433 | C65: 169322 | D65: 111 | E65: 0.1 | F65: =C65/$C$94 -> 0.12355257
A66: Dadra & Nagar Haveli and Daman & Diu | B66: 9169 | C66: 9169 | D66: 0 | E66: 0.0 | F66: =C66/$C$94 -> 0.0066905275
A67: Goa | B67: 4279 | C67: 4279 | D67: 0 | E67: 0.0 | F67: =C67/$C$94 -> 0.0031223435
A68: Western Region | B68: 433746 | D68: 553 | E68: 0.1 | F68: =C68/$C$94 -> 0
A69: Andhra Pradesh | B69: 65604 | C69: 65194 | D69: 410 | E69: 0.6 | F69: =C69/$C$94 -> 0.047571409
A70: Telangana | B70: 68609 | C70: 68576 | D70: 34 | E70: 0.0 | F70: =C70/$C$94 -> 0.050039221
A71: Karnataka | B71: 67159 | C71: 67133 | D71: 26 | E71: 0.0 | F71: =C71/$C$94 -> 0.048986278
A72: Kerala | B72: 25028 | C72: 25007 | D72: 21 | E72: 0.1 | F72: =C72/$C$94 -> 0.018247358
A73: Tamil Nadu | B73: 103794 | C73: 103718 | D73: 77 | E73: 0.1 | F73: =C73/$C$94 -> 0.075681987
A74: Puducherry | B74: 2806 | C74: 2805 | D74: 1 | E74: 0.0 | F74: =C74/$C$94 -> 0.0020467804
A75: Lakshadweep # | B75: 58 | C75: 58 | D75: 0 | E75: 0.0 | F75: =C75/$C$94 -> 4.2322019e-05
A76: Southern Region | B76: 333043 | D76: 567 | E76: 0.2 | F76: =C76/$C$94 -> 0
A77: Bihar | B77: 36635 | C77: 35873 | D77: 762 | E77: 2.1 | F77: =C77/$C$94 -> 0.026176169
A78: DVC | B78: 23858 | C78: 23850 | D78: 8 | E78: 0.0 | F78: =C78/$C$94 -> 0.017403106
A79: Jharkhand | B79: 12006 | C79: 11099 | D79: 907 | E79: 7.6 | F79: =C79/$C$94 -> 0.0080988292
A80: Odisha | B80: 39074 | C80: 39028 | D80: 46 | E80: 0.1 | F80: =C80/$C$94 -> 0.028478341
A81: West Bengal | B81: 55133 | C81: 55066 | D81: 67 | E81: 0.1 | F81: =C81/$C$94 -> 0.040181109
A82: Sikkim | B82: 539 | C82: 539 | D82: 0 | E82: 0.0 | F82: =C82/$C$94 -> 0.00039330291
A83: Andaman- Nicobar Islands # | B83: 318 | C83: 318 | D83: 0 | E83: 0.0 | F83: =C83/$C$94 -> 0.00023204142
A84: Eastern Region | B84: 167298 | D84: 1789 | E84: 1.1 | F84: =C84/$C$94 -> 0
A85: Arunachal Pradesh | B85: 823 | C85: 803 | D85: 20 | E85: 2.4 | F85: =C85/$C$94 -> 0.00058594106
A86: Assam | B86: 10619 | C86: 10612 | D86: 7 | E86: 0.1 | F86: =C86/$C$94 -> 0.0077434702
A87: Manipur | B87: 926 | C87: 925 | D87: 1 | E87: 0.1 | F87: =C87/$C$94 -> 0.00067496324
A88: Meghalaya | B88: 2050 | C88: 2050 | D88: 0 | E88: 0.0 | F88: =C88/$C$94 -> 0.0014958645
A89: Mizoram | B89: 592 | C89: 592 | D89: 0 | E89: 0.0 | F89: =C89/$C$94 -> 0.00043197647
A90: Nagaland | B90: 844 | C90: 802 | D90: 41 | E90: 4.9 | F90: =C90/$C$94 -> 0.00058521137
A91: Tripura * | B91: 1428 | C91: 1428 | D91: 0 | E91: 0.0 | F91: =C91/$C$94 -> 0.0010419973
A92: North-Eastern Region | B92: 17289 | D92: 70 | E92: 0.4 | F92: =C92/$C$94 -> 0 | G92: =SUM(F52:F92) -> 0.99876901
A93: All India | B93: 1382920 | C93: 1375571 | D93: 7,349 | E93: 0.5 | F93: =C93/$C$94 -> 1.0037404
C94: =SUM(C52:C92) -> 1370445

Sheet RPO State forecasts
A1: Looking at past trends, the share of RE (including hydro) in generation has only grown by 2% in the last decade. Policies (like the RPO) can drive this share higher in the future
A2: However, rampant non-compliance may make the 43% RPO target by 2030 unfeasable. We instead set a target of 30% RE generation by 2030 for all states as a proxy that may be replaces later
A3: Unit: dimensionless (share of RPS-qualifying electricity) | B3: 2016 | C3: 2017 | D3: 2018 | E3: 2019 | F3: 2020 | G3: 2021 | H3: 2022 | I3: 2023 | J3: 2024 | K3: 2025 | L3: 2026 | M3: 2027 | N3: 2028 | O3: 2029 | P3: 2030
A4: Chandigarh
A5: Delhi | AA5: Year | AB5: RE+Hydro | AC5: RE (without hydro) | AD5: Thermal | AE5: Nuclear | AF5: Total gen (check) | AG5: Total gen | AH5: Share of RE (+hydro)
A6: Haryana | AA6: 2013 | AB6: =65520+134847 -> 200367 | AC6: 134847 | AD6: 792054 | AE6: 34228 | AF6: =AB6+792054+34228 -> 1026649 | AG6: =AE6+AD6+AB6 -> 1026649 | AH6: =AB6/AG6 -> 0.19516602
A7: Himachal Pradesh | AA7: 2014 | AB7: =61785+129244 -> 191029 | AC7: 129244 | AD7: 877941 | AE7: 36102 | AG7: =AE7+AD7+AB7 -> 1105072 | AH7: =AB7/AG7 -> 0.17286566
A8: UT of J&K and Ladakh | AA8: 2015 | AB8: =65781+121377 -> 187158 | AC8: 121377 | AD8: 943013 | AE8: 37413 | AG8: =AE8+AD8+AB8 -> 1167584 | AH8: =AB8/AG8 -> 0.16029511
A9: Punjab | AA9: 2016 | AB9: =81548+122378 -> 203926 | AC9: 122378 | AD9: 993516 | AE9: 37916 | AG9: =AE9+AD9+AB9 -> 1235358 | AH9: =AB9/AG9 -> 0.16507442
A10: Rajasthan | AA10: 2017 | AB10: =101839+126123 -> 227962 | AC10: 126123 | AD10: 1037146 | AE10: 38346 | AG10: =AE10+AD10+AB10 -> 1303454 | AH10: =AB10/AG10 -> 0.17489071
A11: Uttar Pradesh | AA11: 2018 | AB11: =126759+134894 -> 261653 | AC11: 134894 | AD11: 1072314 | AE11: 37813 | AG11: =AE11+AD11+AB11 -> 1371780 | AH11: =AB11/AG11 -> 0.19073977
A12: Uttarakhand | AA12: 2019 | AB12: =138337+155769 -> 294106 | AC12: 155769 | AD12: 1042838 | AE12: 46472 | AG12: =AE12+AD12+AB12 -> 1383416 | AH12: =AB12/AG12 -> 0.21259404
A13: Chhattisgarh | AA13: 2020 | AB13: =147248+150300 -> 297548 | AC13: 150300 | AD13: 1032611 | AE13: 43029 | AG13: =AE13+AD13+AB13 -> 1373188 | AH13: =AB13/AG13 -> 0.2166841
A14: Gujarat | AA14: 2021 | AB14: =170912+151627 -> 322539 | AC14: 151627 | AD14: 1114811 | AE14: 47112 | AG14: =AE14+AD14+AB14 -> 1484462 | AH14: =AB14/AG14 -> 0.2172767
A15: Madhya Pradesh | AA15: 2022 | AB15: =203533+162099 -> 365632 | AC15: 162099 | AD15: 1206390 | AE15: 45861 | AG15: =AE15+AD15+AB15 -> 1617883 | AH15: =AB15/AG15 -> 0.22599409 | AI15: =(AH15-AH6)/AH6 -> 0.15795819 | AJ15: =AH15-AH6 -> 0.030828072
A16: Maharashtra | AA16: 2030 | AH16: =_xlfn.FORECAST.LINEAR(AA16,AH6:AH15,AA6:AA15) -> 0.27108858
A17: Dadra & Nagar Haveli and Daman & Diu
A18: Goa | AA18: shareo
A19: Andhra Pradesh | C19: 0.05 | D19: 0.09 | E19: 0.11 | F19: 0.13 | G19: 0.15 | H19: 0.17 | I19: 0.18 | J19: 0.19 | K19: 0.2 | L19: 0.22 | M19: 0.24 | N19: =_xlfn.FORECAST.LINEAR(N3,$C19:$M19,$C$3:$M$3) -> 0.26036364 | O19: =_xlfn.FORECAST.LINEAR(O3,$C19:$M19,$C$3:$M$3) -> 0.27754545 | P19: =_xlfn.FORECAST.LINEAR(P3,$C19:$M19,$C$3:$M$3) -> 0.29472727
A20: Telangana
A21: Karnataka
A22: Kerala
A23: Tamil Nadu
A24: Puducherry
A25: Lakshadweep
A26: Bihar
A27: DVC
A28: Jharkhand
A29: Odisha
A30: West Bengal | Q30: Source | R30: General_Review_2024_2.pdf
A31: Sikkim
A32: Andaman-Nicobar Islands
A33: Arunachal Pradesh
A34: Assam
A35: Total RPO | I35: 24.61 | J35: 27.08 | K35: 29.91 | L35: 33.01 | M35: 35.95 | N35: 38.81 | O35: 41.36 | P35: 43.33
A36: Actual share of RE | I36: 22.6 | J36: =I36*(1+0.1349) -> 25.64874 | K36: =J36+(J36-I36) -> 28.69748 | L36: =K36+(K36-J36) -> 31.74622 | M36: =L36+(L36-K36) -> 34.79496 | N36: =M36+(M36-L36) -> 37.8437 | O36: =N36+(N36-M36) -> 40.89244 | P36: =O36+(O36-N36) -> 43.94118

Sheet BRPSDbS-electricity-shares
A1: Unit: dimensionless (share of electricity sales by subregion) | B1: Share of electricity
A2: Chandigarh | B2: 0.001230987
A3: Delhi | B3: 0.024081229
A4: Haryana | B4: 0.041636841
A5: Himachal Pradesh | B5: 0.0083892458
A6: UT of JK and Ladakh | B6: 0.012845463
A7: Punjab | B7: 0.047426931
A8: Rajasthan | B8: 0.067537917
A9: Uttar Pradesh | B9: 0.0973764
A10: Uttarakhand | B10: 0.010395893
A11: Chhattisgarh | B11: 0.025817162
A12: Gujarat | B12: 0.092388239
A13: Madhya Pradesh | B13: 0.061370577
... A61: subregion60 | B61: 0

Sheet BRPSDbS-RPS-percentages
A1: Unit: dimensionless (share of RPS-qualifying electricity) | B1: Year2021 | C1: Year2022 | D1: Year2023 | E1: Year2024 | F1: Year2025 | G1: Year2026 | H1: Year2027 | I1: Year2028 | J1: Year2029 | K1: Year2030 | L1: Year2031 | M1: Year2032 | N1: Year2033 | O1: Year2034 | P1: Year2035 | Q1: Year2036 | R1: Year2037 | S1: Year2038 | T1: Year2039 | U1: Year2040 | V1: Year2041 | W1: Year2042 | X1: Year2043 | Y1: Year2044 | Z1: Year2045 | AA1: Year2046 | AB1: Year2047 | AC1: Year2048 | AD1: Year2049 | AE1: Year2050 | AF1: Year2051 | AG1: Year2052 | AH1: Year2053 | AI1: Year2054 | AJ1: Year2055 | AK1: Year2056 | AL1: Year2057 | AM1: Year2058 | AN1: Year2059 | AO1: Year2060 | AP1: Year2061 | AQ1: Year2062 | AR1: Year2063 | AS1: Year2064 | AT1: Year2065 | AU1: Year2066 | AV1: Year2067 | AW1: Year2068 | AX1: Year2069 | AY1: Year2070 | AZ1: Year2071 | BA1: Year2072 | BB1: Year2073 | BC1: Year2074 | BD1: Year2075 | BE1: Year2076 | BF1: Year2077 | BG1: Year2078 | BH1: Year2079 | BI1: Year2080 | BJ1: Year2081 | BK1: Year2082 | BL1: Year2083 | BM1: Year2084 | BN1: Year2085 | BO1: Year2086 | BP1: Year2087 | BQ1: Year2088 | BR1: Year2089 | BS1: Year2090 | BT1: Year2091 | BU1: Year2092 | BV1: Year2093 | BW1: Year2094 | BX1: Year2095 | BY1: Year2096 | BZ1: Year2097 | CA1: Year2098 | CB1: Year2099 | CC1: Year2100
A2: Chandigarh | B2: ='RPO State forecasts'!$AH$14 -> 0.2172767 | C2: =B2+($K2-$B2)/10 -> 0.22554903 | D2: =C2+($K2-$B2)/10 -> 0.23382136 | E2: =D2+($K2-$B2)/10 -> 0.24209369 | F2: =E2+($K2-$B2)/10 -> 0.25036602 | G2: =F2+($K2-$B2)/10 -> 0.25863835 | H2: =G2+($K2-$B2)/10 -> 0.26691068 | I2: =H2+($K2-$B2)/10 -> 0.27518301 | J2: =I2+($K2-$B2)/10 -> 0.28345534 | K2: 0.3 | L2: 0.3 | M2: 0.3 | N2: 0.3 | O2: 0.3 | P2: 0.3 | Q2: 0.3 | R2: 0.3 | S2: 0.3 | T2: 0.3 | U2: 0.3 | V2: 0.3 | W2: 0.3 | X2: 0.3 | Y2: 0.3 | Z2: 0.3 | AA2: 0.3 | AB2: 0.3 | AC2: 0.3 | AD2: 0.3 | AE2: 0.3 | AF2: 0.3 | AG2: 0.3 | AH2: 0.3 | AI2: 0.3 | AJ2: 0.3 | AK2: 0.3 | AL2: 0.3 | AM2: 0.3 | AN2: 0.3 | AO2: 0.3 | AP2: 0.3 | AQ2: 0.3 | AR2: 0.3 | AS2: 0.3 | AT2: 0.3 | AU2: 0.3 | AV2: 0.3 | AW2: 0.3 | AX2: 0.3 | AY2: 0.3 | AZ2: 0.3 | BA2: 0.3 | BB2: 0.3 | BC2: 0.3 | BD2: 0.3 | BE2: 0.3 | BF2: 0.3 | BG2: 0.3 | BH2: 0.3 | BI2: 0.3 | BJ2: 0.3 | BK2: 0.3 | BL2: 0.3 | BM2: 0.3 | BN2: 0.3 | BO2: 0.3 | BP2: 0.3 | BQ2: 0.3 | BR2: 0.3 | BS2: 0.3 | BT2: 0.3 | BU2: 0.3 | BV2: 0.3 | BW2: 0.3 | BX2: 0.3 | BY2: 0.3 | BZ2: 0.3 | CA2: 0.3 | CB2: 0.3 | CC2: 0.3
A3: Delhi | B3: ='RPO State forecasts'!$AH$14 -> 0.2172767 | C3: =B3+($K3-$B3)/10 -> 0.22554903 | D3: =C3+($K3-$B3)/10 -> 0.23382136 | E3: =D3+($K3-$B3)/10 -> 0.24209369 | F3: =E3+($K3-$B3)/10 -> 0.25036602 | G3: =F3+($K3-$B3)/10 -> 0.25863835 | H3: =G3+($K3-$B3)/10 -> 0.26691068 | I3: =H3+($K3-$B3)/10 -> 0.27518301 | J3: =I3+($K3-$B3)/10 -> 0.28345534 | K3: 0.3 | L3: 0.3 | M3: 0.3 | N3: 0.3 | O3: 0.3 | P3: 0.3 | Q3: 0.3 | R3: 0.3 | S3: 0.3 | T3: 0.3 | U3: 0.3 | V3: 0.3 | W3: 0.3 | X3: 0.3 | Y3: 0.3 | Z3: 0.3 | AA3: 0.3 | AB3: 0.3 | AC3: 0.3 | AD3: 0.3 | AE3: 0.3 | AF3: 0.3 | AG3: 0.3 | AH3: 0.3 | AI3: 0.3 | AJ3: 0.3 | AK3: 0.3 | AL3: 0.3 | AM3: 0.3 | AN3: 0.3 | AO3: 0.3 | AP3: 0.3 | AQ3: 0.3 | AR3: 0.3 | AS3: 0.3 | AT3: 0.3 | AU3: 0.3 | AV3: 0.3 | AW3: 0.3 | AX3: 0.3 | AY3: 0.3 | AZ3: 0.3 | BA3: 0.3 | BB3: 0.3 | BC3: 0.3 | BD3: 0.3 | BE3: 0.3 | BF3: 0.3 | BG3: 0.3 | BH3: 0.3 | BI3: 0.3 | BJ3: 0.3 | BK3: 0.3 | BL3: 0.3 | BM3: 0.3 | BN3: 0.3 | BO3: 0.3 | BP3: 0.3 | BQ3: 0.3 | BR3: 0.3 | BS3: 0.3 | BT3: 0.3 | BU3: 0.3 | BV3: 0.3 | BW3: 0.3 | BX3: 0.3 | BY3: 0.3 | BZ3: 0.3 | CA3: 0.3 | CB3: 0.3 | CC3: 0.3
A4: Haryana | B4: ='RPO State forecasts'!$AH$14 -> 0.2172767 | C4: =B4+($K4-$B4)/10 -> 0.22554903 | D4: =C4+($K4-$B4)/10 -> 0.23382136 | E4: =D4+($K4-$B4)/10 -> 0.24209369 | F4: =E4+($K4-$B4)/10 -> 0.25036602 | G4: =F4+($K4-$B4)/10 -> 0.25863835 | H4: =G4+($K4-$B4)/10 -> 0.26691068 | I4: =H4+($K4-$B4)/10 -> 0.27518301 | J4: =I4+($K4-$B4)/10 -> 0.28345534 | K4: 0.3 | L4: 0.3 | M4: 0.3 | N4: 0.3 | O4: 0.3 | P4: 0.3 | Q4: 0.3 | R4: 0.3 | S4: 0.3 | T4: 0.3 | U4: 0.3 | V4: 0.3 | W4: 0.3 | X4: 0.3 | Y4: 0.3 | Z4: 0.3 | AA4: 0.3 | AB4: 0.3 | AC4: 0.3 | AD4: 0.3 | AE4: 0.3 | AF4: 0.3 | AG4: 0.3 | AH4: 0.3 | AI4: 0.3 | AJ4: 0.3 | AK4: 0.3 | AL4: 0.3 | AM4: 0.3 | AN4: 0.3 | AO4: 0.3 | AP4: 0.3 | AQ4: 0.3 | AR4: 0.3 | AS4: 0.3 | AT4: 0.3 | AU4: 0.3 | AV4: 0.3 | AW4: 0.3 | AX4: 0.3 | AY4: 0.3 | AZ4: 0.3 | BA4: 0.3 | BB4: 0.3 | BC4: 0.3 | BD4: 0.3 | BE4: 0.3 | BF4: 0.3 | BG4: 0.3 | BH4: 0.3 | BI4: 0.3 | BJ4: 0.3 | BK4: 0.3 | BL4: 0.3 | BM4: 0.3 | BN4: 0.3 | BO4: 0.3 | BP4: 0.3 | BQ4: 0.3 | BR4: 0.3 | BS4: 0.3 | BT4: 0.3 | BU4: 0.3 | BV4: 0.3 | BW4: 0.3 | BX4: 0.3 | BY4: 0.3 | BZ4: 0.3 | CA4: 0.3 | CB4: 0.3 | CC4: 0.3
A5: Himachal Pradesh | B5: ='RPO State forecasts'!$AH$14 -> 0.2172767 | C5: =B5+($K5-$B5)/10 -> 0.22554903 | D5: =C5+($K5-$B5)/10 -> 0.23382136 | E5: =D5+($K5-$B5)/10 -> 0.24209369 | F5: =E5+($K5-$B5)/10 -> 0.25036602 | G5: =F5+($K5-$B5)/10 -> 0.25863835 | H5: =G5+($K5-$B5)/10 -> 0.26691068 | I5: =H5+($K5-$B5)/10 -> 0.27518301 | J5: =I5+($K5-$B5)/10 -> 0.28345534 | K5: 0.3 | L5: 0.3 | M5: 0.3 | N5: 0.3 | O5: 0.3 | P5: 0.3 | Q5: 0.3 | R5: 0.3 | S5: 0.3 | T5: 0.3 | U5: 0.3 | V5: 0.3 | W5: 0.3 | X5: 0.3 | Y5: 0.3 | Z5: 0.3 | AA5: 0.3 | AB5: 0.3 | AC5: 0.3 | AD5: 0.3 | AE5: 0.3 | AF5: 0.3 | AG5: 0.3 | AH5: 0.3 | AI5: 0.3 | AJ5: 0.3 | AK5: 0.3 | AL5: 0.3 | AM5: 0.3 | AN5: 0.3 | AO5: 0.3 | AP5: 0.3 | AQ5: 0.3 | AR5: 0.3 | AS5: 0.3 | AT5: 0.3 | AU5: 0.3 | AV5: 0.3 | AW5: 0.3 | AX5: 0.3 | AY5: 0.3 | AZ5: 0.3 | BA5: 0.3 | BB5: 0.3 | BC5: 0.3 | BD5: 0.3 | BE5: 0.3 | BF5: 0.3 | BG5: 0.3 | BH5: 0.3 | BI5: 0.3 | BJ5: 0.3 | BK5: 0.3 | BL5: 0.3 | BM5: 0.3 | BN5: 0.3 | BO5: 0.3 | BP5: 0.3 | BQ5: 0.3 | BR5: 0.3 | BS5: 0.3 | BT5: 0.3 | BU5: 0.3 | BV5: 0.3 | BW5: 0.3 | BX5: 0.3 | BY5: 0.3 | BZ5: 0.3 | CA5: 0.3 | CB5: 0.3 | CC5: 0.3
A6: UT of JK and Ladakh | B6: ='RPO State forecasts'!$AH$14 -> 0.2172767 | C6: =B6+($K6-$B6)/10 -> 0.22554903 | D6: =C6+($K6-$B6)/10 -> 0.23382136 | E6: =D6+($K6-$B6)/10 -> 0.24209369 | F6: =E6+($K6-$B6)/10 -> 0.25036602 | G6: =F6+($K6-$B6)/10 -> 0.25863835 | H6: =G6+($K6-$B6)/10 -> 0.26691068 | I6: =H6+($K6-$B6)/10 -> 0.27518301 | J6: =I6+($K6-$B6)/10 -> 0.28345534 | K6: 0.3 | L6: 0.3 | M6: 0.3 | N6: 0.3 | O6: 0.3 | P6: 0.3 | Q6: 0.3 | R6: 0.3 | S6: 0.3 | T6: 0.3 | U6: 0.3 | V6: 0.3 | W6: 0.3 | X6: 0.3 | Y6: 0.3 | Z6: 0.3 | AA6: 0.3 | AB6: 0.3 | AC6: 0.3 | AD6: 0.3 | AE6: 0.3 | AF6: 0.3 | AG6: 0.3 | AH6: 0.3 | AI6: 0.3 | AJ6: 0.3 | AK6: 0.3 | AL6: 0.3 | AM6: 0.3 | AN6: 0.3 | AO6: 0.3 | AP6: 0.3 | AQ6: 0.3 | AR6: 0.3 | AS6: 0.3 | AT6: 0.3 | AU6: 0.3 | AV6: 0.3 | AW6: 0.3 | AX6: 0.3 | AY6: 0.3 | AZ6: 0.3 | BA6: 0.3 | BB6: 0.3 | BC6: 0.3 | BD6: 0.3 | BE6: 0.3 | BF6: 0.3 | BG6: 0.3 | BH6: 0.3 | BI6: 0.3 | BJ6: 0.3 | BK6: 0.3 | BL6: 0.3 | BM6: 0.3 | BN6: 0.3 | BO6: 0.3 | BP6: 0.3 | BQ6: 0.3 | BR6: 0.3 | BS6: 0.3 | BT6: 0.3 | BU6: 0.3 | BV6: 0.3 | BW6: 0.3 | BX6: 0.3 | BY6: 0.3 | BZ6: 0.3 | CA6: 0.3 | CB6: 0.3 | CC6: 0.3
A7: Punjab | B7: ='RPO State forecasts'!$AH$14 -> 0.2172767 | C7: =B7+($K7-$B7)/10 -> 0.22554903 | D7: =C7+($K7-$B7)/10 -> 0.23382136 | E7: =D7+($K7-$B7)/10 -> 0.24209369 | F7: =E7+($K7-$B7)/10 -> 0.25036602 | G7: =F7+($K7-$B7)/10 -> 0.25863835 | H7: =G7+($K7-$B7)/10 -> 0.26691068 | I7: =H7+($K7-$B7)/10 -> 0.27518301 | J7: =I7+($K7-$B7)/10 -> 0.28345534 | K7: 0.3 | L7: 0.3 | M7: 0.3 | N7: 0.3 | O7: 0.3 | P7: 0.3 | Q7: 0.3 | R7: 0.3 | S7: 0.3 | T7: 0.3 | U7: 0.3 | V7: 0.3 | W7: 0.3 | X7: 0.3 | Y7: 0.3 | Z7: 0.3 | AA7: 0.3 | AB7: 0.3 | AC7: 0.3 | AD7: 0.3 | AE7: 0.3 | AF7: 0.3 | AG7: 0.3 | AH7: 0.3 | AI7: 0.3 | AJ7: 0.3 | AK7: 0.3 | AL7: 0.3 | AM7: 0.3 | AN7: 0.3 | AO7: 0.3 | AP7: 0.3 | AQ7: 0.3 | AR7: 0.3 | AS7: 0.3 | AT7: 0.3 | AU7: 0.3 | AV7: 0.3 | AW7: 0.3 | AX7: 0.3 | AY7: 0.3 | AZ7: 0.3 | BA7: 0.3 | BB7: 0.3 | BC7: 0.3 | BD7: 0.3 | BE7: 0.3 | BF7: 0.3 | BG7: 0.3 | BH7: 0.3 | BI7: 0.3 | BJ7: 0.3 | BK7: 0.3 | BL7: 0.3 | BM7: 0.3 | BN7: 0.3 | BO7: 0.3 | BP7: 0.3 | BQ7: 0.3 | BR7: 0.3 | BS7: 0.3 | BT7: 0.3 | BU7: 0.3 | BV7: 0.3 | BW7: 0.3 | BX7: 0.3 | BY7: 0.3 | BZ7: 0.3 | CA7: 0.3 | CB7: 0.3 | CC7: 0.3
A8: Rajasthan | B8: ='RPO State forecasts'!$AH$14 -> 0.2172767 | C8: =B8+($K8-$B8)/10 -> 0.22554903 | D8: =C8+($K8-$B8)/10 -> 0.23382136 | E8: =D8+($K8-$B8)/10 -> 0.24209369 | F8: =E8+($K8-$B8)/10 -> 0.25036602 | G8: =F8+($K8-$B8)/10 -> 0.25863835 | H8: =G8+($K8-$B8)/10 -> 0.26691068 | I8: =H8+($K8-$B8)/10 -> 0.27518301 | J8: =I8+($K8-$B8)/10 -> 0.28345534 | K8: 0.3 | L8: 0.3 | M8: 0.3 | N8: 0.3 | O8: 0.3 | P8: 0.3 | Q8: 0.3 | R8: 0.3 | S8: 0.3 | T8: 0.3 | U8: 0.3 | V8: 0.3 | W8: 0.3 | X8: 0.3 | Y8: 0.3 | Z8: 0.3 | AA8: 0.3 | AB8: 0.3 | AC8: 0.3 | AD8: 0.3 | AE8: 0.3 | AF8: 0.3 | AG8: 0.3 | AH8: 0.3 | AI8: 0.3 | AJ8: 0.3 | AK8: 0.3 | AL8: 0.3 | AM8: 0.3 | AN8: 0.3 | AO8: 0.3 | AP8: 0.3 | AQ8: 0.3 | AR8: 0.3 | AS8: 0.3 | AT8: 0.3 | AU8: 0.3 | AV8: 0.3 | AW8: 0.3 | AX8: 0.3 | AY8: 0.3 | AZ8: 0.3 | BA8: 0.3 | BB8: 0.3 | BC8: 0.3 | BD8: 0.3 | BE8: 0.3 | BF8: 0.3 | BG8: 0.3 | BH8: 0.3 | BI8: 0.3 | BJ8: 0.3 | BK8: 0.3 | BL8: 0.3 | BM8: 0.3 | BN8: 0.3 | BO8: 0.3 | BP8: 0.3 | BQ8: 0.3 | BR8: 0.3 | BS8: 0.3 | BT8: 0.3 | BU8: 0.3 | BV8: 0.3 | BW8: 0.3 | BX8: 0.3 | BY8: 0.3 | BZ8: 0.3 | CA8: 0.3 | CB8: 0.3 | CC8: 0.3
A9: Uttar Pradesh | B9: ='RPO State forecasts'!$AH$14 -> 0.2172767 | C9: =B9+($K9-$B9)/10 -> 0.22554903 | D9: =C9+($K9-$B9)/10 -> 0.23382136 | E9: =D9+($K9-$B9)/10 -> 0.24209369 | F9: =E9+($K9-$B9)/10 -> 0.25036602 | G9: =F9+($K9-$B9)/10 -> 0.25863835 | H9: =G9+($K9-$B9)/10 -> 0.26691068 | I9: =H9+($K9-$B9)/10 -> 0.27518301 | J9: =I9+($K9-$B9)/10 -> 0.28345534 | K9: 0.3 | L9: 0.3 | M9: 0.3 | N9: 0.3 | O9: 0.3 | P9: 0.3 | Q9: 0.3 | R9: 0.3 | S9: 0.3 | T9: 0.3 | U9: 0.3 | V9: 0.3 | W9: 0.3 | X9: 0.3 | Y9: 0.3 | Z9: 0.3 | AA9: 0.3 | AB9: 0.3 | AC9: 0.3 | AD9: 0.3 | AE9: 0.3 | AF9: 0.3 | AG9: 0.3 | AH9: 0.3 | AI9: 0.3 | AJ9: 0.3 | AK9: 0.3 | AL9: 0.3 | AM9: 0.3 | AN9: 0.3 | AO9: 0.3 | AP9: 0.3 | AQ9: 0.3 | AR9: 0.3 | AS9: 0.3 | AT9: 0.3 | AU9: 0.3 | AV9: 0.3 | AW9: 0.3 | AX9: 0.3 | AY9: 0.3 | AZ9: 0.3 | BA9: 0.3 | BB9: 0.3 | BC9: 0.3 | BD9: 0.3 | BE9: 0.3 | BF9: 0.3 | BG9: 0.3 | BH9: 0.3 | BI9: 0.3 | BJ9: 0.3 | BK9: 0.3 | BL9: 0.3 | BM9: 0.3 | BN9: 0.3 | BO9: 0.3 | BP9: 0.3 | BQ9: 0.3 | BR9: 0.3 | BS9: 0.3 | BT9: 0.3 | BU9: 0.3 | BV9: 0.3 | BW9: 0.3 | BX9: 0.3 | BY9: 0.3 | BZ9: 0.3 | CA9: 0.3 | CB9: 0.3 | CC9: 0.3
A10: Uttarakhand | B10: ='RPO State forecasts'!$AH$14 -> 0.2172767 | C10: =B10+($K10-$B10)/10 -> 0.22554903 | D10: =C10+($K10-$B10)/10 -> 0.23382136 | E10: =D10+($K10-$B10)/10 -> 0.24209369 | F10: =E10+($K10-$B10)/10 -> 0.25036602 | G10: =F10+($K10-$B10)/10 -> 0.25863835 | H10: =G10+($K10-$B10)/10 -> 0.26691068 | I10: =H10+($K10-$B10)/10 -> 0.27518301 | J10: =I10+($K10-$B10)/10 -> 0.28345534 | K10: 0.3 | L10: 0.3 | M10: 0.3 | N10: 0.3 | O10: 0.3 | P10: 0.3 | Q10: 0.3 | R10: 0.3 | S10: 0.3 | T10: 0.3 | U10: 0.3 | V10: 0.3 | W10: 0.3 | X10: 0.3 | Y10: 0.3 | Z10: 0.3 | AA10: 0.3 | AB10: 0.3 | AC10: 0.3 | AD10: 0.3 | AE10: 0.3 | AF10: 0.3 | AG10: 0.3 | AH10: 0.3 | AI10: 0.3 | AJ10: 0.3 | AK10: 0.3 | AL10: 0.3 | AM10: 0.3 | AN10: 0.3 | AO10: 0.3 | AP10: 0.3 | AQ10: 0.3 | AR10: 0.3 | AS10: 0.3 | AT10: 0.3 | AU10: 0.3 | AV10: 0.3 | AW10: 0.3 | AX10: 0.3 | AY10: 0.3 | AZ10: 0.3 | BA10: 0.3 | BB10: 0.3 | BC10: 0.3 | BD10: 0.3 | BE10: 0.3 | BF10: 0.3 | BG10: 0.3 | BH10: 0.3 | BI10: 0.3 | BJ10: 0.3 | BK10: 0.3 | BL10: 0.3 | BM10: 0.3 | BN10: 0.3 | BO10: 0.3 | BP10: 0.3 | BQ10: 0.3 | BR10: 0.3 | BS10: 0.3 | BT10: 0.3 | BU10: 0.3 | BV10: 0.3 | BW10: 0.3 | BX10: 0.3 | BY10: 0.3 | BZ10: 0.3 | CA10: 0.3 | CB10: 0.3 | CC10: 0.3
A11: Chhattisgarh | B11: ='RPO State forecasts'!$AH$14 -> 0.2172767 | C11: =B11+($K11-$B11)/10 -> 0.22554903 | D11: =C11+($K11-$B11)/10 -> 0.23382136 | E11: =D11+($K11-$B11)/10 -> 0.24209369 | F11: =E11+($K11-$B11)/10 -> 0.25036602 | G11: =F11+($K11-$B11)/10 -> 0.25863835 | H11: =G11+($K11-$B11)/10 -> 0.26691068 | I11: =H11+($K11-$B11)/10 -> 0.27518301 | J11: =I11+($K11-$B11)/10 -> 0.28345534 | K11: 0.3 | L11: 0.3 | M11: 0.3 | N11: 0.3 | O11: 0.3 | P11: 0.3 | Q11: 0.3 | R11: 0.3 | S11: 0.3 | T11: 0.3 | U11: 0.3 | V11: 0.3 | W11: 0.3 | X11: 0.3 | Y11: 0.3 | Z11: 0.3 | AA11: 0.3 | AB11: 0.3 | AC11: 0.3 | AD11: 0.3 | AE11: 0.3 | AF11: 0.3 | AG11: 0.3 | AH11: 0.3 | AI11: 0.3 | AJ11: 0.3 | AK11: 0.3 | AL11: 0.3 | AM11: 0.3 | AN11: 0.3 | AO11: 0.3 | AP11: 0.3 | AQ11: 0.3 | AR11: 0.3 | AS11: 0.3 | AT11: 0.3 | AU11: 0.3 | AV11: 0.3 | AW11: 0.3 | AX11: 0.3 | AY11: 0.3 | AZ11: 0.3 | BA11: 0.3 | BB11: 0.3 | BC11: 0.3 | BD11: 0.3 | BE11: 0.3 | BF11: 0.3 | BG11: 0.3 | BH11: 0.3 | BI11: 0.3 | BJ11: 0.3 | BK11: 0.3 | BL11: 0.3 | BM11: 0.3 | BN11: 0.3 | BO11: 0.3 | BP11: 0.3 | BQ11: 0.3 | BR11: 0.3 | BS11: 0.3 | BT11: 0.3 | BU11: 0.3 | BV11: 0.3 | BW11: 0.3 | BX11: 0.3 | BY11: 0.3 | BZ11: 0.3 | CA11: 0.3 | CB11: 0.3 | CC11: 0.3
A12: Gujarat | B12: ='RPO State forecasts'!$AH$14 -> 0.2172767 | C12: =B12+($K12-$B12)/10 -> 0.22554903 | D12: =C12+($K12-$B12)/10 -> 0.23382136 | E12: =D12+($K12-$B12)/10 -> 0.24209369 | F12: =E12+($K12-$B12)/10 -> 0.25036602 | G12: =F12+($K12-$B12)/10 -> 0.25863835 | H12: =G12+($K12-$B12)/10 -> 0.26691068 | I12: =H12+($K12-$B12)/10 -> 0.27518301 | J12: =I12+($K12-$B12)/10 -> 0.28345534 | K12: 0.3 | L12: 0.3 | M12: 0.3 | N12: 0.3 | O12: 0.3 | P12: 0.3 | Q12: 0.3 | R12: 0.3 | S12: 0.3 | T12: 0.3 | U12: 0.3 | V12: 0.3 | W12: 0.3 | X12: 0.3 | Y12: 0.3 | Z12: 0.3 | AA12: 0.3 | AB12: 0.3 | AC12: 0.3 | AD12: 0.3 | AE12: 0.3 | AF12: 0.3 | AG12: 0.3 | AH12: 0.3 | AI12: 0.3 | AJ12: 0.3 | AK12: 0.3 | AL12: 0.3 | AM12: 0.3 | AN12: 0.3 | AO12: 0.3 | AP12: 0.3 | AQ12: 0.3 | AR12: 0.3 | AS12: 0.3 | AT12: 0.3 | AU12: 0.3 | AV12: 0.3 | AW12: 0.3 | AX12: 0.3 | AY12: 0.3 | AZ12: 0.3 | BA12: 0.3 | BB12: 0.3 | BC12: 0.3 | BD12: 0.3 | BE12: 0.3 | BF12: 0.3 | BG12: 0.3 | BH12: 0.3 | BI12: 0.3 | BJ12: 0.3 | BK12: 0.3 | BL12: 0.3 | BM12: 0.3 | BN12: 0.3 | BO12: 0.3 | BP12: 0.3 | BQ12: 0.3 | BR12: 0.3 | BS12: 0.3 | BT12: 0.3 | BU12: 0.3 | BV12: 0.3 | BW12: 0.3 | BX12: 0.3 | BY12: 0.3 | BZ12: 0.3 | CA12: 0.3 | CB12: 0.3 | CC12: 0.3
A13: Madhya Pradesh | B13: ='RPO State forecasts'!$AH$14 -> 0.2172767 | C13: =B13+($K13-$B13)/10 -> 0.22554903 | D13: =C13+($K13-$B13)/10 -> 0.23382136 | E13: =D13+($K13-$B13)/10 -> 0.24209369 | F13: =E13+($K13-$B13)/10 -> 0.25036602 | G13: =F13+($K13-$B13)/10 -> 0.25863835 | H13: =G13+($K13-$B13)/10 -> 0.26691068 | I13: =H13+($K13-$B13)/10 -> 0.27518301 | J13: =I13+($K13-$B13)/10 -> 0.28345534 | K13: 0.3 | L13: 0.3 | M13: 0.3 | N13: 0.3 | O13: 0.3 | P13: 0.3 | Q13: 0.3 | R13: 0.3 | S13: 0.3 | T13: 0.3 | U13: 0.3 | V13: 0.3 | W13: 0.3 | X13: 0.3 | Y13: 0.3 | Z13: 0.3 | AA13: 0.3 | AB13: 0.3 | AC13: 0.3 | AD13: 0.3 | AE13: 0.3 | AF13: 0.3 | AG13: 0.3 | AH13: 0.3 | AI13: 0.3 | AJ13: 0.3 | AK13: 0.3 | AL13: 0.3 | AM13: 0.3 | AN13: 0.3 | AO13: 0.3 | AP13: 0.3 | AQ13: 0.3 | AR13: 0.3 | AS13: 0.3 | AT13: 0.3 | AU13: 0.3 | AV13: 0.3 | AW13: 0.3 | AX13: 0.3 | AY13: 0.3 | AZ13: 0.3 | BA13: 0.3 | BB13: 0.3 | BC13: 0.3 | BD13: 0.3 | BE13: 0.3 | BF13: 0.3 | BG13: 0.3 | BH13: 0.3 | BI13: 0.3 | BJ13: 0.3 | BK13: 0.3 | BL13: 0.3 | BM13: 0.3 | BN13: 0.3 | BO13: 0.3 | BP13: 0.3 | BQ13: 0.3 | BR13: 0.3 | BS13: 0.3 | BT13: 0.3 | BU13: 0.3 | BV13: 0.3 | BW13: 0.3 | BX13: 0.3 | BY13: 0.3 | BZ13: 0.3 | CA13: 0.3 | CB13: 0.3 | CC13: 0.3
... A37: Tripura | B37: ='RPO State forecasts'!$AH$14 -> 0.2172767 | C37: =B37+($K37-$B37)/10 -> 0.22554903 | D37: =C37+($K37-$B37)/10 -> 0.23382136 | E37: =D37+($K37-$B37)/10 -> 0.24209369 | F37: =E37+($K37-$B37)/10 -> 0.25036602 | G37: =F37+($K37-$B37)/10 -> 0.25863835 | H37: =G37+($K37-$B37)/10 -> 0.26691068 | I37: =H37+($K37-$B37)/10 -> 0.27518301 | J37: =I37+($K37-$B37)/10 -> 0.28345534 | K37: 0.3 | L37: 0.3 | M37: 0.3 | N37: 0.3 | O37: 0.3 | P37: 0.3 | Q37: 0.3 | R37: 0.3 | S37: 0.3 | T37: 0.3 | U37: 0.3 | V37: 0.3 | W37: 0.3 | X37: 0.3 | Y37: 0.3 | Z37: 0.3 | AA37: 0.3 | AB37: 0.3 | AC37: 0.3 | AD37: 0.3 | AE37: 0.3 | AF37: 0.3 | AG37: 0.3 | AH37: 0.3 | AI37: 0.3 | AJ37: 0.3 | AK37: 0.3 | AL37: 0.3 | AM37: 0.3 | AN37: 0.3 | AO37: 0.3 | AP37: 0.3 | AQ37: 0.3 | AR37: 0.3 | AS37: 0.3 | AT37: 0.3 | AU37: 0.3 | AV37: 0.3 | AW37: 0.3 | AX37: 0.3 | AY37: 0.3 | AZ37: 0.3 | BA37: 0.3 | BB37: 0.3 | BC37: 0.3 | BD37: 0.3 | BE37: 0.3 | BF37: 0.3 | BG37: 0.3 | BH37: 0.3 | BI37: 0.3 | BJ37: 0.3 | BK37: 0.3 | BL37: 0.3 | BM37: 0.3 | BN37: 0.3 | BO37: 0.3 | BP37: 0.3 | BQ37: 0.3 | BR37: 0.3 | BS37: 0.3 | BT37: 0.3 | BU37: 0.3 | BV37: 0.3 | BW37: 0.3 | BX37: 0.3 | BY37: 0.3 | BZ37: 0.3 | CA37: 0.3 | CB37: 0.3 | CC37: 0.3
A38: subregion37 | B38: 0 | C38: 0 | D38: 0 | E38: 0 | F38: 0 | G38: 0 | H38: 0 | I38: 0 | J38: 0 | K38: 0 | L38: 0 | M38: 0 | N38: 0 | O38: 0 | P38: 0 | Q38: 0 | R38: 0 | S38: 0 | T38: 0 | U38: 0 | V38: 0 | W38: 0 | X38: 0 | Y38: 0 | Z38: 0 | AA38: 0 | AB38: 0 | AC38: 0 | AD38: 0 | AE38: 0 | AF38: 0 | AG38: 0 | AH38: 0 | AI38: 0 | AJ38: 0 | AK38: 0 | AL38: 0 | AM38: 0 | AN38: 0 | AO38: 0 | AP38: 0 | AQ38: 0 | AR38: 0 | AS38: 0 | AT38: 0 | AU38: 0 | AV38: 0 | AW38: 0 | AX38: 0 | AY38: 0 | AZ38: 0 | BA38: 0 | BB38: 0 | BC38: 0 | BD38: 0 | BE38: 0 | BF38: 0 | BG38: 0 | BH38: 0 | BI38: 0 | BJ38: 0 | BK38: 0 | BL38: 0 | BM38: 0 | BN38: 0 | BO38: 0 | BP38: 0 | BQ38: 0 | BR38: 0 | BS38: 0 | BT38: 0 | BU38: 0 | BV38: 0 | BW38: 0 | BX38: 0 | BY38: 0 | BZ38: 0 | CA38: 0 | CB38: 0 | CC38: 0
A39: subregion38 | B39: 0 | C39: 0 | D39: 0 | E39: 0 | F39: 0 | G39: 0 | H39: 0 | I39: 0 | J39: 0 | K39: 0 | L39: 0 | M39: 0 | N39: 0 | O39: 0 | P39: 0 | Q39: 0 | R39: 0 | S39: 0 | T39: 0 | U39: 0 | V39: 0 | W39: 0 | X39: 0 | Y39: 0 | Z39: 0 | AA39: 0 | AB39: 0 | AC39: 0 | AD39: 0 | AE39: 0 | AF39: 0 | AG39: 0 | AH39: 0 | AI39: 0 | AJ39: 0 | AK39: 0 | AL39: 0 | AM39: 0 | AN39: 0 | AO39: 0 | AP39: 0 | AQ39: 0 | AR39: 0 | AS39: 0 | AT39: 0 | AU39: 0 | AV39: 0 | AW39: 0 | AX39: 0 | AY39: 0 | AZ39: 0 | BA39: 0 | BB39: 0 | BC39: 0 | BD39: 0 | BE39: 0 | BF39: 0 | BG39: 0 | BH39: 0 | BI39: 0 | BJ39: 0 | BK39: 0 | BL39: 0 | BM39: 0 | BN39: 0 | BO39: 0 | BP39: 0 | BQ39: 0 | BR39: 0 | BS39: 0 | BT39: 0 | BU39: 0 | BV39: 0 | BW39: 0 | BX39: 0 | BY39: 0 | BZ39: 0 | CA39: 0 | CB39: 0 | CC39: 0
A40: subregion39 | B40: 0 | C40: 0 | D40: 0 | E40: 0 | F40: 0 | G40: 0 | H40: 0 | I40: 0 | J40: 0 | K40: 0 | L40: 0 | M40: 0 | N40: 0 | O40: 0 | P40: 0 | Q40: 0 | R40: 0 | S40: 0 | T40: 0 | U40: 0 | V40: 0 | W40: 0 | X40: 0 | Y40: 0 | Z40: 0 | AA40: 0 | AB40: 0 | AC40: 0 | AD40: 0 | AE40: 0 | AF40: 0 | AG40: 0 | AH40: 0 | AI40: 0 | AJ40: 0 | AK40: 0 | AL40: 0 | AM40: 0 | AN40: 0 | AO40: 0 | AP40: 0 | AQ40: 0 | AR40: 0 | AS40: 0 | AT40: 0 | AU40: 0 | AV40: 0 | AW40: 0 | AX40: 0 | AY40: 0 | AZ40: 0 | BA40: 0 | BB40: 0 | BC40: 0 | BD40: 0 | BE40: 0 | BF40: 0 | BG40: 0 | BH40: 0 | BI40: 0 | BJ40: 0 | BK40: 0 | BL40: 0 | BM40: 0 | BN40: 0 | BO40: 0 | BP40: 0 | BQ40: 0 | BR40: 0 | BS40: 0 | BT40: 0 | BU40: 0 | BV40: 0 | BW40: 0 | BX40: 0 | BY40: 0 | BZ40: 0 | CA40: 0 | CB40: 0 | CC40: 0
A41: subregion40 | B41: 0 | C41: 0 | D41: 0 | E41: 0 | F41: 0 | G41: 0 | H41: 0 | I41: 0 | J41: 0 | K41: 0 | L41: 0 | M41: 0 | N41: 0 | O41: 0 | P41: 0 | Q41: 0 | R41: 0 | S41: 0 | T41: 0 | U41: 0 | V41: 0 | W41: 0 | X41: 0 | Y41: 0 | Z41: 0 | AA41: 0 | AB41: 0 | AC41: 0 | AD41: 0 | AE41: 0 | AF41: 0 | AG41: 0 | AH41: 0 | AI41: 0 | AJ41: 0 | AK41: 0 | AL41: 0 | AM41: 0 | AN41: 0 | AO41: 0 | AP41: 0 | AQ41: 0 | AR41: 0 | AS41: 0 | AT41: 0 | AU41: 0 | AV41: 0 | AW41: 0 | AX41: 0 | AY41: 0 | AZ41: 0 | BA41: 0 | BB41: 0 | BC41: 0 | BD41: 0 | BE41: 0 | BF41: 0 | BG41: 0 | BH41: 0 | BI41: 0 | BJ41: 0 | BK41: 0 | BL41: 0 | BM41: 0 | BN41: 0 | BO41: 0 | BP41: 0 | BQ41: 0 | BR41: 0 | BS41: 0 | BT41: 0 | BU41: 0 | BV41: 0 | BW41: 0 | BX41: 0 | BY41: 0 | BZ41: 0 | CA41: 0 | CB41: 0 | CC41: 0
A42: subregion41 | B42: 0 | C42: 0 | D42: 0 | E42: 0 | F42: 0 | G42: 0 | H42: 0 | I42: 0 | J42: 0 | K42: 0 | L42: 0 | M42: 0 | N42: 0 | O42: 0 | P42: 0 | Q42: 0 | R42: 0 | S42: 0 | T42: 0 | U42: 0 | V42: 0 | W42: 0 | X42: 0 | Y42: 0 | Z42: 0 | AA42: 0 | AB42: 0 | AC42: 0 | AD42: 0 | AE42: 0 | AF42: 0 | AG42: 0 | AH42: 0 | AI42: 0 | AJ42: 0 | AK42: 0 | AL42: 0 | AM42: 0 | AN42: 0 | AO42: 0 | AP42: 0 | AQ42: 0 | AR42: 0 | AS42: 0 | AT42: 0 | AU42: 0 | AV42: 0 | AW42: 0 | AX42: 0 | AY42: 0 | AZ42: 0 | BA42: 0 | BB42: 0 | BC42: 0 | BD42: 0 | BE42: 0 | BF42: 0 | BG42: 0 | BH42: 0 | BI42: 0 | BJ42: 0 | BK42: 0 | BL42: 0 | BM42: 0 | BN42: 0 | BO42: 0 | BP42: 0 | BQ42: 0 | BR42: 0 | BS42: 0 | BT42: 0 | BU42: 0 | BV42: 0 | BW42: 0 | BX42: 0 | BY42: 0 | BZ42: 0 | CA42: 0 | CB42: 0 | CC42: 0
A43: subregion42 | B43: 0 | C43: 0 | D43: 0 | E43: 0 | F43: 0 | G43: 0 | H43: 0 | I43: 0 | J43: 0 | K43: 0 | L43: 0 | M43: 0 | N43: 0 | O43: 0 | P43: 0 | Q43: 0 | R43: 0 | S43: 0 | T43: 0 | U43: 0 | V43: 0 | W43: 0 | X43: 0 | Y43: 0 | Z43: 0 | AA43: 0 | AB43: 0 | AC43: 0 | AD43: 0 | AE43: 0 | AF43: 0 | AG43: 0 | AH43: 0 | AI43: 0 | AJ43: 0 | AK43: 0 | AL43: 0 | AM43: 0 | AN43: 0 | AO43: 0 | AP43: 0 | AQ43: 0 | AR43: 0 | AS43: 0 | AT43: 0 | AU43: 0 | AV43: 0 | AW43: 0 | AX43: 0 | AY43: 0 | AZ43: 0 | BA43: 0 | BB43: 0 | BC43: 0 | BD43: 0 | BE43: 0 | BF43: 0 | BG43: 0 | BH43: 0 | BI43: 0 | BJ43: 0 | BK43: 0 | BL43: 0 | BM43: 0 | BN43: 0 | BO43: 0 | BP43: 0 | BQ43: 0 | BR43: 0 | BS43: 0 | BT43: 0 | BU43: 0 | BV43: 0 | BW43: 0 | BX43: 0 | BY43: 0 | BZ43: 0 | CA43: 0 | CB43: 0 | CC43: 0
A44: subregion43 | B44: 0 | C44: 0 | D44: 0 | E44: 0 | F44: 0 | G44: 0 | H44: 0 | I44: 0 | J44: 0 | K44: 0 | L44: 0 | M44: 0 | N44: 0 | O44: 0 | P44: 0 | Q44: 0 | R44: 0 | S44: 0 | T44: 0 | U44: 0 | V44: 0 | W44: 0 | X44: 0 | Y44: 0 | Z44: 0 | AA44: 0 | AB44: 0 | AC44: 0 | AD44: 0 | AE44: 0 | AF44: 0 | AG44: 0 | AH44: 0 | AI44: 0 | AJ44: 0 | AK44: 0 | AL44: 0 | AM44: 0 | AN44: 0 | AO44: 0 | AP44: 0 | AQ44: 0 | AR44: 0 | AS44: 0 | AT44: 0 | AU44: 0 | AV44: 0 | AW44: 0 | AX44: 0 | AY44: 0 | AZ44: 0 | BA44: 0 | BB44: 0 | BC44: 0 | BD44: 0 | BE44: 0 | BF44: 0 | BG44: 0 | BH44: 0 | BI44: 0 | BJ44: 0 | BK44: 0 | BL44: 0 | BM44: 0 | BN44: 0 | BO44: 0 | BP44: 0 | BQ44: 0 | BR44: 0 | BS44: 0 | BT44: 0 | BU44: 0 | BV44: 0 | BW44: 0 | BX44: 0 | BY44: 0 | BZ44: 0 | CA44: 0 | CB44: 0 | CC44: 0
A45: subregion44 | B45: 0 | C45: 0 | D45: 0 | E45: 0 | F45: 0 | G45: 0 | H45: 0 | I45: 0 | J45: 0 | K45: 0 | L45: 0 | M45: 0 | N45: 0 | O45: 0 | P45: 0 | Q45: 0 | R45: 0 | S45: 0 | T45: 0 | U45: 0 | V45: 0 | W45: 0 | X45: 0 | Y45: 0 | Z45: 0 | AA45: 0 | AB45: 0 | AC45: 0 | AD45: 0 | AE45: 0 | AF45: 0 | AG45: 0 | AH45: 0 | AI45: 0 | AJ45: 0 | AK45: 0 | AL45: 0 | AM45: 0 | AN45: 0 | AO45: 0 | AP45: 0 | AQ45: 0 | AR45: 0 | AS45: 0 | AT45: 0 | AU45: 0 | AV45: 0 | AW45: 0 | AX45: 0 | AY45: 0 | AZ45: 0 | BA45: 0 | BB45: 0 | BC45: 0 | BD45: 0 | BE45: 0 | BF45: 0 | BG45: 0 | BH45: 0 | BI45: 0 | BJ45: 0 | BK45: 0 | BL45: 0 | BM45: 0 | BN45: 0 | BO45: 0 | BP45: 0 | BQ45: 0 | BR45: 0 | BS45: 0 | BT45: 0 | BU45: 0 | BV45: 0 | BW45: 0 | BX45: 0 | BY45: 0 | BZ45: 0 | CA45: 0 | CB45: 0 | CC45: 0
A46: subregion45 | B46: 0 | C46: 0 | D46: 0 | E46: 0 | F46: 0 | G46: 0 | H46: 0 | I46: 0 | J46: 0 | K46: 0 | L46: 0 | M46: 0 | N46: 0 | O46: 0 | P46: 0 | Q46: 0 | R46: 0 | S46: 0 | T46: 0 | U46: 0 | V46: 0 | W46: 0 | X46: 0 | Y46: 0 | Z46: 0 | AA46: 0 | AB46: 0 | AC46: 0 | AD46: 0 | AE46: 0 | AF46: 0 | AG46: 0 | AH46: 0 | AI46: 0 | AJ46: 0 | AK46: 0 | AL46: 0 | AM46: 0 | AN46: 0 | AO46: 0 | AP46: 0 | AQ46: 0 | AR46: 0 | AS46: 0 | AT46: 0 | AU46: 0 | AV46: 0 | AW46: 0 | AX46: 0 | AY46: 0 | AZ46: 0 | BA46: 0 | BB46: 0 | BC46: 0 | BD46: 0 | BE46: 0 | BF46: 0 | BG46: 0 | BH46: 0 | BI46: 0 | BJ46: 0 | BK46: 0 | BL46: 0 | BM46: 0 | BN46: 0 | BO46: 0 | BP46: 0 | BQ46: 0 | BR46: 0 | BS46: 0 | BT46: 0 | BU46: 0 | BV46: 0 | BW46: 0 | BX46: 0 | BY46: 0 | BZ46: 0 | CA46: 0 | CB46: 0 | CC46: 0
A47: subregion46 | B47: 0 | C47: 0 | D47: 0 | E47: 0 | F47: 0 | G47: 0 | H47: 0 | I47: 0 | J47: 0 | K47: 0 | L47: 0 | M47: 0 | N47: 0 | O47: 0 | P47: 0 | Q47: 0 | R47: 0 | S47: 0 | T47: 0 | U47: 0 | V47: 0 | W47: 0 | X47: 0 | Y47: 0 | Z47: 0 | AA47: 0 | AB47: 0 | AC47: 0 | AD47: 0 | AE47: 0 | AF47: 0 | AG47: 0 | AH47: 0 | AI47: 0 | AJ47: 0 | AK47: 0 | AL47: 0 | AM47: 0 | AN47: 0 | AO47: 0 | AP47: 0 | AQ47: 0 | AR47: 0 | AS47: 0 | AT47: 0 | AU47: 0 | AV47: 0 | AW47: 0 | AX47: 0 | AY47: 0 | AZ47: 0 | BA47: 0 | BB47: 0 | BC47: 0 | BD47: 0 | BE47: 0 | BF47: 0 | BG47: 0 | BH47: 0 | BI47: 0 | BJ47: 0 | BK47: 0 | BL47: 0 | BM47: 0 | BN47: 0 | BO47: 0 | BP47: 0 | BQ47: 0 | BR47: 0 | BS47: 0 | BT47: 0 | BU47: 0 | BV47: 0 | BW47: 0 | BX47: 0 | BY47: 0 | BZ47: 0 | CA47: 0 | CB47: 0 | CC47: 0
A48: subregion47 | B48: 0 | C48: 0 | D48: 0 | E48: 0 | F48: 0 | G48: 0 | H48: 0 | I48: 0 | J48: 0 | K48: 0 | L48: 0 | M48: 0 | N48: 0 | O48: 0 | P48: 0 | Q48: 0 | R48: 0 | S48: 0 | T48: 0 | U48: 0 | V48: 0 | W48: 0 | X48: 0 | Y48: 0 | Z48: 0 | AA48: 0 | AB48: 0 | AC48: 0 | AD48: 0 | AE48: 0 | AF48: 0 | AG48: 0 | AH48: 0 | AI48: 0 | AJ48: 0 | AK48: 0 | AL48: 0 | AM48: 0 | AN48: 0 | AO48: 0 | AP48: 0 | AQ48: 0 | AR48: 0 | AS48: 0 | AT48: 0 | AU48: 0 | AV48: 0 | AW48: 0 | AX48: 0 | AY48: 0 | AZ48: 0 | BA48: 0 | BB48: 0 | BC48: 0 | BD48: 0 | BE48: 0 | BF48: 0 | BG48: 0 | BH48: 0 | BI48: 0 | BJ48: 0 | BK48: 0 | BL48: 0 | BM48: 0 | BN48: 0 | BO48: 0 | BP48: 0 | BQ48: 0 | BR48: 0 | BS48: 0 | BT48: 0 | BU48: 0 | BV48: 0 | BW48: 0 | BX48: 0 | BY48: 0 | BZ48: 0 | CA48: 0 | CB48: 0 | CC48: 0
A49: subregion48 | B49: 0 | C49: 0 | D49: 0 | E49: 0 | F49: 0 | G49: 0 | H49: 0 | I49: 0 | J49: 0 | K49: 0 | L49: 0 | M49: 0 | N49: 0 | O49: 0 | P49: 0 | Q49: 0 | R49: 0 | S49: 0 | T49: 0 | U49: 0 | V49: 0 | W49: 0 | X49: 0 | Y49: 0 | Z49: 0 | AA49: 0 | AB49: 0 | AC49: 0 | AD49: 0 | AE49: 0 | AF49: 0 | AG49: 0 | AH49: 0 | AI49: 0 | AJ49: 0 | AK49: 0 | AL49: 0 | AM49: 0 | AN49: 0 | AO49: 0 | AP49: 0 | AQ49: 0 | AR49: 0 | AS49: 0 | AT49: 0 | AU49: 0 | AV49: 0 | AW49: 0 | AX49: 0 | AY49: 0 | AZ49: 0 | BA49: 0 | BB49: 0 | BC49: 0 | BD49: 0 | BE49: 0 | BF49: 0 | BG49: 0 | BH49: 0 | BI49: 0 | BJ49: 0 | BK49: 0 | BL49: 0 | BM49: 0 | BN49: 0 | BO49: 0 | BP49: 0 | BQ49: 0 | BR49: 0 | BS49: 0 | BT49: 0 | BU49: 0 | BV49: 0 | BW49: 0 | BX49: 0 | BY49: 0 | BZ49: 0 | CA49: 0 | CB49: 0 | CC49: 0
... A61: subregion60 | B61: 0 | C61: 0 | D61: 0 | E61: 0 | F61: 0 | G61: 0 | H61: 0 | I61: 0 | J61: 0 | K61: 0 | L61: 0 | M61: 0 | N61: 0 | O61: 0 | P61: 0 | Q61: 0 | R61: 0 | S61: 0 | T61: 0 | U61: 0 | V61: 0 | W61: 0 | X61: 0 | Y61: 0 | Z61: 0 | AA61: 0 | AB61: 0 | AC61: 0 | AD61: 0 | AE61: 0 | AF61: 0 | AG61: 0 | AH61: 0 | AI61: 0 | AJ61: 0 | AK61: 0 | AL61: 0 | AM61: 0 | AN61: 0 | AO61: 0 | AP61: 0 | AQ61: 0 | AR61: 0 | AS61: 0 | AT61: 0 | AU61: 0 | AV61: 0 | AW61: 0 | AX61: 0 | AY61: 0 | AZ61: 0 | BA61: 0 | BB61: 0 | BC61: 0 | BD61: 0 | BE61: 0 | BF61: 0 | BG61: 0 | BH61: 0 | BI61: 0 | BJ61: 0 | BK61: 0 | BL61: 0 | BM61: 0 | BN61: 0 | BO61: 0 | BP61: 0 | BQ61: 0 | BR61: 0 | BS61: 0 | BT61: 0 | BU61: 0 | BV61: 0 | BW61: 0 | BX61: 0 | BY61: 0 | BZ61: 0 | CA61: 0 | CB61: 0 | CC61: 0

Sheet Not Used ->
A1: The sheets to the right are not used in the calculations leading to the blue output tabs.
A2: They are retained here for reference and possible future use.

Sheet EIA 2020 ESRAP Table 10
A1: 2020 Utility Bundled Sales to Ultimate Customers- Total
A2: (Data from forms EIA-861- schedules 4A & 4D and EIA-861S)
A3: Entity | B3: State | C3: Ownership | D3: Customers (Count) | E3: Sales (Megawatthours) | F3: Revenues (Thousands Dollars) | G3: Average Price (cents/kWh)
A4: Alaska Electric Light&Power Co | B4: AK | C4: Investor Owned | D4: 17403 | E4: 384981 | F4: 44688.6 | G4: 11.608001
A5: Alaska Power and Telephone Co | B5: AK | C5: Investor Owned | D5: 8168 | E5: 64407 | F5: 17068 | G5: 26.500225
A6: Alaska Village Elec Coop, Inc | B6: AK | C6: Cooperative | D6: 11513 | E6: 120835 | F6: 53906.3 | G6: 44.611495
A7: Anchorage Municipal Light and Power | B7: AK | C7: Municipal | D7: 31291 | E7: 732828 | F7: 121486.1 | G7: 16.57771
A8: Chugach Electric Assn Inc | B8: AK | C8: Cooperative | D8: 112593 | E8: 1212687 | F8: 226490.8 | G8: 18.676773
A9: Golden Valley Elec Assn Inc | B9: AK | C9: Cooperative | D9: 47059 | E9: 1221811 | F9: 236609 | G9: 19.365434
A10: Homer Electric Assn Inc | B10: AK | C10: Cooperative | D10: 32511 | E10: 437105 | F10: 103146.7 | G10: 23.597694
A11: Ketchikan Public Utilities | B11: AK | C11: Municipal | D11: 7856 | E11: 166832 | F11: 18488.7 | G11: 11.082226
A12: Kodiak Electric Assn Inc | B12: AK | C12: Cooperative | D12: 6086 | E12: 139401 | F12: 22998 | G12: 16.49773
A13: Kotzebue Electric Assn Inc | B13: AK | C13: Cooperative | D13: 1293 | E13: 18915 | F13: 7374.6 | G13: 38.988105
A14: Matanuska Electric Assn Inc | B14: AK | C14: Cooperative | D14: 66667 | E14: 751476 | F14: 153435.2 | G14: 20.417844
A15: TDX North Slope Generating Co | B15: AK | C15: Investor Owned | D15: 165 | E15: 53030 | F15: 11562 | G15: 21.802753
... A1371: MidAmerican Energy Services, LLC | B1371: TX | C1371: Retail Power Marketer | D1371: 15379 | E1371: 1999738 | F1371: 143170.7 | G1371: 7.1594729
A1372: Morgan Stanley Capital Grp Inc | B1372: TX | C1372: Retail Power Marketer | D1372: 1 | E1372: 0 | F1372: 20338 | G1372: .
A1373: Navarro County Elec Coop, Inc | B1373: TX | C1373: Cooperative | D1373: 17307 | E1373: 532085 | F1373: 40300.1 | G1373: 7.5739966
A1374: Navasota Valley Elec Coop, Inc | B1374: TX | C1374: Cooperative | D1374: 20147 | E1374: 369665 | F1374: 34610.7 | G1374: 9.3627203
A1375: NextEra Energy Services, LLC | B1375: TX | C1375: Retail Power Marketer | D1375: 276133 | E1375: 9802936 | F1375: 831334.9 | G1375: 8.4804685
A1376: North Plains Electric Coop Inc | B1376: TX | C1376: Cooperative | D1376: 7122 | E1376: 372752 | F1376: 32634 | G1376: 8.7548826
A1377: Nueces Electric Cooperative | B1377: TX | C1377: Cooperative | D1377: 44596 | E1377: 997403 | F1377: 89447 | G1377: 8.9679899
A1378: Our Energy LLC | B1378: TX | C1378: Retail Power Marketer | D1378: 62719 | E1378: 1500109 | F1378: 134502 | G1378: 8.9661485
A1379: Panola-Harrison Elec Coop, Inc | B1379: TX | C1379: Cooperative | D1379: 10806 | E1379: 199755 | F1379: 17688 | G1379: 8.8548472
A1380: Pedernales Electric Coop, Inc | B1380: TX | C1380: Cooperative | D1380: 379832 | E1380: 6533473 | F1380: 630919.9 | G1380: 9.6567308
A1381: Pogo Energy LLC | B1381: TX | C1381: Retail Power Marketer | D1381: 13647 | E1381: 162924 | F1381: 11194.6 | G1381: 6.8710564
A1382: Pro Power Providers | B1382: TX | C1382: Retail Power Marketer | D1382: 178 | E1382: 519 | F1382: 53.7 | G1382: 10.346821
A1383: Pulse Power, LLC | B1383: TX | C1383: Retail Power Marketer | D1383: 75356 | E1383: 1220110 | F1383: 128014 | G1383: 10.492005
A1384: Reliant Energy Retail Services | B1384: TX | C1384: Retail Power Marketer | D1384: 1404752 | E1384: 39602218 | F1384: 3880617.6 | G1384: 9.7989906
... A1619: Withheld | B1619: TX | C1619: Retail Power Marketer | D1619: 24 | E1619: 6454584 | F1619: 216095.6 | G1619: 3.34794
A1620: Adjustment 2020 | B1620: AK | C1620: Other | D1620: 35725 | E1620: 613269 | F1620: 155580.8 | G1620: .
A1621: Adjustment 2020 | B1621: AL | C1621: Other | D1621: 70418 | E1621: 1371994 | F1621: 153714.5 | G1621: .
A1622: Adjustment 2020 | B1622: AR | C1622: Other | D1622: 28612 | E1622: 606815 | F1622: 65621.9 | G1622: .
A1623: Adjustment 2020 | B1623: AZ | C1623: Other | D1623: -43153 | E1623: 1457512 | F1623: 123329.6 | G1623: .
A1624: Adjustment 2020 | B1624: CA | C1624: Other | D1624: -327155 | E1624: 1836367 | F1624: 273111.2 | G1624: .
A1625: Adjustment 2020 | B1625: CO | C1625: Other | D1625: 58520 | E1625: 1151881 | F1625: 159910.9 | G1625: .
A1626: Adjustment 2020 | B1626: CT | C1626: Other | D1626: -17583 | E1626: 291718 | F1626: 40488.7 | G1626: .
A1627: Adjustment 2020 | B1627: DC | C1627: Other | D1627: -536 | E1627: 0 | F1627: 0 | G1627: .
A1628: Adjustment 2020 | B1628: DE | C1628: Other | D1628: 14372 | E1628: 388579 | F1628: 44066.3 | G1628: .
A1629: Adjustment 2020 | B1629: FL | C1629: Other | D1629: 49950 | E1629: 1142488 | F1629: 131572.3 | G1629: .
A1630: Adjustment 2020 | B1630: GA | C1630: Other | D1630: 150827 | E1630: 3505689 | F1630: 406105.2 | G1630: .
A1631: Adjustment 2020 | B1631: HI | C1631: Other | D1631: -19815 | E1631: 0 | F1631: 0 | G1631: .
... A1669: Adjustment 2020 | B1669: WY | C1669: Other | D1669: 49518 | E1669: 1048533 | F1669: 124972.4 | G1669: .
A1670: City of Macon - (MS) | B1670: MS | C1670: Municipal | D1670: 1189 | E1670: 25043 | F1670: 3021 | G1670: 12.063251
A1671: City of New Albany - (MS) | B1671: MS | C1671: Municipal | D1671: 10894 | E1671: 333680 | F1671: 30641 | G1671: 9.1827499
A1672: City of Okolona | B1672: MS | C1672: Municipal | D1672: 5281 | E1672: 92533 | F1672: 10657 | G1672: 11.516972
A1673: City of Oxford - (MS) | B1673: MS | C1673: Municipal | D1673: 9756 | E1673: 221242 | F1673: 23508 | G1673: 10.625469
A1674: City of Philadelphia - (MS) | B1674: MS | C1674: Municipal | D1674: 3834 | E1674: 117139 | F1674: 11809 | G1674: 10.081186
A1675: City of Starkville | B1675: MS | C1675: Municipal | D1675: 13682 | E1675: 437557 | F1675: 41104 | G1675: 9.3939761
A1676: City of Tupelo - (MS) | B1676: MS | C1676: Municipal | D1676: 15247 | E1676: 621426 | F1676: 53679 | G1676: 8.6380357
A1677: City of Water Valley - (MS) | B1677: MS | C1677: Municipal | D1677: 2048 | E1677: 66776 | F1677: 5327 | G1677: 7.977417
A1678: City of West Point - (MS) | B1678: MS | C1678: Municipal | D1678: 3911 | E1678: 81936 | F1678: 9793 | G1678: 11.952011
A1679: Clarksdale Public Utilities | B1679: MS | C1679: Municipal | D1679: 6474 | E1679: 122772 | F1679: 15509 | G1679: 12.632359
A1680: Coahoma Electric Power Assn | B1680: MS | C1680: Cooperative | D1680: 8021 | E1680: 165549 | F1680: 19002.5 | G1680: 11.478475
A1681: Coast Electric Power Assn | B1681: MS | C1681: Cooperative | D1681: 83541 | E1681: 1776192 | F1681: 192619 | G1681: 10.844492
... A2905: MidAmerican Energy Services, LLC | B2905: TX | C2905: Retail Energy Provider | D2905: 14204 | E2905: 1657364 | F2905: 121800 | G2905: 7.3490193
A2906: Morgan Stanley Capital Grp Inc | B2906: TX | C2906: Retail Energy Provider | D2906: 1 | E2906: 0 | F2906: 15821 | G2906: .
A2907: Navarro County Elec Coop, Inc | B2907: TX | C2907: Cooperative | D2907: 17005 | E2907: 548263 | F2907: 43592 | G2907: 7.9509287
A2908: Navasota Valley Elec Coop, Inc | B2908: TX | C2908: Cooperative | D2908: 19859 | E2908: 363587 | F2908: 35652.3 | G2908: 9.8057136
A2909: NextEra Energy Services, LLC | B2909: TX | C2909: Retail Energy Provider | D2909: 286560 | E2909: 9453911 | F2909: 828286.7 | G2909: 8.7613126
A2910: North American Power and Gas, LLC | B2910: TX | C2910: Retail Energy Provider | D2910: 314 | E2910: 1552 | F2910: 172.1 | G2910: 11.088918
A2911: North Plains Electric Coop Inc | B2911: TX | C2911: Cooperative | D2911: 7181 | E2911: 354723 | F2911: 32013 | G2911: 9.0247884
A2912: Nueces Electric Cooperative | B2912: TX | C2912: Cooperative | D2912: 42886 | E2912: 1308238 | F2912: 105882 | G2912: 8.0934815
A2913: Our Energy LLC | B2913: TX | C2913: Retail Energy Provider | D2913: 59521 | E2913: 1429862 | F2913: 124707 | G2913: 8.7216109
A2914: Panola-Harrison Elec Coop, Inc | B2914: TX | C2914: Cooperative | D2914: 10693 | E2914: 196605 | F2914: 18121.4 | G2914: 9.2171613
A2915: Pedernales Electric Coop, Inc | B2915: TX | C2915: Cooperative | D2915: 363712 | E2915: 6490606 | F2915: 631029.5 | G2915: 9.722197
A2916: Pogo Energy LLC | B2916: TX | C2916: Retail Energy Provider | D2916: 7878 | E2916: 92753 | F2916: 5961.6 | G2916: 6.4273932
A2917: Power Express | B2917: TX | C2917: Retail Energy Provider | D2917: 660 | E2917: 239 | F2917: 12.2 | G2917: 5.1046025
A2918: Pro Power Providers | B2918: TX | C2918: Retail Energy Provider | D2918: 4124 | E2918: 199186 | F2918: 17929.9 | G2918: 9.0015865
... A3310: Withheld | B3310: TX | C3310: Retail Energy Provider | D3310: 25 | E3310: 6817159 | F3310: 274409.4 | G3310: 4.025275
A3311: Adjustment 2019 | B3311: AK | C3311: Other | D3311: 5542 | E3311: 87938 | F3311: 30194.1 | G3311: .
A3312: Adjustment 2019 | B3312: AZ | C3312: Other | D3312: -83099 | E3312: 0 | F3312: 0 | G3312: .
A3313: Adjustment 2019 | B3313: CA | C3313: Other | D3313: -383660 | E3313: 0 | F3313: 0 | G3313: .
A3314: Adjustment 2019 | B3314: CO | C3314: Other | D3314: -20602 | E3314: 7205 | F3314: 790.6 | G3314: .
A3315: Adjustment 2019 | B3315: CT | C3315: Other | D3315: -24955 | E3315: 0 | F3315: 0 | G3315: .
A3316: Adjustment 2019 | B3316: DC | C3316: Other | D3316: -533 | E3316: 0 | F3316: 0 | G3316: .
A3317: Adjustment 2019 | B3317: DE | C3317: Other | D3317: -3749 | E3317: 0 | F3317: 0 | G3317: .
A3318: Adjustment 2019 | B3318: FL | C3318: Other | D3318: -2323 | E3318: 0 | F3318: 0 | G3318: .
A3319: Adjustment 2019 | B3319: GA | C3319: Other | D3319: 3976 | E3319: 54759 | F3319: 5437.1 | G3319: .
A3320: Adjustment 2019 | B3320: HI | C3320: Other | D3320: -17641 | E3320: 0 | F3320: 0 | G3320: .
A3321: Adjustment 2019 | B3321: IA | C3321: Other | D3321: 1562 | E3321: 29947 | F3321: 3587.6 | G3321: .
A3322: Adjustment 2019 | B3322: ID | C3322: Other | D3322: 52 | E3322: 794 | F3322: 70.3 | G3322: .
... A3353: Adjustment 2019 | B3353: WI | C3353: Other | D3353: -4 | E3353: 0 | F3353: 0 | G3353: .

Sheet BNL_RPS Targets (%)
C1: RPS Targets
M3: Contact: Galen Barbose
M4: Lawrence Berkeley National Laboratory
M5: (510) 495-2593, glbarbose@lbl.gov
M6: Last update: February 5, 2021
C24: RPS Targets (Percent of Applicable Retail Electricity Sales) | BE24: Search terms
C25: State | D25: Special Notes | E25: RPS Tier or Carve Out | F25: 2000 | G25: 2001 | H25: 2002 | I25: 2003 | J25: 2004 | K25: 2005 | L25: 2006 | M25: 2007 | N25: 2008 | O25: 2009 | P25: 2010 | Q25: 2011 | R25: 2012 | S25: 2013 | T25: 2014 | U25: 2015 | V25: 2016 | W25: 2017 | X25: 2018 | Y25: 2019 | Z25: 2020 | AA25: 2021 | AB25: 2022 | AC25: 2023 | AD25: 2024 | AE25: 2025 | AF25: 2026 | AG25: 2027 | AH25: 2028 | AI25: 2029 | AJ25: 2030 | AK25: 2031 | AL25: 2032 | AM25: 2033 | AN25: 2034 | AO25: 2035 | AP25: 2036 | AQ25: 2037 | AR25: 2038 | AS25: 2039 | AT25: 2040 | AU25: 2041 | AV25: 2042 | AW25: 2043 | AX25: 2044 | AY25: 2045 | AZ25: 2046 | BA25: 2047 | BB25: 2048 | BC25: 2049 | BD25: 2050 | BE25: State | BF25: Tier
A26: =IF(E26="Total RPS",1,0)+IF(E26="Total RPS (Wtd. Avg.)",1,0) -> 1 | B26: =INDEX(#REF!,MATCH('BNL_RPS Targets (%)'!C26,#REF!,0)) -> #REF! | C26: AZ | D26: Arizona had a solar carve-out, which was subsequently replaced by the current DG carve-out in 2008. | E26: Total RPS | F26: 0 | G26: 0.002 | H26: 0.004 | I26: 0.006 | J26: 0.008 | K26: 0.01 | L26: 0.0125 | M26: 0.015 | N26: 0.0175 | O26: 0.02 | P26: 0.025 | Q26: 0.03 | R26: 0.035 | S26: 0.04 | T26: 0.045 | U26: 0.05 | V26: 0.06 | W26: 0.07 | X26: 0.08 | Y26: 0.09 | Z26: 0.1 | AA26: 0.11 | AB26: 0.12 | AC26: 0.13 | AD26: 0.14 | AE26: 0.15 | AF26: 0.15 | AG26: 0.15 | AH26: 0.15 | AI26: 0.15 | AJ26: 0.15 | AK26: 0.15 | AL26: 0.15 | AM26: 0.15 | AN26: 0.15 | AO26: 0.15 | AP26: 0.15 | AQ26: 0.15 | AR26: 0.15 | AS26: 0.15 | AT26: 0.15 | AU26: 0.15 | AV26: 0.15 | AW26: 0.15 | AX26: 0.15 | AY26: 0.15 | AZ26: 0.15 | BA26: 0.15 | BB26: 0.15 | BC26: 0.15 | BD26: 0.15 | BE26: AZ | BF26: Total RPS
A27: =IF(E27="Total RPS",1,0)+IF(E27="Total RPS (Wtd. Avg.)",1,0) -> 0 | B27: =INDEX(#REF!,MATCH('BNL_RPS Targets (%)'!C27,#REF!,0)) -> #REF! | C27: AZ | E27: DG Carve-Out | F27: 0 | G27: 0 | H27: 0 | I27: 0 | J27: 0 | K27: 0 | L27: 0 | M27: 0 | N27: 0.00175 | O27: 0.003 | P27: 0.005 | Q27: 0.0075 | R27: 0.0105 | S27: 0.012 | T27: 0.0135 | U27: 0.015 | V27: 0.018 | W27: 0.021 | X27: 0.024 | Y27: 0.027 | Z27: 0.03 | AA27: 0.033 | AB27: 0.036 | AC27: 0.039 | AD27: 0.042 | AE27: 0.045 | AF27: 0.045 | AG27: 0.045 | AH27: 0.045 | AI27: 0.045 | AJ27: 0.045 | AK27: 0.045 | AL27: 0.045 | AM27: 0.045 | AN27: 0.045 | AO27: 0.045 | AP27: 0.045 | AQ27: 0.045 | AR27: 0.045 | AS27: 0.045 | AT27: 0.045 | AU27: 0.045 | AV27: 0.045 | AW27: 0.045 | AX27: 0.045 | AY27: 0.045 | AZ27: 0.045 | BA27: 0.045 | BB27: 0.045 | BC27: 0.045 | BD27: 0.045 | BE27: AZ | BF27: Solar or DG Carve-Out
A28: =IF(E28="Total RPS",1,0)+IF(E28="Total RPS (Wtd. Avg.)",1,0) -> 1 | B28: =INDEX(#REF!,MATCH('BNL_RPS Targets (%)'!C28,#REF!,0)) -> #REF! | C28: CA | D28: Through 2015, the values shown here represent targets for the state's three large IOUs through 2015 (targets for other utilities' were lower). From 2016 onward, the values shown here represent statewide targets applicable to all utilities. | E28: Total RPS | F28: 0 | G28: 0 | H28: 0 | I28: 0.11852494 | J28: 0.12852494 | K28: 0.13852494 | L28: 0.14852494 | M28: 0.15852494 | N28: 0.16852494 | O28: 0.17852494 | P28: 0.2 | Q28: 0.2 | R28: 0.2 | S28: 0.2 | T28: 0.217 | U28: 0.233 | V28: 0.25 | W28: 0.27 | X28: 0.29 | Y28: 0.31 | Z28: 0.33 | AA28: 0.33 | AB28: 0.33 | AC28: 0.33 | AD28: 0.44 | AE28: 0.44 | AF28: 0.44 | AG28: 0.52 | AH28: 0.52 | AI28: 0.52 | AJ28: 0.6 | AK28: 0.6 | AL28: 0.6 | AM28: 0.6 | AN28: 0.6 | AO28: 0.6 | AP28: 0.6 | AQ28: 0.6 | AR28: 0.6 | AS28: 0.6 | AT28: 0.6 | AU28: 0.6 | AV28: 0.6 | AW28: 0.6 | AX28: 0.6 | AY28: 0.6 | AZ28: 0.6 | BA28: 0.6 | BB28: 0.6 | BC28: 0.6 | BD28: 0.6 | BE28: CA | BF28: Total RPS
A29: =IF(E29="Total RPS",1,0)+IF(E29="Total RPS (Wtd. Avg.)",1,0) -> 1 | B29: =INDEX(#REF!,MATCH('BNL_RPS Targets (%)'!C29,#REF!,0)) -> #REF! | C29: CO | D29: Targets vary based on utility type and size, and whether the utility is served by a generation and transmission (G&T) cooperative. Weighted averages are based on the retail electricity sales of utilities subject to the RPS. | E29: Total RPS (Wtd. Avg.) | F29: 0 | G29: 0 | H29: 0 | I29: 0 | J29: 0 | K29: 0 | L29: 0 | M29: 0.03 | N29: 0.034567782 | O29: 0.034261979 | P29: 0.034203742 | Q29: 0.08435376 | R29: 0.084921879 | S29: 0.085100327 | T29: 0.084973227 | U29: 0.14498606 | V29: 0.144233 | W29: 0.14368257 | X29: 0.14191418 | Y29: 0.14191418 | Z29: 0.2410564 | AA29: 0.2410564 | AB29: 0.2410564 | AC29: 0.23922197 | AD29: 0.23922197 | AE29: 0.23922197 | AF29: 0.23922197 | AG29: 0.23922197 | AH29: 0.23922197 | AI29: 0.23922197 | AJ29: 0.23922197 | AK29: 0.23922197 | AL29: 0.23922197 | AM29: 0.23922197 | AN29: 0.23922197 | AO29: 0.23922197 | AP29: 0.23922197 | AQ29: 0.23922197 | AR29: 0.23922197 | AS29: 0.23922197 | AT29: 0.23922197 | AU29: 0.23922197 | AV29: 0.23922197 | AW29: 0.23922197 | AX29: 0.23922197 | AY29: 0.23922197 | AZ29: 0.23922197 | BA29: 0.23922197 | BB29: 0.23922197 | BC29: 0.23922197 | BD29: 0.23922197 | BE29: CO | BF29: Total RPS
A30: =IF(E30="Total RPS",1,0)+IF(E30="Total RPS (Wtd. Avg.)",1,0) -> 0 | B30: =INDEX(#REF!,MATCH('BNL_RPS Targets (%)'!C30,#REF!,0)) -> #REF! | C30: CO | E30: IOUs | F30: 0 | G30: 0 | H30: 0 | I30: 0 | J30: 0 | K30: 0 | L30: 0 | M30: 0.03 | N30: 0.05 | O30: 0.05 | P30: 0.05 | Q30: 0.12 | R30: 0.12 | S30: 0.12 | T30: 0.12 | U30: 0.2 | V30: 0.2 | W30: 0.2 | X30: 0.2 | Y30: 0.2 | Z30: 0.3 | AA30: 0.3 | AB30: 0.3 | AC30: 0.3 | AD30: 0.3 | AE30: 0.3 | AF30: 0.3 | AG30: 0.3 | AH30: 0.3 | AI30: 0.3 | AJ30: 0.3 | AK30: 0.3 | AL30: 0.3 | AM30: 0.3 | AN30: 0.3 | AO30: 0.3 | AP30: 0.3 | AQ30: 0.3 | AR30: 0.3 | AS30: 0.3 | AT30: 0.3 | AU30: 0.3 | AV30: 0.3 | AW30: 0.3 | AX30: 0.3 | AY30: 0.3 | AZ30: 0.3 | BA30: 0.3 | BB30: 0.3 | BC30: 0.3 | BD30: 0.3 | BE30: CO
A31: =IF(E31="Total RPS",1,0)+IF(E31="Total RPS (Wtd. Avg.)",1,0) -> 0 | B31: =INDEX(#REF!,MATCH('BNL_RPS Targets (%)'!C31,#REF!,0)) -> #REF! | C31: CO | E31: Coops (G&T-served or >100k customers) | F31: 0 | G31: 0 | H31: 0 | I31: 0 | J31: 0 | K31: 0 | L31: 0 | M31: 0 | N31: 0.01 | O31: 0.01 | P31: 0.01 | Q31: 0.03 | R31: 0.03 | S31: 0.03 | T31: 0.03 | U31: 0.06 | V31: 0.06 | W31: 0.06 | X31: 0.06 | Y31: 0.06 | Z31: 0.2 | AA31: 0.2 | AB31: 0.2 | AC31: 0.2 | AD31: 0.2 | AE31: 0.2 | AF31: 0.2 | AG31: 0.2 | AH31: 0.2 | AI31: 0.2 | AJ31: 0.2 | AK31: 0.2 | AL31: 0.2 | AM31: 0.2 | AN31: 0.2 | AO31: 0.2 | AP31: 0.2 | AQ31: 0.2 | AR31: 0.2 | AS31: 0.2 | AT31: 0.2 | AU31: 0.2 | AV31: 0.2 | AW31: 0.2 | AX31: 0.2 | AY31: 0.2 | AZ31: 0.2 | BA31: 0.2 | BB31: 0.2 | BC31: 0.2 | BD31: 0.2 | BE31: CO
A32: =IF(E32="Total RPS",1,0)+IF(E32="Total RPS (Wtd. Avg.)",1,0) -> 0 | B32: =INDEX(#REF!,MATCH('BNL_RPS Targets (%)'!C32,#REF!,0)) -> #REF! | C32: CO | E32: Munis & Non-G&T served Coops with <100k customers) | F32: 0 | G32: 0 | H32: 0 | I32: 0 | J32: 0 | K32: 0 | L32: 0 | M32: 0 | N32: 0.01 | O32: 0.01 | P32: 0.01 | Q32: 0.03 | R32: 0.03 | S32: 0.03 | T32: 0.03 | U32: 0.06 | V32: 0.06 | W32: 0.06 | X32: 0.06 | Y32: 0.06 | Z32: 0.1 | AA32: 0.1 | AB32: 0.1 | AC32: 0.1 | AD32: 0.1 | AE32: 0.1 | AF32: 0.1 | AG32: 0.1 | AH32: 0.1 | AI32: 0.1 | AJ32: 0.1 | AK32: 0.1 | AL32: 0.1 | AM32: 0.1 | AN32: 0.1 | AO32: 0.1 | AP32: 0.1 | AQ32: 0.1 | AR32: 0.1 | AS32: 0.1 | AT32: 0.1 | AU32: 0.1 | AV32: 0.1 | AW32: 0.1 | AX32: 0.1 | AY32: 0.1 | AZ32: 0.1 | BA32: 0.1 | BB32: 0.1 | BC32: 0.1 | BD32: 0.1 | BE32: CO
A33: =IF(E33="Total RPS",1,0)+IF(E33="Total RPS (Wtd. Avg.)",1,0) -> 0 | B33: =INDEX(#REF!,MATCH('BNL_RPS Targets (%)'!C33,#REF!,0)) -> #REF! | C33: CO | E33: DG Carve-Out (Wtd. Avg.) | F33: 0 | G33: 0 | H33: 0 | I33: 0 | J33: 0 | K33: 0 | L33: 0 | M33: 0 | N33: 0 | O33: 0 | P33: 0 | Q33: 0.0060393067 | R33: 0.0061024311 | S33: 0.0076528231 | T33: 0.0076351704 | U33: 0.010623257 | V33: 0.010529125 | W33: 0.011954652 | X33: 0.011702025 | Y33: 0.011702025 | Z33: 0.019456432 | AA33: 0.019456432 | AB33: 0.019456432 | AC33: 0.019203402 | AD33: 0.019203402 | AE33: 0.019203402 | AF33: 0.019203402 | AG33: 0.019203402 | AH33: 0.019203402 | AI33: 0.019203402 | AJ33: 0.019203402 | AK33: 0.019203402 | AL33: 0.019203402 | AM33: 0.019203402 | AN33: 0.019203402 | AO33: 0.019203402 | AP33: 0.019203402 | AQ33: 0.019203402 | AR33: 0.019203402 | AS33: 0.019203402 | AT33: 0.019203402 | AU33: 0.019203402 | AV33: 0.019203402 | AW33: 0.019203402 | AX33: 0.019203402 | AY33: 0.019203402 | AZ33: 0.019203402 | BA33: 0.019203402 | BB33: 0.019203402 | BC33: 0.019203402 | BD33: 0.019203402 | BE33: CO | BF33: Solar or DG Carve-Out
A34: =IF(E34="Total RPS",1,0)+IF(E34="Total RPS (Wtd. Avg.)",1,0) -> 0 | B34: =INDEX(#REF!,MATCH('BNL_RPS Targets (%)'!C34,#REF!,0)) -> #REF! | C34: CO | E34: IOUs | F34: 0 | G34: 0 | H34: 0 | I34: 0 | J34: 0 | K34: 0 | L34: 0 | M34: 0 | N34: 0 | O34: 0 | P34: 0 | Q34: 0.01 | R34: 0.01 | S34: 0.0125 | T34: 0.0125 | U34: 0.0175 | V34: 0.0175 | W34: 0.02 | X34: 0.02 | Y34: 0.02 | Z34: 0.03 | AA34: 0.03 | AB34: 0.03 | AC34: 0.03 | AD34: 0.03 | AE34: 0.03 | AF34: 0.03 | AG34: 0.03 | AH34: 0.03 | AI34: 0.03 | AJ34: 0.03 | AK34: 0.03 | AL34: 0.03 | AM34: 0.03 | AN34: 0.03 | AO34: 0.03 | AP34: 0.03 | AQ34: 0.03 | AR34: 0.03 | AS34: 0.03 | AT34: 0.03 | AU34: 0.03 | AV34: 0.03 | AW34: 0.03 | AX34: 0.03 | AY34: 0.03 | AZ34: 0.03 | BA34: 0.03 | BB34: 0.03 | BC34: 0.03 | BD34: 0.03 | BE34: CO
A35: =IF(E35="Total RPS",1,0)+IF(E35="Total RPS (Wtd. Avg.)",1,0) -> 0 | B35: =INDEX(#REF!,MATCH('BNL_RPS Targets (%)'!C35,#REF!,0)) -> #REF! | C35: CO | E35: Coops (>10k customers) | F35: 0 | G35: 0 | H35: 0 | I35: 0 | J35: 0 | K35: 0 | L35: 0 | M35: 0 | N35: 0 | O35: 0 | P35: 0 | Q35: 0 | R35: 0 | S35: 0 | T35: 0 | U35: 0 | V35: 0 | W35: 0 | X35: 0 | Y35: 0 | Z35: 0.01 | AA35: 0.01 | AB35: 0.01 | AC35: 0.01 | AD35: 0.01 | AE35: 0.01 | AF35: 0.01 | AG35: 0.01 | AH35: 0.01 | AI35: 0.01 | AJ35: 0.01 | AK35: 0.01 | AL35: 0.01 | AM35: 0.01 | AN35: 0.01 | AO35: 0.01 | AP35: 0.01 | AQ35: 0.01 | AR35: 0.01 | AS35: 0.01 | AT35: 0.01 | AU35: 0.01 | AV35: 0.01 | AW35: 0.01 | AX35: 0.01 | AY35: 0.01 | AZ35: 0.01 | BA35: 0.01 | BB35: 0.01 | BC35: 0.01 | BD35: 0.01 | BE35: CO
A36: =IF(E36="Total RPS",1,0)+IF(E36="Total RPS (Wtd. Avg.)",1,0) -> 0 | B36: =INDEX(#REF!,MATCH('BNL_RPS Targets (%)'!C36,#REF!,0)) -> #REF! | C36: CO | E36: Coops (<10k customers) | F36: 0 | G36: 0 | H36: 0 | I36: 0 | J36: 0 | K36: 0 | L36: 0 | M36: 0 | N36: 0 | O36: 0 | P36: 0 | Q36: 0 | R36: 0 | S36: 0 | T36: 0 | U36: 0 | V36: 0 | W36: 0 | X36: 0 | Y36: 0 | Z36: 0.0075 | AA36: 0.0075 | AB36: 0.0075 | AC36: 0.0075 | AD36: 0.0075 | AE36: 0.0075 | AF36: 0.0075 | AG36: 0.0075 | AH36: 0.0075 | AI36: 0.0075 | AJ36: 0.0075 | AK36: 0.0075 | AL36: 0.0075 | AM36: 0.0075 | AN36: 0.0075 | AO36: 0.0075 | AP36: 0.0075 | AQ36: 0.0075 | AR36: 0.0075 | AS36: 0.0075 | AT36: 0.0075 | AU36: 0.0075 | AV36: 0.0075 | AW36: 0.0075 | AX36: 0.0075 | AY36: 0.0075 | AZ36: 0.0075 | BA36: 0.0075 | BB36: 0.0075 | BC36: 0.0075 | BD36: 0.0075 | BE36: CO
A37: =IF(E37="Total RPS",1,0)+IF(E37="Total RPS (Wtd. Avg.)",1,0) -> 1 | B37: =INDEX(#REF!,MATCH('BNL_RPS Targets (%)'!C37,#REF!,0)) -> #REF! | C37: CT | D37: None | E37: Total RPS | F37: 0 | G37: 0.0625 | H37: 0.065 | I37: 0.07 | J37: 0.04 | K37: 0.045 | L37: 0.05 | M37: 0.065 | N37: 0.08 | O37: 0.09 | P37: 0.1 | Q37: 0.11 | R37: 0.12 | S37: 0.13 | T37: 0.14 | U37: 0.155 | V37: 0.17 | W37: 0.185 | X37: 0.21 | Y37: 0.235 | Z37: 0.25 | AA37: 0.265 | AB37: 0.28 | AC37: 0.3 | AD37: 0.32 | AE37: 0.34 | AF37: 0.36 | AG37: 0.38 | AH37: 0.4 | AI37: 0.42 | AJ37: 0.44 | AK37: 0.44 | AL37: 0.44 | AM37: 0.44 | AN37: 0.44 | AO37: 0.44 | AP37: 0.44 | AQ37: 0.44 | AR37: 0.44 | AS37: 0.44 | AT37: 0.44 | AU37: 0.44 | AV37: 0.44 | AW37: 0.44 | AX37: 0.44 | AY37: 0.44 | AZ37: 0.44 | BA37: 0.44 | BB37: 0.44 | BC37: 0.44 | BD37: 0.44 | BE37: CT | BF37: Total RPS
A38: =IF(E38="Total RPS",1,0)+IF(E38="Total RPS (Wtd. Avg.)",1,0) -> 0 | B38: =INDEX(#REF!,MATCH('BNL_RPS Targets (%)'!C38,#REF!,0)) -> #REF! | C38: CT | E38: Class I | F38: 0 | G38: 0.0075 | H38: 0.01 | I38: 0.015 | J38: 0.01 | K38: 0.015 | L38: 0.02 | M38: 0.035 | N38: 0.05 | O38: 0.06 | P38: 0.07 | Q38: 0.08 | R38: 0.09 | S38: 0.1 | T38: 0.11 | U38: 0.125 | V38: 0.14 | W38: 0.155 | X38: 0.17 | Y38: 0.195 | Z38: 0.21 | AA38: 0.225 | AB38: 0.24 | AC38: 0.26 | AD38: 0.28 | AE38: 0.3 | AF38: 0.32 | AG38: 0.34 | AH38: 0.36 | AI38: 0.38 | AJ38: 0.4 | AK38: 0.4 | AL38: 0.4 | AM38: 0.4 | AN38: 0.4 | AO38: 0.4 | AP38: 0.4 | AQ38: 0.4 | AR38: 0.4 | AS38: 0.4 | AT38: 0.4 | AU38: 0.4 | AV38: 0.4 | AW38: 0.4 | AX38: 0.4 | AY38: 0.4 | AZ38: 0.4 | BA38: 0.4 | BB38: 0.4 | BC38: 0.4 | BD38: 0.4 | BE38: CT | BF38: General RPS/Primary Tier
A39: =IF(E39="Total RPS",1,0)+IF(E39="Total RPS (Wtd. Avg.)",1,0) -> 0 | B39: =INDEX(#REF!,MATCH('BNL_RPS Targets (%)'!C39,#REF!,0)) -> #REF! | C39: CT | E39: Class II | F39: 0 | G39: 0.055 | H39: 0.055 | I39: 0.055 | J39: 0.03 | K39: 0.03 | L39: 0.03 | M39: 0.03 | N39: 0.03 | O39: 0.03 | P39: 0.03 | Q39: 0.03 | R39: 0.03 | S39: 0.03 | T39: 0.03 | U39: 0.03 | V39: 0.03 | W39: 0.03 | X39: 0.04 | Y39: 0.04 | Z39: 0.04 | AA39: 0.04 | AB39: 0.04 | AC39: 0.04 | AD39: 0.04 | AE39: 0.04 | AF39: 0.04 | AG39: 0.04 | AH39: 0.04 | AI39: 0.04 | AJ39: 0.04 | AK39: 0.04 | AL39: 0.04 | AM39: 0.04 | AN39: 0.04 | AO39: 0.04 | AP39: 0.04 | AQ39: 0.04 | AR39: 0.04 | AS39: 0.04 | AT39: 0.04 | AU39: 0.04 | AV39: 0.04 | AW39: 0.04 | AX39: 0.04 | AY39: 0.04 | AZ39: 0.04 | BA39: 0.04 | BB39: 0.04 | BC39: 0.04 | BD39: 0.04 | BE39: CT | BF39: Secondary Tier
A40: =IF(E40="Total RPS",1,0)+IF(E40="Total RPS (Wtd. Avg.)",1,0) -> 1 | B40: =INDEX(#REF!,MATCH('BNL_RPS Targets (%)'!C40,#REF!,0)) -> #REF! | C40: DC | D40: None | E40: Total RPS | F40: 0 | G40: 0 | H40: 0 | I40: 0 | J40: 0 | K40: 0 | L40: 0 | M40: 0.04 | N40: 0.045 | O40: 0.05 | P40: 0.055 | Q40: 0.065 | R40: 0.075 | S40: 0.09 | T40: 0.105 | U40: 0.12 | V40: 0.135 | W40: 0.15 | X40: 0.165 | Y40: 0.18 | Z40: 0.2 | AA40: 0.2625 | AB40: 0.325 | AC40: 0.3875 | AD40: 0.45 | AE40: 0.52 | AF40: 0.59 | AG40: 0.66 | AH40: 0.73 | AI40: 0.8 | AJ40: 0.87 | AK40: 0.94 | AL40: 1 | AM40: 1 | AN40: 1 | AO40: 1 | AP40: 1 | AQ40: 1 | AR40: 1 | AS40: 1 | AT40: 1 | AU40: 1 | AV40: 1 | AW40: 1 | AX40: 1 | AY40: 1 | AZ40: 1 | BA40: 1 | BB40: 1 | BC40: 1 | BD40: 1 | BE40: DC | BF40: Total RPS
A41: =IF(E41="Total RPS",1,0)+IF(E41="Total RPS (Wtd. Avg.)",1,0) -> 0 | B41: =INDEX(#REF!,MATCH('BNL_RPS Targets (%)'!C41,#REF!,0)) -> #REF! | C41: DC | E41: Solar Carve-Out | F41: 0 | G41: 0 | H41: 0 | I41: 0 | J41: 0 | K41: 0 | L41: 0 | M41: 0.0005 | N41: 0.0011 | O41: 0.0019 | P41: 0.0028 | Q41: 0.004 | R41: 0.005 | S41: 0.005 | T41: 0.006 | U41: 0.007 | V41: 0.0083 | W41: 0.0098 | X41: 0.0115 | Y41: 0.0185 | Z41: 0.02175 | AA41: 0.025 | AB41: 0.026 | AC41: 0.0285 | AD41: 0.0315 | AE41: 0.0345 | AF41: 0.0375 | AG41: 0.041 | AH41: 0.045 | AI41: 0.0475 | AJ41: 0.05 | AK41: 0.0525 | AL41: 0.055 | AM41: 0.06 | AN41: 0.065 | AO41: 0.07 | AP41: 0.075 | AQ41: 0.08 | AR41: 0.085 | AS41: 0.09 | AT41: 0.095 | AU41: 0.1 | AV41: 0.1 | AW41: 0.1 | AX41: 0.1 | AY41: 0.1 | AZ41: 0.1 | BA41: 0.1 | BB41: 0.1 | BC41: 0.1 | BD41: 0.1 | BE41: DC | BF41: Solar or DG Carve-Out
A42: =IF(E42="Total RPS",1,0)+IF(E42="Total RPS (Wtd. Avg.)",1,0) -> 0 | B42: =INDEX(#REF!,MATCH('BNL_RPS Targets (%)'!C42,#REF!,0)) -> #REF! | C42: DC | E42: Tier I Non-Solar | F42: 0 | G42: 0 | H42: 0 | I42: 0 | J42: 0 | K42: 0 | L42: 0 | M42: 0.0145 | N42: 0.0189 | O42: 0.0231 | P42: 0.0272 | Q42: 0.036 | R42: 0.045 | S42: 0.06 | T42: 0.074 | U42: 0.088 | V42: 0.1067 | W42: 0.1252 | X42: 0.1435 | Y42: 0.1565 | Z42: 0.17825 | AA42: 0.2375 | AB42: 0.299 | AC42: 0.359 | AD42: 0.4185 | AE42: 0.4855 | AF42: 0.5525 | AG42: 0.619 | AH42: 0.685 | AI42: 0.7525 | AJ42: 0.82 | AK42: 0.8875 | AL42: 0.945 | AM42: 0.94 | AN42: 0.935 | AO42: 0.93 | AP42: 0.925 | AQ42: 0.92 | AR42: 0.915 | AS42: 0.91 | AT42: 0.905 | AU42: 0.9 | AV42: 0.9 | AW42: 0.9 | AX42: 0.9 | AY42: 0.9 | AZ42: 0.9 | BA42: 0.9 | BB42: 0.9 | BC42: 0.9 | BD42: 0.9 | BE42: DC | BF42: General RPS/Primary Tier
A43: =IF(E43="Total RPS",1,0)+IF(E43="Total RPS (Wtd. Avg.)",1,0) -> 0 | B43: =INDEX(#REF!,MATCH('BNL_RPS Targets (%)'!C43,#REF!,0)) -> #REF! | C43: DC | E43: Tier II | F43: 0 | G43: 0 | H43: 0 | I43: 0 | J43: 0 | K43: 0 | L43: 0 | M43: 0.025 | N43: 0.025 | O43: 0.025 | P43: 0.025 | Q43: 0.025 | R43: 0.025 | S43: 0.025 | T43: 0.025 | U43: 0.025 | V43: 0.02 | W43: 0.015 | X43: 0.01 | Y43: 0.005 | Z43: 0 | AA43: 0 | AB43: 0 | AC43: 0 | AD43: 0 | AE43: 0 | AF43: 0 | AG43: 0 | AH43: 0 | AI43: 0 | AJ43: 0 | AK43: 0 | AL43: 0 | AM43: 0 | AN43: 0 | AO43: 0 | AP43: 0 | AQ43: 0 | AR43: 0 | AS43: 0 | AT43: 0 | AU43: 0 | AV43: 0 | AW43: 0 | AX43: 0 | AY43: 0 | AZ43: 0 | BA43: 0 | BB43: 0 | BC43: 0 | BD43: 0 | BE43: DC | BF43: Secondary Tier
A44: =IF(E44="Total RPS",1,0)+IF(E44="Total RPS (Wtd. Avg.)",1,0) -> 1 | B44: =INDEX(#REF!,MATCH('BNL_RPS Targets (%)'!C44,#REF!,0)) -> #REF! | C44: DE | D44: None | E44: Total RPS | F44: 0 | G44: 0 | H44: 0 | I44: 0 | J44: 0 | K44: 0 | L44: 0 | M44: 0 | N44: 0 | O44: 0 | P44: 0 | Q44: 0 | R44: 0 | S44: 0 | T44: 0.1 | U44: 0.115 | V44: 0.13 | W44: 0.145 | X44: 0.16 | Y44: 0.175 | Z44: 0.19 | AA44: 0.2 | AB44: 0.21 | AC44: 0.22 | AD44: 0.23 | AE44: 0.24 | AF44: 0.25 | AG44: 0.25 | AH44: 0.25 | AI44: 0.25 | AJ44: 0.25 | AK44: 0.25 | AL44: 0.25 | AM44: 0.25 | AN44: 0.25 | AO44: 0.25 | AP44: 0.25 | AQ44: 0.25 | AR44: 0.25 | AS44: 0.25 | AT44: 0.25 | AU44: 0.25 | AV44: 0.25 | AW44: 0.25 | AX44: 0.25 | AY44: 0.25 | AZ44: 0.25 | BA44: 0.25 | BB44: 0.25 | BC44: 0.25 | BD44: 0.25 | BE44: DE | BF44: Total RPS
A45: =IF(E45="Total RPS",1,0)+IF(E45="Total RPS (Wtd. Avg.)",1,0) -> 0 | B45: =INDEX(#REF!,MATCH('BNL_RPS Targets (%)'!C45,#REF!,0)) -> #REF! | C45: DE | E45: Solar Carve-Out | F45: 0 | G45: 0 | H45: 0 | I45: 0 | J45: 0 | K45: 0 | L45: 0 | M45: 0 | N45: 0 | O45: 0.00011 | P45: 0.00014 | Q45: 0.00018 | R45: 0.002 | S45: 0.004 | T45: 0.006 | U45: 0.008 | V45: 0.01 | W45: 0.0125 | X45: 0.015 | Y45: 0.0175 | Z45: 0.02 | AA45: 0.0225 | AB45: 0.025 | AC45: 0.0275 | AD45: 0.03 | AE45: 0.0325 | AF45: 0.035 | AG45: 0.035 | AH45: 0.035 | AI45: 0.035 | AJ45: 0.035 | AK45: 0.035 | AL45: 0.035 | AM45: 0.035 | AN45: 0.035 | AO45: 0.035 | AP45: 0.035 | AQ45: 0.035 | AR45: 0.035 | AS45: 0.035 | AT45: 0.035 | AU45: 0.035 | AV45: 0.035 | AW45: 0.035 | AX45: 0.035 | AY45: 0.035 | AZ45: 0.035 | BA45: 0.035 | BB45: 0.035 | BC45: 0.035 | BD45: 0.035 | BE45: DE | BF45: Solar or DG Carve-Out
A46: =IF(E46="Total RPS",1,0)+IF(E46="Total RPS (Wtd. Avg.)",1,0) -> 0 | B46: =INDEX(#REF!,MATCH('BNL_RPS Targets (%)'!C46,#REF!,0)) -> #REF! | C46: DE | E46: New Non-Solar | F46: 0 | G46: 0 | H46: 0 | I46: 0 | J46: 0 | K46: 0 | L46: 0 | M46: 0 | N46: 0 | O46: 0 | P46: 0 | Q46: 0 | R46: 0 | S46: 0 | T46: 0.084 | U46: 0.097 | V46: 0.11 | W46: 0.1225 | X46: 0.135 | Y46: 0.1475 | Z46: 0.17 | AA46: 0.1775 | AB46: 0.185 | AC46: 0.1925 | AD46: 0.2 | AE46: 0.2075 | AF46: 0.215 | AG46: 0.215 | AH46: 0.215 | AI46: 0.215 | AJ46: 0.215 | AK46: 0.215 | AL46: 0.215 | AM46: 0.215 | AN46: 0.215 | AO46: 0.215 | AP46: 0.215 | AQ46: 0.215 | AR46: 0.215 | AS46: 0.215 | AT46: 0.215 | AU46: 0.215 | AV46: 0.215 | AW46: 0.215 | AX46: 0.215 | AY46: 0.215 | AZ46: 0.215 | BA46: 0.215 | BB46: 0.215 | BC46: 0.215 | BD46: 0.215 | BE46: DE | BF46: General RPS/Primary Tier
A47: =IF(E47="Total RPS",1,0)+IF(E47="Total RPS (Wtd. Avg.)",1,0) -> 0 | B47: =INDEX(#REF!,MATCH('BNL_RPS Targets (%)'!C47,#REF!,0)) -> #REF! | C47: DE | E47: Existing | F47: 0 | G47: 0 | H47: 0 | I47: 0 | J47: 0 | K47: 0 | L47: 0 | M47: 0 | N47: 0.01 | O47: 0.01 | P47: 0.01 | Q47: 0.01 | R47: 0.01 | S47: 0.01 | T47: 0.01 | U47: 0.01 | V47: 0.01 | W47: 0.01 | X47: 0.01 | Y47: 0.01 | Z47: 0 | AA47: 0 | AB47: 0 | AC47: 0 | AD47: 0 | AE47: 0 | AF47: 0 | AG47: 0 | AH47: 0 | AI47: 0 | AJ47: 0 | AK47: 0 | AL47: 0 | AM47: 0 | AN47: 0 | AO47: 0 | AP47: 0 | AQ47: 0 | AR47: 0 | AS47: 0 | AT47: 0 | AU47: 0 | AV47: 0 | AW47: 0 | AX47: 0 | AY47: 0 | AZ47: 0 | BA47: 0 | BB47: 0 | BC47: 0 | BD47: 0 | BE47: DE | BF47: Secondary Tier
A48: =IF(E48="Total RPS",1,0)+IF(E48="Total RPS (Wtd. Avg.)",1,0) -> 1 | B48: =INDEX(#REF!,MATCH('BNL_RPS Targets (%)'!C48,#REF!,0)) -> #REF! | C48: HI | D48: None | E48: Total RPS | F48: 0 | G48: 0 | H48: 0 | I48: 0 | J48: 0 | K48: 0.08 | L48: 0 | M48: 0 | N48: 0 | O48: 0 | P48: 0.1 | Q48: 0.1 | R48: 0.1 | S48: 0.1 | T48: 0.1 | U48: 0.15 | V48: 0.15 | W48: 0.15 | X48: 0.15 | Y48: 0.15 | Z48: 0.3 | AA48: 0.3 | AB48: 0.3 | AC48: 0.3 | AD48: 0.3 | AE48: 0.3 | AF48: 0.3 | AG48: 0.3 | AH48: 0.3 | AI48: 0.3 | AJ48: 0.4 | AK48: 0.4 | AL48: 0.4 | AM48: 0.4 | AN48: 0.4 | AO48: 0.4 | AP48: 0.4 | AQ48: 0.4 | AR48: 0.4 | AS48: 0.4 | AT48: 0.7 | AU48: 0.7 | AV48: 0.7 | AW48: 0.7 | AX48: 0.7 | AY48: 1 | AZ48: 1 | BA48: 1 | BB48: 1 | BC48: 1 | BD48: 1 | BE48: HI | BF48: Total RPS
A49: =IF(E49="Total RPS",1,0)+IF(E49="Total RPS (Wtd. Avg.)",1,0) -> 1 | B49: =INDEX(#REF!,MATCH('BNL_RPS Targets (%)'!C49,#REF!,0)) -> #REF! | C49: IA | D49: RPS target denominated in MW terms; translated to equivalent percentage of applicable sales | E49: Total RPS | F49: 0.010000416 | G49: 0.0099997035 | H49: 0.0096149299 | I49: 0.0096224775 | J49: 0.009826096 | K49: 0.0092528337 | L49: 0.0090790219 | M49: 0.008729176 | N49: 0.0087380653 | O49: 0.0092105431 | P49: 0.0087343927 | Q49: 0.008676656 | R49: 0.0086437624 | S49: 0.0084989879 | T49: 0.0084023867 | U49: 0.0083727842 | V49: 0.0081420119 | W49: 0.0080470209 | X49: 0.0077077294 | Y49: 0.0076030434 | Z49: 0.0077522263 | AA49: 0.0076788991 | AB49: 0.0076033105 | AC49: 0.0075546275 | AD49: 0.0075056853 | AE49: 0.0074590358 | AF49: 0.0074113337 | AG49: 0.0073804203 | AH49: 0.0073280197 | AI49: 0.0072829183 | AJ49: 0.0072402793 | AK49: 0.0072063461 | AL49: 0.0071687792 | AM49: 0.0071321816 | AN49: 0.0070800692 | AO49: 0.0070353382 | AP49: 0.0069961166 | AQ49: 0.0069448411 | AR49: 0.0068996039 | AS49: 0.006850558 | AT49: 0.0068059574 | AU49: 0.0067586053 | AV49: 0.0067108024 | AW49: 0.0066621081 | AX49: 0.0066101924 | AY49: 0.0065608432 | AZ49: 0.0065109868 | BA49: 0.006458243 | BB49: 0.006408411 | BC49: 0.0063535222 | BD49: 0.0063028468 | BE49: IA | BF49: Total RPS
A50: =IF(E50="Total RPS",1,0)+IF(E50="Total RPS (Wtd. Avg.)",1,0) -> 1 | B50: =INDEX(#REF!,MATCH('BNL_RPS Targets (%)'!C50,#REF!,0)) -> #REF! | C50: IL | D50: Until recently, Illinois had a different set of solar and DG carve-outs, applicable only to the IOUs fixed-price service load. Those have since been phased out and replaced with the statewide "New Solar" requirement, which has a DG component. | E50: Total RPS | F50: 0 | G50: 0 | H50: 0 | I50: 0 | J50: 0 | K50: 0 | L50: 0 | M50: 0 | N50: 0 | O50: 0.02 | P50: 0.04 | Q50: 0.05 | R50: 0.06 | S50: 0.07 | T50: 0.08 | U50: 0.09 | V50: 0.1 | W50: 0.115 | X50: 0.13 | Y50: 0.145 | Z50: 0.16 | AA50: 0.175 | AB50: 0.19 | AC50: 0.205 | AD50: 0.22 | AE50: 0.235 | AF50: 0.25 | AG50: 0.25 | AH50: 0.25 | AI50: 0.25 | AJ50: 0.25 | AK50: 0.25 | AL50: 0.25 | AM50: 0.25 | AN50: 0.25 | AO50: 0.25 | AP50: 0.25 | AQ50: 0.25 | AR50: 0.25 | AS50: 0.25 | AT50: 0.25 | AU50: 0.25 | AV50: 0.25 | AW50: 0.25 | AX50: 0.25 | AY50: 0.25 | AZ50: 0.25 | BA50: 0.25 | BB50: 0.25 | BC50: 0.25 | BD50: 0.25 | BE50: IL | BF50: Total RPS
A51: =IF(E51="Total RPS",1,0)+IF(E51="Total RPS (Wtd. Avg.)",1,0) -> 0 | B51: =INDEX(#REF!,MATCH('BNL_RPS Targets (%)'!C51,#REF!,0)) -> #REF! | C51: IL | E51: New Wind Requirement | F51: 0 | G51: 0 | H51: 0 | I51: 0 | J51: 0 | K51: 0 | L51: 0 | M51: 0 | N51: 0 | O51: 0 | P51: 0 | Q51: 0 | R51: 0 | S51: 0 | T51: 0 | U51: 0 | V51: 0 | W51: 0 | X51: 0 | Y51: 0 | Z51: 0 | AA51: 0.015370435 | AB51: 0.01503136 | AC51: 0.014894438 | AD51: 0.014821859 | AE51: 0.014749311 | AF51: 0.022036377 | AG51: 0.021934053 | AH51: 0.021882682 | AI51: 0.02173226 | AJ51: 0.021617039 | AK51: 0.028672975 | AL51: 0.0285465 | AM51: 0.028404458 | AN51: 0.028280981 | AO51: 0.028079558 | AP51: 0.027911321 | AQ51: 0.027775754 | AR51: 0.027575094 | AS51: 0.027412356 | AT51: 0.027232156 | AU51: 0.027073433 | AV51: 0.026906195 | AW51: 0.026736295 | AX51: 0.026556181 | AY51: 0.02636178 | AZ51: 0.026176881 | BA51: 0.025984992 | BB51: 0.025777555 | BC51: 0.025585681 | BD51: 0.025371333 | BE51: IL
A52: =IF(E52="Total RPS",1,0)+IF(E52="Total RPS (Wtd. Avg.)",1,0) -> 0 | B52: =INDEX(#REF!,MATCH('BNL_RPS Targets (%)'!C52,#REF!,0)) -> #REF! | C52: IL | E52: New Solar Requirement (total) | F52: 0 | G52: 0 | H52: 0 | I52: 0 | J52: 0 | K52: 0 | L52: 0 | M52: 0 | N52: 0 | O52: 0 | P52: 0 | Q52: 0 | R52: 0 | S52: 0 | T52: 0 | U52: 0 | V52: 0 | W52: 0 | X52: 0 | Y52: 0 | Z52: 0 | AA52: 0.015370435 | AB52: 0.01503136 | AC52: 0.014894438 | AD52: 0.014821859 | AE52: 0.014749311 | AF52: 0.022036377 | AG52: 0.021934053 | AH52: 0.021882682 | AI52: 0.02173226 | AJ52: 0.021617039 | AK52: 0.028672975 | AL52: 0.0285465 | AM52: 0.028404458 | AN52: 0.028280981 | AO52: 0.028079558 | AP52: 0.027911321 | AQ52: 0.027775754 | AR52: 0.027575094 | AS52: 0.027412356 | AT52: 0.027232156 | AU52: 0.027073433 | AV52: 0.026906195 | AW52: 0.026736295 | AX52: 0.026556181 | AY52: 0.02636178 | AZ52: 0.026176881 | BA52: 0.025984992 | BB52: 0.025777555 | BC52: 0.025585681 | BD52: 0.025371333 | BE52: IL | BF52: Solar or DG Carve-Out
A53: =IF(E53="Total RPS",1,0)+IF(E53="Total RPS (Wtd. Avg.)",1,0) -> 0 | B53: =INDEX(#REF!,MATCH('BNL_RPS Targets (%)'!C53,#REF!,0)) -> #REF! | C53: IL | E53: New Solar Requirement (DG portion) | F53: 0 | G53: 0 | H53: 0 | I53: 0 | J53: 0 | K53: 0 | L53: 0 | M53: 0 | N53: 0 | O53: 0 | P53: 0 | Q53: 0 | R53: 0 | S53: 0 | T53: 0 | U53: 0 | V53: 0 | W53: 0 | X53: 0 | Y53: 0 | Z53: 0 | AA53: 0.0038426087 | AB53: 0.00375784 | AC53: 0.0037236096 | AD53: 0.0037054648 | AE53: 0.0036873277 | AF53: 0.0055090942 | AG53: 0.0054835133 | AH53: 0.0054706705 | AI53: 0.0054330651 | AJ53: 0.0054042597 | AK53: 0.0071682439 | AL53: 0.0071366249 | AM53: 0.0071011146 | AN53: 0.0070702453 | AO53: 0.0070198894 | AP53: 0.0069778302 | AQ53: 0.0069439386 | AR53: 0.0068937734 | AS53: 0.006853089 | AT53: 0.0068080389 | AU53: 0.0067683582 | AV53: 0.0067265487 | AW53: 0.0066840736 | AX53: 0.0066390453 | AY53: 0.0065904449 | AZ53: 0.0065442202 | BA53: 0.0064962481 | BB53: 0.0064443888 | BC53: 0.0063964202 | BD53: 0.0063428332 | BE53: IL
A54: =IF(E54="Total RPS",1,0)+IF(E54="Total RPS (Wtd. Avg.)",1,0) -> 1 | B54: =INDEX(#REF!,MATCH('BNL_RPS Targets (%)'!C54,#REF!,0)) -> #REF! | C54: MA | D54: Class I (Solar) consists of the SREC I, SREC II, and SMART programs; the targets for those programs are denominated in MW and translated here to the equivalent percentage of retail electricity sales. | E54: Total RPS | F54: 0 | G54: 0 | H54: 0 | I54: 0.01 | J54: 0.015 | K54: 0.02 | L54: 0.025 | M54: 0.03 | N54: 0.035 | O54: 0.111 | P54: 0.121 | Q54: 0.131 | R54: 0.141 | S54: 0.13 | T54: 0.143 | U54: 0.155 | V54: 0.170319 | W54: 0.180909 | X54: 0.191155 | Y54: 0.201833 | Z54: 0.227056 | AA54: 0.247056 | AB54: 0.267056 | AC54: 0.287056 | AD54: 0.307056 | AE54: 0.327056 | AF54: 0.347056 | AG54: 0.367056 | AH54: 0.387056 | AI54: 0.407056 | AJ54: 0.417056 | AK54: 0.427056 | AL54: 0.437056 | AM54: 0.447056 | AN54: 0.457056 | AO54: 0.467056 | AP54: 0.477056 | AQ54: 0.487056 | AR54: 0.497056 | AS54: 0.507056 | AT54: 0.517056 | AU54: 0.527056 | AV54: 0.537056 | AW54: 0.547056 | AX54: 0.557056 | AY54: 0.567056 | AZ54: 0.577056 | BA54: 0.587056 | BB54: 0.597056 | BC54: 0.607056 | BD54: 0.617056 | BE54: MA | BF54: Total RPS
A55: =IF(E55="Total RPS",1,0)+IF(E55="Total RPS (Wtd. Avg.)",1,0) -> 0 | B55: =INDEX(#REF!,MATCH('BNL_RPS Targets (%)'!C55,#REF!,0)) -> #REF! | C55: MA | E55: Class I (Solar Carve-Out) | F55: 0 | G55: 0 | H55: 0 | I55: 0 | J55: 0 | K55: 0 | L55: 0 | M55: 0 | N55: 0 | O55: 0 | P55: 0.00069827709 | Q55: 0.001656559 | R55: 0.0017027194 | S55: 0.0039593834 | T55: 0.010794288 | U55: 0.026018207 | V55: 0.027329556 | W55: 0.050886347 | X55: 0.064192724 | Y55: 0.066579894 | Z55: 0.079791567 | AA55: 0.091744135 | AB55: 0.10423796 | AC55: 0.11670955 | AD55: 0.12925454 | AE55: 0.14205985 | AF55: 0.15452612 | AG55: 0.16124754 | AH55: 0.16081423 | AI55: 0.1595618 | AJ55: 0.15855419 | AK55: 0.15748631 | AL55: 0.15656221 | AM55: 0.15579622 | AN55: 0.15502418 | AO55: 0.1538744 | AP55: 0.15284918 | AQ55: 0.15174285 | AR55: 0.15099412 | AS55: 0.15018517 | AT55: 0.14923862 | AU55: 0.14822261 | AV55: 0.14722471 | AW55: 0.14608659 | AX55: 0.14494014 | AY55: 0.14378201 | AZ55: 0.14256611 | BA55: 0.14132659 | BB55: 0.13999102 | BC55: 0.13862526 | BD55: 0.13728984 | BE55: MA | BF55: Solar or DG Carve-Out
A56: =IF(E56="Total RPS",1,0)+IF(E56="Total RPS (Wtd. Avg.)",1,0) -> 0 | B56: =INDEX(#REF!,MATCH('BNL_RPS Targets (%)'!C56,#REF!,0)) -> #REF! | C56: MA | E56: Class I (Non-Solar) | F56: 0 | G56: 0 | H56: 0 | I56: 0.01 | J56: 0.015 | K56: 0.02 | L56: 0.025 | M56: 0.03 | N56: 0.035 | O56: 0.04 | P56: 0.049301723 | Q56: 0.058343441 | R56: 0.068297281 | S56: 0.076040617 | T56: 0.079205712 | U56: 0.073981793 | V56: 0.082670444 | W56: 0.069113653 | X56: 0.065807276 | Y56: 0.073420106 | Z56: 0.080208433 | AA56: 0.088255865 | AB56: 0.095762044 | AC56: 0.10329045 | AD56: 0.11074546 | AE56: 0.11794015 | AF56: 0.12547388 | AG56: 0.13875246 | AH56: 0.15918577 | AI56: 0.1804382 | AJ56: 0.19144581 | AK56: 0.20251369 | AL56: 0.21343779 | AM56: 0.22420378 | AN56: 0.23497582 | AO56: 0.2461256 | AP56: 0.25715082 | AQ56: 0.26825715 | AR56: 0.27900588 | AS56: 0.28981483 | AT56: 0.30076138 | AU56: 0.31177739 | AV56: 0.32277529 | AW56: 0.33391341 | AX56: 0.34505986 | AY56: 0.35621799 | AZ56: 0.36743389 | BA56: 0.37867341 | BB56: 0.39000898 | BC56: 0.40137474 | BD56: 0.41271016 | BE56: MA | BF56: General RPS/Primary Tier
A57: =IF(E57="Total RPS",1,0)+IF(E57="Total RPS (Wtd. Avg.)",1,0) -> 0 | B57: =INDEX(#REF!,MATCH('BNL_RPS Targets (%)'!C57,#REF!,0)) -> #REF! | C57: MA | E57: Class II Existing RE | F57: 0 | G57: 0 | H57: 0 | I57: 0 | J57: 0 | K57: 0 | L57: 0 | M57: 0 | N57: 0 | O57: 0.036 | P57: 0.036 | Q57: 0.036 | R57: 0.036 | S57: 0.015 | T57: 0.018 | U57: 0.02 | V57: 0.025319 | W57: 0.025909 | X57: 0.026155 | Y57: 0.026833 | Z57: 0.032056 | AA57: 0.032056 | AB57: 0.032056 | AC57: 0.032056 | AD57: 0.032056 | AE57: 0.032056 | AF57: 0.032056 | AG57: 0.032056 | AH57: 0.032056 | AI57: 0.032056 | AJ57: 0.032056 | AK57: 0.032056 | AL57: 0.032056 | AM57: 0.032056 | AN57: 0.032056 | AO57: 0.032056 | AP57: 0.032056 | AQ57: 0.032056 | AR57: 0.032056 | AS57: 0.032056 | AT57: 0.032056 | AU57: 0.032056 | AV57: 0.032056 | AW57: 0.032056 | AX57: 0.032056 | AY57: 0.032056 | AZ57: 0.032056 | BA57: 0.032056 | BB57: 0.032056 | BC57: 0.032056 | BD57: 0.032056 | BE57: MA | BF57: Secondary Tier
A58: =IF(E58="Total RPS",1,0)+IF(E58="Total RPS (Wtd. Avg.)",1,0) -> 0 | B58: =INDEX(#REF!,MATCH('BNL_RPS Targets (%)'!C58,#REF!,0)) -> #REF! | C58: MA | E58: Class II MSW | F58: 0 | G58: 0 | H58: 0 | I58: 0 | J58: 0 | K58: 0 | L58: 0 | M58: 0 | N58: 0 | O58: 0.035 | P58: 0.035 | Q58: 0.035 | R58: 0.035 | S58: 0.035 | T58: 0.035 | U58: 0.035 | V58: 0.035 | W58: 0.035 | X58: 0.035 | Y58: 0.035 | Z58: 0.035 | AA58: 0.035 | AB58: 0.035 | AC58: 0.035 | AD58: 0.035 | AE58: 0.035 | AF58: 0.035 | AG58: 0.035 | AH58: 0.035 | AI58: 0.035 | AJ58: 0.035 | AK58: 0.035 | AL58: 0.035 | AM58: 0.035 | AN58: 0.035 | AO58: 0.035 | AP58: 0.035 | AQ58: 0.035 | AR58: 0.035 | AS58: 0.035 | AT58: 0.035 | AU58: 0.035 | AV58: 0.035 | AW58: 0.035 | AX58: 0.035 | AY58: 0.035 | AZ58: 0.035 | BA58: 0.035 | BB58: 0.035 | BC58: 0.035 | BD58: 0.035 | BE58: MA | BF58: Secondary Tier
A59: =IF(E59="Total RPS",1,0)+IF(E59="Total RPS (Wtd. Avg.)",1,0) -> 1 | B59: =INDEX(#REF!,MATCH('BNL_RPS Targets (%)'!C59,#REF!,0)) -> #REF! | C59: MD | D59: Offshore wind carve-out target includes both Round 1 and Round 2 solicitations, with MW targets translated to percentage of retail sales | E59: Total RPS | F59: 0 | G59: 0 | H59: 0 | I59: 0 | J59: 0 | K59: 0 | L59: 0.035 | M59: 0.035 | N59: 0.04505 | O59: 0.0451 | P59: 0.05525 | Q59: 0.075 | R59: 0.09 | S59: 0.107 | T59: 0.128 | U59: 0.13 | V59: 0.152 | W59: 0.156 | X59: 0.183 | Y59: 0.232 | Z59: 0.305 | AA59: 0.308 | AB59: 0.331 | AC59: 0.354 | AD59: 0.377 | AE59: 0.4 | AF59: 0.425 | AG59: 0.455 | AH59: 0.475 | AI59: 0.485 | AJ59: 0.5 | AK59: 0.5 | AL59: 0.5 | AM59: 0.5 | AN59: 0.5 | AO59: 0.5 | AP59: 0.5 | AQ59: 0.5 | AR59: 0.5 | AS59: 0.5 | AT59: 0.5 | AU59: 0.5 | AV59: 0.5 | AW59: 0.5 | AX59: 0.5 | AY59: 0.5 | AZ59: 0.5 | BA59: 0.5 | BB59: 0.5 | BC59: 0.5 | BD59: 0.5 | BE59: MD | BF59: Total RPS
A60: =IF(E60="Total RPS",1,0)+IF(E60="Total RPS (Wtd. Avg.)",1,0) -> 0 | B60: =INDEX(#REF!,MATCH('BNL_RPS Targets (%)'!C60,#REF!,0)) -> #REF! | C60: MD | E60: Solar Carve-Out | F60: 0 | G60: 0 | H60: 0 | I60: 0 | J60: 0 | K60: 0 | L60: 0 | M60: 0 | N60: 5e-05 | O60: 0.0001 | P60: 0.00025 | Q60: 0.0005 | R60: 0.001 | S60: 0.0025 | T60: 0.0035 | U60: 0.005 | V60: 0.007 | W60: 0.0115 | X60: 0.015 | Y60: 0.055 | Z60: 0.06 | AA60: 0.075 | AB60: 0.085 | AC60: 0.095 | AD60: 0.105 | AE60: 0.115 | AF60: 0.125 | AG60: 0.135 | AH60: 0.145 | AI60: 0.145 | AJ60: 0.145 | AK60: 0.145 | AL60: 0.145 | AM60: 0.145 | AN60: 0.145 | AO60: 0.145 | AP60: 0.145 | AQ60: 0.145 | AR60: 0.145 | AS60: 0.145 | AT60: 0.145 | AU60: 0.145 | AV60: 0.145 | AW60: 0.145 | AX60: 0.145 | AY60: 0.145 | AZ60: 0.145 | BA60: 0.145 | BB60: 0.145 | BC60: 0.145 | BD60: 0.145 | BE60: MD | BF60: Solar or DG Carve-Out
A61: =IF(E61="Total RPS",1,0)+IF(E61="Total RPS (Wtd. Avg.)",1,0) -> 0 | B61: =INDEX(#REF!,MATCH('BNL_RPS Targets (%)'!C61,#REF!,0)) -> #REF! | C61: MD | E61: Offshore Wind Carve-Out | F61: 0 | G61: 0 | H61: 0 | I61: 0 | J61: 0 | K61: 0 | L61: 0 | M61: 0 | N61: 0 | O61: 0 | P61: 0 | Q61: 0 | R61: 0 | S61: 0 | T61: 0 | U61: 0 | V61: 0 | W61: 0 | X61: 0 | Y61: 0 | Z61: 0 | AA61: 0.014851635 | AB61: 0.014787259 | AC61: 0.022157327 | AD61: 0.022169366 | AE61: 0.022177684 | AF61: 0.046297358 | AG61: 0.046269283 | AH61: 0.07012707 | AI61: 0.069696404 | AJ61: 0.093026735 | AK61: 0.092615934 | AL61: 0.092016403 | AM61: 0.091557713 | AN61: 0.091057766 | AO61: 0.090466745 | AP61: 0.089865985 | AQ61: 0.089209984 | AR61: 0.088680485 | AS61: 0.088144957 | AT61: 0.08755537 | AU61: 0.086978772 | AV61: 0.086521144 | AW61: 0.085840431 | AX61: 0.085240503 | AY61: 0.084548363 | AZ61: 0.08383114 | BA61: 0.083101307 | BB61: 0.08234592 | BC61: 0.081513325 | BD61: 0.080733348 | BE61: MD
A62: =IF(E62="Total RPS",1,0)+IF(E62="Total RPS (Wtd. Avg.)",1,0) -> 0 | B62: =INDEX(#REF!,MATCH('BNL_RPS Targets (%)'!C62,#REF!,0)) -> #REF! | C62: MD | E62: Tier I Non-Solar/Non-Offshore Wind | F62: 0 | G62: 0 | H62: 0 | I62: 0 | J62: 0 | K62: 0 | L62: 0.01 | M62: 0.01 | N62: 0.02 | O62: 0.02 | P62: 0.03 | Q62: 0.0495 | R62: 0.064 | S62: 0.0795 | T62: 0.0995 | U62: 0.1 | V62: 0.12 | W62: 0.1195 | X62: 0.143 | Y62: 0.152 | Z62: 0.22 | AA62: 0.21814837 | AB62: 0.23121274 | AC62: 0.23684267 | AD62: 0.24983063 | AE62: 0.26282232 | AF62: 0.25370264 | AG62: 0.27373072 | AH62: 0.25987293 | AI62: 0.2703036 | AJ62: 0.26197326 | AK62: 0.26238407 | AL62: 0.2629836 | AM62: 0.26344229 | AN62: 0.26394223 | AO62: 0.26453326 | AP62: 0.26513402 | AQ62: 0.26579002 | AR62: 0.26631952 | AS62: 0.26685504 | AT62: 0.26744463 | AU62: 0.26802123 | AV62: 0.26847886 | AW62: 0.26915957 | AX62: 0.2697595 | AY62: 0.27045164 | AZ62: 0.27116886 | BA62: 0.27189869 | BB62: 0.27265408 | BC62: 0.27348667 | BD62: 0.27426665 | BE62: MD | BF62: General RPS/Primary Tier
A63: =IF(E63="Total RPS",1,0)+IF(E63="Total RPS (Wtd. Avg.)",1,0) -> 0 | B63: =INDEX(#REF!,MATCH('BNL_RPS Targets (%)'!C63,#REF!,0)) -> #REF! | C63: MD | E63: Tier II | F63: 0 | G63: 0 | H63: 0 | I63: 0 | J63: 0 | K63: 0 | L63: 0.025 | M63: 0.025 | N63: 0.025 | O63: 0.025 | P63: 0.025 | Q63: 0.025 | R63: 0.025 | S63: 0.025 | T63: 0.025 | U63: 0.025 | V63: 0.025 | W63: 0.025 | X63: 0.025 | Y63: 0.025 | Z63: 0.025 | AA63: 0 | AB63: 0 | AC63: 0 | AD63: 0 | AE63: 0 | AF63: 0 | AG63: 0 | AH63: 0 | AI63: 0 | AJ63: 0 | AK63: 0 | AL63: 0 | AM63: 0 | AN63: 0 | AO63: 0 | AP63: 0 | AQ63: 0 | AR63: 0 | AS63: 0 | AT63: 0 | AU63: 0 | AV63: 0 | AW63: 0 | AX63: 0 | AY63: 0 | AZ63: 0 | BA63: 0 | BB63: 0 | BC63: 0 | BD63: 0 | BE63: MD | BF63: Secondary Tier
A64: =IF(E64="Total RPS",1,0)+IF(E64="Total RPS (Wtd. Avg.)",1,0) -> 1 | B64: =INDEX(#REF!,MATCH('BNL_RPS Targets (%)'!C64,#REF!,0)) -> #REF! | C64: ME | D64: None | E64: Total RPS | F64: 0.3 | G64: 0.3 | H64: 0.3 | I64: 0.3 | J64: 0.3 | K64: 0.3 | L64: 0.3 | M64: 0.3 | N64: 0.31 | O64: 0.32 | P64: 0.33 | Q64: 0.34 | R64: 0.35 | S64: 0.36 | T64: 0.37 | U64: 0.38 | V64: 0.39 | W64: 0.4 | X64: 0.4 | Y64: 0.4 | Z64: 0.425 | AA64: 0.454 | AB64: 0.488 | AC64: 0.522 | AD64: 0.566 | AE64: 0.61 | AF64: 0.654 | AG64: 0.698 | AH64: 0.742 | AI64: 0.786 | AJ64: 0.84 | AK64: 0.84 | AL64: 0.84 | AM64: 0.84 | AN64: 0.84 | AO64: 0.84 | AP64: 0.84 | AQ64: 0.84 | AR64: 0.84 | AS64: 0.84 | AT64: 0.84 | AU64: 0.84 | AV64: 0.84 | AW64: 0.84 | AX64: 0.84 | AY64: 0.84 | AZ64: 0.84 | BA64: 0.84 | BB64: 0.84 | BC64: 0.84 | BD64: 0.84 | BE64: ME | BF64: Total RPS
A65: =IF(E65="Total RPS",1,0)+IF(E65="Total RPS (Wtd. Avg.)",1,0) -> 0 | B65: =INDEX(#REF!,MATCH('BNL_RPS Targets (%)'!C65,#REF!,0)) -> #REF! | C65: ME | E65: Class I/New | F65: 0 | G65: 0 | H65: 0 | I65: 0 | J65: 0 | K65: 0 | L65: 0 | M65: 0 | N65: 0.01 | O65: 0.02 | P65: 0.03 | Q65: 0.04 | R65: 0.05 | S65: 0.06 | T65: 0.07 | U65: 0.08 | V65: 0.09 | W65: 0.1 | X65: 0.1 | Y65: 0.1 | Z65: 0.1 | AA65: 0.1 | AB65: 0.1 | AC65: 0.1 | AD65: 0.1 | AE65: 0.1 | AF65: 0.1 | AG65: 0.1 | AH65: 0.1 | AI65: 0.1 | AJ65: 0.1 | AK65: 0.1 | AL65: 0.1 | AM65: 0.1 | AN65: 0.1 | AO65: 0.1 | AP65: 0.1 | AQ65: 0.1 | AR65: 0.1 | AS65: 0.1 | AT65: 0.1 | AU65: 0.1 | AV65: 0.1 | AW65: 0.1 | AX65: 0.1 | AY65: 0.1 | AZ65: 0.1 | BA65: 0.1 | BB65: 0.1 | BC65: 0.1 | BD65: 0.1 | BE65: ME | BF65: General RPS/Primary Tier
A66: =IF(E66="Total RPS",1,0)+IF(E66="Total RPS (Wtd. Avg.)",1,0) -> 0 | B66: =INDEX(#REF!,MATCH('BNL_RPS Targets (%)'!C66,#REF!,0)) -> #REF! | C66: ME | E66: Class IA | F66: 0 | G66: 0 | H66: 0 | I66: 0 | J66: 0 | K66: 0 | L66: 0 | M66: 0 | N66: 0 | O66: 0 | P66: 0 | Q66: 0 | R66: 0 | S66: 0 | T66: 0 | U66: 0 | V66: 0 | W66: 0 | X66: 0 | Y66: 0 | Z66: 0.025 | AA66: 0.05 | AB66: 0.08 | AC66: 0.11 | AD66: 0.15 | AE66: 0.19 | AF66: 0.23 | AG66: 0.27 | AH66: 0.31 | AI66: 0.35 | AJ66: 0.4 | AK66: 0.4 | AL66: 0.4 | AM66: 0.4 | AN66: 0.4 | AO66: 0.4 | AP66: 0.4 | AQ66: 0.4 | AR66: 0.4 | AS66: 0.4 | AT66: 0.4 | AU66: 0.4 | AV66: 0.4 | AW66: 0.4 | AX66: 0.4 | AY66: 0.4 | AZ66: 0.4 | BA66: 0.4 | BB66: 0.4 | BC66: 0.4 | BD66: 0.4 | BE66: ME | BF66: General RPS/Primary Tier
A67: =IF(E67="Total RPS",1,0)+IF(E67="Total RPS (Wtd. Avg.)",1,0) -> 0 | B67: =INDEX(#REF!,MATCH('BNL_RPS Targets (%)'!C67,#REF!,0)) -> #REF! | C67: ME | E67: Thermal | F67: 0 | G67: 0 | H67: 0 | I67: 0 | J67: 0 | K67: 0 | L67: 0 | M67: 0 | N67: 0 | O67: 0 | P67: 0 | Q67: 0 | R67: 0 | S67: 0 | T67: 0 | U67: 0 | V67: 0 | W67: 0 | X67: 0 | Y67: 0 | Z67: 0 | AA67: 0.004 | AB67: 0.008 | AC67: 0.012 | AD67: 0.016 | AE67: 0.02 | AF67: 0.024 | AG67: 0.028 | AH67: 0.032 | AI67: 0.036 | AJ67: 0.04 | AK67: 0.04 | AL67: 0.04 | AM67: 0.04 | AN67: 0.04 | AO67: 0.04 | AP67: 0.04 | AQ67: 0.04 | AR67: 0.04 | AS67: 0.04 | AT67: 0.04 | AU67: 0.04 | AV67: 0.04 | AW67: 0.04 | AX67: 0.04 | AY67: 0.04 | AZ67: 0.04 | BA67: 0.04 | BB67: 0.04 | BC67: 0.04 | BD67: 0.04 | BE67: ME | BF67: Secondary Tier
A68: =IF(E68="Total RPS",1,0)+IF(E68="Total RPS (Wtd. Avg.)",1,0) -> 0 | B68: =INDEX(#REF!,MATCH('BNL_RPS Targets (%)'!C68,#REF!,0)) -> #REF! | C68: ME | E68: Existing | F68: 0.3 | G68: 0.3 | H68: 0.3 | I68: 0.3 | J68: 0.3 | K68: 0.3 | L68: 0.3 | M68: 0.3 | N68: 0.3 | O68: 0.3 | P68: 0.3 | Q68: 0.3 | R68: 0.3 | S68: 0.3 | T68: 0.3 | U68: 0.3 | V68: 0.3 | W68: 0.3 | X68: 0.3 | Y68: 0.3 | Z68: 0.3 | AA68: 0.3 | AB68: 0.3 | AC68: 0.3 | AD68: 0.3 | AE68: 0.3 | AF68: 0.3 | AG68: 0.3 | AH68: 0.3 | AI68: 0.3 | AJ68: 0.3 | AK68: 0.3 | AL68: 0.3 | AM68: 0.3 | AN68: 0.3 | AO68: 0.3 | AP68: 0.3 | AQ68: 0.3 | AR68: 0.3 | AS68: 0.3 | AT68: 0.3 | AU68: 0.3 | AV68: 0.3 | AW68: 0.3 | AX68: 0.3 | AY68: 0.3 | AZ68: 0.3 | BA68: 0.3 | BB68: 0.3 | BC68: 0.3 | BD68: 0.3 | BE68: ME | BF68: Secondary Tier
A69: =IF(E69="Total RPS",1,0)+IF(E69="Total RPS (Wtd. Avg.)",1,0) -> 1 | B69: =INDEX(#REF!,MATCH('BNL_RPS Targets (%)'!C69,#REF!,0)) -> #REF! | C69: MI | D69: Percentage targets decline after 2021 (and in some intervening years before then), reflecting the fact that absolute RPS requirements remain fixed in absolute MWh terms, while retail electricity sales increase. | E69: Total RPS | F69: 0 | G69: 0 | H69: 0 | I69: 0 | J69: 0 | K69: 0 | L69: 0 | M69: 0 | N69: 0 | O69: 0 | P69: 0 | Q69: 0 | R69: 0.036729608 | S69: 0.048160677 | T69: 0.06111393 | U69: 0.1 | V69: 0.099004826 | W69: 0.10150059 | X69: 0.098625607 | Y69: 0.125 | Z69: 0.12561821 | AA69: 0.15 | AB69: 0.14727123 | AC69: 0.14662332 | AD69: 0.14596508 | AE69: 0.14544122 | AF69: 0.14482665 | AG69: 0.1444958 | AH69: 0.14355296 | AI69: 0.14281265 | AJ69: 0.14211442 | AK69: 0.1414958 | AL69: 0.14079396 | AM69: 0.14017213 | AN69: 0.13919287 | AO69: 0.13835291 | AP69: 0.13765661 | AQ69: 0.13666635 | AR69: 0.13584875 | AS69: 0.13494877 | AT69: 0.13416123 | AU69: 0.13333017 | AV69: 0.13248438 | AW69: 0.13158438 | AX69: 0.13061633 | AY69: 0.12969128 | AZ69: 0.12872813 | BA69: 0.1276914 | BB69: 0.12672171 | BC69: 0.12564389 | BD69: 0.12459369 | BE69: MI | BF69: Total RPS
A70: =IF(E70="Total RPS",1,0)+IF(E70="Total RPS (Wtd. Avg.)",1,0) -> 1 | B70: =INDEX(#REF!,MATCH('BNL_RPS Targets (%)'!C70,#REF!,0)) -> #REF! | C70: MN | D70: Targets differ between Xcel and other utilities, and the weighted average is based on the retail electricity sales of utilities subject to the RPS. Wind and solar carve-outs apply to only a subset of RPS-obligated utilities, as indicated. | E70: Total RPS (Wtd. Avg.) | F70: 0 | G70: 0 | H70: 0 | I70: 0 | J70: 0 | K70: 0.01 | L70: 0.02 | M70: 0.01 | N70: 0.01 | O70: 0.01 | P70: 0.10781825 | Q70: 0.10740885 | R70: 0.14788816 | S70: 0.14745364 | T70: 0.14687419 | U70: 0.14733915 | V70: 0.20645258 | W70: 0.20546771 | X70: 0.20548334 | Y70: 0.20548334 | Z70: 0.24435418 | AA70: 0.24435418 | AB70: 0.24435418 | AC70: 0.24435418 | AD70: 0.24435418 | AE70: 0.27217709 | AF70: 0.27217709 | AG70: 0.27217709 | AH70: 0.27217709 | AI70: 0.27217709 | AJ70: 0.27217709 | AK70: 0.27217709 | AL70: 0.27217709 | AM70: 0.27217709 | AN70: 0.27217709 | AO70: 0.27217709 | AP70: 0.27217709 | AQ70: 0.27217709 | AR70: 0.27217709 | AS70: 0.27217709 | AT70: 0.27217709 | AU70: 0.27217709 | AV70: 0.27217709 | AW70: 0.27217709 | AX70: 0.27217709 | AY70: 0.27217709 | AZ70: 0.27217709 | BA70: 0.27217709 | BB70: 0.27217709 | BC70: 0.27217709 | BD70: 0.27217709 | BE70: MN | BF70: Total RPS
A71: =IF(E71="Total RPS",1,0)+IF(E71="Total RPS (Wtd. Avg.)",1,0) -> 0 | B71: =INDEX(#REF!,MATCH('BNL_RPS Targets (%)'!C71,#REF!,0)) -> #REF! | C71: MN | E71: Xcel | F71: 0 | G71: 0 | H71: 0 | I71: 0 | J71: 0 | K71: 0.01 | L71: 0.02 | M71: 0.01 | N71: 0.01 | O71: 0.01 | P71: 0.15 | Q71: 0.15 | R71: 0.18 | S71: 0.18 | T71: 0.18 | U71: 0.18 | V71: 0.25 | W71: 0.25 | X71: 0.25 | Y71: 0.25 | Z71: 0.3 | AA71: 0.3 | AB71: 0.3 | AC71: 0.3 | AD71: 0.3 | AE71: 0.3 | AF71: 0.3 | AG71: 0.3 | AH71: 0.3 | AI71: 0.3 | AJ71: 0.3 | AK71: 0.3 | AL71: 0.3 | AM71: 0.3 | AN71: 0.3 | AO71: 0.3 | AP71: 0.3 | AQ71: 0.3 | AR71: 0.3 | AS71: 0.3 | AT71: 0.3 | AU71: 0.3 | AV71: 0.3 | AW71: 0.3 | AX71: 0.3 | AY71: 0.3 | AZ71: 0.3 | BA71: 0.3 | BB71: 0.3 | BC71: 0.3 | BD71: 0.3 | BE71: MN
A72: =IF(E72="Total RPS",1,0)+IF(E72="Total RPS (Wtd. Avg.)",1,0) -> 0 | B72: =INDEX(#REF!,MATCH('BNL_RPS Targets (%)'!C72,#REF!,0)) -> #REF! | C72: MN | E72: Other utilities | F72: 0 | G72: 0 | H72: 0 | I72: 0 | J72: 0 | K72: 0.01 | L72: 0.02 | M72: 0.01 | N72: 0.01 | O72: 0.01 | P72: 0.07 | Q72: 0.07 | R72: 0.12 | S72: 0.12 | T72: 0.12 | U72: 0.12 | V72: 0.17 | W72: 0.17 | X72: 0.17 | Y72: 0.17 | Z72: 0.2 | AA72: 0.2 | AB72: 0.2 | AC72: 0.2 | AD72: 0.2 | AE72: 0.25 | AF72: 0.25 | AG72: 0.25 | AH72: 0.25 | AI72: 0.25 | AJ72: 0.25 | AK72: 0.25 | AL72: 0.25 | AM72: 0.25 | AN72: 0.25 | AO72: 0.25 | AP72: 0.25 | AQ72: 0.25 | AR72: 0.25 | AS72: 0.25 | AT72: 0.25 | AU72: 0.25 | AV72: 0.25 | AW72: 0.25 | AX72: 0.25 | AY72: 0.25 | AZ72: 0.25 | BA72: 0.25 | BB72: 0.25 | BC72: 0.25 | BD72: 0.25 | BE72: MN
A73: =IF(E73="Total RPS",1,0)+IF(E73="Total RPS (Wtd. Avg.)",1,0) -> 0 | B73: =INDEX(#REF!,MATCH('BNL_RPS Targets (%)'!C73,#REF!,0)) -> #REF! | C73: MN | E73: Wind Carve-Out (Xcel only) | F73: 0 | G73: 0 | H73: 0 | I73: 0 | J73: 0 | K73: 0 | L73: 0 | M73: 0.0083333333 | N73: 0.0083333333 | O73: 0.0083333333 | P73: 0.125 | Q73: 0.125 | R73: 0.15 | S73: 0.15 | T73: 0.15 | U73: 0.15 | V73: 0.20833333 | W73: 0.20833333 | X73: 0.20833333 | Y73: 0.20833333 | Z73: 0.25 | AA73: 0.25 | AB73: 0.25 | AC73: 0.25 | AD73: 0.25 | AE73: 0.25 | AF73: 0.25 | AG73: 0.25 | AH73: 0.25 | AI73: 0.25 | AJ73: 0.25 | AK73: 0.25 | AL73: 0.25 | AM73: 0.25 | AN73: 0.25 | AO73: 0.25 | AP73: 0.25 | AQ73: 0.25 | AR73: 0.25 | AS73: 0.25 | AT73: 0.25 | AU73: 0.25 | AV73: 0.25 | AW73: 0.25 | AX73: 0.25 | AY73: 0.25 | AZ73: 0.25 | BA73: 0.25 | BB73: 0.25 | BC73: 0.25 | BD73: 0.25 | BE73: MN
A74: =IF(E74="Total RPS",1,0)+IF(E74="Total RPS (Wtd. Avg.)",1,0) -> 0 | B74: =INDEX(#REF!,MATCH('BNL_RPS Targets (%)'!C74,#REF!,0)) -> #REF! | C74: MN | E74: Solar Carve-Out (IOUs only) | F74: 0 | G74: 0 | H74: 0 | I74: 0 | J74: 0 | K74: 0 | L74: 0 | M74: 0 | N74: 0 | O74: 0 | P74: 0 | Q74: 0 | R74: 0 | S74: 0 | T74: 0 | U74: 0 | V74: 0 | W74: 0 | X74: 0 | Y74: 0 | Z74: 0.012494632 | AA74: 0.012519797 | AB74: 0.012545663 | AC74: 0.012562821 | AD74: 0.012580044 | AE74: 0.012596509 | AF74: 0.012613295 | AG74: 0.01262466 | AH74: 0.012642924 | AI74: 0.012658822 | AJ74: 0.012673912 | AK74: 0.01268619 | AL74: 0.012699621 | AM74: 0.012712727 | AN74: 0.012730792 | AO74: 0.012746472 | AP74: 0.012760372 | AQ74: 0.012778113 | AR74: 0.012793903 | AS74: 0.012810894 | AT74: 0.012826446 | AU74: 0.012842859 | AV74: 0.012859398 | AW74: 0.012876203 | AX74: 0.012894015 | AY74: 0.012910991 | AZ74: 0.012928109 | BA74: 0.012946126 | BB74: 0.012963198 | BC74: 0.012981857 | BD74: 0.012999158 | BE74: MN | BF74: Solar or DG Carve-Out
A75: =IF(E75="Total RPS",1,0)+IF(E75="Total RPS (Wtd. Avg.)",1,0) -> 1 | B75: =INDEX(#REF!,MATCH('BNL_RPS Targets (%)'!C75,#REF!,0)) -> #REF! | C75: MO | D75: None | E75: Total RPS | F75: 0 | G75: 0 | H75: 0 | I75: 0 | J75: 0 | K75: 0 | L75: 0 | M75: 0 | N75: 0 | O75: 0 | P75: 0 | Q75: 0.02 | R75: 0.02 | S75: 0.02 | T75: 0.05 | U75: 0.05 | V75: 0.05 | W75: 0.05 | X75: 0.1 | Y75: 0.1 | Z75: 0.1 | AA75: 0.15 | AB75: 0.15 | AC75: 0.15 | AD75: 0.15 | AE75: 0.15 | AF75: 0.15 | AG75: 0.15 | AH75: 0.15 | AI75: 0.15 | AJ75: 0.15 | AK75: 0.15 | AL75: 0.15 | AM75: 0.15 | AN75: 0.15 | AO75: 0.15 | AP75: 0.15 | AQ75: 0.15 | AR75: 0.15 | AS75: 0.15 | AT75: 0.15 | AU75: 0.15 | AV75: 0.15 | AW75: 0.15 | AX75: 0.15 | AY75: 0.15 | AZ75: 0.15 | BA75: 0.15 | BB75: 0.15 | BC75: 0.15 | BD75: 0.15 | BE75: MO | BF75: Total RPS
A76: =IF(E76="Total RPS",1,0)+IF(E76="Total RPS (Wtd. Avg.)",1,0) -> 0 | B76: =INDEX(#REF!,MATCH('BNL_RPS Targets (%)'!C76,#REF!,0)) -> #REF! | C76: MO | E76: Solar Carve-Out | F76: 0 | G76: 0 | H76: 0 | I76: 0 | J76: 0 | K76: 0 | L76: 0 | M76: 0 | N76: 0 | O76: 0 | P76: 0 | Q76: 0.0004 | R76: 0.0004 | S76: 0.0004 | T76: 0.001 | U76: 0.001 | V76: 0.001 | W76: 0.001 | X76: 0.002 | Y76: 0.002 | Z76: 0.002 | AA76: 0.003 | AB76: 0.003 | AC76: 0.003 | AD76: 0.003 | AE76: 0.003 | AF76: 0.003 | AG76: 0.003 | AH76: 0.003 | AI76: 0.003 | AJ76: 0.003 | AK76: 0.003 | AL76: 0.003 | AM76: 0.003 | AN76: 0.003 | AO76: 0.003 | AP76: 0.003 | AQ76: 0.003 | AR76: 0.003 | AS76: 0.003 | AT76: 0.003 | AU76: 0.003 | AV76: 0.003 | AW76: 0.003 | AX76: 0.003 | AY76: 0.003 | AZ76: 0.003 | BA76: 0.003 | BB76: 0.003 | BC76: 0.003 | BD76: 0.003 | BE76: MO | BF76: Solar or DG Carve-Out
A77: =IF(E77="Total RPS",1,0)+IF(E77="Total RPS (Wtd. Avg.)",1,0) -> 1 | B77: =INDEX(#REF!,MATCH('BNL_RPS Targets (%)'!C77,#REF!,0)) -> #REF! | C77: MT | D77: None | E77: Total RPS | F77: 0 | G77: 0 | H77: 0 | I77: 0 | J77: 0 | K77: 0 | L77: 0 | M77: 0 | N77: 0.05 | O77: 0.05 | P77: 0.1 | Q77: 0.1 | R77: 0.1 | S77: 0.1 | T77: 0.1 | U77: 0.15 | V77: 0.15 | W77: 0.15 | X77: 0.15 | Y77: 0.15 | Z77: 0.15 | AA77: 0.15 | AB77: 0.15 | AC77: 0.15 | AD77: 0.15 | AE77: 0.15 | AF77: 0.15 | AG77: 0.15 | AH77: 0.15 | AI77: 0.15 | AJ77: 0.15 | AK77: 0.15 | AL77: 0.15 | AM77: 0.15 | AN77: 0.15 | AO77: 0.15 | AP77: 0.15 | AQ77: 0.15 | AR77: 0.15 | AS77: 0.15 | AT77: 0.15 | AU77: 0.15 | AV77: 0.15 | AW77: 0.15 | AX77: 0.15 | AY77: 0.15 | AZ77: 0.15 | BA77: 0.15 | BB77: 0.15 | BC77: 0.15 | BD77: 0.15 | BE77: MT | BF77: Total RPS
A78: =IF(E78="Total RPS",1,0)+IF(E78="Total RPS (Wtd. Avg.)",1,0) -> 1 | B78: =INDEX(#REF!,MATCH('BNL_RPS Targets (%)'!C78,#REF!,0)) -> #REF! | C78: NC | D78: Targets differ between IOUs and POUs (munis and coops), and the weighted average is based on the retail electricity sales of utilities subject to the RPS. | E78: Total RPS (Wtd. Avg.) | F78: 0 | G78: 0 | H78: 0 | I78: 0 | J78: 0 | K78: 0 | L78: 0 | M78: 0 | N78: 0 | O78: 0 | P78: 0 | Q78: 0 | R78: 0.03 | S78: 0.03 | T78: 0.03 | U78: 0.06 | V78: 0.06 | W78: 0.06 | X78: 0.1 | Y78: 0.1 | Z78: 0.1 | AA78: 0.1187992 | AB78: 0.1187992 | AC78: 0.1187992 | AD78: 0.1187992 | AE78: 0.1187992 | AF78: 0.1187992 | AG78: 0.1187992 | AH78: 0.1187992 | AI78: 0.1187992 | AJ78: 0.1187992 | AK78: 0.1187992 | AL78: 0.1187992 | AM78: 0.1187992 | AN78: 0.1187992 | AO78: 0.1187992 | AP78: 0.1187992 | AQ78: 0.1187992 | AR78: 0.1187992 | AS78: 0.1187992 | AT78: 0.1187992 | AU78: 0.1187992 | AV78: 0.1187992 | AW78: 0.1187992 | AX78: 0.1187992 | AY78: 0.1187992 | AZ78: 0.1187992 | BA78: 0.1187992 | BB78: 0.1187992 | BC78: 0.1187992 | BD78: 0.1187992 | BE78: NC | BF78: Total RPS
A79: =IF(E79="Total RPS",1,0)+IF(E79="Total RPS (Wtd. Avg.)",1,0) -> 0 | B79: =INDEX(#REF!,MATCH('BNL_RPS Targets (%)'!C79,#REF!,0)) -> #REF! | C79: NC | E79: IOUs | F79: 0 | G79: 0 | H79: 0 | I79: 0 | J79: 0 | K79: 0 | L79: 0 | M79: 0 | N79: 0 | O79: 0 | P79: 0 | Q79: 0 | R79: 0.03 | S79: 0.03 | T79: 0.03 | U79: 0.06 | V79: 0.06 | W79: 0.06 | X79: 0.1 | Y79: 0.1 | Z79: 0.1 | AA79: 0.125 | AB79: 0.125 | AC79: 0.125 | AD79: 0.125 | AE79: 0.125 | AF79: 0.125 | AG79: 0.125 | AH79: 0.125 | AI79: 0.125 | AJ79: 0.125 | AK79: 0.125 | AL79: 0.125 | AM79: 0.125 | AN79: 0.125 | AO79: 0.125 | AP79: 0.125 | AQ79: 0.125 | AR79: 0.125 | AS79: 0.125 | AT79: 0.125 | AU79: 0.125 | AV79: 0.125 | AW79: 0.125 | AX79: 0.125 | AY79: 0.125 | AZ79: 0.125 | BA79: 0.125 | BB79: 0.125 | BC79: 0.125 | BD79: 0.125 | BE79: NC
A80: =IF(E80="Total RPS",1,0)+IF(E80="Total RPS (Wtd. Avg.)",1,0) -> 0 | B80: =INDEX(#REF!,MATCH('BNL_RPS Targets (%)'!C80,#REF!,0)) -> #REF! | C80: NC | E80: Munis and Coops | F80: 0 | G80: 0 | H80: 0 | I80: 0 | J80: 0 | K80: 0 | L80: 0 | M80: 0 | N80: 0 | O80: 0 | P80: 0 | Q80: 0 | R80: 0.03 | S80: 0.03 | T80: 0.03 | U80: 0.06 | V80: 0.06 | W80: 0.06 | X80: 0.1 | Y80: 0.1 | Z80: 0.1 | AA80: 0.1 | AB80: 0.1 | AC80: 0.1 | AD80: 0.1 | AE80: 0.1 | AF80: 0.1 | AG80: 0.1 | AH80: 0.1 | AI80: 0.1 | AJ80: 0.1 | AK80: 0.1 | AL80: 0.1 | AM80: 0.1 | AN80: 0.1 | AO80: 0.1 | AP80: 0.1 | AQ80: 0.1 | AR80: 0.1 | AS80: 0.1 | AT80: 0.1 | AU80: 0.1 | AV80: 0.1 | AW80: 0.1 | AX80: 0.1 | AY80: 0.1 | AZ80: 0.1 | BA80: 0.1 | BB80: 0.1 | BC80: 0.1 | BD80: 0.1 | BE80: NC
A81: =IF(E81="Total RPS",1,0)+IF(E81="Total RPS (Wtd. Avg.)",1,0) -> 0 | B81: =INDEX(#REF!,MATCH('BNL_RPS Targets (%)'!C81,#REF!,0)) -> #REF! | C81: NC | E81: Solar Carve-Out | F81: 0 | G81: 0 | H81: 0 | I81: 0 | J81: 0 | K81: 0 | L81: 0 | M81: 0 | N81: 0 | O81: 0 | P81: 0.0002 | Q81: 0.0002 | R81: 0.0007 | S81: 0.0007 | T81: 0.0007 | U81: 0.0014 | V81: 0.0014 | W81: 0.0014 | X81: 0.002 | Y81: 0.002 | Z81: 0.002 | AA81: 0.002 | AB81: 0.002 | AC81: 0.002 | AD81: 0.002 | AE81: 0.002 | AF81: 0.002 | AG81: 0.002 | AH81: 0.002 | AI81: 0.002 | AJ81: 0.002 | AK81: 0.002 | AL81: 0.002 | AM81: 0.002 | AN81: 0.002 | AO81: 0.002 | AP81: 0.002 | AQ81: 0.002 | AR81: 0.002 | AS81: 0.002 | AT81: 0.002 | AU81: 0.002 | AV81: 0.002 | AW81: 0.002 | AX81: 0.002 | AY81: 0.002 | AZ81: 0.002 | BA81: 0.002 | BB81: 0.002 | BC81: 0.002 | BD81: 0.002 | BE81: NC | BF81: Solar or DG Carve-Out
A82: =IF(E82="Total RPS",1,0)+IF(E82="Total RPS (Wtd. Avg.)",1,0) -> 0 | B82: =INDEX(#REF!,MATCH('BNL_RPS Targets (%)'!C82,#REF!,0)) -> #REF! | C82: NC | E82: Swine Waste Carve-Out | F82: 0 | G82: 0 | H82: 0 | I82: 0 | J82: 0 | K82: 0 | L82: 0 | M82: 0 | N82: 0 | O82: 0 | P82: 0 | Q82: 0 | R82: 0 | S82: 0 | T82: 0 | U82: 0 | V82: 0 | W82: 0.0007 | X82: 0.0002 | Y82: 0.0004 | Z82: 0.0007 | AA82: 0.0007 | AB82: 0.0014 | AC82: 0.0014 | AD82: 0.0014 | AE82: 0.002 | AF82: 0.002 | AG82: 0.002 | AH82: 0.002 | AI82: 0.002 | AJ82: 0.002 | AK82: 0.002 | AL82: 0.002 | AM82: 0.002 | AN82: 0.002 | AO82: 0.002 | AP82: 0.002 | AQ82: 0.002 | AR82: 0.002 | AS82: 0.002 | AT82: 0.002 | AU82: 0.002 | AV82: 0.002 | AW82: 0.002 | AX82: 0.002 | AY82: 0.002 | AZ82: 0.002 | BA82: 0.002 | BB82: 0.002 | BC82: 0.002 | BD82: 0.002 | BE82: NC | BF82: Secondary Tier
A83: =IF(E83="Total RPS",1,0)+IF(E83="Total RPS (Wtd. Avg.)",1,0) -> 0 | B83: =INDEX(#REF!,MATCH('BNL_RPS Targets (%)'!C83,#REF!,0)) -> #REF! | C83: NC | E83: Poultry Waste Carve-Out | F83: 0 | G83: 0 | H83: 0 | I83: 0 | J83: 0 | K83: 0 | L83: 0 | M83: 0 | N83: 0 | O83: 0 | P83: 0 | Q83: 0 | R83: 0 | S83: 0 | T83: 0.0013121529 | U83: 0.0012790377 | V83: 0.001272125 | W83: 0.0012667928 | X83: 0.002286367 | Y83: 0.0036214116 | Z83: 0.004960153 | AA83: 0.0064285277 | AB83: 0.0062687093 | AC83: 0.0061898664 | AD83: 0.0061486739 | AE83: 0.0061107057 | AF83: 0.006076053 | AG83: 0.0060380529 | AH83: 0.0060016738 | AI83: 0.0059574816 | AJ83: 0.0059074496 | AK83: 0.0058633568 | AL83: 0.0058189512 | AM83: 0.0057698279 | AN83: 0.0057221075 | AO83: 0.005670887 | AP83: 0.0056180349 | AQ83: 0.0055664884 | AR83: 0.0055144292 | AS83: 0.005464918 | AT83: 0.005415546 | AU83: 0.0053654776 | AV83: 0.0053130646 | AW83: 0.0052621956 | AX83: 0.0052082339 | AY83: 0.005155944 | AZ83: 0.0051022359 | BA83: 0.0050481005 | BB83: 0.0049927018 | BC83: 0.0049388987 | BD83: 0.0048828067 | BE83: NC | BF83: Secondary Tier
A84: =IF(E84="Total RPS",1,0)+IF(E84="Total RPS (Wtd. Avg.)",1,0) -> 1 | B84: =INDEX(#REF!,MATCH('BNL_RPS Targets (%)'!C84,#REF!,0)) -> #REF! | C84: NH | D84: None | E84: Total RPS | F84: 0 | G84: 0 | H84: 0 | I84: 0 | J84: 0 | K84: 0 | L84: 0 | M84: 0 | N84: 0.04 | O84: 0.06 | P84: 0.0754 | Q84: 0.0958 | R84: 0.0555 | S84: 0.058 | T84: 0.072 | U84: 0.083 | V84: 0.085 | W84: 0.176 | X84: 0.187 | Y84: 0.197 | Z84: 0.207 | AA84: 0.216 | AB84: 0.225 | AC84: 0.234 | AD84: 0.243 | AE84: 0.252 | AF84: 0.252 | AG84: 0.252 | AH84: 0.252 | AI84: 0.252 | AJ84: 0.252 | AK84: 0.252 | AL84: 0.252 | AM84: 0.252 | AN84: 0.252 | AO84: 0.252 | AP84: 0.252 | AQ84: 0.252 | AR84: 0.252 | AS84: 0.252 | AT84: 0.252 | AU84: 0.252 | AV84: 0.252 | AW84: 0.252 | AX84: 0.252 | AY84: 0.252 | AZ84: 0.252 | BA84: 0.252 | BB84: 0.252 | BC84: 0.252 | BD84: 0.252 | BE84: NH | BF84: Total RPS
A85: =IF(E85="Total RPS",1,0)+IF(E85="Total RPS (Wtd. Avg.)",1,0) -> 0 | B85: =INDEX(#REF!,MATCH('BNL_RPS Targets (%)'!C85,#REF!,0)) -> #REF! | C85: NH | E85: Class I (Non-Thermal) | F85: 0 | G85: 0 | H85: 0 | I85: 0 | J85: 0 | K85: 0 | L85: 0 | M85: 0 | N85: 0 | O85: 0.005 | P85: 0.01 | Q85: 0.02 | R85: 0.03 | S85: 0.038 | T85: 0.046 | U85: 0.054 | V85: 0.056 | W85: 0.068 | X85: 0.075 | Y85: 0.082 | Z85: 0.089 | AA85: 0.096 | AB85: 0.103 | AC85: 0.11 | AD85: 0.119 | AE85: 0.128 | AF85: 0.128 | AG85: 0.128 | AH85: 0.128 | AI85: 0.128 | AJ85: 0.128 | AK85: 0.128 | AL85: 0.128 | AM85: 0.128 | AN85: 0.128 | AO85: 0.128 | AP85: 0.128 | AQ85: 0.128 | AR85: 0.128 | AS85: 0.128 | AT85: 0.128 | AU85: 0.128 | AV85: 0.128 | AW85: 0.128 | AX85: 0.128 | AY85: 0.128 | AZ85: 0.128 | BA85: 0.128 | BB85: 0.128 | BC85: 0.128 | BD85: 0.128 | BE85: NH | BF85: General RPS/Primary Tier
A86: =IF(E86="Total RPS",1,0)+IF(E86="Total RPS (Wtd. Avg.)",1,0) -> 0 | B86: =INDEX(#REF!,MATCH('BNL_RPS Targets (%)'!C86,#REF!,0)) -> #REF! | C86: NH | E86: Class I (Thermal) | F86: 0 | G86: 0 | H86: 0 | I86: 0 | J86: 0 | K86: 0 | L86: 0 | M86: 0 | N86: 0 | O86: 0 | P86: 0 | Q86: 0 | R86: 0 | S86: 0 | T86: 0.004 | U86: 0.006 | V86: 0.006 | W86: 0.01 | X86: 0.012 | Y86: 0.014 | Z86: 0.016 | AA86: 0.018 | AB86: 0.02 | AC86: 0.022 | AD86: 0.022 | AE86: 0.022 | AF86: 0.022 | AG86: 0.022 | AH86: 0.022 | AI86: 0.022 | AJ86: 0.022 | AK86: 0.022 | AL86: 0.022 | AM86: 0.022 | AN86: 0.022 | AO86: 0.022 | AP86: 0.022 | AQ86: 0.022 | AR86: 0.022 | AS86: 0.022 | AT86: 0.022 | AU86: 0.022 | AV86: 0.022 | AW86: 0.022 | AX86: 0.022 | AY86: 0.022 | AZ86: 0.022 | BA86: 0.022 | BB86: 0.022 | BC86: 0.022 | BD86: 0.022 | BE86: NH | BF86: Secondary Tier
A87: =IF(E87="Total RPS",1,0)+IF(E87="Total RPS (Wtd. Avg.)",1,0) -> 0 | B87: =INDEX(#REF!,MATCH('BNL_RPS Targets (%)'!C87,#REF!,0)) -> #REF! | C87: NH | E87: Class II (Solar Carve-Out) | F87: 0 | G87: 0 | H87: 0 | I87: 0 | J87: 0 | K87: 0 | L87: 0 | M87: 0 | N87: 0 | O87: 0 | P87: 0.0004 | Q87: 0.0008 | R87: 0.0015 | S87: 0.002 | T87: 0.003 | U87: 0.003 | V87: 0.003 | W87: 0.003 | X87: 0.005 | Y87: 0.006 | Z87: 0.007 | AA87: 0.007 | AB87: 0.007 | AC87: 0.007 | AD87: 0.007 | AE87: 0.007 | AF87: 0.007 | AG87: 0.007 | AH87: 0.007 | AI87: 0.007 | AJ87: 0.007 | AK87: 0.007 | AL87: 0.007 | AM87: 0.007 | AN87: 0.007 | AO87: 0.007 | AP87: 0.007 | AQ87: 0.007 | AR87: 0.007 | AS87: 0.007 | AT87: 0.007 | AU87: 0.007 | AV87: 0.007 | AW87: 0.007 | AX87: 0.007 | AY87: 0.007 | AZ87: 0.007 | BA87: 0.007 | BB87: 0.007 | BC87: 0.007 | BD87: 0.007 | BE87: NH | BF87: Solar or DG Carve-Out
A88: =IF(E88="Total RPS",1,0)+IF(E88="Total RPS (Wtd. Avg.)",1,0) -> 0 | B88: =INDEX(#REF!,MATCH('BNL_RPS Targets (%)'!C88,#REF!,0)) -> #REF! | C88: NH | E88: Class III (Existing Biomass/Methane) | F88: 0 | G88: 0 | H88: 0 | I88: 0 | J88: 0 | K88: 0 | L88: 0 | M88: 0 | N88: 0.035 | O88: 0.045 | P88: 0.055 | Q88: 0.065 | R88: 0.014 | S88: 0.005 | T88: 0.005 | U88: 0.005 | V88: 0.005 | W88: 0.08 | X88: 0.08 | Y88: 0.08 | Z88: 0.08 | AA88: 0.08 | AB88: 0.08 | AC88: 0.08 | AD88: 0.08 | AE88: 0.08 | AF88: 0.08 | AG88: 0.08 | AH88: 0.08 | AI88: 0.08 | AJ88: 0.08 | AK88: 0.08 | AL88: 0.08 | AM88: 0.08 | AN88: 0.08 | AO88: 0.08 | AP88: 0.08 | AQ88: 0.08 | AR88: 0.08 | AS88: 0.08 | AT88: 0.08 | AU88: 0.08 | AV88: 0.08 | AW88: 0.08 | AX88: 0.08 | AY88: 0.08 | AZ88: 0.08 | BA88: 0.08 | BB88: 0.08 | BC88: 0.08 | BD88: 0.08 | BE88: NH | BF88: Secondary Tier
A89: =IF(E89="Total RPS",1,0)+IF(E89="Total RPS (Wtd. Avg.)",1,0) -> 0 | B89: =INDEX(#REF!,MATCH('BNL_RPS Targets (%)'!C89,#REF!,0)) -> #REF! | C89: NH | E89: Class IV (Existing Small Hydro) | F89: 0 | G89: 0 | H89: 0 | I89: 0 | J89: 0 | K89: 0 | L89: 0 | M89: 0 | N89: 0.005 | O89: 0.01 | P89: 0.01 | Q89: 0.01 | R89: 0.01 | S89: 0.013 | T89: 0.014 | U89: 0.015 | V89: 0.015 | W89: 0.015 | X89: 0.015 | Y89: 0.015 | Z89: 0.015 | AA89: 0.015 | AB89: 0.015 | AC89: 0.015 | AD89: 0.015 | AE89: 0.015 | AF89: 0.015 | AG89: 0.015 | AH89: 0.015 | AI89: 0.015 | AJ89: 0.015 | AK89: 0.015 | AL89: 0.015 | AM89: 0.015 | AN89: 0.015 | AO89: 0.015 | AP89: 0.015 | AQ89: 0.015 | AR89: 0.015 | AS89: 0.015 | AT89: 0.015 | AU89: 0.015 | AV89: 0.015 | AW89: 0.015 | AX89: 0.015 | AY89: 0.015 | AZ89: 0.015 | BA89: 0.015 | BB89: 0.015 | BC89: 0.015 | BD89: 0.015 | BE89: NH | BF89: Secondary Tier
A90: =IF(E90="Total RPS",1,0)+IF(E90="Total RPS (Wtd. Avg.)",1,0) -> 1 | B90: =INDEX(#REF!,MATCH('BNL_RPS Targets (%)'!C90,#REF!,0)) -> #REF! | C90: NJ | D90: NJ has an offshore wind carve-out as part of its Class I requirement, though specific annual targets have not yet been developed. | E90: Total RPS | F90: 0 | G90: 0 | H90: 0.03 | I90: 0.03 | J90: 0.03 | K90: 0.0325 | L90: 0.035 | M90: 0.045763 | N90: 0.055057 | O90: 0.065 | P90: 0.07406 | Q90: 0.083860741 | R90: 0.094066245 | S90: 0.10450496 | T90: 0.12527 | U90: 0.13757 | V90: 0.14899 | W90: 0.15985 | X90: 0.18025 | Y90: 0.20975 | Z90: 0.284 | AA90: 0.286 | AB90: 0.286 | AC90: 0.286 | AD90: 0.284 | AE90: 0.423 | AF90: 0.42 | AG90: 0.4185 | AH90: 0.4124 | AI90: 0.4057 | AJ90: 0.5471 | AK90: 0.5408 | AL90: 0.539 | AM90: 0.536 | AN90: 0.525 | AO90: 0.525 | AP90: 0.525 | AQ90: 0.525 | AR90: 0.525 | AS90: 0.525 | AT90: 0.525 | AU90: 0.525 | AV90: 0.525 | AW90: 0.525 | AX90: 0.525 | AY90: 0.525 | AZ90: 0.525 | BA90: 0.525 | BB90: 0.525 | BC90: 0.525 | BD90: 0.525 | BE90: NJ | BF90: Total RPS
A91: =IF(E91="Total RPS",1,0)+IF(E91="Total RPS (Wtd. Avg.)",1,0) -> 0 | B91: =INDEX(#REF!,MATCH('BNL_RPS Targets (%)'!C91,#REF!,0)) -> #REF! | C91: NJ | E91: Solar Carve-Out | F91: 0 | G91: 0 | H91: 0 | I91: 0 | J91: 0 | K91: 0.0001 | L91: 0.00017 | M91: 0.000393 | N91: 0.000817 | O91: 0.0016 | P91: 0.00221 | Q91: 0.0039407412 | R91: 0.0058662445 | S91: 0.0080749595 | T91: 0.0205 | U91: 0.0245 | V91: 0.0275 | W91: 0.03 | X91: 0.032 | Y91: 0.043 | Z91: 0.049 | AA91: 0.051 | AB91: 0.051 | AC91: 0.051 | AD91: 0.049 | AE91: 0.048 | AF91: 0.045 | AG91: 0.0435 | AH91: 0.0374 | AI91: 0.0307 | AJ91: 0.0221 | AK91: 0.0158 | AL91: 0.014 | AM91: 0.011 | AN91: 0 | AO91: 0 | AP91: 0 | AQ91: 0 | AR91: 0 | AS91: 0 | AT91: 0 | AU91: 0 | AV91: 0 | AW91: 0 | AX91: 0 | AY91: 0 | AZ91: 0 | BA91: 0 | BB91: 0 | BC91: 0 | BD91: 0 | BE91: NJ | BF91: Solar or DG Carve-Out
A92: =IF(E92="Total RPS",1,0)+IF(E92="Total RPS (Wtd. Avg.)",1,0) -> 0 | B92: =INDEX(#REF!,MATCH('BNL_RPS Targets (%)'!C92,#REF!,0)) -> #REF! | C92: NJ | E92: Class I Non-Solar | F92: 0 | G92: 0 | H92: 0.005 | I92: 0.005 | J92: 0.005 | K92: 0.0074 | L92: 0.00983 | M92: 0.02037 | N92: 0.02924 | O92: 0.0384 | P92: 0.04685 | Q92: 0.05492 | R92: 0.0632 | S92: 0.07143 | T92: 0.07977 | U92: 0.08807 | V92: 0.09649 | W92: 0.10485 | X92: 0.12325 | Y92: 0.14175 | Z92: 0.21 | AA92: 0.21 | AB92: 0.21 | AC92: 0.21 | AD92: 0.21 | AE92: 0.35 | AF92: 0.35 | AG92: 0.35 | AH92: 0.35 | AI92: 0.35 | AJ92: 0.5 | AK92: 0.5 | AL92: 0.5 | AM92: 0.5 | AN92: 0.5 | AO92: 0.5 | AP92: 0.5 | AQ92: 0.5 | AR92: 0.5 | AS92: 0.5 | AT92: 0.5 | AU92: 0.5 | AV92: 0.5 | AW92: 0.5 | AX92: 0.5 | AY92: 0.5 | AZ92: 0.5 | BA92: 0.5 | BB92: 0.5 | BC92: 0.5 | BD92: 0.5 | BE92: NJ | BF92: General RPS/Primary Tier
A93: =IF(E93="Total RPS",1,0)+IF(E93="Total RPS (Wtd. Avg.)",1,0) -> 0 | B93: =INDEX(#REF!,MATCH('BNL_RPS Targets (%)'!C93,#REF!,0)) -> #REF! | C93: NJ | E93: Class II | F93: 0 | G93: 0 | H93: 0.025 | I93: 0.025 | J93: 0.025 | K93: 0.025 | L93: 0.025 | M93: 0.025 | N93: 0.025 | O93: 0.025 | P93: 0.025 | Q93: 0.025 | R93: 0.025 | S93: 0.025 | T93: 0.025 | U93: 0.025 | V93: 0.025 | W93: 0.025 | X93: 0.025 | Y93: 0.025 | Z93: 0.025 | AA93: 0.025 | AB93: 0.025 | AC93: 0.025 | AD93: 0.025 | AE93: 0.025 | AF93: 0.025 | AG93: 0.025 | AH93: 0.025 | AI93: 0.025 | AJ93: 0.025 | AK93: 0.025 | AL93: 0.025 | AM93: 0.025 | AN93: 0.025 | AO93: 0.025 | AP93: 0.025 | AQ93: 0.025 | AR93: 0.025 | AS93: 0.025 | AT93: 0.025 | AU93: 0.025 | AV93: 0.025 | AW93: 0.025 | AX93: 0.025 | AY93: 0.025 | AZ93: 0.025 | BA93: 0.025 | BB93: 0.025 | BC93: 0.025 | BD93: 0.025 | BE93: NJ | BF93: Secondary Tier
A94: =IF(E94="Total RPS",1,0)+IF(E94="Total RPS (Wtd. Avg.)",1,0) -> 1 | B94: =INDEX(#REF!,MATCH('BNL_RPS Targets (%)'!C94,#REF!,0)) -> #REF! | C94: NM | D94: Targets differ between IOUs and Coops, and the weighted average is based on the retail electricity sales of utilities subject to the RPS. | E94: Total RPS (Wtd. Avg.) | F94: 0 | G94: 0 | H94: 0 | I94: 0 | J94: 0 | K94: 0 | L94: 0.05 | M94: 0.05 | N94: 0.05 | O94: 0.06 | P94: 0.06 | Q94: 0.1 | R94: 0.1 | S94: 0.1 | T94: 0.1 | U94: 0.12562261 | V94: 0.1287406 | W94: 0.13108365 | X94: 0.13345682 | Y94: 0.13582014 | Z94: 0.17636689 | AA94: 0.17636689 | AB94: 0.17636689 | AC94: 0.17636689 | AD94: 0.17636689 | AE94: 0.4 | AF94: 0.4 | AG94: 0.4 | AH94: 0.4 | AI94: 0.4 | AJ94: 0.5 | AK94: 0.5 | AL94: 0.5 | AM94: 0.5 | AN94: 0.5 | AO94: 0.5 | AP94: 0.5 | AQ94: 0.5 | AR94: 0.5 | AS94: 0.5 | AT94: 0.72910068 | AU94: 0.72910068 | AV94: 0.72910068 | AW94: 0.72910068 | AX94: 0.72910068 | AY94: 0.72910068 | AZ94: 0.72910068 | BA94: 0.72910068 | BB94: 0.72910068 | BC94: 0.72910068 | BD94: 0.8 | BE94: NM | BF94: Total RPS
A95: =IF(E95="Total RPS",1,0)+IF(E95="Total RPS (Wtd. Avg.)",1,0) -> 0 | B95: =INDEX(#REF!,MATCH('BNL_RPS Targets (%)'!C95,#REF!,0)) -> #REF! | C95: NM | E95: IOUs | F95: 0 | G95: 0 | H95: 0 | I95: 0 | J95: 0 | K95: 0 | L95: 0.05 | M95: 0.05 | N95: 0.05 | O95: 0.06 | P95: 0.06 | Q95: 0.1 | R95: 0.1 | S95: 0.1 | T95: 0.1 | U95: 0.15 | V95: 0.15 | W95: 0.15 | X95: 0.15 | Y95: 0.15 | Z95: 0.2 | AA95: 0.2 | AB95: 0.2 | AC95: 0.2 | AD95: 0.2 | AE95: 0.4 | AF95: 0.4 | AG95: 0.4 | AH95: 0.4 | AI95: 0.4 | AJ95: 0.5 | AK95: 0.5 | AL95: 0.5 | AM95: 0.5 | AN95: 0.5 | AO95: 0.5 | AP95: 0.5 | AQ95: 0.5 | AR95: 0.5 | AS95: 0.5 | AT95: 0.8 | AU95: 0.8 | AV95: 0.8 | AW95: 0.8 | AX95: 0.8 | AY95: 0.8 | AZ95: 0.8 | BA95: 0.8 | BB95: 0.8 | BC95: 0.8 | BD95: 0.8 | BE95: NM
A96: =IF(E96="Total RPS",1,0)+IF(E96="Total RPS (Wtd. Avg.)",1,0) -> 0 | B96: =INDEX(#REF!,MATCH('BNL_RPS Targets (%)'!C96,#REF!,0)) -> #REF! | C96: NM | E96: Coops | F96: 0 | G96: 0 | H96: 0 | I96: 0 | J96: 0 | K96: 0 | L96: 0 | M96: 0 | N96: 0 | O96: 0 | P96: 0 | Q96: 0 | R96: 0 | S96: 0 | T96: 0 | U96: 0.05 | V96: 0.06 | W96: 0.07 | X96: 0.08 | Y96: 0.09 | Z96: 0.1 | AA96: 0.1 | AB96: 0.1 | AC96: 0.1 | AD96: 0.1 | AE96: 0.4 | AF96: 0.4 | AG96: 0.4 | AH96: 0.4 | AI96: 0.4 | AJ96: 0.5 | AK96: 0.5 | AL96: 0.5 | AM96: 0.5 | AN96: 0.5 | AO96: 0.5 | AP96: 0.5 | AQ96: 0.5 | AR96: 0.5 | AS96: 0.5 | AT96: 0.5 | AU96: 0.5 | AV96: 0.5 | AW96: 0.5 | AX96: 0.5 | AY96: 0.5 | AZ96: 0.5 | BA96: 0.5 | BB96: 0.5 | BC96: 0.5 | BD96: 0.8 | BE96: NM
A97: =IF(E97="Total RPS",1,0)+IF(E97="Total RPS (Wtd. Avg.)",1,0) -> 1 | B97: =INDEX(#REF!,MATCH('BNL_RPS Targets (%)'!C97,#REF!,0)) -> #REF! | C97: NV | D97: None | E97: Total RPS | F97: 0 | G97: 0 | H97: 0 | I97: 0.05 | J97: 0.05 | K97: 0.06 | L97: 0.06 | M97: 0.09 | N97: 0.09 | O97: 0.12 | P97: 0.12 | Q97: 0.15 | R97: 0.15 | S97: 0.18 | T97: 0.18 | U97: 0.2 | V97: 0.2 | W97: 0.2 | X97: 0.2 | Y97: 0.2 | Z97: 0.22 | AA97: 0.24 | AB97: 0.29 | AC97: 0.29 | AD97: 0.34 | AE97: 0.34 | AF97: 0.34 | AG97: 0.42 | AH97: 0.42 | AI97: 0.42 | AJ97: 0.5 | AK97: 0.5 | AL97: 0.5 | AM97: 0.5 | AN97: 0.5 | AO97: 0.5 | AP97: 0.5 | AQ97: 0.5 | AR97: 0.5 | AS97: 0.5 | AT97: 0.5 | AU97: 0.5 | AV97: 0.5 | AW97: 0.5 | AX97: 0.5 | AY97: 0.5 | AZ97: 0.5 | BA97: 0.5 | BB97: 0.5 | BC97: 0.5 | BD97: 0.5 | BE97: NV | BF97: Total RPS
A98: =IF(E98="Total RPS",1,0)+IF(E98="Total RPS (Wtd. Avg.)",1,0) -> 1 | B98: =INDEX(#REF!,MATCH('BNL_RPS Targets (%)'!C98,#REF!,0)) -> #REF! | C98: NY | D98: Targets through 2021 are based on NYSERDA's final Phase 2 Implementation Plan, while the targets from 2022-2029 are interpolated assuming a linear ramp up to the final 70% percentage requirement in 2030, with Tier 1 constituting the entirety of all RPS demand growth beyond 2021. The targets for the Main Tier and Customer-Sited Tier for the legacy RPS are included only for informational purposes, and are equal to their terminal levels for 2015. | E98: Total RPS | F98: 0 | G98: 0 | H98: 0 | I98: 0 | J98: 0 | K98: 0 | L98: 0 | M98: 0 | N98: 0 | O98: 0 | P98: 0 | Q98: 0 | R98: 0 | S98: 0 | T98: 0 | U98: 0 | V98: 0 | W98: n/a | X98: 0.274 | Y98: 0.282 | Z98: 0.302 | AA98: 0.32 | AB98: 0.36136551 | AC98: 0.40445661 | AD98: 0.44766233 | AE98: 0.49146266 | AF98: 0.53581916 | AG98: 0.57957691 | AH98: 0.62122007 | AI98: 0.66035338 | AJ98: 0.7 | AK98: 0.7 | AL98: 0.7 | AM98: 0.7 | AN98: 0.7 | AO98: 0.7 | AP98: 0.7 | AQ98: 0.7 | AR98: 0.7 | AS98: 0.7 | AT98: 0.7 | AU98: 0.7 | AV98: 0.7 | AW98: 0.7 | AX98: 0.7 | AY98: 0.7 | AZ98: 0.7 | BA98: 0.7 | BB98: 0.7 | BC98: 0.7 | BD98: 0.7 | BE98: NY | BF98: Total RPS
A99: =IF(E99="Total RPS",1,0)+IF(E99="Total RPS (Wtd. Avg.)",1,0) -> 0 | B99: =INDEX(#REF!,MATCH('BNL_RPS Targets (%)'!C99,#REF!,0)) -> #REF! | C99: NY | E99: Tier 1 (RES) | F99: 0 | G99: 0 | H99: 0 | I99: 0 | J99: 0 | K99: 0 | L99: 0 | M99: 0 | N99: 0 | O99: 0 | P99: 0 | Q99: 0 | R99: 0 | S99: 0 | T99: 0 | U99: 0 | V99: 0 | W99: 0.00035 | X99: 0.0015 | Y99: 0.0078 | Z99: 0.0284 | AA99: 0.042 | AB99: 0.082172547 | AC99: 0.12432557 | AD99: 0.1666973 | AE99: 0.20946553 | AF99: 0.2526591 | AG99: 0.29571745 | AH99: 0.33772164 | AI99: 0.37824212 | AJ99: 0.41890323 | AK99: 0.41977223 | AL99: 0.42136217 | AM99: 0.42220183 | AN99: 0.42320505 | AO99: 0.42460969 | AP99: 0.4260926 | AQ99: 0.42790621 | AR99: 0.42910461 | AS99: 0.43042249 | AT99: 0.43196147 | AU99: 0.43330305 | AV99: 0.43416852 | AW99: 0.43599904 | AX99: 0.43745756 | AY99: 0.43932523 | AZ99: 0.44137847 | BA99: 0.44341121 | BB99: 0.44563236 | BC99: 0.44821298 | BD99: 0.45064334 | BE99: NY
A100: =IF(E100="Total RPS",1,0)+IF(E100="Total RPS (Wtd. Avg.)",1,0) -> 1 | B100: =INDEX(#REF!,MATCH('BNL_RPS Targets (%)'!C100,#REF!,0)) -> #REF! | C100: OH | D100: None | E100: Total RPS | F100: 0 | G100: 0 | H100: 0 | I100: 0 | J100: 0 | K100: 0 | L100: 0 | M100: 0 | N100: 0 | O100: 0.0025 | P100: 0.005 | Q100: 0.01 | R100: 0.015 | S100: 0.02 | T100: 0.025 | U100: 0.025 | V100: 0.025 | W100: 0.035 | X100: 0.045 | Y100: 0.055 | Z100: 0.055 | AA100: 0.06 | AB100: 0.065 | AC100: 0.07 | AD100: 0.075 | AE100: 0.08 | AF100: 0.085 | AG100: 0 | AH100: 0 | AI100: 0 | AJ100: 0 | AK100: 0 | AL100: 0 | AM100: 0 | AN100: 0 | AO100: 0 | AP100: 0 | AQ100: 0 | AR100: 0 | AS100: 0 | AT100: 0 | AU100: 0 | AV100: 0 | AW100: 0 | AX100: 0 | AY100: 0 | AZ100: 0 | BA100: 0 | BB100: 0 | BC100: 0 | BD100: 0 | BE100: OH | BF100: Total RPS
A101: =IF(E101="Total RPS",1,0)+IF(E101="Total RPS (Wtd. Avg.)",1,0) -> 0 | B101: =INDEX(#REF!,MATCH('BNL_RPS Targets (%)'!C101,#REF!,0)) -> #REF! | C101: OH | E101: Solar Carve-Out | F101: 0 | G101: 0 | H101: 0 | I101: 0 | J101: 0 | K101: 0 | L101: 0 | M101: 0 | N101: 0 | O101: 4e-05 | P101: 0.0001 | Q101: 0.0003 | R101: 0.0006 | S101: 0.0009 | T101: 0.0012 | U101: 0.0012 | V101: 0.0012 | W101: 0.0015 | X101: 0.0018 | Y101: 0.0022 | Z101: 0 | AA101: 0 | AB101: 0 | AC101: 0 | AD101: 0 | AE101: 0 | AF101: 0 | AG101: 0 | AH101: 0 | AI101: 0 | AJ101: 0 | AK101: 0 | AL101: 0 | AM101: 0 | AN101: 0 | AO101: 0 | AP101: 0 | AQ101: 0 | AR101: 0 | AS101: 0 | AT101: 0 | AU101: 0 | AV101: 0 | AW101: 0 | AX101: 0 | AY101: 0 | AZ101: 0 | BA101: 0 | BB101: 0 | BC101: 0 | BD101: 0 | BE101: OH | BF101: Solar or DG Carve-Out
A102: =IF(E102="Total RPS",1,0)+IF(E102="Total RPS (Wtd. Avg.)",1,0) -> 1 | B102: =INDEX(#REF!,MATCH('BNL_RPS Targets (%)'!C102,#REF!,0)) -> #REF! | C102: OR | D102: Targets differ between based on utility type and size, and the weighted average is based on the retail electricity sales of utilities subject to the RPS. The solar carve-out applies only to IOUs. | E102: Total RPS (Wtd. Avg.) | F102: 0 | G102: 0 | H102: 0 | I102: 0 | J102: 0 | K102: 0 | L102: 0 | M102: 0 | N102: 0 | O102: 0 | P102: 0 | Q102: 0.0369152 | R102: 0.036771553 | S102: 0.036595614 | T102: 0.036264262 | U102: 0.11264328 | V102: 0.11170755 | W102: 0.11046182 | X102: 0.11004013 | Y102: 0.11003776 | Z102: 0.15115327 | AA102: 0.15115844 | AB102: 0.15116039 | AC102: 0.15116094 | AD102: 0.1511615 | AE102: 0.2148495 | AF102: 0.21484985 | AG102: 0.21484989 | AH102: 0.21485075 | AI102: 0.21485193 | AJ102: 0.27812266 | AK102: 0.27812342 | AL102: 0.27812474 | AM102: 0.27812637 | AN102: 0.2781281 | AO102: 0.35070037 | AP102: 0.35070253 | AQ102: 0.35070504 | AR102: 0.35070739 | AS102: 0.35070982 | AT102: 0.3848247 | AU102: 0.38482729 | AV102: 0.38482958 | AW102: 0.38483223 | AX102: 0.38483486 | AY102: 0.38483753 | AZ102: 0.38484016 | BA102: 0.38484298 | BB102: 0.38484606 | BC102: 0.38484883 | BD102: 0.38485146 | BE102: OR | BF102: Total RPS
A103: =IF(E103="Total RPS",1,0)+IF(E103="Total RPS (Wtd. Avg.)",1,0) -> 0 | B103: =INDEX(#REF!,MATCH('BNL_RPS Targets (%)'!C103,#REF!,0)) -> #REF! | C103: OR | E103: Large IOUs | F103: 0 | G103: 0 | H103: 0 | I103: 0 | J103: 0 | K103: 0 | L103: 0 | M103: 0 | N103: 0 | O103: 0 | P103: 0 | Q103: 0.05 | R103: 0.05 | S103: 0.05 | T103: 0.05 | U103: 0.15 | V103: 0.15 | W103: 0.15 | X103: 0.15 | Y103: 0.15 | Z103: 0.2 | AA103: 0.2 | AB103: 0.2 | AC103: 0.2 | AD103: 0.2 | AE103: 0.27 | AF103: 0.27 | AG103: 0.27 | AH103: 0.27 | AI103: 0.27 | AJ103: 0.35 | AK103: 0.35 | AL103: 0.35 | AM103: 0.35 | AN103: 0.35 | AO103: 0.45 | AP103: 0.45 | AQ103: 0.45 | AR103: 0.45 | AS103: 0.45 | AT103: 0.5 | AU103: 0.5 | AV103: 0.5 | AW103: 0.5 | AX103: 0.5 | AY103: 0.5 | AZ103: 0.5 | BA103: 0.5 | BB103: 0.5 | BC103: 0.5 | BD103: 0.5 | BE103: OR
A104: =IF(E104="Total RPS",1,0)+IF(E104="Total RPS (Wtd. Avg.)",1,0) -> 0 | B104: =INDEX(#REF!,MATCH('BNL_RPS Targets (%)'!C104,#REF!,0)) -> #REF! | C104: OR | E104: Large Consumer Owned Utilities | F104: 0 | G104: 0 | H104: 0 | I104: 0 | J104: 0 | K104: 0 | L104: 0 | M104: 0 | N104: 0 | O104: 0 | P104: 0 | Q104: 0.05 | R104: 0.05 | S104: 0.05 | T104: 0.05 | U104: 0.15 | V104: 0.15 | W104: 0.15 | X104: 0.15 | Y104: 0.15 | Z104: 0.2 | AA104: 0.2 | AB104: 0.2 | AC104: 0.2 | AD104: 0.2 | AE104: 0.25 | AF104: 0.25 | AG104: 0.25 | AH104: 0.25 | AI104: 0.25 | AJ104: 0.25 | AK104: 0.25 | AL104: 0.25 | AM104: 0.25 | AN104: 0.25 | AO104: 0.25 | AP104: 0.25 | AQ104: 0.25 | AR104: 0.25 | AS104: 0.25 | AT104: 0.25 | AU104: 0.25 | AV104: 0.25 | AW104: 0.25 | AX104: 0.25 | AY104: 0.25 | AZ104: 0.25 | BA104: 0.25 | BB104: 0.25 | BC104: 0.25 | BD104: 0.25 | BE104: OR
A105: =IF(E105="Total RPS",1,0)+IF(E105="Total RPS (Wtd. Avg.)",1,0) -> 0 | B105: =INDEX(#REF!,MATCH('BNL_RPS Targets (%)'!C105,#REF!,0)) -> #REF! | C105: OR | E105: Medium-to-Large Utilities | F105: 0 | G105: 0 | H105: 0 | I105: 0 | J105: 0 | K105: 0 | L105: 0 | M105: 0 | N105: 0 | O105: 0 | P105: 0 | Q105: 0 | R105: 0 | S105: 0 | T105: 0 | U105: 0 | V105: 0 | W105: 0 | X105: 0 | Y105: 0 | Z105: 0.05 | AA105: 0.05 | AB105: 0.05 | AC105: 0.05 | AD105: 0.05 | AE105: 0.1 | AF105: 0.1 | AG105: 0.1 | AH105: 0.1 | AI105: 0.1 | AJ105: 0.2 | AK105: 0.2 | AL105: 0.2 | AM105: 0.2 | AN105: 0.2 | AO105: 0.25 | AP105: 0.25 | AQ105: 0.25 | AR105: 0.25 | AS105: 0.25 | AT105: 0.25 | AU105: 0.25 | AV105: 0.25 | AW105: 0.25 | AX105: 0.25 | AY105: 0.25 | AZ105: 0.25 | BA105: 0.25 | BB105: 0.25 | BC105: 0.25 | BD105: 0.25 | BE105: OR
A106: =IF(E106="Total RPS",1,0)+IF(E106="Total RPS (Wtd. Avg.)",1,0) -> 0 | B106: =INDEX(#REF!,MATCH('BNL_RPS Targets (%)'!C106,#REF!,0)) -> #REF! | C106: OR | E106: Medium Utilities | F106: 0 | G106: 0 | H106: 0 | I106: 0 | J106: 0 | K106: 0 | L106: 0 | M106: 0 | N106: 0 | O106: 0 | P106: 0 | Q106: 0 | R106: 0 | S106: 0 | T106: 0 | U106: 0 | V106: 0 | W106: 0 | X106: 0 | Y106: 0 | Z106: 0 | AA106: 0 | AB106: 0 | AC106: 0 | AD106: 0 | AE106: 0.1 | AF106: 0.1 | AG106: 0.1 | AH106: 0.1 | AI106: 0.1 | AJ106: 0.1 | AK106: 0.1 | AL106: 0.1 | AM106: 0.1 | AN106: 0.1 | AO106: 0.1 | AP106: 0.1 | AQ106: 0.1 | AR106: 0.1 | AS106: 0.1 | AT106: 0.1 | AU106: 0.1 | AV106: 0.1 | AW106: 0.1 | AX106: 0.1 | AY106: 0.1 | AZ106: 0.1 | BA106: 0.1 | BB106: 0.1 | BC106: 0.1 | BD106: 0.1 | BE106: OR
A107: =IF(E107="Total RPS",1,0)+IF(E107="Total RPS (Wtd. Avg.)",1,0) -> 0 | B107: =INDEX(#REF!,MATCH('BNL_RPS Targets (%)'!C107,#REF!,0)) -> #REF! | C107: OR | E107: Small Utilities | F107: 0 | G107: 0 | H107: 0 | I107: 0 | J107: 0 | K107: 0 | L107: 0 | M107: 0 | N107: 0 | O107: 0 | P107: 0 | Q107: 0 | R107: 0 | S107: 0 | T107: 0 | U107: 0 | V107: 0 | W107: 0 | X107: 0 | Y107: 0 | Z107: 0 | AA107: 0 | AB107: 0 | AC107: 0 | AD107: 0 | AE107: 0.05 | AF107: 0.05 | AG107: 0.05 | AH107: 0.05 | AI107: 0.05 | AJ107: 0.05 | AK107: 0.05 | AL107: 0.05 | AM107: 0.05 | AN107: 0.05 | AO107: 0.05 | AP107: 0.05 | AQ107: 0.05 | AR107: 0.05 | AS107: 0.05 | AT107: 0.05 | AU107: 0.05 | AV107: 0.05 | AW107: 0.05 | AX107: 0.05 | AY107: 0.05 | AZ107: 0.05 | BA107: 0.05 | BB107: 0.05 | BC107: 0.05 | BD107: 0.05 | BE107: OR
A108: =IF(E108="Total RPS",1,0)+IF(E108="Total RPS (Wtd. Avg.)",1,0) -> 0 | B108: =INDEX(#REF!,MATCH('BNL_RPS Targets (%)'!C108,#REF!,0)) -> #REF! | C108: OR | E108: Solar Carve-Out (IOUs only) | F108: 0 | G108: 0 | H108: 0 | I108: 0 | J108: 0 | K108: 0 | L108: 0 | M108: 0 | N108: 0 | O108: 0 | P108: 0 | Q108: 0 | R108: 0 | S108: 0 | T108: 0 | U108: 0.00039056142 | V108: 0.00039628944 | W108: 0.00038556861 | X108: 0.0003971322 | Y108: 0.00040061415 | Z108: 0.00040183468 | AA108: 0.0003942593 | AB108: 0.00039140095 | AC108: 0.00039059802 | AD108: 0.00038977209 | AE108: 0.00039003465 | AF108: 0.00038951845 | AG108: 0.00038946436 | AH108: 0.00038820271 | AI108: 0.00038647137 | AJ108: 0.00038740348 | AK108: 0.00038628603 | AL108: 0.00038434896 | AM108: 0.00038196757 | AN108: 0.00037942391 | AO108: 0.00037640054 | AP108: 0.00037323634 | AQ108: 0.0003695625 | AR108: 0.00036612046 | AS108: 0.00036255787 | AT108: 0.00035848671 | AU108: 0.00035469205 | AV108: 0.00035134521 | AW108: 0.00034746313 | AX108: 0.00034360167 | AY108: 0.00033968603 | AZ108: 0.00033582898 | BA108: 0.00033169841 | BB108: 0.00032718688 | BC108: 0.00032312112 | BD108: 0.00031927475 | BE108: OR | BF108: Solar or DG Carve-Out
A109: =IF(E109="Total RPS",1,0)+IF(E109="Total RPS (Wtd. Avg.)",1,0) -> 1 | B109: =INDEX(#REF!,MATCH('BNL_RPS Targets (%)'!C109,#REF!,0)) -> #REF! | C109: PA | D109: None | E109: Total RPS | F109: 0 | G109: 0 | H109: 0.02 | I109: 0 | J109: 0 | K109: 0 | L109: 0 | M109: 0.057 | N109: 0.057 | O109: 0.062 | P109: 0.067 | Q109: 0.092 | R109: 0.097 | S109: 0.102 | T109: 0.107 | U109: 0.112 | V109: 0.137 | W109: 0.142 | X109: 0.147 | Y109: 0.152 | Z109: 0.157 | AA109: 0.18 | AB109: 0.18 | AC109: 0.18 | AD109: 0.18 | AE109: 0.18 | AF109: 0.18 | AG109: 0.18 | AH109: 0.18 | AI109: 0.18 | AJ109: 0.18 | AK109: 0.18 | AL109: 0.18 | AM109: 0.18 | AN109: 0.18 | AO109: 0.18 | AP109: 0.18 | AQ109: 0.18 | AR109: 0.18 | AS109: 0.18 | AT109: 0.18 | AU109: 0.18 | AV109: 0.18 | AW109: 0.18 | AX109: 0.18 | AY109: 0.18 | AZ109: 0.18 | BA109: 0.18 | BB109: 0.18 | BC109: 0.18 | BD109: 0.18 | BE109: PA | BF109: Total RPS
A110: =IF(E110="Total RPS",1,0)+IF(E110="Total RPS (Wtd. Avg.)",1,0) -> 0 | B110: =INDEX(#REF!,MATCH('BNL_RPS Targets (%)'!C110,#REF!,0)) -> #REF! | C110: PA | E110: Solar Carve-Out | F110: 0 | G110: 0 | H110: 0 | I110: 0 | J110: 0 | K110: 0 | L110: 0 | M110: 1.3e-05 | N110: 3e-05 | O110: 6.3e-05 | P110: 0.00012 | Q110: 0.000203 | R110: 0.000325 | S110: 0.00051 | T110: 0.00084 | U110: 0.00144 | V110: 0.0025 | W110: 0.002933 | X110: 0.0034 | Y110: 0.0039 | Z110: 0.004433 | AA110: 0.005 | AB110: 0.005 | AC110: 0.005 | AD110: 0.005 | AE110: 0.005 | AF110: 0.005 | AG110: 0.005 | AH110: 0.005 | AI110: 0.005 | AJ110: 0.005 | AK110: 0.005 | AL110: 0.005 | AM110: 0.005 | AN110: 0.005 | AO110: 0.005 | AP110: 0.005 | AQ110: 0.005 | AR110: 0.005 | AS110: 0.005 | AT110: 0.005 | AU110: 0.005 | AV110: 0.005 | AW110: 0.005 | AX110: 0.005 | AY110: 0.005 | AZ110: 0.005 | BA110: 0.005 | BB110: 0.005 | BC110: 0.005 | BD110: 0.005 | BE110: PA | BF110: Solar or DG Carve-Out
A111: =IF(E111="Total RPS",1,0)+IF(E111="Total RPS (Wtd. Avg.)",1,0) -> 0 | B111: =INDEX(#REF!,MATCH('BNL_RPS Targets (%)'!C111,#REF!,0)) -> #REF! | C111: PA | E111: Tier I Non-Solar | F111: 0 | G111: 0 | H111: 0.02 | I111: 0 | J111: 0 | K111: 0 | L111: 0 | M111: 0.014987 | N111: 0.01497 | O111: 0.019937 | P111: 0.02488 | Q111: 0.029797 | R111: 0.034675 | S111: 0.03949 | T111: 0.04416 | U111: 0.04856 | V111: 0.0525 | W111: 0.057067 | X111: 0.0616 | Y111: 0.0661 | Z111: 0.070567 | AA111: 0.075 | AB111: 0.075 | AC111: 0.075 | AD111: 0.075 | AE111: 0.075 | AF111: 0.075 | AG111: 0.075 | AH111: 0.075 | AI111: 0.075 | AJ111: 0.075 | AK111: 0.075 | AL111: 0.075 | AM111: 0.075 | AN111: 0.075 | AO111: 0.075 | AP111: 0.075 | AQ111: 0.075 | AR111: 0.075 | AS111: 0.075 | AT111: 0.075 | AU111: 0.075 | AV111: 0.075 | AW111: 0.075 | AX111: 0.075 | AY111: 0.075 | AZ111: 0.075 | BA111: 0.075 | BB111: 0.075 | BC111: 0.075 | BD111: 0.075 | BE111: PA | BF111: General RPS/Primary Tier
A112: =IF(E112="Total RPS",1,0)+IF(E112="Total RPS (Wtd. Avg.)",1,0) -> 0 | B112: =INDEX(#REF!,MATCH('BNL_RPS Targets (%)'!C112,#REF!,0)) -> #REF! | C112: PA | E112: Tier II | F112: 0 | G112: 0 | H112: 0 | I112: 0 | J112: 0 | K112: 0 | L112: 0 | M112: 0.042 | N112: 0.042 | O112: 0.042 | P112: 0.042 | Q112: 0.062 | R112: 0.062 | S112: 0.062 | T112: 0.062 | U112: 0.062 | V112: 0.082 | W112: 0.082 | X112: 0.082 | Y112: 0.082 | Z112: 0.082 | AA112: 0.1 | AB112: 0.1 | AC112: 0.1 | AD112: 0.1 | AE112: 0.1 | AF112: 0.1 | AG112: 0.1 | AH112: 0.1 | AI112: 0.1 | AJ112: 0.1 | AK112: 0.1 | AL112: 0.1 | AM112: 0.1 | AN112: 0.1 | AO112: 0.1 | AP112: 0.1 | AQ112: 0.1 | AR112: 0.1 | AS112: 0.1 | AT112: 0.1 | AU112: 0.1 | AV112: 0.1 | AW112: 0.1 | AX112: 0.1 | AY112: 0.1 | AZ112: 0.1 | BA112: 0.1 | BB112: 0.1 | BC112: 0.1 | BD112: 0.1 | BE112: PA | BF112: Secondary Tier
A113: =IF(E113="Total RPS",1,0)+IF(E113="Total RPS (Wtd. Avg.)",1,0) -> 1 | B113: =INDEX(#REF!,MATCH('BNL_RPS Targets (%)'!C113,#REF!,0)) -> #REF! | C113: RI | D113: None | E113: Total RPS | F113: 0 | G113: 0 | H113: 0 | I113: 0 | J113: 0 | K113: 0 | L113: 0 | M113: 0.03 | N113: 0.035 | O113: 0.04 | P113: 0.045 | Q113: 0.055 | R113: 0.065 | S113: 0.075 | T113: 0.085 | U113: 0.085 | V113: 0.1 | W113: 0.115 | X113: 0.13 | Y113: 0.145 | Z113: 0.16 | AA113: 0.175 | AB113: 0.19 | AC113: 0.205 | AD113: 0.22 | AE113: 0.235 | AF113: 0.25 | AG113: 0.265 | AH113: 0.28 | AI113: 0.295 | AJ113: 0.31 | AK113: 0.325 | AL113: 0.34 | AM113: 0.355 | AN113: 0.37 | AO113: 0.385 | AP113: 0.385 | AQ113: 0.385 | AR113: 0.385 | AS113: 0.385 | AT113: 0.385 | AU113: 0.385 | AV113: 0.385 | AW113: 0.385 | AX113: 0.385 | AY113: 0.385 | AZ113: 0.385 | BA113: 0.385 | BB113: 0.385 | BC113: 0.385 | BD113: 0.385 | BE113: RI | BF113: Total RPS
A114: =IF(E114="Total RPS",1,0)+IF(E114="Total RPS (Wtd. Avg.)",1,0) -> 0 | B114: =INDEX(#REF!,MATCH('BNL_RPS Targets (%)'!C114,#REF!,0)) -> #REF! | C114: RI | E114: New | F114: 0 | G114: 0 | H114: 0 | I114: 0 | J114: 0 | K114: 0 | L114: 0 | M114: 0.01 | N114: 0.015 | O114: 0.02 | P114: 0.025 | Q114: 0.035 | R114: 0.045 | S114: 0.055 | T114: 0.065 | U114: 0.065 | V114: 0.08 | W114: 0.095 | X114: 0.11 | Y114: 0.125 | Z114: 0.14 | AA114: 0.155 | AB114: 0.17 | AC114: 0.185 | AD114: 0.2 | AE114: 0.215 | AF114: 0.23 | AG114: 0.245 | AH114: 0.26 | AI114: 0.275 | AJ114: 0.29 | AK114: 0.305 | AL114: 0.32 | AM114: 0.335 | AN114: 0.35 | AO114: 0.365 | AP114: 0.365 | AQ114: 0.365 | AR114: 0.365 | AS114: 0.365 | AT114: 0.365 | AU114: 0.365 | AV114: 0.365 | AW114: 0.365 | AX114: 0.365 | AY114: 0.365 | AZ114: 0.365 | BA114: 0.365 | BB114: 0.365 | BC114: 0.365 | BD114: 0.365 | BE114: RI | BF114: General RPS/Primary Tier
A115: =IF(E115="Total RPS",1,0)+IF(E115="Total RPS (Wtd. Avg.)",1,0) -> 0 | B115: =INDEX(#REF!,MATCH('BNL_RPS Targets (%)'!C115,#REF!,0)) -> #REF! | C115: RI | E115: Existing | F115: 0 | G115: 0 | H115: 0 | I115: 0 | J115: 0 | K115: 0 | L115: 0 | M115: 0.02 | N115: 0.02 | O115: 0.02 | P115: 0.02 | Q115: 0.02 | R115: 0.02 | S115: 0.02 | T115: 0.02 | U115: 0.02 | V115: 0.02 | W115: 0.02 | X115: 0.02 | Y115: 0.02 | Z115: 0.02 | AA115: 0.02 | AB115: 0.02 | AC115: 0.02 | AD115: 0.02 | AE115: 0.02 | AF115: 0.02 | AG115: 0.02 | AH115: 0.02 | AI115: 0.02 | AJ115: 0.02 | AK115: 0.02 | AL115: 0.02 | AM115: 0.02 | AN115: 0.02 | AO115: 0.02 | AP115: 0.02 | AQ115: 0.02 | AR115: 0.02 | AS115: 0.02 | AT115: 0.02 | AU115: 0.02 | AV115: 0.02 | AW115: 0.02 | AX115: 0.02 | AY115: 0.02 | AZ115: 0.02 | BA115: 0.02 | BB115: 0.02 | BC115: 0.02 | BD115: 0.02 | BE115: RI | BF115: Secondary Tier
A116: =IF(E116="Total RPS",1,0)+IF(E116="Total RPS (Wtd. Avg.)",1,0) -> 1 | B116: =INDEX(#REF!,MATCH('BNL_RPS Targets (%)'!C116,#REF!,0)) -> #REF! | C116: TX | D116: RPS target denominated in MW terms; translated to equivalent percentage of applicable sales based on average capacity factor of operating wind power projects in Texas. | E116: Total RPS | F116: 0 | G116: 0 | H116: 0.016018435 | I116: 0.016690136 | J116: 0.016365272 | K116: 0.016929774 | L116: 0.016836018 | M116: 0.02249756 | N116: 0.025867451 | O116: 0.037591663 | P116: 0.034105899 | Q116: 0.041843895 | R116: 0.044636072 | S116: 0.054162946 | T116: 0.053301962 | U116: 0.059336411 | V116: 0.060231445 | W116: 0.059729037 | X116: 0.056557196 | Y116: 0.055210701 | Z116: 0.055617006 | AA116: 0.054423454 | AB116: 0.05372915 | AC116: 0.05325407 | AD116: 0.052810565 | AE116: 0.052406423 | AF116: 0.052079438 | AG116: 0.051799203 | AH116: 0.051469769 | AI116: 0.051036525 | AJ116: 0.050615821 | AK116: 0.050176663 | AL116: 0.049726154 | AM116: 0.04926472 | AN116: 0.048810336 | AO116: 0.048306321 | AP116: 0.047791549 | AQ116: 0.047246389 | AR116: 0.046739508 | AS116: 0.046258014 | AT116: 0.045781984 | AU116: 0.04529136 | AV116: 0.044707887 | AW116: 0.044242939 | AX116: 0.043776756 | AY116: 0.043279452 | AZ116: 0.042761754 | BA116: 0.042269298 | BB116: 0.041799412 | BC116: 0.041319105 | BD116: 0.040826268 | BE116: TX | BF116: Total RPS
A117: =IF(E117="Total RPS",1,0)+IF(E117="Total RPS (Wtd. Avg.)",1,0) -> 1 | B117: =INDEX(#REF!,MATCH('BNL_RPS Targets (%)'!C117,#REF!,0)) -> #REF! | C117: VA | D117: Targets differ between the two utilities subject to the RPS, and the weighted average is based on their respective retail electricity sales. | E117: Total RPS (Wtd. Avg.) | F117: 0 | G117: 0 | H117: 0 | I117: 0 | J117: 0 | K117: 0 | L117: 0 | M117: 0 | N117: 0 | O117: 0 | P117: 0 | Q117: 0 | R117: 0 | S117: 0 | T117: 0 | U117: 0 | V117: 0 | W117: 0 | X117: 0 | Y117: 0 | Z117: 0 | AA117: 0.12706546 | AB117: 0.15383025 | AC117: 0.18059538 | AD117: 0.2089774 | AE117: 0.24059372 | AF117: 0.27059285 | AG117: 0.30059188 | AH117: 0.33220812 | AI117: 0.36220688 | AJ117: 0.39220584 | AK117: 0.43058694 | AL117: 0.46896766 | AM117: 0.49896619 | AN117: 0.52896463 | AO117: 0.56734478 | AP117: 0.61381646 | AQ117: 0.64734128 | AR117: 0.6873396 | AS117: 0.72733793 | AT117: 0.76733629 | AU117: 0.80571559 | AV117: 0.8440947 | AW117: 0.88247341 | AX117: 0.92085194 | AY117: 0.96761067 | AZ117: 0.97408642 | BA117: 0.98056318 | BB117: 0.98704105 | BC117: 0.99351996 | BD117: 1 | BE117: VA | BF117: Total RPS
A118: =IF(E118="Total RPS",1,0)+IF(E118="Total RPS (Wtd. Avg.)",1,0) -> 0 | B118: =INDEX(#REF!,MATCH('BNL_RPS Targets (%)'!C118,#REF!,0)) -> #REF! | C118: VA | E118: DG Carve-Out (Dominion) | F118: 0 | G118: 0 | H118: 0 | I118: 0 | J118: 0 | K118: 0 | L118: 0 | M118: 0 | N118: 0 | O118: 0 | P118: 0 | Q118: 0 | R118: 0 | S118: 0 | T118: 0 | U118: 0 | V118: 0 | W118: 0 | X118: 0 | Y118: 0 | Z118: 0 | AA118: 0.0014 | AB118: 0.0017 | AC118: 0.002 | AD118: 0.0023 | AE118: 0.0026 | AF118: 0.0029 | AG118: 0.0032 | AH118: 0.0035 | AI118: 0.0038 | AJ118: 0.0041 | AK118: 0.0045 | AL118: 0.0049 | AM118: 0.0052 | AN118: 0.0055 | AO118: 0.0059 | AP118: 0.0063 | AQ118: 0.0067 | AR118: 0.0071 | AS118: 0.0075 | AT118: 0.0079 | AU118: 0.0083 | AV118: 0.0087 | AW118: 0.0091 | AX118: 0.0095 | AY118: 0.01 | AZ118: 0.01 | BA118: 0.01 | BB118: 0.01 | BC118: 0.01 | BD118: 0.01 | BE118: VA | BF118: Solar or DG Carve-Out
...

Sheet BNL calcs
C2: RPS Targets (Percent of Applicable Retail Electricity Sales) | BE2: Search terms
A3: RPS TOTAL 1=true | B3: GENERATION | C3: State | D3: Special Notes | E3: RPS Tier or Carve Out | F3: 2000 | G3: 2001 | H3: 2002 | I3: 2003 | J3: 2004 | K3: 2005 | L3: 2006 | M3: 2007 | N3: 2008 | O3: 2009 | P3: 2010 | Q3: 2011 | R3: 2012 | S3: 2013 | T3: 2014 | U3: 2015 | V3: 2016 | W3: 2017 | X3: 2018 | Y3: 2019 | Z3: 2020 | AA3: 2021 | AB3: 2022 | AC3: 2023 | AD3: 2024 | AE3: 2025 | AF3: 2026 | AG3: 2027 | AH3: 2028 | AI3: 2029 | AJ3: 2030 | AK3: 2031 | AL3: 2032 | AM3: 2033 | AN3: 2034 | AO3: 2035 | AP3: 2036 | AQ3: 2037 | AR3: 2038 | AS3: 2039 | AT3: 2040 | AU3: 2041 | AV3: 2042 | AW3: 2043 | AX3: 2044 | AY3: 2045 | AZ3: 2046 | BA3: 2047 | BB3: 2048 | BC3: 2049 | BD3: 2050 | BE3: State | BF3: Tier
A4: 1 | B4: =SUMIFS(#REF!,#REF!,$C4,#REF!,"Total",#REF!,"Total Electric Power Industry") -> #REF! | C4: AZ | D4: Arizona had a solar carve-out, which was subsequently replaced by the current DG carve-out in 2008. | E4: Total RPS | F4: 0 | G4: 0.002 | H4: 0.004 | I4: 0.006 | J4: 0.008 | K4: 0.01 | L4: 0.0125 | M4: 0.015 | N4: 0.0175 | O4: 0.02 | P4: 0.025 | Q4: 0.03 | R4: 0.035 | S4: 0.04 | T4: 0.045 | U4: 0.05 | V4: 0.06 | W4: 0.07 | X4: 0.08 | Y4: 0.09 | Z4: 0.1 | AA4: 0.11 | AB4: 0.12 | AC4: 0.13 | AD4: 0.14 | AE4: 0.15 | AF4: 0.15 | AG4: 0.15 | AH4: 0.15 | AI4: 0.15 | AJ4: 0.15 | AK4: 0.15 | AL4: 0.15 | AM4: 0.15 | AN4: 0.15 | AO4: 0.15 | AP4: 0.15 | AQ4: 0.15 | AR4: 0.15 | AS4: 0.15 | AT4: 0.15 | AU4: 0.15 | AV4: 0.15 | AW4: 0.15 | AX4: 0.15 | AY4: 0.15 | AZ4: 0.15 | BA4: 0.15 | BB4: 0.15 | BC4: 0.15 | BD4: 0.15 | BE4: AZ | BF4: Total RPS
A5: 1 | B5: =SUMIFS(#REF!,#REF!,$C5,#REF!,"Total",#REF!,"Total Electric Power Industry") -> #REF! | C5: CA | D5: Through 2015, the values shown here represent targets for the state's three large IOUs through 2015 (targets for other utilities' were lower). From 2016 onward, the values shown here represent statewide targets applicable to all utilities. | E5: Total RPS | F5: 0 | G5: 0 | H5: 0 | I5: 0.11852494 | J5: 0.12852494 | K5: 0.13852494 | L5: 0.14852494 | M5: 0.15852494 | N5: 0.16852494 | O5: 0.17852494 | P5: 0.2 | Q5: 0.2 | R5: 0.2 | S5: 0.2 | T5: 0.217 | U5: 0.233 | V5: 0.25 | W5: 0.27 | X5: 0.29 | Y5: 0.31 | Z5: 0.33 | AA5: 0.33 | AB5: 0.33 | AC5: 0.33 | AD5: 0.44 | AE5: 0.44 | AF5: 0.44 | AG5: 0.52 | AH5: 0.52 | AI5: 0.52 | AJ5: 0.6 | AK5: 0.6 | AL5: 0.6 | AM5: 0.6 | AN5: 0.6 | AO5: 0.6 | AP5: 0.6 | AQ5: 0.6 | AR5: 0.6 | AS5: 0.6 | AT5: 0.6 | AU5: 0.6 | AV5: 0.6 | AW5: 0.6 | AX5: 0.6 | AY5: 0.6 | AZ5: 0.6 | BA5: 0.6 | BB5: 0.6 | BC5: 0.6 | BD5: 0.6 | BE5: CA | BF5: Total RPS
A6: 1 | B6: =SUMIFS(#REF!,#REF!,$C6,#REF!,"Total",#REF!,"Total Electric Power Industry") -> #REF! | C6: CO | D6: Targets vary based on utility type and size, and whether the utility is served by a generation and transmission (G&T) cooperative. Weighted averages are based on the retail electricity sales of utilities subject to the RPS. | E6: Total RPS (Wtd. Avg.) | F6: 0 | G6: 0 | H6: 0 | I6: 0 | J6: 0 | K6: 0 | L6: 0 | M6: 0.03 | N6: 0.034567782 | O6: 0.034261979 | P6: 0.034203742 | Q6: 0.08435376 | R6: 0.084921879 | S6: 0.085100327 | T6: 0.084973227 | U6: 0.14498606 | V6: 0.144233 | W6: 0.14368257 | X6: 0.14191418 | Y6: 0.14191418 | Z6: 0.2410564 | AA6: 0.2410564 | AB6: 0.2410564 | AC6: 0.23922197 | AD6: 0.23922197 | AE6: 0.23922197 | AF6: 0.23922197 | AG6: 0.23922197 | AH6: 0.23922197 | AI6: 0.23922197 | AJ6: 0.23922197 | AK6: 0.23922197 | AL6: 0.23922197 | AM6: 0.23922197 | AN6: 0.23922197 | AO6: 0.23922197 | AP6: 0.23922197 | AQ6: 0.23922197 | AR6: 0.23922197 | AS6: 0.23922197 | AT6: 0.23922197 | AU6: 0.23922197 | AV6: 0.23922197 | AW6: 0.23922197 | AX6: 0.23922197 | AY6: 0.23922197 | AZ6: 0.23922197 | BA6: 0.23922197 | BB6: 0.23922197 | BC6: 0.23922197 | BD6: 0.23922197 | BE6: CO | BF6: Total RPS
A7: 1 | B7: =SUMIFS(#REF!,#REF!,$C7,#REF!,"Total",#REF!,"Total Electric Power Industry") -> #REF! | C7: CT | D7: None | E7: Total RPS | F7: 0 | G7: 0.0625 | H7: 0.065 | I7: 0.07 | J7: 0.04 | K7: 0.045 | L7: 0.05 | M7: 0.065 | N7: 0.08 | O7: 0.09 | P7: 0.1 | Q7: 0.11 | R7: 0.12 | S7: 0.13 | T7: 0.14 | U7: 0.155 | V7: 0.17 | W7: 0.185 | X7: 0.21 | Y7: 0.235 | Z7: 0.25 | AA7: 0.265 | AB7: 0.28 | AC7: 0.3 | AD7: 0.32 | AE7: 0.34 | AF7: 0.36 | AG7: 0.38 | AH7: 0.4 | AI7: 0.42 | AJ7: 0.44 | AK7: 0.44 | AL7: 0.44 | AM7: 0.44 | AN7: 0.44 | AO7: 0.44 | AP7: 0.44 | AQ7: 0.44 | AR7: 0.44 | AS7: 0.44 | AT7: 0.44 | AU7: 0.44 | AV7: 0.44 | AW7: 0.44 | AX7: 0.44 | AY7: 0.44 | AZ7: 0.44 | BA7: 0.44 | BB7: 0.44 | BC7: 0.44 | BD7: 0.44 | BE7: CT | BF7: Total RPS
A8: 1 | B8: =SUMIFS(#REF!,#REF!,$C8,#REF!,"Total",#REF!,"Total Electric Power Industry") -> #REF! | C8: DC | D8: None | E8: Total RPS | F8: 0 | G8: 0 | H8: 0 | I8: 0 | J8: 0 | K8: 0 | L8: 0 | M8: 0.04 | N8: 0.045 | O8: 0.05 | P8: 0.055 | Q8: 0.065 | R8: 0.075 | S8: 0.09 | T8: 0.105 | U8: 0.12 | V8: 0.135 | W8: 0.15 | X8: 0.165 | Y8: 0.18 | Z8: 0.2 | AA8: 0.2625 | AB8: 0.325 | AC8: 0.3875 | AD8: 0.45 | AE8: 0.52 | AF8: 0.59 | AG8: 0.66 | AH8: 0.73 | AI8: 0.8 | AJ8: 0.87 | AK8: 0.94 | AL8: 1 | AM8: 1 | AN8: 1 | AO8: 1 | AP8: 1 | AQ8: 1 | AR8: 1 | AS8: 1 | AT8: 1 | AU8: 1 | AV8: 1 | AW8: 1 | AX8: 1 | AY8: 1 | AZ8: 1 | BA8: 1 | BB8: 1 | BC8: 1 | BD8: 1 | BE8: DC | BF8: Total RPS
A9: 1 | B9: =SUMIFS(#REF!,#REF!,$C9,#REF!,"Total",#REF!,"Total Electric Power Industry") -> #REF! | C9: DE | D9: None | E9: Total RPS | F9: 0 | G9: 0 | H9: 0 | I9: 0 | J9: 0 | K9: 0 | L9: 0 | M9: 0 | N9: 0 | O9: 0 | P9: 0 | Q9: 0 | R9: 0 | S9: 0 | T9: 0.1 | U9: 0.115 | V9: 0.13 | W9: 0.145 | X9: 0.16 | Y9: 0.175 | Z9: 0.19 | AA9: 0.2 | AB9: 0.21 | AC9: 0.22 | AD9: 0.23 | AE9: 0.24 | AF9: 0.25 | AG9: 0.25 | AH9: 0.25 | AI9: 0.25 | AJ9: 0.25 | AK9: 0.25 | AL9: 0.25 | AM9: 0.25 | AN9: 0.25 | AO9: 0.25 | AP9: 0.25 | AQ9: 0.25 | AR9: 0.25 | AS9: 0.25 | AT9: 0.25 | AU9: 0.25 | AV9: 0.25 | AW9: 0.25 | AX9: 0.25 | AY9: 0.25 | AZ9: 0.25 | BA9: 0.25 | BB9: 0.25 | BC9: 0.25 | BD9: 0.25 | BE9: DE | BF9: Total RPS
A10: 1 | B10: =SUMIFS(#REF!,#REF!,$C10,#REF!,"Total",#REF!,"Total Electric Power Industry") -> #REF! | C10: HI | D10: None | E10: Total RPS | F10: 0 | G10: 0 | H10: 0 | I10: 0 | J10: 0 | K10: 0.08 | L10: 0 | M10: 0 | N10: 0 | O10: 0 | P10: 0.1 | Q10: 0.1 | R10: 0.1 | S10: 0.1 | T10: 0.1 | U10: 0.15 | V10: 0.15 | W10: 0.15 | X10: 0.15 | Y10: 0.15 | Z10: 0.3 | AA10: 0.3 | AB10: 0.3 | AC10: 0.3 | AD10: 0.3 | AE10: 0.3 | AF10: 0.3 | AG10: 0.3 | AH10: 0.3 | AI10: 0.3 | AJ10: 0.4 | AK10: 0.4 | AL10: 0.4 | AM10: 0.4 | AN10: 0.4 | AO10: 0.4 | AP10: 0.4 | AQ10: 0.4 | AR10: 0.4 | AS10: 0.4 | AT10: 0.7 | AU10: 0.7 | AV10: 0.7 | AW10: 0.7 | AX10: 0.7 | AY10: 1 | AZ10: 1 | BA10: 1 | BB10: 1 | BC10: 1 | BD10: 1 | BE10: HI | BF10: Total RPS
A11: 1 | B11: =SUMIFS(#REF!,#REF!,$C11,#REF!,"Total",#REF!,"Total Electric Power Industry") -> #REF! | C11: IA | D11: RPS target denominated in MW terms; translated to equivalent percentage of applicable sales | E11: Total RPS | F11: 0.010000416 | G11: 0.0099997035 | H11: 0.0096149299 | I11: 0.0096224775 | J11: 0.009826096 | K11: 0.0092528337 | L11: 0.0090790219 | M11: 0.008729176 | N11: 0.0087380653 | O11: 0.0092105431 | P11: 0.0087343927 | Q11: 0.008676656 | R11: 0.0086437624 | S11: 0.0084989879 | T11: 0.0084023867 | U11: 0.0083727842 | V11: 0.0081420119 | W11: 0.0080470209 | X11: 0.0077077294 | Y11: 0.0076030434 | Z11: 0.0077522263 | AA11: 0.0076788991 | AB11: 0.0076033105 | AC11: 0.0075546275 | AD11: 0.0075056853 | AE11: 0.0074590358 | AF11: 0.0074113337 | AG11: 0.0073804203 | AH11: 0.0073280197 | AI11: 0.0072829183 | AJ11: 0.0072402793 | AK11: 0.0072063461 | AL11: 0.0071687792 | AM11: 0.0071321816 | AN11: 0.0070800692 | AO11: 0.0070353382 | AP11: 0.0069961166 | AQ11: 0.0069448411 | AR11: 0.0068996039 | AS11: 0.006850558 | AT11: 0.0068059574 | AU11: 0.0067586053 | AV11: 0.0067108024 | AW11: 0.0066621081 | AX11: 0.0066101924 | AY11: 0.0065608432 | AZ11: 0.0065109868 | BA11: 0.006458243 | BB11: 0.006408411 | BC11: 0.0063535222 | BD11: 0.0063028468 | BE11: IA | BF11: Total RPS
A12: 1 | B12: =SUMIFS(#REF!,#REF!,$C12,#REF!,"Total",#REF!,"Total Electric Power Industry") -> #REF! | C12: IL | D12: Until recently, Illinois had a different set of solar and DG carve-outs, applicable only to the IOUs fixed-price service load. Those have since been phased out and replaced with the statewide "New Solar" requirement, which has a DG component. | E12: Total RPS | F12: 0 | G12: 0 | H12: 0 | I12: 0 | J12: 0 | K12: 0 | L12: 0 | M12: 0 | N12: 0 | O12: 0.02 | P12: 0.04 | Q12: 0.05 | R12: 0.06 | S12: 0.07 | T12: 0.08 | U12: 0.09 | V12: 0.1 | W12: 0.115 | X12: 0.13 | Y12: 0.145 | Z12: 0.16 | AA12: 0.175 | AB12: 0.19 | AC12: 0.205 | AD12: 0.22 | AE12: 0.235 | AF12: 0.25 | AG12: 0.25 | AH12: 0.25 | AI12: 0.25 | AJ12: 0.25 | AK12: 0.25 | AL12: 0.25 | AM12: 0.25 | AN12: 0.25 | AO12: 0.25 | AP12: 0.25 | AQ12: 0.25 | AR12: 0.25 | AS12: 0.25 | AT12: 0.25 | AU12: 0.25 | AV12: 0.25 | AW12: 0.25 | AX12: 0.25 | AY12: 0.25 | AZ12: 0.25 | BA12: 0.25 | BB12: 0.25 | BC12: 0.25 | BD12: 0.25 | BE12: IL | BF12: Total RPS
A13: 1 | B13: =SUMIFS(#REF!,#REF!,$C13,#REF!,"Total",#REF!,"Total Electric Power Industry") -> #REF! | C13: MA | D13: Class I (Solar) consists of the SREC I, SREC II, and SMART programs; the targets for those programs are denominated in MW and translated here to the equivalent percentage of retail electricity sales. | E13: Total RPS | F13: 0 | G13: 0 | H13: 0 | I13: 0.01 | J13: 0.015 | K13: 0.02 | L13: 0.025 | M13: 0.03 | N13: 0.035 | O13: 0.111 | P13: 0.121 | Q13: 0.131 | R13: 0.141 | S13: 0.13 | T13: 0.143 | U13: 0.155 | V13: 0.170319 | W13: 0.180909 | X13: 0.191155 | Y13: 0.201833 | Z13: 0.227056 | AA13: 0.247056 | AB13: 0.267056 | AC13: 0.287056 | AD13: 0.307056 | AE13: 0.327056 | AF13: 0.347056 | AG13: 0.367056 | AH13: 0.387056 | AI13: 0.407056 | AJ13: 0.417056 | AK13: 0.427056 | AL13: 0.437056 | AM13: 0.447056 | AN13: 0.457056 | AO13: 0.467056 | AP13: 0.477056 | AQ13: 0.487056 | AR13: 0.497056 | AS13: 0.507056 | AT13: 0.517056 | AU13: 0.527056 | AV13: 0.537056 | AW13: 0.547056 | AX13: 0.557056 | AY13: 0.567056 | AZ13: 0.577056 | BA13: 0.587056 | BB13: 0.597056 | BC13: 0.607056 | BD13: 0.617056 | BE13: MA | BF13: Total RPS
A14: 1 | B14: =SUMIFS(#REF!,#REF!,$C14,#REF!,"Total",#REF!,"Total Electric Power Industry") -> #REF! | C14: MD | D14: Offshore wind carve-out target includes both Round 1 and Round 2 solicitations, with MW targets translated to percentage of retail sales | E14: Total RPS | F14: 0 | G14: 0 | H14: 0 | I14: 0 | J14: 0 | K14: 0 | L14: 0.035 | M14: 0.035 | N14: 0.04505 | O14: 0.0451 | P14: 0.05525 | Q14: 0.075 | R14: 0.09 | S14: 0.107 | T14: 0.128 | U14: 0.13 | V14: 0.152 | W14: 0.156 | X14: 0.183 | Y14: 0.232 | Z14: 0.305 | AA14: 0.308 | AB14: 0.331 | AC14: 0.354 | AD14: 0.377 | AE14: 0.4 | AF14: 0.425 | AG14: 0.455 | AH14: 0.475 | AI14: 0.485 | AJ14: 0.5 | AK14: 0.5 | AL14: 0.5 | AM14: 0.5 | AN14: 0.5 | AO14: 0.5 | AP14: 0.5 | AQ14: 0.5 | AR14: 0.5 | AS14: 0.5 | AT14: 0.5 | AU14: 0.5 | AV14: 0.5 | AW14: 0.5 | AX14: 0.5 | AY14: 0.5 | AZ14: 0.5 | BA14: 0.5 | BB14: 0.5 | BC14: 0.5 | BD14: 0.5 | BE14: MD | BF14: Total RPS
A15: 1 | B15: =SUMIFS(#REF!,#REF!,$C15,#REF!,"Total",#REF!,"Total Electric Power Industry") -> #REF! | C15: ME | D15: None | E15: Total RPS | F15: 0.3 | G15: 0.3 | H15: 0.3 | I15: 0.3 | J15: 0.3 | K15: 0.3 | L15: 0.3 | M15: 0.3 | N15: 0.31 | O15: 0.32 | P15: 0.33 | Q15: 0.34 | R15: 0.35 | S15: 0.36 | T15: 0.37 | U15: 0.38 | V15: 0.39 | W15: 0.4 | X15: 0.4 | Y15: 0.4 | Z15: 0.425 | AA15: 0.454 | AB15: 0.488 | AC15: 0.522 | AD15: 0.566 | AE15: 0.61 | AF15: 0.654 | AG15: 0.698 | AH15: 0.742 | AI15: 0.786 | AJ15: 0.84 | AK15: 0.84 | AL15: 0.84 | AM15: 0.84 | AN15: 0.84 | AO15: 0.84 | AP15: 0.84 | AQ15: 0.84 | AR15: 0.84 | AS15: 0.84 | AT15: 0.84 | AU15: 0.84 | AV15: 0.84 | AW15: 0.84 | AX15: 0.84 | AY15: 0.84 | AZ15: 0.84 | BA15: 0.84 | BB15: 0.84 | BC15: 0.84 | BD15: 0.84 | BE15: ME | BF15: Total RPS
... A34: 1 | B34: =SUMIFS(#REF!,#REF!,$C34,#REF!,"Total",#REF!,"Total Electric Power Industry") -> #REF! | C34: WI | D34: None | E34: Total RPS | F34: 0 | G34: 0 | H34: 0 | I34: 0 | J34: 0 | K34: 0 | L34: 0.04 | M34: 0.04 | N34: 0.04 | O34: 0.04 | P34: 0.06 | Q34: 0.06 | R34: 0.06 | S34: 0.06 | T34: 0.06 | U34: 0.1 | V34: 0.1 | W34: 0.1 | X34: 0.1 | Y34: 0.1 | Z34: 0.1 | AA34: 0.1 | AB34: 0.1 | AC34: 0.1 | AD34: 0.1 | AE34: 0.1 | AF34: 0.1 | AG34: 0.1 | AH34: 0.1 | AI34: 0.1 | AJ34: 0.1 | AK34: 0.1 | AL34: 0.1 | AM34: 0.1 | AN34: 0.1 | AO34: 0.1 | AP34: 0.1 | AQ34: 0.1 | AR34: 0.1 | AS34: 0.1 | AT34: 0.1 | AU34: 0.1 | AV34: 0.1 | AW34: 0.1 | AX34: 0.1 | AY34: 0.1 | AZ34: 0.1 | BA34: 0.1 | BB34: 0.1 | BC34: 0.1 | BD34: 0.1 | BE34: WI | BF34: Total RPS
A36: Calculated RPS value
C37: RPS Targets (Percent of Applicable Retail Electricity Sales)
A38: RPS TOTAL 1=true | B38: GENERATION | C38: State | D38: Special Notes | E38: RPS Tier or Carve Out | F38: 2000 | G38: 2001 | H38: 2002 | I38: 2003 | J38: 2004 | K38: 2005 | L38: 2006 | M38: 2007 | N38: 2008 | O38: 2009 | P38: 2010 | Q38: 2011 | R38: 2012 | S38: 2013 | T38: 2014 | U38: 2015 | V38: 2016 | W38: 2017 | X38: 2018 | Y38: 2019 | Z38: 2020 | AA38: 2021 | AB38: 2022 | AC38: 2023 | AD38: 2024 | AE38: 2025 | AF38: 2026 | AG38: 2027 | AH38: 2028 | AI38: 2029 | AJ38: 2030 | AK38: 2031 | AL38: 2032 | AM38: 2033 | AN38: 2034 | AO38: 2035 | AP38: 2036 | AQ38: 2037 | AR38: 2038 | AS38: 2039 | AT38: 2040 | AU38: 2041 | AV38: 2042 | AW38: 2043 | AX38: 2044 | AY38: 2045 | AZ38: 2046 | BA38: 2047 | BB38: 2048 | BC38: 2049 | BD38: 2050
A39: 1 | B39: =B4 -> #REF! | C39: AZ | D39: Arizona had a solar carve-out, which was subsequently replaced by the current DG carve-out in 2008. | E39: Total RPS | F39: =F4*$B4 -> #REF! | G39: =G4*$B4 -> #REF! | H39: =H4*$B4 -> #REF! | I39: =I4*$B4 -> #REF! | J39: =J4*$B4 -> #REF! | K39: =K4*$B4 -> #REF! | L39: =L4*$B4 -> #REF! | M39: =M4*$B4 -> #REF! | ... BD39: =BD4*$B4 -> #REF!
A40: 1 | B40: =B5 -> #REF! | C40: CA | D40: Through 2015, the values shown here represent targets for the state's three large IOUs through 2015 (targets for other utilities' were lower). From 2016 onward, the values shown here represent statewide targets applicable to all utilities. | E40: Total RPS | F40: =F5*$B5 -> #REF! | G40: =G5*$B5 -> #REF! | H40: =H5*$B5 -> #REF! | I40: =I5*$B5 -> #REF! | J40: =J5*$B5 -> #REF! | K40: =K5*$B5 -> #REF! | L40: =L5*$B5 -> #REF! | M40: =M5*$B5 -> #REF! | ... BD40: =BD5*$B5 -> #REF!
A41: 1 | B41: =B6 -> #REF! | C41: CO | D41: Targets vary based on utility type and size, and whether the utility is served by a generation and transmission (G&T) cooperative. Weighted averages are based on the retail electricity sales of utilities subject to the RPS. | E41: Total RPS (Wtd. Avg.) | F41: =F6*$B6 -> #REF! | G41: =G6*$B6 -> #REF! | H41: =H6*$B6 -> #REF! | I41: =I6*$B6 -> #REF! | J41: =J6*$B6 -> #REF! | K41: =K6*$B6 -> #REF! | L41: =L6*$B6 -> #REF! | M41: =M6*$B6 -> #REF! | ... BD41: =BD6*$B6 -> #REF!
A42: 1 | B42: =B7 -> #REF! | C42: CT | D42: None | E42: Total RPS | F42: =F7*$B7 -> #REF! | G42: =G7*$B7 -> #REF! | H42: =H7*$B7 -> #REF! | I42: =I7*$B7 -> #REF! | J42: =J7*$B7 -> #REF! | K42: =K7*$B7 -> #REF! | L42: =L7*$B7 -> #REF! | M42: =M7*$B7 -> #REF! | ... BD42: =BD7*$B7 -> #REF!
A43: 1 | B43: =B8 -> #REF! | C43: DC | D43: None | E43: Total RPS | F43: =F8*$B8 -> #REF! | G43: =G8*$B8 -> #REF! | H43: =H8*$B8 -> #REF! | I43: =I8*$B8 -> #REF! | J43: =J8*$B8 -> #REF! | K43: =K8*$B8 -> #REF! | L43: =L8*$B8 -> #REF! | M43: =M8*$B8 -> #REF! | ... BD43: =BD8*$B8 -> #REF!
A44: 1 | B44: =B9 -> #REF! | C44: DE | D44: None | E44: Total RPS | F44: =F9*$B9 -> #REF! | G44: =G9*$B9 -> #REF! | H44: =H9*$B9 -> #REF! | I44: =I9*$B9 -> #REF! | J44: =J9*$B9 -> #REF! | K44: =K9*$B9 -> #REF! | L44: =L9*$B9 -> #REF! | M44: =M9*$B9 -> #REF! | ... BD44: =BD9*$B9 -> #REF!
A45: 1 | B45: =B10 -> #REF! | C45: HI | D45: None | E45: Total RPS | F45: =F10*$B10 -> #REF! | G45: =G10*$B10 -> #REF! | H45: =H10*$B10 -> #REF! | I45: =I10*$B10 -> #REF! | J45: =J10*$B10 -> #REF! | K45: =K10*$B10 -> #REF! | L45: =L10*$B10 -> #REF! | M45: =M10*$B10 -> #REF! | ... BD45: =BD10*$B10 -> #REF!
A46: 1 | B46: =B11 -> #REF! | C46: IA | D46: RPS target denominated in MW terms; translated to equivalent percentage of applicable sales | E46: Total RPS | F46: =F11*$B11 -> #REF! | G46: =G11*$B11 -> #REF! | H46: =H11*$B11 -> #REF! | I46: =I11*$B11 -> #REF! | J46: =J11*$B11 -> #REF! | K46: =K11*$B11 -> #REF! | L46: =L11*$B11 -> #REF! | M46: =M11*$B11 -> #REF! | ... BD46: =BD11*$B11 -> #REF!
A47: 1 | B47: =B12 -> #REF! | C47: IL | D47: Until recently, Illinois had a different set of solar and DG carve-outs, applicable only to the IOUs fixed-price service load. Those have since been phased out and replaced with the statewide "New Solar" requirement, which has a DG component. | E47: Total RPS | F47: =F12*$B12 -> #REF! | G47: =G12*$B12 -> #REF! | H47: =H12*$B12 -> #REF! | I47: =I12*$B12 -> #REF! | J47: =J12*$B12 -> #REF! | K47: =K12*$B12 -> #REF! | L47: =L12*$B12 -> #REF! | M47: =M12*$B12 -> #REF! | ... BD47: =BD12*$B12 -> #REF!
A48: 1 | B48: =B13 -> #REF! | C48: MA | D48: Class I (Solar) consists of the SREC I, SREC II, and SMART programs; the targets for those programs are denominated in MW and translated here to the equivalent percentage of retail electricity sales. | E48: Total RPS | F48: =F13*$B13 -> #REF! | G48: =G13*$B13 -> #REF! | H48: =H13*$B13 -> #REF! | I48: =I13*$B13 -> #REF! | J48: =J13*$B13 -> #REF! | K48: =K13*$B13 -> #REF! | L48: =L13*$B13 -> #REF! | M48: =M13*$B13 -> #REF! | ... BD48: =BD13*$B13 -> #REF!
A49: 1 | B49: =B14 -> #REF! | C49: MD | D49: Offshore wind carve-out target includes both Round 1 and Round 2 solicitations, with MW targets translated to percentage of retail sales | E49: Total RPS | F49: =F14*$B14 -> #REF! | G49: =G14*$B14 -> #REF! | H49: =H14*$B14 -> #REF! | I49: =I14*$B14 -> #REF! | J49: =J14*$B14 -> #REF! | K49: =K14*$B14 -> #REF! | L49: =L14*$B14 -> #REF! | M49: =M14*$B14 -> #REF! | ... BD49: =BD14*$B14 -> #REF!
A50: 1 | B50: =B15 -> #REF! | C50: ME | D50: None | E50: Total RPS | F50: =F15*$B15 -> #REF! | G50: =G15*$B15 -> #REF! | H50: =H15*$B15 -> #REF! | I50: =I15*$B15 -> #REF! | J50: =J15*$B15 -> #REF! | K50: =K15*$B15 -> #REF! | L50: =L15*$B15 -> #REF! | M50: =M15*$B15 -> #REF! | ... BD50: =BD15*$B15 -> #REF!
... A69: 1 | B69: =B34 -> #REF! | C69: WI | D69: None | E69: Total RPS | F69: =F34*$B34 -> #REF! | G69: =G34*$B34 -> #REF! | H69: =H34*$B34 -> #REF! | I69: =I34*$B34 -> #REF! | J69: =J34*$B34 -> #REF! | K69: =K34*$B34 -> #REF! | L69: =L34*$B34 -> #REF! | M69: =M34*$B34 -> #REF! | ... BD69: =BD34*$B34 -> #REF!
F70: =SUM(F39:F69) -> #REF! | G70: =SUM(G39:G69) -> #REF! | H70: =SUM(H39:H69) -> #REF! | I70: =SUM(I39:I69) -> #REF! | J70: =SUM(J39:J69) -> #REF! | K70: =SUM(K39:K69) -> #REF! | L70: =SUM(L39:L69) -> #REF! | M70: =SUM(M39:M69) -> #REF! | ... BD70: =SUM(BD39:BD69) -> #REF!
F71: =#REF! -> #REF! | G71: =#REF! -> #REF! | H71: =#REF! -> #REF! | I71: =#REF! -> #REF! | J71: =#REF! -> #REF! | K71: =#REF! -> #REF! | L71: =#REF! -> #REF! | M71: =#REF! -> #REF! | ... BD71: =#REF! -> #REF!
D73: Calculated RPS value | F73: =F70/F71 -> #REF! | G73: =G70/G71 -> #REF! | H73: =H70/H71 -> #REF! | I73: =I70/I71 -> #REF! | J73: =J70/J71 -> #REF! | K73: =K70/K71 -> #REF! | L73: =L70/L71 -> #REF! | M73: =M70/M71 -> #REF! | ... BD73: =BD70/BD71 -> #REF!
