Workbook
Name dollars_2019_2012: [1]About!$A$99
Name dollars_2019_2012: About!$A$254
Name gal_per_barrel: [2]About!$A$40
Name lignite_multiplier: #REF!
Name lignite_multiplier: #REF!
Name lignite_multiplier: #REF!
Name lignite_multiplier: #REF!
Name lignite_multiplier: #REF!
Name lignite_multiplier: #REF!
Name lignite_multiplier: #REF!
Name lignite_multiplier: #REF!
Name lignite_multiplier: #REF!
Name lignite_multiplier: '[1]Hard Coal and Lig Multipliers'!$N$15
Name lignite_multiplier: #REF!
Name lignite_multiplier: #REF!
Name lignite_multiplier: #REF!
Name lignite_multiplier: #REF!
Name lignite_multiplier: #REF!
Name lignite_multiplier: #REF!
Name lignite_multiplier: #REF!
Name lignite_multiplier: #REF!
Name lignite_multiplier: #REF!
Name lignite_multiplier: #REF!
Name nonlignite_multiplier: #REF!
Name nonlignite_multiplier: #REF!
Name nonlignite_multiplier: #REF!
Name nonlignite_multiplier: #REF!
Name nonlignite_multiplier: #REF!
Name nonlignite_multiplier: #REF!
Name nonlignite_multiplier: #REF!
Name nonlignite_multiplier: #REF!
Name nonlignite_multiplier: #REF!
Name nonlignite_multiplier: '[1]Hard Coal and Lig Multipliers'!$N$16
Name nonlignite_multiplier: #REF!
Name nonlignite_multiplier: #REF!
Name nonlignite_multiplier: #REF!
Name nonlignite_multiplier: #REF!
Name nonlignite_multiplier: #REF!
Name nonlignite_multiplier: #REF!
Name nonlignite_multiplier: #REF!
Name nonlignite_multiplier: #REF!
Name nonlignite_multiplier: #REF!
Name nonlignite_multiplier: #REF!
Name tax_fuel_labels: 'Tax_Share of Price'!$A$2:$A$22
Name Tax_share: 'Tax_Share of Price'!$B$2:$AI$22

Sheet About
A1: BFPaT BAU Pretax Fuel Price by Sector
A2: BFPaT BAU Fuel Tax by Sector
A4: Sources: | B4: Prices
B6: Electricity Price | D6: hydrogen start year costs
B7: Central Electricity Authority | D7: California Energy Commission and California Air Resources Board
B8: 2022 | D8: 2015
B9: Electricity Tariff & Duty & Average Rates of Electricity Supply in India | D9: Assessment of Time and Cost Needed to Attain 100 Hydrogen Refueling Stations in California
B10: Cover 3rd book 2023 FINAL.cdr (cea.nic.in) | D10: https://ww2.energy.ca.gov/2015publications/CEC-600-2015-016/CEC-600-2015-016.pdf
D11: Page 57, Table 12
B13: 2014 Coal Price | D13: hydrogen future costs
B14: Planning Commission, Government of India | D14: Bloomberg New Energy Finance
B15: 2014 | D15: 2020
B16: Annual Report (2013-14) on the Working of State Power Utilities & Electricity Departments | D16: Hydrogen Economy Outlook: Key Messages
B17: http://planningcommission.nic.in/reports/genrep/rep_arpower0306.pdf | D17: https://data.bloomberglp.com/professional/sites/24/BNEF-Hydrogen-Economy-Outlook-Key-Messages-30-Mar-2020.pdf
B18: Annex 4.8 and 4.10 | D18: Page 5
B20: Coal and Lignite Price Scaling Factors to Start Year | D20: Industry-wise consumption of Coal & Lignite in India
B21: Ministry of Coal, Government of India | D21: Ministry of Statistics and Programme Implementation
B22: 2019 | D22: 2019
B23: Coal Statistics | D23: Energy Statistics
B24: http://www.coalcontroller.gov.in/writereaddata/files/download/coaldirectory/CoalDirectory2019-20.pdf | D24: http://www.mospi.gov.in/sites/default/files/publication_reports/Energy%20Statistics%202019-finall.pdf
B25: Section VI, Page 6.1 (Statement 6.1) & Page 6.2 (Table 6.1) | D25: Tables 6.4, 6.5; pp 62-63
B27: Kerosene, LPG, Kerosene, Prices | D27: NE states population for weighting Nat Gas price
B28: Ministry of Petroleum and Natural Gas | D28: Census of India - Demographics
B29: 2021 | D29: 2011
B30: Indian Petroleum and Natural Gas Statistics, 2021-22 | D30: Indiastat Database
D31: https://www.indiastat.com/
B32: Nat Gas - Table IV.1 (Page 71), LPG&Kerosene - Table IV.11 (Page 78), | D32: Table: State-wise Total Population by Residence and Sex in India
B34: Start Year Natural Gas Prices and Imported Coal Price
B35: IEA
B36: 2021
B37: India Energy Outlook 2021
B38: https://iea.blob.core.windows.net/assets/1de6d91e-e23f-4e02-b1fb-51fdd6283b22/India_Energy_Outlook_2021.pdf
B39: page 139 and Figure 3.15
B41: Standing Committee on Energy
B42: Stressed/Non-Performing Assets in Gas based Power Plants
B43: 2019
B44: http://164.100.47.193/lsscommittee/Energy/16_Energy_42.pdf
B45: Table 3.11
B47: Jet Fuel Prices | D47: Communication on Kerosene price increase
B48: IndianOil | D48: Public Information Bureau
B49: 2018 | D49: 42675
B50: Previous Price of ATF (Domestic) | D50: Subsidy on Kerosene
B51: https://www.iocl.com/Product_PreviousPrice/ATFDomesticPreviousPrice.aspx | D51: https://pib.gov.in/newsite/mbErel.aspx?relid=154127
B53: Nuclear Fuel Price | D53: Economic Times
B54: Energy Information Administraton | D54: 42948
B55: 2017 | D55: After diesel and LPG, govt. to now end subsidy on kerosene
B56: State Energy Data System (SEDS): 1970-2017 (complete) | D56: https://economictimes.indiatimes.com/industry/energy/oil-gas/after-diesel-and-lpg-government-to-now-end-subsidy-on-kerosene/articleshow/59888617.cms
B57: http://www.eia.gov/state/seds/sep_prices/total/pdf/pr_US.pdf
B58: Table ET1, Row "2012", Column "Nuclear Fuel"
B60: Biomass Prices
B61: CENTRAL ELECTRICITY REGULATORY COMMISSION
B62: 2019
B63: CERC RE Tariff Order 2018-19
B64: http://www.cercind.gov.in/2018/orders/02.pdf
B65: Page 22
B67: Petroleum Gasoline and Diesel Prices | D67: Ethanol Procurement Prices
B68: Ministry of Petroleum and Natural Gas | D68: Ministry of Petroleum and Natural Gas
B69: December 2021 | D69: 2019
B70: Snapshot of India's Oil & Gas Data | D70: Biofuels
B71: https://ppac.gov.in/uploads/rep_studies/1670472940_202202040453534545669SnapshotofIndiaOilandGasdataDecember2021webupload.pdf | D71: http://petroleum.nic.in/sites/default/files/biofuels.pdf
B72: Table 23, Page 18 | D72: Page 3
B74: Crude Oil Prices
B75: Ministry of Petroleum and Natural Gas
B76: December 2021
B77: Snapshot of India's Oil & Gas Data
B78: https://ppac.gov.in/uploads/rep_studies/1670472940_202202040453534545669SnapshotofIndiaOilandGasdataDecember2021webupload.pdf
B79: Table 25, Page 33
B81: Heavy Fuel Oil Price
B82: Energy Information Administraton
B83: 2017
B84: State Energy Data System (SEDS): 1970-2017 (complete)
B85: http://www.eia.gov/state/seds/sep_prices/total/pdf/pr_US.pdf
B86: Table ET1, Row "2012", Column "Residual Fuel Oil"
B88: Municipal Solid Waste Price (Tipping fee) | D88: Waste to Energy Scheme
B89: Delhi High Court Committee (Gauri Grover vs. Govt. of NCT) | D89: Ministry of New and Renewable Energy
B90: 2015 | D90: 2018
B91: Recommendations for Long Term Action Plan for Solid Waste Management in Delhi | D91: PROGRAMME GUIDELINES onENERGY FROM URBAN, INDUSTRIAL AND AGRICULTURAL WASTES/RESIDUESfor PLAN PERIOD (2017-18,2018-19 & 2019-20)
B92: http://www.indiaenvironmentportal.org.in/files/file/solid%20waste%20management%20in%20Delhi.pdf | D92: https://mnre.gov.in/sites/default/files/schemes/programme_energy-urban-industrial-agriculture-wastes-2017-2020_0.pdf
B93: Table 5, Page 19 | D93: Table 5, Page 19
B95: Energy Contents
B97: Biomass & MSW Energy Content
B98: Indian Institute for Science, Centre for Ecological Sciences
B99: undated
B100: http://www.ces.iisc.ernet.in/energy/paper/alternative/calorific.html
B102: Gasoline, LPG, Natural Gas Energy Content
B103: TERI
B104: 2016
B105: TERI Energy and Environment Data Diary and Yearbook 2015/16
B106: http://bookstore.teri.res.in/books/9788179935835
B107: Page 15
B109: Diesel, Jet Fuel, Crude Oil Energy Content
B110: Energy Information Administration
B111: 2016
B112: Annual Energy Outlook 2016
B113: http://www.eia.gov/forecasts/aeo/supplement/excel/suptab_73.xlsx
B114: Table 73
B116: Future Year Price Scaling Factors
B118: Future Year Price Scaling Factors
B119: U.S. Energy Information Administration
B120: 2020, 2021
...

Sheet Tax Data>

Sheet Petroleum & Diesel Prices
A1: 23. Information on Prices, Taxes and Under-recoveries/Subsidies
A2: Price buildup of petroleum products (Rs./litre/Cylinder)
A3: Particulars | B3: Petrol | C3: Diesel
A4: Price charged to dealers (excluding Excise Duty and VAT) | B4: 48.23 | C4: 49.61
A5: Excise Duty | B5: 27.9 | C5: 21.8 | D5: |
A6: Dealer Commission (Average) | B6: 3.78 | C6: 2.55 | D6: |<-- Tax component
A7: VAT (incl VAT on dealer commission) | B7: 15.5 | C7: 12.68 | D7: |
A8: Retail selling price (RSP) -RoundedFO | B8: 95.41 | C8: 86.67
A9: Tax percentage | B9: =SUM(B5:B7)/B8 -> 0.49449743 | C9: =SUM(C5:C7)/C8 -> 0.4272528
A11: Source: Snapshot of India's Oil & Gas Data, Dec 2021 (PPAC)
A12: Table 23, Page 18
A14: Note: We include Excise Duty and Dealer commission as it is passed on to the consumer in the final retail price

Sheet Tax Rates
A1: VII.3 Sales tax rates applicable on crude oil, natural gas and petroleum products (Contd...) | I1: (Excerpt for Crude Oil, Natural Gas and ATF (Bonded))
A2: (As on 01.04.2022)
A3: (in Percentage)
A4: State/U.T | B4: Crude Oil | C4: Natural Gas | D4: MS (Petrol) | E4: Branded Petrol | F4: HSD (Diesel) | G4: Branded Diesel | H4: Naphtha | I4: LPG(Domestic) | J4: LPG (Non Dom) | K4: AUTO LPG | L4: SKO (PDS) | M4: SKO(IND) | N4: FO | O4: LSHS | P4: ATF (Duty Paid/ Bonded) | Q4: ATF Declared | R4: ATF (When Sold to Aircraft having maximum take off mass of < 40000 Kgs, operated by scheduled airlines) i.e. declared goods under CST Act | S4: BITUMEN | T4: LDO | U4: LUBE | V4: SULPHUR | W4: ASPHALT | Y4: ATF Consumption | Z4: NG Consumption
A5: -1 | B5: -2 | C5: -3 | D5: -4 | E5: -5 | F5: -6 | G5: -7 | H5: -8 | I5: -9 | J5: -10 | K5: -11 | L5: -12 | M5: -13 | N5: -14 | O5: -15 | P5: -16 | Q5: -17 | R5: -18 | S5: -19 | T5: -20 | U5: -21 | V5: -22 | W5: -23
A6: Andhra Pradesh | B6: 0.05 | C6: 0.245 | P6: 0.01 | X6: =A6 -> Andhra Pradesh | Y6: =IFERROR(INDEX('Petroleum Products Consumption'!$F$5:$F$40,MATCH('Tax Rates'!A6,'Petroleum Products Consumption'!$A$5:$A$40,0),1),0) -> 58.1 | Z6: =SUMIFS('NG Sales'!$H$6:$H$74,'NG Sales'!$I$6:$I$74,'Tax Rates'!A6,'NG Sales'!$A$6:$A$74,"Net Production (sales)") -> 743.76
A7: Arunachal Pradesh | B7: 0.04 | C7: 0.2 | P7: 0.2 | X7: =A7 -> Arunachal Pradesh | Y7: =IFERROR(INDEX('Petroleum Products Consumption'!$F$5:$F$40,MATCH('Tax Rates'!A7,'Petroleum Products Consumption'!$A$5:$A$40,0),1),0) -> 1.5 | Z7: =SUMIFS('NG Sales'!$H$6:$H$74,'NG Sales'!$I$6:$I$74,'Tax Rates'!A7,'NG Sales'!$A$6:$A$74,"Net Production (sales)") -> 0
A8: Assam | B8: 0.05 | C8: 0.145 | P8: 0.2365 | X8: =A8 -> Assam | Y8: =IFERROR(INDEX('Petroleum Products Consumption'!$F$5:$F$40,MATCH('Tax Rates'!A8,'Petroleum Products Consumption'!$A$5:$A$40,0),1),0) -> 122.6 | Z8: =SUMIFS('NG Sales'!$H$6:$H$74,'NG Sales'!$I$6:$I$74,'Tax Rates'!A8,'NG Sales'!$A$6:$A$74,"Net Production (sales)") -> 2486.43
A9: Bihar | B9: 0.06 | C9: 0.2 | P9: 0.29 | X9: =A9 -> Bihar | Y9: =IFERROR(INDEX('Petroleum Products Consumption'!$F$5:$F$40,MATCH('Tax Rates'!A9,'Petroleum Products Consumption'!$A$5:$A$40,0),1),0) -> 26.6 | Z9: =SUMIFS('NG Sales'!$H$6:$H$74,'NG Sales'!$I$6:$I$74,'Tax Rates'!A9,'NG Sales'!$A$6:$A$74,"Net Production (sales)") -> 0
A10: Chandigarh | B10: 0.125 | C10: 0.05 | P10: 0.2 | X10: =A10 -> Chandigarh | Y10: =IFERROR(INDEX('Petroleum Products Consumption'!$F$5:$F$40,MATCH('Tax Rates'!A10,'Petroleum Products Consumption'!$A$5:$A$40,0),1),0) -> 26.6 | Z10: =SUMIFS('NG Sales'!$H$6:$H$74,'NG Sales'!$I$6:$I$74,'Tax Rates'!A10,'NG Sales'!$A$6:$A$74,"Net Production (sales)") -> 0
A11: Chhattisgarh | B11: 0.05 | C11: 0.25 | P11: 0.04 | X11: =A11 -> Chhattisgarh | Y11: =IFERROR(INDEX('Petroleum Products Consumption'!$F$5:$F$40,MATCH('Tax Rates'!A11,'Petroleum Products Consumption'!$A$5:$A$40,0),1),0) -> 28.5 | Z11: =SUMIFS('NG Sales'!$H$6:$H$74,'NG Sales'!$I$6:$I$74,'Tax Rates'!A11,'NG Sales'!$A$6:$A$74,"Net Production (sales)") -> 0
A12: Delhi | B12: 0.05 | C12: 0 | P12: 0.25 | X12: =A12 -> Delhi | Y12: =IFERROR(INDEX('Petroleum Products Consumption'!$F$5:$F$40,MATCH('Tax Rates'!A12,'Petroleum Products Consumption'!$A$5:$A$40,0),1),0) -> 1314.4 | Z12: =SUMIFS('NG Sales'!$H$6:$H$74,'NG Sales'!$I$6:$I$74,'Tax Rates'!A12,'NG Sales'!$A$6:$A$74,"Net Production (sales)") -> 0
A13: Goa | B13: 0.2 | C13: 0.3 | P13: 0.18 | X13: =A13 -> Goa | Y13: =IFERROR(INDEX('Petroleum Products Consumption'!$F$5:$F$40,MATCH('Tax Rates'!A13,'Petroleum Products Consumption'!$A$5:$A$40,0),1),0) -> 87.7 | Z13: =SUMIFS('NG Sales'!$H$6:$H$74,'NG Sales'!$I$6:$I$74,'Tax Rates'!A13,'NG Sales'!$A$6:$A$74,"Net Production (sales)") -> 0
A14: Gujarat | B14: 0.05 | C14: 0.15 | P14: 0.38 | X14: =A14 -> Gujarat | Y14: =IFERROR(INDEX('Petroleum Products Consumption'!$F$5:$F$40,MATCH('Tax Rates'!A14,'Petroleum Products Consumption'!$A$5:$A$40,0),1),0) -> 172 | Z14: =SUMIFS('NG Sales'!$H$6:$H$74,'NG Sales'!$I$6:$I$74,'Tax Rates'!A14,'NG Sales'!$A$6:$A$74,"Net Production (sales)") -> 635.05
A15: Haryana | B15: 0.125 | C15: 0.125 | P15: 0.2 | X15: =A15 -> Haryana | Y15: =IFERROR(INDEX('Petroleum Products Consumption'!$F$5:$F$40,MATCH('Tax Rates'!A15,'Petroleum Products Consumption'!$A$5:$A$40,0),1),0) -> 27.8 | Z15: =SUMIFS('NG Sales'!$H$6:$H$74,'NG Sales'!$I$6:$I$74,'Tax Rates'!A15,'NG Sales'!$A$6:$A$74,"Net Production (sales)") -> 0
A16: Himachal Pradesh | B16: 0.1375 | C16: 0.04 | P16: 0.26 | X16: =A16 -> Himachal Pradesh | Y16: =IFERROR(INDEX('Petroleum Products Consumption'!$F$5:$F$40,MATCH('Tax Rates'!A16,'Petroleum Products Consumption'!$A$5:$A$40,0),1),0) -> 4.4 | Z16: =SUMIFS('NG Sales'!$H$6:$H$74,'NG Sales'!$I$6:$I$74,'Tax Rates'!A16,'NG Sales'!$A$6:$A$74,"Net Production (sales)") -> 0
A17: J & K | B17: 0.145 | C17: 0.21 | P17: 0.01 | X17: =A17 -> J & K | Y17: =IFERROR(INDEX('Petroleum Products Consumption'!$F$5:$F$40,MATCH('Tax Rates'!A17,'Petroleum Products Consumption'!$A$5:$A$40,0),1),0) -> 0 | Z17: =SUMIFS('NG Sales'!$H$6:$H$74,'NG Sales'!$I$6:$I$74,'Tax Rates'!A17,'NG Sales'!$A$6:$A$74,"Net Production (sales)") -> 0
... A40: Ladakh | B40: 0.145 | C40: 0.21 | P40: 0.01 | X40: =A40 -> Ladakh | Y40: =IFERROR(INDEX('Petroleum Products Consumption'!$F$5:$F$40,MATCH('Tax Rates'!A40,'Petroleum Products Consumption'!$A$5:$A$40,0),1),0) -> 0 | Z40: =SUMIFS('NG Sales'!$H$6:$H$74,'NG Sales'!$I$6:$I$74,'Tax Rates'!A40,'NG Sales'!$A$6:$A$74,"Net Production (sales)") -> 0
A42: Source: Indian Petroleum and Natural Gas Statistics, 2021-22 (MoPNG)
A43: Table IV.14, Page 112

Sheet Electricity Tax Rates
A1: Tax
A2: State | B2: Domestic | C2: Commercial | D2: Agriculture | E2: LT Industry | F2: HT industry | G2: Railway
A3: Andhra Pradesh | B3: 6 | C3: 6 | D3: 6 | E3: 6 | F3: 6
A4: Assam | B4: 0.05 | C4: 0.05 | D4: 0.05 | E4: 0.05 | F4: 0.05 | G4: 0.05
A5: Bihar | B5: 0.06 | C5: 0.06 | D5: 6 | E5: 0.06 | F5: 0.06
A6: Chandigarh | B6: 9 | C6: 11 | D6: 0 | E6: 11 | F6: 11
A7: Delhi | B7: 0.05 | C7: 0.05 | D7: 0.05 | E7: 0.05 | F7: 0.05 | G7: 0.05
A8: Goa | B8: 20 | C8: 70 | D8: 20 | E8: 70 | F8: 70
A9: Gujarat | B9: 0.1125 | C9: 0.2 | D9: 0 | E9: 0.1 | F9: 0.15
A10: Haryana | B10: 10 | C10: 10 | D10: 0 | E10: 10 | F10: 10 | G10: 10
A11: Himachal Pradesh | B11: 0.03 | C11: 0.08 | D11: 0.1 | E11: 0.07 | F11: 0.11 | G11: 0.1
A12: Jammu and Kashmir | B12: 0.15 | C12: 0.15 | D12: 0.15 | E12: 0.15 | F12: 0.15 | G12: 0.15
A13: Jharkhand | B13: 22 | C13: 27 | D13: 2 | E13: 5 | F13: 5 | G13: 15
A14: Karnataka | B14: 0.09 | C14: 0.09 | D14: 0.09 | E14: 0.09 | F14: 0.09 | G14: 0.09
A15: Kerala | B15: 0.1 | C15: 0.1 | D15: 0.1 | E15: 0.1 | F15: 10
A16: Madhya Pradesh | B16: 0.105 | C16: 0.12 | E16: 0.09 | F16: 0.15
A17: Maharashtra | B17: 0.16 | C17: 0.21 | E17: 0.075 | F17: 0.075
A18: Manipur
A19: Meghalaya | B19: 5 | C19: 6 | D19: 6 | E19: 4.1666667 | F19: 4.1666667
A20: Orissa | B20: 0.04 | C20: 0.04 | D20: 0.02 | E20: 0.05 | F20: 0.08
A21: Punjab | B21: 0.13 | C21: 0.13 | E21: 0.13 | F21: 0.13
A22: Rajasthan | B22: 40 | C22: 40 | D22: 4 | E22: 40 | F22: 40 | G22: 40
A23: Tamil Nadu | C23: 0.05 | E23: 0.05 | F23: 0.05 | G23: 0.05
A24: Uttarakhand | B24: 22.5 | C24: 35 | E24: 40 | F24: 60
A25: Uttar Pradesh | B25: 0.05 | C25: 0.075 | E25: 0.075 | F25: 0.075
A26: West Bengal | B26: 0.1 | C26: 0.125 | E26: 0.075 | F26: 0.15
A27: Source: CEA | B27: Cover 3rd book 2023 FINAL.cdr (cea.nic.in)
A28: Equivalent Tax Rate
A29: State | B29: Domestic | C29: Commercial | D29: Agriculture | E29: LT Industry | F29: HT industry | G29: Railway
A30: Andhra Pradesh | B30: =IF(B3<1,B3,B3/INDEX('Electricity Tariffs and Consump'!$C$4:$G$35,MATCH('Electricity Tax Rates'!$A3,'Electricity Tariffs and Consump'!$B$4:$B$35,0),MATCH('Electricity Tax Rates'!B$2,'Electricity Tariffs and Consump'!$C$3:$G$3,0))) -> 0.010273973 | C30: =IF(C3<1,C3,C3/INDEX('Electricity Tariffs and Consump'!$C$4:$G$35,MATCH('Electricity Tax Rates'!$A3,'Electricity Tariffs and Consump'!$B$4:$B$35,0),MATCH('Electricity Tax Rates'!C$2,'Electricity Tariffs and Consump'!$C$3:$G$3,0))) -> 0.005907173 | D30: =IF(D3<1,D3,D3/INDEX('Electricity Tariffs and Consump'!$C$4:$G$35,MATCH('Electricity Tax Rates'!$A3,'Electricity Tariffs and Consump'!$B$4:$B$35,0),MATCH('Electricity Tax Rates'!D$2,'Electricity Tariffs and Consump'!$C$3:$G$3,0))) -> 0.026666667 | E30: =IF(E3<1,E3,E3/INDEX('Electricity Tariffs and Consump'!$C$4:$G$35,MATCH('Electricity Tax Rates'!$A3,'Electricity Tariffs and Consump'!$B$4:$B$35,0),MATCH("Industry",'Electricity Tariffs and Consump'!$C$3:$G$3,0))) -> 0.00795053 | F30: =IF(F3<1,F3,F3/INDEX('Electricity Tariffs and Consump'!$C$4:$G$35,MATCH('Electricity Tax Rates'!$A3,'Electricity Tariffs and Consump'!$B$4:$B$35,0),MATCH("Industry",'Electricity Tariffs and Consump'!$C$3:$G$3,0))) -> 0.00795053 | G30: =IF(G3<1,G3,G3/INDEX('Electricity Tariffs and Consump'!$C$4:$G$35,MATCH('Electricity Tax Rates'!$A3,'Electricity Tariffs and Consump'!$B$4:$B$35,0),MATCH("Railway",'Electricity Tariffs and Consump'!$C$3:$G$3,0))) -> 0
A31: Assam | B31: =IF(B4<1,B4,B4/INDEX('Electricity Tariffs and Consump'!$C$4:$G$35,MATCH('Electricity Tax Rates'!$A4,'Electricity Tariffs and Consump'!$B$4:$B$35,0),MATCH('Electricity Tax Rates'!B$2,'Electricity Tariffs and Consump'!$C$3:$G$3,0))) -> 0.05 | C31: =IF(C4<1,C4,C4/INDEX('Electricity Tariffs and Consump'!$C$4:$G$35,MATCH('Electricity Tax Rates'!$A4,'Electricity Tariffs and Consump'!$B$4:$B$35,0),MATCH('Electricity Tax Rates'!C$2,'Electricity Tariffs and Consump'!$C$3:$G$3,0))) -> 0.05 | D31: =IF(D4<1,D4,D4/INDEX('Electricity Tariffs and Consump'!$C$4:$G$35,MATCH('Electricity Tax Rates'!$A4,'Electricity Tariffs and Consump'!$B$4:$B$35,0),MATCH('Electricity Tax Rates'!D$2,'Electricity Tariffs and Consump'!$C$3:$G$3,0))) -> 0.05 | E31: =IF(E4<1,E4,E4/INDEX('Electricity Tariffs and Consump'!$C$4:$G$35,MATCH('Electricity Tax Rates'!$A4,'Electricity Tariffs and Consump'!$B$4:$B$35,0),MATCH("Industry",'Electricity Tariffs and Consump'!$C$3:$G$3,0))) -> 0.05 | F31: =IF(F4<1,F4,F4/INDEX('Electricity Tariffs and Consump'!$C$4:$G$35,MATCH('Electricity Tax Rates'!$A4,'Electricity Tariffs and Consump'!$B$4:$B$35,0),MATCH("Industry",'Electricity Tariffs and Consump'!$C$3:$G$3,0))) -> 0.05 | G31: =IF(G4<1,G4,G4/INDEX('Electricity Tariffs and Consump'!$C$4:$G$35,MATCH('Electricity Tax Rates'!$A4,'Electricity Tariffs and Consump'!$B$4:$B$35,0),MATCH("Railway",'Electricity Tariffs and Consump'!$C$3:$G$3,0))) -> 0.05
A32: Bihar | B32: =IF(B5<1,B5,B5/INDEX('Electricity Tariffs and Consump'!$C$4:$G$35,MATCH('Electricity Tax Rates'!$A5,'Electricity Tariffs and Consump'!$B$4:$B$35,0),MATCH('Electricity Tax Rates'!B$2,'Electricity Tariffs and Consump'!$C$3:$G$3,0))) -> 0.06 | C32: =IF(C5<1,C5,C5/INDEX('Electricity Tariffs and Consump'!$C$4:$G$35,MATCH('Electricity Tax Rates'!$A5,'Electricity Tariffs and Consump'!$B$4:$B$35,0),MATCH('Electricity Tax Rates'!C$2,'Electricity Tariffs and Consump'!$C$3:$G$3,0))) -> 0.06 | D32: =IF(D5<1,D5,D5/INDEX('Electricity Tariffs and Consump'!$C$4:$G$35,MATCH('Electricity Tax Rates'!$A5,'Electricity Tariffs and Consump'!$B$4:$B$35,0),MATCH('Electricity Tax Rates'!D$2,'Electricity Tariffs and Consump'!$C$3:$G$3,0))) -> 0.010526316 | E32: =IF(E5<1,E5,E5/INDEX('Electricity Tariffs and Consump'!$C$4:$G$35,MATCH('Electricity Tax Rates'!$A5,'Electricity Tariffs and Consump'!$B$4:$B$35,0),MATCH("Industry",'Electricity Tariffs and Consump'!$C$3:$G$3,0))) -> 0.06 | F32: =IF(F5<1,F5,F5/INDEX('Electricity Tariffs and Consump'!$C$4:$G$35,MATCH('Electricity Tax Rates'!$A5,'Electricity Tariffs and Consump'!$B$4:$B$35,0),MATCH("Industry",'Electricity Tariffs and Consump'!$C$3:$G$3,0))) -> 0.06 | G32: =IF(G5<1,G5,G5/INDEX('Electricity Tariffs and Consump'!$C$4:$G$35,MATCH('Electricity Tax Rates'!$A5,'Electricity Tariffs and Consump'!$B$4:$B$35,0),MATCH("Railway",'Electricity Tariffs and Consump'!$C$3:$G$3,0))) -> 0
A33: Chandigarh | B33: 0 | C33: 0 | D33: =IF(D6<1,D6,D6/INDEX('Electricity Tariffs and Consump'!$C$4:$G$35,MATCH('Electricity Tax Rates'!$A6,'Electricity Tariffs and Consump'!$B$4:$B$35,0),MATCH('Electricity Tax Rates'!D$2,'Electricity Tariffs and Consump'!$C$3:$G$3,0))) -> 0 | E33: 0 | F33: 0 | G33: =IF(G6<1,G6,G6/INDEX('Electricity Tariffs and Consump'!$C$4:$G$35,MATCH('Electricity Tax Rates'!$A6,'Electricity Tariffs and Consump'!$B$4:$B$35,0),MATCH("Railway",'Electricity Tariffs and Consump'!$C$3:$G$3,0))) -> 0
A34: Delhi | B34: =IF(B7<1,B7,B7/INDEX('Electricity Tariffs and Consump'!$C$4:$G$35,MATCH('Electricity Tax Rates'!$A7,'Electricity Tariffs and Consump'!$B$4:$B$35,0),MATCH('Electricity Tax Rates'!B$2,'Electricity Tariffs and Consump'!$C$3:$G$3,0))) -> 0.05 | C34: =IF(C7<1,C7,C7/INDEX('Electricity Tariffs and Consump'!$C$4:$G$35,MATCH('Electricity Tax Rates'!$A7,'Electricity Tariffs and Consump'!$B$4:$B$35,0),MATCH('Electricity Tax Rates'!C$2,'Electricity Tariffs and Consump'!$C$3:$G$3,0))) -> 0.05 | D34: =IF(D7<1,D7,D7/INDEX('Electricity Tariffs and Consump'!$C$4:$G$35,MATCH('Electricity Tax Rates'!$A7,'Electricity Tariffs and Consump'!$B$4:$B$35,0),MATCH('Electricity Tax Rates'!D$2,'Electricity Tariffs and Consump'!$C$3:$G$3,0))) -> 0.05 | E34: =IF(E7<1,E7,E7/INDEX('Electricity Tariffs and Consump'!$C$4:$G$35,MATCH('Electricity Tax Rates'!$A7,'Electricity Tariffs and Consump'!$B$4:$B$35,0),MATCH("Industry",'Electricity Tariffs and Consump'!$C$3:$G$3,0))) -> 0.05 | F34: =IF(F7<1,F7,F7/INDEX('Electricity Tariffs and Consump'!$C$4:$G$35,MATCH('Electricity Tax Rates'!$A7,'Electricity Tariffs and Consump'!$B$4:$B$35,0),MATCH("Industry",'Electricity Tariffs and Consump'!$C$3:$G$3,0))) -> 0.05 | G34: =IF(G7<1,G7,G7/INDEX('Electricity Tariffs and Consump'!$C$4:$G$35,MATCH('Electricity Tax Rates'!$A7,'Electricity Tariffs and Consump'!$B$4:$B$35,0),MATCH("Railway",'Electricity Tariffs and Consump'!$C$3:$G$3,0))) -> 0.05
A35: Goa | B35: =IF(B8<1,B8,B8/INDEX('Electricity Tariffs and Consump'!$C$4:$G$35,MATCH('Electricity Tax Rates'!$A8,'Electricity Tariffs and Consump'!$B$4:$B$35,0),MATCH('Electricity Tax Rates'!B$2,'Electricity Tariffs and Consump'!$C$3:$G$3,0))) -> 0.072332731 | C35: =IF(C8<1,C8,C8/INDEX('Electricity Tariffs and Consump'!$C$4:$G$35,MATCH('Electricity Tax Rates'!$A8,'Electricity Tariffs and Consump'!$B$4:$B$35,0),MATCH('Electricity Tax Rates'!C$2,'Electricity Tariffs and Consump'!$C$3:$G$3,0))) -> 0.13964092 | D35: =IF(D8<1,D8,D8/INDEX('Electricity Tariffs and Consump'!$C$4:$G$35,MATCH('Electricity Tax Rates'!$A8,'Electricity Tariffs and Consump'!$B$4:$B$35,0),MATCH('Electricity Tax Rates'!D$2,'Electricity Tariffs and Consump'!$C$3:$G$3,0))) -> 0.12578616 | E35: =IF(E8<1,E8,E8/INDEX('Electricity Tariffs and Consump'!$C$4:$G$35,MATCH('Electricity Tax Rates'!$A8,'Electricity Tariffs and Consump'!$B$4:$B$35,0),MATCH("Industry",'Electricity Tariffs and Consump'!$C$3:$G$3,0))) -> 0.12076291 | F35: =IF(F8<1,F8,F8/INDEX('Electricity Tariffs and Consump'!$C$4:$G$35,MATCH('Electricity Tax Rates'!$A8,'Electricity Tariffs and Consump'!$B$4:$B$35,0),MATCH("Industry",'Electricity Tariffs and Consump'!$C$3:$G$3,0))) -> 0.12076291 | G35: =IF(G8<1,G8,G8/INDEX('Electricity Tariffs and Consump'!$C$4:$G$35,MATCH('Electricity Tax Rates'!$A8,'Electricity Tariffs and Consump'!$B$4:$B$35,0),MATCH("Railway",'Electricity Tariffs and Consump'!$C$3:$G$3,0))) -> 0
A36: Gujarat | B36: =IF(B9<1,B9,B9/INDEX('Electricity Tariffs and Consump'!$C$4:$G$35,MATCH('Electricity Tax Rates'!$A9,'Electricity Tariffs and Consump'!$B$4:$B$35,0),MATCH('Electricity Tax Rates'!B$2,'Electricity Tariffs and Consump'!$C$3:$G$3,0))) -> 0.1125 | C36: =IF(C9<1,C9,C9/INDEX('Electricity Tariffs and Consump'!$C$4:$G$35,MATCH('Electricity Tax Rates'!$A9,'Electricity Tariffs and Consump'!$B$4:$B$35,0),MATCH('Electricity Tax Rates'!C$2,'Electricity Tariffs and Consump'!$C$3:$G$3,0))) -> 0.2 | D36: =IF(D9<1,D9,D9/INDEX('Electricity Tariffs and Consump'!$C$4:$G$35,MATCH('Electricity Tax Rates'!$A9,'Electricity Tariffs and Consump'!$B$4:$B$35,0),MATCH('Electricity Tax Rates'!D$2,'Electricity Tariffs and Consump'!$C$3:$G$3,0))) -> 0 | E36: =IF(E9<1,E9,E9/INDEX('Electricity Tariffs and Consump'!$C$4:$G$35,MATCH('Electricity Tax Rates'!$A9,'Electricity Tariffs and Consump'!$B$4:$B$35,0),MATCH("Industry",'Electricity Tariffs and Consump'!$C$3:$G$3,0))) -> 0.1 | F36: =IF(F9<1,F9,F9/INDEX('Electricity Tariffs and Consump'!$C$4:$G$35,MATCH('Electricity Tax Rates'!$A9,'Electricity Tariffs and Consump'!$B$4:$B$35,0),MATCH("Industry",'Electricity Tariffs and Consump'!$C$3:$G$3,0))) -> 0.15 | G36: =IF(G9<1,G9,G9/INDEX('Electricity Tariffs and Consump'!$C$4:$G$35,MATCH('Electricity Tax Rates'!$A9,'Electricity Tariffs and Consump'!$B$4:$B$35,0),MATCH("Railway",'Electricity Tariffs and Consump'!$C$3:$G$3,0))) -> 0
A37: Haryana | B37: =IF(B10<1,B10,B10/INDEX('Electricity Tariffs and Consump'!$C$4:$G$35,MATCH('Electricity Tax Rates'!$A10,'Electricity Tariffs and Consump'!$B$4:$B$35,0),MATCH('Electricity Tax Rates'!B$2,'Electricity Tariffs and Consump'!$C$3:$G$3,0))) -> 0.022099448 | C37: =IF(C10<1,C10,C10/INDEX('Electricity Tariffs and Consump'!$C$4:$G$35,MATCH('Electricity Tax Rates'!$A10,'Electricity Tariffs and Consump'!$B$4:$B$35,0),MATCH('Electricity Tax Rates'!C$2,'Electricity Tariffs and Consump'!$C$3:$G$3,0))) -> 0.013180192 | D37: =IF(D10<1,D10,D10/INDEX('Electricity Tariffs and Consump'!$C$4:$G$35,MATCH('Electricity Tax Rates'!$A10,'Electricity Tariffs and Consump'!$B$4:$B$35,0),MATCH('Electricity Tax Rates'!D$2,'Electricity Tariffs and Consump'!$C$3:$G$3,0))) -> 0 | E37: =IF(E10<1,E10,E10/INDEX('Electricity Tariffs and Consump'!$C$4:$G$35,MATCH('Electricity Tax Rates'!$A10,'Electricity Tariffs and Consump'!$B$4:$B$35,0),MATCH("Industry",'Electricity Tariffs and Consump'!$C$3:$G$3,0))) -> 0.013807446 | F37: =IF(F10<1,F10,F10/INDEX('Electricity Tariffs and Consump'!$C$4:$G$35,MATCH('Electricity Tax Rates'!$A10,'Electricity Tariffs and Consump'!$B$4:$B$35,0),MATCH("Industry",'Electricity Tariffs and Consump'!$C$3:$G$3,0))) -> 0.013807446 | G37: =IF(G10<1,G10,G10/INDEX('Electricity Tariffs and Consump'!$C$4:$G$35,MATCH('Electricity Tax Rates'!$A10,'Electricity Tariffs and Consump'!$B$4:$B$35,0),MATCH("Railway",'Electricity Tariffs and Consump'!$C$3:$G$3,0))) -> 0.012288786
A38: Himachal Pradesh | B38: =IF(B11<1,B11,B11/INDEX('Electricity Tariffs and Consump'!$C$4:$G$35,MATCH('Electricity Tax Rates'!$A11,'Electricity Tariffs and Consump'!$B$4:$B$35,0),MATCH('Electricity Tax Rates'!B$2,'Electricity Tariffs and Consump'!$C$3:$G$3,0))) -> 0.03 | C38: =IF(C11<1,C11,C11/INDEX('Electricity Tariffs and Consump'!$C$4:$G$35,MATCH('Electricity Tax Rates'!$A11,'Electricity Tariffs and Consump'!$B$4:$B$35,0),MATCH('Electricity Tax Rates'!C$2,'Electricity Tariffs and Consump'!$C$3:$G$3,0))) -> 0.08 | D38: =IF(D11<1,D11,D11/INDEX('Electricity Tariffs and Consump'!$C$4:$G$35,MATCH('Electricity Tax Rates'!$A11,'Electricity Tariffs and Consump'!$B$4:$B$35,0),MATCH('Electricity Tax Rates'!D$2,'Electricity Tariffs and Consump'!$C$3:$G$3,0))) -> 0.1 | E38: =IF(E11<1,E11,E11/INDEX('Electricity Tariffs and Consump'!$C$4:$G$35,MATCH('Electricity Tax Rates'!$A11,'Electricity Tariffs and Consump'!$B$4:$B$35,0),MATCH("Industry",'Electricity Tariffs and Consump'!$C$3:$G$3,0))) -> 0.07 | F38: =IF(F11<1,F11,F11/INDEX('Electricity Tariffs and Consump'!$C$4:$G$35,MATCH('Electricity Tax Rates'!$A11,'Electricity Tariffs and Consump'!$B$4:$B$35,0),MATCH("Industry",'Electricity Tariffs and Consump'!$C$3:$G$3,0))) -> 0.11 | G38: =IF(G11<1,G11,G11/INDEX('Electricity Tariffs and Consump'!$C$4:$G$35,MATCH('Electricity Tax Rates'!$A11,'Electricity Tariffs and Consump'!$B$4:$B$35,0),MATCH("Railway",'Electricity Tariffs and Consump'!$C$3:$G$3,0))) -> 0.1
A39: Jammu and Kashmir | B39: =IF(B12<1,B12,B12/INDEX('Electricity Tariffs and Consump'!$C$4:$G$35,MATCH('Electricity Tax Rates'!$A12,'Electricity Tariffs and Consump'!$B$4:$B$35,0),MATCH('Electricity Tax Rates'!B$2,'Electricity Tariffs and Consump'!$C$3:$G$3,0))) -> 0.15 | C39: =IF(C12<1,C12,C12/INDEX('Electricity Tariffs and Consump'!$C$4:$G$35,MATCH('Electricity Tax Rates'!$A12,'Electricity Tariffs and Consump'!$B$4:$B$35,0),MATCH('Electricity Tax Rates'!C$2,'Electricity Tariffs and Consump'!$C$3:$G$3,0))) -> 0.15 | D39: =IF(D12<1,D12,D12/INDEX('Electricity Tariffs and Consump'!$C$4:$G$35,MATCH('Electricity Tax Rates'!$A12,'Electricity Tariffs and Consump'!$B$4:$B$35,0),MATCH('Electricity Tax Rates'!D$2,'Electricity Tariffs and Consump'!$C$3:$G$3,0))) -> 0.15 | E39: =IF(E12<1,E12,E12/INDEX('Electricity Tariffs and Consump'!$C$4:$G$35,MATCH('Electricity Tax Rates'!$A12,'Electricity Tariffs and Consump'!$B$4:$B$35,0),MATCH("Industry",'Electricity Tariffs and Consump'!$C$3:$G$3,0))) -> 0.15 | F39: =IF(F12<1,F12,F12/INDEX('Electricity Tariffs and Consump'!$C$4:$G$35,MATCH('Electricity Tax Rates'!$A12,'Electricity Tariffs and Consump'!$B$4:$B$35,0),MATCH("Industry",'Electricity Tariffs and Consump'!$C$3:$G$3,0))) -> 0.15 | G39: =IF(G12<1,G12,G12/INDEX('Electricity Tariffs and Consump'!$C$4:$G$35,MATCH('Electricity Tax Rates'!$A12,'Electricity Tariffs and Consump'!$B$4:$B$35,0),MATCH("Railway",'Electricity Tariffs and Consump'!$C$3:$G$3,0))) -> 0.15
A40: Jharkhand | B40: =IF(B13<1,B13,B13/INDEX('Electricity Tariffs and Consump'!$C$4:$G$35,MATCH('Electricity Tax Rates'!$A13,'Electricity Tariffs and Consump'!$B$4:$B$35,0),MATCH('Electricity Tax Rates'!B$2,'Electricity Tariffs and Consump'!$C$3:$G$3,0))) -> 0.035651587 | C40: =IF(C13<1,C13,C13/INDEX('Electricity Tariffs and Consump'!$C$4:$G$35,MATCH('Electricity Tax Rates'!$A13,'Electricity Tariffs and Consump'!$B$4:$B$35,0),MATCH('Electricity Tax Rates'!C$2,'Electricity Tariffs and Consump'!$C$3:$G$3,0))) -> 0.042857143 | D40: =IF(D13<1,D13,D13/INDEX('Electricity Tariffs and Consump'!$C$4:$G$35,MATCH('Electricity Tax Rates'!$A13,'Electricity Tariffs and Consump'!$B$4:$B$35,0),MATCH('Electricity Tax Rates'!D$2,'Electricity Tariffs and Consump'!$C$3:$G$3,0))) -> 0.0039215686 | E40: =IF(E13<1,E13,E13/INDEX('Electricity Tariffs and Consump'!$C$4:$G$35,MATCH('Electricity Tax Rates'!$A13,'Electricity Tariffs and Consump'!$B$4:$B$35,0),MATCH("Industry",'Electricity Tariffs and Consump'!$C$3:$G$3,0))) -> 0.0075659923 | F40: =IF(F13<1,F13,F13/INDEX('Electricity Tariffs and Consump'!$C$4:$G$35,MATCH('Electricity Tax Rates'!$A13,'Electricity Tariffs and Consump'!$B$4:$B$35,0),MATCH("Industry",'Electricity Tariffs and Consump'!$C$3:$G$3,0))) -> 0.0075659923 | G40: =IF(G13<1,G13,G13/INDEX('Electricity Tariffs and Consump'!$C$4:$G$35,MATCH('Electricity Tax Rates'!$A13,'Electricity Tariffs and Consump'!$B$4:$B$35,0),MATCH("Railway",'Electricity Tariffs and Consump'!$C$3:$G$3,0))) -> 0.018203883
A41: Karnataka | B41: =IF(B14<1,B14,B14/INDEX('Electricity Tariffs and Consump'!$C$4:$G$35,MATCH('Electricity Tax Rates'!$A14,'Electricity Tariffs and Consump'!$B$4:$B$35,0),MATCH('Electricity Tax Rates'!B$2,'Electricity Tariffs and Consump'!$C$3:$G$3,0))) -> 0.09 | C41: =IF(C14<1,C14,C14/INDEX('Electricity Tariffs and Consump'!$C$4:$G$35,MATCH('Electricity Tax Rates'!$A14,'Electricity Tariffs and Consump'!$B$4:$B$35,0),MATCH('Electricity Tax Rates'!C$2,'Electricity Tariffs and Consump'!$C$3:$G$3,0))) -> 0.09 | D41: =IF(D14<1,D14,D14/INDEX('Electricity Tariffs and Consump'!$C$4:$G$35,MATCH('Electricity Tax Rates'!$A14,'Electricity Tariffs and Consump'!$B$4:$B$35,0),MATCH('Electricity Tax Rates'!D$2,'Electricity Tariffs and Consump'!$C$3:$G$3,0))) -> 0.09 | E41: =IF(E14<1,E14,E14/INDEX('Electricity Tariffs and Consump'!$C$4:$G$35,MATCH('Electricity Tax Rates'!$A14,'Electricity Tariffs and Consump'!$B$4:$B$35,0),MATCH("Industry",'Electricity Tariffs and Consump'!$C$3:$G$3,0))) -> 0.09 | F41: =IF(F14<1,F14,F14/INDEX('Electricity Tariffs and Consump'!$C$4:$G$35,MATCH('Electricity Tax Rates'!$A14,'Electricity Tariffs and Consump'!$B$4:$B$35,0),MATCH("Industry",'Electricity Tariffs and Consump'!$C$3:$G$3,0))) -> 0.09 | G41: =IF(G14<1,G14,G14/INDEX('Electricity Tariffs and Consump'!$C$4:$G$35,MATCH('Electricity Tax Rates'!$A14,'Electricity Tariffs and Consump'!$B$4:$B$35,0),MATCH("Railway",'Electricity Tariffs and Consump'!$C$3:$G$3,0))) -> 0.09
A42: Kerala | B42: =IF(B15<1,B15,B15/INDEX('Electricity Tariffs and Consump'!$C$4:$G$35,MATCH('Electricity Tax Rates'!$A15,'Electricity Tariffs and Consump'!$B$4:$B$35,0),MATCH('Electricity Tax Rates'!B$2,'Electricity Tariffs and Consump'!$C$3:$G$3,0))) -> 0.1 | C42: =IF(C15<1,C15,C15/INDEX('Electricity Tariffs and Consump'!$C$4:$G$35,MATCH('Electricity Tax Rates'!$A15,'Electricity Tariffs and Consump'!$B$4:$B$35,0),MATCH('Electricity Tax Rates'!C$2,'Electricity Tariffs and Consump'!$C$3:$G$3,0))) -> 0.1 | D42: =IF(D15<1,D15,D15/INDEX('Electricity Tariffs and Consump'!$C$4:$G$35,MATCH('Electricity Tax Rates'!$A15,'Electricity Tariffs and Consump'!$B$4:$B$35,0),MATCH('Electricity Tax Rates'!D$2,'Electricity Tariffs and Consump'!$C$3:$G$3,0))) -> 0.1 | E42: =IF(E15<1,E15,E15/INDEX('Electricity Tariffs and Consump'!$C$4:$G$35,MATCH('Electricity Tax Rates'!$A15,'Electricity Tariffs and Consump'!$B$4:$B$35,0),MATCH("Industry",'Electricity Tariffs and Consump'!$C$3:$G$3,0))) -> 0.1 | F42: =IF(F15<1,F15,F15/INDEX('Electricity Tariffs and Consump'!$C$4:$G$35,MATCH('Electricity Tax Rates'!$A15,'Electricity Tariffs and Consump'!$B$4:$B$35,0),MATCH("Industry",'Electricity Tariffs and Consump'!$C$3:$G$3,0))) -> 0.016051364 | G42: =IF(G15<1,G15,G15/INDEX('Electricity Tariffs and Consump'!$C$4:$G$35,MATCH('Electricity Tax Rates'!$A15,'Electricity Tariffs and Consump'!$B$4:$B$35,0),MATCH("Railway",'Electricity Tariffs and Consump'!$C$3:$G$3,0))) -> 0
A43: Madhya Pradesh | B43: =IF(B16<1,B16,B16/INDEX('Electricity Tariffs and Consump'!$C$4:$G$35,MATCH('Electricity Tax Rates'!$A16,'Electricity Tariffs and Consump'!$B$4:$B$35,0),MATCH('Electricity Tax Rates'!B$2,'Electricity Tariffs and Consump'!$C$3:$G$3,0))) -> 0.105 | C43: =IF(C16<1,C16,C16/INDEX('Electricity Tariffs and Consump'!$C$4:$G$35,MATCH('Electricity Tax Rates'!$A16,'Electricity Tariffs and Consump'!$B$4:$B$35,0),MATCH('Electricity Tax Rates'!C$2,'Electricity Tariffs and Consump'!$C$3:$G$3,0))) -> 0.12 | D43: =IF(D16<1,D16,D16/INDEX('Electricity Tariffs and Consump'!$C$4:$G$35,MATCH('Electricity Tax Rates'!$A16,'Electricity Tariffs and Consump'!$B$4:$B$35,0),MATCH('Electricity Tax Rates'!D$2,'Electricity Tariffs and Consump'!$C$3:$G$3,0))) -> 0 | E43: =IF(E16<1,E16,E16/INDEX('Electricity Tariffs and Consump'!$C$4:$G$35,MATCH('Electricity Tax Rates'!$A16,'Electricity Tariffs and Consump'!$B$4:$B$35,0),MATCH("Industry",'Electricity Tariffs and Consump'!$C$3:$G$3,0))) -> 0.09 | F43: =IF(F16<1,F16,F16/INDEX('Electricity Tariffs and Consump'!$C$4:$G$35,MATCH('Electricity Tax Rates'!$A16,'Electricity Tariffs and Consump'!$B$4:$B$35,0),MATCH("Industry",'Electricity Tariffs and Consump'!$C$3:$G$3,0))) -> 0.15 | G43: =IF(G16<1,G16,G16/INDEX('Electricity Tariffs and Consump'!$C$4:$G$35,MATCH('Electricity Tax Rates'!$A16,'Electricity Tariffs and Consump'!$B$4:$B$35,0),MATCH("Railway",'Electricity Tariffs and Consump'!$C$3:$G$3,0))) -> 0
A44: Maharashtra | B44: =IF(B17<1,B17,B17/INDEX('Electricity Tariffs and Consump'!$C$4:$G$35,MATCH('Electricity Tax Rates'!$A17,'Electricity Tariffs and Consump'!$B$4:$B$35,0),MATCH('Electricity Tax Rates'!B$2,'Electricity Tariffs and Consump'!$C$3:$G$3,0))) -> 0.16 | C44: =IF(C17<1,C17,C17/INDEX('Electricity Tariffs and Consump'!$C$4:$G$35,MATCH('Electricity Tax Rates'!$A17,'Electricity Tariffs and Consump'!$B$4:$B$35,0),MATCH('Electricity Tax Rates'!C$2,'Electricity Tariffs and Consump'!$C$3:$G$3,0))) -> 0.21 | D44: =IF(D17<1,D17,D17/INDEX('Electricity Tariffs and Consump'!$C$4:$G$35,MATCH('Electricity Tax Rates'!$A17,'Electricity Tariffs and Consump'!$B$4:$B$35,0),MATCH('Electricity Tax Rates'!D$2,'Electricity Tariffs and Consump'!$C$3:$G$3,0))) -> 0 | E44: =IF(E17<1,E17,E17/INDEX('Electricity Tariffs and Consump'!$C$4:$G$35,MATCH('Electricity Tax Rates'!$A17,'Electricity Tariffs and Consump'!$B$4:$B$35,0),MATCH("Industry",'Electricity Tariffs and Consump'!$C$3:$G$3,0))) -> 0.075 | F44: =IF(F17<1,F17,F17/INDEX('Electricity Tariffs and Consump'!$C$4:$G$35,MATCH('Electricity Tax Rates'!$A17,'Electricity Tariffs and Consump'!$B$4:$B$35,0),MATCH("Industry",'Electricity Tariffs and Consump'!$C$3:$G$3,0))) -> 0.075 | G44: =IF(G17<1,G17,G17/INDEX('Electricity Tariffs and Consump'!$C$4:$G$35,MATCH('Electricity Tax Rates'!$A17,'Electricity Tariffs and Consump'!$B$4:$B$35,0),MATCH("Railway",'Electricity Tariffs and Consump'!$C$3:$G$3,0))) -> 0
A45: Manipur | B45: =IF(B18<1,B18,B18/INDEX('Electricity Tariffs and Consump'!$C$4:$G$35,MATCH('Electricity Tax Rates'!$A18,'Electricity Tariffs and Consump'!$B$4:$B$35,0),MATCH('Electricity Tax Rates'!B$2,'Electricity Tariffs and Consump'!$C$3:$G$3,0))) -> 0 | C45: =IF(C18<1,C18,C18/INDEX('Electricity Tariffs and Consump'!$C$4:$G$35,MATCH('Electricity Tax Rates'!$A18,'Electricity Tariffs and Consump'!$B$4:$B$35,0),MATCH('Electricity Tax Rates'!C$2,'Electricity Tariffs and Consump'!$C$3:$G$3,0))) -> 0 | D45: =IF(D18<1,D18,D18/INDEX('Electricity Tariffs and Consump'!$C$4:$G$35,MATCH('Electricity Tax Rates'!$A18,'Electricity Tariffs and Consump'!$B$4:$B$35,0),MATCH('Electricity Tax Rates'!D$2,'Electricity Tariffs and Consump'!$C$3:$G$3,0))) -> 0 | E45: =IF(E18<1,E18,E18/INDEX('Electricity Tariffs and Consump'!$C$4:$G$35,MATCH('Electricity Tax Rates'!$A18,'Electricity Tariffs and Consump'!$B$4:$B$35,0),MATCH("Industry",'Electricity Tariffs and Consump'!$C$3:$G$3,0))) -> 0 | F45: =IF(F18<1,F18,F18/INDEX('Electricity Tariffs and Consump'!$C$4:$G$35,MATCH('Electricity Tax Rates'!$A18,'Electricity Tariffs and Consump'!$B$4:$B$35,0),MATCH("Industry",'Electricity Tariffs and Consump'!$C$3:$G$3,0))) -> 0 | G45: =IF(G18<1,G18,G18/INDEX('Electricity Tariffs and Consump'!$C$4:$G$35,MATCH('Electricity Tax Rates'!$A18,'Electricity Tariffs and Consump'!$B$4:$B$35,0),MATCH("Railway",'Electricity Tariffs and Consump'!$C$3:$G$3,0))) -> 0
... A53: West Bengal | B53: =IF(B26<1,B26,B26/INDEX('Electricity Tariffs and Consump'!$C$4:$G$35,MATCH('Electricity Tax Rates'!$A26,'Electricity Tariffs and Consump'!$B$4:$B$35,0),MATCH('Electricity Tax Rates'!B$2,'Electricity Tariffs and Consump'!$C$3:$G$3,0))) -> 0.1 | C53: =IF(C26<1,C26,C26/INDEX('Electricity Tariffs and Consump'!$C$4:$G$35,MATCH('Electricity Tax Rates'!$A26,'Electricity Tariffs and Consump'!$B$4:$B$35,0),MATCH('Electricity Tax Rates'!C$2,'Electricity Tariffs and Consump'!$C$3:$G$3,0))) -> 0.125 | D53: =IF(D26<1,D26,D26/INDEX('Electricity Tariffs and Consump'!$C$4:$G$35,MATCH('Electricity Tax Rates'!$A26,'Electricity Tariffs and Consump'!$B$4:$B$35,0),MATCH('Electricity Tax Rates'!D$2,'Electricity Tariffs and Consump'!$C$3:$G$3,0))) -> 0 | E53: =IF(E26<1,E26,E26/INDEX('Electricity Tariffs and Consump'!$C$4:$G$35,MATCH('Electricity Tax Rates'!$A26,'Electricity Tariffs and Consump'!$B$4:$B$35,0),MATCH("Industry",'Electricity Tariffs and Consump'!$C$3:$G$3,0))) -> 0.075 | F53: =IF(F26<1,F26,F26/INDEX('Electricity Tariffs and Consump'!$C$4:$G$35,MATCH('Electricity Tax Rates'!$A26,'Electricity Tariffs and Consump'!$B$4:$B$35,0),MATCH("Industry",'Electricity Tariffs and Consump'!$C$3:$G$3,0))) -> 0.15 | G53: =IF(G26<1,G26,G26/INDEX('Electricity Tariffs and Consump'!$C$4:$G$35,MATCH('Electricity Tax Rates'!$A26,'Electricity Tariffs and Consump'!$B$4:$B$35,0),MATCH("Railway",'Electricity Tariffs and Consump'!$C$3:$G$3,0))) -> 0
A55: Consumption
A56: State | B56: Domestic | C56: Commercial | D56: Agriculture | E56: LT Industry | F56: HT industry | G56: Railway
A57: Andhra Pradesh | B57: =IFERROR(INDEX('Electricity Tariffs and Consump'!$C$44:$H$75,MATCH('Electricity Tax Rates'!$A57,'Electricity Tariffs and Consump'!$B$44:$B$75,0),MATCH('Electricity Tax Rates'!B$56,'Electricity Tariffs and Consump'!$C$43:$H$43,0)),"") -> 17933.6 | C57: =IFERROR(INDEX('Electricity Tariffs and Consump'!$C$44:$H$75,MATCH('Electricity Tax Rates'!$A57,'Electricity Tariffs and Consump'!$B$44:$B$75,0),MATCH('Electricity Tax Rates'!C$56,'Electricity Tariffs and Consump'!$C$43:$H$43,0)),"") -> 4957.5 | D57: =IFERROR(INDEX('Electricity Tariffs and Consump'!$C$44:$H$75,MATCH('Electricity Tax Rates'!$A57,'Electricity Tariffs and Consump'!$B$44:$B$75,0),MATCH('Electricity Tax Rates'!D$56,'Electricity Tariffs and Consump'!$C$43:$H$43,0)),"") -> 16261.8 | E57: =IFERROR(INDEX('Electricity Tariffs and Consump'!$C$44:$H$75,MATCH('Electricity Tax Rates'!$A57,'Electricity Tariffs and Consump'!$B$44:$B$75,0),MATCH("industry",'Electricity Tariffs and Consump'!$C$43:$H$43,0))/2,"") -> 8706 | F57: =IFERROR(INDEX('Electricity Tariffs and Consump'!$C$44:$H$75,MATCH('Electricity Tax Rates'!$A57,'Electricity Tariffs and Consump'!$B$44:$B$75,0),MATCH("industry",'Electricity Tariffs and Consump'!$C$43:$H$43,0))/2,"") -> 8706 | G57: =IFERROR(INDEX('Electricity Tariffs and Consump'!$C$44:$H$75,MATCH('Electricity Tax Rates'!$A57,'Electricity Tariffs and Consump'!$B$44:$B$75,0),MATCH('Electricity Tax Rates'!G$56,'Electricity Tariffs and Consump'!$C$43:$H$43,0)),"") -> 0
A58: Assam | B58: =IFERROR(INDEX('Electricity Tariffs and Consump'!$C$44:$H$75,MATCH('Electricity Tax Rates'!$A58,'Electricity Tariffs and Consump'!$B$44:$B$75,0),MATCH('Electricity Tax Rates'!B$56,'Electricity Tariffs and Consump'!$C$43:$H$43,0)),"") -> 4329 | C58: =IFERROR(INDEX('Electricity Tariffs and Consump'!$C$44:$H$75,MATCH('Electricity Tax Rates'!$A58,'Electricity Tariffs and Consump'!$B$44:$B$75,0),MATCH('Electricity Tax Rates'!C$56,'Electricity Tariffs and Consump'!$C$43:$H$43,0)),"") -> 1237 | D58: =IFERROR(INDEX('Electricity Tariffs and Consump'!$C$44:$H$75,MATCH('Electricity Tax Rates'!$A58,'Electricity Tariffs and Consump'!$B$44:$B$75,0),MATCH('Electricity Tax Rates'!D$56,'Electricity Tariffs and Consump'!$C$43:$H$43,0)),"") -> 65 | E58: =IFERROR(INDEX('Electricity Tariffs and Consump'!$C$44:$H$75,MATCH('Electricity Tax Rates'!$A58,'Electricity Tariffs and Consump'!$B$44:$B$75,0),MATCH("industry",'Electricity Tariffs and Consump'!$C$43:$H$43,0))/2,"") -> 843 | F58: =IFERROR(INDEX('Electricity Tariffs and Consump'!$C$44:$H$75,MATCH('Electricity Tax Rates'!$A58,'Electricity Tariffs and Consump'!$B$44:$B$75,0),MATCH("industry",'Electricity Tariffs and Consump'!$C$43:$H$43,0))/2,"") -> 843 | G58: =IFERROR(INDEX('Electricity Tariffs and Consump'!$C$44:$H$75,MATCH('Electricity Tax Rates'!$A58,'Electricity Tariffs and Consump'!$B$44:$B$75,0),MATCH('Electricity Tax Rates'!G$56,'Electricity Tariffs and Consump'!$C$43:$H$43,0)),"") -> 0
A59: Bihar | B59: =IFERROR(INDEX('Electricity Tariffs and Consump'!$C$44:$H$75,MATCH('Electricity Tax Rates'!$A59,'Electricity Tariffs and Consump'!$B$44:$B$75,0),MATCH('Electricity Tax Rates'!B$56,'Electricity Tariffs and Consump'!$C$43:$H$43,0)),"") -> 16738.3 | C59: =IFERROR(INDEX('Electricity Tariffs and Consump'!$C$44:$H$75,MATCH('Electricity Tax Rates'!$A59,'Electricity Tariffs and Consump'!$B$44:$B$75,0),MATCH('Electricity Tax Rates'!C$56,'Electricity Tariffs and Consump'!$C$43:$H$43,0)),"") -> 2397.6 | D59: =IFERROR(INDEX('Electricity Tariffs and Consump'!$C$44:$H$75,MATCH('Electricity Tax Rates'!$A59,'Electricity Tariffs and Consump'!$B$44:$B$75,0),MATCH('Electricity Tax Rates'!D$56,'Electricity Tariffs and Consump'!$C$43:$H$43,0)),"") -> 1240.1 | E59: =IFERROR(INDEX('Electricity Tariffs and Consump'!$C$44:$H$75,MATCH('Electricity Tax Rates'!$A59,'Electricity Tariffs and Consump'!$B$44:$B$75,0),MATCH("industry",'Electricity Tariffs and Consump'!$C$43:$H$43,0))/2,"") -> 1501.2 | F59: =IFERROR(INDEX('Electricity Tariffs and Consump'!$C$44:$H$75,MATCH('Electricity Tax Rates'!$A59,'Electricity Tariffs and Consump'!$B$44:$B$75,0),MATCH("industry",'Electricity Tariffs and Consump'!$C$43:$H$43,0))/2,"") -> 1501.2 | G59: =IFERROR(INDEX('Electricity Tariffs and Consump'!$C$44:$H$75,MATCH('Electricity Tax Rates'!$A59,'Electricity Tariffs and Consump'!$B$44:$B$75,0),MATCH('Electricity Tax Rates'!G$56,'Electricity Tariffs and Consump'!$C$43:$H$43,0)),"") -> 116.4
A60: Chandigarh | B60: 0 | C60: 0 | D60: 0 | E60: 0 | F60: 0 | G60: 0
A61: Delhi | B61: =IFERROR(INDEX('Electricity Tariffs and Consump'!$C$44:$H$75,MATCH('Electricity Tax Rates'!$A61,'Electricity Tariffs and Consump'!$B$44:$B$75,0),MATCH('Electricity Tax Rates'!B$56,'Electricity Tariffs and Consump'!$C$43:$H$43,0)),"") -> 16674.6 | C61: =IFERROR(INDEX('Electricity Tariffs and Consump'!$C$44:$H$75,MATCH('Electricity Tax Rates'!$A61,'Electricity Tariffs and Consump'!$B$44:$B$75,0),MATCH('Electricity Tax Rates'!C$56,'Electricity Tariffs and Consump'!$C$43:$H$43,0)),"") -> 6685.5 | D61: =IFERROR(INDEX('Electricity Tariffs and Consump'!$C$44:$H$75,MATCH('Electricity Tax Rates'!$A61,'Electricity Tariffs and Consump'!$B$44:$B$75,0),MATCH('Electricity Tax Rates'!D$56,'Electricity Tariffs and Consump'!$C$43:$H$43,0)),"") -> 44 | E61: =IFERROR(INDEX('Electricity Tariffs and Consump'!$C$44:$H$75,MATCH('Electricity Tax Rates'!$A61,'Electricity Tariffs and Consump'!$B$44:$B$75,0),MATCH("industry",'Electricity Tariffs and Consump'!$C$43:$H$43,0))/2,"") -> 1716.5 | F61: =IFERROR(INDEX('Electricity Tariffs and Consump'!$C$44:$H$75,MATCH('Electricity Tax Rates'!$A61,'Electricity Tariffs and Consump'!$B$44:$B$75,0),MATCH("industry",'Electricity Tariffs and Consump'!$C$43:$H$43,0))/2,"") -> 1716.5 | G61: =IFERROR(INDEX('Electricity Tariffs and Consump'!$C$44:$H$75,MATCH('Electricity Tax Rates'!$A61,'Electricity Tariffs and Consump'!$B$44:$B$75,0),MATCH('Electricity Tax Rates'!G$56,'Electricity Tariffs and Consump'!$C$43:$H$43,0)),"") -> 0
A62: Goa | B62: =IFERROR(INDEX('Electricity Tariffs and Consump'!$C$44:$H$75,MATCH('Electricity Tax Rates'!$A62,'Electricity Tariffs and Consump'!$B$44:$B$75,0),MATCH('Electricity Tax Rates'!B$56,'Electricity Tariffs and Consump'!$C$43:$H$43,0)),"") -> 1303.4 | C62: =IFERROR(INDEX('Electricity Tariffs and Consump'!$C$44:$H$75,MATCH('Electricity Tax Rates'!$A62,'Electricity Tariffs and Consump'!$B$44:$B$75,0),MATCH('Electricity Tax Rates'!C$56,'Electricity Tariffs and Consump'!$C$43:$H$43,0)),"") -> 614.6 | D62: =IFERROR(INDEX('Electricity Tariffs and Consump'!$C$44:$H$75,MATCH('Electricity Tax Rates'!$A62,'Electricity Tariffs and Consump'!$B$44:$B$75,0),MATCH('Electricity Tax Rates'!D$56,'Electricity Tariffs and Consump'!$C$43:$H$43,0)),"") -> 34.3 | E62: =IFERROR(INDEX('Electricity Tariffs and Consump'!$C$44:$H$75,MATCH('Electricity Tax Rates'!$A62,'Electricity Tariffs and Consump'!$B$44:$B$75,0),MATCH("industry",'Electricity Tariffs and Consump'!$C$43:$H$43,0))/2,"") -> 1043 | F62: =IFERROR(INDEX('Electricity Tariffs and Consump'!$C$44:$H$75,MATCH('Electricity Tax Rates'!$A62,'Electricity Tariffs and Consump'!$B$44:$B$75,0),MATCH("industry",'Electricity Tariffs and Consump'!$C$43:$H$43,0))/2,"") -> 1043 | G62: =IFERROR(INDEX('Electricity Tariffs and Consump'!$C$44:$H$75,MATCH('Electricity Tax Rates'!$A62,'Electricity Tariffs and Consump'!$B$44:$B$75,0),MATCH('Electricity Tax Rates'!G$56,'Electricity Tariffs and Consump'!$C$43:$H$43,0)),"") -> 0
A63: Gujarat | B63: =IFERROR(INDEX('Electricity Tariffs and Consump'!$C$44:$H$75,MATCH('Electricity Tax Rates'!$A63,'Electricity Tariffs and Consump'!$B$44:$B$75,0),MATCH('Electricity Tax Rates'!B$56,'Electricity Tariffs and Consump'!$C$43:$H$43,0)),"") -> 16588.9 | C63: =IFERROR(INDEX('Electricity Tariffs and Consump'!$C$44:$H$75,MATCH('Electricity Tax Rates'!$A63,'Electricity Tariffs and Consump'!$B$44:$B$75,0),MATCH('Electricity Tax Rates'!C$56,'Electricity Tariffs and Consump'!$C$43:$H$43,0)),"") -> 2613.7 | D63: =IFERROR(INDEX('Electricity Tariffs and Consump'!$C$44:$H$75,MATCH('Electricity Tax Rates'!$A63,'Electricity Tariffs and Consump'!$B$44:$B$75,0),MATCH('Electricity Tax Rates'!D$56,'Electricity Tariffs and Consump'!$C$43:$H$43,0)),"") -> 20433.4 | E63: =IFERROR(INDEX('Electricity Tariffs and Consump'!$C$44:$H$75,MATCH('Electricity Tax Rates'!$A63,'Electricity Tariffs and Consump'!$B$44:$B$75,0),MATCH("industry",'Electricity Tariffs and Consump'!$C$43:$H$43,0))/2,"") -> 31359.55 | F63: =IFERROR(INDEX('Electricity Tariffs and Consump'!$C$44:$H$75,MATCH('Electricity Tax Rates'!$A63,'Electricity Tariffs and Consump'!$B$44:$B$75,0),MATCH("industry",'Electricity Tariffs and Consump'!$C$43:$H$43,0))/2,"") -> 31359.55 | G63: =IFERROR(INDEX('Electricity Tariffs and Consump'!$C$44:$H$75,MATCH('Electricity Tax Rates'!$A63,'Electricity Tariffs and Consump'!$B$44:$B$75,0),MATCH('Electricity Tax Rates'!G$56,'Electricity Tariffs and Consump'!$C$43:$H$43,0)),"") -> 8
A64: Haryana | B64: =IFERROR(INDEX('Electricity Tariffs and Consump'!$C$44:$H$75,MATCH('Electricity Tax Rates'!$A64,'Electricity Tariffs and Consump'!$B$44:$B$75,0),MATCH('Electricity Tax Rates'!B$56,'Electricity Tariffs and Consump'!$C$43:$H$43,0)),"") -> 13374.4 | C64: =IFERROR(INDEX('Electricity Tariffs and Consump'!$C$44:$H$75,MATCH('Electricity Tax Rates'!$A64,'Electricity Tariffs and Consump'!$B$44:$B$75,0),MATCH('Electricity Tax Rates'!C$56,'Electricity Tariffs and Consump'!$C$43:$H$43,0)),"") -> 3119 | D64: =IFERROR(INDEX('Electricity Tariffs and Consump'!$C$44:$H$75,MATCH('Electricity Tax Rates'!$A64,'Electricity Tariffs and Consump'!$B$44:$B$75,0),MATCH('Electricity Tax Rates'!D$56,'Electricity Tariffs and Consump'!$C$43:$H$43,0)),"") -> 9318.4 | E64: =IFERROR(INDEX('Electricity Tariffs and Consump'!$C$44:$H$75,MATCH('Electricity Tax Rates'!$A64,'Electricity Tariffs and Consump'!$B$44:$B$75,0),MATCH("industry",'Electricity Tariffs and Consump'!$C$43:$H$43,0))/2,"") -> 8466.3 | F64: =IFERROR(INDEX('Electricity Tariffs and Consump'!$C$44:$H$75,MATCH('Electricity Tax Rates'!$A64,'Electricity Tariffs and Consump'!$B$44:$B$75,0),MATCH("industry",'Electricity Tariffs and Consump'!$C$43:$H$43,0))/2,"") -> 8466.3 | G64: =IFERROR(INDEX('Electricity Tariffs and Consump'!$C$44:$H$75,MATCH('Electricity Tax Rates'!$A64,'Electricity Tariffs and Consump'!$B$44:$B$75,0),MATCH('Electricity Tax Rates'!G$56,'Electricity Tariffs and Consump'!$C$43:$H$43,0)),"") -> 71.8
A65: Himachal Pradesh | B65: =IFERROR(INDEX('Electricity Tariffs and Consump'!$C$44:$H$75,MATCH('Electricity Tax Rates'!$A65,'Electricity Tariffs and Consump'!$B$44:$B$75,0),MATCH('Electricity Tax Rates'!B$56,'Electricity Tariffs and Consump'!$C$43:$H$43,0)),"") -> 2457.5 | C65: =IFERROR(INDEX('Electricity Tariffs and Consump'!$C$44:$H$75,MATCH('Electricity Tax Rates'!$A65,'Electricity Tariffs and Consump'!$B$44:$B$75,0),MATCH('Electricity Tax Rates'!C$56,'Electricity Tariffs and Consump'!$C$43:$H$43,0)),"") -> 621.9 | D65: =IFERROR(INDEX('Electricity Tariffs and Consump'!$C$44:$H$75,MATCH('Electricity Tax Rates'!$A65,'Electricity Tariffs and Consump'!$B$44:$B$75,0),MATCH('Electricity Tax Rates'!D$56,'Electricity Tariffs and Consump'!$C$43:$H$43,0)),"") -> 85.1 | E65: =IFERROR(INDEX('Electricity Tariffs and Consump'!$C$44:$H$75,MATCH('Electricity Tax Rates'!$A65,'Electricity Tariffs and Consump'!$B$44:$B$75,0),MATCH("industry",'Electricity Tariffs and Consump'!$C$43:$H$43,0))/2,"") -> 2996.65 | F65: =IFERROR(INDEX('Electricity Tariffs and Consump'!$C$44:$H$75,MATCH('Electricity Tax Rates'!$A65,'Electricity Tariffs and Consump'!$B$44:$B$75,0),MATCH("industry",'Electricity Tariffs and Consump'!$C$43:$H$43,0))/2,"") -> 2996.65 | G65: =IFERROR(INDEX('Electricity Tariffs and Consump'!$C$44:$H$75,MATCH('Electricity Tax Rates'!$A65,'Electricity Tariffs and Consump'!$B$44:$B$75,0),MATCH('Electricity Tax Rates'!G$56,'Electricity Tariffs and Consump'!$C$43:$H$43,0)),"") -> 0
A66: Jammu & Kashmir | B66: =IFERROR(INDEX('Electricity Tariffs and Consump'!$C$44:$H$75,MATCH('Electricity Tax Rates'!$A66,'Electricity Tariffs and Consump'!$B$44:$B$75,0),MATCH('Electricity Tax Rates'!B$56,'Electricity Tariffs and Consump'!$C$43:$H$43,0)),"") -> 4003.6 | C66: =IFERROR(INDEX('Electricity Tariffs and Consump'!$C$44:$H$75,MATCH('Electricity Tax Rates'!$A66,'Electricity Tariffs and Consump'!$B$44:$B$75,0),MATCH('Electricity Tax Rates'!C$56,'Electricity Tariffs and Consump'!$C$43:$H$43,0)),"") -> 1765.1 | D66: =IFERROR(INDEX('Electricity Tariffs and Consump'!$C$44:$H$75,MATCH('Electricity Tax Rates'!$A66,'Electricity Tariffs and Consump'!$B$44:$B$75,0),MATCH('Electricity Tax Rates'!D$56,'Electricity Tariffs and Consump'!$C$43:$H$43,0)),"") -> 400.4 | E66: =IFERROR(INDEX('Electricity Tariffs and Consump'!$C$44:$H$75,MATCH('Electricity Tax Rates'!$A66,'Electricity Tariffs and Consump'!$B$44:$B$75,0),MATCH("industry",'Electricity Tariffs and Consump'!$C$43:$H$43,0))/2,"") -> 749.2 | F66: =IFERROR(INDEX('Electricity Tariffs and Consump'!$C$44:$H$75,MATCH('Electricity Tax Rates'!$A66,'Electricity Tariffs and Consump'!$B$44:$B$75,0),MATCH("industry",'Electricity Tariffs and Consump'!$C$43:$H$43,0))/2,"") -> 749.2 | G66: =IFERROR(INDEX('Electricity Tariffs and Consump'!$C$44:$H$75,MATCH('Electricity Tax Rates'!$A66,'Electricity Tariffs and Consump'!$B$44:$B$75,0),MATCH('Electricity Tax Rates'!G$56,'Electricity Tariffs and Consump'!$C$43:$H$43,0)),"") -> 0
A67: Jharkhand | B67: =IFERROR(INDEX('Electricity Tariffs and Consump'!$C$44:$H$75,MATCH('Electricity Tax Rates'!$A67,'Electricity Tariffs and Consump'!$B$44:$B$75,0),MATCH('Electricity Tax Rates'!B$56,'Electricity Tariffs and Consump'!$C$43:$H$43,0)),"") -> 5886.5 | C67: =IFERROR(INDEX('Electricity Tariffs and Consump'!$C$44:$H$75,MATCH('Electricity Tax Rates'!$A67,'Electricity Tariffs and Consump'!$B$44:$B$75,0),MATCH('Electricity Tax Rates'!C$56,'Electricity Tariffs and Consump'!$C$43:$H$43,0)),"") -> 894.7 | D67: =IFERROR(INDEX('Electricity Tariffs and Consump'!$C$44:$H$75,MATCH('Electricity Tax Rates'!$A67,'Electricity Tariffs and Consump'!$B$44:$B$75,0),MATCH('Electricity Tax Rates'!D$56,'Electricity Tariffs and Consump'!$C$43:$H$43,0)),"") -> 255.7 | E67: =IFERROR(INDEX('Electricity Tariffs and Consump'!$C$44:$H$75,MATCH('Electricity Tax Rates'!$A67,'Electricity Tariffs and Consump'!$B$44:$B$75,0),MATCH("industry",'Electricity Tariffs and Consump'!$C$43:$H$43,0))/2,"") -> 1365.2 | F67: =IFERROR(INDEX('Electricity Tariffs and Consump'!$C$44:$H$75,MATCH('Electricity Tax Rates'!$A67,'Electricity Tariffs and Consump'!$B$44:$B$75,0),MATCH("industry",'Electricity Tariffs and Consump'!$C$43:$H$43,0))/2,"") -> 1365.2 | G67: =IFERROR(INDEX('Electricity Tariffs and Consump'!$C$44:$H$75,MATCH('Electricity Tax Rates'!$A67,'Electricity Tariffs and Consump'!$B$44:$B$75,0),MATCH('Electricity Tax Rates'!G$56,'Electricity Tariffs and Consump'!$C$43:$H$43,0)),"") -> 104.4
A68: Karnataka | B68: =IFERROR(INDEX('Electricity Tariffs and Consump'!$C$44:$H$75,MATCH('Electricity Tax Rates'!$A68,'Electricity Tariffs and Consump'!$B$44:$B$75,0),MATCH('Electricity Tax Rates'!B$56,'Electricity Tariffs and Consump'!$C$43:$H$43,0)),"") -> 14101.9 | C68: =IFERROR(INDEX('Electricity Tariffs and Consump'!$C$44:$H$75,MATCH('Electricity Tax Rates'!$A68,'Electricity Tariffs and Consump'!$B$44:$B$75,0),MATCH('Electricity Tax Rates'!C$56,'Electricity Tariffs and Consump'!$C$43:$H$43,0)),"") -> 5479.8 | D68: =IFERROR(INDEX('Electricity Tariffs and Consump'!$C$44:$H$75,MATCH('Electricity Tax Rates'!$A68,'Electricity Tariffs and Consump'!$B$44:$B$75,0),MATCH('Electricity Tax Rates'!D$56,'Electricity Tariffs and Consump'!$C$43:$H$43,0)),"") -> 21834.3 | E68: =IFERROR(INDEX('Electricity Tariffs and Consump'!$C$44:$H$75,MATCH('Electricity Tax Rates'!$A68,'Electricity Tariffs and Consump'!$B$44:$B$75,0),MATCH("industry",'Electricity Tariffs and Consump'!$C$43:$H$43,0))/2,"") -> 4990.55 | F68: =IFERROR(INDEX('Electricity Tariffs and Consump'!$C$44:$H$75,MATCH('Electricity Tax Rates'!$A68,'Electricity Tariffs and Consump'!$B$44:$B$75,0),MATCH("industry",'Electricity Tariffs and Consump'!$C$43:$H$43,0))/2,"") -> 4990.55 | G68: =IFERROR(INDEX('Electricity Tariffs and Consump'!$C$44:$H$75,MATCH('Electricity Tax Rates'!$A68,'Electricity Tariffs and Consump'!$B$44:$B$75,0),MATCH('Electricity Tax Rates'!G$56,'Electricity Tariffs and Consump'!$C$43:$H$43,0)),"") -> 0
A69: Kerala | B69: =IFERROR(INDEX('Electricity Tariffs and Consump'!$C$44:$H$75,MATCH('Electricity Tax Rates'!$A69,'Electricity Tariffs and Consump'!$B$44:$B$75,0),MATCH('Electricity Tax Rates'!B$56,'Electricity Tariffs and Consump'!$C$43:$H$43,0)),"") -> 12386.5 | C69: =IFERROR(INDEX('Electricity Tariffs and Consump'!$C$44:$H$75,MATCH('Electricity Tax Rates'!$A69,'Electricity Tariffs and Consump'!$B$44:$B$75,0),MATCH('Electricity Tax Rates'!C$56,'Electricity Tariffs and Consump'!$C$43:$H$43,0)),"") -> 3885.5 | D69: =IFERROR(INDEX('Electricity Tariffs and Consump'!$C$44:$H$75,MATCH('Electricity Tax Rates'!$A69,'Electricity Tariffs and Consump'!$B$44:$B$75,0),MATCH('Electricity Tax Rates'!D$56,'Electricity Tariffs and Consump'!$C$43:$H$43,0)),"") -> 387.2 | E69: =IFERROR(INDEX('Electricity Tariffs and Consump'!$C$44:$H$75,MATCH('Electricity Tax Rates'!$A69,'Electricity Tariffs and Consump'!$B$44:$B$75,0),MATCH("industry",'Electricity Tariffs and Consump'!$C$43:$H$43,0))/2,"") -> 3438.05 | F69: =IFERROR(INDEX('Electricity Tariffs and Consump'!$C$44:$H$75,MATCH('Electricity Tax Rates'!$A69,'Electricity Tariffs and Consump'!$B$44:$B$75,0),MATCH("industry",'Electricity Tariffs and Consump'!$C$43:$H$43,0))/2,"") -> 3438.05 | G69: =IFERROR(INDEX('Electricity Tariffs and Consump'!$C$44:$H$75,MATCH('Electricity Tax Rates'!$A69,'Electricity Tariffs and Consump'!$B$44:$B$75,0),MATCH('Electricity Tax Rates'!G$56,'Electricity Tariffs and Consump'!$C$43:$H$43,0)),"") -> 323.1
A70: Madhya Pradesh | B70: =IFERROR(INDEX('Electricity Tariffs and Consump'!$C$44:$H$75,MATCH('Electricity Tax Rates'!$A70,'Electricity Tariffs and Consump'!$B$44:$B$75,0),MATCH('Electricity Tax Rates'!B$56,'Electricity Tariffs and Consump'!$C$43:$H$43,0)),"") -> 18771.2 | C70: =IFERROR(INDEX('Electricity Tariffs and Consump'!$C$44:$H$75,MATCH('Electricity Tax Rates'!$A70,'Electricity Tariffs and Consump'!$B$44:$B$75,0),MATCH('Electricity Tax Rates'!C$56,'Electricity Tariffs and Consump'!$C$43:$H$43,0)),"") -> 3734.4 | D70: =IFERROR(INDEX('Electricity Tariffs and Consump'!$C$44:$H$75,MATCH('Electricity Tax Rates'!$A70,'Electricity Tariffs and Consump'!$B$44:$B$75,0),MATCH('Electricity Tax Rates'!D$56,'Electricity Tariffs and Consump'!$C$43:$H$43,0)),"") -> 25452.5 | E70: =IFERROR(INDEX('Electricity Tariffs and Consump'!$C$44:$H$75,MATCH('Electricity Tax Rates'!$A70,'Electricity Tariffs and Consump'!$B$44:$B$75,0),MATCH("industry",'Electricity Tariffs and Consump'!$C$43:$H$43,0))/2,"") -> 6142.7 | F70: =IFERROR(INDEX('Electricity Tariffs and Consump'!$C$44:$H$75,MATCH('Electricity Tax Rates'!$A70,'Electricity Tariffs and Consump'!$B$44:$B$75,0),MATCH("industry",'Electricity Tariffs and Consump'!$C$43:$H$43,0))/2,"") -> 6142.7 | G70: =IFERROR(INDEX('Electricity Tariffs and Consump'!$C$44:$H$75,MATCH('Electricity Tax Rates'!$A70,'Electricity Tariffs and Consump'!$B$44:$B$75,0),MATCH('Electricity Tax Rates'!G$56,'Electricity Tariffs and Consump'!$C$43:$H$43,0)),"") -> 110.7
A71: Maharashtra | B71: =IFERROR(INDEX('Electricity Tariffs and Consump'!$C$44:$H$75,MATCH('Electricity Tax Rates'!$A71,'Electricity Tariffs and Consump'!$B$44:$B$75,0),MATCH('Electricity Tax Rates'!B$56,'Electricity Tariffs and Consump'!$C$43:$H$43,0)),"") -> 30803.1 | C71: =IFERROR(INDEX('Electricity Tariffs and Consump'!$C$44:$H$75,MATCH('Electricity Tax Rates'!$A71,'Electricity Tariffs and Consump'!$B$44:$B$75,0),MATCH('Electricity Tax Rates'!C$56,'Electricity Tariffs and Consump'!$C$43:$H$43,0)),"") -> 13915.6 | D71: =IFERROR(INDEX('Electricity Tariffs and Consump'!$C$44:$H$75,MATCH('Electricity Tax Rates'!$A71,'Electricity Tariffs and Consump'!$B$44:$B$75,0),MATCH('Electricity Tax Rates'!D$56,'Electricity Tariffs and Consump'!$C$43:$H$43,0)),"") -> 28546.9 | E71: =IFERROR(INDEX('Electricity Tariffs and Consump'!$C$44:$H$75,MATCH('Electricity Tax Rates'!$A71,'Electricity Tariffs and Consump'!$B$44:$B$75,0),MATCH("industry",'Electricity Tariffs and Consump'!$C$43:$H$43,0))/2,"") -> 22015.65 | F71: =IFERROR(INDEX('Electricity Tariffs and Consump'!$C$44:$H$75,MATCH('Electricity Tax Rates'!$A71,'Electricity Tariffs and Consump'!$B$44:$B$75,0),MATCH("industry",'Electricity Tariffs and Consump'!$C$43:$H$43,0))/2,"") -> 22015.65 | G71: =IFERROR(INDEX('Electricity Tariffs and Consump'!$C$44:$H$75,MATCH('Electricity Tax Rates'!$A71,'Electricity Tariffs and Consump'!$B$44:$B$75,0),MATCH('Electricity Tax Rates'!G$56,'Electricity Tariffs and Consump'!$C$43:$H$43,0)),"") -> 115.3
A72: Manipur | B72: =IFERROR(INDEX('Electricity Tariffs and Consump'!$C$44:$H$75,MATCH('Electricity Tax Rates'!$A72,'Electricity Tariffs and Consump'!$B$44:$B$75,0),MATCH('Electricity Tax Rates'!B$56,'Electricity Tariffs and Consump'!$C$43:$H$43,0)),"") -> 462.2 | C72: =IFERROR(INDEX('Electricity Tariffs and Consump'!$C$44:$H$75,MATCH('Electricity Tax Rates'!$A72,'Electricity Tariffs and Consump'!$B$44:$B$75,0),MATCH('Electricity Tax Rates'!C$56,'Electricity Tariffs and Consump'!$C$43:$H$43,0)),"") -> 85.1 | D72: =IFERROR(INDEX('Electricity Tariffs and Consump'!$C$44:$H$75,MATCH('Electricity Tax Rates'!$A72,'Electricity Tariffs and Consump'!$B$44:$B$75,0),MATCH('Electricity Tax Rates'!D$56,'Electricity Tariffs and Consump'!$C$43:$H$43,0)),"") -> 1.9 | E72: =IFERROR(INDEX('Electricity Tariffs and Consump'!$C$44:$H$75,MATCH('Electricity Tax Rates'!$A72,'Electricity Tariffs and Consump'!$B$44:$B$75,0),MATCH("industry",'Electricity Tariffs and Consump'!$C$43:$H$43,0))/2,"") -> 18.45 | F72: =IFERROR(INDEX('Electricity Tariffs and Consump'!$C$44:$H$75,MATCH('Electricity Tax Rates'!$A72,'Electricity Tariffs and Consump'!$B$44:$B$75,0),MATCH("industry",'Electricity Tariffs and Consump'!$C$43:$H$43,0))/2,"") -> 18.45 | G72: =IFERROR(INDEX('Electricity Tariffs and Consump'!$C$44:$H$75,MATCH('Electricity Tax Rates'!$A72,'Electricity Tariffs and Consump'!$B$44:$B$75,0),MATCH('Electricity Tax Rates'!G$56,'Electricity Tariffs and Consump'!$C$43:$H$43,0)),"") -> 0
... A80: West Bengal | B80: =IFERROR(INDEX('Electricity Tariffs and Consump'!$C$44:$H$75,MATCH('Electricity Tax Rates'!$A80,'Electricity Tariffs and Consump'!$B$44:$B$75,0),MATCH('Electricity Tax Rates'!B$56,'Electricity Tariffs and Consump'!$C$43:$H$43,0)),"") -> 13922.3 | C80: =IFERROR(INDEX('Electricity Tariffs and Consump'!$C$44:$H$75,MATCH('Electricity Tax Rates'!$A80,'Electricity Tariffs and Consump'!$B$44:$B$75,0),MATCH('Electricity Tax Rates'!C$56,'Electricity Tariffs and Consump'!$C$43:$H$43,0)),"") -> 4617.2 | D80: =IFERROR(INDEX('Electricity Tariffs and Consump'!$C$44:$H$75,MATCH('Electricity Tax Rates'!$A80,'Electricity Tariffs and Consump'!$B$44:$B$75,0),MATCH('Electricity Tax Rates'!D$56,'Electricity Tariffs and Consump'!$C$43:$H$43,0)),"") -> 1224.6 | E80: =IFERROR(INDEX('Electricity Tariffs and Consump'!$C$44:$H$75,MATCH('Electricity Tax Rates'!$A80,'Electricity Tariffs and Consump'!$B$44:$B$75,0),MATCH("industry",'Electricity Tariffs and Consump'!$C$43:$H$43,0))/2,"") -> 5278.85 | F80: =IFERROR(INDEX('Electricity Tariffs and Consump'!$C$44:$H$75,MATCH('Electricity Tax Rates'!$A80,'Electricity Tariffs and Consump'!$B$44:$B$75,0),MATCH("industry",'Electricity Tariffs and Consump'!$C$43:$H$43,0))/2,"") -> 5278.85 | G80: =IFERROR(INDEX('Electricity Tariffs and Consump'!$C$44:$H$75,MATCH('Electricity Tax Rates'!$A80,'Electricity Tariffs and Consump'!$B$44:$B$75,0),MATCH('Electricity Tax Rates'!G$56,'Electricity Tariffs and Consump'!$C$43:$H$43,0)),"") -> 1204.9

Sheet Electricity Tariffs and Consump
A1: CONSUMER CATEGORYWISE AVERAGE TARIFF, 2022
A2: SPUs (Paise/Kwh)
A3: Sr. No | B3: State | C3: Domestic | D3: Commercial | E3: Agriculture | F3: Industry | G3: Railway
A4: 1 | B4: Andhra Pradesh | C4: 584 | D4: 1015.7143 | E4: 225 | F4: 754.66667 | G4: 763
A5: 2 | B5: Assam | C5: 662.16667 | D5: 825.85714 | E5: 447 | F5: 650.46154 | G5: 771
A6: 3 | B6: Bihar | C6: 706.08333 | D6: 792.85714 | E6: 570 | F6: 615.85185 | G6: 900
A7: 4 | B7: Chattisgarh | C7: 499.16667 | D7: 444.87 | E7: 540 | F7: 773.85185 | G7: 697
A8: 5 | B8: Delhi | C8: 482.5 | D8: 1090.2857 | E8: 197 | F8: 868.59259 | G8: 836
A9: 6 | B9: Gujarat | C9: 494.66667 | D9: 500.57143 | E9: 90 | F9: 500.81481 | G9: 600
A10: 7 | B10: Haryana | C10: 452.5 | D10: 758.71429 | E10: 10 | F10: 724.24691 | G10: =AVERAGE(831,819,808,797) -> 813.75
A11: 8 | B11: Himachal Pradesh | C11: 494.33333 | D11: 582.71429 | E11: 383 | F11: 561.77778 | G11: 744
A12: 9 | B12: Jammu & Kashmir | C12: 261.83333 | D12: 523 | E12: 74 | F12: 390.37037 | G12: 0
A13: 10 | B13: Jharkhand | C13: 617.08333 | D13: 630 | E13: 510 | F13: 660.85185 | G13: 824
A14: 11 | B14: Karnataka | C14: 738.83333 | D14: 972.28571 | E14: 0 | F14: 764.90123 | G14: 794
A15: 12 | B15: Kerala | C15: 756.5 | D15: 961.85714 | E15: 234 | F15: 623 | G15: 677
A16: 13 | B16: Madhya Pradesh | C16: 788.25 | D16: 776.35714 | E16: 568 | F16: 793.14815 | G16: 762
A17: 14 | B17: Maharashtra | C17: 899.16667 | D17: 1175.8571 | E17: 350 | F17: 869.27778 | G17: 1064
A18: 15 | B18: Meghalaya | C18: 558.16667 | D18: 801.28571 | E18: 341 | F18: 746.66667 | G18: 0
A19: 16 | B19: Orissa | C19: 522.83333 | D19: 754.28571 | E19: 156.25 | F19: 665.07407 | G19: 724
A20: 17 | B20: Punjab | C20: 629.33333 | D20: 767 | E20: 566 | F20: 757.14815 | G20: 963
A21: 18 | B21: Rajasthan | C21: 782.83333 | D21: 1032.4286 | E21: 570 | F21: 538.40741 | G21: 645
A22: 19 | B22: Tamil Nadu | C22: 407.5 | D22: 838.28571 | E22: 0 | F22: 672.01852 | G22: 802
A23: 20 | B23: Uttar Pradesh | C23: 629.91667 | D23: 872.57143 | E23: 450 | F23: 836.78395 | G23: =AVERAGE(1235,1271) -> 1253
A24: 21 | B24: Uttarakhand | C24: 491 | D24: 688.42857 | E24: 208 | F24: 619.11111 | G24: 709
A25: 22 | B25: West Bengal | C25: 785.25 | D25: 908.57143 | E25: 510 | F25: 759.68519 | G25: =AVERAGE(936) -> 936
A26: Average of SPUs 303.89 648.80 138.18 488.22 494.34 351.26 368.27
A27: II. EDs
A28: 1 | B28: Arunachal Pradesh | C28: 400 | D28: 500 | E28: 310 | F28: 354.44444 | G28: 0
A29: 2 | B29: Goa | C29: 276.5 | D29: 501.28571 | E29: 159 | F29: 579.64815 | G29: 0
A30: 3 | B30: Manipur | C30: 666 | D30: 808.57143 | E30: 479 | F30: 573.48148 | G30: 0
A31: 4 | B31: Mizoram | C31: 593.16667 | D31: 755.14286 | E31: 384 | F31: 506 | G31: 0
A32: 5 | B32: Nagaland | C32: 612.16667 | D32: 869.28571 | E32: 310 | F32: 444.7037 | G32: 0
A33: 6 | B33: Pondicherry | C33: 379.16667 | D33: 774.28571 | E33: 0 | F33: 491.48148 | G33: 0
A34: 7 | B34: Sikkim | C34: 281.16667 | D34: 623.42857 | E34: 0 | F34: 483.2963 | G34: 0
A35: 8 | B35: Tripura | C35: 659.16667 | D35: 749.14286 | E35: 393.75 | F35: 140.11111 | G35: 0
A38: Source: CEA
A41: CONSUMER CATEGORYWISE SALE OF POWER - 2021-22 (in MU)
A42: S.No | B42: State | C42: Domestic | D42: Commer- cial | E42: Agri/ irrig. | F42: Industry | G42: Railway traction | H42: Total
A43: I. SPUs | C43: domestic | D43: commercial | E43: agriculture | F43: industry | G43: railway
A44: 1 | B44: Andhra Pradesh | C44: 17933.6 | D44: 4957.5 | E44: 16261.8 | F44: 17412 | G44: 0 | H44: =SUM(C44:G44)+3537.5 -> 60102.4
A45: 2 | B45: Assam | C45: 4329 | D45: 1237 | E45: 65 | F45: 1686 | G45: 0 | H45: =SUM(C45:G45)+105+614 -> 8036
A46: 3 | B46: Bihar | C46: 16738.3 | D46: 2397.6 | E46: 1240.1 | F46: 3002.4 | G46: 116.4 | H46: =SUM(C46:G46)+401.3+151.6 -> 24047.7
A47: 4 | B47: Chhatisgarh | C47: 6767.3 | D47: 927.5 | E47: 2181 | F47: 10394.4 | G47: 1085.3 | H47: =SUM(C47:G47)+442.2+966.1 -> 22763.8
A48: 5 | B48: Delhi | C48: 16674.6 | D48: 6685.5 | E48: 44 | F48: 3433 | G48: 0 | H48: =SUM(C48:G48)+1870.9+391.2+97 -> 29196.2
A49: 6 | B49: Gujarat | C49: 16588.9 | D49: 2613.7 | E49: 20433.4 | F49: 62719.1 | G49: 8 | H49: =SUM(C49:G49)+1006+2196.6 -> 105565.7
A50: 7 | B50: Haryana | C50: 13374.4 | D50: 3119 | E50: 9318.4 | F50: 16932.6 | G50: 71.8 | H50: =SUM(C50:G50)+1364.3+1597.7 -> 45778.2
A51: 8 | B51: Himachal Pradesh | C51: 2457.5 | D51: 621.9 | E51: 85.1 | F51: 5993.3 | G51: 0 | H51: =SUM(C51:G51)+363.5+676.8 -> 10198.1
A52: 9 | B52: Jammu & Kashmir | C52: 4003.6 | D52: 1765.1 | E52: 400.4 | F52: 1498.4 | G52: 0 | H52: =SUM(C52:G52)+260.6+709.9 -> 8638
A53: 10 | B53: Jharkhand | C53: 5886.5 | D53: 894.7 | E53: 255.7 | F53: 2730.4 | G53: 104.4 | H53: =SUM(C53:G53)+22.1 -> 9893.8
A54: 11 | B54: Karnataka | C54: 14101.9 | D54: 5479.8 | E54: 21834.3 | F54: 9981.1 | G54: 0 | H54: =SUM(C54:G54)+5625.5+1070.7 -> 58093.3
A55: 12 | B55: Kerala | C55: 12386.5 | D55: 3885.5 | E55: 387.2 | F55: 6876.1 | G55: 323.1 | H55: =SUM(C55:G55)+440.1+693.1 -> 24991.6
A56: 13 | B56: Madhya Pradesh | C56: 18771.2 | D56: 3734.4 | E56: 25452.5 | F56: 12285.4 | G56: 110.7 | H56: =SUM(C56:G56)+1209.1+2700.1 -> 64263.4
A57: 14 | B57: Maharashtra | C57: 30803.1 | D57: 13915.6 | E57: 28546.9 | F57: 44031.3 | G57: 115.3 | H57: =SUM(C57:G57)+7677.1+278.6 -> 125367.9
A58: 15 | B58: Meghalaya | C58: 510.5 | D58: 103.1 | E58: 0.6 | F58: 203.5 | G58: 0 | H58: =SUM(C58:G58)+608.4+44.7 -> 1470.8
A59: 16 | B59: Orissa | C59: 7709.4 | D59: 1927.3 | E59: 754.1 | F59: 8501.7 | G59: 1043.7 | H59: =SUM(C59:G59)+1054.3+456.2 -> 21446.7
A60: 17 | B60: Punjab | C60: 14305 | D60: 3948 | E60: 11956 | F60: 21804 | G60: 0 | H60: =SUM(C60:G60)+1267+432 -> 53712
A61: 18 | B61: Rajasthan | C61: 13210.6 | D61: 4369.6 | E61: 28802.3 | F61: 17102 | G61: 1.5 | H61: =SUM(C61:G61)+3370.2+2960 -> 69816.2
A62: 19 | B62: Tamil Nadu | C62: 31205 | D62: 8736 | E62: 16501 | F62: 21506 | G62: 1038 | H62: =SUM(C62:G62)+301+4580 -> 83867
A63: 20 | B63: Uttar Pradesh | C63: 46155.5 | D63: 11309.2 | E63: 19798 | F63: 16044.2 | G63: 190 | H63: =SUM(C63:G63)+2940.8+2475.7 -> 98913.4
A64: 21 | B64: Uttrakhand | C64: 3348.2 | D64: 1367.8 | E64: 275.1 | F64: 6532.9 | G64: 46.3 | H64: =SUM(C64:G64)+696.2+172.1 -> 12438.6
A65: 22 | B65: West Bengal | C65: 13922.3 | D65: 4617.2 | E65: 1224.6 | F65: 10557.7 | G65: 1204.9 | H65: =SUM(C65:G65)+1130.3+565.6 -> 33222.6
A66: Sub-total :(I) 143757.8 47709.2 138983.2 197417.7 10911.2 18762.0 46142.8 603683.6
A67: II EDs
A68: 1 | B68: Arunachal Pradesh | C68: 190.7 | D68: 60.9 | E68: 0 | F68: 202.4 | G68: 0 | H68: =SUM(C68:G68)+81.3+8.5 -> 543.8
A69: 2 | B69: Goa | C69: 1303.4 | D69: 614.6 | E69: 34.3 | F69: 2086 | G69: 0 | H69: =SUM(C69:G69)+29.6+17.9 -> 4085.8
A70: 3 | B70: Manipur | C70: 462.2 | D70: 85.1 | E70: 1.9 | F70: 36.9 | G70: 0 | H70: =SUM(C70:G70)+92.1+28.4 -> 706.6
A71: 4 | B71: Mizoram | C71: 337.1 | D71: 63.8 | E71: 0.2 | F71: 12 | G71: 0 | H71: =SUM(C71:G71)+138.7+73.2 -> 625
A72: 5 | B72: Nagaland | C72: 405.4 | D72: 104.1 | E72: 0 | F72: 46.8 | G72: 0 | H72: =SUM(C72:G72)+130.8+28.1 -> 715.2
A73: 6 | B73: Pondicherry | C73: 810.2 | D73: 204.9 | E73: 61.7 | F73: 1598.8 | G73: 0 | H73: =SUM(C73:G73)+79.1+19 -> 2773.7
A74: 7 | B74: Sikkim | C74: 114 | D74: 35 | E74: 0 | F74: 288.8 | G74: 0 | H74: =SUM(C74:G74)+35+0.3 -> 473.1
A75: 8 | B75: Tripura | C75: 622.2 | D75: 72.2 | E75: 40 | F75: 45.2 | G75: 0 | H75: =SUM(C75:G75)+154.8+91.7 -> 1026.1
A76: Sub-total :(II)
A80: Source: Niti Aayog ICED database https://iced.niti.gov.in/energy/electricity/distribution/consumer

Sheet Average electricity tariffs
A1: State | B1: Domestic 6 KW (600 units/month) | C1: Commercial - 30 KW (4500 units/month) | D1: Agriculture - 5 HP (1000 units/Month) | E1: Industry - small/large | F1: Railway traction 12500 KW (2500000 unit/month)
A2: Andhra Pradesh | B2: 708 | C2: 1051 | D2: =(100+350)/2 -> 225 | F2: 763
A3: Assam | B3: 725 | C3: 851 | D3: 447 | F3: 771
A4: Bihar | B4: =(794+664)/2 -> 729 | C4: =(856+751)/2 -> 803.5 | D4: 570 | F4: 900
A5: Chandigarh | B5: 405 | C5: 563 | D5: 260 | F5: 0
A6: Delhi | B6: 567 | C6: 1130 | D6: 197 | F6: 836
A7: Goa | B7: 317 | C7: 519 | D7: 159 | F7: 0
A8: Gujarat | B8: =(469+435)/2 -> 452 | C8: 514 | D8: 90 | F8: 600
A9: Haryana | B9: 531 | C9: 818 | D9: 10 | F9: =(831+819+808+797)/4 -> 813.75
A10: Himachal Pradesh | B10: 508 | C10: 620 | D10: 379 | F10: 744
A11: Jammu and Kashmir | B11: 297 | C11: 571 | D11: 74 | F11: 0
A12: Jharkhand | B12: =(638+578)/2 -> 608 | C12: =(667+608)/2 -> 637.5 | D12: 510 | F12: 824
A13: Karnataka | B13: =(835+783)/2 -> 809 | C13: =(1004+947)/2 -> 975.5 | D13: 0 | F13: 794
A14: Kerala | B14: 940 | C14: 1023 | D14: 234 | F14: 677
A15: Madhya Pradesh | B15: =(862+852)/2 -> 857 | C15: =(823+797)/2 -> 810 | D15: 583 | F15: 762
A16: Maharashtra | B16: 999 | C16: 1524 | D16: 350 | F16: 1064
A17: Manipur | B17: 699 | C17: 818 | D17: 479 | F17: 0
A18: Meghalaya | B18: 600 | C18: 808 | D18: 341 | F18: 0
A19: Orissa | B19: 565 | C19: 774 | D19: 155 | F19: 724
A20: Punjab | B20: 682 | C20: 780 | D20: 566 | F20: 963
A21: Rajasthan | B21: 786 | C21: 1090 | D21: 570 | F21: 645
A22: Tamil Nadu | B22: 533 | C22: 848 | D22: 0 | F22: 802
A23: Uttarakhand | B23: 555 | C23: 753 | D23: 208 | F23: 709
A24: Uttar Pradesh | B24: =(731+586)/2 -> 658.5 | C24: =(1161+623)/2 -> 892 | D24: =(665+235)/2 -> 450 | F24: =(1235+1271)/2 -> 1253
A25: West Bengal | B25: =(840+832)/2 -> 836 | C25: =(931+932)/2 -> 931.5 | D25: =(322+602)/2 -> 462 | F25: 936

Sheet Petroleum Products Consumption
A1: V.13 State-wise Sales of Major Petroleum Products during 2021-22 (P)
A2: ( in '000' Tonnes)
A3: Region/state | B3: Naphtha | C3: LPG | D3: MS | E3: SKO | F3: ATF | G3: HSD | H3: LDO | I3: FO | J3: HHS/LSHS | K3: Lubs/Grs | L3: Bitumen | M3: Others | N3: Total | P3: MS Tax Rate
A4: Region: North
A5: Jammu & Kashmir | B5: 0 | C5: 215.8 | D5: 316.3 | E5: 67.1 | F5: 53.4 | G5: 698 | H5: 1.9 | I5: 4 | J5: 0 | K5: 9.2 | L5: 39.8 | M5: 94.5 | N5: 1500
A6: Punjab | B6: 0 | C6: 1027.1 | D6: 1015.8 | E6: 0.7 | F6: 131.8 | G6: 3113 | H6: 11.5 | I6: 160.7 | J6: 0.9 | K6: 42.3 | L6: 149.7 | M6: 924.5 | N6: 6578
A7: Rajasthan | B7: 2.7 | C7: 1494.1 | D7: 1621.5 | E7: 1.9 | F7: 141.4 | G7: 4452 | H7: 82.2 | I7: 0 | J7: 72.1 | K7: 56.8 | L7: 325.1 | M7: 1991.2 | N7: 10241
A8: Uttar Pradesh | B8: 1.2 | C8: 3855.4 | D8: 3696.1 | E8: 2.5 | F8: 211.1 | G8: 9496 | H8: 99.5 | I8: 0 | J8: 130.7 | K8: 87.4 | L8: 770.3 | M8: 438.8 | N8: 18789
A9: Haryana | B9: 3446.6 | C9: 930.8 | D9: 1113.7 | E9: 0.9 | F9: 27.8 | G9: 4450 | H9: 25.1 | I9: 0 | J9: 77.5 | K9: 54.5 | L9: 279.5 | M9: 139.6 | N9: 10546
A10: Himachal Pradesh | B10: 0 | C10: 194.2 | D10: 272.3 | E10: 5.4 | F10: 4.4 | G10: 777 | H10: 1.3 | I10: 40.8 | J10: 4 | K10: 10.5 | L10: 74.7 | M10: 539.4 | N10: 1924
A11: Uttarakhand | B11: 0 | C11: 321.8 | D11: 338.4 | E11: 3.5 | F11: 15.5 | G11: 700 | H11: 2.9 | I11: 99 | J11: 3.8 | K11: 14.4 | L11: 32.3 | M11: 87.4 | N11: 1619
A12: Chandigarh | B12: 0 | C12: 52.6 | D12: 110 | E12: 0.1 | F12: 26.6 | G12: 171 | H12: 0.5 | I12: 1 | J12: 0 | K12: 2.7 | L12: 0.8 | M12: 3.7 | N12: 369
A13: Delhi | B13: 0 | C13: 771.1 | D13: 693.3 | E13: 0.1 | F13: 1314.4 | G13: 597 | H13: 2.4 | I13: 0 | J13: 0 | K13: 13.6 | L13: 3.5 | M13: 9.6 | N13: 3405
A14: Arunachal Pradesh | B14: 0 | C14: 25.4 | D14: 55.4 | E14: 9.7 | F14: 1.5 | G14: 192 | H14: 0 | I14: 0 | J14: 0 | K14: 0.5 | L14: 17.2 | M14: 0.3 | N14: 302
A15: Assam | B15: 297.4 | C15: 486.3 | D15: 510 | E15: 92.3 | F15: 122.6 | G15: 1123 | H15: 5 | I15: 6.5 | J15: 0 | K15: 37.6 | L15: 20.6 | M15: 221.7 | N15: 2923
A16: Manipur | B16: 0 | C16: 51.9 | D16: 67.5 | E16: 7.9 | F16: 3.3 | G16: 119 | H16: 0.3 | I16: 0.5 | J16: 0 | K16: 0.5 | L16: 2.4 | M16: 0.7 | N16: 254
... A41: Total Consumption | B41: 12709.1 | C41: 28253.4 | D41: 30848.9 | E41: 1493.4 | F41: 5007.1 | G41: 76620 | H41: 1012.6 | I41: 5353.3 | J41: 446.7 | K41: 1544.8 | L41: 5241 | M41: 35702.7 | N41: 204233
A42: Source: Petroleum Planning and Analysis Cell. P: Provisional

Sheet NG Sales
A1: II.17 State-wise Gross & Net Production of Natural Gas in India | I1: (Excerpt for Gross Production & Net Production Values)
A2: (in MMSCM)
A3: State / Utilisation | H3: 2021-22 (P)
A4: -1 | H4: -8
A5: Assam
A6: Gross Production (GP) | H6: 3371.45 | I6: =IF(LEFT(A6,5)="Gross",A5,I5) -> Assam
A7: Flared | I7: =IF(LEFT(A7,5)="Gross",A6,I6) -> Assam
A8: Net Availability | I8: =IF(LEFT(A8,5)="Gross",A7,I7) -> Assam
A9: Internal Use+Losses | I9: =IF(LEFT(A9,5)="Gross",A8,I8) -> Assam
A10: Net Production (Sales) | H10: 2486.43 | I10: =IF(LEFT(A10,5)="Gross",A9,I9) -> Assam
A11: % Flared to GP | I11: =IF(LEFT(A11,5)="Gross",A10,I10) -> Assam
A12: Arunachal Pradesh
A13: Gross Production | H13: 57.7 | I13: =IF(LEFT(A13,5)="Gross",A12,I12) -> Arunachal Pradesh
A14: Flared | I14: =IF(LEFT(A14,5)="Gross",A13,I13) -> Arunachal Pradesh
A15: Net Availability | I15: =IF(LEFT(A15,5)="Gross",A14,I14) -> Arunachal Pradesh
A16: Internal Use+Losses | I16: =IF(LEFT(A16,5)="Gross",A15,I15) -> Arunachal Pradesh
A17: Net Production (Sales) | H17: 0 | I17: =IF(LEFT(A17,5)="Gross",A16,I16) -> Arunachal Pradesh
A18: % Flared to GP | I18: =IF(LEFT(A18,5)="Gross",A17,I17) -> Arunachal Pradesh
A19: Rajasthan
A20: Gross Production | H20: 2618.83 | I20: =IF(LEFT(A20,5)="Gross",A19,I19) -> Rajasthan
A21: Flared | I21: =IF(LEFT(A21,5)="Gross",A20,I20) -> Rajasthan
A22: Net Availability | I22: =IF(LEFT(A22,5)="Gross",A21,I21) -> Rajasthan
A23: Internal Use+Losses | I23: =IF(LEFT(A23,5)="Gross",A22,I22) -> Rajasthan
A24: Net Production (Sales) | H24: 1785.88 | I24: =IF(LEFT(A24,5)="Gross",A23,I23) -> Rajasthan
A25: % Flared to GP | I25: =IF(LEFT(A25,5)="Gross",A24,I24) -> Rajasthan
A26: Gujarat
A27: Gross Production | H27: 1017.29 | I27: =IF(LEFT(A27,5)="Gross",A26,I26) -> Gujarat
A28: Flared | I28: =IF(LEFT(A28,5)="Gross",A27,I27) -> Gujarat
A29: Net Availability | I29: =IF(LEFT(A29,5)="Gross",A28,I28) -> Gujarat
A30: Internal Use+Losses | I30: =IF(LEFT(A30,5)="Gross",A29,I29) -> Gujarat
A31: Net Production (Sales) | H31: 635.05 | I31: =IF(LEFT(A31,5)="Gross",A30,I30) -> Gujarat
A32: % Flared to GP | I32: =IF(LEFT(A32,5)="Gross",A31,I31) -> Gujarat
A33: Tamil Nadu
A34: Gross Production | H34: 1066.52 | I34: =IF(LEFT(A34,5)="Gross",A33,I33) -> Tamil Nadu
A35: Flared | I35: =IF(LEFT(A35,5)="Gross",A34,I34) -> Tamil Nadu
A36: Net Availability | I36: =IF(LEFT(A36,5)="Gross",A35,I35) -> Tamil Nadu
A37: Internal Use+Losses | I37: =IF(LEFT(A37,5)="Gross",A36,I36) -> Tamil Nadu
A38: Net Production (Sales) | H38: 1038.08 | I38: =IF(LEFT(A38,5)="Gross",A37,I37) -> Tamil Nadu
A39: % Flared to GP | I39: =IF(LEFT(A39,5)="Gross",A38,I38) -> Tamil Nadu
A40: Andhra Pradesh
A41: Gross Production | H41: 808.64 | I41: =IF(LEFT(A41,5)="Gross",A40,I40) -> Andhra Pradesh
A42: Flared | I42: =IF(LEFT(A42,5)="Gross",A41,I41) -> Andhra Pradesh
A43: Net Availability | I43: =IF(LEFT(A43,5)="Gross",A42,I42) -> Andhra Pradesh
A44: Internal Use+Losses | I44: =IF(LEFT(A44,5)="Gross",A43,I43) -> Andhra Pradesh
A45: Net Production (Sales) | H45: 743.76 | I45: =IF(LEFT(A45,5)="Gross",A44,I44) -> Andhra Pradesh
A46: % Flared to GP | I46: =IF(LEFT(A46,5)="Gross",A45,I45) -> Andhra Pradesh
A47: Tripura
A48: Gross Production | H48: 1530.78 | I48: =IF(LEFT(A48,5)="Gross",A47,I47) -> Tripura
A49: Flared | I49: =IF(LEFT(A49,5)="Gross",A48,I48) -> Tripura
A50: Net Availability | I50: =IF(LEFT(A50,5)="Gross",A49,I49) -> Tripura
A51: Internal Use+Losses | I51: =IF(LEFT(A51,5)="Gross",A50,I50) -> Tripura
A52: Net Production (Sales) | H52: 1527.47 | I52: =IF(LEFT(A52,5)="Gross",A51,I51) -> Tripura
A53: % Flared to GP | I53: =IF(LEFT(A53,5)="Gross",A52,I52) -> Tripura
A54: West Bengal
A55: Gross Production | H55: 389.25 | I55: =IF(LEFT(A55,5)="Gross",A54,I54) -> West Bengal
A56: Flared | I56: =IF(LEFT(A56,5)="Gross",A55,I55) -> West Bengal
A57: Net Availability | I57: =IF(LEFT(A57,5)="Gross",A56,I56) -> West Bengal
A58: Internal Use+Losses | I58: =IF(LEFT(A58,5)="Gross",A57,I57) -> West Bengal
A59: Net Production (Sales) | H59: 296.51 | I59: =IF(LEFT(A59,5)="Gross",A58,I58) -> West Bengal
A60: % Flared to GP | I60: =IF(LEFT(A60,5)="Gross",A59,I59) -> West Bengal
A61: Madhya Pradesh
A62: Gross Production | H62: 290.1 | I62: =IF(LEFT(A62,5)="Gross",A61,I61) -> Madhya Pradesh
A63: Flared | I63: =IF(LEFT(A63,5)="Gross",A62,I62) -> Madhya Pradesh
A64: Net Availability | I64: =IF(LEFT(A64,5)="Gross",A63,I63) -> Madhya Pradesh
A65: Internal Use+Losses | I65: =IF(LEFT(A65,5)="Gross",A64,I64) -> Madhya Pradesh
A66: Net Production (Sales) | H66: 265.11 | I66: =IF(LEFT(A66,5)="Gross",A65,I65) -> Madhya Pradesh
A67: % Flared to GP | I67: =IF(LEFT(A67,5)="Gross",A66,I66) -> Madhya Pradesh
A68: Jharkhand
A69: Gross Production | H69: 4.04 | I69: =IF(LEFT(A69,5)="Gross",A68,I68) -> Jharkhand
A70: Flared | I70: =IF(LEFT(A70,5)="Gross",A69,I69) -> Jharkhand
A71: Net Availability | I71: =IF(LEFT(A71,5)="Gross",A70,I70) -> Jharkhand
A72: Internal Use+Losses | I72: =IF(LEFT(A72,5)="Gross",A71,I71) -> Jharkhand
A73: Net Production (Sales) | H73: 2.24 | I73: =IF(LEFT(A73,5)="Gross",A72,I72) -> Jharkhand
A74: % Flared to GP | I74: =IF(LEFT(A74,5)="Gross",A73,I73) -> Jharkhand
A75: A. Total Onshore
A76: Gross Production | I76: =IF(LEFT(A76,5)="Gross",A75,I75) -> A. Total Onshore
A77: Flared | I77: =IF(LEFT(A77,5)="Gross",A76,I76) -> A. Total Onshore
A78: Net Availability | I78: =IF(LEFT(A78,5)="Gross",A77,I77) -> A. Total Onshore
A79: Internal Use+Losses | I79: =IF(LEFT(A79,5)="Gross",A78,I78) -> A. Total Onshore
A80: Net Production (Sales) | H80: 8780.52 | I80: =IF(LEFT(A80,5)="Gross",A79,I79) -> A. Total Onshore
A81: % Flared to GP | I81: =IF(LEFT(A81,5)="Gross",A80,I80) -> A. Total Onshore
A82: B. Offshore | I82: =IF(LEFT(A82,5)="Gross",A81,I81) -> A. Total Onshore
A83: Gross Production | I83: =IF(LEFT(A83,5)="Gross",A82,I82) -> B. Offshore
A84: Flared | I84: =IF(LEFT(A84,5)="Gross",A83,I83) -> B. Offshore
A85: Net Availability | I85: =IF(LEFT(A85,5)="Gross",A84,I84) -> B. Offshore
A86: Internal Use+Losses | I86: =IF(LEFT(A86,5)="Gross",A85,I85) -> B. Offshore
A87: Net Production (Sales) | H87: 18593.12 | I87: =IF(LEFT(A87,5)="Gross",A86,I86) -> B. Offshore
A88: % Flared to GP | I88: =IF(LEFT(A88,5)="Gross",A87,I87) -> B. Offshore
A89: Total (A+B) | I89: =IF(LEFT(A89,5)="Gross",A88,I88) -> B. Offshore
A90: Gross Production | I90: =IF(LEFT(A90,5)="Gross",A89,I89) -> Total (A+B)
A91: Flared | I91: =IF(LEFT(A91,5)="Gross",A90,I90) -> Total (A+B)
A92: Net Availability | I92: =IF(LEFT(A92,5)="Gross",A91,I91) -> Total (A+B)
A93: Internal Use+Losses | I93: =IF(LEFT(A93,5)="Gross",A92,I92) -> Total (A+B)
A94: Net Production (Sales) | H94: =H87+H80 -> 27373.64 | I94: =IF(LEFT(A94,5)="Gross",A93,I93) -> Total (A+B)
A95: % Flared to GP | I95: =IF(LEFT(A95,5)="Gross",A94,I94) -> Total (A+B)
A97: Source: Indian Petroleum and Natural Gas Statistics, 2021-22 (MoPNG)
A98: Table II.17, Page 57

Sheet Crude Oil Production
A1: II.12 Production of Crude Oil and Condensate (Financial Year-wise)
A2: State / Region | B2: 2021-22 (P)
A3: -1 | B3: -8
A4: 1. Crude Oil Production (TMT)
A5: (a) Onshore | C5: Tax Rate
A6: Andhra Pradesh | B6: 202 | C6: ='Tax Rates'!B6 -> 0.05 | D6: =B6*C6 -> 10.1
A7: Arunachal Pradesh | B7: 48 | C7: ='Tax Rates'!B7 -> 0.04 | D7: =B7*C7 -> 1.92
A8: Assam | B8: 3988 | C8: ='Tax Rates'!B8 -> 0.05 | D8: =B8*C8 -> 199.4
A9: Gujarat | B9: 4627 | C9: ='Tax Rates'!B14 -> 0.05 | D9: =B9*C9 -> 231.35
A10: Rajasthan | B10: 5887 | C10: ='Tax Rates'!B30 -> 0.05 | D10: =B10*C10 -> 294.35
A11: Tamil Nadu | B11: 367 | C11: ='Tax Rates'!B33 -> 0.05 | D11: =B11*C11 -> 18.35
A12: Total (a) | B12: 15122 | D12: =SUM(D6:D11) -> 755.47
A13: (b) Offshore | D13: =D12/B12 -> 0.049958339 | E13: <-- Weighted tax rate
A14: ONGC | B14: 13619
A15: PSC Regime | B15: 950
A16: Total (b) | B16: 14569

Sheet Coal & Lignite
A1: Coal & Lignite Pit head values (2021-22) | E1: Pit Head Prices of Non-Coking coal (2023)
B2: Coal | C2: Lignite | E2: Prices for Power Utilities (May 2023) (Rs./ton)
A3: Production | B3: 778.21 | C3: 47.37 | E3: Table I | F3: Table II
A4: Pit head value | B4: 1076698.8 | C4: 71267.6 | E4: 1240 | F4: 1490
A5: Value per unit produced | B5: =B4/B3 -> 1383.5582 | C5: =C4/C3 -> 1504.4881 | E5: Avg. (Rs./ton) | F5: =AVERAGE(E4:F4) -> 1365
E6: *Price considered for median grade (G9)
A7: Source: Ministry of Coal, 2021 | E7: Source: Price Notification (May 2023), Coal India Ltd.
A8: Pit head value - coal directory of India 2020-21 | E8: Tables I and II
A10: Scaled Lignite Cost (2021)* | E10: Freight Rates (Coal Transport) (Rs./ton)
A11: =F5*(C5/B5) -> 1484.3078 | B11: Rs./ton | E11: Distance slabs (km)* | F11: Class 145A (Wagon load)
A12: *Scaling is done relative to per unit pit head value of coal in 2018 | E12: 426 - 500 | F12: 1054.7
A14: Price Build-up of Coal & Lignite (2023) (Rs./ton) | E14: Source: Unstarred question - Ministry of parliamentary affairs, coal and mines (https://coal.gov.in/sites/default/files/2022-09/1644383577_1264.PDF)
B15: Coal | C15: Lignite | E15: Rate class 145A (Train Rate)
A16: Pit Head Price | B16: =F5 -> 1365 | C16: =A11 -> 1484.3078
A17: GST (@5%) | B17: =0.05*B16 -> 68.25 | C17: =0.05*C16 -> 74.215392 | E17: *Assumption for average distance transported: "According to Coal India executives, coal travels about 477 km on average from pithead to destination." -- Source: https://economictimes.indiatimes.com/industry/indl-goods/svs/metals-mining/coal-india-looks-to-cut-power-producers-transport-costs/articleshow/61192411.cms?from=mdr
A18: Compensation Cess | B18: 400 | C18: 400
A19: Royalty (@14%-coal;6%-lignite) | B19: =0.14*B16 -> 191.1 | C19: =0.06*C16 -> 89.05847
A20: Transportation | B20: =F12 -> 1054.7 | C20: =F12 -> 1054.7
A21: Transportation tax* (@5%) | B21: =0.05*B20 -> 52.735 | C21: =0.05*C20 -> 52.735
A22: Final Price | B22: =SUM(B16:B21) -> 3131.785 | C22: =SUM(C16:C21) -> 3155.0167
A23: Tax fraction (GST + Cess + Royalty+Transport tax) | B23: =SUM(B17:B19,B21)/B22 -> 0.22737353 | C23: =SUM(C17:C19,C21)/C22 -> 0.19524742
A25: *Transportation tax of 5% under GST: "Under GST, the tax rate on transportation services through rail has been charged at the rate of 5%." -- Source: https://cleartax.in/s/6815

Sheet Fuel Oil & LPG
A1: IV.15: GST Rates Applicable on Select Petroleum Products (As on 01.04.2022)
A2: Product | B2: Central | C2: State/UT | D2: (in %)
A3: Fuel Oil | B3: 9 | C3: 9
A4: LPG - Domestic | B4: 2.5 | C4: 2.5
A5: Source: Indian Petroleum and Natural Gas Statistics, 2021-22 (MoPNG)
A6: Table IV.15, Page 115

Sheet Start Year Taxes
B1: Tax Fraction
A2: hard coal | B2: ='Coal & Lignite'!B23 -> 0.22737353
A3: natural gas | B3: =SUMPRODUCT('Tax Rates'!C6:C38,'Tax Rates'!Z6:Z38)/SUM('Tax Rates'!Z6:Z38) -> 0.1300879
A4: petroleum gasoline | B4: ='Petroleum & Diesel Prices'!B9 -> 0.49449743
A5: petroleum diesel | B5: ='Petroleum & Diesel Prices'!C9 -> 0.4272528
A6: jet fuel | B6: =SUMPRODUCT('Tax Rates'!Y6:Y38,'Tax Rates'!P6:P38)/SUM('Tax Rates'!Y6:Y38) -> 0.17497962
A7: biofuel gasoline | B7: 0.05
A8: biofuel diesel | B8: 0.05
A9: electricity | B9: =SUMPRODUCT('Electricity Tax Rates'!B30:G53,'Electricity Tax Rates'!B57:G80)/SUM('Electricity Tax Rates'!B57:G80) -> 0.063888703
A10: biomass | B10: 0.05
A11: lignite | B11: ='Coal & Lignite'!C23 -> 0.19524742
A12: crude oil | B12: ='Crude Oil Production'!D13 -> 0.049958339
A13: heavy fuel oil | B13: =SUM('Fuel Oil & LPG'!B3:C3)/100 -> 0.18
A14: LPG propane or butane | B14: =SUM('Fuel Oil & LPG'!B4:C4)/100 -> 0.05
A15: municipal solid waste | B15: 0
A16: hydrogen | B16: =B9 -> 0.063888703
A21: Others
A22: Kersoene (PDS SKO) | B22: 1.1 | C22: Rs/liter

Sheet Tax_Share of Price
A1: Share of Price That is Tax (dimensionless) | B1: 2017 | C1: 2018 | D1: 2019 | E1: 2020 | F1: 2021 | G1: 2022 | H1: 2023 | I1: 2024 | J1: 2025 | K1: 2026 | L1: 2027 | M1: 2028 | N1: 2029 | O1: 2030 | P1: 2031 | Q1: 2032 | R1: 2033 | S1: 2034 | T1: 2035 | U1: 2036 | V1: 2037 | W1: 2038 | X1: 2039 | Y1: 2040 | Z1: 2041 | AA1: 2042 | AB1: 2043 | AC1: 2044 | AD1: 2045 | AE1: 2046 | AF1: 2047 | AG1: 2048 | AH1: 2049 | AI1: 2050
A2: electricity | B2: ='Start Year Taxes'!B9 -> 0.063888703 | C2: =B2 -> 0.063888703 | D2: =C2 -> 0.063888703 | E2: =D2 -> 0.063888703 | F2: =E2 -> 0.063888703 | G2: =F2 -> 0.063888703 | H2: =G2 -> 0.063888703 | I2: =H2 -> 0.063888703 | J2: =I2 -> 0.063888703 | ... AI2: =AH2 -> 0.063888703
A3: Coal | B3: ='Start Year Taxes'!B2 -> 0.22737353 | C3: =B3 -> 0.22737353 | D3: =C3 -> 0.22737353 | E3: =D3 -> 0.22737353 | F3: =E3 -> 0.22737353 | G3: =F3 -> 0.22737353 | H3: =G3 -> 0.22737353 | I3: =H3 -> 0.22737353 | J3: =I3 -> 0.22737353 | ... AI3: =AH3 -> 0.22737353
A4: natural gas | B4: ='Start Year Taxes'!B3 -> 0.1300879 | C4: =B4 -> 0.1300879 | D4: =C4 -> 0.1300879 | E4: =D4 -> 0.1300879 | F4: =E4 -> 0.1300879 | G4: =F4 -> 0.1300879 | H4: =G4 -> 0.1300879 | I4: =H4 -> 0.1300879 | J4: =I4 -> 0.1300879 | ... AI4: =AH4 -> 0.1300879
A5: nuclear | B5: =About!$G$59 -> 0 | C5: =B5 -> 0 | D5: =C5 -> 0 | E5: =D5 -> 0 | F5: =E5 -> 0 | G5: =F5 -> 0 | H5: =G5 -> 0 | I5: =H5 -> 0 | J5: =I5 -> 0 | ... AI5: =AH5 -> 0
A6: Hydro | B6: 0 | C6: =B6 -> 0 | D6: =C6 -> 0 | E6: =D6 -> 0 | F6: =E6 -> 0 | G6: =F6 -> 0 | H6: =G6 -> 0 | I6: =H6 -> 0 | J6: =I6 -> 0 | ... AI6: =AH6 -> 0
A7: Wind | B7: 0 | C7: =B7 -> 0 | D7: =C7 -> 0 | E7: =D7 -> 0 | F7: =E7 -> 0 | G7: =F7 -> 0 | H7: =G7 -> 0 | I7: =H7 -> 0 | J7: =I7 -> 0 | ... AI7: =AH7 -> 0
A8: Solar | B8: 0 | C8: =B8 -> 0 | D8: =C8 -> 0 | E8: =D8 -> 0 | F8: =E8 -> 0 | G8: =F8 -> 0 | H8: =G8 -> 0 | I8: =H8 -> 0 | J8: =I8 -> 0 | ... AI8: =AH8 -> 0
A9: biomass | B9: ='Start Year Taxes'!B10 -> 0.05 | C9: =B9 -> 0.05 | D9: =C9 -> 0.05 | E9: =D9 -> 0.05 | F9: =E9 -> 0.05 | G9: =F9 -> 0.05 | H9: =G9 -> 0.05 | I9: =H9 -> 0.05 | J9: =I9 -> 0.05 | ... AI9: =AH9 -> 0.05
A10: petroleum gasoline | B10: ='Start Year Taxes'!B4 -> 0.49449743 | C10: =B10 -> 0.49449743 | D10: =C10 -> 0.49449743 | E10: =D10 -> 0.49449743 | F10: =E10 -> 0.49449743 | G10: =F10 -> 0.49449743 | H10: =G10 -> 0.49449743 | I10: =H10 -> 0.49449743 | J10: =I10 -> 0.49449743 | ... AI10: =AH10 -> 0.49449743
A11: petroleum diesel | B11: ='Start Year Taxes'!B5 -> 0.4272528 | C11: =B11 -> 0.4272528 | D11: =C11 -> 0.4272528 | E11: =D11 -> 0.4272528 | F11: =E11 -> 0.4272528 | G11: =F11 -> 0.4272528 | H11: =G11 -> 0.4272528 | I11: =H11 -> 0.4272528 | J11: =I11 -> 0.4272528 | ... AI11: =AH11 -> 0.4272528
A12: biofuel gasoline | B12: ='Start Year Taxes'!B7 -> 0.05 | C12: =B12 -> 0.05 | D12: =C12 -> 0.05 | E12: =D12 -> 0.05 | F12: =E12 -> 0.05 | G12: =F12 -> 0.05 | H12: =G12 -> 0.05 | I12: =H12 -> 0.05 | J12: =I12 -> 0.05 | ... AI12: =AH12 -> 0.05
A13: biofuel diesel | B13: ='Start Year Taxes'!B8 -> 0.05 | C13: =B13 -> 0.05 | D13: =C13 -> 0.05 | E13: =D13 -> 0.05 | F13: =E13 -> 0.05 | G13: =F13 -> 0.05 | H13: =G13 -> 0.05 | I13: =H13 -> 0.05 | J13: =I13 -> 0.05 | ... AI13: =AH13 -> 0.05
A14: Jet Fuel or Kerosene | B14: ='Start Year Taxes'!B6 -> 0.17497962 | C14: =B14 -> 0.17497962 | D14: =C14 -> 0.17497962 | E14: =D14 -> 0.17497962 | F14: =E14 -> 0.17497962 | G14: =F14 -> 0.17497962 | H14: =G14 -> 0.17497962 | I14: =H14 -> 0.17497962 | J14: =I14 -> 0.17497962 | ... AI14: =AH14 -> 0.17497962
A15: heat | B15: 0 | C15: =B15 -> 0 | D15: =C15 -> 0 | E15: =D15 -> 0 | F15: =E15 -> 0 | G15: =F15 -> 0 | H15: =G15 -> 0 | I15: =H15 -> 0 | J15: =I15 -> 0 | ... AI15: =AH15 -> 0
A16: Geothermal | B16: =0 -> 0 | C16: =B16 -> 0 | D16: =C16 -> 0 | E16: =D16 -> 0 | F16: =E16 -> 0 | G16: =F16 -> 0 | H16: =G16 -> 0 | I16: =H16 -> 0 | J16: =I16 -> 0 | ... AI16: =AH16 -> 0
A17: lignite | B17: ='Start Year Taxes'!B11 -> 0.19524742 | C17: =B17 -> 0.19524742 | D17: =C17 -> 0.19524742 | E17: =D17 -> 0.19524742 | F17: =E17 -> 0.19524742 | G17: =F17 -> 0.19524742 | H17: =G17 -> 0.19524742 | I17: =H17 -> 0.19524742 | J17: =I17 -> 0.19524742 | ... AI17: =AH17 -> 0.19524742
A18: crude oil | B18: ='Start Year Taxes'!B12 -> 0.049958339 | C18: =B18 -> 0.049958339 | D18: =C18 -> 0.049958339 | E18: =D18 -> 0.049958339 | F18: =E18 -> 0.049958339 | G18: =F18 -> 0.049958339 | H18: =G18 -> 0.049958339 | I18: =H18 -> 0.049958339 | J18: =I18 -> 0.049958339 | ... AI18: =AH18 -> 0.049958339
A19: heavy fuel oil | B19: ='Start Year Taxes'!B13 -> 0.18 | C19: =B19 -> 0.18 | D19: =C19 -> 0.18 | E19: =D19 -> 0.18 | F19: =E19 -> 0.18 | G19: =F19 -> 0.18 | H19: =G19 -> 0.18 | I19: =H19 -> 0.18 | J19: =I19 -> 0.18 | ... AI19: =AH19 -> 0.18
A20: LPG propane or butane | B20: ='Start Year Taxes'!B14 -> 0.05 | C20: =B20 -> 0.05 | D20: =C20 -> 0.05 | E20: =D20 -> 0.05 | F20: =E20 -> 0.05 | G20: =F20 -> 0.05 | H20: =G20 -> 0.05 | I20: =H20 -> 0.05 | J20: =I20 -> 0.05 | ... AI20: =AH20 -> 0.05
A21: municipal solid waste | B21: ='Start Year Taxes'!B15 -> 0 | C21: =B21 -> 0 | D21: =C21 -> 0 | E21: =D21 -> 0 | F21: =E21 -> 0 | G21: =F21 -> 0 | H21: =G21 -> 0 | I21: =H21 -> 0 | J21: =I21 -> 0 | ... AI21: =AH21 -> 0
A22: hydrogen | B22: ='Start Year Taxes'!B16 -> 0.063888703 | C22: =B22 -> 0.063888703 | D22: =C22 -> 0.063888703 | E22: =D22 -> 0.063888703 | F22: =E22 -> 0.063888703 | G22: =F22 -> 0.063888703 | H22: =G22 -> 0.063888703 | I22: =H22 -> 0.063888703 | J22: =I22 -> 0.063888703 | ... AI22: =AH22 -> 0.063888703

Sheet Total Fuel Cost>

Sheet Conversion Factors
A1: Currency | E1: Historical Consumer Price Index for All Urban Consumers (CPI-U): U.S. city average, all items, index
A2: India Inflation Rates | B2: See scaling-factors.xlsx for source info | E2: See cpi.xlsx for source info
A3: Year | B3: Rate | C3: Value Indexed to 2012 | E3: Year | F3: Multiply by to get 2012 Dollars
A4: 2010 | B4: 0.0947 | C4: 0.84470209 | E4: 2010............................................................................. . | F4: 1.052913
A5: 2011 | B5: 0.0649 | C5: 0.89952325 | E5: 2011............................................................................. . | F5: 1.0206945
A6: 2012 | B6: 0.1117 | C6: 1 | E6: 2012............................................................................. . | F6: 1
A7: 2013 | B7: 0.0913 | C7: 1.0913 | E7: 2013............................................................................. . | F7: 0.98556386
A8: 2014 | B8: 0.0586 | C8: 1.1552502 | E8: 2014............................................................................. . | F8: 0.96983137
A9: 2015 | B9: 0.0632 | C9: 1.228262 | E9: 2015............................................................................. . | F9: 0.96868157
A10: 2016 | B10: 0.0223 | C10: 1.2556522 | E10: 2016............................................................................. . | F10: 0.95661377
A11: 2017 | B11: 0.04 | C11: 1.3058783 | E11: 2017............................................................................. . | F11: 0.9366596
A12: 2018 | B12: 0.0524 | C12: =C11*(1+B12) -> 1.3743063 | E12: 2018............................................................................. . | F12: 0.91432736
A13: 2019 | B13: 0.0766 | C13: =C12*(1+B13) -> 1.4795782 | E13: 2019............................................................................. . | F13: 0.898
A14: 2020 | B14: 0.0558 | C14: =C13*(1+B14) -> 1.5621387 | E14: 2020............................................................................. . | F14: 0.887
A15: 2021 | B15: 0.0489 | C15: =C14*(1+B15) -> 1.6385273
A17: Rupees per dollar | B17: See scaling-factors.xlsx for source info
A18: 2010 | B18: 44.81
A19: 2011 | B19: 53.26
A20: 2012 | B20: 54.77
A21: 2013 | B21: 61.89
A22: 2014 | B22: 63.33
A23: 2015 | B23: 66.32
A24: 2016 | B24: 67.95
A25: 2017 | B25: 63.92
A26: 2018 | B26: 68.66
A27: 2019 | B27: 70.897
A28: 2020 | B28: 74.225
A29: 2021 | B29: 74.504
A31: Source: Economic Survey (30.01.2023) https://www.indiabudget.gov.in/economicsurvey/doc/stat/tab54.pdf
A33: Fuel-Independent Conversion Factors
A34: liters per barrel | B34: 158.9873
A35: BTU/kcal | B35: 3.96567
A36: BTU/kWh (unit conversion, not a heat rate) | B36: 3412.14
A38: Energy in Biomass
A39: Wood wastes | B39: =AVERAGE(2500,3850) -> 3175 | C39: kcal/kg
A40: Cowdung | B40: =AVERAGE(3140,3290) -> 3215 | C40: kcal/kg
A41: Average of biomass fuels | B41: =AVERAGE(B39:B40) -> 3195 | C41: kcal/kg
B42: 3.96567 | C42: BTU/kcal
B43: =B41*B42 -> 12670.316 | C43: BTU/kg
B44: =B43*1000 -> 12670316 | C44: BTU/ton
A46: Energy in Jet Fuel / Kerosene
B47: 5670000 | C47: BTU/barrel
B48: =B47/B34 -> 35663.226 | C48: BTU/liter
A50: Energy in Petroleum Gasoline
B51: 10700 | C51: kcal/kg
B52: 8.53 | C52: barrels/ton
B53: =B51*1000/B52 -> 1254396.2 | C53: kcal/barrel
B54: =B53*B35 -> 4974521.6 | C54: BTU/barrel
B55: =B54/B34 -> 31288.798 | C55: BTU/liter
A57: Energy in Petroleum Diesel
B58: 5.817 | C58: million BTU/barrel
B59: =B58/B34 -> 0.036587828 | C59: million BTU/l
B60: =B59*10^6 -> 36587.828 | C60: BTU/l
A62: Energy in LPG
B63: 14.2 | C63: kg/cylinder
B64: 11300 | C64: kcal/kg
B65: =B63*B64 -> 160460 | C65: kcal/cylinder
B66: =B65*B35 -> 636331.41 | C66: BTU/cylinder
A68: Natural Gas
B69: 36 | C69: trillion BTU / billion cubic m
B70: =B69*10^6 -> 36000000 | C70: BTU / thousand cubic m
A72: Coal
B73: 6500 | C73: kcal/kg
B74: =B35*B73 -> 25776.855 | C74: BTU/kg
B75: =B74*1000 -> 25776855 | C75: BTU/ton
A77: Crude Oil
B78: 5.8 | C78: million BTU / bbl
B79: =B78*10^6 -> 5800000 | C79: BTU / bbl
A81: Ethanol - 100%
A82: LHV | B82: 76330 | C82: BTU / gal | D82: https://afdc.energy.gov/fuels/fuel_comparison_chart.pdf
A83: HHV | B83: 84530 | C83: BTU / gal
A84: Average | B84: =AVERAGE(B82:B83) -> 80430 | C84: BTU / gal
B85: 3.78541 | C85: litre/gal
B86: =B84/B85 -> 21247.368 | C86: BTU/l

Sheet AEO Table 73
B1: ref2021.d113020a | C1: 2020 | D1: 2021 | E1: 2022 | F1: 2023 | G1: 2024 | H1: 2025 | I1: 2026 | J1: 2027 | K1: 2028 | L1: 2029 | M1: 2030 | N1: 2031 | O1: 2032 | P1: 2033 | Q1: 2034 | R1: 2035 | S1: 2036 | T1: 2037 | U1: 2038 | V1: 2039 | W1: 2040 | X1: 2041 | Y1: 2042 | Z1: 2043 | AA1: 2044 | AB1: 2045 | AC1: 2046 | AD1: 2047 | AE1: 2048 | AF1: 2049 | AG1: 2050
C3: Report | D3: Annual Energy Outlook 2021
C4: Scenario | D4: ref2021 | G4: Reference case
C5: Datekey | D5: d113020a
C6: Release Date | E6: January 2021
A10: CNV000 | B10: 71. Conversion Factors | AH10: Compound
B11: (from physical units to million Btu) | AH11: Growth
AH12: 2020-2050
C13: 2020 | D13: 2021 | E13: 2022 | F13: 2023 | G13: 2024 | H13: 2025 | I13: 2026 | J13: 2027 | K13: 2028 | L13: 2029 | M13: 2030 | N13: 2031 | O13: 2032 | P13: 2033 | Q13: 2034 | R13: 2035 | S13: 2036 | T13: 2037 | U13: 2038 | V13: 2039 | W13: 2040 | X13: 2041 | Y13: 2042 | Z13: 2043 | AA13: 2044 | AB13: 2045 | AC13: 2046 | AD13: 2047 | AE13: 2048 | AF13: 2049 | AG13: 2050 | AH13: (percent)
B14: Petroleum and Other Liquids
B15: (million Btu per barrel)
A16: CNV000:aa_AsphaltandRoa | B16: Asphalt and Road Oil | C16: 6.636 | D16: 6.636 | E16: 6.636 | F16: 6.636 | G16: 6.636 | H16: 6.636 | I16: 6.636 | J16: 6.636 | K16: 6.636 | L16: 6.636 | M16: 6.636 | N16: 6.636 | O16: 6.636 | P16: 6.636 | Q16: 6.636 | R16: 6.636 | S16: 6.636 | T16: 6.636 | U16: 6.636 | V16: 6.636 | W16: 6.636 | X16: 6.636 | Y16: 6.636 | Z16: 6.636 | AA16: 6.636 | AB16: 6.636 | AC16: 6.636 | AD16: 6.636 | AE16: 6.636 | AF16: 6.636 | AG16: 6.636 | AH16: 0
A17: CNV000:aa_AviationGasol | B17: Aviation Gasoline | C17: 5.048 | D17: 5.048 | E17: 5.048 | F17: 5.048 | G17: 5.048 | H17: 5.048 | I17: 5.048 | J17: 5.048 | K17: 5.048 | L17: 5.048 | M17: 5.048 | N17: 5.048 | O17: 5.048 | P17: 5.048 | Q17: 5.048 | R17: 5.048 | S17: 5.048 | T17: 5.048 | U17: 5.048 | V17: 5.048 | W17: 5.048 | X17: 5.048 | Y17: 5.048 | Z17: 5.048 | AA17: 5.048 | AB17: 5.048 | AC17: 5.048 | AD17: 5.048 | AE17: 5.048 | AF17: 5.048 | AG17: 5.048 | AH17: 0
A18: CNV000:ea_Biodiesel | B18: Biodiesel | C18: 5.359 | D18: 5.359 | E18: 5.359 | F18: 5.359 | G18: 5.359 | H18: 5.359 | I18: 5.359 | J18: 5.359 | K18: 5.359 | L18: 5.359 | M18: 5.359 | N18: 5.359 | O18: 5.359 | P18: 5.359 | Q18: 5.359 | R18: 5.359 | S18: 5.359 | T18: 5.359 | U18: 5.359 | V18: 5.359 | W18: 5.359 | X18: 5.359 | Y18: 5.359 | Z18: 5.359 | AA18: 5.359 | AB18: 5.359 | AC18: 5.359 | AD18: 5.359 | AE18: 5.359 | AF18: 5.359 | AG18: 5.359 | AH18: 0
A19: CNV000:aa_Distillate | B19: Distillate Fuel Oil | C19: 5.825 | D19: 5.825 | E19: 5.825 | F19: 5.825 | G19: 5.825 | H19: 5.825 | I19: 5.825 | J19: 5.825 | K19: 5.825 | L19: 5.825 | M19: 5.825 | N19: 5.825 | O19: 5.825 | P19: 5.825 | Q19: 5.825 | R19: 5.825 | S19: 5.825 | T19: 5.825 | U19: 5.825 | V19: 5.825 | W19: 5.825 | X19: 5.825 | Y19: 5.825 | Z19: 5.825 | AA19: 5.825 | AB19: 5.825 | AC19: 5.825 | AD19: 5.825 | AE19: 5.825 | AF19: 5.825 | AG19: 5.825 | AH19: 0
A20: CNV000:aa_Residential | B20: Residential | C20: 5.772225 | D20: 5.770434 | E20: 5.769468 | F20: 5.769597 | G20: 5.770083 | H20: 5.769742 | I20: 5.769996 | J20: 5.770608 | K20: 5.769846 | L20: 5.770197 | M20: 5.76971 | N20: 5.7698 | O20: 5.769487 | P20: 5.769598 | Q20: 5.769436 | R20: 5.769614 | S20: 5.770103 | T20: 5.769971 | U20: 5.770141 | V20: 5.769869 | W20: 5.770143 | X20: 5.770298 | Y20: 5.770511 | Z20: 5.770051 | AA20: 5.769538 | AB20: 5.769256 | AC20: 5.770041 | AD20: 5.769023 | AE20: 5.768785 | AF20: 5.768611 | AG20: 5.768018 | AH20: -2.4e-05
A21: CNV000:aa_Commercial | B21: Commercial | C21: 5.772225 | D21: 5.770434 | E21: 5.769468 | F21: 5.769597 | G21: 5.770083 | H21: 5.769742 | I21: 5.769996 | J21: 5.770608 | K21: 5.769846 | L21: 5.770197 | M21: 5.76971 | N21: 5.7698 | O21: 5.769487 | P21: 5.769598 | Q21: 5.769436 | R21: 5.769614 | S21: 5.770103 | T21: 5.769971 | U21: 5.770141 | V21: 5.769869 | W21: 5.770143 | X21: 5.770298 | Y21: 5.770511 | Z21: 5.770051 | AA21: 5.769538 | AB21: 5.769256 | AC21: 5.770041 | AD21: 5.769023 | AE21: 5.768785 | AF21: 5.768611 | AG21: 5.768018 | AH21: -2.4e-05
A22: CNV000:aa_Transportatio | B22: Transportation | C22: 5.772225 | D22: 5.770434 | E22: 5.769468 | F22: 5.769597 | G22: 5.770083 | H22: 5.769742 | I22: 5.769996 | J22: 5.770608 | K22: 5.769846 | L22: 5.770197 | M22: 5.76971 | N22: 5.7698 | O22: 5.769487 | P22: 5.769598 | Q22: 5.769436 | R22: 5.769614 | S22: 5.770103 | T22: 5.769971 | U22: 5.770141 | V22: 5.769869 | W22: 5.770143 | X22: 5.770298 | Y22: 5.770511 | Z22: 5.770051 | AA22: 5.769538 | AB22: 5.769256 | AC22: 5.770041 | AD22: 5.769023 | AE22: 5.768785 | AF22: 5.768611 | AG22: 5.768018 | AH22: -2.4e-05
A23: CNV000:aa_Industrial | B23: Industrial | C23: 5.772225 | D23: 5.770434 | E23: 5.769468 | F23: 5.769597 | G23: 5.770083 | H23: 5.769742 | I23: 5.769996 | J23: 5.770608 | K23: 5.769846 | L23: 5.770197 | M23: 5.76971 | N23: 5.7698 | O23: 5.769487 | P23: 5.769598 | Q23: 5.769436 | R23: 5.769614 | S23: 5.770103 | T23: 5.769971 | U23: 5.770141 | V23: 5.769869 | W23: 5.770143 | X23: 5.770298 | Y23: 5.770511 | Z23: 5.770051 | AA23: 5.769538 | AB23: 5.769256 | AC23: 5.770041 | AD23: 5.769023 | AE23: 5.768785 | AF23: 5.768611 | AG23: 5.768018 | AH23: -2.4e-05
A24: CNV000:aa_ElectricPower | B24: Electric Power | C24: 5.772225 | D24: 5.770434 | E24: 5.769468 | F24: 5.769597 | G24: 5.770083 | H24: 5.769742 | I24: 5.769996 | J24: 5.770608 | K24: 5.769846 | L24: 5.770197 | M24: 5.76971 | N24: 5.7698 | O24: 5.769487 | P24: 5.769598 | Q24: 5.769436 | R24: 5.769614 | S24: 5.770103 | T24: 5.769971 | U24: 5.770141 | V24: 5.769869 | W24: 5.770143 | X24: 5.770298 | Y24: 5.770511 | Z24: 5.770051 | AA24: 5.769538 | AB24: 5.769256 | AC24: 5.770041 | AD24: 5.769023 | AE24: 5.768785 | AF24: 5.768611 | AG24: 5.768018 | AH24: -2.4e-05
A25: CNV000:aa_TotalDistilla | B25: Total Distillate | C25: 5.772226 | D25: 5.770434 | E25: 5.769468 | F25: 5.769597 | G25: 5.770083 | H25: 5.769742 | I25: 5.769997 | J25: 5.770607 | K25: 5.769845 | L25: 5.770196 | M25: 5.76971 | N25: 5.7698 | O25: 5.769487 | P25: 5.769598 | Q25: 5.769436 | R25: 5.769614 | S25: 5.770103 | T25: 5.769971 | U25: 5.770141 | V25: 5.769869 | W25: 5.770143 | X25: 5.770298 | Y25: 5.770511 | Z25: 5.770051 | AA25: 5.769537 | AB25: 5.769256 | AC25: 5.770042 | AD25: 5.769023 | AE25: 5.768785 | AF25: 5.768611 | AG25: 5.768018 | AH25: -2.4e-05
A26: CNV000:aa_DistLowSulf | B26: Distillate Fuel Oil - Low Sulfur Diesel | C26: 5.817 | D26: 5.817 | E26: 5.817 | F26: 5.817 | G26: 5.817 | H26: 5.817 | I26: 5.817 | J26: 5.817 | K26: 5.817 | L26: 5.817 | M26: 5.817 | N26: 5.817 | O26: 5.817 | P26: 5.817 | Q26: 5.817 | R26: 5.817 | S26: 5.817 | T26: 5.817 | U26: 5.817 | V26: 5.817 | W26: 5.817 | X26: 5.817 | Y26: 5.817 | Z26: 5.817 | AA26: 5.817 | AB26: 5.817 | AC26: 5.817 | AD26: 5.817 | AE26: 5.817 | AF26: 5.817 | AG26: 5.817 | AH26: 0
A27: CNV000:aa_DistUltraLow | B27: Distillate Fuel Oil - Ultra Low Sulfur Diesel | C27: 5.77 | D27: 5.77 | E27: 5.77 | F27: 5.77 | G27: 5.77 | H27: 5.77 | I27: 5.77 | J27: 5.77 | K27: 5.77 | L27: 5.77 | M27: 5.77 | N27: 5.77 | O27: 5.77 | P27: 5.77 | Q27: 5.77 | R27: 5.77 | S27: 5.77 | T27: 5.77 | U27: 5.77 | V27: 5.77 | W27: 5.77 | X27: 5.77 | Y27: 5.77 | Z27: 5.77 | AA27: 5.77 | AB27: 5.77 | AC27: 5.77 | AD27: 5.77 | AE27: 5.77 | AF27: 5.77 | AG27: 5.77 | AH27: 0
... A46: CNV000:aa_Exports | B46: Petroleum Product Exports | C46: 5.208902 | D46: 5.233259 | E46: 5.248022 | F46: 5.255337 | G46: 5.284336 | H46: 5.284585 | I46: 5.293683 | J46: 5.295779 | K46: 5.304686 | L46: 5.305382 | M46: 5.288252 | N46: 5.307133 | O46: 5.317582 | P46: 5.324971 | Q46: 5.329218 | R46: 5.340077 | S46: 5.341102 | T46: 5.350363 | U46: 5.351419 | V46: 5.347663 | W46: 5.341086 | X46: 5.342655 | Y46: 5.341298 | Z46: 5.333441 | AA46: 5.32583 | AB46: 5.325848 | AC46: 5.324336 | AD46: 5.331812 | AE46: 5.337536 | AF46: 5.337165 | AG46: 5.341957 | AH46: 0.000841
B47: Crude Oil
A48: CNV000:aa_CrudeOilProdu | B48: Production | C48: 5.701258 | D48: 5.705287 | E48: 5.698242 | F48: 5.690741 | G48: 5.686217 | H48: 5.680397 | I48: 5.679482 | J48: 5.680235 | K48: 5.682467 | L48: 5.683152 | M48: 5.685532 | N48: 5.686835 | O48: 5.686281 | P48: 5.688497 | Q48: 5.689099 | R48: 5.687949 | S48: 5.684894 | T48: 5.68398 | U48: 5.68161 | V48: 5.680455 | W48: 5.678696 | X48: 5.677988 | Y48: 5.678402 | Z48: 5.678963 | AA48: 5.678901 | AB48: 5.675479 | AC48: 5.677872 | AD48: 5.678594 | AE48: 5.676446 | AF48: 5.673857 | AG48: 5.669861 | AH48: -0.000184
A49: CNV000:aa_CrudeOilImpor | B49: Imports | C49: 6.085091 | D49: 6.066456 | E49: 6.068346 | F49: 6.068904 | G49: 6.068149 | H49: 6.070602 | I49: 6.087798 | J49: 6.087098 | K49: 6.09395 | L49: 6.091728 | M49: 6.087254 | N49: 6.093457 | O49: 6.103011 | P49: 6.10403 | Q49: 6.110426 | R49: 6.110364 | S49: 6.113935 | T49: 6.127923 | U49: 6.126749 | V49: 6.126231 | W49: 6.121337 | X49: 6.12137 | Y49: 6.118534 | Z49: 6.108738 | AA49: 6.108547 | AB49: 6.110272 | AC49: 6.10705 | AD49: 6.107703 | AE49: 6.109305 | AF49: 6.10804 | AG49: 6.116878 | AH49: 0.000174
A50: CNV000:aa_CrudeOilExpor | B50: Exports | C50: 5.586683 | D50: 5.596693 | E50: 5.596242 | F50: 5.595907 | G50: 5.595245 | H50: 5.595181 | I50: 5.584603 | J50: 5.587386 | K50: 5.595116 | L50: 5.586189 | M50: 5.59499 | N50: 5.585876 | O50: 5.594877 | P50: 5.59394 | Q50: 5.590277 | R50: 5.591412 | S50: 5.590872 | T50: 5.594198 | U50: 5.594143 | V50: 5.588477 | W50: 5.593933 | X50: 5.593874 | Y50: 5.593719 | Z50: 5.593579 | AA50: 5.597045 | AB50: 5.59432 | AC50: 5.593446 | AD50: 5.593292 | AE50: 5.593154 | AF50: 5.593037 | AG50: 5.592913 | AH50: 3.7e-05
A51: CNV000:aa_NaturalGasPla | B51: Natural Gas Plant Liquids | C51: 3.588495 | D51: 3.53136 | E51: 3.523382 | F51: 3.549014 | G51: 3.544739 | H51: 3.540329 | I51: 3.539303 | J51: 3.538394 | K51: 3.537459 | L51: 3.535216 | M51: 3.533556 | N51: 3.532846 | O51: 3.532958 | P51: 3.533101 | Q51: 3.532566 | R51: 3.531256 | S51: 3.530272 | T51: 3.529652 | U51: 3.528985 | V51: 3.52799 | W51: 3.527618 | X51: 3.528339 | Y51: 3.528407 | Z51: 3.529173 | AA51: 3.529438 | AB51: 3.528521 | AC51: 3.529552 | AD51: 3.529862 | AE51: 3.52899 | AF51: 3.527624 | AG51: 3.525624 | AH51: -0.000589
B53: Natural Gas (thousand Btu per cubic foot)
A54: CNV000:ba_Consumption | B54: Consumption | C54: 1.037 | D54: 1.037 | E54: 1.037 | F54: 1.037 | G54: 1.037 | H54: 1.037 | I54: 1.037 | J54: 1.037 | K54: 1.037 | L54: 1.037 | M54: 1.037 | N54: 1.037 | O54: 1.037 | P54: 1.037 | Q54: 1.037 | R54: 1.037 | S54: 1.037 | T54: 1.037 | U54: 1.037 | V54: 1.037 | W54: 1.037 | X54: 1.037 | Y54: 1.037 | Z54: 1.037 | AA54: 1.037 | AB54: 1.037 | AC54: 1.037 | AD54: 1.037 | AE54: 1.037 | AF54: 1.037 | AG54: 1.037 | AH54: 0
A55: CNV000:ba_Utility | B55: Electric Power Sector 2/ | C55: 1.034 | D55: 1.034 | E55: 1.034 | F55: 1.034 | G55: 1.034 | H55: 1.034 | I55: 1.034 | J55: 1.034 | K55: 1.034 | L55: 1.034 | M55: 1.034 | N55: 1.034 | O55: 1.034 | P55: 1.034 | Q55: 1.034 | R55: 1.034 | S55: 1.034 | T55: 1.034 | U55: 1.034 | V55: 1.034 | W55: 1.034 | X55: 1.034 | Y55: 1.034 | Z55: 1.034 | AA55: 1.034 | AB55: 1.034 | AC55: 1.034 | AD55: 1.034 | AE55: 1.034 | AF55: 1.034 | AG55: 1.034 | AH55: 0
A56: CNV000:ba_Nonutility | B56: End-use Sector | C56: 1.039 | D56: 1.039 | E56: 1.039 | F56: 1.039 | G56: 1.039 | H56: 1.039 | I56: 1.039 | J56: 1.039 | K56: 1.039 | L56: 1.039 | M56: 1.039 | N56: 1.039 | O56: 1.039 | P56: 1.039 | Q56: 1.039 | R56: 1.039 | S56: 1.039 | T56: 1.039 | U56: 1.039 | V56: 1.039 | W56: 1.039 | X56: 1.039 | Y56: 1.039 | Z56: 1.039 | AA56: 1.039 | AB56: 1.039 | AC56: 1.039 | AD56: 1.039 | AE56: 1.039 | AF56: 1.039 | AG56: 1.039 | AH56: 0
A57: CNV000:ba_Production | B57: Production | C57: 1.037 | D57: 1.037 | E57: 1.037 | F57: 1.037 | G57: 1.037 | H57: 1.037 | I57: 1.037 | J57: 1.037 | K57: 1.037 | L57: 1.037 | M57: 1.037 | N57: 1.037 | O57: 1.037 | P57: 1.037 | Q57: 1.037 | R57: 1.037 | S57: 1.037 | T57: 1.037 | U57: 1.037 | V57: 1.037 | W57: 1.037 | X57: 1.037 | Y57: 1.037 | Z57: 1.037 | AA57: 1.037 | AB57: 1.037 | AC57: 1.037 | AD57: 1.037 | AE57: 1.037 | AF57: 1.037 | AG57: 1.037 | AH57: 0
A58: CNV000:ba_Imports | B58: Imports | C58: 1.025 | D58: 1.025 | E58: 1.025 | F58: 1.025 | G58: 1.025 | H58: 1.025 | I58: 1.025 | J58: 1.025 | K58: 1.025 | L58: 1.025 | M58: 1.025 | N58: 1.025 | O58: 1.025 | P58: 1.025 | Q58: 1.025 | R58: 1.025 | S58: 1.025 | T58: 1.025 | U58: 1.025 | V58: 1.025 | W58: 1.025 | X58: 1.025 | Y58: 1.025 | Z58: 1.025 | AA58: 1.025 | AB58: 1.025 | AC58: 1.025 | AD58: 1.025 | AE58: 1.025 | AF58: 1.025 | AG58: 1.025 | AH58: 0
A59: CNV000:ba_Exports | B59: Exports | C59: 1.009 | D59: 1.009 | E59: 1.009 | F59: 1.009 | G59: 1.009 | H59: 1.009 | I59: 1.009 | J59: 1.009 | K59: 1.009 | L59: 1.009 | M59: 1.009 | N59: 1.009 | O59: 1.009 | P59: 1.009 | Q59: 1.009 | R59: 1.009 | S59: 1.009 | T59: 1.009 | U59: 1.009 | V59: 1.009 | W59: 1.009 | X59: 1.009 | Y59: 1.009 | Z59: 1.009 | AA59: 1.009 | AB59: 1.009 | AC59: 1.009 | AD59: 1.009 | AE59: 1.009 | AF59: 1.009 | AG59: 1.009 | AH59: 0
A60: CNV000:ba_CompressedNat | B60: Compressed/Liquefied Natural Gas | C60: 0.96 | D60: 0.96 | E60: 0.96 | F60: 0.96 | G60: 0.96 | H60: 0.96 | I60: 0.96 | J60: 0.96 | K60: 0.96 | L60: 0.96 | M60: 0.96 | N60: 0.96 | O60: 0.96 | P60: 0.96 | Q60: 0.96 | R60: 0.96 | S60: 0.96 | T60: 0.96 | U60: 0.96 | V60: 0.96 | W60: 0.96 | X60: 0.96 | Y60: 0.96 | Z60: 0.96 | AA60: 0.96 | AB60: 0.96 | AC60: 0.96 | AD60: 0.96 | AE60: 0.96 | AF60: 0.96 | AG60: 0.96 | AH60: 0
B62: Coal (million Btu per short ton)
A63: CNV000:ca_Production | B63: Production | C63: 20.313612 | D63: 20.251499 | E63: 20.463696 | F63: 20.630898 | G63: 20.58532 | H63: 20.620371 | I63: 20.558367 | J63: 20.551445 | K63: 20.452055 | L63: 20.355701 | M63: 20.289701 | N63: 20.316072 | O63: 20.341093 | P63: 20.369787 | Q63: 20.349621 | R63: 20.382479 | S63: 20.405159 | T63: 20.455118 | U63: 20.57431 | V63: 20.58498 | W63: 20.617809 | X63: 20.606735 | Y63: 20.642296 | Z63: 20.684587 | AA63: 20.690783 | AB63: 20.781717 | AC63: 20.824453 | AD63: 20.813873 | AE63: 20.786306 | AF63: 20.831282 | AG63: 20.832466 | AH63: 0.000841
A64: CNV000:ca_EastoftheMiss | B64: East of the Mississippi | C64: 25.162447 | D64: 25.061907 | E64: 24.844831 | F64: 25.003353 | G64: 25.014917 | H64: 25.161196 | I64: 25.144636 | J64: 25.18247 | K64: 25.190441 | L64: 25.210474 | M64: 25.271479 | N64: 25.263571 | O64: 25.235905 | P64: 25.426609 | Q64: 25.42605 | R64: 25.406256 | S64: 25.35174 | T64: 25.317278 | U64: 25.262371 | V64: 25.204082 | W64: 25.170408 | X64: 25.136366 | Y64: 25.124195 | Z64: 25.10177 | AA64: 25.08288 | AB64: 25.03639 | AC64: 25.004837 | AD64: 24.996422 | AE64: 24.994413 | AF64: 25.032789 | AG64: 25.018826 | AH64: -0.000191
A65: CNV000:ca_WestoftheMiss | B65: West of the Mississippi | C65: 17.310602 | D65: 17.309647 | E65: 17.211004 | F65: 17.263588 | G65: 17.337936 | H65: 17.308016 | I65: 17.259657 | J65: 17.224226 | K65: 17.166725 | L65: 17.176584 | M65: 17.131996 | N65: 17.134941 | O65: 17.114252 | P65: 17.09199 | Q65: 17.09087 | R65: 17.088018 | S65: 17.077797 | T65: 17.051991 | U65: 17.025953 | V65: 17.01372 | W65: 16.977299 | X65: 16.978853 | Y65: 17.006622 | Z65: 17.016672 | AA65: 17.028193 | AB65: 17.032866 | AC65: 17.039537 | AD65: 17.015118 | AE65: 16.990679 | AF65: 16.993908 | AG65: 16.98835 | AH65: -0.000626
A66: CNV000:ca_Consumption | B66: Consumption | C66: 19.465235 | D66: 19.47703 | E66: 19.633654 | F66: 19.748119 | G66: 19.604624 | H66: 19.514042 | I66: 19.460508 | J66: 19.416695 | K66: 19.301138 | L66: 19.199217 | M66: 19.119923 | N66: 19.131233 | O66: 19.13302 | P66: 19.181492 | Q66: 19.162058 | R66: 19.166834 | S66: 19.206079 | T66: 19.242796 | U66: 19.352158 | V66: 19.394049 | W66: 19.422735 | X66: 19.419495 | Y66: 19.465462 | Z66: 19.508917 | AA66: 19.511177 | AB66: 19.602798 | AC66: 19.653093 | AD66: 19.640366 | AE66: 19.61727 | AF66: 19.648813 | AG66: 19.641287 | AH66: 0.0003
A67: CNV000:ca_Residentialan | B67: Commercial and Institutional | C67: 19.07375 | D67: 19.023113 | E67: 19.023102 | F67: 19.320454 | G67: 19.262178 | H67: 19.226744 | I67: 19.203001 | J67: 19.198051 | K67: 19.173183 | L67: 19.142059 | M67: 19.111967 | N67: 19.063097 | O67: 19.027267 | P67: 18.988686 | Q67: 18.945419 | R67: 18.899261 | S67: 18.854065 | T67: 18.823059 | U67: 18.801371 | V67: 18.77677 | W67: 18.747007 | X67: 18.720158 | Y67: 18.696239 | Z67: 18.664991 | AA67: 18.637045 | AB67: 18.618738 | AC67: 18.595921 | AD67: 18.562662 | AE67: 18.520023 | AF67: 18.478739 | AG67: 18.440039 | AH67: -0.001126
A68: CNV000:ca_Industrial | B68: Industrial 3/ | C68: 19.047443 | D68: 19.29319 | E68: 19.406574 | F68: 19.401604 | G68: 19.396521 | H68: 19.387011 | I68: 19.386452 | J68: 19.379221 | K68: 19.369596 | L68: 19.360327 | M68: 19.351662 | N68: 19.3437 | O68: 19.335772 | P68: 19.328518 | Q68: 19.320198 | R68: 19.320457 | S68: 19.30393 | T68: 19.276167 | U68: 19.278488 | V68: 19.280405 | W68: 19.310587 | X68: 19.309147 | Y68: 19.301651 | Z68: 19.294476 | AA68: 19.266329 | AB68: 19.271349 | AC68: 19.274885 | AD68: 19.282909 | AE68: 19.308189 | AF68: 19.31518 | AG68: 19.319613 | AH68: 0.000473
A69: CNV000:ca_Coking | B69: Coking | C69: 28.46183 | D69: 28.444407 | E69: 28.425611 | F69: 28.430611 | G69: 28.426397 | H69: 28.410816 | I69: 28.410643 | J69: 28.404917 | K69: 28.393972 | L69: 28.382809 | M69: 28.384378 | N69: 28.385469 | O69: 28.383551 | P69: 28.379475 | Q69: 28.381683 | R69: 28.384056 | S69: 28.383585 | T69: 28.384052 | U69: 28.38829 | V69: 28.391367 | W69: 28.388498 | X69: 28.391012 | Y69: 28.398878 | Z69: 28.404837 | AA69: 28.404747 | AB69: 28.404837 | AC69: 28.405666 | AD69: 28.405745 | AE69: 28.408457 | AF69: 28.40884 | AG69: 28.414181 | AH69: -5.6e-05
A70: CNV000:ca_ElectricPower | B70: Electric Power 2/ | C70: 18.96517 | D70: 19.123833 | E70: 19.29612 | F70: 19.282087 | G70: 19.073906 | H70: 18.931747 | I70: 18.8878 | J70: 18.832237 | K70: 18.730505 | L70: 18.639585 | M70: 18.542288 | N70: 18.545713 | O70: 18.545574 | P70: 18.609898 | Q70: 18.586058 | R70: 18.576267 | S70: 18.626122 | T70: 18.661646 | U70: 18.765039 | V70: 18.805761 | W70: 18.843643 | X70: 18.834778 | Y70: 18.874973 | Z70: 18.909355 | AA70: 18.914787 | AB70: 19.009039 | AC70: 19.066225 | AD70: 19.052853 | AE70: 19.023752 | AF70: 19.06444 | AG70: 19.044859 | AH70: 0.00014
A71: CNV000:ca_Imports | B71: Imports | C71: 21.803574 | D71: 23.877344 | E71: 24.519646 | F71: 24.553909 | G71: 24.555077 | H71: 24.556545 | I71: 24.558163 | J71: 24.560095 | K71: 24.562294 | L71: 24.564135 | M71: 24.566006 | N71: 24.567417 | O71: 24.569372 | P71: 24.571028 | Q71: 24.572569 | R71: 24.572277 | S71: 24.416414 | T71: 24.415298 | U71: 24.413433 | V71: 24.411963 | W71: 24.410923 | X71: 24.409023 | Y71: 24.406759 | Z71: 24.364962 | AA71: 24.290007 | AB71: 24.287508 | AC71: 24.284723 | AD71: 24.282084 | AE71: 24.279228 | AF71: 24.275148 | AG71: 24.271727 | AH71: 0.003581
A72: CNV000:ca_Exports | B72: Exports | C72: 26.459833 | D72: 26.347706 | E72: 26.128981 | F72: 25.58699 | G72: 25.522665 | H72: 25.523605 | I72: 25.521624 | J72: 25.518833 | K72: 25.515526 | L72: 25.523022 | M72: 25.52689 | N72: 25.522734 | O72: 25.498999 | P72: 25.49938 | Q72: 25.492809 | R72: 25.47209 | S72: 25.474277 | T72: 25.513758 | U72: 25.504108 | V72: 25.435743 | W72: 25.415844 | X72: 25.386637 | Y72: 25.381466 | Z72: 25.371529 | AA72: 25.363153 | AB72: 25.322754 | AC72: 25.289442 | AD72: 25.279551 | AE72: 25.278866 | AF72: 25.38624 | AG72: 25.345205 | AH72: -0.001434
A73: CNV000:ca_CoaltoLiquids | B73: Coal to Liquids | C73: - - | D73: - - | E73: - - | F73: - - | G73: - - | H73: - - | I73: - - | J73: - - | K73: - - | L73: - - | M73: - - | N73: - - | O73: - - | P73: - - | Q73: - - | R73: - - | S73: - - | T73: - - | U73: - - | V73: - - | W73: - - | X73: - - | Y73: - - | Z73: - - | AA73: - - | AB73: - - | AC73: - - | AD73: - - | AE73: - - | AF73: - - | AG73: - - | AH73: - -
A74: CNV000:ca_WasteCoal | B74: Waste Coal | C74: 13.506 | D74: 13.506 | E74: 13.506001 | F74: 13.506001 | G74: 13.506001 | H74: 13.506001 | I74: 13.506001 | J74: 13.506 | K74: 13.506 | L74: 13.506001 | M74: 13.506001 | N74: 13.506001 | O74: 13.506 | P74: 13.506001 | Q74: 13.506001 | R74: 13.506001 | S74: 13.506 | T74: 13.506 | U74: 13.506001 | V74: 13.506001 | W74: 13.506 | X74: 13.506001 | Y74: 13.506001 | Z74: 13.506001 | AA74: 13.506001 | AB74: 13.506 | AC74: 13.506 | AD74: 13.506 | AE74: 13.506 | AF74: 13.506001 | AG74: 13.506 | AH74: 0
B76: Approximate Heat Rates and Heat Content
B77: (Btu per kilowatthour)
A78: CNV000:da_Electricity | B78: Electricity Heat Content | C78: 3412 | D78: 3412 | E78: 3412 | F78: 3412 | G78: 3412 | H78: 3412 | I78: 3412 | J78: 3412 | K78: 3412 | L78: 3412 | M78: 3412 | N78: 3412 | O78: 3412 | P78: 3412 | Q78: 3412 | R78: 3412 | S78: 3412 | T78: 3412 | U78: 3412 | V78: 3412 | W78: 3412 | X78: 3412 | Y78: 3412 | Z78: 3412 | AA78: 3412 | AB78: 3412 | AC78: 3412 | AD78: 3412 | AE78: 3412 | AF78: 3412 | AG78: 3412 | AH78: 0
A79: CNV000:fossil_hr_us | B79: Fossil Fuel Heat Rate | C79: 8813.9736 | D79: 8888.75 | E79: 8900.5576 | F79: 8681.874 | G79: 8583.335 | H79: 8331.1445 | I79: 8270.6992 | J79: 8207.6904 | K79: 8195.6641 | L79: 8180.2568 | M79: 8174.5835 | N79: 8143.1289 | O79: 8114.2529 | P79: 8096.6523 | Q79: 8080.8423 | R79: 8058.7603 | S79: 8044.7466 | T79: 8019.1504 | U79: 7976.832 | V79: 7954.623 | W79: 7933.0767 | X79: 7915.2524 | Y79: 7900.6011 | Z79: 7871.0732 | AA79: 7850.0557 | AB79: 7821.7222 | AC79: 7808.6509 | AD79: 7797.0405 | AE79: 7788.7275 | AF79: 7768.7769 | AG79: 7750.7515 | AH79: -0.004276
B80: 1/ Includes ethane, natural gasoline, and refinery olefins.
B81: 2/ Includes all electricity-only and combined heat and power plants that have a regulatory status.
B82: 3/ Includes combined heat and power plants that have a non-regulatory status, and small on-site generating systems.
B83: - - = Not applicable.
B84: Sources: 2020: U.S. Energy Information Administration (EIA), Short-Term Energy Outlook, October 2020 and EIA,
B85: AEO2021 National Energy Modeling System run ref2021.d113020a. Projections: EIA, AEO2021 National Energy Modeling System run ref2021.d113020a.

Sheet Electricity
A1: Electricity
E2: CONSUMER CATEGORYWISE AVERAGE TARIFF, 2021-22 (All India Average)
A3: Consumer price (overall avg) | B3: Commercial price | C3: Industry price | F3: Domestic | G3: Commercial | H3: Agri./Irrig. | I3: Industrial | J3: Rly. Traction | K3: Outside state | L3: Overall Avg.
A4: =F4 -> 638.25 | B4: =G4 -> 946.14286 | C4: =(I4*SUM('BIFUbC-electricity'!B2:B7,'BIFUbC-electricity'!B9)+Electricity!H4*'BIFUbC-electricity'!B8)/SUM('BIFUbC-electricity'!B2:B9) -> 603.90779 | D4: 2021 paise/kWh | F4: =J17 -> 638.25 | G4: =J18 -> 946.14286 | H4: =J19 -> 332.5 | I4: =AVERAGE(J20:J24) -> 731.7375 | J4: =J25 -> 935.5 | L4: =AVERAGE(F4:J4) -> 716.82607 | M4: 2021 paise/kWh
A5: =A4/100 -> 6.3825 | B5: =B4/100 -> 9.4614286 | C5: =C4/100 -> 6.0390779 | D5: 2021 Rs/kWh | F5: =F4/100 -> 6.3825 | G5: =G4/100 -> 9.4614286 | H5: =H4/100 -> 3.325 | I5: =I4/100 -> 7.317375 | J5: =J4/100 -> 9.355 | K5: =K4/100 -> 0 | L5: =L4/100 -> 7.1682607 | M5: 2021 Rs/kWh
A6: =A5/'Conversion Factors'!$B$36 -> 0.001870527 | B6: =B5/'Conversion Factors'!$B$36 -> 0.0027728723 | C6: =C5/'Conversion Factors'!$B$36 -> 0.0017698799 | D6: 2021 Rs/BTU | F6: =F5/'Conversion Factors'!$B$36 -> 0.001870527 | G6: =G5/'Conversion Factors'!$B$36 -> 0.0027728723 | H6: =H5/'Conversion Factors'!$B$36 -> 0.00097446177 | I6: =I5/'Conversion Factors'!$B$36 -> 0.0021445119 | J6: =J5/'Conversion Factors'!$B$36 -> 0.0027416812 | K6: =K5/'Conversion Factors'!$B$36 -> 0 | L6: =L5/'Conversion Factors'!$B$36 -> 0.0021008108 | M6: 2021 Rs/BTU
A7: =A6/'Conversion Factors'!$C$13 -> 0.0012642299 | B7: =B6/'Conversion Factors'!$C$13 -> 0.0018740965 | C7: =C6/'Conversion Factors'!$C$15 -> 0.001080165 | D7: 2012 Rs/BTU | F7: =F6/'Conversion Factors'!$C$13 -> 0.0012642299 | G7: =G6/'Conversion Factors'!$C$13 -> 0.0018740965 | H7: =H6/'Conversion Factors'!$C$13 -> 0.00065860782 | I7: =I6/'Conversion Factors'!$C$13 -> 0.0014494076 | J7: =J6/'Conversion Factors'!$C$13 -> 0.0018530154 | K7: =K6/'Conversion Factors'!$C$13 -> 0 | L7: =L6/'Conversion Factors'!$C$15 -> 0.0012821336 | M7: 2012 Rs/BTU
A8: =A7/'Conversion Factors'!$B$22 -> 1.9962575e-05 | B8: =B7/'Conversion Factors'!$B$22 -> 2.9592555e-05 | C8: =C7/'Conversion Factors'!$B$29 -> 1.4498081e-05 | D8: 2012 USD/BTU | F8: =F7/'Conversion Factors'!$B$22 -> 1.9962575e-05 | G8: =G7/'Conversion Factors'!$B$22 -> 2.9592555e-05 | H8: =H7/'Conversion Factors'!$B$22 -> 1.0399618e-05 | I8: =I7/'Conversion Factors'!$B$22 -> 2.2886588e-05 | J8: =J7/'Conversion Factors'!$B$22 -> 2.9259677e-05 | K8: =K7/'Conversion Factors'!$B$22 -> 0 | L8: =L7/'Conversion Factors'!$B$29 -> 1.7208923e-05 | M8: 2012 USD/BTU
E10: Source: Electricity Tariff & Duty & Average rates of electricity supply in India (March 2022)
A12: 2021 Electricity Tariffs | B12: Source: https://cea.nic.in/wp-content/uploads/fs___a/2023/11/Book_2022.pdf
A13: Electricity Tariff & Duty and Average rates of electricity supply in India
A14: CATEGORY-WISE MAXIMUM & MINIMUM EFFECTIVE RATES OF ELECTRICITY IN THE COUNTRY
C15: AT VARIOUS ASSUMED SANCTIONED LOADS / CONSUMPTION LEVELS
A16: NSo.. | B16: Category | C16: Load/consumtion | D16: max (paisa/kwh) | E16: State/ Utility | F16: min (paisa/kwh) | G16: State/ Utility | H16: AVERAGE rate (paisa/kwh) | I16: category-average
A17: 1 | B17: DOMESTIC | C17: 1 KW (100 Unit/Month) | D17: 833 | E17: Rajasthan | F17: 85 | G17: Tamilnadu | H17: =AVERAGE(F17,D17) -> 459 | I17: =B17 -> DOMESTIC | J17: =AVERAGE(H17:H22) -> 638.25
A18: 2 | C18: 2 KW (200 Unit/Month) | D18: 844 | E18: Maharashtra | F18: 180 | G18: Daman and Diu | H18: =AVERAGE(F18,D18) -> 512 | I18: =B23 -> COMMERCIAL | J18: =AVERAGE(H23:H29) -> 946.14286
A19: 3 | C19: 4 KW (400 Unit/Month) | D19: 1016 | E19: Maharashtra - Mumbai -(Tata) | F19: 215 | G19: Daman and Diu | H19: =AVERAGE(F19,D19) -> 615.5 | I19: =B30 -> AGRICULTURE | J19: =AVERAGE(H30:H33) -> 332.5
A20: 4 | C20: 6 KW (600 Unit/Month) | D20: 1159 | E20: Maharashtra - Mumbai -(Tata) | F20: 243 | G20: Daman and Diu | H20: =AVERAGE(F20,D20) -> 701 | I20: =B34 -> SMALL INDUSTRIES | J20: =AVERAGE(H34:H36) -> 746.5
A21: 5 | C21: 8 KW (800 Unit/Month) | D21: 1252 | E21: Maharashtra - Mumbai -(Tata) | F21: 258 | G21: Daman and Diu | H21: =AVERAGE(F21,D21) -> 755 | I21: =B37 -> MEDIUM INDUSTRIES | J21: =AVERAGE(H37:H38) -> 763.75
A22: 6 | C22: 10 KW (1000 Unit/Month) | D22: 1308 | E22: Maharashtra - Mumbai -(Tata) | F22: 266 | G22: Daman and Diu | H22: =AVERAGE(F22,D22) -> 787 | I22: =B39 -> LARGE INDUSTRIES 11 kv | J22: =AVERAGE(H39:H50) -> 740.25
A23: 7 | B23: COMMERCIAL | C23: 2 KW (300 Unit/Month) | D23: 1222 | E23: Maharashtra | F23: 378 | G23: Daman and Diu | H23: =AVERAGE(F23,D23) -> 800 | I23: =B51 -> LARGE INDUSTRIES 33 KV | J23: =AVERAGE(H51:H58) -> 708.1875
A24: 8 | C24: 5 KW (750 Unit/Month) | D24: 1187 | E24: Uttar Pradesh (Urban) | F24: 394 | G24: Daman and Diu | H24: =AVERAGE(F24,D24) -> 790.5 | I24: =B59 -> POWER INTENSIVE INDUSTRIES | J24: =AVERAGE(H59:H60) -> 700
A25: 9 | C25: 10 KW (1500 Unit/Month) | D25: 1219 | E25: Uttar Pradesh (Urban) | F25: 400 | G25: Daman and Diu | H25: =AVERAGE(F25,D25) -> 809.5 | I25: =B61 -> RAILWAY TRACTION | J25: =H61 -> 935.5
A26: 10 | C26: 20 KW (3000 Unit/Month) | D26: 1241 | E26: Uttar Pradesh (Urban) | F26: 402 | G26: Daman and Diu | H26: =AVERAGE(F26,D26) -> 821.5
A27: 11 | C27: 30 KW (4500 Unit/Month) | D27: 1864 | E27: Maharashtra | F27: 403 | G27: Daman and Diu | H27: =AVERAGE(F27,D27) -> 1133.5
A28: 12 | C28: 40 KW (6000 Unit/Month) | D28: 1864 | E28: Maharashtra | F28: 404 | G28: Daman and Diu | H28: =AVERAGE(F28,D28) -> 1134
A29: 13 | C29: 50 KW (7500 Unit/Month) | D29: 1864 | E29: Maharashtra | F29: 404 | G29: Daman and Diu | H29: =AVERAGE(F29,D29) -> 1134
A30: 14 | B30: AGRICULTURE | C30: 2 HP (400 Unit/Month) | D30: 665 | E30: Uttar Pradesh (Urban) | F30: 0 | G30: Karnataka & Tamil Nadu,Punjab | H30: =AVERAGE(F30,D30) -> 332.5
A31: 15 | C31: 3 HP (600 Unit/Month) | D31: 665 | E31: Uttar Pradesh (Urban) | F31: 0 | G31: Karnataka & Tamil Nadu,Punjab | H31: =AVERAGE(F31,D31) -> 332.5
A32: 16 | C32: 5 HP (1000 Unit/Month) | D32: 665 | E32: Uttar Pradesh (Urban) | F32: 0 | G32: Karnataka & Tamil Nadu,Punjab | H32: =AVERAGE(F32,D32) -> 332.5
A33: 17 | C33: 10 HP (2000 Unit/Month) | D33: 665 | E33: Uttar Pradesh (Urban) | F33: 0 | G33: Karnataka & Tamil Nadu,Punjab | H33: =AVERAGE(F33,D33) -> 332.5
A34: 18 | B34: SMALL INDUSTRIES | C34: 5 KW (750 Unit/Month) | D34: 1089 | E34: Delhi - (BRPL/BYPL/TPDDL and NDMC) | F34: 387 | G34: Sikkim (rural) | H34: =AVERAGE(F34,D34) -> 738
A35: 19 | C35: 10 KW (15000 Unit/Month) | D35: 1089 | E35: Delhi - (BRPL/BYPL/TPDDL and NDMC) | F35: 407 | G35: Dadra & Nagar Haveli | H35: =AVERAGE(F35,D35) -> 748
A36: 20 | C36: 15 KW (22500 Unit/Month) | D36: 1089 | E36: Delhi - (BRPL/BYPL/TPDDL and NDMC) | F36: 418 | G36: Jammu and Kashmir and Ladakh | H36: =AVERAGE(F36,D36) -> 753.5
A37: 21 | B37: MEDIUM INDUSTRIES | C37: 50 KW (7500 Unit/Month) | D37: 1097 | E37: Maharashtra - Mumbai (Adani Electricity) | F37: 416 | G37: Jammu and Kashmir and Ladakh | H37: =AVERAGE(F37,D37) -> 756.5
A38: 22 | C38: 100 KW (15000 Unit/Month) | D38: 1151 | E38: Uttar Pradesh (Urban) | F38: 391 | G38: Jammu and Kashmir | H38: =AVERAGE(F38,D38) -> 771
A39: 23 | B39: LARGE INDUSTRIES 11 kv | C39: 250 KW 40% LF (73000 Unit/Month) (AT 11 KV) | D39: 1125 | E39: Maharashtra - (Non-continous industries) | F39: 385 | G39: Arunachal Pradesh | H39: =AVERAGE(F39,D39) -> 755
A40: 24 | C40: 250 KW 60% LF (109500 Unit/Month) (AT 11 KV) | D40: 1066 | E40: Maharashtra - (Non-continous industries) | F40: 385 | G40: Arunachal Pradesh | H40: =AVERAGE(F40,D40) -> 725.5
A41: 25 | C41: 500 KW 40% LF (146000 Unit/Month) (AT 11 KV) | D41: 1125 | E41: Maharashtra - (Non-continous industries) | F41: 385 | G41: Arunachal Pradesh | H41: =AVERAGE(F41,D41) -> 755
A42: 26 | C42: 500 KW 60% LF (219000 Unit/Month) (AT 11 KV) | D42: 1066 | E42: Maharashtra - (Non-continous industries) | F42: 385 | G42: Arunachal Pradesh | H42: =AVERAGE(F42,D42) -> 725.5
A43: 27 | C43: 1000 KW 40% LF (292000 Unit/Month) (AT 11 KV) | D43: 1125 | E43: Maharashtra - (Non-continous industries) | F43: 385 | G43: Arunachal Pradesh | H43: =AVERAGE(F43,D43) -> 755
A44: 28 | C44: 1000 KW 60% LF (438000 Unit/Month) (AT 11 KV) | D44: 1066 | E44: Maharashtra - (Non-continous industries) | F44: 385 | G44: Arunachal Pradesh | H44: =AVERAGE(F44,D44) -> 725.5
A45: 29 | C45: 5000 KW 40% LF (1460000 Unit/Month) (AT 11 KV) | D45: 1125 | E45: Maharashtra - (Non-continous industries) | F45: 385 | G45: Arunachal Pradesh | H45: =AVERAGE(F45,D45) -> 755
A46: 30 | C46: 5000 KW 60% LF (2190000 Unit/Month) (AT 11 KV) | D46: 1066 | E46: Maharashtra - (Non-continous industries) | F46: 385 | G46: Arunachal Pradesh | H46: =AVERAGE(F46,D46) -> 725.5
A47: 31 | C47: 10000 KW 40% LF (2920000 Unit/Month) (AT 11 KV) | D47: 1125 | E47: Maharashtra - (Non-continous industries) | F47: 385 | G47: Arunachal Pradesh | H47: =AVERAGE(F47,D47) -> 755
A48: 32 | C48: 10000 KW 60% LF (4380000 Unit/Month) (AT 11 KV) | D48: 1066 | E48: Maharashtra - (Non-continous industries) | F48: 385 | G48: Arunachal Pradesh | H48: =AVERAGE(F48,D48) -> 725.5
A49: 33 | C49: 20000 KW 40% LF (5840000 Unit/Month) (AT 11 KV) | D49: 1125 | E49: Maharashtra - (Non-continous industries) | F49: 385 | G49: Arunachal Pradesh | H49: =AVERAGE(F49,D49) -> 755
A50: 34 | C50: 20000 KW 60% LF (8760000 Unit/Month) (AT 11 KV) | D50: 1066 | E50: Maharashtra - (Non-continous industries) | F50: 385 | G50: Arunachal Pradesh | H50: =AVERAGE(F50,D50) -> 725.5
A51: 35 | B51: LARGE INDUSTRIES 33 KV | C51: 5000 KW 40% LF (1460000 Unit/Month) (AT 33 KV) | D51: 1094 | E51: Maharashtra | F51: 350 | G51: Arunachal Pradesh | H51: =AVERAGE(F51,D51) -> 722
A52: 36 | C52: 5000 KW 60% LF (2190000 Unit/Month) (AT 33 KV) | D52: 1035 | E52: Maharashtra | F52: 350 | G52: Arunachal Pradesh | H52: =AVERAGE(F52,D52) -> 692.5
A53: 37 | C53: 10000 KW 40% LF (2920000 Unit/Month) (AT 33 KV) | D53: 1094 | E53: Maharashtra | F53: 350 | G53: Arunachal Pradesh | H53: =AVERAGE(F53,D53) -> 722
A54: 38 | C54: 10000 KW 60% LF (4380000 Unit/Month) (AT 33 KV) | D54: 1035 | E54: Maharashtra | F54: 350 | G54: Arunachal Pradesh | H54: =AVERAGE(F54,D54) -> 692.5
A55: 39 | C55: 20000 KW 40% LF (5840000 Unit/Month) (AT 33 KV) | D55: 1094 | E55: Maharashtra | F55: 350 | G55: Arunachal Pradesh | H55: =AVERAGE(F55,D55) -> 722
A56: 40 | C56: 20000 KW 60% LF (8760000 Unit/Month) (AT 33 KV) | D56: 1035 | E56: Maharashtra | F56: 350 | G56: Arunachal Pradesh | H56: =AVERAGE(F56,D56) -> 692.5
A57: 41 | C57: 50000 KW 40% LF (14600000 Unit/Month) (AT 33 KV) | D57: 1094 | E57: Maharashtra | F57: 350 | G57: Arunachal Pradesh | H57: =AVERAGE(F57,D57) -> 722
A58: 42 | C58: 50000 KW 60% LF (21900000 Unit/Month) (AT 33 KV) | D58: 1050 | E58: Madhya Pradesh (At 33 KV) | F58: 350 | G58: Arunachal Pradesh | H58: =AVERAGE(F58,D58) -> 700
A59: 43 | B59: POWER INTENSIVE INDUSTRIES | C59: 50000 KW 60% LF (21900000 Unit/Month) | D59: 905 | E59: Punjab | F59: 514 | G59: Jammu and Kashmir and Ladakh (At 33 KV) | H59: =AVERAGE(F59,D59) -> 709.5
A60: 44 | C60: 50000 KW 80% LF (29200000 Unit/Month) | D60: 883 | E60: Punjab | F60: 498 | G60: Jammu and Kashmir and Ladakh (At 33 KV) | H60: =AVERAGE(F60,D60) -> 690.5
A61: 45 | B61: RAILWAY TRACTION | C61: 12500 KW (2500000 Unit/Month) | D61: 1271 | E61: Uttar Pradesh (Below 132 kV) | F61: 600 | G61: Gujarat (At 132 KV) | H61: =AVERAGE(F61,D61) -> 935.5

Sheet BIFUbC-electricity
A1: BTU/yr | B1: 2017 | C1: 2018 | D1: 2019 | E1: 2020 | F1: 2021 | G1: 2022 | H1: 2023 | I1: 2024 | J1: 2025 | K1: 2026 | L1: 2027 | M1: 2028 | N1: 2029 | O1: 2030 | P1: 2031 | Q1: 2032 | R1: 2033 | S1: 2034 | T1: 2035 | U1: 2036 | V1: 2037 | W1: 2038 | X1: 2039 | Y1: 2040 | Z1: 2041 | AA1: 2042 | AB1: 2043 | AC1: 2044 | AD1: 2045 | AE1: 2046 | AF1: 2047 | AG1: 2048 | AH1: 2049 | AI1: 2050
A2: Cement and other carbonate use | B2: 25591062225000 | C2: 2.7092405e+13 | D2: 28593746859400 | E2: 30095089176600 | F2: 31596431493800 | G2: 3.3097774e+13 | H2: 35281544454200 | I2: 3.7465315e+13 | J2: 39649085740600 | K2: 41832856383800 | L2: 44016627027000 | M2: 4.6951069e+13 | N2: 49885510630600 | O2: 5.2819952e+13 | P2: 55754394234200 | Q2: 5.8688836e+13 | R2: 6.1759764e+13 | S2: 6.4830691e+13 | T2: 6.7901618e+13 | U2: 7.0972546e+13 | V2: 74043473371000 | W2: 76295486846800 | X2: 7.85475e+13 | Y2: 80799513798400 | Z2: 83051527274200 | AA2: 8.5303541e+13 | AB2: 86804883067200 | AC2: 88306225384400 | AD2: 89807567701600 | AE2: 9.130891e+13 | AF2: 92810252336000 | AG2: 9.4311595e+13 | AH2: 9.5812937e+13 | AI2: 97314279287600
A3: Natural gas and petroleum systems | B3: 0 | C3: 0 | D3: 0 | E3: 0 | F3: 0 | G3: 0 | H3: 0 | I3: 0 | J3: 0 | K3: 0 | L3: 0 | M3: 0 | N3: 0 | O3: 0 | P3: 0 | Q3: 0 | R3: 0 | S3: 0 | T3: 0 | U3: 0 | V3: 0 | W3: 0 | X3: 0 | Y3: 0 | Z3: 0 | AA3: 0 | AB3: 0 | AC3: 0 | AD3: 0 | AE3: 0 | AF3: 0 | AG3: 0 | AH3: 0 | AI3: 0
A4: Iron and steel | B4: 1.8965181e+14 | C4: 2.0918662e+14 | D4: 228721425999809 | E4: 2.4825624e+14 | F4: 2.6779105e+14 | G4: 2.8732586e+14 | H4: 3.1058935e+14 | I4: 333852844965741 | J4: 3.5711634e+14 | K4: 3.8037983e+14 | L4: 4.0364333e+14 | M4: 4.3077407e+14 | N4: 4.5790481e+14 | O4: 4.8503555e+14 | P4: 5.1216629e+14 | Q4: 5.3929703e+14 | R4: 5.6530325e+14 | S4: 5.9130946e+14 | T4: 6.1731567e+14 | U4: 6.4332189e+14 | V4: 6.693281e+14 | W4: 6.9089336e+14 | X4: 7.1245862e+14 | Y4: 7.3402389e+14 | Z4: 7.5558915e+14 | AA4: 7.7715441e+14 | AB4: 7.9336929e+14 | AC4: 8.0958418e+14 | AD4: 8.2579906e+14 | AE4: 8.4201394e+14 | AF4: 8.5822883e+14 | AG4: 8.7444371e+14 | AH4: 8.906586e+14 | AI4: 906873479849107
A5: Chemicals | B5: 7.5920919e+13 | C5: 7.6623047e+13 | D5: 7.7325174e+13 | E5: 7.8027302e+13 | F5: 7.872943e+13 | G5: 7.9431558e+13 | H5: 7.9849764e+13 | I5: 8.0267969e+13 | J5: 8.0686175e+13 | K5: 8.1104381e+13 | L5: 8.1522587e+13 | M5: 8.1741719e+13 | N5: 8.1960852e+13 | O5: 8.2179984e+13 | P5: 8.2399117e+13 | Q5: 8.261825e+13 | R5: 8.2780241e+13 | S5: 8.2942232e+13 | T5: 8.3104223e+13 | U5: 8.3266214e+13 | V5: 8.3428206e+13 | W5: 8.3590311e+13 | X5: 8.3752417e+13 | Y5: 8.3914523e+13 | Z5: 8.4076629e+13 | AA5: 8.4238734e+13 | AB5: 8.4252699e+13 | AC5: 8.4266664e+13 | AD5: 8.4280629e+13 | AE5: 8.4294594e+13 | AF5: 8.4308559e+13 | AG5: 8.4322523e+13 | AH5: 8.4336488e+13 | AI5: 84350453118046
A6: Coal Mining | B6: 0 | C6: 0 | D6: 0 | E6: 0 | F6: 0 | G6: 0 | H6: 0 | I6: 0 | J6: 0 | K6: 0 | L6: 0 | M6: 0 | N6: 0 | O6: 0 | P6: 0 | Q6: 0 | R6: 0 | S6: 0 | T6: 0 | U6: 0 | V6: 0 | W6: 0 | X6: 0 | Y6: 0 | Z6: 0 | AA6: 0 | AB6: 0 | AC6: 0 | AD6: 0 | AE6: 0 | AF6: 0 | AG6: 0 | AH6: 0 | AI6: 0
A7: Water + Waste | B7: 5.901879e+11 | C7: 5.9674212e+11 | D7: 6.0321436e+11 | E7: 6.09587e+11 | F7: 6.1585608e+11 | G7: 6.2202247e+11 | H7: 6.2807913e+11 | I7: 6.3401856e+11 | J7: 6.3983326e+11 | K7: 6.4551708e+11 | L7: 6.5106384e+11 | M7: 6.5646384e+11 | N7: 6.6170695e+11 | O7: 6.6678523e+11 | P7: 6.7169428e+11 | Q7: 6.7642969e+11 | R7: 6.8098441e+11 | S7: 6.8534919e+11 | T7: 6.8951917e+11 | U7: 6.9349084e+11 | V7: 6.972655e+11 | W7: 7.0085067e+11 | X7: 7.042569e+11 | Y7: 7.0749391e+11 | Z7: 7.10563e+11 | AA7: 7.134655e+11 | AB7: 7.1620539e+11 | AC7: 7.1878838e+11 | AD7: 7.2121757e+11 | AE7: 7.2349647e+11 | AF7: 7.2562553e+11 | AG7: 7.2760696e+11 | AH7: 7.2943986e+11 | AI7: 7.3112557e+11
A8: Agriculture | B8: 6.4412708e+14 | C8: 6.9432016e+14 | D8: 7.4451324e+14 | E8: 7.9470632e+14 | F8: 8.448994e+14 | G8: 8.9509248e+14 | H8: 9.4519294e+14 | I8: 995293395123103 | J8: 1.0453939e+15 | K8: 1.0954943e+15 | L8: 1.1455948e+15 | M8: 1.2090861e+15 | N8: 1.2725775e+15 | O8: 1.3360688e+15 | P8: 1.3995601e+15 | Q8: 1.4630515e+15 | R8: 1.5163714e+15 | S8: 1.5696912e+15 | T8: 1.6230111e+15 | U8: 1.676331e+15 | V8: 1.7296509e+15 | W8: 1.7926781e+15 | X8: 1.8557053e+15 | Y8: 1.9187324e+15 | Z8: 1.9817596e+15 | AA8: 2.0447868e+15 | AB8: 2.0852545e+15 | AC8: 2.1257223e+15 | AD8: 2.1661901e+15 | AE8: 2.2066578e+15 | AF8: 2.2471256e+15 | AG8: 2.2875933e+15 | AH8: 2.3280611e+15 | AI8: 2.3685288e+15
A9: Other industries | B9: 1.0758554e+15 | C9: 1.1235032e+15 | D9: 1.1711509e+15 | E9: 1.2187986e+15 | F9: 1.2664463e+15 | G9: 1.3140941e+15 | H9: 1.3755067e+15 | I9: 1.4369193e+15 | J9: 1.4983319e+15 | K9: 1.5597446e+15 | L9: 1.6211572e+15 | M9: 1.6933851e+15 | N9: 1.765613e+15 | O9: 1.8378409e+15 | P9: 1.9100688e+15 | Q9: 1.9822967e+15 | R9: 2.0888612e+15 | S9: 2.1954257e+15 | T9: 2.3019903e+15 | U9: 2.4085548e+15 | V9: 2.5151193e+15 | W9: 2.6551885e+15 | X9: 2.7952577e+15 | Y9: 2.9353269e+15 | Z9: 3.0753961e+15 | AA9: 3.2154653e+15 | AB9: 3.3398788e+15 | AC9: 3.4642923e+15 | AD9: 3.5887058e+15 | AE9: 3.7131193e+15 | AF9: 3.8375328e+15 | AG9: 3.9619463e+15 | AH9: 4.0863598e+15 | AI9: 4.2107733e+15

Sheet Coal and Lignite
A1: 2014 Price | G1: 2019 Price
A2: Coal | G2: Source: | H2: http://www.coalcontroller.gov.in/writereaddata/files/download/coaldirectory/CoalDirectory2019-20.pdf
G3: Table 6.8 : PIT HEAD (Run of Mine) PRICE (Rupees Per Tonne) OF NON-COKING COAL OF COAL INDIA LTD
A4: Coal plant efficiency | B4: 0.75 | C4: kg/kWh | G4: Applicable to power utilities, fertilizer and defense sectors
A5: Coal electricity cost | B5: 225.35 | C5: 2014 paise/kWh | G5: Grade 13 (3400 - 3700 GCV band), 01-04-19 to 31-03-20
B6: =B5/100 -> 2.2535 | C6: 2014 Rs/kWh | G6: 817 | H6: 2019 Rs/tonne
B7: =B6/B4 -> 3.0046667 | C7: 2014 Rs/kg | G7: =G6/1000 -> 0.817 | H7: 2019 Rs/kg
B8: =B7/'Conversion Factors'!B74 -> 0.00011656452 | C8: 2014 Rs/BTU | G8: =G7/'Conversion Factors'!B74 -> 3.16951e-05 | H8: 2019 Rs/BTU
B9: =B8/'Conversion Factors'!B26 -> 1.6977063e-06 | C9: 2014 USD/BTU | G9: =G8/'Conversion Factors'!$C$13 -> 2.1421713e-05 | H9: 2012 Rs/BTU
B10: =B9*'Conversion Factors'!F8 -> 1.6464889e-06 | C10: 2012 USD/BTU | G10: =G9/'Conversion Factors'!$B$22 -> 3.3825538e-07 | H10: 2012 USD/BTU
A12: This is the price of coal in 2014. We will scale based on coal pit head prices
A13: (not retail prices) in 2019, for coal and for lignite, to estimate coal and | G13: Table 6.9 : PIT HEAD (Run of Mine) PRICE (Rupees Per Tonne) OF NON-COKING COAL OF COAL INDIA LTD
A14: lignite retail prices in 2019. | G14: Applicable to sectors other than power utilities, fertilizer and defense
G15: Grade 13 (3400 - 3700 GCV band), 01-04-19 to 31-03-20
A16: Coal | B16: 2014 | C16: 2019 | G16: 980 | H16: 2019 Rs/tonne
A17: Production | B17: 565.765 | C17: 730.874 | G17: =G16/1000 -> 0.98 | H17: 2019 Rs/kg
A18: Pit head value | B18: 825347.5 | C18: 1110043.7 | G18: =G17/'Conversion Factors'!B74 -> 3.8018602e-05 | H18: 2019 Rs/BTU
A19: Value per unit produced | B19: =B18/B17 -> 1458.8168 | C19: =C18/C17 -> 1518.7894 | G19: =G18/'Conversion Factors'!$C$13 -> 2.5695568e-05 | H19: 2012 Rs/BTU
G20: =G19/'Conversion Factors'!$B$22 -> 4.0574085e-07 | H20: 2012 USD/BTU
A21: Lignite | B21: 2014 | C21: 2019
A22: Production | B22: 44.3 | C22: 42.096
A23: Pit head value | B23: 59675.3 | C23: 65113.7
A24: Value per unit produced | B24: =B23/B22 -> 1347.0722 | C24: =C23/C22 -> 1546.7907
A27: Domestic Coal and Lignite Power Sector Price Estimates
A28: coal | B28: =B10*(C19/B19) -> 1.7141768e-06 | C28: 2012 USD/BTU
A29: lignite | B29: =B10*(C24/B24) -> 1.8905992e-06 | C29: 2012 USD/BTU
A31: Imported Coal Price
H34: coal | I34: 2019 USD / tonne | J34: 68
H35: coal | I35: 2012 USD / BTU | J35: =J34/1000/6000/B45 -> 2.8566363e-06
A45: kcal per BTU | B45: 3.96737 | C45: https://www.convertunits.com/from/btu/to/kcal
A47: Weighted Average Coal Price
A49: hard coal | B49: =B28*(1-BFPIaE!B7)+'Coal and Lignite'!J35*BFPIaE!B7 -> 1.9762037e-06
A50: lignite | B50: =B29 -> 1.8905992e-06
A51: *India has effectivly 0 lignite imports, so the domestic lignite price is taken for this file

Sheet BFPIaE
A1: hard coal (see fuels/BFPIaE)
B2: 2019 | C2: 2020 | D2: 2021 | E2: 2022 | F2: 2023 | G2: 2024 | H2: 2025 | I2: 2026 | J2: 2027 | K2: 2028 | L2: 2029 | M2: 2030 | N2: 2031 | O2: 2032 | P2: 2033 | Q2: 2034 | R2: 2035 | S2: 2036 | T2: 2037 | U2: 2038 | V2: 2039 | W2: 2040 | X2: 2041 | Y2: 2042 | Z2: 2043 | AA2: 2044 | AB2: 2045 | AC2: 2046 | AD2: 2047 | AE2: 2048 | AF2: 2049 | AG2: 2050
A3: production | B3: 1.1481663e+16 | C3: 1.201737e+16 | D3: 1.2578071e+16 | E3: 1.3164933e+16 | F3: 1.3593085e+16 | G3: 1.4035161e+16 | H3: 1.4491614e+16 | I3: 1.4962912e+16 | J3: 1.5449538e+16 | K3: 1.5746475e+16 | L3: 1.6049119e+16 | M3: 1.6357579e+16 | N3: 1.6671969e+16 | O3: 1.69924e+16 | P3: 1.7107453e+16 | Q3: 1.7223285e+16 | R3: 1.7339901e+16 | S3: 1.7457306e+16 | T3: 1.7575507e+16 | U3: 1.7569604e+16 | V3: 1.7563703e+16 | W3: 1.7557805e+16 | X3: 1.7551908e+16 | Y3: 1.7546013e+16 | Z3: 1.7451568e+16 | AA3: 1.7357632e+16 | AB3: 1.7264202e+16 | AC3: 1.7171274e+16 | AD3: 1.7078847e+16 | AE3: 1.7078847e+16 | AF3: 1.7078847e+16 | AG3: 1.7078847e+16
A4: imports | B4: 3.4125939e+15 | C4: 2.4154874e+15 | D4: 3.0925861e+15 | E4: 3.4118238e+15 | F4: 4.0696722e+15 | G4: 4.4750963e+15 | H4: 4.769443e+15 | I4: 4.8783449e+15 | J4: 4.7982193e+15 | K4: 5.1700824e+15 | L4: 5.5397384e+15 | M4: 5.8886777e+15 | N4: 6.2939885e+15 | O4: 6.6829567e+15 | P4: 7.370904e+15 | Q4: 7.8378723e+15 | R4: 8.3039563e+15 | S4: 8.7666507e+15 | T4: 9.2272502e+15 | U4: 9.772653e+15 | V4: 1.0229554e+16 | W4: 1.0897053e+16 | X4: 1.1354349e+16 | Y4: 1.1879244e+16 | Z4: 1.2421889e+16 | AA4: 1.2898925e+16 | AB4: 1.3410955e+16 | AC4: 1.3910583e+16 | AD4: 1.427501e+16 | AE4: 1.493201e+16 | AF4: 1.521281e+16 | AG4: 1.561281e+16
A5: exports | B5: 1.5057156e+13 | C5: 1.5057156e+13 | D5: 1.5057156e+13 | E5: 1.5057156e+13 | F5: 1.5057156e+13 | G5: 1.5057156e+13 | H5: 1.5057156e+13 | I5: 1.5057156e+13 | J5: 1.5057156e+13 | K5: 1.5057156e+13 | L5: 1.5057156e+13 | M5: 1.5057156e+13 | N5: 1.5057156e+13 | O5: 1.5057156e+13 | P5: 1.5057156e+13 | Q5: 1.5057156e+13 | R5: 1.5057156e+13 | S5: 1.5057156e+13 | T5: 1.5057156e+13 | U5: 1.5057156e+13 | V5: 1.5057156e+13 | W5: 1.5057156e+13 | X5: 1.5057156e+13 | Y5: 1.5057156e+13 | Z5: 1.5057156e+13 | AA5: 1.5057156e+13 | AB5: 1.5057156e+13 | AC5: 1.5057156e+13 | AD5: 1.5057156e+13 | AE5: 1.5057156e+13 | AF5: 1.5057156e+13 | AG5: 1.5057156e+13
A7: share of consumption that is imports: | B7: =B4/(B3+B4-B5) -> 0.22935332

Sheet Consumption of Coal&Lignite
A1: Table 6.3 : Trends in Industrywise Consumption of Raw Coal in India | M1: Table 6.4 : Trends in Industrywise Consumption of Lignite in India
K2: (Million tonnes) | T2: (Million tonnes)
A3: Year | B3: Electricity | C3: Steel & Washery | D3: Cement | E3: Paper | F3: Textile | G3: Sponge Iron | H3: Fertilizers &chemicals | I3: Brick | J3: Others * | K3: Total | M3: Year | N3: Electricity | O3: Steel & Washery | P3: Cement | Q3: Paper | R3: Textile | S3: Others * | T3: Total
A4: 1 | B4: 2 | C4: 3 | D4: 4 | E4: 5 | F4: 6 | G4: 7 | H4: 8 | I4: 9 | J4: 10 | K4: 11 = 2 to 10 | M4: 1 | N4: 2 | O4: 3 | P4: 4 | Q4: 5 | R4: 6 | S4: 7 | T4: 8=2 to 7
A5: 2012-13 | B5: 446.76 | C5: 51.7 | D5: 13.11 | E5: 2.12 | F5: 0.3 | G5: 20.9 | H5: 2.86 | I5: 2.01 | J5: 173.62 | K5: 713.39 | M5: 2012-13 | N5: 37.199 | O5: 0.049 | P5: 1.097 | Q5: 0.694 | R5: 3.468 | S5: 2.94 | T5: 46.313
A6: 2013-14 | B6: 448.95 | C6: 53.05 | D6: 11.94 | E6: 1.91 | F6: 0.36 | G6: 18.49 | H6: 2.64 | I6: 4.01 | J6: 198 | K6: 739.34 | M6: 2013-14 | N6: 36.336 | O6: 0.03 | P6: 1.489 | Q6: 1.29 | R6: 0.733 | S6: 3.016 | T6: 43.897
A7: 2014-15 | B7: 497.7 | C7: 56.24 | D7: 11.36 | E7: 1.65 | F7: 0.42 | G7: 17.77 | H7: 2.7 | I7: 0.09 | J7: 234.22 | K7: 822.13 | M7: 2014-15 | N7: 39.473 | O7: 0.023 | P7: 1.269 | Q7: 0.65 | R7: 2.887 | S7: 1.976 | T7: 46.949
A8: 2015-16 | B8: 517.77 | C8: 57.08 | D8: 8.99 | E8: 1.21 | F8: 0.27 | G8: 7.76 | H8: 2.62 | I8: 0.07 | J8: 240.95 | K8: 836.73 | M8: 2015-16 | N8: 37.555 | O8: 0.012 | P8: 0.225 | Q8: 0.427 | R8: 1.728 | S8: 1.872 | T8: 42.211
A9: 2016-17 | B9: 535.04 | C9: 51.98 | D9: 6.36 | E9: 1.18 | F9: 0.24 | G9: 5.56 | H9: 2.45 | I9: 0.1 | J9: 234.31 | K9: 837.22 | M9: 2016-17 | N9: 38.824 | O9: 0.035 | P9: 0.291 | Q9: 0.526 | R9: 1.292 | S9: 1.772 | T9: 43.155
A10: 2017-18 | B10: 585.49 | C10: 58.45 | D10: 7.71 | E10: 1.51 | F10: 0.24 | G10: 8.53 | H10: 2.16 | I10: 0.12 | J10: 234.3 | K10: 898.49 | M10: 2017-18 | N10: 38.839 | O10: 0.12 | P10: 1.091 | Q10: 0.758 | R10: 2.457 | S10: 2.672 | T10: 46.317
A11: 2018-19 | B11: 621.64 | C11: 64.65 | D11: 8.82 | E11: 1.64 | F11: 0.2 | G11: 12.09 | H11: 1.79 | I11: 0.09 | J11: 257.44 | K11: 968.36 | M11: 2018-19 | N11: 37.728 | O11: 0.094 | P11: 1.803 | Q11: 0.602 | R11: 2.614 | S11: 2.336 | T11: 45.811
A12: 2019-20 | B12: 626.15 | C12: 63.74 | D12: 8.57 | E12: 1.33 | F12: 0.1 | G12: 10.53 | H12: 1.76 | I12: 0.03 | J12: 243.72 | K12: 955.92 | M12: 2019-20 | N12: 36.332 | O12: 0.021 | P12: 0.996 | Q12: 0.546 | R12: 0.162 | S12: 3.745 | T12: 42.267
A13: 2020-21 | B13: 581.23 | C13: 60.17 | D13: 6.75 | E13: 1.05 | F13: 0.08 | G13: 9.57 | H13: 1.53 | I13: 0.03 | J13: 245.93 | K13: 906.33 | M13: 2020-21 | N13: 32.937 | O13: 0.024 | P13: 0.811 | Q13: 0.566 | R13: 0.29 | S13: 3.436 | T13: 38.492
A14: 2021-22 (P) | B14: 709.86 | C14: 65.38 | D14: 7.29 | E14: 1.25 | F14: 0.08 | G14: 8.67 | H14: 1.46 | I14: 0.02 | J14: 234.1 | K14: 1028.12 | M14: 2021-22 (P) | N14: 38.756 | O14: 0.268 | P14: 1.547 | Q14: 0.782 | R14: 3.398 | S14: 3.779 | T14: 49.073
A15: Percentage Distribution ( in 2021-22) | B15: 69.044268 | C15: 6.3592586 | D15: 0.70905913 | E15: 0.12158078 | F15: 0.0079756994 | G15: 0.84347884 | H15: 0.14229815 | I15: 0.0021398218 | J15: 22.769941 | K15: 100 | M15: Distribution (%) in 2021-22 | N15: 78.976219 | O15: 0.54612516 | P15: 3.1524464 | Q15: 1.5935443 | R15: 6.924378 | S15: 7.7007723 | T15: 100
A16: Growth rate of 2021-22 over 2020-21(%) | B16: 5.2795057 | C16: 2.6424853 | D16: -6.3151218 | E16: -5.6908601 | F16: -13.548777 | G16: -9.3128763 | H16: -7.1811306 | I16: -39.433508 | J16: 3.376887 | K16: 4.1442693 | M16: Growth rate of 2021-22 over 2020-21(%) | N16: 17.667061 | O16: - | P16: - | Q16: - | R16: - | S16: 9.9825378 | T16: 27.488829
A17: Source: Energy Statistics 2021 | M17: CAGR 2012-13 to 2021-22(%) | N17: 0.45663612 | O17: 20.77949 | P17: 3.8931888 | Q17: 1.335312 | R17: -0.22631059 | S17: 2.8287119 | T17: 0.64525381
A18: Tables 6.3, 6.4
A19: (P): Provisional | M19: (P): Provisional
A20: * Includes Sponge Iron, colliery consumption, jute, bricks, coal for soft coke, fertilisers & other industries consumption. | M20: * Includes Sponge Iron, colliery consumption., jute, bricks, coal for soft coke, chemicals, fertilisers & other industries consumption.
A21: @ From 1996-97 and onwards Cotton includes 'Rayon' also. | M21: From 2008-09 onwards cotton is also included in others.
M22: Note: Industrywise breakup of consumption for the period 1970-71 to 1999-2000 are not readily available, hence estimated by production data as it is observed, approximately for lignite, production= despatch= consumption.

Sheet NE Population
A1: State-wise Total Population by Residence and Sex in India
A2: (As per 2011 Census)
A3: States/UTs | B3: Total | E3: Rural | H3: Urban
B4: Persons | C4: Male | D4: Female | E4: Persons | F4: Male | G4: Female | H4: Persons | I4: Male | J4: Female
A5: Andaman and Nicobar Islands | B5: 380581 | C5: 202871 | D5: 177710 | E5: 237093 | F5: 126287 | G5: 110806 | H5: 143488 | I5: 76584 | J5: 66904
A6: Andhra Pradesh | B6: 49386799 | C6: 24738068 | D6: 24648731 | E6: 34776389 | F6: 17445803 | G6: 17330586 | H6: 14610410 | I6: 7292265 | J6: 7318145
A7: Andhra Pradesh (Un-Divided) | B7: 84580777 | C7: 42442146 | D7: 42138631 | E7: 56361702 | F7: 28243241 | G7: 28118461 | H7: 28219075 | I7: 14198905 | J7: 14020170
A8: Arunachal Pradesh | B8: 1383727 | C8: 713912 | D8: 669815 | E8: 1066358 | F8: 546011 | G8: 520347 | H8: 317369 | I8: 167901 | J8: 149468
A9: Assam | B9: 31205576 | C9: 15939443 | D9: 15266133 | E9: 26807034 | F9: 13678989 | G9: 13128045 | H9: 4398542 | I9: 2260454 | J9: 2138088
A10: Bihar | B10: 104099452 | C10: 54278157 | D10: 49821295 | E10: 92341436 | F10: 48073850 | G10: 44267586 | H10: 11758016 | I10: 6204307 | J10: 5553709
A11: Chandigarh | B11: 1055450 | C11: 580663 | D11: 474787 | E11: 28991 | F11: 17150 | G11: 11841 | H11: 1026459 | I11: 563513 | J11: 462946
A12: Chhattisgarh | B12: 25545198 | C12: 12832895 | D12: 12712303 | E12: 19607961 | F12: 9797426 | G12: 9810535 | H12: 5937237 | I12: 3035469 | J12: 2901768
A13: Dadra and Nagar Haveli | B13: 343709 | C13: 193760 | D13: 149949 | E13: 183114 | F13: 98305 | G13: 84809 | H13: 160595 | I13: 95455 | J13: 65140
A14: Daman and Diu | B14: 243247 | C14: 150301 | D14: 92946 | E14: 60396 | F14: 32395 | G14: 28001 | H14: 182851 | I14: 117906 | J14: 64945
A15: Delhi | B15: 16787941 | C15: 8987326 | D15: 7800615 | E15: 419042 | F15: 226321 | G15: 192721 | H15: 16368899 | I15: 8761005 | J15: 7607894
A16: Goa | B16: 1458545 | C16: 739140 | D16: 719405 | E16: 551731 | F16: 275436 | G16: 276295 | H16: 906814 | I16: 463704 | J16: 443110
... A42: India | B42: 1210854977 | C42: 623270258 | D42: 587584719 | E42: 833748852 | F42: 427781058 | G42: 405967794 | H42: 377106125 | I42: 195489200 | J42: 181616925
A44: Source : Office of the Registrar General and Census Commissioner, India.
A47: Source: India Stat database, Results from Census 2011 | F47: Total NE pop: | G47: =SUM(B8,B9,B27:B30,B35,B38) -> 45772188
A48: Table: State-wise Total Population by Residence and Sex in India | F48: NonNE states: | G48: =B42-G47 -> 1165082789

Sheet Natural Gas
A1: All Sectors Except Power
E3: Average end user price (2019 USD/BTU) | F3: =12/1000000 -> 1.2e-05
E4: Average end user price (2019 USD/BTU) | F4: =F3*dollars_2019_2012 -> 1.0776658e-05
A9: Power Sector
G10: domestic bar | H10: whole bar
F11: Number of pixels, Power bar | G11: 147 | H11: 247
F13: % domestic in power sector | G13: =G11/H11 -> 0.5951417
F15: power sector price ($/MMBtu) | G15: =G13*G36+(1-G13)*G37 -> 7.2803644
F16: power sector price (2019 USD/BTU) | G16: =G15/1000000 -> 7.2803644e-06
F17: power sector price (2012 USD/BTU) | G17: =G16*dollars_2019_2012 -> 6.5381663e-06
F36: average domestic price | G36: =AVERAGE(4,5.5) -> 4.75
F37: average RLNG | G37: 11

Sheet LPG
A1: Liquefied Petroleum Gas (Domestic) (₹/14.2 Kg Cyl)
A2: 2021 | B2: Delhi | C2: Kolkata | D2: Mumbai | E2: Chennai
A3: Retail Selling Price | B3: 949.5 | C3: 976 | D3: 949.5 | E3: 965.5
A4: Note: cost before subsidy deduction as subsidies per unit energy are handled in 'BAU Subsidies' variable
A5: LPG Average Cost | B5: =AVERAGE(B3:E3) -> 960.125 | C5: 2021 Rs/cyl
B6: =B5/'Conversion Factors'!B66 -> 0.0015088443 | C6: 2021 Rs/BTU
B7: =B6/'Conversion Factors'!$C$15 -> 0.00092085393 | C7: 2012 Rs/BTU
B8: =B7/'Conversion Factors'!$B$29 -> 1.2359792e-05 | C8: 2012 USD/BTU
A11: Source: Indian Petroleum & Nat Gas Statistics 2021-22
A12: Table IV.8, Page 106
G16: Source: Indian Petroleum & Nat Gas Statistics 2021-22
G17: Fig. V.7, Page 132

Sheet Nuclear Fuel
A1: Fuel | B1: Cost | C1: Unit
A2: nuclear fuel | B2: 0.74 | C2: 2012 $/million BTU
B3: =B2/10^6 -> 7.4e-07 | C3: 2012 $/BTU

Sheet Biomass
A1: Table 4.1 CENTRAL ELECTRICITY REGULATORY COMMISSION
A2: State | B2: Biomass Price (2021-22)(Rs./MT)
A3: Andhra Pradesh | B3: 3492.3
A4: Haryana | B4: 3975.3
A5: Maharashtra | B5: 4065.6
A6: Punjab | B6: 4158
A7: Rajasthan | B7: 3470.25
A8: Tamil Nadu | B8: 3435.6
A9: Telangana | B9: 3492.3
A10: Uttar Pradesh | B10: 3553.2
A11: Other States | B11: 3734.85
A13: Simple Average | B13: =AVERAGE(B3:B11) -> 3708.6 | C13: 2021 Rs/ton
B14: =B13/'Conversion Factors'!$B$44 -> 0.00029269989 | C14: 2021 Rs/BTU
B15: =B14/'Conversion Factors'!$C$15 -> 0.00017863596 | C15: 2012 Rs/BTU
B16: =B15/'Conversion Factors'!$B$29 -> 2.3976694e-06 | C16: 2012 USD/BTU
A18: Source: CERC RE Tariff Order 2021-22
A19: Fuel Costs, Biomass Price for FY 2021-22, Page 24

Sheet Petro Gasoline & Diesel
A1: Petroleum Gasoline
A2: As of Dec 2021
A3: India Avg | B3: 95.41 | C3: 2021 rs/liter
B4: =B3/'Conversion Factors'!B55 -> 0.0030493341 | C4: 2021 Rs/BTU
B5: =B4/'Conversion Factors'!$C$15 -> 0.0018610213 | C5: 2012 Rs/BTU
B6: =B5/'Conversion Factors'!$B$29 -> 2.497881e-05 | C6: 2012 USD/BTU
A9: Petroleum Diesel | E9: Source: Snapshot of India's Oil & Gas Data, Dec 2021 (PPAC)
A10: As of Dec 2021 | E10: Table 25, Page 30
A11: India Avg | B11: 86.67 | C11: 2018 rs/liter
B12: =B11/'Conversion Factors'!B60 -> 0.0023688206 | C12: 2018 Rs/BTU
B13: =B12/'Conversion Factors'!$C$15 -> 0.001445701 | C13: 2012 Rs/BTU
B14: =B13/'Conversion Factors'!$B$29 -> 1.9404341e-05 | C14: 2012 USD/BTU

Sheet Bio gasoline
A1: Ex-mill price of ethanol | E1: Ethanol supply and Blending status since 2012-'13
E2: Year | F2: Blending %
A3: C-heavy molasses | B3: 45.69 | C3: Rs/liter | E3: 2013 | F3: 2
A4: B-heavy molasses | B4: 57.61 | C4: Rs/liter | E4: 2021 | F4: 9.53
A5: Average | B5: =AVERAGE(B3:B4) -> 51.65 | C5: 2021 Rs/l
B6: =B5/'Conversion Factors'!B86 -> 0.0024308893 | C6: 2021 Rs/BTU
B7: =B6/'Conversion Factors'!C15 -> 0.0014835818 | C7: 2012 Rs/BTU
A8: current %blending of ethanol | B8: =F4 -> 9.53 | C8: %
A10: Price of blended gasoline (@6.1%) | B10: =(B8/100)*B7+(1-B8/100)*'Petro Gasoline & Diesel'!B5 -> 0.0018250513 | C10: 2012 Rs/BTU
B11: =B10/'Conversion Factors'!B29 -> 2.4496018e-05 | C11: 2012 USD/BTU
A15: https://pib.gov.in/Pressreleaseshare.aspx?PRID=1770519
A16: https://arcusresearch.in/wp-content/uploads/2023/05/Ethanol-blending-of-petrol-in-India-APR-.pdf

Sheet Kerosene
A1: IV.11 Price Build-up of Selected Petroleum Products in Major Cities (Contd...)
A2: (As on 01.04.2022)
A3: Market | B3: Delhi | C3: Kolkata | D3: Mumbai | E3: Chennai
A4: Superior Kerosene Oil (₹/Kl)
A5: Ex-Storage Price | B5: Kerosene free state | C5: 70048 | D5: 70048 | E5: 70048
A6: State Specific Cost | C6: 0 | D6: 0 | E6: -
A7: Siding Charge | C7: 19.37 | D7: - | E7: -
A8: Ass. Value | C8: =SUM(C5:C7) -> 70067.37 | D8: =SUM(D5:D7) -> 70048 | E8: =SUM(E5:E7) -> 70048
A9: Other State Levies | C9: - | D9: - | E9: -57689
A10: Sub Total | C10: =SUM(C8:C9) -> 70067.37 | D10: =SUM(D8:D9) -> 70048 | E10: =SUM(E8:E9) -> 12359
A11: GST% | C11: 5 | D11: 5 | E11: 5
A12: Sales/GST Tax Amount | C12: =C11*C10/100 -> 3503.3685 | D12: =D11*D10/100 -> 3502.4 | E12: =E11*E10/100 -> 617.95 | G12: Source: Indian Petroleum & Nat Gas Statistics 2021-22
A13: Sub Total | C13: =C10+C12 -> 73570.738 | D13: =D10+D12 -> 73550.4 | E13: =E10+E12 -> 12976.95 | G13: Table V.12, Page 135
A14: Ex-Mi/ Depot Price/KL-Oil Co. | C14: =C13 -> 73570.738 | D14: =D13 -> 73550.4 | E14: =E13 -> 12976.95
A15: Ex-Mi/ Depot Price/KL-St. Govt. | C15: =C14 -> 73570.738 | D15: =D14 -> 73550.4 | E15: =E14 -> 12976.95
A16: Wholesales Margin | C16: 1341.88 | D16: 1341.88 | E16: 1341.88
A17: Transport Charges | C17: 816.6 | D17: 481.25 | E17: 216.8
A18: Toll | C18: - | D18: 70 | E18: -
A19: Handling Charges | C19: 750.67 | D19: 99 | E19: -
A20: Rounding up | C20: - | D20: 8.68 | E20: -
A21: GST on wholesale margin | C21: - | D21: 100.04 | E21: 67.09
A22: Wholesales Price/KL | C22: =SUM(C15:C21) -> 76479.889 | D22: =SUM(D15:D21) -> 75651.25 | E22: =SUM(E15:E21) -> 14602.72
A23: Retailer Margin | C23: 1048.3 | D23: 675 | E23: 360
A24: Handling Charges | C24: 1709.53 | D24: - | E24: -
A25: Retailer Transportation | C25: 386.6 | D25: - | E25: 40
A26: GST On Retailer Margin | C26: - | D26: 33.75 | E26: 18
A27: Retail Selling Price/KL | C27: =SUM(C22:C26) -> 79624.319 | D27: =SUM(D22:D26) -> 76360 | E27: =SUM(E22:E26) -> 15020.72
A29: Jet fuel Average Cost | B29: =AVERAGE(C27:E27)/1000 -> 57.00168 | C29: 2021 Rs/l
B30: =B29/'Conversion Factors'!$B$48 -> 0.0015983321 | C30: 2021 Rs/BTU
B31: =B30/'Conversion Factors'!$C$15 -> 0.00097546874 | C31: 2012 Rs/BTU
B32: =B31/'Conversion Factors'!$B$29 -> 1.3092837e-05 | C32: 2012 USD/BTU
A34: Source: Indian Petroleum & Nat Gas Statistics 2021-22
A35: Table IV.11, Page 109

Sheet Jet Fuel
A1: Previous Price of ATF(Domestic)
A2: (Rupees/KL)
A3: Month | B3: Delhi | C3: Kolkata | D3: Mumbai | E3: Chennai
A4: 43435 | B4: 68050.97 | C4: 73393.55 | D4: 67979.58 | E4: 69216.61
A5: 43405 | B5: 76378.8 | C5: 81441.06 | D5: 76013.2 | E5: 77521.63
A6: 43384 | B6: 72605 | C6: 77638 | D6: 72225 | E6: 73534
A7: 43374 | B7: 74567 | C7: 79736 | D7: 74177 | E7: 75521
A8: 43344 | B8: 69461 | C8: 74677 | D8: 69161 | E8: 70316
A9: 43313 | B9: 69090 | C9: 74335 | D9: 68791 | E9: 69948
A10: 43282 | B10: 68086 | C10: 72718 | D10: 67722 | E10: 68810
A11: 43252 | B11: 70028 | C11: 74599 | D11: 69603 | E11: 70751
A12: 43221 | B12: 65340 | C12: 69897 | D12: 64901 | E12: 65898
A13: 43191 | B13: 61450 | C13: 65985 | D13: 61025 | E13: 64615
A14: 43160 | B14: 61681 | C14: 65803 | D14: 60738 | E14: 64427
A15: 43147 | B15: 61139 | C15: 65583 | D15: 60581 | E15: 64236
... A17: 43101 | B17: 57460 | C17: 62083 | D17: 57133 | E17: 60640
A18: 2018 Average | B18: =AVERAGE(B4:B17) -> 66873.626 | C18: =AVERAGE(C4:C17) -> 71676.544 | D18: =AVERAGE(D4:D17) -> 66473.627 | E18: =AVERAGE(E4:E17) -> 68547.874
A19: All India 2018 Avg. | B19: =AVERAGE(B18:E18) -> 68392.918
A21: Jet fuel Average Cost | B21: =B19/1000 -> 68.392918 | C21: 2018 Rs/l
B22: =B21/'Conversion Factors'!$B$48 -> 0.0019177434 | C22: 2018 Rs/BTU
B23: =B22/'Conversion Factors'!$C$12 -> 0.0013954265 | C23: 2012 Rs/BTU
B24: =B23/'Conversion Factors'!$B$20 -> 2.5477934e-05 | C24: 2012 USD/BTU
A26: Source: Indian Oil Website
A27: Aviation - https://www.iocl.com/Products/AviationTurbineFuel.aspx
A28: Previous Price of ATF (all months of 2018) - https://www.iocl.com/Product_PreviousPrice/ATFDomesticPreviousPrice.aspx

Sheet Crude Oil
A4: Year | B4: Price
A5: 2021-22 | B5: 73.3 | C5: 2021 USD/bbl
B8: =B5 -> 73.3 | C8: 2021 USD/bbl
B9: =B8/'Conversion Factors'!$B$79 -> 1.2637931e-05 | C9: 2021 USD/BTU
B10: =B9*'Conversion Factors'!$F$14 -> 1.1209845e-05 | C10: 2012 USD/BTU
A15: Source: Snapshot of India's Oil & Gas Data, Dec 2021 (PPAC)
A16: Table 25, Page 33

Sheet Heavy Fuel Oil
A1: Fuel | B1: Cost | C1: Unit
A2: Residual Fuel Oil | B2: 17.31 | C2: 2012 $/million BTU
B3: =B2/10^6 -> 1.731e-05 | C3: 2012 $/BTU

Sheet Municipal Solid Waste
A1: Year | B1: MSW Tipping Fee
A2: 2015 | B2: 1727 | C2: 2015 Rs./metric tonne
B3: =B2/'Conversion Factors'!$B$44 -> 0.00013630284 | C3: 2015 Rs/BTU
B4: =B3/'Conversion Factors'!$C$9 -> 0.00011097212 | C4: 2012 Rs/BTU
B5: =B4/'Conversion Factors'!$B$20 -> 2.0261479e-06 | C5: 2012 USD/BTU
G11: Price assumed to be as of agreement year i.e. 2015

Sheet Hydrogen
A1: Table 12: New Vehicle Fuel Economies, Fuel Economy Ratios, Gasoline Fuel Prices, and GasolineEquivalent Hydrogen Prices
A2: Vehicle Fuel Economies
B3: 2015 | C3: 2016 | D3: 2017 | E3: 2018 | F3: 2019 | G3: 2020 | H3: 2021 | I3: 2022 | J3: 2023 | K3: 2024 | L3: 2025
A4: New Fuel Cell Electric Vehicle (FCEV) | B4: 72 | C4: 74.1 | D4: 77.6 | E4: 79.3 | F4: 81.4 | G4: 83 | H4: 85.3 | I4: 87.3 | J4: 88.9 | K4: 90.8 | L4: 93.3
A5: New Conventional Gasoline Vehicle (CGV) | B5: 28.6 | C5: 29.8 | D5: 31.6 | E5: 32.7 | F5: 33.9 | G5: 35.1 | H5: 36.5 | I5: 37.8 | J5: 39.1 | K5: 40.4 | L5: 42.1
A6: Fuel Economy Ratio (FCEV/CGV) | B6: 2.52 | C6: 2.49 | D6: 2.46 | E6: 2.43 | F6: 2.4 | G6: 2.36 | H6: 2.34 | I6: 2.31 | J6: 2.27 | K6: 2.25 | L6: 2.22
A7: Fuel Prices
B8: 2015 | C8: 2016 | D8: 2017 | E8: 2018 | F8: 2019 | G8: 2020 | H8: 2021 | I8: 2022 | J8: 2023 | K8: 2024 | L8: 2025
A9: Gasoline Price ($/gal) | B9: 2.89 | C9: 3.35 | D9: 3.54 | E9: 3.63 | F9: 3.75 | G9: 4.01 | H9: 4.15 | I9: 4.32 | J9: 4.48 | K9: 4.64 | L9: 4.81
A10: Gasoline-Equivalent Hydrogen Price ($/kg) | B10: 7.28 | C10: 8.33 | D10: 8.7 | E10: 8.8 | F10: 9 | G10: 9.48 | H10: 9.71 | I10: 9.97 | J10: 10.19 | K10: 10.43 | L10: 10.66
A11: Hydrogen Price used in Scenario Analyses ($/kg) | B11: 14 | C11: 13.71 | D11: 13.42 | E11: 13.13 | F11: 12.85 | G11: 12.56 | H11: 12.27 | I11: 11.98 | J11: 11.69 | K11: 11.4 | L11: 11.11
A14: Hydrogen Energy Content (using Higher Heating Values)
A15: 61013 | B15: BTU/lb
A16: Source: U.S. DOE, Alternative Fuels Data Center, https://afdc.energy.gov/fuels/fuel_comparison_chart.pdf
A18: Conversion factor
A19: 2.20462 | B19: lb/kg
A22: Hydrogen Prices in $/BTU and Extrapolated to 2050
B23: 2015 | C23: 2016 | D23: 2017 | E23: 2018 | F23: 2019 | G23: 2020 | H23: 2021 | I23: 2022 | J23: 2023 | K23: 2024 | L23: 2025
A24: Hydrogen Prices ($/BTU) | B24: =B11/$A$19/$A$15 -> 0.00010408111 | C24: =C11/$A$19/$A$15 -> 0.00010192514 | D24: =D11/$A$19/$A$15 -> 9.9769178e-05 | E24: =E11/$A$19/$A$15 -> 9.7613212e-05 | F24: =F11/$A$19/$A$15 -> 9.553159e-05 | G24: =G11/$A$19/$A$15 -> 9.3375624e-05 | H24: =H11/$A$19/$A$15 -> 9.1219658e-05 | I24: =I11/$A$19/$A$15 -> 8.9063692e-05 | ... L24: =L11/$A$19/$A$15 -> 8.2595795e-05
A26: These data points form a linear cost decline. Projecting it out to 2050 results in a cost decline of 70% relative to 2018.
A27: However, the IEA source (The Future of Hydrogen) only projects a 50% cost cecline in hydrogen supplier CapEx and OpEx
A28: over that time period, and only for electrolysis, not for natural gas reforming or coal gasification.
A30: To have the drop in prices charged by hydrogen suppliers better match the price drops in their CapEx and OpEx costs,
A31: we use IEA data to project percentage declines in hydrogen cost, though we continue to rely on
A32: California Energy Commission / California Air Resources Board data for prices in the start year.
A33: We only use electrolysis costs here, because they are the only costs that decline, and they may drive the market
A34: price of hydrogen fuel. (In any case, these declines are already more conservative than extrapolating CEC/CARB values.)
A36: BNEF Year | D36: 2017 | E36: 2030 | F36: 2050
A37: Hydrogen Price ($/BTU) | D37: =D24 -> 9.9769178e-05 | E37: =1.97*(7.4)/1000000 -> 1.4578e-05 | F37: =1.01*(7.4)/1000000 -> 7.474e-06
A39: Hydrogen Prices using CEC/CARB Start Year Price and IEA Rate of Price Decline
B40: 2017 | C40: 2018 | D40: 2019 | E40: 2020 | F40: 2021 | G40: 2022 | H40: 2023 | I40: 2024 | J40: 2025 | K40: 2026 | L40: 2027 | M40: 2028 | N40: 2029 | O40: 2030 | P40: 2031 | Q40: 2032 | R40: 2033 | S40: 2034 | T40: 2035 | U40: 2036 | V40: 2037 | W40: 2038 | X40: 2039 | Y40: 2040 | Z40: 2041 | AA40: 2042 | AB40: 2043 | AC40: 2044 | AD40: 2045 | AE40: 2046 | AF40: 2047 | AG40: 2048 | AH40: 2049 | AI40: 2050
A41: Hydrogen Prices ($/BTU) | B41: =TREND($D37:$E37,$D$36:$E$36,B$40) -> 9.9769178e-05 | C41: =TREND($D37:$E37,$D$36:$E$36,C$40) -> 9.321601e-05 | D41: =TREND($D37:$E37,$D$36:$E$36,D$40) -> 8.6662843e-05 | E41: =TREND($D37:$E37,$D$36:$E$36,E$40) -> 8.0109675e-05 | F41: =TREND($D37:$E37,$D$36:$E$36,F$40) -> 7.3556508e-05 | G41: =TREND($D37:$E37,$D$36:$E$36,G$40) -> 6.700334e-05 | H41: =TREND($D37:$E37,$D$36:$E$36,H$40) -> 6.0450173e-05 | I41: =TREND($D37:$E37,$D$36:$E$36,I$40) -> 5.3897005e-05 | ... O41: =TREND($D37:$E37,$D$36:$E$36,O$40) -> 1.4578e-05 | P41: =TREND($E37:$F37,$E$36:$F$36,P$40) -> 1.42228e-05 | Q41: =TREND($E37:$F37,$E$36:$F$36,Q$40) -> 1.38676e-05 | R41: =TREND($E37:$F37,$E$36:$F$36,R$40) -> 1.35124e-05 | S41: =TREND($E37:$F37,$E$36:$F$36,S$40) -> 1.31572e-05 | T41: =TREND($E37:$F37,$E$36:$F$36,T$40) -> 1.2802e-05 | U41: =TREND($E37:$F37,$E$36:$F$36,U$40) -> 1.24468e-05 | V41: =TREND($E37:$F37,$E$36:$F$36,V$40) -> 1.20916e-05 | W41: =TREND($E37:$F37,$E$36:$F$36,W$40) -> 1.17364e-05 | ... AI41: =TREND($E37:$F37,$E$36:$F$36,AI$40) -> 7.474e-06

Sheet Start Year Prices
B1: Transportation Sector Price (2012 $/BTU) | C1: Electricity Sector Price (2012 $/BTU) | D1: Residential Buildings Sector Price (2012 $/BTU) | E1: Commercial Buildings Sector Price (2012 $/BTU) | F1: Industry Sector Price (2012 $/BTU)
A2: electricity | B2: =Electricity!$A$8 -> 1.9962575e-05 | C2: 0 | D2: =Electricity!$F$8 -> 1.9962575e-05 | E2: =Electricity!$G$8 -> 2.9592555e-05 | F2: =Electricity!$C$8 -> 1.4498081e-05
A3: coal | B3: 0 | C3: ='Coal and Lignite'!B49 -> 1.9762037e-06 | D3: 0 | E3: 0 | F3: =C3*'Coal and Lignite'!G20/'Coal and Lignite'!G10 -> 2.3704768e-06
A4: natural gas | B4: ='Natural Gas'!$C$36 -> 0 | C4: ='Natural Gas'!$C$36 -> 0 | D4: 0 | E4: 0 | F4: ='Natural Gas'!$C$36 -> 0
A5: nuclear | B5: 0 | C5: ='Nuclear Fuel'!B3 -> 7.4e-07 | D5: 0 | E5: 0 | F5: 0
A6: biomass | B6: 0 | C6: =Biomass!$B$16 -> 2.3976694e-06 | D6: =Biomass!$B$16 -> 2.3976694e-06 | E6: =Biomass!$B$16 -> 2.3976694e-06 | F6: =Biomass!$B$16 -> 2.3976694e-06
A7: petroleum gasoline | B7: ='Petro Gasoline & Diesel'!B6 -> 2.497881e-05 | C7: 0 | D7: 0 | E7: 0 | F7: 0
A8: petroleum diesel | B8: ='Petro Gasoline & Diesel'!$B$14 -> 1.9404341e-05 | C8: ='Petro Gasoline & Diesel'!$B$14 -> 1.9404341e-05 | D8: =Kerosene!$B$32 -> 1.3092837e-05 | E8: =Kerosene!$B$32 -> 1.3092837e-05 | F8: ='Petro Gasoline & Diesel'!$B$14 -> 1.9404341e-05
A9: biofuel gasoline | B9: =B7 -> 2.497881e-05 | C9: 0 | D9: 0 | E9: 0 | F9: 0
A10: biofuel diesel | B10: =B8 -> 1.9404341e-05 | C10: =C8 -> 1.9404341e-05 | D10: =D8 -> 1.3092837e-05 | E10: =E8 -> 1.3092837e-05 | F10: =F8 -> 1.9404341e-05
A11: jet fuel / kerosene | B11: ='Jet Fuel'!$B$24 -> 2.5477934e-05 | C11: 0 | D11: =Kerosene!B32 -> 1.3092837e-05 | E11: =Kerosene!B32 -> 1.3092837e-05 | F11: 0
A12: heat | B12: 0 | C12: 0 | D12: 0 | E12: 0 | F12: 0
A13: lignite | B13: 0 | C13: ='Coal and Lignite'!$B$29 -> 1.8905992e-06 | D13: 0 | E13: 0 | F13: ='Coal and Lignite'!$B$29 -> 1.8905992e-06
A14: crude oil | B14: 0 | C14: ='Crude Oil'!$B$10 -> 1.1209845e-05 | D14: 0 | E14: 0 | F14: ='Crude Oil'!$B$10 -> 1.1209845e-05
A15: heavy fuel oil | B15: 0 | C15: ='Heavy Fuel Oil'!$B$3 -> 1.731e-05 | D15: 0 | E15: 0 | F15: ='Heavy Fuel Oil'!$B$3 -> 1.731e-05
A16: LPG propane or butane | B16: 0 | C16: 0 | D16: =LPG!$B$8 -> 1.2359792e-05 | E16: =LPG!$B$8 -> 1.2359792e-05 | F16: =LPG!$B$8 -> 1.2359792e-05
A17: municipal solid waste | B17: 0 | C17: ='Municipal Solid Waste'!$B$5 -> 2.0261479e-06 | D17: 0 | E17: 0 | F17: ='Municipal Solid Waste'!$B$5 -> 2.0261479e-06
A39: Source: Indian Petroleum & Nat Gas Statistics 2017-18
A40: Table V.17, Page 95
E44: Source: Indian Petroleum & Nat Gas Statistics 2017-18
E45: Table V.2, Page 84

Sheet AEO Table 3
B1: ref2020.d112119a | C1: 2019 | D1: 2020 | E1: 2021 | F1: 2022 | G1: 2023 | H1: 2024 | I1: 2025 | J1: 2026 | K1: 2027 | L1: 2028 | M1: 2029 | N1: 2030 | O1: 2031 | P1: 2032 | Q1: 2033 | R1: 2034 | S1: 2035 | T1: 2036 | U1: 2037 | V1: 2038 | W1: 2039 | X1: 2040 | Y1: 2041 | Z1: 2042 | AA1: 2043 | AB1: 2044 | AC1: 2045 | AD1: 2046 | AE1: 2047 | AF1: 2048 | AG1: 2049 | AH1: 2050
C3: Report | D3: Annual Energy Outlook 2020
C4: Scenario | D4: ref2020 | G4: Reference case
C5: Datekey | D5: d112119a
C6: Release Date | E6: January 2020
A10: PRC000 | B10: 3. Energy Prices by Sector and Source
B11: (2019 dollars per million Btu, unless otherwise noted)
AI12: 2019-
B13: Sector and Source | C13: 2019 | D13: 2020 | E13: 2021 | F13: 2022 | G13: 2023 | H13: 2024 | I13: 2025 | J13: 2026 | K13: 2027 | L13: 2028 | M13: 2029 | N13: 2030 | O13: 2031 | P13: 2032 | Q13: 2033 | R13: 2034 | S13: 2035 | T13: 2036 | U13: 2037 | V13: 2038 | W13: 2039 | X13: 2040 | Y13: 2041 | Z13: 2042 | AA13: 2043 | AB13: 2044 | AC13: 2045 | AD13: 2046 | AE13: 2047 | AF13: 2048 | AG13: 2049 | AH13: 2050 | AI13: 2050
B15: Residential
A16: PRC000:ba_LiquefiedPetr | B16: Propane | C16: 21.37 | D16: 21.1 | E16: 21.47 | F16: 22.18 | G16: 22.88 | H16: 23.65 | I16: 24.63 | J16: 25.69 | K16: 26.54 | L16: 27.19 | M16: 27.65 | N16: 28.04 | O16: 28.19 | P16: 28.35 | Q16: 28.67 | R16: 29 | S16: 29.37 | T16: 29.78 | U16: 30.23 | V16: 30.69 | W16: 31.13 | X16: 31.54 | Y16: 31.93 | Z16: 32.41 | AA16: 32.85 | AB16: 33.28 | AC16: 33.71 | AD16: 34.12 | AE16: 34.6 | AF16: 35.1 | AG16: 35.56 | AH16: 36 | AI16: 0.017
A17: PRC000:ba_DistillateFue | B17: Distillate Fuel Oil | C17: 21.89 | D17: 21.3 | E17: 21.63 | F17: 22.21 | G17: 22.61 | H17: 23.27 | I17: 23.71 | J17: 24.07 | K17: 24.1 | L17: 24.44 | M17: 24.64 | N17: 24.76 | O17: 25.03 | P17: 25.2 | Q17: 25.52 | R17: 25.74 | S17: 25.95 | T17: 26.19 | U17: 26.35 | V17: 26.56 | W17: 26.78 | X17: 26.79 | Y17: 26.98 | Z17: 27.35 | AA17: 27.51 | AB17: 27.71 | AC17: 28.06 | AD17: 28.11 | AE17: 28.36 | AF17: 28.63 | AG17: 28.81 | AH17: 28.94 | AI17: 0.009
A18: PRC000:ba_NaturalGas | B18: Natural Gas | C18: 10.4 | D18: 10.01 | E18: 10.14 | F18: 10.06 | G18: 10.03 | H18: 10.06 | I18: 10.19 | J18: 10.38 | K18: 10.54 | L18: 10.65 | M18: 10.71 | N18: 10.98 | O18: 10.98 | P18: 11.02 | Q18: 11.16 | R18: 11.24 | S18: 11.27 | T18: 11.28 | U18: 11.35 | V18: 11.41 | W18: 11.45 | X18: 11.48 | Y18: 11.52 | Z18: 11.56 | AA18: 11.6 | AB18: 11.63 | AC18: 11.69 | AD18: 11.75 | AE18: 11.82 | AF18: 11.87 | AG18: 11.94 | AH18: 12 | AI18: 0.005
A19: PRC000:ba_Electricity | B19: Electricity | C19: 36.81 | D19: 36.33 | E19: 36.52 | F19: 36.57 | G19: 36.77 | H19: 37.16 | I19: 37.69 | J19: 38.17 | K19: 38.43 | L19: 38.38 | M19: 38.25 | N19: 38.27 | O19: 38.19 | P19: 38.1 | Q19: 38.23 | R19: 38.28 | S19: 38.1 | T19: 37.99 | U19: 37.87 | V19: 37.91 | W19: 37.8 | X19: 37.64 | Y19: 37.57 | Z19: 37.46 | AA19: 37.36 | AB19: 37.35 | AC19: 37.28 | AD19: 37.16 | AE19: 37.14 | AF19: 37.03 | AG19: 36.83 | AH19: 36.68 | AI19: 0
B21: Commercial
A22: PRC000:ca_LiquefiedGas | B22: Propane | C22: 17.53 | D22: 16.46 | E22: 16.9 | F22: 17.64 | G22: 18.15 | H22: 18.71 | I22: 19.49 | J22: 20.25 | K22: 20.67 | L22: 20.92 | M22: 21.03 | N22: 21.18 | O22: 21.19 | P22: 21.27 | Q22: 21.56 | R22: 21.81 | S22: 22.07 | T22: 22.36 | U22: 22.67 | V22: 22.97 | W22: 23.23 | X22: 23.46 | Y22: 23.68 | Z22: 24.02 | AA22: 24.28 | AB22: 24.53 | AC22: 24.79 | AD22: 25.03 | AE22: 25.35 | AF22: 25.68 | AG22: 25.94 | AH22: 26.18 | AI22: 0.013
A23: PRC000:ca_DistillateFue | B23: Distillate Fuel Oil | C23: 21.97 | D23: 21.38 | E23: 20.73 | F23: 20.32 | G23: 19.74 | H23: 19.41 | I23: 18.84 | J23: 19.22 | K23: 19.26 | L23: 19.6 | M23: 19.81 | N23: 20.23 | O23: 20.5 | P23: 20.67 | Q23: 21.06 | R23: 21.27 | S23: 21.49 | T23: 21.75 | U23: 21.9 | V23: 22.11 | W23: 22.35 | X23: 22.36 | Y23: 22.56 | Z23: 22.93 | AA23: 23.1 | AB23: 23.3 | AC23: 23.67 | AD23: 23.72 | AE23: 23.99 | AF23: 24.26 | AG23: 24.45 | AH23: 24.6 | AI23: 0.004
A24: PRC000:ca_ResidualFuel | B24: Residual Fuel Oil | C24: 6.36 | D24: 3.62 | E24: 5.09 | F24: 6.3 | G24: 7.47 | H24: 8.75 | I24: 10.1 | J24: 10.09 | K24: 10.46 | L24: 10.39 | M24: 10.83 | N24: 10.98 | O24: 11.3 | P24: 11.4 | Q24: 11.66 | R24: 11.76 | S24: 12 | T24: 12.23 | U24: 12.36 | V24: 12.55 | W24: 12.85 | X24: 13.17 | Y24: 13.49 | Z24: 13.69 | AA24: 13.91 | AB24: 14.06 | AC24: 14.14 | AD24: 14.48 | AE24: 14.52 | AF24: 14.68 | AG24: 14.89 | AH24: 15.22 | AI24: 0.029
A25: PRC000:ca_NaturalGas | B25: Natural Gas | C25: 7.52 | D25: 7.16 | E25: 7.3 | F25: 7.32 | G25: 7.38 | H25: 7.5 | I25: 7.72 | J25: 7.86 | K25: 7.99 | L25: 8.06 | M25: 8.08 | N25: 8.25 | O25: 8.22 | P25: 8.24 | Q25: 8.34 | R25: 8.4 | S25: 8.41 | T25: 8.4 | U25: 8.45 | V25: 8.49 | W25: 8.51 | X25: 8.52 | Y25: 8.55 | Z25: 8.58 | AA25: 8.6 | AB25: 8.62 | AC25: 8.66 | AD25: 8.7 | AE25: 8.76 | AF25: 8.79 | AG25: 8.85 | AH25: 8.89 | AI25: 0.005
A26: PRC000:ca_Electricity | B26: Electricity | C26: 30.83 | D26: 30.22 | E26: 29.92 | F26: 29.87 | G26: 29.84 | H26: 30.01 | I26: 30.44 | J26: 30.81 | K26: 30.94 | L26: 30.75 | M26: 30.49 | N26: 30.43 | O26: 30.25 | P26: 30 | Q26: 30.09 | R26: 30.07 | S26: 29.83 | T26: 29.7 | U26: 29.54 | V26: 29.59 | W26: 29.46 | X26: 29.24 | Y26: 29.18 | Z26: 29.1 | AA26: 28.94 | AB26: 28.92 | AC26: 28.82 | AD26: 28.69 | AE26: 28.68 | AF26: 28.56 | AG26: 28.39 | AH26: 28.27 | AI26: -0.003
B28: Industrial 1/
A29: PRC000:da_LiquefiedPetr | B29: Propane | C29: 12.66 | D29: 11.56 | E29: 12.12 | F29: 12.9 | G29: 13.38 | H29: 13.92 | I29: 14.72 | J29: 15.49 | K29: 15.87 | L29: 16.09 | M29: 16.19 | N29: 16.11 | O29: 16.13 | P29: 16.22 | Q29: 16.52 | R29: 16.78 | S29: 17.04 | T29: 17.35 | U29: 17.68 | V29: 17.98 | W29: 18.26 | X29: 18.5 | Y29: 18.73 | Z29: 19.1 | AA29: 19.37 | AB29: 19.64 | AC29: 19.92 | AD29: 20.18 | AE29: 20.54 | AF29: 20.9 | AG29: 21.17 | AH29: 21.42 | AI29: 0.017
A30: PRC000:da_DistillateFue | B30: Distillate Fuel Oil | C30: 21.89 | D30: 21.3 | E30: 20.68 | F30: 20.29 | G30: 19.72 | H30: 19.42 | I30: 18.85 | J30: 19.25 | K30: 19.3 | L30: 19.65 | M30: 19.86 | N30: 19.99 | O30: 20.26 | P30: 20.44 | Q30: 20.8 | R30: 21.01 | S30: 21.24 | T30: 21.5 | U30: 21.65 | V30: 21.87 | W30: 22.1 | X30: 22.12 | Y30: 22.32 | Z30: 22.69 | AA30: 22.87 | AB30: 23.07 | AC30: 23.45 | AD30: 23.49 | AE30: 23.77 | AF30: 24.02 | AG30: 24.21 | AH30: 24.37 | AI30: 0.003
A31: PRC000:da_ResidualFuel | B31: Residual Fuel Oil | C31: 6.48 | D31: 3.62 | E31: 5.27 | F31: 6.98 | G31: 8.56 | H31: 10.32 | I31: 12.02 | J31: 11.99 | K31: 12.45 | L31: 12.29 | M31: 12.74 | N31: 12.94 | O31: 13.28 | P31: 13.36 | Q31: 13.6 | R31: 13.67 | S31: 13.91 | T31: 14.14 | U31: 14.34 | V31: 14.53 | W31: 14.83 | X31: 15.18 | Y31: 15.47 | Z31: 15.7 | AA31: 15.91 | AB31: 16.07 | AC31: 16.15 | AD31: 16.48 | AE31: 16.53 | AF31: 16.69 | AG31: 16.9 | AH31: 17.21 | AI31: 0.032
A32: PRC000:da_NaturalGas | B32: Natural Gas 2/ | C32: 3.6 | D32: 3.44 | E32: 3.54 | F32: 3.47 | G32: 3.49 | H32: 3.56 | I32: 3.76 | J32: 3.99 | K32: 4.14 | L32: 4.22 | M32: 4.23 | N32: 4.16 | O32: 4.12 | P32: 4.14 | Q32: 4.2 | R32: 4.24 | S32: 4.24 | T32: 4.23 | U32: 4.27 | V32: 4.29 | W32: 4.3 | X32: 4.3 | Y32: 4.3 | Z32: 4.32 | AA32: 4.33 | AB32: 4.34 | AC32: 4.37 | AD32: 4.41 | AE32: 4.46 | AF32: 4.49 | AG32: 4.52 | AH32: 4.57 | AI32: 0.008
A33: PRC000:da_Metallurgical | B33: Metallurgical Coal | C33: 4.14 | D33: 3.72 | E33: 3.48 | F33: 3.31 | G33: 3.23 | H33: 3.23 | I33: 3.23 | J33: 3.24 | K33: 3.27 | L33: 3.29 | M33: 3.33 | N33: 3.37 | O33: 3.41 | P33: 3.44 | Q33: 3.48 | R33: 3.51 | S33: 3.55 | T33: 3.58 | U33: 3.61 | V33: 3.64 | W33: 3.68 | X33: 3.71 | Y33: 3.75 | Z33: 3.78 | AA33: 3.82 | AB33: 3.86 | AC33: 3.9 | AD33: 3.93 | AE33: 3.97 | AF33: 4.01 | AG33: 4.05 | AH33: 4.09 | AI33: 0
A34: PRC000:da_SteamCoal | B34: Other Industrial Coal | C34: 2.6 | D34: 2.6 | E34: 2.63 | F34: 2.63 | G34: 2.63 | H34: 2.64 | I34: 2.65 | J34: 2.66 | K34: 2.68 | L34: 2.68 | M34: 2.69 | N34: 2.7 | O34: 2.71 | P34: 2.71 | Q34: 2.72 | R34: 2.72 | S34: 2.73 | T34: 2.73 | U34: 2.74 | V34: 2.75 | W34: 2.76 | X34: 2.77 | Y34: 2.78 | Z34: 2.79 | AA34: 2.8 | AB34: 2.81 | AC34: 2.82 | AD34: 2.83 | AE34: 2.84 | AF34: 2.85 | AG34: 2.86 | AH34: 2.87 | AI34: 0.003
A35: PRC000:da_CoaltoLiquids | B35: Coal to Liquids | C35: - - | D35: - - | E35: - - | F35: - - | G35: - - | H35: - - | I35: - - | J35: - - | K35: - - | L35: - - | M35: - - | N35: - - | O35: - - | P35: - - | Q35: - - | R35: - - | S35: - - | T35: - - | U35: - - | V35: - - | W35: - - | X35: - - | Y35: - - | Z35: - - | AA35: - - | AB35: - - | AC35: - - | AD35: - - | AE35: - - | AF35: - - | AG35: - - | AH35: - - | AI35: - -
A36: PRC000:da_Electricity | B36: Electricity | C36: 20.24 | D36: 19.76 | E36: 19.08 | F36: 19.03 | G36: 18.94 | H36: 19 | I36: 19.29 | J36: 19.51 | K36: 19.59 | L36: 19.51 | M36: 19.4 | N36: 19.26 | O36: 19.15 | P36: 19.06 | Q36: 19.1 | R36: 19.1 | S36: 18.99 | T36: 18.92 | U36: 18.87 | V36: 18.88 | W36: 18.81 | X36: 18.71 | Y36: 18.65 | Z36: 18.59 | AA36: 18.54 | AB36: 18.52 | AC36: 18.47 | AD36: 18.43 | AE36: 18.46 | AF36: 18.43 | AG36: 18.39 | AH36: 18.38 | AI36: -0.003
B38: Transportation
A39: PRC000:ea_LiquefiedPetr | B39: Propane | C39: 16.63 | D39: 15.56 | E39: 16.02 | F39: 16.71 | G39: 17.15 | H39: 17.64 | I39: 18.33 | J39: 19 | K39: 19.33 | L39: 19.53 | M39: 19.62 | N39: 20.1 | O39: 20.11 | P39: 20.18 | Q39: 20.5 | R39: 20.71 | S39: 20.92 | T39: 21.17 | U39: 21.44 | V39: 21.69 | W39: 21.91 | X39: 22.1 | Y39: 22.28 | Z39: 22.57 | AA39: 22.79 | AB39: 23 | AC39: 23.21 | AD39: 23.41 | AE39: 23.68 | AF39: 23.96 | AG39: 24.17 | AH39: 24.36 | AI39: 0.012
A40: PRC000:ea_Ethanol(E85) | B40: E85 3/ | C40: 24.54 | D40: 24.24 | E40: 29.91 | F40: 28.43 | G40: 28.62 | H40: 28.52 | I40: 27.86 | J40: 27.94 | K40: 28.16 | L40: 28.43 | M40: 28.71 | N40: 30.06 | O40: 30.39 | P40: 30.55 | Q40: 31.21 | R40: 31.7 | S40: 32.78 | T40: 32.66 | U40: 32.83 | V40: 33.77 | W40: 34.77 | X40: 35.61 | Y40: 35.92 | Z40: 37.48 | AA40: 37.94 | AB40: 38.35 | AC40: 38.77 | AD40: 39.26 | AE40: 42.46 | AF40: 43.54 | AG40: 43.59 | AH40: 43.89 | AI40: 0.019
A41: PRC000:ea_MotorGasoline | B41: Motor Gasoline 4/ | C41: 22.17 | D41: 21.95 | E41: 21.98 | F41: 21.98 | G41: 21.89 | H41: 21.6 | I41: 21.85 | J41: 22.03 | K41: 22.3 | L41: 22.41 | M41: 22.71 | N41: 23.41 | O41: 23.57 | P41: 23.78 | Q41: 24.2 | R41: 24.59 | S41: 24.85 | T41: 25.15 | U41: 25.22 | V41: 25.5 | W41: 25.84 | X41: 25.93 | Y41: 26.12 | Z41: 26.52 | AA41: 26.74 | AB41: 26.95 | AC41: 27.29 | AD41: 27.38 | AE41: 27.85 | AF41: 28.18 | AG41: 28.42 | AH41: 28.63 | AI41: 0.008
A42: PRC000:ea_JetFuel | B42: Jet Fuel 5/ | C42: 14.64 | D42: 14.45 | E42: 14.47 | F42: 14.68 | G42: 14.78 | H42: 15.18 | I42: 15.25 | J42: 15.71 | K42: 15.74 | L42: 16.21 | M42: 16.43 | N42: 16.66 | O42: 17.01 | P42: 17.19 | Q42: 17.58 | R42: 17.87 | S42: 18.14 | T42: 18.38 | U42: 18.62 | V42: 18.83 | W42: 19.11 | X42: 19.2 | Y42: 19.45 | Z42: 19.83 | AA42: 20.04 | AB42: 20.28 | AC42: 20.7 | AD42: 20.75 | AE42: 21.18 | AF42: 21.52 | AG42: 21.77 | AH42: 21.86 | AI42: 0.013
A43: PRC000:ea_DistillateFue | B43: Diesel Fuel (distillate fuel oil) 6/ | C43: 22.11 | D43: 21.34 | E43: 21.46 | F43: 21.79 | G43: 21.92 | H43: 22.31 | I43: 22.45 | J43: 22.86 | K43: 22.91 | L43: 23.27 | M43: 23.48 | N43: 23.97 | O43: 24.24 | P43: 24.42 | Q43: 24.81 | R43: 25.01 | S43: 25.23 | T43: 25.49 | U43: 25.66 | V43: 25.88 | W43: 26.1 | X43: 26.1 | Y43: 26.27 | Z43: 26.66 | AA43: 26.82 | AB43: 27.03 | AC43: 27.4 | AD43: 27.41 | AE43: 27.67 | AF43: 27.91 | AG43: 28.08 | AH43: 28.23 | AI43: 0.008
A44: PRC000:ea_ResidualFuel | B44: Residual Fuel Oil | C44: 9.58 | D44: 10.57 | E44: 10.42 | F44: 10.19 | G44: 8.91 | H44: 9.21 | I44: 9.46 | J44: 10.1 | K44: 10.91 | L44: 11.29 | M44: 11.57 | N44: 11.02 | O44: 11.24 | P44: 11.3 | Q44: 11.56 | R44: 11.69 | S44: 12.39 | T44: 12.83 | U44: 12.92 | V44: 13.49 | W44: 13.65 | X44: 13.83 | Y44: 13.94 | Z44: 13.97 | AA44: 14.61 | AB44: 14.87 | AC44: 14.9 | AD44: 15.53 | AE44: 15.82 | AF44: 16.03 | AG44: 16.22 | AH44: 15.66 | AI44: 0.016
A45: PRC000:ea_NaturalGas | B45: Natural Gas 7/ | C45: 13.7 | D45: 13.29 | E45: 12.66 | F45: 12.42 | G45: 12.43 | H45: 12.3 | I45: 12.31 | J45: 12.27 | K45: 12.14 | L45: 11.94 | M45: 11.67 | N45: 12.1 | O45: 11.82 | P45: 11.66 | Q45: 11.65 | R45: 11.56 | S45: 11.46 | T45: 11.37 | U45: 11.34 | V45: 11.31 | W45: 11.27 | X45: 11.22 | Y45: 11.17 | Z45: 11.16 | AA45: 11.14 | AB45: 11.13 | AC45: 11.13 | AD45: 11.15 | AE45: 11.19 | AF45: 11.21 | AG45: 11.23 | AH45: 11.28 | AI45: -0.006
A46: PRC000:ea_Electricity | B46: Electricity | C46: 33.25 | D46: 33.91 | E46: 33.97 | F46: 34.36 | G46: 34.9 | H46: 35.39 | I46: 36.14 | J46: 36.76 | K46: 37.03 | L46: 36.98 | M46: 36.85 | N46: 36.7 | O46: 36.65 | P46: 36.63 | Q46: 36.83 | R46: 36.91 | S46: 36.57 | T46: 36.3 | U46: 36.14 | V46: 36.03 | W46: 35.83 | X46: 35.61 | Y46: 35.42 | Z46: 35.25 | AA46: 34.98 | AB46: 34.81 | AC46: 34.68 | AD46: 34.55 | AE46: 34.42 | AF46: 34.26 | AG46: 34.01 | AH46: 33.78 | AI46: 0.001
B48: Electric Power 8/
A49: PRC000:ga_DistillateFue | B49: Distillate Fuel Oil | C49: 21.9 | D49: 21.31 | E49: 20.57 | F49: 20 | G49: 19.33 | H49: 18.92 | I49: 18.26 | J49: 18.48 | K49: 18.43 | L49: 18.73 | M49: 18.92 | N49: 19.02 | O49: 19.2 | P49: 19.35 | Q49: 19.72 | R49: 19.97 | S49: 20.21 | T49: 20.49 | U49: 20.63 | V49: 20.73 | W49: 20.97 | X49: 21.03 | Y49: 21.23 | Z49: 21.61 | AA49: 21.76 | AB49: 21.95 | AC49: 22.35 | AD49: 22.44 | AE49: 22.8 | AF49: 23.15 | AG49: 23.38 | AH49: 23.53 | AI49: 0.002
A50: PRC000:ga_ResidualFuel | B50: Residual Fuel Oil | C50: 12.4 | D50: 11.55 | E50: 13.36 | F50: 13.39 | G50: 13.32 | H50: 13.43 | I50: 13.6 | J50: 13.72 | K50: 14.01 | L50: 14.02 | M50: 14.41 | N50: 14.62 | O50: 14.89 | P50: 15.03 | Q50: 15.29 | R50: 15.46 | S50: 15.67 | T50: 15.85 | U50: 16.04 | V50: 16.21 | W50: 16.44 | X50: 16.65 | Y50: 16.76 | Z50: 16.93 | AA50: 16.97 | AB50: 16.95 | AC50: 16.84 | AD50: 17.1 | AE50: 17.25 | AF50: 17.49 | AG50: 17.72 | AH50: 17.97 | AI50: 0.012
A51: PRC000:ga_NaturalGas | B51: Natural Gas | C51: 2.86 | D51: 2.65 | E51: 2.82 | F51: 2.81 | G51: 2.88 | H51: 3.03 | I51: 3.31 | J51: 3.52 | K51: 3.65 | L51: 3.71 | M51: 3.7 | N51: 3.63 | O51: 3.6 | P51: 3.62 | Q51: 3.69 | R51: 3.74 | S51: 3.74 | T51: 3.74 | U51: 3.77 | V51: 3.8 | W51: 3.8 | X51: 3.81 | Y51: 3.8 | Z51: 3.81 | AA51: 3.82 | AB51: 3.84 | AC51: 3.85 | AD51: 3.89 | AE51: 3.95 | AF51: 3.99 | AG51: 4.01 | AH51: 4.07 | AI51: 0.011
A52: PRC000:ga_SteamCoal | B52: Steam Coal | C52: 2.05 | D52: 2.06 | E52: 2.03 | F52: 2 | G52: 1.98 | H52: 1.97 | I52: 1.95 | J52: 1.96 | K52: 1.97 | L52: 1.96 | M52: 1.96 | N52: 1.96 | O52: 1.95 | P52: 1.95 | Q52: 1.96 | R52: 1.96 | S52: 1.95 | T52: 1.95 | U52: 1.96 | V52: 1.96 | W52: 1.95 | X52: 1.95 | Y52: 1.95 | Z52: 1.95 | AA52: 1.95 | AB52: 1.95 | AC52: 1.95 | AD52: 1.95 | AE52: 1.95 | AF52: 1.95 | AG52: 1.95 | AH52: 1.95 | AI52: -0.002
A53: PRC000:ga_uranium | B53: Uranium | C53: 0.68 | D53: 0.68 | E53: 0.68 | F53: 0.68 | G53: 0.68 | H53: 0.68 | I53: 0.69 | J53: 0.69 | K53: 0.69 | L53: 0.69 | M53: 0.69 | N53: 0.69 | O53: 0.69 | P53: 0.7 | Q53: 0.7 | R53: 0.7 | S53: 0.7 | T53: 0.7 | U53: 0.7 | V53: 0.71 | W53: 0.71 | X53: 0.71 | Y53: 0.71 | Z53: 0.71 | AA53: 0.72 | AB53: 0.72 | AC53: 0.72 | AD53: 0.72 | AE53: 0.72 | AF53: 0.73 | AG53: 0.73 | AH53: 0.73 | AI53: 0.002
B56: Average Price to All Users 9/
A57: PRC000:ha_LiquefiedPetr | B57: Propane | C57: 18.52 | D57: 17.8 | E57: 18.16 | F57: 18.89 | G57: 19.48 | H57: 20.12 | I57: 20.97 | J57: 21.84 | K57: 22.42 | L57: 22.83 | M57: 23.07 | N57: 23.24 | O57: 23.27 | P57: 23.35 | Q57: 23.63 | R57: 23.88 | S57: 24.15 | T57: 24.47 | U57: 24.82 | V57: 25.16 | W57: 25.48 | X57: 25.76 | Y57: 26.02 | Z57: 26.4 | AA57: 26.7 | AB57: 27 | AC57: 27.3 | AD57: 27.59 | AE57: 27.95 | AF57: 28.33 | AG57: 28.64 | AH57: 28.94 | AI57: 0.015
A58: PRC000:ha_Ethanol(E85) | B58: E85 3/ | C58: 24.54 | D58: 24.24 | E58: 29.91 | F58: 28.43 | G58: 28.62 | H58: 28.52 | I58: 27.86 | J58: 27.94 | K58: 28.16 | L58: 28.43 | M58: 28.71 | N58: 30.06 | O58: 30.39 | P58: 30.55 | Q58: 31.21 | R58: 31.7 | S58: 32.78 | T58: 32.66 | U58: 32.83 | V58: 33.77 | W58: 34.77 | X58: 35.61 | Y58: 35.92 | Z58: 37.48 | AA58: 37.94 | AB58: 38.35 | AC58: 38.77 | AD58: 39.26 | AE58: 42.46 | AF58: 43.54 | AG58: 43.59 | AH58: 43.89 | AI58: 0.019
A59: PRC000:ha_MotorGasoline | B59: Motor Gasoline 4/ | C59: 22.15 | D59: 21.94 | E59: 21.97 | F59: 21.98 | G59: 21.89 | H59: 21.61 | I59: 21.86 | J59: 22.04 | K59: 22.31 | L59: 22.42 | M59: 22.72 | N59: 23.42 | O59: 23.59 | P59: 23.8 | Q59: 24.22 | R59: 24.61 | S59: 24.87 | T59: 25.16 | U59: 25.24 | V59: 25.52 | W59: 25.86 | X59: 25.95 | Y59: 26.14 | Z59: 26.54 | AA59: 26.76 | AB59: 26.96 | AC59: 27.31 | AD59: 27.4 | AE59: 27.87 | AF59: 28.19 | AG59: 28.44 | AH59: 28.65 | AI59: 0.008
A60: PRC000:ha_JetFuel | B60: Jet Fuel 5/ | C60: 14.64 | D60: 14.45 | E60: 14.47 | F60: 14.68 | G60: 14.78 | H60: 15.18 | I60: 15.25 | J60: 15.71 | K60: 15.74 | L60: 16.21 | M60: 16.43 | N60: 16.66 | O60: 17.01 | P60: 17.19 | Q60: 17.58 | R60: 17.87 | S60: 18.14 | T60: 18.38 | U60: 18.62 | V60: 18.83 | W60: 19.11 | X60: 19.2 | Y60: 19.45 | Z60: 19.83 | AA60: 20.04 | AB60: 20.28 | AC60: 20.7 | AD60: 20.75 | AE60: 21.18 | AF60: 21.52 | AG60: 21.77 | AH60: 21.86 | AI60: 0.013
A61: PRC000:ha_DistillateFue | B61: Distillate Fuel Oil | C61: 22.06 | D61: 21.33 | E61: 21.31 | F61: 21.51 | G61: 21.51 | H61: 21.77 | I61: 21.77 | J61: 22.17 | K61: 22.22 | L61: 22.56 | M61: 22.77 | N61: 23.14 | O61: 23.4 | P61: 23.57 | Q61: 23.94 | R61: 24.13 | S61: 24.35 | T61: 24.6 | U61: 24.76 | V61: 24.97 | W61: 25.19 | X61: 25.19 | Y61: 25.36 | Z61: 25.74 | AA61: 25.9 | AB61: 26.1 | AC61: 26.47 | AD61: 26.49 | AE61: 26.75 | AF61: 26.99 | AG61: 27.15 | AH61: 27.31 | AI61: 0.007
A62: PRC000:ha_ResidualFuel | B62: Residual Fuel Oil | C62: 9.75 | D62: 10.19 | E62: 10.27 | F62: 10.17 | G62: 9.18 | H62: 9.55 | I62: 9.88 | J62: 10.46 | K62: 11.21 | L62: 11.54 | M62: 11.84 | N62: 11.37 | O62: 11.61 | P62: 11.68 | Q62: 11.93 | R62: 12.06 | S62: 12.7 | T62: 13.12 | U62: 13.22 | V62: 13.74 | W62: 13.91 | X62: 14.11 | Y62: 14.23 | Z62: 14.28 | AA62: 14.84 | AB62: 15.07 | AC62: 15.09 | AD62: 15.68 | AE62: 15.94 | AF62: 16.15 | AG62: 16.34 | AH62: 15.92 | AI62: 0.016
A63: PRC000:ha_NaturalGas | B63: Natural Gas | C63: 5.03 | D63: 4.76 | E63: 4.85 | F63: 4.83 | G63: 4.87 | H63: 4.98 | I63: 5.2 | J63: 5.4 | K63: 5.55 | L63: 5.63 | M63: 5.64 | N63: 5.68 | O63: 5.64 | P63: 5.65 | Q63: 5.71 | R63: 5.74 | S63: 5.74 | T63: 5.73 | U63: 5.76 | V63: 5.78 | W63: 5.78 | X63: 5.78 | Y63: 5.78 | Z63: 5.8 | AA63: 5.81 | AB63: 5.83 | AC63: 5.85 | AD63: 5.89 | AE63: 5.93 | AF63: 5.95 | AG63: 5.97 | AH63: 6.02 | AI63: 0.006
A64: PRC000:ha_Metallugical | B64: Metallurgical Coal | C64: 4.14 | D64: 3.72 | E64: 3.48 | F64: 3.31 | G64: 3.23 | H64: 3.23 | I64: 3.23 | J64: 3.24 | K64: 3.27 | L64: 3.29 | M64: 3.33 | N64: 3.37 | O64: 3.41 | P64: 3.44 | Q64: 3.48 | R64: 3.51 | S64: 3.55 | T64: 3.58 | U64: 3.61 | V64: 3.64 | W64: 3.68 | X64: 3.71 | Y64: 3.75 | Z64: 3.78 | AA64: 3.82 | AB64: 3.86 | AC64: 3.9 | AD64: 3.93 | AE64: 3.97 | AF64: 4.01 | AG64: 4.05 | AH64: 4.09 | AI64: 0
A65: PRC000:ha_Coal | B65: Other Coal | C65: 2.08 | D65: 2.09 | E65: 2.07 | F65: 2.04 | G65: 2.03 | H65: 2.02 | I65: 2.01 | J65: 2.02 | K65: 2.03 | L65: 2.01 | M65: 2.02 | N65: 2.02 | O65: 2.01 | P65: 2.01 | Q65: 2.02 | R65: 2.02 | S65: 2.01 | T65: 2.01 | U65: 2.02 | V65: 2.02 | W65: 2.02 | X65: 2.01 | Y65: 2.01 | Z65: 2.02 | AA65: 2.02 | AB65: 2.02 | AC65: 2.02 | AD65: 2.02 | AE65: 2.02 | AF65: 2.02 | AG65: 2.02 | AH65: 2.02 | AI65: -0.001
A66: PRC000:ha_CoaltoLiquids | B66: Coal to Liquids | C66: - - | D66: - - | E66: - - | F66: - - | G66: - - | H66: - - | I66: - - | J66: - - | K66: - - | L66: - - | M66: - - | N66: - - | O66: - - | P66: - - | Q66: - - | R66: - - | S66: - - | T66: - - | U66: - - | V66: - - | W66: - - | X66: - - | Y66: - - | Z66: - - | AA66: - - | AB66: - - | AC66: - - | AD66: - - | AE66: - - | AF66: - - | AG66: - - | AH66: - - | AI66: - -
A67: PRC000:ha_Electricity | B67: Electricity | C67: 30.45 | D67: 29.93 | E67: 29.73 | F67: 29.66 | G67: 29.66 | H67: 29.85 | I67: 30.25 | J67: 30.59 | K67: 30.75 | L67: 30.63 | M67: 30.45 | N67: 30.39 | O67: 30.27 | P67: 30.13 | Q67: 30.23 | R67: 30.26 | S67: 30.08 | T67: 29.99 | U67: 29.89 | V67: 29.94 | W67: 29.85 | X67: 29.69 | Y67: 29.64 | Z67: 29.57 | AA67: 29.47 | AB67: 29.46 | AC67: 29.4 | AD67: 29.31 | AE67: 29.32 | AF67: 29.24 | AG67: 29.11 | AH67: 29.02 | AI67: -0.002
B69: Non-Renewable Energy Expenditures by Sector
B70: (billion 2019 dollars)
A71: PRC000:ia_Residential | B71: Residential | C71: 255 | D71: 245 | E71: 249 | F71: 249 | G71: 250 | H71: 252 | I71: 254 | J71: 258 | K71: 260 | L71: 261 | M71: 261 | N71: 263 | O71: 263 | P71: 264 | Q71: 266 | R71: 268 | S71: 269 | T71: 270 | U71: 272 | V71: 274 | W71: 275 | X71: 276 | Y71: 277 | Z71: 279 | AA71: 280 | AB71: 282 | AC71: 284 | AD71: 286 | AE71: 288 | AF71: 290 | AG71: 291 | AH71: 293 | AI71: 0.005
A72: PRC000:ia_Commercial | B72: Commercial | C72: 189 | D72: 184 | E72: 186 | F72: 187 | G72: 188 | H72: 190 | I72: 193 | J72: 196 | K72: 198 | L72: 198 | M72: 198 | N72: 199 | O72: 200 | P72: 200 | Q72: 202 | R72: 203 | S72: 203 | T72: 204 | U72: 205 | V72: 207 | W72: 208 | X72: 208 | Y72: 210 | Z72: 211 | AA72: 212 | AB72: 214 | AC72: 216 | AD72: 217 | AE72: 220 | AF72: 222 | AG72: 223 | AH72: 225 | AI72: 0.006
A73: PRC000:ia_Industrial | B73: Industrial 1/ | C73: 185 | D73: 178 | E73: 183 | F73: 190 | G73: 195 | H73: 201 | I73: 210 | J73: 219 | K73: 225 | L73: 229 | M73: 233 | N73: 235 | O73: 238 | P73: 241 | Q73: 246 | R73: 251 | S73: 255 | T73: 260 | U73: 264 | V73: 269 | W73: 273 | X73: 277 | Y73: 281 | Z73: 287 | AA73: 292 | AB73: 297 | AC73: 303 | AD73: 308 | AE73: 314 | AF73: 321 | AG73: 327 | AH73: 332 | AI73: 0.019
A74: PRC000:ia_Transportatio | B74: Transportation | C74: 574 | D74: 568 | E74: 566 | F74: 563 | G74: 555 | H74: 548 | I74: 546 | J74: 548 | K74: 548 | L74: 549 | M74: 552 | N74: 562 | O74: 564 | P74: 566 | Q74: 574 | R74: 579 | S74: 583 | T74: 588 | U74: 590 | V74: 596 | W74: 602 | X74: 605 | Y74: 610 | Z74: 621 | AA74: 628 | AB74: 635 | AC74: 647 | AD74: 651 | AE74: 665 | AF74: 676 | AG74: 685 | AH74: 693 | AI74: 0.006
A75: PRC000:ia_TotalNon-Rene | B75: Total Non-Renewable Expenditures | C75: 1203 | D75: 1176 | E75: 1184 | F75: 1189 | G75: 1187 | H75: 1190 | I75: 1203 | J75: 1221 | K75: 1230 | L75: 1237 | M75: 1244 | N75: 1259 | O75: 1265 | P75: 1271 | Q75: 1288 | R75: 1302 | S75: 1311 | T75: 1322 | U75: 1331 | V75: 1345 | W75: 1358 | X75: 1365 | Y75: 1378 | Z75: 1398 | AA75: 1412 | AB75: 1429 | AC75: 1450 | AD75: 1462 | AE75: 1487 | AF75: 1508 | AG75: 1526 | AH75: 1543 | AI75: 0.008
A76: PRC000:ja_Transportatio | B76: Transportation Renewable Expenditures | C76: 0 | D76: 0 | E76: 1 | F76: 1 | G76: 1 | H76: 1 | I76: 1 | J76: 1 | K76: 1 | L76: 1 | M76: 1 | N76: 1 | O76: 1 | P76: 1 | Q76: 1 | R76: 1 | S76: 1 | T76: 1 | U76: 1 | V76: 1 | W76: 1 | X76: 1 | Y76: 1 | Z76: 0 | AA76: 0 | AB76: 0 | AC76: 0 | AD76: 0 | AE76: 0 | AF76: 0 | AG76: 0 | AH76: 0 | AI76: 0.004
A77: PRC000:ja_TotalExpendit | B77: Total Expenditures | C77: 1203 | D77: 1176 | E77: 1184 | F77: 1190 | G77: 1188 | H77: 1191 | I77: 1204 | J77: 1221 | K77: 1231 | L77: 1238 | M77: 1245 | N77: 1260 | O77: 1266 | P77: 1271 | Q77: 1289 | R77: 1302 | S77: 1312 | T77: 1323 | U77: 1332 | V77: 1346 | W77: 1359 | X77: 1366 | Y77: 1379 | Z77: 1399 | AA77: 1413 | AB77: 1429 | AC77: 1450 | AD77: 1463 | AE77: 1488 | AF77: 1508 | AG77: 1527 | AH77: 1543 | AI77: 0.008
B80: Prices in Nominal Dollars
B81: Residential
A82: PRC000:nom_R_LiquefiedP | B82: Propane | C82: 21.37 | D82: 21.62 | E82: 22.53 | F82: 23.86 | G82: 25.22 | H82: 26.66 | I82: 28.39 | J82: 30.31 | K82: 32.06 | L82: 33.64 | M82: 35.02 | N82: 36.34 | O82: 37.37 | P82: 38.41 | Q82: 39.71 | R82: 41.04 | S82: 42.46 | T82: 44 | U82: 45.66 | V82: 47.39 | W82: 49.15 | X82: 50.91 | Y82: 52.7 | Z82: 54.72 | AA82: 56.74 | AB82: 58.82 | AC82: 60.99 | AD82: 63.21 | AE82: 65.64 | AF82: 68.24 | AG82: 70.85 | AH82: 73.47 | AI82: 0.041
A83: PRC000:nom_R_Distillate | B83: Distillate Fuel Oil | C83: 21.89 | D83: 21.82 | E83: 22.71 | F83: 23.89 | G83: 24.91 | H83: 26.24 | I83: 27.33 | J83: 28.4 | K83: 29.12 | L83: 30.24 | M83: 31.21 | N83: 32.09 | O83: 33.18 | P83: 34.14 | Q83: 35.35 | R83: 36.41 | S83: 37.52 | T83: 38.7 | U83: 39.79 | V83: 41.01 | W83: 42.28 | X83: 43.24 | Y83: 44.53 | Z83: 46.17 | AA83: 47.52 | AB83: 48.98 | AC83: 50.78 | AD83: 52.07 | AE83: 53.8 | AF83: 55.65 | AG83: 57.39 | AH83: 59.07 | AI83: 0.033
A84: PRC000:nom_R_NaturalGas | B84: Natural Gas | C84: 10.4 | D84: 10.26 | E84: 10.64 | F84: 10.83 | G84: 11.05 | H84: 11.34 | I84: 11.75 | J84: 12.24 | K84: 12.73 | L84: 13.17 | M84: 13.56 | N84: 14.23 | O84: 14.55 | P84: 14.93 | Q84: 15.45 | R84: 15.9 | S84: 16.3 | T84: 16.67 | U84: 17.15 | V84: 17.62 | W84: 18.07 | X84: 18.52 | Y84: 19.02 | Z84: 19.52 | AA84: 20.03 | AB84: 20.56 | AC84: 21.15 | AD84: 21.76 | AE84: 22.43 | AF84: 23.07 | AG84: 23.78 | AH84: 24.49 | AI84: 0.028
A85: PRC000:nom_R_Electricit | B85: Electricity | C85: 36.81 | D85: 37.21 | E85: 38.34 | F85: 39.34 | G85: 40.53 | H85: 41.88 | I85: 43.45 | J85: 45.04 | K85: 46.42 | L85: 47.48 | M85: 48.44 | N85: 49.61 | O85: 50.62 | P85: 51.62 | Q85: 52.94 | R85: 54.17 | S85: 55.08 | T85: 56.13 | U85: 57.2 | V85: 58.54 | W85: 59.68 | X85: 60.75 | Y85: 62.02 | Z85: 63.25 | AA85: 64.54 | AB85: 66.02 | AC85: 67.45 | AD85: 68.84 | AE85: 70.46 | AF85: 71.98 | AG85: 73.38 | AH85: 74.87 | AI85: 0.023
B87: Commercial
A88: PRC000:nom_C_LiquefiedG | B88: Propane | C88: 17.53 | D88: 16.86 | E88: 17.74 | F88: 18.98 | G88: 20.01 | H88: 21.09 | I88: 22.47 | J88: 23.9 | K88: 24.97 | L88: 25.87 | M88: 26.64 | N88: 27.45 | O88: 28.08 | P88: 28.82 | Q88: 29.86 | R88: 30.86 | S88: 31.91 | T88: 33.04 | U88: 34.24 | V88: 35.46 | W88: 36.68 | X88: 37.87 | Y88: 39.08 | Z88: 40.56 | AA88: 41.94 | AB88: 43.37 | AC88: 44.85 | AD88: 46.37 | AE88: 48.1 | AF88: 49.93 | AG88: 51.68 | AH88: 53.43 | AI88: 0.037
A89: PRC000:nom_C_Distillate | B89: Distillate Fuel Oil | C89: 21.97 | D89: 21.9 | E89: 21.76 | F89: 21.86 | G89: 21.75 | H89: 21.89 | I89: 21.72 | J89: 22.68 | K89: 23.26 | L89: 24.25 | M89: 25.09 | N89: 26.22 | O89: 27.17 | P89: 28 | Q89: 29.16 | R89: 30.09 | S89: 31.07 | T89: 32.13 | U89: 33.08 | V89: 34.15 | W89: 35.28 | X89: 36.09 | Y89: 37.23 | Z89: 38.72 | AA89: 39.91 | AB89: 41.19 | AC89: 42.83 | AD89: 43.93 | AE89: 45.52 | AF89: 47.16 | AG89: 48.7 | AH89: 50.2 | AI89: 0.027
A90: PRC000:nom_C_ResidualFu | B90: Residual Fuel Oil | C90: 6.36 | D90: 3.71 | E90: 5.34 | F90: 6.77 | G90: 8.23 | H90: 9.86 | I90: 11.64 | J90: 11.91 | K90: 12.64 | L90: 12.85 | M90: 13.72 | N90: 14.23 | O90: 14.98 | P90: 15.45 | Q90: 16.14 | R90: 16.64 | S90: 17.35 | T90: 18.06 | U90: 18.67 | V90: 19.38 | W90: 20.28 | X90: 21.26 | Y90: 22.26 | Z90: 23.12 | AA90: 24.02 | AB90: 24.85 | AC90: 25.59 | AD90: 26.82 | AE90: 27.54 | AF90: 28.54 | AG90: 29.66 | AH90: 31.07 | AI90: 0.053
A91: PRC000:nom_C_NaturalGas | B91: Natural Gas | C91: 7.52 | D91: 7.33 | E91: 7.66 | F91: 7.88 | G91: 8.13 | H91: 8.45 | I91: 8.9 | J91: 9.28 | K91: 9.65 | L91: 9.97 | M91: 10.24 | N91: 10.7 | O91: 10.9 | P91: 11.16 | Q91: 11.55 | R91: 11.88 | S91: 12.16 | T91: 12.41 | U91: 12.77 | V91: 13.1 | W91: 13.43 | X91: 13.75 | Y91: 14.11 | Z91: 14.48 | AA91: 14.85 | AB91: 15.23 | AC91: 15.67 | AD91: 16.12 | AE91: 16.62 | AF91: 17.09 | AG91: 17.62 | AH91: 18.15 | AI91: 0.029
A92: PRC000:nom_C_Electricit | B92: Electricity | C92: 30.83 | D92: 30.96 | E92: 31.41 | F92: 32.14 | G92: 32.89 | H92: 33.83 | I92: 35.09 | J92: 36.35 | K92: 37.38 | L92: 38.04 | M92: 38.62 | N92: 39.45 | O92: 40.1 | P92: 40.65 | Q92: 41.67 | R92: 42.54 | S92: 43.13 | T92: 43.88 | U92: 44.62 | V92: 45.69 | W92: 46.51 | X92: 47.2 | Y92: 48.16 | Z92: 49.13 | AA92: 49.99 | AB92: 51.11 | AC92: 52.15 | AD92: 53.14 | AE92: 54.41 | AF92: 55.53 | AG92: 56.56 | AH92: 57.7 | AI92: 0.02
B94: Industrial 1/
A95: PRC000:nom_I_LiquefiedP | B95: Propane | C95: 12.66 | D95: 11.84 | E95: 12.72 | F95: 13.88 | G95: 14.74 | H95: 15.69 | I95: 16.97 | J95: 18.28 | K95: 19.17 | L95: 19.91 | M95: 20.51 | N95: 20.88 | O95: 21.38 | P95: 21.98 | Q95: 22.88 | R95: 23.74 | S95: 24.64 | T95: 25.63 | U95: 26.7 | V95: 27.77 | W95: 28.83 | X95: 29.86 | Y95: 30.91 | Z95: 32.26 | AA95: 33.46 | AB95: 34.72 | AC95: 36.04 | AD95: 37.38 | AE95: 38.96 | AF95: 40.63 | AG95: 42.17 | AH95: 43.73 | AI95: 0.041
A96: PRC000:nom_I_Distillate | B96: Distillate Fuel Oil | C96: 21.89 | D96: 21.82 | E96: 21.71 | F96: 21.83 | G96: 21.74 | H96: 21.89 | I96: 21.73 | J96: 22.71 | K96: 23.32 | L96: 24.31 | M96: 25.16 | N96: 25.9 | O96: 26.86 | P96: 27.69 | Q96: 28.8 | R96: 29.73 | S96: 30.71 | T96: 31.76 | U96: 32.71 | V96: 33.77 | W96: 34.9 | X96: 35.7 | Y96: 36.83 | Z96: 38.32 | AA96: 39.5 | AB96: 40.78 | AC96: 42.44 | AD96: 43.51 | AE96: 45.09 | AF96: 46.7 | AG96: 48.23 | AH96: 49.74 | AI96: 0.027
A97: PRC000:nom_I_ResidualFu | B97: Residual Fuel Oil | C97: 6.48 | D97: 3.71 | E97: 5.53 | F97: 7.51 | G97: 9.43 | H97: 11.63 | I97: 13.86 | J97: 14.14 | K97: 15.04 | L97: 15.2 | M97: 16.14 | N97: 16.77 | O97: 17.61 | P97: 18.1 | Q97: 18.83 | R97: 19.34 | S97: 20.12 | T97: 20.89 | U97: 21.66 | V97: 22.44 | W97: 23.41 | X97: 24.5 | Y97: 25.54 | Z97: 26.51 | AA97: 27.48 | AB97: 28.4 | AC97: 29.23 | AD97: 30.53 | AE97: 31.36 | AF97: 32.45 | AG97: 33.67 | AH97: 35.13 | AI97: 0.056
A98: PRC000:nom_I_NaturalGas | B98: Natural Gas 2/ | C98: 3.6 | D98: 3.53 | E98: 3.71 | F98: 3.74 | G98: 3.84 | H98: 4.02 | I98: 4.34 | J98: 4.71 | K98: 5 | L98: 5.22 | M98: 5.36 | N98: 5.4 | O98: 5.46 | P98: 5.6 | Q98: 5.81 | R98: 6 | S98: 6.13 | T98: 6.25 | U98: 6.45 | V98: 6.63 | W98: 6.78 | X98: 6.94 | Y98: 7.1 | Z98: 7.29 | AA98: 7.48 | AB98: 7.68 | AC98: 7.9 | AD98: 8.16 | AE98: 8.45 | AF98: 8.72 | AG98: 9 | AH98: 9.32 | AI98: 0.031
A99: PRC000:nom_I_Metallurgi | B99: Metallurgical Coal | C99: 4.14 | D99: 3.81 | E99: 3.65 | F99: 3.57 | G99: 3.56 | H99: 3.64 | I99: 3.73 | J99: 3.82 | K99: 3.95 | L99: 4.08 | M99: 4.22 | N99: 4.36 | O99: 4.51 | P99: 4.66 | Q99: 4.81 | R99: 4.97 | S99: 5.13 | T99: 5.29 | U99: 5.45 | V99: 5.62 | W99: 5.8 | X99: 5.98 | Y99: 6.18 | Z99: 6.39 | AA99: 6.6 | AB99: 6.82 | AC99: 7.05 | AD99: 7.28 | AE99: 7.53 | AF99: 7.79 | AG99: 8.07 | AH99: 8.34 | AI99: 0.023
A100: PRC000:nom_I_SteamCoal | B100: Other Industrial Coal | C100: 2.6 | D100: 2.66 | E100: 2.77 | F100: 2.83 | G100: 2.9 | H100: 2.98 | I100: 3.06 | J100: 3.14 | K100: 3.24 | L100: 3.32 | M100: 3.41 | N100: 3.5 | O100: 3.59 | P100: 3.68 | Q100: 3.76 | R100: 3.85 | S100: 3.94 | T100: 4.04 | U100: 4.15 | V100: 4.25 | W100: 4.36 | X100: 4.46 | Y100: 4.59 | Z100: 4.71 | AA100: 4.84 | AB100: 4.96 | AC100: 5.1 | AD100: 5.24 | AE100: 5.38 | AF100: 5.53 | AG100: 5.7 | AH100: 5.86 | AI100: 0.027
A101: PRC000:nom_I_CoaltoLiqu | B101: Coal to Liquids | C101: - - | D101: - - | E101: - - | F101: - - | G101: - - | H101: - - | I101: - - | J101: - - | K101: - - | L101: - - | M101: - - | N101: - - | O101: - - | P101: - - | Q101: - - | R101: - - | S101: - - | T101: - - | U101: - - | V101: - - | W101: - - | X101: - - | Y101: - - | Z101: - - | AA101: - - | AB101: - - | AC101: - - | AD101: - - | AE101: - - | AF101: - - | AG101: - - | AH101: - - | AI101: - -
A102: PRC000:nom_I_Electricit | B102: Electricity | C102: 20.24 | D102: 20.25 | E102: 20.03 | F102: 20.48 | G102: 20.87 | H102: 21.42 | I102: 22.24 | J102: 23.02 | K102: 23.67 | L102: 24.14 | M102: 24.57 | N102: 24.97 | O102: 25.38 | P102: 25.82 | Q102: 26.45 | R102: 27.03 | S102: 27.45 | T102: 27.95 | U102: 28.5 | V102: 29.16 | W102: 29.7 | X102: 30.2 | Y102: 30.79 | Z102: 31.39 | AA102: 32.03 | AB102: 32.73 | AC102: 33.42 | AD102: 34.15 | AE102: 35.01 | AF102: 35.83 | AG102: 36.64 | AH102: 37.51 | AI102: 0.02
B105: Transportation
A106: PRC000:nom_T_LiquefiedP | B106: Propane | C106: 16.63 | D106: 15.94 | E106: 16.82 | F106: 17.98 | G106: 18.9 | H106: 19.88 | I106: 21.13 | J106: 22.42 | K106: 23.36 | L106: 24.16 | M106: 24.86 | N106: 26.05 | O106: 26.65 | P106: 27.34 | Q106: 28.38 | R106: 29.3 | S106: 30.25 | T106: 31.28 | U106: 32.38 | V106: 33.49 | W106: 34.59 | X106: 35.67 | Y106: 36.77 | Z106: 38.12 | AA106: 39.36 | AB106: 40.65 | AC106: 41.99 | AD106: 43.36 | AE106: 44.93 | AF106: 46.58 | AG106: 48.15 | AH106: 49.73 | AI106: 0.036
A107: PRC000:nom_T_Ethan(E85) | B107: E85 3/ | C107: 24.54 | D107: 24.84 | E107: 31.39 | F107: 30.59 | G107: 31.54 | H107: 32.15 | I107: 32.12 | J107: 32.96 | K107: 34.02 | L107: 35.16 | M107: 36.37 | N107: 38.96 | O107: 40.28 | P107: 41.39 | Q107: 43.22 | R107: 44.85 | S107: 47.39 | T107: 48.26 | U107: 49.59 | V107: 52.14 | W107: 54.9 | X107: 57.47 | Y107: 59.28 | Z107: 63.29 | AA107: 65.53 | AB107: 67.78 | AC107: 70.15 | AD107: 72.73 | AE107: 80.55 | AF107: 84.65 | AG107: 86.85 | AH107: 89.59 | AI107: 0.043
A108: PRC000:nom_T_MotorGasol | B108: Motor Gasoline 4/ | C108: 22.17 | D108: 22.49 | E108: 23.07 | F108: 23.65 | G108: 24.13 | H108: 24.35 | I108: 25.19 | J108: 25.99 | K108: 26.94 | L108: 27.73 | M108: 28.76 | N108: 30.34 | O108: 31.25 | P108: 32.22 | Q108: 33.52 | R108: 34.8 | S108: 35.92 | T108: 37.15 | U108: 38.1 | V108: 39.38 | W108: 40.8 | X108: 41.86 | Y108: 43.11 | Z108: 44.78 | AA108: 46.18 | AB108: 47.63 | AC108: 49.38 | AD108: 50.71 | AE108: 52.84 | AF108: 54.77 | AG108: 56.62 | AH108: 58.44 | AI108: 0.032
A109: PRC000:nom_T_JetFuel | B109: Jet Fuel 5/ | C109: 14.64 | D109: 14.8 | E109: 15.19 | F109: 15.79 | G109: 16.29 | H109: 17.11 | I109: 17.59 | J109: 18.54 | K109: 19.01 | L109: 20.06 | M109: 20.8 | N109: 21.6 | O109: 22.55 | P109: 23.29 | Q109: 24.35 | R109: 25.28 | S109: 26.22 | T109: 27.16 | U109: 28.13 | V109: 29.08 | W109: 30.16 | X109: 30.99 | Y109: 32.11 | Z109: 33.49 | AA109: 34.62 | AB109: 35.84 | AC109: 37.45 | AD109: 38.44 | AE109: 40.17 | AF109: 41.83 | AG109: 43.36 | AH109: 44.61 | AI109: 0.037
