Workbook
Name nonlignite_multiplier: #REF!
Name tax_fuel_labels: '[1]Tax_Share of Price'!$A$2:$A$22
Name Tax_share: '[1]Tax_Share of Price'!$B$2:$AI$22

Sheet About
A1: IMFPbFT International Market Fuel Price by Fuel Type
A3: Source: | B3: Crude oil, selected petroleum products (petroleum, diesel, LPG) | D3: Start year coal, crude, and natural gas prices | F3: Petroleum gasoline, petroleum diesel, LPG
B4: Ministry of Petroleum and Natural Gas | D4: International Energy Agency | F4: Ministry of Petroleum and Natural Gas
B5: 2019 | D5: 2021 | F5: 2019
B6: Indian Petroleum and Nat Gas Statistics | D6: India Energy Outlook | F6: Indian Petroleum and Natural Gas Statistics 2018-2019
B7: http://petroleum.nic.in/sites/default/files/arep2020.pdf | D7: https://iea.blob.core.windows.net/assets/1de6d91e-e23f-4e02-b1fb-51fdd6283b22/India_Energy_Outlook_2021.pdf | F7: http://petroleum.nic.in/sites/default/files/arep2020.pdf
D8: Table 1.3 | F8: Table IV.4
B9: Table IV.4, page 80
B10: LNG | D10: Jet Fuel and Heavy Fuel Oil | F10: Crude oil scaling
B11: Petroleum Planning & Analysis Cell (PPAC) | D11: Petroleum Planning & Analysis Cell (PPAC) | F11: Energy Information Administration
B12: 2020 | D12: 2020 | F12: 2020
B13: Ready Reckoner: Oil Industry Information at a Glance | D13: Import/Export data tab | F13: Annual Energy Outlook
B14: https://www.ppac.gov.in/WriteReadData/Reports/202101120159244134186PPACRRNov2020WebVersion.pdf | D14: https://www.ppac.gov.in/content/212_1_ImportExport.aspx | F14: https://www.eia.gov/outlooks/aeo/
B15: Table 3.10, page 26 | D15: Data for Crude and Products - Value in Dollars (Historical); Data for Crude and Products - Quantity (Historical) | F15: Table 1
C17: Other fuels: fuel prices in EPS file fuels/BFPaT
A19: Notes | C19: 2019 to 2012 USD | D19: 0.89805482
A20: The prices in this variable should include export taxes, if any. In other words, they should be
A21: the prices paid on the global market.
A23: Electricity exports are handled separately (in the power sector), not in this variable.
A25: Nuclear here refers to nuclear fuel, i.e. uranium oxide, not electricity from nuclear plants.
A27: We estimate this value based on the prices seen within the United States.
A28: For fuels that vary by sector, we take a weighted average based on the first year consumption in the model.
A35: BTU per barrel crude oil | B35: 5698000 | C35: https://www.eia.gov/energyexplained/units-and-calculators/
A36: BTU per gallon motor gasoline | B36: 120286 | C36: https://www.eia.gov/energyexplained/units-and-calculators/
A37: BTU per gallon diesel fuel | B37: 137381 | C37: https://www.eia.gov/energyexplained/units-and-calculators/
A38: BTU per gallon propane | B38: 91452 | C38: https://www.eia.gov/energyexplained/units-and-calculators/
A39: gallons per barrel | B39: 42
A40: pounds per gallon propane | B40: 4.23 | C40: https://www.elgas.com.au/blog/1675-propane-conversion-values-pounds-gallons-btu-therms-ft-usa
A41: pounds per metric ton | B41: 2204.62
A42: 2019 to 2012 USD | B42: 0.89805482

Sheet Crude
B1: ref2020.d112119a | C1: 2019 | D1: 2020 | E1: 2021 | F1: 2022 | G1: 2023 | H1: 2024 | I1: 2025 | J1: 2026 | K1: 2027 | L1: 2028 | M1: 2029 | N1: 2030 | O1: 2031 | P1: 2032 | Q1: 2033 | R1: 2034 | S1: 2035 | T1: 2036 | U1: 2037 | V1: 2038 | W1: 2039 | X1: 2040 | Y1: 2041 | Z1: 2042 | AA1: 2043 | AB1: 2044 | AC1: 2045 | AD1: 2046 | AE1: 2047 | AF1: 2048 | AG1: 2049 | AH1: 2050
C3: Report | D3: Annual Energy Outlook 2020
C4: Scenario | D4: ref2020 | G4: Reference case
C5: Datekey | D5: d112119a
C6: Release Date | E6: January 2020
A10: SUP000 | B10: 1. Total Energy Supply, Disposition, and Price Summary
B11: (quadrillion Btu, unless otherwise noted)
AI12: 2019-
B13: Supply, Disposition, and Prices | C13: 2019 | D13: 2020 | E13: 2021 | F13: 2022 | G13: 2023 | H13: 2024 | I13: 2025 | J13: 2026 | K13: 2027 | L13: 2028 | M13: 2029 | N13: 2030 | O13: 2031 | P13: 2032 | Q13: 2033 | R13: 2034 | S13: 2035 | T13: 2036 | U13: 2037 | V13: 2038 | W13: 2039 | X13: 2040 | Y13: 2041 | Z13: 2042 | AA13: 2043 | AB13: 2044 | AC13: 2045 | AD13: 2046 | AE13: 2047 | AF13: 2048 | AG13: 2049 | AH13: 2050 | AI13: 2050
B15: Production
A16: SUP000:ba_CrudeOilLease | B16: Crude Oil and Lease Condensate | C16: 25.611994 | D16: 27.470049 | E16: 28.494802 | F16: 29.284983 | G16: 29.437077 | H16: 29.64554 | I16: 29.641726 | J16: 29.790983 | K16: 29.775187 | L16: 29.516684 | M16: 29.532515 | N16: 29.747253 | O16: 29.890884 | P16: 30.092388 | Q16: 30.068521 | R16: 29.858009 | S16: 29.67897 | T16: 29.407721 | U16: 29.011501 | V16: 28.693754 | W16: 28.532722 | X16: 28.853626 | Y16: 29.041647 | Z16: 29.058006 | AA16: 28.954979 | AB16: 28.623829 | AC16: 28.151617 | AD16: 27.620865 | AE16: 27.029858 | AF16: 26.494122 | AG16: 25.881308 | AH16: 24.79623 | AI16: -0.001044
A17: SUP000:ba_NaturalGasPla | B17: Natural Gas Plant Liquids | C17: 6.601902 | D17: 7.23189 | E17: 7.384439 | F17: 8.154555 | G17: 8.19707 | H17: 8.271167 | I17: 8.376472 | J17: 8.540577 | K17: 8.686964 | L17: 8.760511 | M17: 8.773496 | N17: 8.743604 | O17: 8.729358 | P17: 8.687426 | Q17: 8.662551 | R17: 8.694551 | S17: 8.730196 | T17: 8.706344 | U17: 8.6321 | V17: 8.586074 | W17: 8.573707 | X17: 8.595632 | Y17: 8.611508 | Z17: 8.613832 | AA17: 8.620247 | AB17: 8.584071 | AC17: 8.544112 | AD17: 8.467919 | AE17: 8.443357 | AF17: 8.449029 | AG17: 8.39084 | AH17: 8.190884 | AI17: 0.006981
A18: SUP000:ba_DryNaturalGas | B18: Dry Natural Gas | C18: 35.031666 | D18: 36.033657 | E18: 37.331188 | F18: 37.590195 | G18: 37.847775 | H18: 38.332695 | I18: 39.291294 | J18: 39.964729 | K18: 40.147495 | L18: 40.689774 | M18: 40.984024 | N18: 40.933514 | O18: 41.105022 | P18: 41.415512 | Q18: 41.783867 | R18: 42.303432 | S18: 42.534462 | T18: 42.787468 | U18: 43.062252 | V18: 43.329517 | W18: 43.569817 | X18: 43.935242 | Y18: 44.149738 | Z18: 44.370525 | AA18: 44.607227 | AB18: 44.817394 | AC18: 44.978981 | AD18: 45.196522 | AE18: 45.565365 | AF18: 46.018311 | AG18: 46.380791 | AH18: 46.616814 | AI18: 0.009259
A19: SUP000:ba_Coal | B19: Coal 1/ | C19: 13.567287 | D19: 12.301702 | E19: 11.91614 | F19: 12.097934 | G19: 11.528378 | H19: 11.431785 | I19: 10.959244 | J19: 11.374875 | K19: 11.346438 | L19: 11.251115 | M19: 11.165606 | N19: 11.150665 | O19: 11.095863 | P19: 11.075275 | Q19: 11.138651 | R19: 11.05944 | S19: 10.961893 | T19: 10.900166 | U19: 10.886232 | V19: 10.788899 | W19: 10.74003 | X19: 10.712185 | Y19: 10.675381 | Z19: 10.670083 | AA19: 10.665628 | AB19: 10.664737 | AC19: 10.636406 | AD19: 10.700363 | AE19: 10.683536 | AF19: 10.674273 | AG19: 10.64956 | AH19: 10.675206 | AI19: -0.007704
A20: SUP000:ba_NuclearPower | B20: Nuclear / Uranium 2/ | C20: 8.444715 | D20: 8.296324 | E20: 8.161823 | F20: 8.00919 | G20: 8.031043 | H20: 8.063392 | I20: 7.822189 | J20: 7.098251 | K20: 7.101179 | L20: 7.104901 | M20: 7.108607 | N20: 7.115708 | O20: 7.126846 | P20: 7.134424 | Q20: 6.972309 | R20: 6.798795 | S20: 6.813493 | T20: 6.82442 | U20: 6.826629 | V20: 6.828832 | W20: 6.828832 | X20: 6.739802 | Y20: 6.752901 | Z20: 6.762374 | AA20: 6.679939 | AB20: 6.687841 | AC20: 6.696404 | AD20: 6.700862 | AE20: 6.705318 | AF20: 6.708094 | AG20: 6.711448 | AH20: 6.716295 | AI20: -0.00736
A21: SUP000:ba_Hydropower | B21: Conventional Hydroelectric Power | C21: 2.627223 | D21: 2.628049 | E21: 2.60916 | F21: 2.559922 | G21: 2.51507 | H21: 2.473457 | I21: 2.458508 | J21: 2.399374 | K21: 2.392694 | L21: 2.383727 | M21: 2.377184 | N21: 2.371095 | O21: 2.372903 | P21: 2.363693 | Q21: 2.359036 | R21: 2.356455 | S21: 2.347385 | T21: 2.341803 | U21: 2.334253 | V21: 2.326471 | W21: 2.316797 | X21: 2.30683 | Y21: 2.298737 | Z21: 2.284055 | AA21: 2.284775 | AB21: 2.281344 | AC21: 2.272747 | AD21: 2.273704 | AE21: 2.281751 | AF21: 2.27995 | AG21: 2.273778 | AH21: 2.262525 | AI21: -0.004809
A22: SUP000:ba_Biomass | B22: Biomass 3/ | C22: 4.82346 | D22: 4.739875 | E22: 4.813442 | F22: 4.877365 | G22: 4.894251 | H22: 4.927381 | I22: 4.956337 | J22: 4.994683 | K22: 5.023758 | L22: 5.07172 | M22: 5.099788 | N22: 5.133343 | O22: 5.150183 | P22: 5.161369 | Q22: 5.174324 | R22: 5.189592 | S22: 5.204309 | T22: 5.217783 | U22: 5.227083 | V22: 5.240051 | W22: 5.251781 | X22: 5.269779 | Y22: 5.290954 | Z22: 5.310064 | AA22: 5.335333 | AB22: 5.360538 | AC22: 5.388065 | AD22: 5.414016 | AE22: 5.44756 | AF22: 5.475977 | AG22: 5.506855 | AH22: 5.535339 | AI22: 0.004451
A23: SUP000:ba_RenewableEner | B23: Other Renewable Energy 4/ | C23: 3.986613 | D23: 4.492028 | E23: 5.064552 | F23: 5.879107 | G23: 6.4833 | H23: 6.778963 | I23: 7.215426 | J23: 7.376397 | K23: 7.580525 | L23: 7.776433 | M23: 8.060765 | N23: 8.472414 | O23: 8.59905 | P23: 8.625295 | Q23: 8.670287 | R23: 8.711535 | S23: 8.961061 | T23: 9.156096 | U23: 9.308583 | V23: 9.491894 | W23: 9.665843 | X23: 9.871405 | Y23: 10.118544 | Z23: 10.417507 | AA23: 10.760035 | AB23: 11.121703 | AC23: 11.526014 | AD23: 11.799397 | AE23: 12.039868 | AF23: 12.214866 | AG23: 12.415702 | AH23: 12.642707 | AI23: 0.037932
A24: SUP000:ba_Other | B24: Other 5/ | C24: 1.418888 | D24: 0.827416 | E24: 0.769159 | F24: 0.813704 | G24: 0.904986 | H24: 0.936299 | I24: 0.882399 | J24: 0.736504 | K24: 0.703379 | L24: 0.718961 | M24: 0.716729 | N24: 0.678758 | O24: 0.673709 | P24: 0.67886 | Q24: 0.659729 | R24: 0.685346 | S24: 0.687655 | T24: 0.673603 | U24: 0.709672 | V24: 0.714011 | W24: 0.714281 | X24: 0.708251 | Y24: 0.716679 | Z24: 0.717886 | AA24: 0.720414 | AB24: 0.727804 | AC24: 0.736641 | AD24: 0.732407 | AE24: 0.752588 | AF24: 0.763026 | AG24: 0.771784 | AH24: 0.771613 | AI24: -0.019458
A25: SUP000:ba_Total | B25: Total | C25: 102.11375 | D25: 104.021 | E25: 106.5447 | F25: 109.26695 | G25: 109.83895 | H25: 110.86069 | I25: 111.60359 | J25: 112.27638 | K25: 112.75762 | L25: 113.27383 | M25: 113.81872 | N25: 114.34635 | O25: 114.74382 | P25: 115.23424 | Q25: 115.48928 | R25: 115.65715 | S25: 115.91942 | T25: 116.0154 | U25: 115.99831 | V25: 115.99951 | W25: 116.19381 | X25: 116.99274 | Y25: 117.65609 | Z25: 118.20432 | AA25: 118.62857 | AB25: 118.86927 | AC25: 118.93099 | AD25: 118.90606 | AE25: 118.94919 | AF25: 119.07764 | AG25: 118.98206 | AH25: 118.20762 | AI25: 0.004732
B27: Imports
A28: SUP000:ca_CrudeOil | B28: Crude Oil | C28: 15.553844 | D28: 15.955926 | E28: 14.746981 | F28: 14.677569 | G28: 14.71904 | H28: 15.418278 | I28: 14.744417 | J28: 15.570346 | K28: 14.863302 | L28: 15.257556 | M28: 15.021279 | N28: 14.408842 | O28: 14.093936 | P28: 14.057603 | Q28: 13.628367 | R28: 14.341786 | S28: 14.514404 | T28: 14.28753 | U28: 15.278381 | V28: 15.240164 | W28: 15.243741 | X28: 15.07306 | Y28: 15.523646 | Z28: 15.26584 | AA28: 15.396822 | AB28: 15.742918 | AC28: 16.219759 | AD28: 15.569624 | AE28: 16.714657 | AF28: 17.507576 | AG28: 17.736099 | AH28: 17.060543 | AI28: 0.002987
A29: SUP000:ca_PetroleumProd | B29: Petroleum and Other Liquids 6/ | C29: 4.821846 | D29: 4.868283 | E29: 4.253634 | F29: 4.223125 | G29: 4.250302 | H29: 4.26148 | I29: 4.086537 | J29: 3.826477 | K29: 3.768937 | L29: 3.592145 | M29: 3.521687 | N29: 3.555264 | O29: 3.535076 | P29: 3.544602 | Q29: 3.573062 | R29: 3.546082 | S29: 3.558302 | T29: 3.549997 | U29: 3.605515 | V29: 3.636478 | W29: 3.669384 | X29: 3.704446 | Y29: 3.763665 | Z29: 3.789318 | AA29: 3.821779 | AB29: 3.847737 | AC29: 3.916323 | AD29: 3.991392 | AE29: 4.004275 | AF29: 4.06438 | AG29: 4.142569 | AH29: 4.259105 | AI29: -0.003995
A30: SUP000:ca_NaturalGas | B30: Natural Gas | C30: 2.790417 | D30: 2.737625 | E30: 2.505311 | F30: 2.498467 | G30: 2.401366 | H30: 2.379171 | I30: 2.454679 | J30: 2.571234 | K30: 2.459452 | L30: 2.242131 | M30: 2.195501 | N30: 2.176357 | O30: 2.236829 | P30: 2.212133 | Q30: 2.110987 | R30: 2.082128 | S30: 2.056724 | T30: 2.042701 | U30: 2.06943 | V30: 2.063668 | W30: 2.065515 | X30: 2.069751 | Y30: 2.065326 | Z30: 2.055792 | AA30: 2.045062 | AB30: 2.024317 | AC30: 2.0111 | AD30: 2.004917 | AE30: 2.008925 | AF30: 1.993243 | AG30: 1.992269 | AH30: 1.991732 | AI30: -0.010818
A31: SUP000:ca_OtherImports | B31: Other 7/ | C31: 0.291471 | D31: 0.311483 | E31: 0.197879 | F31: 0.192162 | G31: 0.189143 | H31: 0.192052 | I31: 0.185666 | J31: 0.196601 | K31: 0.210408 | L31: 0.216355 | M31: 0.210658 | N31: 0.210847 | O31: 0.202959 | P31: 0.21087 | Q31: 0.211023 | R31: 0.219916 | S31: 0.217975 | T31: 0.213222 | U31: 0.212056 | V31: 0.210805 | W31: 0.211803 | X31: 0.211116 | Y31: 0.212711 | Z31: 0.211293 | AA31: 0.209861 | AB31: 0.208391 | AC31: 0.207404 | AD31: 0.202997 | AE31: 0.200745 | AF31: 0.198074 | AG31: 0.196592 | AH31: 0.195047 | AI31: -0.012874
A32: SUP000:ca_Total | B32: Total | C32: 23.457579 | D32: 23.873318 | E32: 21.703804 | F32: 21.591322 | G32: 21.559851 | H32: 22.250982 | I32: 21.4713 | J32: 22.164658 | K32: 21.302099 | L32: 21.308189 | M32: 20.949127 | N32: 20.351311 | O32: 20.068798 | P32: 20.025208 | Q32: 19.523439 | R32: 20.189913 | S32: 20.347406 | T32: 20.093451 | U32: 21.16538 | V32: 21.151117 | W32: 21.190443 | X32: 21.058371 | Y32: 21.56535 | Z32: 21.322243 | AA32: 21.473522 | AB32: 21.823364 | AC32: 22.354588 | AD32: 21.76893 | AE32: 22.9286 | AF32: 23.763273 | AG32: 24.06753 | AH32: 23.506428 | AI32: 6.7e-05
B34: Exports
A35: SUP000:da_Petroleum | B35: Petroleum and Other Liquids 8/ | C35: 16.702091 | D35: 19.42975 | E35: 19.203918 | F35: 20.904346 | G35: 21.426332 | H35: 22.721699 | I35: 22.201431 | J35: 23.043636 | K35: 22.691139 | L35: 22.76705 | M35: 22.613102 | N35: 22.22241 | O35: 22.091738 | P35: 22.258442 | Q35: 21.989693 | R35: 22.429056 | S35: 22.497185 | T35: 22.096922 | U35: 22.619617 | V35: 22.251133 | W35: 22.084496 | X35: 22.271158 | Y35: 22.863661 | Z35: 22.565138 | AA35: 22.484831 | AB35: 22.337135 | AC35: 22.191292 | AD35: 20.846298 | AE35: 21.177912 | AF35: 21.276543 | AG35: 20.703648 | AH35: 18.656487 | AI35: 0.003576
A36: SUP000:da_NaturalGas | B36: Natural Gas | C36: 4.483311 | D36: 5.391038 | E36: 6.298673 | F36: 6.64667 | G36: 6.840334 | H36: 7.332547 | I36: 8.27201 | J36: 9.033115 | K36: 9.262769 | L36: 9.576627 | M36: 9.78857 | N36: 9.935247 | O36: 9.964076 | P36: 10.002685 | Q36: 10.012971 | R36: 10.033694 | S36: 10.057024 | T36: 10.103948 | U36: 10.085648 | V36: 10.09483 | W36: 10.105273 | X36: 10.137658 | Y36: 10.119766 | Z36: 10.127851 | AA36: 10.137839 | AB36: 10.175268 | AC36: 10.159142 | AD36: 10.165966 | AE36: 10.173054 | AF36: 10.20885 | AG36: 10.192398 | AH36: 10.173193 | AI36: 0.026785
A37: SUP000:da_Coal | B37: Coal | C37: 2.384848 | D37: 2.087301 | E37: 2.218853 | F37: 2.73313 | G37: 2.749026 | H37: 2.765525 | I37: 2.784021 | J37: 2.799102 | K37: 2.782602 | L37: 2.714034 | M37: 2.662478 | N37: 2.660494 | O37: 2.659725 | P37: 2.65904 | Q37: 2.658399 | R37: 2.651743 | S37: 2.651135 | T37: 2.650574 | U37: 2.650053 | V37: 2.649575 | W37: 2.649134 | X37: 2.64873 | Y37: 2.648362 | Z37: 2.672349 | AA37: 2.697726 | AB37: 2.697454 | AC37: 2.705754 | AD37: 2.705624 | AE37: 2.69681 | AF37: 2.696648 | AG37: 2.705398 | AH37: 2.705374 | AI37: 0.004076
A38: SUP000:da_Total | B38: Total | C38: 23.57025 | D38: 26.908091 | E38: 27.721443 | F38: 30.284147 | G38: 31.015694 | H38: 32.819771 | I38: 33.257462 | J38: 34.875854 | K38: 34.736507 | L38: 35.057713 | M38: 35.064152 | N38: 34.818153 | O38: 34.715538 | P38: 34.920166 | Q38: 34.66106 | R38: 35.114494 | S38: 35.205341 | T38: 34.851444 | U38: 35.355316 | V38: 34.995537 | W38: 34.838905 | X38: 35.057549 | Y38: 35.63179 | Z38: 35.365337 | AA38: 35.320396 | AB38: 35.209858 | AC38: 35.056187 | AD38: 33.717888 | AE38: 34.047775 | AF38: 34.182041 | AG38: 33.601444 | AH38: 31.535053 | AI38: 0.009435
A40: SUP000:ea_Discrepancy | B40: Discrepancy 9/ | C40: 2.005173 | D40: 1.395311 | E40: 0.313889 | F40: 0.279282 | G40: 0.270277 | H40: 0.280891 | I40: 0.242027 | J40: 0.302582 | K40: 0.246792 | L40: 0.316021 | M40: 0.313488 | N40: 0.326683 | O40: 0.305225 | P40: 0.30619 | Q40: 0.196102 | R40: 0.262886 | S40: 0.272327 | T40: 0.187534 | U40: 0.302933 | V40: 0.293968 | W40: 0.297363 | X40: 0.276245 | Y40: 0.310047 | Z40: 0.27367 | AA40: 0.284153 | AB40: 0.290325 | AC40: 0.27346 | AD40: 0.243225 | AE40: 0.282581 | AF40: 0.31216 | AG40: 0.295788 | AH40: 0.254417 | AI40: - -
B42: Consumption
A43: SUP000:fa_PetroleumProd | B43: Petroleum and Other Liquids 10/ | C43: 38.035393 | D43: 38.281551 | E43: 38.194523 | F43: 38.067791 | G43: 37.910881 | H43: 37.636486 | I43: 37.401596 | J43: 37.254978 | K43: 37.025654 | L43: 36.959 | M43: 36.854237 | N43: 36.842789 | O43: 36.79459 | P43: 36.740559 | Q43: 36.651112 | R43: 36.683517 | S43: 36.670483 | T43: 36.619984 | U43: 36.633987 | V43: 36.659451 | W43: 36.704563 | X43: 36.747784 | Y43: 36.86544 | Z43: 36.99564 | AA43: 37.145874 | AB43: 37.317387 | AC43: 37.533596 | AD43: 37.730907 | AE43: 37.954109 | AF43: 38.181633 | AG43: 38.41666 | AH43: 38.663658 | AI43: 0.000529
A44: SUP000:fa_NaturalGas | B44: Natural Gas | C44: 32.14539 | D44: 32.202682 | E44: 33.071632 | F44: 32.998856 | G44: 32.985462 | H44: 32.969063 | I44: 33.063847 | J44: 33.072159 | K44: 32.902473 | L44: 32.90086 | M44: 32.929447 | N44: 32.68071 | O44: 32.879433 | P44: 33.152905 | Q44: 33.413578 | R44: 33.883789 | S44: 34.050732 | T44: 34.238548 | U44: 34.522491 | V44: 34.760571 | W44: 34.983902 | X44: 35.316647 | Y44: 35.527851 | Z44: 35.729935 | AA44: 35.940025 | AB44: 36.082645 | AC44: 36.243198 | AD44: 36.443565 | AE44: 36.785 | AF44: 37.169861 | AG44: 37.552456 | AH44: 37.810448 | AI44: 0.00525
A45: SUP000:fa_Coal | B45: Coal 11/ | C45: 11.249906 | D45: 10.258844 | E45: 9.692323 | F45: 9.344917 | G45: 8.750343 | H45: 8.628566 | I45: 8.145056 | J45: 8.559067 | K45: 8.541109 | L45: 8.518984 | M45: 8.481165 | N45: 8.459363 | O45: 8.403361 | P45: 8.385563 | Q45: 8.449744 | R45: 8.376008 | S45: 8.278006 | T45: 8.216821 | U45: 8.203781 | V45: 8.111191 | W45: 8.057528 | X45: 8.031965 | Y45: 7.995692 | Z45: 7.965323 | AA45: 7.935738 | AB45: 7.933951 | AC45: 7.896763 | AD45: 7.962496 | AE45: 7.953084 | AF45: 7.944196 | AG45: 7.91083 | AH45: 7.936447 | AI45: -0.011192
A46: SUP000:fa_NuclearPower | B46: Nuclear / Uranium 2/ | C46: 8.444715 | D46: 8.296324 | E46: 8.161823 | F46: 8.00919 | G46: 8.031043 | H46: 8.063392 | I46: 7.822189 | J46: 7.098251 | K46: 7.101179 | L46: 7.104901 | M46: 7.108607 | N46: 7.115708 | O46: 7.126846 | P46: 7.134424 | Q46: 6.972309 | R46: 6.798795 | S46: 6.813493 | T46: 6.82442 | U46: 6.826629 | V46: 6.828832 | W46: 6.828832 | X46: 6.739802 | Y46: 6.752901 | Z46: 6.762374 | AA46: 6.679939 | AB46: 6.687841 | AC46: 6.696404 | AD46: 6.700862 | AE46: 6.705318 | AF46: 6.708094 | AG46: 6.711448 | AH46: 6.716295 | AI46: -0.00736
A47: SUP000:fa_Hydropower | B47: Conventional Hydroelectric Power | C47: 2.627223 | D47: 2.628049 | E47: 2.60916 | F47: 2.559922 | G47: 2.51507 | H47: 2.473457 | I47: 2.458508 | J47: 2.399374 | K47: 2.392694 | L47: 2.383727 | M47: 2.377184 | N47: 2.371095 | O47: 2.372903 | P47: 2.363693 | Q47: 2.359036 | R47: 2.356455 | S47: 2.347385 | T47: 2.341803 | U47: 2.334253 | V47: 2.326471 | W47: 2.316797 | X47: 2.30683 | Y47: 2.298737 | Z47: 2.284055 | AA47: 2.284775 | AB47: 2.281344 | AC47: 2.272747 | AD47: 2.273704 | AE47: 2.281751 | AF47: 2.27995 | AG47: 2.273778 | AH47: 2.262525 | AI47: -0.004809
A48: SUP000:fa_Biomass | B48: Biomass 12/ | C48: 3.225397 | D48: 3.108829 | E48: 3.111676 | F48: 3.142795 | G48: 3.15063 | H48: 3.167369 | I48: 3.186579 | J48: 3.215469 | K48: 3.232934 | L48: 3.257947 | M48: 3.275252 | N48: 3.298345 | O48: 3.311273 | P48: 3.31843 | Q48: 3.327163 | R48: 3.338353 | S48: 3.348562 | T48: 3.357383 | U48: 3.361934 | V48: 3.370085 | W48: 3.376801 | X48: 3.389724 | Y48: 3.405491 | Z48: 3.419021 | AA48: 3.438693 | AB48: 3.456382 | AC48: 3.476807 | AD48: 3.496759 | AE48: 3.524088 | AF48: 3.546339 | AG48: 3.570926 | AH48: 3.59317 | AI48: 0.003489
A49: SUP000:fa_RenewableEner | B49: Other Renewable Energy 4/ | C49: 3.986613 | D49: 4.492028 | E49: 5.064552 | F49: 5.879107 | G49: 6.4833 | H49: 6.778963 | I49: 7.215426 | J49: 7.376397 | K49: 7.580525 | L49: 7.776433 | M49: 8.060765 | N49: 8.472414 | O49: 8.59905 | P49: 8.625295 | Q49: 8.670287 | R49: 8.711535 | S49: 8.961061 | T49: 9.156096 | U49: 9.308583 | V49: 9.491894 | W49: 9.665843 | X49: 9.871405 | Y49: 10.118544 | Z49: 10.417507 | AA49: 10.760035 | AB49: 11.121703 | AC49: 11.526014 | AD49: 11.799397 | AE49: 12.039868 | AF49: 12.214866 | AG49: 12.415702 | AH49: 12.642707 | AI49: 0.037932
A50: SUP000:fa_Other | B50: Other 13/ | C50: 0.281268 | D50: 0.322602 | E50: 0.307481 | F50: 0.292265 | G50: 0.286105 | H50: 0.293724 | I50: 0.282206 | J50: 0.286904 | K50: 0.299847 | L50: 0.30642 | M50: 0.303551 | N50: 0.312399 | O50: 0.3044 | P50: 0.312225 | Q50: 0.312328 | R50: 0.321226 | S50: 0.319437 | T50: 0.314813 | U50: 0.31378 | V50: 0.312619 | W50: 0.313725 | X50: 0.313166 | Y50: 0.31495 | Z50: 0.313708 | AA50: 0.312468 | AB50: 0.311192 | AC50: 0.310404 | AD50: 0.306194 | AE50: 0.304216 | AF50: 0.301768 | AG50: 0.300562 | AH50: 0.299321 | AI50: 0.002009
A51: SUP000:fa_Total | B51: Total | C51: 99.995903 | D51: 99.590912 | E51: 100.21317 | F51: 100.29485 | G51: 100.11283 | H51: 100.01101 | I51: 99.575401 | J51: 99.262596 | K51: 99.076424 | L51: 99.208282 | M51: 99.390205 | N51: 99.552826 | O51: 99.791855 | P51: 100.03309 | Q51: 100.15556 | R51: 100.46968 | S51: 100.78915 | T51: 101.06987 | U51: 101.50544 | V51: 101.86112 | W51: 102.24799 | X51: 102.71732 | Y51: 103.2796 | Z51: 103.88756 | AA51: 104.49754 | AB51: 105.19245 | AC51: 105.95593 | AD51: 106.71388 | AE51: 107.54743 | AF51: 108.34671 | AG51: 109.15236 | AH51: 109.92458 | AI51: 0.003058
B53: Prices (2019 dollars per unit)
A54: SUP000:ha_WorldOilPrice | B54: Brent Spot Price (dollars per barrel) | C54: 63.371998 | D54: 58.505806 | E54: 61.63221 | F54: 64.001991 | G54: 65.341621 | H54: 67.003448 | I54: 68.735039 | J54: 70.371643 | K54: 71.580528 | L54: 73.166756 | M54: 74.728348 | N54: 75.831558 | O54: 77.375023 | P54: 78.623016 | Q54: 80.499657 | R54: 81.877769 | S54: 83.325172 | T54: 84.876801 | U54: 86.175789 | V54: 87.637856 | W54: 89.162689 | X54: 90.480171 | Y54: 91.638084 | Z54: 93.707344 | AA54: 94.894356 | AB54: 96.306297 | AC54: 97.76226 | AD54: 99.024994 | AE54: 100.73233 | AF54: 102.33839 | AG54: 103.79858 | AH54: 104.98383 | AI54: 0.016417
A55: SUP000:ha_ForLowSulfLit | B55: West Texas Intermediate Spot Price (dollars per barrel) | C55: 56.261002 | D55: 53.136776 | E55: 58.231895 | F55: 59.639107 | G55: 60.805595 | H55: 63.003368 | I55: 64.557953 | J55: 66.193848 | K55: 67.774689 | L55: 68.532478 | M55: 70.067909 | N55: 71.338821 | O55: 73.019859 | P55: 73.873024 | Q55: 76.580032 | R55: 77.812531 | S55: 79.355728 | T55: 81.41993 | U55: 81.804588 | V55: 83.338547 | W55: 84.788506 | X55: 85.737099 | Y55: 86.74752 | Z55: 89.025314 | AA55: 90.120522 | AB55: 91.401299 | AC55: 93.352013 | AD55: 94.050812 | AE55: 96.415947 | AF55: 98.235748 | AG55: 99.713112 | AH55: 100.72344 | AI55: 0.018964
A56: SUP000:ha_GasPriceHenry | B56: Natural Gas at Henry Hub (dollars per mmBtu) | C56: 2.567243 | D56: 2.435248 | E56: 2.493109 | F56: 2.490749 | G56: 2.523033 | H56: 2.617738 | I56: 2.839973 | J56: 3.081076 | K56: 3.232042 | L56: 3.319359 | M56: 3.331645 | N56: 3.285855 | O56: 3.239649 | P56: 3.258222 | Q56: 3.320172 | R56: 3.36772 | S56: 3.36251 | T56: 3.358324 | U56: 3.403626 | V56: 3.431597 | W56: 3.440993 | X56: 3.444895 | Y56: 3.443121 | Z56: 3.465679 | AA56: 3.48235 | AB56: 3.495807 | AC56: 3.51752 | AD56: 3.552241 | AE56: 3.596649 | AF56: 3.627521 | AG56: 3.647321 | AH56: 3.694113 | AI56: 0.011808
A57: SUP000:ha_CoalMinemouth | B57: Coal, Minemouth (dollars per ton) 14/ | C57: 34.304489 | D57: 32.995308 | E57: 34.696388 | F57: 34.934284 | G57: 34.221855 | H57: 34.061409 | I57: 34.292255 | J57: 33.714443 | K57: 33.938473 | L57: 33.576248 | M57: 33.236691 | N57: 33.546734 | O57: 33.568375 | P57: 33.668274 | Q57: 33.778675 | R57: 33.89706 | S57: 34.30653 | T57: 34.600712 | U57: 35.440517 | V57: 35.844482 | W57: 36.508194 | X57: 36.632168 | Y57: 36.780327 | Z57: 36.947044 | AA57: 37.08009 | AB57: 37.165894 | AC57: 37.497112 | AD57: 37.419582 | AE57: 37.52877 | AF57: 37.622448 | AG57: 37.723869 | AH57: 37.805992 | AI57: 0.00314
A58: SUP000:ha_CoalMineBtu | B58: Coal, Minemouth (dollars per million Btu) 14/ | C58: 1.706012 | D58: 1.623933 | E58: 1.665675 | F58: 1.663128 | G58: 1.63487 | H58: 1.625933 | I58: 1.63371 | J58: 1.615628 | K58: 1.625014 | L58: 1.608162 | M58: 1.597794 | N58: 1.611644 | O58: 1.61495 | P58: 1.62017 | Q58: 1.625653 | R58: 1.631636 | S58: 1.646284 | T58: 1.657024 | U58: 1.687355 | V58: 1.702707 | W58: 1.723963 | X58: 1.728505 | Y58: 1.734878 | Z58: 1.74166 | AA58: 1.747105 | AB58: 1.751634 | AC58: 1.764135 | AD58: 1.764581 | AE58: 1.770754 | AF58: 1.776235 | AG58: 1.78148 | AH58: 1.785845 | AI58: 0.001476
A59: SUP000:ha_CoalDelivered | B59: Coal, Delivered (dollars per million Btu) 15/ | C59: 2.189812 | D59: 2.184627 | E59: 2.141867 | F59: 2.110086 | G59: 2.095121 | H59: 2.091057 | I59: 2.083735 | J59: 2.084596 | K59: 2.099018 | L59: 2.084966 | M59: 2.08854 | N59: 2.088609 | O59: 2.089755 | P59: 2.089417 | Q59: 2.096385 | R59: 2.100292 | S59: 2.098434 | T59: 2.10177 | U59: 2.109018 | V59: 2.110163 | W59: 2.112422 | X59: 2.109144 | Y59: 2.112328 | Z59: 2.117609 | AA59: 2.121895 | AB59: 2.124453 | AC59: 2.130141 | AD59: 2.128616 | AE59: 2.132633 | AF59: 2.134578 | AG59: 2.135415 | AH59: 2.136426 | AI59: -0.000796
A60: SUP000:ha_Electricity(c | B60: Electricity (cents per kilowatthour) | C60: 10.391058 | D60: 10.212733 | E60: 10.144772 | F60: 10.119162 | G60: 10.121079 | H60: 10.184604 | I60: 10.321589 | J60: 10.438571 | K60: 10.493044 | L60: 10.451485 | M60: 10.390381 | N60: 10.370628 | O60: 10.328291 | P60: 10.280963 | Q60: 10.315948 | R60: 10.32381 | S60: 10.26488 | T60: 10.233636 | U60: 10.199707 | V60: 10.21621 | W60: 10.185767 | X60: 10.131741 | Y60: 10.114 | Z60: 10.088268 | AA60: 10.056148 | AB60: 10.052033 | AC60: 10.030838 | AD60: 10.001727 | AE60: 10.003813 | AF60: 9.97754 | AG60: 9.932341 | AH60: 9.903041 | AI60: -0.001551
B63: Prices (nominal dollars per unit)
A64: SUP000:nom_ImportRACost | B64: Brent Spot Price (dollars per barrel) | C64: 63.371998 | D64: 59.932999 | E64: 64.689865 | F64: 68.861427 | G64: 72.013763 | H64: 75.530228 | I64: 79.240425 | J64: 83.028534 | K64: 86.475121 | L64: 90.513268 | M64: 94.651405 | N64: 98.288391 | O64: 102.55667 | P64: 106.52165 | Q64: 111.47933 | R64: 115.85136 | S64: 120.46687 | T64: 125.41026 | U64: 130.15895 | V64: 135.32948 | W64: 140.76572 | X64: 146.03995 | Y64: 151.26097 | Z64: 158.22603 | AA64: 163.91548 | AB64: 170.23128 | AC64: 176.88776 | AD64: 183.42715 | AE64: 191.10295 | AF64: 198.93951 | AG64: 206.79265 | AH64: 214.27734 | AI64: 0.040081
A65: SUP000:nom_ForLowSulfLi | B65: West Texas Intermediate Spot Price (dollars per barrel) | C65: 56.261002 | D65: 54.432999 | E65: 61.120861 | F65: 64.167282 | G65: 67.014549 | H65: 71.021103 | I65: 74.424919 | J65: 78.099335 | K65: 81.87735 | L65: 84.780281 | M65: 88.748466 | N65: 92.465172 | O65: 96.784126 | P65: 100.08617 | Q65: 106.05126 | R65: 110.09933 | S65: 114.72807 | T65: 120.30254 | U65: 123.55674 | V65: 128.69054 | W65: 133.85997 | X65: 138.38437 | Y65: 143.18843 | Z65: 150.32037 | AA65: 155.66942 | AB65: 161.56119 | AC65: 168.90799 | AD65: 174.21332 | AE65: 182.91419 | AF65: 190.96422 | AG65: 198.65338 | AH65: 205.58166 | AI65: 0.042687
A66: SUP000:nom_Gas@HenryHub | B66: Natural Gas at Henry Hub (dollars per mmBtu) | C66: 2.567243 | D66: 2.494653 | E66: 2.616796 | F66: 2.679862 | G66: 2.780663 | H66: 2.950869 | I66: 3.274031 | J66: 3.635231 | K66: 3.90457 | L66: 4.106319 | M66: 4.219883 | N66: 4.258932 | O66: 4.29399 | P66: 4.414371 | Q66: 4.597914 | R66: 4.76509 | S66: 4.861329 | T66: 4.962113 | U66: 5.1408 | V66: 5.299037 | W66: 5.432473 | X66: 5.560249 | Y66: 5.683333 | Z66: 5.851842 | AA66: 6.015227 | AB66: 6.179199 | AC66: 6.364482 | AD66: 6.579929 | AE66: 6.823333 | AF66: 7.051677 | AG66: 7.266372 | AH66: 7.539873 | AI66: 0.035365
A67: SUP000:nom_CoalMinemout | B67: Coal, Minemouth (dollars per ton) 14/ | C67: 34.304489 | D67: 33.800194 | E67: 36.417725 | F67: 37.586716 | G67: 37.716305 | H67: 38.396023 | I67: 39.533447 | J67: 39.778252 | K67: 41.000446 | L67: 41.536564 | M67: 42.097805 | N67: 43.481297 | O67: 44.493183 | P67: 45.615143 | Q67: 46.778133 | R67: 47.961994 | S67: 49.598457 | T67: 51.124504 | U67: 53.528965 | V67: 55.350685 | W67: 57.63736 | X67: 59.126328 | Y67: 60.710873 | Z67: 62.385551 | AA67: 64.050179 | AB67: 65.694534 | AC67: 67.846008 | AD67: 69.313484 | AE67: 71.197189 | AF67: 73.135712 | AG67: 75.155357 | AH67: 77.163956 | AI67: 0.026495
A68: SUP000:nom_CoalMineBtu | B68: Coal, Minemouth (dollars per million Btu) 14/ | C68: 1.706012 | D68: 1.663548 | E68: 1.748311 | F68: 1.789403 | G68: 1.801809 | H68: 1.832847 | I68: 1.883405 | J68: 1.906211 | K68: 1.963149 | L68: 1.989428 | M68: 2.023776 | N68: 2.088918 | O68: 2.140534 | P68: 2.195072 | Q68: 2.251273 | R68: 2.308652 | S68: 2.380105 | T68: 2.448346 | U68: 2.548563 | V68: 2.629302 | W68: 2.721709 | X68: 2.789902 | Y68: 2.863649 | Z68: 2.940814 | AA68: 3.017857 | AB68: 3.096194 | AC68: 3.191967 | AD68: 3.26859 | AE68: 3.359361 | AF68: 3.45289 | AG68: 3.549152 | AH68: 3.645 | AI68: 0.024793
A69: SUP000:nom_CoalDeliverd | B69: Coal, Delivered (dollars per million Btu) 15/ | C69: 2.189812 | D69: 2.237919 | E69: 2.248128 | F69: 2.270297 | G69: 2.309057 | H69: 2.357162 | I69: 2.402211 | J69: 2.459527 | K69: 2.535785 | L69: 2.579273 | M69: 2.645358 | N69: 2.707131 | O69: 2.769865 | P69: 2.830827 | Q69: 2.903163 | R69: 2.971767 | S69: 3.033798 | T69: 3.105484 | U69: 3.185438 | V69: 3.258493 | W69: 3.334989 | X69: 3.404274 | Y69: 3.486681 | Z69: 3.57561 | AA69: 3.665249 | AB69: 3.755188 | AC69: 3.854206 | AD69: 3.942903 | AE69: 4.045896 | AF69: 4.149487 | AG69: 4.254279 | AH69: 4.360555 | AI69: 0.022467
A70: SUP000:nom_Electricity | B70: Electricity (cents per kilowatthour) | C70: 10.391058 | D70: 10.461864 | E70: 10.648067 | F70: 10.887472 | G70: 11.154559 | H70: 11.480684 | I70: 11.899129 | J70: 12.316031 | K70: 12.676454 | L70: 12.929342 | M70: 13.160523 | N70: 13.441796 | O70: 13.689627 | P70: 13.929066 | Q70: 14.28596 | R70: 14.607475 | S70: 14.840388 | T70: 15.120773 | U70: 15.405524 | V70: 15.775767 | W70: 16.080793 | X70: 16.353184 | Y70: 16.694515 | Z70: 17.034168 | AA70: 17.370457 | AB70: 17.768002 | AC70: 18.14946 | AD70: 18.526518 | AE70: 18.978594 | AF70: 19.39572 | AG70: 19.787699 | AH70: 20.21261 | AI70: 0.021695
B72: 1/ Includes waste coal.
B73: 2/ These values represent the energy obtained from uranium when it is used in light water reactors. The total energy content of uranium
B74: is much larger, but alternative processes are required to take advantage of it.
B75: 3/ Includes grid-connected electricity from wood and wood waste; biomass, such as corn, used for liquid fuels production; and non-electric
B76: energy demand from wood. Refer to Table 17 for details.
B77: 4/ Includes grid-connected electricity from landfill gas; biogenic municipal waste; wind; photovoltaic and solar thermal sources; and
B78: non-electric energy from renewable sources, such as active and passive solar systems. Excludes electricity imports using renewable sources
B79: and nonmarketed renewable energy. See Table 17 for selected nonmarketed residential and commercial renewable energy data.
B80: 5/ Includes non-biogenic municipal waste, hydrogen, methanol, and some domestic inputs to refineries.
B81: 6/ Includes imports of finished petroleum products, unfinished oils, alcohols, ethers, blending components, and renewable fuels such as ethanol.
B82: 7/ Includes coal, coal coke (net), and electricity (net). Excludes imports of fuel used in nuclear power plants.
B83: 8/ Includes crude oil, petroleum products, ethanol, and biodiesel.
... B100: Energy Modeling System run ref2020.d112119a. Projections: EIA, AEO2020 National Energy Modeling System run ref2020.d112119a.

Sheet India Petroleum Products
C23: crude | D23: petrol | E23: diesel | F23: kerosene | G23: LPG
B24: 2018-2019 | C24: 69.88 | D24: 75.58 | E24: 82.51 | F24: 82.24 | G24: 526
B25: correct units | D25: =D24/About!B39/About!B36*About!B42 -> 1.3435238e-05 | E25: =E24/About!B39/About!B37*About!B42 -> 1.2842024e-05 | G25: =G24/About!B38*About!B42*About!B40/About!B41 -> 9.910647e-06
B26: US value | C26: =Crude!C54 -> 63.371998
B27: ratio to US | C27: =C24/Crude!C54 -> 1.1026952

Sheet IEA
A2: crude oil | B2: 2019 USD / barrel | C2: 63
A3: natural gas | B3: 2019 USD / Mbtu | C3: 11
A4: coal | B4: 2019 USD / tonne | C4: 68
A6: crude oil | B6: 2012 USD / BTU | C6: =C2/B25*About!D19 -> 9.9415662e-06
A7: natural gas | B7: 2012 USD / BTU | C7: =C3/1000000*About!D19 -> 9.878603e-06
A8: coal | B8: 2012 USD / BTU | C8: =C4/1000/6000/B26 -> 2.8566363e-06
A25: BTU per gallon crude | B25: 5691000 | C25: https://www.eia.gov/energyexplained/units-and-calculators/
A26: kcal per BTU | B26: 3.96737 | C26: https://www.convertunits.com/from/btu/to/kcal

Sheet LNG
A1: Import Quantity and Value of LNG in India
A2: Financial Year | B2: LNG Import Quantity (MMT) | C2: Value (Million USD) | D2: Price (USD/MT)
A3: 2019 | B3: 21.7 | C3: 10253 | D3: =C3/B3 -> 472.48848
A4: 2020 | B4: 25.6 | C4: 9489 | D4: =C4/B4 -> 370.66406
G13: Source: | H13: PPAC

Sheet Data - Other Petroleum Producs
E3: Petroleum Planning & Analysis Cell
A5: Period : 1998-99 - 2019-20
A6: ('Million US$)
A7: Import/Export of Crude oil and Petroleum Products
A8: IMPORT/EXPORT | B8: 1998-99 | C8: 1999-2000 | D8: 2000-01 | E8: 2001-02 | F8: 2002-03 | G8: 2003-04 | H8: 2004-05 | I8: 2005-06 | J8: 2006-07 | K8: 2007-08 | L8: 2008-09 | M8: 2009-10 | N8: 2010-11 | O8: 2011-12 | P8: 2012-13 | Q8: 2013-14 | R8: 2014-15 | S8: 2015-16 | T8: 2016-17 | U8: 2017-18 | V8: 2018-19 | W8: 2019-20
A9: IMPORT^
A10: CRUDE OIL$ | B10: 3518 | C10: 9210 | D10: 14403 | E10: 12635 | F10: 15759 | G10: 18268 | H10: 25990 | I10: 38776 | J10: 48389 | K10: 67988 | L10: 76876 | M10: 79553 | N10: 100080 | O10: 139689.92 | P10: 144293.12 | Q10: 142961.59 | R10: 112743.58 | S10: 63972.376 | T10: 70196.061 | U10: 87803.146 | V10: 111914.67 | W10: 101376.19
A11: PRODUCTS
A12: LPG | B12: 300 | C12: 414 | D12: 291 | E12: 168 | F12: 388 | G12: 561 | H12: 998 | I12: 1575 | J12: 1276 | K12: 2163 | L12: 1733 | M12: 1767.1847 | N12: 3469.1717 | O12: 5584.0221 | P12: 5803.2922 | Q12: 6144.0164 | R12: 5954.7569 | S12: 3921.7221 | T12: 4774.5942 | U12: 5848.8457 | V12: 7178.232 | W12: 7069.9862
A13: MS | B13: 45 | C13: 0 | D13: 0 | E13: 0 | F13: 0 | G13: 0 | H13: 114 | I13: 293 | J13: 290 | K13: 281 | L13: 352 | M13: 266.12711 | N13: 1403.3623 | O13: 716.13787 | P13: 159.86164 | Q13: 247.54491 | R13: 375.45 | S13: 648.2648 | T13: 239.491 | U13: 90.872213 | V13: 444.88045 | W13: 1356.8026
A14: Naphtha | B14: 315 | C14: 452 | D14: 897 | E14: 724 | F14: 729 | G14: 626 | H14: 841 | I14: 1209 | J14: 3142 | K14: 4582 | L14: 3802 | M14: 1029.1056 | N14: 1452.9948 | O14: 2022.4442 | P14: 1691.3716 | Q14: 981.7382 | R14: 744.49111 | S14: 1462.9304 | T14: 1239.774 | U14: 1260.6556 | V14: 1390.5608 | W14: 941.03583
A15: ATF | B15: 0 | C15: 0 | D15: 0 | E15: 0 | F15: 0 | G15: 0 | H15: 0 | I15: 0 | J15: 0 | K15: 0 | L15: 0 | N15: 0 | O15: 0 | P15: 0 | Q15: 0 | R15: 113.70392 | S15: 135.31372 | T15: 163.38542 | U15: 178.43668 | V15: 199.98127 | W15: 44.667822
A16: SKO | B16: 923 | C16: 1276 | D16: 521 | E16: 81 | F16: 166 | G16: 191 | H16: 98 | I16: 597 | J16: 933 | K16: 2072 | L16: 1486 | M16: 614.22717 | N16: 1080.9681 | O16: 596.83554 | P16: 0 | Q16: 0 | R16: 28.813641 | S16: 24.659992 | T16: 0 | U16: 0 | V16: 0 | W16: 0
A17: HSD | B17: 1134 | C17: 854 | D17: 0 | E17: 6 | F17: 24 | G17: 25 | H17: 361 | I17: 435 | J17: 589 | K17: 2265 | L17: 2198 | M17: 1331.5644 | N17: 1505.0639 | O17: 1096.036 | P17: 506.88767 | Q17: 74.072632 | R17: 108.41536 | S17: 91.621161 | T17: 438.26333 | U17: 659.50824 | V17: 360.45934 | W17: 1632.3766
A18: LOBS/ Lube oil | B18: 35 | C18: 68 | D18: 123 | E18: 123 | F18: 108 | G18: 213 | H18: 215 | I18: 661 | J18: 748 | K18: 844 | L18: 988 | M18: 732.67094 | N18: 854.70487 | O18: 1707.5715 | P18: 2067.5304 | Q18: 2121.5847 | R18: 2067.2065 | S18: 1438.875 | T18: 1275.6037 | U18: 1860.1072 | V18: 1909.5383 | W18: 1672.9278
A19: Fuel Oil | B19: 142 | C19: 199 | D19: 286 | E19: 306 | F19: 403 | G19: 337 | H19: 374 | I19: 685 | J19: 1142 | K19: 1861 | L19: 1748 | M19: 405.54544 | N19: 527.18041 | O19: 911.78997 | P19: 777.60723 | Q19: 942.13116 | R19: 598.74818 | S19: 363.3913 | T19: 273.42338 | U19: 499.38452 | V19: 696.48878 | W19: 1649.7757
A20: Bitumen | B20: 0 | C20: 0 | D20: 0 | E20: 1 | F20: 0 | G20: 1 | H20: 4 | I20: 5 | J20: 4 | K20: 13 | L20: 43.022 | M20: 28.920326 | N20: 43.495004 | O20: 40.240202 | P20: 49.799675 | Q20: 132.43756 | R20: 261.51723 | S20: 278.89057 | T20: 242.41381 | U20: 293.24164 | V20: 309.13012 | W20: 509.73769
A21: Others& | B21: 1 | C21: 1 | D21: 524 | E21: 102 | F21: 4 | G21: 160 | H21: 273 | I21: 842 | J21: 944 | K21: 1045 | L21: 1207 | M21: 912.25609 | N21: 1731.3884 | O21: 1513.7227 | P21: 1533.6298 | Q21: 1822.2735 | R21: 1884.8814 | S21: 1586.4007 | T21: 1966.8227 | U21: 2945.9146 | V21: 3851.5187 | W21: 2811.3684
A22: PRODUCT IMPORT* | B22: =SUM(B12:B21) -> 2895 | C22: =SUM(C12:C21) -> 3264 | D22: =SUM(D12:D21) -> 2642 | E22: =SUM(E12:E21) -> 1511 | F22: =SUM(F12:F21) -> 1822 | G22: =SUM(G12:G21) -> 2114 | H22: =SUM(H12:H21) -> 3278 | I22: =SUM(I12:I21) -> 6302 | ... W22: =SUM(W12:W21) -> 17688.679
A24: TOTAL IMPORTS | B24: =+B10+B22 -> 6413 | C24: =+C10+C22 -> 12474 | D24: =+D10+D22 -> 17045 | E24: =+E10+E22 -> 14146 | F24: =+F10+F22 -> 17581 | G24: =+G10+G22 -> 20382 | H24: =+H10+H22 -> 29268 | I24: =+I10+I22 -> 45078 | ... W24: =+W10+W22 -> 119064.87
A26: PRODUCT EXPORT @
A27: LPG | B27: 0 | C27: 0 | D27: 0 | E27: 0 | F27: 0 | G27: 0 | H27: 69 | I27: 37 | J27: 75 | K27: 99 | L27: 97 | M27: 104 | N27: 151 | O27: 195.03531 | P27: 235.95505 | Q27: 259.57026 | R27: 235.74398 | S27: 119.53333 | T27: 172.90567 | U27: 231.16794 | V27: 282.75008 | W27: 276.98938
A28: MS! | B28: 0 | C28: 32 | D28: 315 | E28: 538 | F28: 623 | G28: 876 | H28: 1251 | I28: 1314 | J28: 2252 | K28: 3392 | L28: 4008 | M28: 6650 | N28: 10861 | O28: 15477.819 | P28: 17528.218 | Q28: 15397.215 | R28: 13453.878 | S28: 9119.5401 | T28: 7895.4941 | U28: 8464.4876 | V28: 8641.1337 | W28: 7707.509
A29: Naphtha$ | B29: 86 | C29: 120 | D29: 715 | E29: 479 | F29: 485 | G29: 577 | H29: 1123 | I29: 2426 | J29: 4741 | K29: 6791 | L29: 5643 | M29: 6419 | N29: 8161 | O29: 9482.1125 | P29: 7991.7216 | Q29: 7583.6722 | R29: 5176.2248 | S29: 3070.8717 | T29: 3666.0796 | U29: 4504.6418 | V29: 4137.0453 | W29: 4438.9957
A30: ATF# | B30: 0 | C30: 0 | D30: 38 | E30: 36 | F30: 169 | G30: 427 | H30: 991 | I30: 1588 | J30: 2264 | K30: 3376 | L30: 2999 | M30: 2824 | N30: 3546 | O30: 4568.3114 | P30: 4644.5557 | Q30: 5487.0023 | R30: 4155.3918 | S30: 2439.7655 | T30: 3323.9504 | U30: 3931.1457 | V30: 4866.6891 | W30: 4020.9875
A31: SKO | B31: 0 | C31: 0 | D31: 0 | E31: 0 | F31: 0 | G31: 0 | H31: 102 | I31: 84 | J31: 119 | K31: 122 | L31: 77 | M31: 32 | N31: 30.905 | O31: 39.352431 | P31: 25.468013 | Q31: 16.068751 | R31: 13.153516 | S31: 5.3835747 | T31: 8.0592246 | U31: 10.48838 | V31: 14.004637 | W31: 77.579332
A32: HSD | B32: 0 | C32: 0 | D32: 409 | E32: 533 | F32: 735 | G32: 1475 | H32: 2627 | I32: 4189 | J32: 6427 | K32: 10178 | L32: 11032 | M32: 10747 | N32: 15220 | O32: 21746.08 | P32: 21252.772 | Q32: 24336.183 | R32: 18865.25 | S32: 10179.635 | T32: 11904.571 | U32: 15420.008 | V32: 17625.177 | W32: 17480.663
A33: LDO | B33: 0 | C33: 0 | D33: 2 | E33: 5 | F33: 0 | G33: 0 | H33: 0 | I33: 0.1 | J33: 0.1 | K33: 0 | L33: 0.29 | M33: 19 | N33: 56 | O33: 69.168862 | P33: 7.8491182 | Q33: 21.569 | R33: 4.7613024 | S33: 0 | T33: 58.93556 | U33: 5.7399022 | V33: 49.59 | W33: 0
A34: LOBS/ Lube Oil | B34: 0 | C34: 0 | D34: 0 | E34: 0 | F34: 5 | G34: 8 | H34: 5 | I34: 80 | J34: 273 | K34: 171 | L34: 136 | M34: 26 | N34: 33.6 | O34: 36.499165 | P34: 64.939777 | Q34: 26.531846 | R34: 16.008203 | S34: 19.626317 | T34: 15.403929 | U34: 18.280079 | V34: 15.122732 | W34: 13.483252
A35: Fuel Oil | B35: 0 | C35: 0 | D35: 70 | E35: 53 | F35: 178 | G35: 204 | H35: 338 | I35: 522 | J35: 1101 | K35: 1696 | L35: 2737 | M35: 2250 | N35: 3318 | O35: 5311.9325 | P35: 3757.0654 | Q35: 3670.7011 | R35: 2320.6854 | S35: 687.76926 | T35: 583.31613 | U35: 817.37605 | V35: 922.63138 | W35: 536.51121
A36: Bitumen | B36: 0 | C36: 0 | D36: 0 | E36: 0 | F36: 0 | G36: 1 | H36: 7 | I36: 6 | J36: 17 | K36: 13 | L36: 13.6 | M36: 12 | N36: 27 | O36: 5.6141804 | P36: 52.028923 | Q36: 52.35385 | R36: 40.032269 | S36: 27.439318 | T36: 5.5166441 | U36: 18.248011 | V36: 10.180122 | W36: 12.514926
A37: Others% | B37: 0 | C37: 9 | D37: 127 | E37: 87 | F37: 56 | G37: 93 | H37: 147 | I37: 987 | J37: 638 | K37: 1718 | L37: 539 | M37: 1580 | N37: 1935.4 | O37: 2386.993 | P37: 3287.8382 | Q37: 3813.5562 | R37: 2995.4754 | S37: 1389.7833 | T37: 1415.1403 | U37: 1518.2003 | V37: 1671.2996 | W37: 1282.7146
A38: TOTAL PRODUCT EXPORT | B38: =SUM(B27:B37) -> 86 | C38: =SUM(C27:C37) -> 161 | D38: =SUM(D27:D37) -> 1676 | E38: =SUM(E27:E37) -> 1731 | F38: =SUM(F27:F37) -> 2251 | G38: =SUM(G27:G37) -> 3661 | H38: =SUM(H27:H37) -> 6660 | I38: =SUM(I27:I37) -> 11233.1 | ... W38: =SUM(W27:W37) -> 35847.948
A40: NET IMPORT | B40: =+B24-B38 -> 6327 | C40: =+C24-C38 -> 12313 | D40: =+D24-D38 -> 15369 | E40: =+E24-E38 -> 12415 | F40: =+F24-F38 -> 15330 | G40: =+G24-G38 -> 16721 | H40: =+H24-H38 -> 22608 | I40: =+I24-I38 -> 33844.9 | ... W40: =+W24-W38 -> 83216.923
A42: NET PRODUCT EXPORT | B42: =+B38-B22 -> -2809 | C42: =+C38-C22 -> -3103 | D42: =+D38-D22 -> -966 | E42: =+E38-E22 -> 220 | F42: =+F38-F22 -> 429 | G42: =+G38-G22 -> 1547 | H42: =+H38-H22 -> 3382 | I42: =+I38-I22 -> 4931.1 | ... W42: =+W38-W22 -> 18159.27
A43: Source : Oil Companies & DGCIS, (P) : Provisional
A44: Notes:
A45: RIL SEZ imports/exports included in country's import/export data
A46: ^LNG import not included
A47: $Crude oil imports does not include value of crude oil quantity of 756 TMT imported at ISPRL, Mangalore during 2018-19.
A48: & Others in import include Paraffin wax, Petroleum Jelly, Aviation Gas, MTBE, Reformate etc.
A49: @ Nepal sales by IOCL, Nepal and Bhutan sales by BPCL are considered in total exports with average Rupee-US$ exchange rate
A50: ! RIL SEZ's MS export includes export of Alkylates
A51: # ATF exports by RIL does not include ATF sales to foreign going airlines
A52: % Others in export include Benzene, Hexane, MTO, Sulphur etc.
H57: Petroleum Planning & Analysis Cell
A59: Period : 1998-99 - 2019-20
A60: ('000 Metric Tonnes)
A61: Import/Export of Crude oil and Petroleum Products
A62: IMPORT/EXPORT | B62: 1998-99 | C62: 1999-2000 | D62: 2000-01 | E62: 2001-02 | F62: 2002-03 | G62: 2003-04 | H62: 2004-05 | I62: 2005-06 | J62: 2006-07 | K62: 2007-08 | L62: 2008-09 | M62: 2009-10 | N62: 2010-11 | O62: 2011-12 | P62: 2012-13 | Q62: 2013-14 | R62: 2014-15 | S62: 2015-16 | T62: 0 | U62: 0 | V62: 2018-19 | W62: 2019-20
A63: IMPORT^
A64: CRUDE OIL$ | B64: 39808 | C64: 57805 | D64: 74097 | E64: 78706 | F64: 81989 | G64: 90434 | H64: 95861 | I64: 99409 | J64: 111502 | K64: 121672 | L64: 132775 | M64: 159259 | N64: 163595 | O64: 0 | P64: 0 | Q64: 0 | R64: 0 | S64: 0 | T64: 0 | U64: 0 | V64: 0 | W64: 0
A65: PRODUCT
A66: LPG | B66: 1722 | C66: 1587 | D66: 853 | E66: 659 | F66: 1073 | G66: 1708 | H66: 2334 | I66: 2883 | J66: 2278 | K66: 2833 | L66: 2422.568 | M66: 2718 | N66: 4484.3425 | O66: 0 | P66: 0 | Q66: 0 | R66: 0 | S66: 0 | T66: 0 | U66: 0 | V66: 0 | W66: 0
A67: MS | B67: 251 | C67: 0 | D67: 0 | E67: 0 | F67: 0 | G67: 0 | H67: 233 | I67: 486 | J67: 421 | K67: 328 | L67: 397.41 | M67: 385 | N67: 1702.2146 | O67: 0 | P67: 0 | Q67: 0 | R67: 0 | S67: 0 | T67: 0 | U67: 0 | V67: 0 | W67: 0
A68: Naphtha | B68: 2407 | C68: 1917 | D68: 3165 | E68: 3308 | F68: 2784 | G68: 2371 | H68: 2214 | I68: 2331 | J68: 5307 | K68: 5983 | L68: 5022.631 | M68: 1734 | N68: 2062.518 | O68: 0 | P68: 0 | Q68: 0 | R68: 0 | S68: 0 | T68: 0 | U68: 0 | V68: 0 | W68: 0
A69: ATF | B69: 0 | C69: 0 | D69: 0 | E69: 0 | F69: 0 | G69: 0 | H69: 0 | I69: 0 | J69: 0 | K69: 0 | L69: 0 | M69: 0 | N69: 0 | O69: 0 | P69: 0 | Q69: 0 | R69: 0 | S69: 0 | T69: 0 | U69: 0 | V69: 0 | W69: 0
A70: SKO | B70: 7065 | C70: 6312 | D70: 1918 | E70: 391 | F70: 698 | G70: 804 | H70: 210 | I70: 1044 | J70: 1424 | K70: 2489 | L70: 1448.15 | M70: 985 | N70: 1380.5205 | O70: 0 | P70: 0 | Q70: 0 | R70: 0 | S70: 0 | T70: 0 | U70: 0 | V70: 0 | W70: 0
A71: HSD | B71: 10231 | C71: 5006 | D71: 0 | E71: 31 | F71: 106 | G71: 100 | H71: 814 | I71: 801 | J71: 968 | K71: 2951 | L71: 2742.358 | M71: 2531 | N71: 1996.2493 | O71: 0 | P71: 0 | Q71: 0 | R71: 0 | S71: 0 | T71: 0 | U71: 0 | V71: 0 | W71: 0
A72: LOBS/ Lube oil | B72: 396 | C72: 407 | D72: 255 | E72: 326 | F72: 340 | G72: 612 | H72: 557 | I72: 1189 | J72: 1021 | K72: 1253 | L72: 985.97794 | M72: 1419 | N72: 1291.257 | O72: 0 | P72: 0 | Q72: 0 | R72: 0 | S72: 0 | T72: 0 | U72: 0 | V72: 0 | W72: 0
A73: Fuel Oil | B73: 1696 | C73: 1377 | D73: 1728 | E73: 1977 | F73: 2220 | G73: 1728 | H73: 1585 | I73: 2015 | J73: 2983 | K73: 3659 | L73: 2759.628 | M73: 896 | N73: 1012.7708 | O73: 0 | P73: 0 | Q73: 0 | R73: 0 | S73: 0 | T73: 0 | U73: 0 | V73: 0 | W73: 0
A74: Bitumen | B74: 0 | C74: 0 | D74: 0 | E74: 9 | F74: 0 | G74: 6 | H74: 21 | I74: 23 | J74: 14 | K74: 35 | L74: 104.64786 | M74: 69 | N74: 98.004 | O74: 0 | P74: 0 | Q74: 0 | R74: 0 | S74: 0 | T74: 0 | U74: 0 | V74: 0 | W74: 0
A75: Others& | B75: 3 | C75: 1 | D75: 1348 | E75: 308 | F75: 7 | G75: 672 | H75: 860 | I75: 2669 | J75: 3244 | K75: 2931 | L75: 2701.8166 | M75: 3928 | N75: 3351.5646 | O75: 0 | P75: 0 | Q75: 0 | R75: 0 | S75: 0 | T75: 0 | U75: 0 | V75: 0 | W75: 0
A76: TOTAL PRODUCT IMPORT | B76: 23771 | C76: 16607 | D76: 9267 | E76: 7009 | F76: 7228 | G76: 8001 | H76: 8828 | I76: 13441 | J76: 17660 | K76: 22462 | L76: =SUM(L66:L75) -> 18585.187 | M76: =SUM(M66:M75) -> 14665 | N76: =SUM(N66:N75) -> 17379.441 | O76: =SUM(O66:O75) -> 0 | P76: =SUM(P66:P75) -> 0 | Q76: =SUM(Q66:Q75) -> 0 | R76: =SUM(R66:R75) -> 0 | S76: =SUM(S66:S75) -> 0 | ... W76: =SUM(W66:W75) -> 0
A78: TOTAL IMPORT | B78: =+B64+B76 -> 63579 | C78: =+C64+C76 -> 74412 | D78: =+D64+D76 -> 83364 | E78: =+E64+E76 -> 85715 | F78: =+F64+F76 -> 89217 | G78: =+G64+G76 -> 98435 | H78: =+H64+H76 -> 104689 | I78: =+I64+I76 -> 112850 | ... W78: =+W64+W76 -> 0
A79: PRODUCT EXPORT @
A80: LPG | B80: 0 | C80: 0 | D80: 0 | E80: 0 | F80: 0 | G80: 0 | H80: 145 | I80: 53 | J80: 112 | K80: 99 | L80: 109 | M80: 131 | N80: 154 | O80: 0 | P80: 0 | Q80: 0 | R80: 0 | S80: 0 | T80: 0 | U80: 0 | V80: 0 | W80: 0
A81: MS! | B81: 0 | C81: 131 | D81: 1202 | E81: 2406 | F81: 2336 | G81: 2979 | H81: 2897 | I81: 2417 | J81: 3615 | K81: 4258 | L81: 5440 | M81: 9771 | N81: 13578 | O81: 0 | P81: 0 | Q81: 0 | R81: 0 | S81: 0 | T81: 0 | U81: 0 | V81: 0 | W81: 0
A82: Naphtha | B82: 720 | C82: 583 | D82: 2882 | E82: 2535 | F82: 2067 | G82: 2176 | H82: 2926 | I82: 5066 | J82: 8411 | K82: 9297 | L82: 7601 | M82: 10042.68 | N82: 10655 | O82: 0 | P82: 0 | Q82: 0 | R82: 0 | S82: 0 | T82: 0 | U82: 0 | V82: 0 | W82: 0
A83: ATF# | B83: 0 | C83: 0 | D83: 160 | E83: 194 | F83: 697 | G83: 1660 | H83: 2480 | I83: 2828 | J83: 3652 | K83: 4486 | L83: 3701 | M83: 4588 | N83: 4478.093 | O83: 0 | P83: 0 | Q83: 0 | R83: 0 | S83: 0 | T83: 0 | U83: 0 | V83: 0 | W83: 0
A84: SKO | B84: 0 | C84: 0 | D84: 0 | E84: 0 | F84: 0 | G84: 0 | H84: 207 | I84: 121 | J84: 150 | K84: 137 | L84: 77 | M84: 46 | N84: 33 | O84: 0 | P84: 0 | Q84: 0 | R84: 0 | S84: 0 | T84: 0 | U84: 0 | V84: 0 | W84: 0
A85: HSD | B85: 0 | C85: 0 | D85: 1597 | E85: 2860 | F85: 3178 | G85: 6181 | H85: 7286 | I85: 8504 | J85: 11369 | K85: 14308 | L85: 14720 | M85: 18451 | N85: 20335 | O85: 0 | P85: 0 | Q85: 0 | R85: 0 | S85: 0 | T85: 0 | U85: 0 | V85: 0 | W85: 0
A86: LDO | B86: 0 | C86: 0 | D86: 10 | E86: 30 | F86: 0 | G86: 0 | H86: 0 | I86: 0.2 | J86: 0.1 | K86: 0 | L86: 0.4 | M86: 41 | N86: 98 | O86: 0 | P86: 0 | Q86: 0 | R86: 0 | S86: 0 | T86: 0 | U86: 0 | V86: 0 | W86: 0
A87: LOBS/ Lube Oil | B87: 0 | C87: 0 | D87: 0 | E87: 0 | F87: 23 | G87: 17 | H87: 5 | I87: 291 | J87: 509 | K87: 311 | L87: 139 | M87: 28 | N87: 29 | O87: 0 | P87: 0 | Q87: 0 | R87: 0 | S87: 0 | T87: 0 | U87: 0 | V87: 0 | W87: 0
A88: Fuel Oil | B88: 0 | C88: 0 | D88: 508 | E88: 482 | F88: 1120 | G88: 1310 | H88: 1792 | I88: 1815 | J88: 3759 | K88: 4718 | L88: 6207 | M88: 5186.066 | N88: 6734 | O88: 0 | P88: 0 | Q88: 0 | R88: 0 | S88: 0 | T88: 0 | U88: 0 | V88: 0 | W88: 0
A89: Bitumen | B89: 0 | C89: 0 | D89: 0 | E89: 0 | F89: 0 | G89: 4 | H89: 47 | I89: 33 | J89: 66 | K89: 43 | L89: 45 | M89: 31 | N89: 56 | O89: 0 | P89: 0 | Q89: 0 | R89: 0 | S89: 0 | T89: 0 | U89: 0 | V89: 0 | W89: 0
A90: Others% | B90: 0 | C90: 32 | D90: 2006 | E90: 1578 | F90: 868 | G90: 293 | H90: 427 | I90: 2333 | J90: 1980 | K90: 3122 | L90: 905 | M90: 2839.173 | N90: 2927 | O90: 0 | P90: 0 | Q90: 0 | R90: 0 | S90: 0 | T90: 0 | U90: 0 | V90: 0 | W90: 0
A91: TOTAL EXPORT | B91: 720 | C91: 746 | D91: 8365 | E91: 10085 | F91: 10289 | G91: 14620 | H91: 18211 | I91: 23460 | J91: 33624 | K91: 40779 | L91: =SUM(L80:L90) -> 38944.4 | M91: =SUM(M80:M90) -> 51154.919 | N91: =SUM(N80:N90) -> 59077.093 | O91: =SUM(O80:O90) -> 0 | P91: =SUM(P80:P90) -> 0 | Q91: =SUM(Q80:Q90) -> 0 | R91: =SUM(R80:R90) -> 0 | S91: =SUM(S80:S90) -> 0 | ... W91: =SUM(W80:W90) -> 0
A93: NET IMPORT | B93: =+B78-B91 -> 62859 | C93: =+C78-C91 -> 73666 | D93: =+D78-D91 -> 74999 | E93: =+E78-E91 -> 75630 | F93: =+F78-F91 -> 78928 | G93: =+G78-G91 -> 83815 | H93: =+H78-H91 -> 86478 | I93: =+I78-I91 -> 89390 | ... W93: =+W78-W91 -> 0
A95: Net Product Export | B95: =+B91-B76 -> -23051 | C95: =+C91-C76 -> -15861 | D95: =+D91-D76 -> -902 | E95: =+E91-E76 -> 3076 | F95: =+F91-F76 -> 3061 | G95: =+G91-G76 -> 6619 | H95: =+H91-H76 -> 9383 | I95: =+I91-I76 -> 10019 | ... W95: =+W91-W76 -> 0
A96: Source: Oil Companies & DGCIS P= Provisional
A97: Notes:
A98: RIL SEZ imports/exports included in country's import/export data
A99: ^LNG import not included
A100: & Others in import include Petcoke, Paraffin wax, Petroleum Jelly, Aviation Gas, MTBE, Reformate etc.
A101: @ Nepal sales by IOCL, Nepal and Bhutan sales by BPCL are considered in total exports with average Rupee-US$ exchange rate
A102: ! RIL SEZ's MS export includes export of Alkylates
A103: # ATF exports by RIL does not include ATF sales to foreign going airlines
A104: % Others in export include Petcoke/CBFS, Benzene, Hexane, MTO, Sulphur etc.

Sheet Pretax Fuel Prices
A1: Hard Coal
A2: Year | B2: 2021 | C2: 2022 | D2: 2023 | E2: 2024 | F2: 2025 | G2: 2026 | H2: 2027 | I2: 2028 | J2: 2029 | K2: 2030 | L2: 2031 | M2: 2032 | N2: 2033 | O2: 2034 | P2: 2035 | Q2: 2036 | R2: 2037 | S2: 2038 | T2: 2039 | U2: 2040 | V2: 2041 | W2: 2042 | X2: 2043 | Y2: 2044 | Z2: 2045 | AA2: 2046 | AB2: 2047 | AC2: 2048 | AD2: 2049 | AE2: 2050 | AF2: 2051 | AG2: 2052 | AH2: 2053 | AI2: 2054 | AJ2: 2055 | AK2: 2056 | AL2: 2057 | AM2: 2058 | AN2: 2059 | AO2: 2060 | AP2: 2061 | AQ2: 2062 | AR2: 2063 | AS2: 2064 | AT2: 2065 | AU2: 2066 | AV2: 2067 | AW2: 2068 | AX2: 2069 | AY2: 2070
A3: Transportation Sector | B3: 0 | C3: 0 | D3: 0 | E3: 0 | F3: 0 | G3: 0 | H3: 0 | I3: 0 | J3: 0 | K3: 0 | L3: 0 | M3: 0 | N3: 0 | O3: 0 | P3: 0 | Q3: 0 | R3: 0 | S3: 0 | T3: 0 | U3: 0 | V3: 0 | W3: 0 | X3: 0 | Y3: 0 | Z3: 0 | AA3: 0 | AB3: 0 | AC3: 0 | AD3: 0 | AE3: 0
A4: Electricity Sector | B4: 1.5268673e-06 | C4: 1.5268673e-06 | D4: 1.5194553e-06 | E4: 1.5268673e-06 | F4: 1.5046313e-06 | G4: 1.4823954e-06 | H4: 1.4675714e-06 | I4: 1.4601595e-06 | J4: 1.4453355e-06 | K4: 1.4527475e-06 | L4: 1.4601595e-06 | M4: 1.4527475e-06 | N4: 1.4527475e-06 | O4: 1.4527475e-06 | P4: 1.4453355e-06 | Q4: 1.4453355e-06 | R4: 1.4527475e-06 | S4: 1.4527475e-06 | T4: 1.4453355e-06 | U4: 1.4453355e-06 | V4: 1.4527475e-06 | W4: 1.4527475e-06 | X4: 1.4453355e-06 | Y4: 1.4453355e-06 | Z4: 1.4453355e-06 | AA4: 1.4453355e-06 | AB4: 1.4453355e-06 | AC4: 1.4453355e-06 | AD4: 1.4453355e-06 | AE4: 1.4453355e-06
A5: Residential Buildings Sector | B5: 0 | C5: 0 | D5: 0 | E5: 0 | F5: 0 | G5: 0 | H5: 0 | I5: 0 | J5: 0 | K5: 0 | L5: 0 | M5: 0 | N5: 0 | O5: 0 | P5: 0 | Q5: 0 | R5: 0 | S5: 0 | T5: 0 | U5: 0 | V5: 0 | W5: 0 | X5: 0 | Y5: 0 | Z5: 0 | AA5: 0 | AB5: 0 | AC5: 0 | AD5: 0 | AE5: 0
A6: Commercial Buildings Sector | B6: 0 | C6: 0 | D6: 0 | E6: 0 | F6: 0 | G6: 0 | H6: 0 | I6: 0 | J6: 0 | K6: 0 | L6: 0 | M6: 0 | N6: 0 | O6: 0 | P6: 0 | Q6: 0 | R6: 0 | S6: 0 | T6: 0 | U6: 0 | V6: 0 | W6: 0 | X6: 0 | Y6: 0 | Z6: 0 | AA6: 0 | AB6: 0 | AC6: 0 | AD6: 0 | AE6: 0
A7: Industry Sector | B7: 1.8314932e-06 | C7: 1.8314932e-06 | D7: 1.8314932e-06 | E7: 1.8314932e-06 | F7: 1.8526258e-06 | G7: 1.8526258e-06 | H7: 1.8526258e-06 | I7: 1.85967e-06 | J7: 1.8667142e-06 | K7: 1.8737584e-06 | L7: 1.8878468e-06 | M7: 1.8878468e-06 | N7: 1.894891e-06 | O7: 1.9019352e-06 | P7: 1.9089794e-06 | Q7: 1.9089794e-06 | R7: 1.9160236e-06 | S7: 1.9160236e-06 | T7: 1.9230678e-06 | U7: 1.9230678e-06 | V7: 1.930112e-06 | W7: 1.9371562e-06 | X7: 1.9442004e-06 | Y7: 1.9512446e-06 | Z7: 1.9582888e-06 | AA7: 1.965333e-06 | AB7: 1.9723773e-06 | AC7: 1.9794215e-06 | AD7: 1.9864657e-06 | AE7: 1.9935099e-06
A8: District Heating Sector | B8: 1.8314932e-06 | C8: 1.8314932e-06 | D8: 1.8314932e-06 | E8: 1.8314932e-06 | F8: 1.8526258e-06 | G8: 1.8526258e-06 | H8: 1.8526258e-06 | I8: 1.85967e-06 | J8: 1.8667142e-06 | K8: 1.8737584e-06 | L8: 1.8878468e-06 | M8: 1.8878468e-06 | N8: 1.894891e-06 | O8: 1.9019352e-06 | P8: 1.9089794e-06 | Q8: 1.9089794e-06 | R8: 1.9160236e-06 | S8: 1.9160236e-06 | T8: 1.9230678e-06 | U8: 1.9230678e-06 | V8: 1.930112e-06 | W8: 1.9371562e-06 | X8: 1.9442004e-06 | Y8: 1.9512446e-06 | Z8: 1.9582888e-06 | AA8: 1.965333e-06 | AB8: 1.9723773e-06 | AC8: 1.9794215e-06 | AD8: 1.9864657e-06 | AE8: 1.9935099e-06
A9: LULUCF Sector | B9: 0 | C9: 0 | D9: 0 | E9: 0 | F9: 0 | G9: 0 | H9: 0 | I9: 0 | J9: 0 | K9: 0 | L9: 0 | M9: 0 | N9: 0 | O9: 0 | P9: 0 | Q9: 0 | R9: 0 | S9: 0 | T9: 0 | U9: 0 | V9: 0 | W9: 0 | X9: 0 | Y9: 0 | Z9: 0 | AA9: 0 | AB9: 0 | AC9: 0 | AD9: 0 | AE9: 0
A10: Geoengineering Sector | B10: 1.8314932e-06 | C10: 1.8314932e-06 | D10: 1.8314932e-06 | E10: 1.8314932e-06 | F10: 1.8526258e-06 | G10: 1.8526258e-06 | H10: 1.8526258e-06 | I10: 1.85967e-06 | J10: 1.8667142e-06 | K10: 1.8737584e-06 | L10: 1.8878468e-06 | M10: 1.8878468e-06 | N10: 1.894891e-06 | O10: 1.9019352e-06 | P10: 1.9089794e-06 | Q10: 1.9089794e-06 | R10: 1.9160236e-06 | S10: 1.9160236e-06 | T10: 1.9230678e-06 | U10: 1.9230678e-06 | V10: 1.930112e-06 | W10: 1.9371562e-06 | X10: 1.9442004e-06 | Y10: 1.9512446e-06 | Z10: 1.9582888e-06 | AA10: 1.965333e-06 | AB10: 1.9723773e-06 | AC10: 1.9794215e-06 | AD10: 1.9864657e-06 | AE10: 1.9935099e-06
A11: Natural Gas
A12: Year | B12: 2021 | C12: 2022 | D12: 2023 | E12: 2024 | F12: 2025 | G12: 2026 | H12: 2027 | I12: 2028 | J12: 2029 | K12: 2030 | L12: 2031 | M12: 2032 | N12: 2033 | O12: 2034 | P12: 2035 | Q12: 2036 | R12: 2037 | S12: 2038 | T12: 2039 | U12: 2040 | V12: 2041 | W12: 2042 | X12: 2043 | Y12: 2044 | Z12: 2045 | AA12: 2046 | AB12: 2047 | AC12: 2048 | AD12: 2049 | AE12: 2050 | AF12: 2051 | AG12: 2052 | AH12: 2053 | AI12: 2054 | AJ12: 2055 | AK12: 2056 | AL12: 2057 | AM12: 2058 | AN12: 2059 | AO12: 2060 | AP12: 2061 | AQ12: 2062 | AR12: 2063 | AS12: 2064 | AT12: 2065 | AU12: 2066 | AV12: 2067 | AW12: 2068 | AX12: 2069 | AY12: 2070
A13: Transportation Sector | B13: 9.374745e-06 | C13: 9.374745e-06 | D13: 9.374745e-06 | E13: 9.374745e-06 | F13: 1.4066754e-05 | G13: 1.463362e-05 | H13: 1.357496e-05 | I13: 1.2710594e-05 | J13: 1.3066861e-05 | K13: 1.3538699e-05 | L13: 1.3800959e-05 | M13: 1.4406e-05 | N13: 1.4928258e-05 | O13: 1.5170167e-05 | P13: 1.5236079e-05 | Q13: 1.5528957e-05 | R13: 1.5820057e-05 | S13: 1.5955383e-05 | T13: 1.6026417e-05 | U13: 1.6047372e-05 | V13: 1.6006556e-05 | W13: 1.610373e-05 | X13: 1.6106525e-05 | Y13: 1.6101521e-05 | Z13: 1.6100477e-05 | AA13: 1.6008398e-05 | AB13: 1.5903716e-05 | AC13: 1.5886559e-05 | AD13: 1.5913007e-05 | AE13: 1.597338e-05
A14: Electricity Sector | B14: 5.68763e-06 | C14: 5.68763e-06 | D14: 5.68763e-06 | E14: 5.68763e-06 | F14: 8.5342578e-06 | G14: 8.8781735e-06 | H14: 8.2358879e-06 | I14: 7.7114793e-06 | J14: 7.927626e-06 | K14: 8.2138884e-06 | L14: 8.3730011e-06 | M14: 8.7400777e-06 | N14: 9.0569296e-06 | O14: 9.2036953e-06 | P14: 9.243684e-06 | Q14: 9.4213722e-06 | R14: 9.5979815e-06 | S14: 9.6800838e-06 | T14: 9.7231799e-06 | U14: 9.735893e-06 | V14: 9.7111302e-06 | W14: 9.7700852e-06 | X14: 9.7717807e-06 | Y14: 9.7687449e-06 | Z14: 9.7681118e-06 | AA14: 9.7122476e-06 | AB14: 9.6487374e-06 | AC14: 9.6383281e-06 | AD14: 9.6543742e-06 | AE14: 9.6910023e-06
A15: Residential Buildings Sector | B15: 9.374745e-06 | C15: 9.374745e-06 | D15: 9.374745e-06 | E15: 9.374745e-06 | F15: 9.374745e-06 | G15: 9.374745e-06 | H15: 9.374745e-06 | I15: 9.374745e-06 | J15: 9.374745e-06 | K15: 9.374745e-06 | L15: 9.374745e-06 | M15: 9.374745e-06 | N15: 9.374745e-06 | O15: 9.374745e-06 | P15: 9.374745e-06 | Q15: 9.374745e-06 | R15: 9.374745e-06 | S15: 9.374745e-06 | T15: 9.374745e-06 | U15: 9.374745e-06 | V15: 9.374745e-06 | W15: 9.374745e-06 | X15: 9.374745e-06 | Y15: 9.374745e-06 | Z15: 9.374745e-06 | AA15: 9.374745e-06 | AB15: 9.374745e-06 | AC15: 9.374745e-06 | AD15: 9.374745e-06 | AE15: 9.374745e-06
A16: Commercial Buildings Sector | B16: 9.374745e-06 | C16: 9.374745e-06 | D16: 9.374745e-06 | E16: 9.374745e-06 | F16: 9.374745e-06 | G16: 9.374745e-06 | H16: 9.374745e-06 | I16: 9.374745e-06 | J16: 9.374745e-06 | K16: 9.374745e-06 | L16: 9.374745e-06 | M16: 9.374745e-06 | N16: 9.374745e-06 | O16: 9.374745e-06 | P16: 9.374745e-06 | Q16: 9.374745e-06 | R16: 9.374745e-06 | S16: 9.374745e-06 | T16: 9.374745e-06 | U16: 9.374745e-06 | V16: 9.374745e-06 | W16: 9.374745e-06 | X16: 9.374745e-06 | Y16: 9.374745e-06 | Z16: 9.374745e-06 | AA16: 9.374745e-06 | AB16: 9.374745e-06 | AC16: 9.374745e-06 | AD16: 9.374745e-06 | AE16: 9.374745e-06
A17: Industry Sector | B17: 9.374745e-06 | C17: 9.374745e-06 | D17: 9.374745e-06 | E17: 9.374745e-06 | F17: 9.374745e-06 | G17: 9.374745e-06 | H17: 9.374745e-06 | I17: 9.374745e-06 | J17: 9.374745e-06 | K17: 9.374745e-06 | L17: 9.374745e-06 | M17: 9.374745e-06 | N17: 9.374745e-06 | O17: 9.374745e-06 | P17: 9.374745e-06 | Q17: 9.374745e-06 | R17: 9.374745e-06 | S17: 9.374745e-06 | T17: 9.374745e-06 | U17: 9.374745e-06 | V17: 9.374745e-06 | W17: 9.374745e-06 | X17: 9.374745e-06 | Y17: 9.374745e-06 | Z17: 9.374745e-06 | AA17: 9.374745e-06 | AB17: 9.374745e-06 | AC17: 9.374745e-06 | AD17: 9.374745e-06 | AE17: 9.374745e-06
A18: District Heating Sector | B18: 9.374745e-06 | C18: 9.374745e-06 | D18: 9.374745e-06 | E18: 9.374745e-06 | F18: 9.374745e-06 | G18: 9.374745e-06 | H18: 9.374745e-06 | I18: 9.374745e-06 | J18: 9.374745e-06 | K18: 9.374745e-06 | L18: 9.374745e-06 | M18: 9.374745e-06 | N18: 9.374745e-06 | O18: 9.374745e-06 | P18: 9.374745e-06 | Q18: 9.374745e-06 | R18: 9.374745e-06 | S18: 9.374745e-06 | T18: 9.374745e-06 | U18: 9.374745e-06 | V18: 9.374745e-06 | W18: 9.374745e-06 | X18: 9.374745e-06 | Y18: 9.374745e-06 | Z18: 9.374745e-06 | AA18: 9.374745e-06 | AB18: 9.374745e-06 | AC18: 9.374745e-06 | AD18: 9.374745e-06 | AE18: 9.374745e-06
A19: LULUCF Sector | B19: 9.374745e-06 | C19: 9.374745e-06 | D19: 9.374745e-06 | E19: 9.374745e-06 | F19: 9.374745e-06 | G19: 9.374745e-06 | H19: 9.374745e-06 | I19: 9.374745e-06 | J19: 9.374745e-06 | K19: 9.374745e-06 | L19: 9.374745e-06 | M19: 9.374745e-06 | N19: 9.374745e-06 | O19: 9.374745e-06 | P19: 9.374745e-06 | Q19: 9.374745e-06 | R19: 9.374745e-06 | S19: 9.374745e-06 | T19: 9.374745e-06 | U19: 9.374745e-06 | V19: 9.374745e-06 | W19: 9.374745e-06 | X19: 9.374745e-06 | Y19: 9.374745e-06 | Z19: 9.374745e-06 | AA19: 9.374745e-06 | AB19: 9.374745e-06 | AC19: 9.374745e-06 | AD19: 9.374745e-06 | AE19: 9.374745e-06
A20: Geoengineering Sector | B20: 9.374745e-06 | C20: 9.374745e-06 | D20: 9.374745e-06 | E20: 9.374745e-06 | F20: 9.374745e-06 | G20: 9.374745e-06 | H20: 9.374745e-06 | I20: 9.374745e-06 | J20: 9.374745e-06 | K20: 9.374745e-06 | L20: 9.374745e-06 | M20: 9.374745e-06 | N20: 9.374745e-06 | O20: 9.374745e-06 | P20: 9.374745e-06 | Q20: 9.374745e-06 | R20: 9.374745e-06 | S20: 9.374745e-06 | T20: 9.374745e-06 | U20: 9.374745e-06 | V20: 9.374745e-06 | W20: 9.374745e-06 | X20: 9.374745e-06 | Y20: 9.374745e-06 | Z20: 9.374745e-06 | AA20: 9.374745e-06 | AB20: 9.374745e-06 | AC20: 9.374745e-06 | AD20: 9.374745e-06 | AE20: 9.374745e-06
A21: Nuclear
A22: Year | B22: 2021 | C22: 2022 | D22: 2023 | E22: 2024 | F22: 2025 | G22: 2026 | H22: 2027 | I22: 2028 | J22: 2029 | K22: 2030 | L22: 2031 | M22: 2032 | N22: 2033 | O22: 2034 | P22: 2035 | Q22: 2036 | R22: 2037 | S22: 2038 | T22: 2039 | U22: 2040 | V22: 2041 | W22: 2042 | X22: 2043 | Y22: 2044 | Z22: 2045 | AA22: 2046 | AB22: 2047 | AC22: 2048 | AD22: 2049 | AE22: 2050 | AF22: 2051 | AG22: 2052 | AH22: 2053 | AI22: 2054 | AJ22: 2055 | AK22: 2056 | AL22: 2057 | AM22: 2058 | AN22: 2059 | AO22: 2060 | AP22: 2061 | AQ22: 2062 | AR22: 2063 | AS22: 2064 | AT22: 2065 | AU22: 2066 | AV22: 2067 | AW22: 2068 | AX22: 2069 | AY22: 2070
A23: Transportation Sector | B23: 0 | C23: 0 | D23: 0 | E23: 0 | F23: 0 | G23: 0 | H23: 0 | I23: 0 | J23: 0 | K23: 0 | L23: 0 | M23: 0 | N23: 0 | O23: 0 | P23: 0 | Q23: 0 | R23: 0 | S23: 0 | T23: 0 | U23: 0 | V23: 0 | W23: 0 | X23: 0 | Y23: 0 | Z23: 0 | AA23: 0 | AB23: 0 | AC23: 0 | AD23: 0 | AE23: 0
A24: Electricity Sector | B24: 7.4e-07 | C24: 7.4e-07 | D24: 7.4e-07 | E24: 7.4e-07 | F24: 7.4e-07 | G24: 7.4e-07 | H24: 7.4e-07 | I24: 7.4e-07 | J24: 7.5088235e-07 | K24: 7.5088235e-07 | L24: 7.5088235e-07 | M24: 7.5088235e-07 | N24: 7.5088235e-07 | O24: 7.5088235e-07 | P24: 7.5088235e-07 | Q24: 7.6176471e-07 | R24: 7.6176471e-07 | S24: 7.6176471e-07 | T24: 7.6176471e-07 | U24: 7.6176471e-07 | V24: 7.6176471e-07 | W24: 7.7264706e-07 | X24: 7.7264706e-07 | Y24: 7.7264706e-07 | Z24: 7.7264706e-07 | AA24: 7.7264706e-07 | AB24: 7.8352941e-07 | AC24: 7.8352941e-07 | AD24: 7.8352941e-07 | AE24: 7.8352941e-07
A25: Residential Buildings Sector | B25: 0 | C25: 0 | D25: 0 | E25: 0 | F25: 0 | G25: 0 | H25: 0 | I25: 0 | J25: 0 | K25: 0 | L25: 0 | M25: 0 | N25: 0 | O25: 0 | P25: 0 | Q25: 0 | R25: 0 | S25: 0 | T25: 0 | U25: 0 | V25: 0 | W25: 0 | X25: 0 | Y25: 0 | Z25: 0 | AA25: 0 | AB25: 0 | AC25: 0 | AD25: 0 | AE25: 0
A26: Commercial Buildings Sector | B26: 0 | C26: 0 | D26: 0 | E26: 0 | F26: 0 | G26: 0 | H26: 0 | I26: 0 | J26: 0 | K26: 0 | L26: 0 | M26: 0 | N26: 0 | O26: 0 | P26: 0 | Q26: 0 | R26: 0 | S26: 0 | T26: 0 | U26: 0 | V26: 0 | W26: 0 | X26: 0 | Y26: 0 | Z26: 0 | AA26: 0 | AB26: 0 | AC26: 0 | AD26: 0 | AE26: 0
A27: Industry Sector | B27: 0 | C27: 0 | D27: 0 | E27: 0 | F27: 0 | G27: 0 | H27: 0 | I27: 0 | J27: 0 | K27: 0 | L27: 0 | M27: 0 | N27: 0 | O27: 0 | P27: 0 | Q27: 0 | R27: 0 | S27: 0 | T27: 0 | U27: 0 | V27: 0 | W27: 0 | X27: 0 | Y27: 0 | Z27: 0 | AA27: 0 | AB27: 0 | AC27: 0 | AD27: 0 | AE27: 0
A28: District Heating Sector | B28: 0 | C28: 0 | D28: 0 | E28: 0 | F28: 0 | G28: 0 | H28: 0 | I28: 0 | J28: 0 | K28: 0 | L28: 0 | M28: 0 | N28: 0 | O28: 0 | P28: 0 | Q28: 0 | R28: 0 | S28: 0 | T28: 0 | U28: 0 | V28: 0 | W28: 0 | X28: 0 | Y28: 0 | Z28: 0 | AA28: 0 | AB28: 0 | AC28: 0 | AD28: 0 | AE28: 0
A29: LULUCF Sector | B29: 0 | C29: 0 | D29: 0 | E29: 0 | F29: 0 | G29: 0 | H29: 0 | I29: 0 | J29: 0 | K29: 0 | L29: 0 | M29: 0 | N29: 0 | O29: 0 | P29: 0 | Q29: 0 | R29: 0 | S29: 0 | T29: 0 | U29: 0 | V29: 0 | W29: 0 | X29: 0 | Y29: 0 | Z29: 0 | AA29: 0 | AB29: 0 | AC29: 0 | AD29: 0 | AE29: 0
A30: Geoengineering Sector | B30: 0 | C30: 0 | D30: 0 | E30: 0 | F30: 0 | G30: 0 | H30: 0 | I30: 0 | J30: 0 | K30: 0 | L30: 0 | M30: 0 | N30: 0 | O30: 0 | P30: 0 | Q30: 0 | R30: 0 | S30: 0 | T30: 0 | U30: 0 | V30: 0 | W30: 0 | X30: 0 | Y30: 0 | Z30: 0 | AA30: 0 | AB30: 0 | AC30: 0 | AD30: 0 | AE30: 0
A31: Biomass
A32: Year | B32: 2021 | C32: 2022 | D32: 2023 | E32: 2024 | F32: 2025 | G32: 2026 | H32: 2027 | I32: 2028 | J32: 2029 | K32: 2030 | L32: 2031 | M32: 2032 | N32: 2033 | O32: 2034 | P32: 2035 | Q32: 2036 | R32: 2037 | S32: 2038 | T32: 2039 | U32: 2040 | V32: 2041 | W32: 2042 | X32: 2043 | Y32: 2044 | Z32: 2045 | AA32: 2046 | AB32: 2047 | AC32: 2048 | AD32: 2049 | AE32: 2050 | AF32: 2051 | AG32: 2052 | AH32: 2053 | AI32: 2054 | AJ32: 2055 | AK32: 2056 | AL32: 2057 | AM32: 2058 | AN32: 2059 | AO32: 2060 | AP32: 2061 | AQ32: 2062 | AR32: 2063 | AS32: 2064 | AT32: 2065 | AU32: 2066 | AV32: 2067 | AW32: 2068 | AX32: 2069 | AY32: 2070
A33: Transportation Sector | B33: 0 | C33: 0 | D33: 0 | E33: 0 | F33: 0 | G33: 0 | H33: 0 | I33: 0 | J33: 0 | K33: 0 | L33: 0 | M33: 0 | N33: 0 | O33: 0 | P33: 0 | Q33: 0 | R33: 0 | S33: 0 | T33: 0 | U33: 0 | V33: 0 | W33: 0 | X33: 0 | Y33: 0 | Z33: 0 | AA33: 0 | AB33: 0 | AC33: 0 | AD33: 0 | AE33: 0
A34: Electricity Sector | B34: 2.2777859e-06 | C34: 2.2777859e-06 | D34: 2.2777859e-06 | E34: 2.2777859e-06 | F34: 2.2777859e-06 | G34: 2.2777859e-06 | H34: 2.2777859e-06 | I34: 2.2777859e-06 | J34: 2.2777859e-06 | K34: 2.2777859e-06 | L34: 2.2777859e-06 | M34: 2.2777859e-06 | N34: 2.2777859e-06 | O34: 2.2777859e-06 | P34: 2.2777859e-06 | Q34: 2.2777859e-06 | R34: 2.2777859e-06 | S34: 2.2777859e-06 | T34: 2.2777859e-06 | U34: 2.2777859e-06 | V34: 2.2777859e-06 | W34: 2.2777859e-06 | X34: 2.2777859e-06 | Y34: 2.2777859e-06 | Z34: 2.2777859e-06 | AA34: 2.2777859e-06 | AB34: 2.2777859e-06 | AC34: 2.2777859e-06 | AD34: 2.2777859e-06 | AE34: 2.2777859e-06
A35: Residential Buildings Sector | B35: 2.2777859e-06 | C35: 2.2777859e-06 | D35: 2.2777859e-06 | E35: 2.2777859e-06 | F35: 2.2777859e-06 | G35: 2.2777859e-06 | H35: 2.2777859e-06 | I35: 2.2777859e-06 | J35: 2.2777859e-06 | K35: 2.2777859e-06 | L35: 2.2777859e-06 | M35: 2.2777859e-06 | N35: 2.2777859e-06 | O35: 2.2777859e-06 | P35: 2.2777859e-06 | Q35: 2.2777859e-06 | R35: 2.2777859e-06 | S35: 2.2777859e-06 | T35: 2.2777859e-06 | U35: 2.2777859e-06 | V35: 2.2777859e-06 | W35: 2.2777859e-06 | X35: 2.2777859e-06 | Y35: 2.2777859e-06 | Z35: 2.2777859e-06 | AA35: 2.2777859e-06 | AB35: 2.2777859e-06 | AC35: 2.2777859e-06 | AD35: 2.2777859e-06 | AE35: 2.2777859e-06
A36: Commercial Buildings Sector | B36: 2.2777859e-06 | C36: 2.2777859e-06 | D36: 2.2777859e-06 | E36: 2.2777859e-06 | F36: 2.2777859e-06 | G36: 2.2777859e-06 | H36: 2.2777859e-06 | I36: 2.2777859e-06 | J36: 2.2777859e-06 | K36: 2.2777859e-06 | L36: 2.2777859e-06 | M36: 2.2777859e-06 | N36: 2.2777859e-06 | O36: 2.2777859e-06 | P36: 2.2777859e-06 | Q36: 2.2777859e-06 | R36: 2.2777859e-06 | S36: 2.2777859e-06 | T36: 2.2777859e-06 | U36: 2.2777859e-06 | V36: 2.2777859e-06 | W36: 2.2777859e-06 | X36: 2.2777859e-06 | Y36: 2.2777859e-06 | Z36: 2.2777859e-06 | AA36: 2.2777859e-06 | AB36: 2.2777859e-06 | AC36: 2.2777859e-06 | AD36: 2.2777859e-06 | AE36: 2.2777859e-06
A37: Industry Sector | B37: 2.2777859e-06 | C37: 2.2777859e-06 | D37: 2.2777859e-06 | E37: 2.2777859e-06 | F37: 2.2777859e-06 | G37: 2.2777859e-06 | H37: 2.2777859e-06 | I37: 2.2777859e-06 | J37: 2.2777859e-06 | K37: 2.2777859e-06 | L37: 2.2777859e-06 | M37: 2.2777859e-06 | N37: 2.2777859e-06 | O37: 2.2777859e-06 | P37: 2.2777859e-06 | Q37: 2.2777859e-06 | R37: 2.2777859e-06 | S37: 2.2777859e-06 | T37: 2.2777859e-06 | U37: 2.2777859e-06 | V37: 2.2777859e-06 | W37: 2.2777859e-06 | X37: 2.2777859e-06 | Y37: 2.2777859e-06 | Z37: 2.2777859e-06 | AA37: 2.2777859e-06 | AB37: 2.2777859e-06 | AC37: 2.2777859e-06 | AD37: 2.2777859e-06 | AE37: 2.2777859e-06
A38: District Heating Sector | B38: 2.2777859e-06 | C38: 2.2777859e-06 | D38: 2.2777859e-06 | E38: 2.2777859e-06 | F38: 2.2777859e-06 | G38: 2.2777859e-06 | H38: 2.2777859e-06 | I38: 2.2777859e-06 | J38: 2.2777859e-06 | K38: 2.2777859e-06 | L38: 2.2777859e-06 | M38: 2.2777859e-06 | N38: 2.2777859e-06 | O38: 2.2777859e-06 | P38: 2.2777859e-06 | Q38: 2.2777859e-06 | R38: 2.2777859e-06 | S38: 2.2777859e-06 | T38: 2.2777859e-06 | U38: 2.2777859e-06 | V38: 2.2777859e-06 | W38: 2.2777859e-06 | X38: 2.2777859e-06 | Y38: 2.2777859e-06 | Z38: 2.2777859e-06 | AA38: 2.2777859e-06 | AB38: 2.2777859e-06 | AC38: 2.2777859e-06 | AD38: 2.2777859e-06 | AE38: 2.2777859e-06
A39: LULUCF Sector | B39: 0 | C39: 0 | D39: 0 | E39: 0 | F39: 0 | G39: 0 | H39: 0 | I39: 0 | J39: 0 | K39: 0 | L39: 0 | M39: 0 | N39: 0 | O39: 0 | P39: 0 | Q39: 0 | R39: 0 | S39: 0 | T39: 0 | U39: 0 | V39: 0 | W39: 0 | X39: 0 | Y39: 0 | Z39: 0 | AA39: 0 | AB39: 0 | AC39: 0 | AD39: 0 | AE39: 0
A40: Geoengineering Sector | B40: 2.2777859e-06 | C40: 2.2777859e-06 | D40: 2.2777859e-06 | E40: 2.2777859e-06 | F40: 2.2777859e-06 | G40: 2.2777859e-06 | H40: 2.2777859e-06 | I40: 2.2777859e-06 | J40: 2.2777859e-06 | K40: 2.2777859e-06 | L40: 2.2777859e-06 | M40: 2.2777859e-06 | N40: 2.2777859e-06 | O40: 2.2777859e-06 | P40: 2.2777859e-06 | Q40: 2.2777859e-06 | R40: 2.2777859e-06 | S40: 2.2777859e-06 | T40: 2.2777859e-06 | U40: 2.2777859e-06 | V40: 2.2777859e-06 | W40: 2.2777859e-06 | X40: 2.2777859e-06 | Y40: 2.2777859e-06 | Z40: 2.2777859e-06 | AA40: 2.2777859e-06 | AB40: 2.2777859e-06 | AC40: 2.2777859e-06 | AD40: 2.2777859e-06 | AE40: 2.2777859e-06
A41: Petroleum Gasoline
A42: Year | B42: 2021 | C42: 2022 | D42: 2023 | E42: 2024 | F42: 2025 | G42: 2026 | H42: 2027 | I42: 2028 | J42: 2029 | K42: 2030 | L42: 2031 | M42: 2032 | N42: 2033 | O42: 2034 | P42: 2035 | Q42: 2036 | R42: 2037 | S42: 2038 | T42: 2039 | U42: 2040 | V42: 2041 | W42: 2042 | X42: 2043 | Y42: 2044 | Z42: 2045 | AA42: 2046 | AB42: 2047 | AC42: 2048 | AD42: 2049 | AE42: 2050 | AF42: 2051 | AG42: 2052 | AH42: 2053 | AI42: 2054 | AJ42: 2055 | AK42: 2056 | AL42: 2057 | AM42: 2058 | AN42: 2059 | AO42: 2060 | AP42: 2061 | AQ42: 2062 | AR42: 2063 | AS42: 2064 | AT42: 2065 | AU42: 2066 | AV42: 2067 | AW42: 2068 | AX42: 2069 | AY42: 2070
A43: Transportation Sector | B43: 1.2626853e-05 | C43: 1.2626853e-05 | D43: 1.2753409e-05 | E43: 1.2626853e-05 | F43: 1.264411e-05 | G43: 1.264411e-05 | H43: 1.2592337e-05 | I43: 1.2425513e-05 | J43: 1.2569327e-05 | K43: 1.2672873e-05 | L43: 1.2828192e-05 | M43: 1.289147e-05 | N43: 1.3064047e-05 | O43: 1.3466725e-05 | P43: 1.3558766e-05 | Q43: 1.367957e-05 | R43: 1.3921177e-05 | S43: 1.4145527e-05 | T43: 1.4295093e-05 | U43: 1.446767e-05 | V43: 1.4507937e-05 | W43: 1.4669009e-05 | X43: 1.4864596e-05 | Y43: 1.4916369e-05 | Z43: 1.5025667e-05 | AA43: 1.5255769e-05 | AB43: 1.5382325e-05 | AC43: 1.5503129e-05 | AD43: 1.5698716e-05 | AE43: 1.5750489e-05
A44: Electricity Sector | B44: 0 | C44: 0 | D44: 0 | E44: 0 | F44: 0 | G44: 0 | H44: 0 | I44: 0 | J44: 0 | K44: 0 | L44: 0 | M44: 0 | N44: 0 | O44: 0 | P44: 0 | Q44: 0 | R44: 0 | S44: 0 | T44: 0 | U44: 0 | V44: 0 | W44: 0 | X44: 0 | Y44: 0 | Z44: 0 | AA44: 0 | AB44: 0 | AC44: 0 | AD44: 0 | AE44: 0
A45: Residential Buildings Sector | B45: 0 | C45: 0 | D45: 0 | E45: 0 | F45: 0 | G45: 0 | H45: 0 | I45: 0 | J45: 0 | K45: 0 | L45: 0 | M45: 0 | N45: 0 | O45: 0 | P45: 0 | Q45: 0 | R45: 0 | S45: 0 | T45: 0 | U45: 0 | V45: 0 | W45: 0 | X45: 0 | Y45: 0 | Z45: 0 | AA45: 0 | AB45: 0 | AC45: 0 | AD45: 0 | AE45: 0
A46: Commercial Buildings Sector | B46: 0 | C46: 0 | D46: 0 | E46: 0 | F46: 0 | G46: 0 | H46: 0 | I46: 0 | J46: 0 | K46: 0 | L46: 0 | M46: 0 | N46: 0 | O46: 0 | P46: 0 | Q46: 0 | R46: 0 | S46: 0 | T46: 0 | U46: 0 | V46: 0 | W46: 0 | X46: 0 | Y46: 0 | Z46: 0 | AA46: 0 | AB46: 0 | AC46: 0 | AD46: 0 | AE46: 0
A47: Industry Sector | B47: 0 | C47: 0 | D47: 0 | E47: 0 | F47: 0 | G47: 0 | H47: 0 | I47: 0 | J47: 0 | K47: 0 | L47: 0 | M47: 0 | N47: 0 | O47: 0 | P47: 0 | Q47: 0 | R47: 0 | S47: 0 | T47: 0 | U47: 0 | V47: 0 | W47: 0 | X47: 0 | Y47: 0 | Z47: 0 | AA47: 0 | AB47: 0 | AC47: 0 | AD47: 0 | AE47: 0
A48: District Heating Sector | B48: 0 | C48: 0 | D48: 0 | E48: 0 | F48: 0 | G48: 0 | H48: 0 | I48: 0 | J48: 0 | K48: 0 | L48: 0 | M48: 0 | N48: 0 | O48: 0 | P48: 0 | Q48: 0 | R48: 0 | S48: 0 | T48: 0 | U48: 0 | V48: 0 | W48: 0 | X48: 0 | Y48: 0 | Z48: 0 | AA48: 0 | AB48: 0 | AC48: 0 | AD48: 0 | AE48: 0
A49: LULUCF Sector | B49: 0 | C49: 0 | D49: 0 | E49: 0 | F49: 0 | G49: 0 | H49: 0 | I49: 0 | J49: 0 | K49: 0 | L49: 0 | M49: 0 | N49: 0 | O49: 0 | P49: 0 | Q49: 0 | R49: 0 | S49: 0 | T49: 0 | U49: 0 | V49: 0 | W49: 0 | X49: 0 | Y49: 0 | Z49: 0 | AA49: 0 | AB49: 0 | AC49: 0 | AD49: 0 | AE49: 0
A50: Geoengineering Sector | B50: 0 | C50: 0 | D50: 0 | E50: 0 | F50: 0 | G50: 0 | H50: 0 | I50: 0 | J50: 0 | K50: 0 | L50: 0 | M50: 0 | N50: 0 | O50: 0 | P50: 0 | Q50: 0 | R50: 0 | S50: 0 | T50: 0 | U50: 0 | V50: 0 | W50: 0 | X50: 0 | Y50: 0 | Z50: 0 | AA50: 0 | AB50: 0 | AC50: 0 | AD50: 0 | AE50: 0
A51: Petroleum Diesel
A52: Year | B52: 2021 | C52: 2022 | D52: 2023 | E52: 2024 | F52: 2025 | G52: 2026 | H52: 2027 | I52: 2028 | J52: 2029 | K52: 2030 | L52: 2031 | M52: 2032 | N52: 2033 | O52: 2034 | P52: 2035 | Q52: 2036 | R52: 2037 | S52: 2038 | T52: 2039 | U52: 2040 | V52: 2041 | W52: 2042 | X52: 2043 | Y52: 2044 | Z52: 2045 | AA52: 2046 | AB52: 2047 | AC52: 2048 | AD52: 2049 | AE52: 2050 | AF52: 2051 | AG52: 2052 | AH52: 2053 | AI52: 2054 | AJ52: 2055 | AK52: 2056 | AL52: 2057 | AM52: 2058 | AN52: 2059 | AO52: 2060 | AP52: 2061 | AQ52: 2062 | AR52: 2063 | AS52: 2064 | AT52: 2065 | AU52: 2066 | AV52: 2067 | AW52: 2068 | AX52: 2069 | AY52: 2070
A53: Transportation Sector | B53: 1.1113782e-05 | C53: 1.1113782e-05 | D53: 1.1514795e-05 | E53: 1.1113782e-05 | F53: 1.1176278e-05 | G53: 1.134814e-05 | H53: 1.1415844e-05 | I53: 1.1618954e-05 | J53: 1.1691866e-05 | K53: 1.1905392e-05 | L53: 1.1931432e-05 | M53: 1.2118918e-05 | N53: 1.2228285e-05 | O53: 1.2483475e-05 | P53: 1.262409e-05 | Q53: 1.2717833e-05 | R53: 1.2920944e-05 | S53: 1.3025103e-05 | T53: 1.3139678e-05 | U53: 1.3275085e-05 | V53: 1.336362e-05 | W53: 1.3478195e-05 | X53: 1.359277e-05 | Y53: 1.359277e-05 | Z53: 1.3681305e-05 | AA53: 1.3884416e-05 | AB53: 1.3967743e-05 | AC53: 1.407711e-05 | AD53: 1.4269805e-05 | AE53: 1.4275013e-05
A54: Electricity Sector | B54: 1.1113782e-05 | C54: 1.1113782e-05 | D54: 1.1421484e-05 | E54: 1.1113782e-05 | F54: 1.0727851e-05 | G54: 1.0430579e-05 | H54: 1.0081155e-05 | I54: 9.867328e-06 | J54: 9.5231189e-06 | K54: 9.6378553e-06 | L54: 9.6117788e-06 | M54: 9.7682375e-06 | N54: 9.867328e-06 | O54: 9.9194809e-06 | P54: 1.0013356e-05 | Q54: 1.0091585e-05 | R54: 1.0284551e-05 | S54: 1.0414933e-05 | T54: 1.05401e-05 | U54: 1.0686128e-05 | V54: 1.0759143e-05 | W54: 1.0811295e-05 | X54: 1.0936462e-05 | Y54: 1.0967754e-05 | Z54: 1.107206e-05 | AA54: 1.1270241e-05 | AB54: 1.134847e-05 | AC54: 1.1447561e-05 | AD54: 1.1656172e-05 | AE54: 1.170311e-05
A55: Residential Buildings Sector | B55: 7.4988858e-06 | C55: 7.4988858e-06 | D55: 7.7066015e-06 | E55: 7.4988858e-06 | F55: 7.6150658e-06 | G55: 7.8192608e-06 | H55: 7.9600849e-06 | I55: 8.1924448e-06 | J55: 8.3473513e-06 | K55: 8.4740931e-06 | L55: 8.4846549e-06 | M55: 8.6043554e-06 | N55: 8.6747675e-06 | O55: 8.7170147e-06 | P55: 8.812071e-06 | Q55: 8.8719213e-06 | R55: 8.9845806e-06 | S55: 9.0620339e-06 | T55: 9.1359666e-06 | U55: 9.220461e-06 | V55: 9.2767907e-06 | W55: 9.3507234e-06 | X55: 9.4281767e-06 | Y55: 9.4316973e-06 | Z55: 9.4985887e-06 | AA55: 9.6288511e-06 | AB55: 9.6851807e-06 | AC55: 9.7555928e-06 | AD55: 9.8788139e-06 | AE55: 9.896417e-06
A56: Commercial Buildings Sector | B56: 1.1113782e-05 | C56: 1.1113782e-05 | D56: 1.1420477e-05 | E56: 1.1113782e-05 | F56: 1.0775898e-05 | G56: 1.0562771e-05 | H56: 1.0261275e-05 | I56: 1.0089734e-05 | J56: 9.7934358e-06 | K56: 9.9909679e-06 | L56: 1.0011761e-05 | M56: 1.01885e-05 | N56: 1.0297663e-05 | O56: 1.0515988e-05 | P56: 1.0656339e-05 | Q56: 1.0744709e-05 | R56: 1.0947439e-05 | S56: 1.1056602e-05 | T56: 1.1170963e-05 | U56: 1.1306116e-05 | V56: 1.1384089e-05 | W56: 1.1493252e-05 | X56: 1.1618009e-05 | Y56: 1.1623207e-05 | Z56: 1.1727172e-05 | AA56: 1.1919505e-05 | AB56: 1.2007875e-05 | AC56: 1.2111839e-05 | AD56: 1.2304173e-05 | AE56: 1.2330164e-05
A57: Industry Sector | B57: 1.1113782e-05 | C57: 1.1113782e-05 | D57: 1.1421629e-05 | E57: 1.1113782e-05 | F57: 1.0790282e-05 | G57: 1.0586791e-05 | H57: 1.028938e-05 | I57: 1.0132847e-05 | J57: 9.8354364e-06 | K57: 1.0044146e-05 | L57: 1.0070235e-05 | M57: 1.0252855e-05 | N57: 1.0362428e-05 | O57: 1.0430259e-05 | P57: 1.0571137e-05 | Q57: 1.0665057e-05 | R57: 1.0852895e-05 | S57: 1.0962468e-05 | T57: 1.1082476e-05 | U57: 1.1218137e-05 | V57: 1.1296403e-05 | W57: 1.1411193e-05 | X57: 1.1531201e-05 | Y57: 1.1541637e-05 | Z57: 1.1645992e-05 | AA57: 1.1839048e-05 | AB57: 1.1932967e-05 | AC57: 1.2037322e-05 | AD57: 1.2235596e-05 | AE57: 1.2256467e-05
A58: District Heating Sector | B58: 1.1113782e-05 | C58: 1.1113782e-05 | D58: 1.1421629e-05 | E58: 1.1113782e-05 | F58: 1.0790282e-05 | G58: 1.0586791e-05 | H58: 1.028938e-05 | I58: 1.0132847e-05 | J58: 9.8354364e-06 | K58: 1.0044146e-05 | L58: 1.0070235e-05 | M58: 1.0252855e-05 | N58: 1.0362428e-05 | O58: 1.0430259e-05 | P58: 1.0571137e-05 | Q58: 1.0665057e-05 | R58: 1.0852895e-05 | S58: 1.0962468e-05 | T58: 1.1082476e-05 | U58: 1.1218137e-05 | V58: 1.1296403e-05 | W58: 1.1411193e-05 | X58: 1.1531201e-05 | Y58: 1.1541637e-05 | Z58: 1.1645992e-05 | AA58: 1.1839048e-05 | AB58: 1.1932967e-05 | AC58: 1.2037322e-05 | AD58: 1.2235596e-05 | AE58: 1.2256467e-05
A59: LULUCF Sector | B59: 0 | C59: 0 | D59: 0 | E59: 0 | F59: 0 | G59: 0 | H59: 0 | I59: 0 | J59: 0 | K59: 0 | L59: 0 | M59: 0 | N59: 0 | O59: 0 | P59: 0 | Q59: 0 | R59: 0 | S59: 0 | T59: 0 | U59: 0 | V59: 0 | W59: 0 | X59: 0 | Y59: 0 | Z59: 0 | AA59: 0 | AB59: 0 | AC59: 0 | AD59: 0 | AE59: 0
A60: Geoengineering Sector | B60: 1.1113782e-05 | C60: 1.1113782e-05 | D60: 1.1421629e-05 | E60: 1.1113782e-05 | F60: 1.0790282e-05 | G60: 1.0586791e-05 | H60: 1.028938e-05 | I60: 1.0132847e-05 | J60: 9.8354364e-06 | K60: 1.0044146e-05 | L60: 1.0070235e-05 | M60: 1.0252855e-05 | N60: 1.0362428e-05 | O60: 1.0430259e-05 | P60: 1.0571137e-05 | Q60: 1.0665057e-05 | R60: 1.0852895e-05 | S60: 1.0962468e-05 | T60: 1.1082476e-05 | U60: 1.1218137e-05 | V60: 1.1296403e-05 | W60: 1.1411193e-05 | X60: 1.1531201e-05 | Y60: 1.1541637e-05 | Z60: 1.1645992e-05 | AA60: 1.1839048e-05 | AB60: 1.1932967e-05 | AC60: 1.2037322e-05 | AD60: 1.2235596e-05 | AE60: 1.2256467e-05
A61: Biofuel Gasoline
A62: Year | B62: 2021 | C62: 2022 | D62: 2023 | E62: 2024 | F62: 2025 | G62: 2026 | H62: 2027 | I62: 2028 | J62: 2029 | K62: 2030 | L62: 2031 | M62: 2032 | N62: 2033 | O62: 2034 | P62: 2035 | Q62: 2036 | R62: 2037 | S62: 2038 | T62: 2039 | U62: 2040 | V62: 2041 | W62: 2042 | X62: 2043 | Y62: 2044 | Z62: 2045 | AA62: 2046 | AB62: 2047 | AC62: 2048 | AD62: 2049 | AE62: 2050 | AF62: 2051 | AG62: 2052 | AH62: 2053 | AI62: 2054 | AJ62: 2055 | AK62: 2056 | AL62: 2057 | AM62: 2058 | AN62: 2059 | AO62: 2060 | AP62: 2061 | AQ62: 2062 | AR62: 2063 | AS62: 2064 | AT62: 2065 | AU62: 2066 | AV62: 2067 | AW62: 2068 | AX62: 2069 | AY62: 2070
A63: Transportation Sector | B63: 2.372987e-05 | C63: 2.372987e-05 | D63: 2.4023556e-05 | E63: 2.372987e-05 | F63: 2.9280545e-05 | G63: 2.7831691e-05 | H63: 2.8017693e-05 | I63: 2.7919797e-05 | J63: 2.7273687e-05 | K63: 2.7352003e-05 | L63: 2.7567374e-05 | M63: 2.7831691e-05 | N63: 2.8105799e-05 | O63: 2.9427388e-05 | P63: 2.9750443e-05 | Q63: 2.9907076e-05 | R63: 3.0553186e-05 | S63: 3.1032874e-05 | T63: 3.2090146e-05 | U63: 3.1972671e-05 | V63: 3.2139094e-05 | W63: 3.3059311e-05 | X63: 3.4038266e-05 | Y63: 3.4860588e-05 | Z63: 3.5164065e-05 | AA63: 3.6691234e-05 | AB63: 3.7141554e-05 | AC63: 3.7542925e-05 | AD63: 3.7954086e-05 | AE63: 3.8433774e-05
A64: Electricity Sector | B64: 0 | C64: 0 | D64: 0 | E64: 0 | F64: 0 | G64: 0 | H64: 0 | I64: 0 | J64: 0 | K64: 0 | L64: 0 | M64: 0 | N64: 0 | O64: 0 | P64: 0 | Q64: 0 | R64: 0 | S64: 0 | T64: 0 | U64: 0 | V64: 0 | W64: 0 | X64: 0 | Y64: 0 | Z64: 0 | AA64: 0 | AB64: 0 | AC64: 0 | AD64: 0 | AE64: 0
A65: Residential Buildings Sector | B65: 0 | C65: 0 | D65: 0 | E65: 0 | F65: 0 | G65: 0 | H65: 0 | I65: 0 | J65: 0 | K65: 0 | L65: 0 | M65: 0 | N65: 0 | O65: 0 | P65: 0 | Q65: 0 | R65: 0 | S65: 0 | T65: 0 | U65: 0 | V65: 0 | W65: 0 | X65: 0 | Y65: 0 | Z65: 0 | AA65: 0 | AB65: 0 | AC65: 0 | AD65: 0 | AE65: 0
A66: Commercial Buildings Sector | B66: 0 | C66: 0 | D66: 0 | E66: 0 | F66: 0 | G66: 0 | H66: 0 | I66: 0 | J66: 0 | K66: 0 | L66: 0 | M66: 0 | N66: 0 | O66: 0 | P66: 0 | Q66: 0 | R66: 0 | S66: 0 | T66: 0 | U66: 0 | V66: 0 | W66: 0 | X66: 0 | Y66: 0 | Z66: 0 | AA66: 0 | AB66: 0 | AC66: 0 | AD66: 0 | AE66: 0
A67: Industry Sector | B67: 0 | C67: 0 | D67: 0 | E67: 0 | F67: 0 | G67: 0 | H67: 0 | I67: 0 | J67: 0 | K67: 0 | L67: 0 | M67: 0 | N67: 0 | O67: 0 | P67: 0 | Q67: 0 | R67: 0 | S67: 0 | T67: 0 | U67: 0 | V67: 0 | W67: 0 | X67: 0 | Y67: 0 | Z67: 0 | AA67: 0 | AB67: 0 | AC67: 0 | AD67: 0 | AE67: 0
A68: District Heating Sector | B68: 0 | C68: 0 | D68: 0 | E68: 0 | F68: 0 | G68: 0 | H68: 0 | I68: 0 | J68: 0 | K68: 0 | L68: 0 | M68: 0 | N68: 0 | O68: 0 | P68: 0 | Q68: 0 | R68: 0 | S68: 0 | T68: 0 | U68: 0 | V68: 0 | W68: 0 | X68: 0 | Y68: 0 | Z68: 0 | AA68: 0 | AB68: 0 | AC68: 0 | AD68: 0 | AE68: 0
A69: LULUCF Sector | B69: 0 | C69: 0 | D69: 0 | E69: 0 | F69: 0 | G69: 0 | H69: 0 | I69: 0 | J69: 0 | K69: 0 | L69: 0 | M69: 0 | N69: 0 | O69: 0 | P69: 0 | Q69: 0 | R69: 0 | S69: 0 | T69: 0 | U69: 0 | V69: 0 | W69: 0 | X69: 0 | Y69: 0 | Z69: 0 | AA69: 0 | AB69: 0 | AC69: 0 | AD69: 0 | AE69: 0
A70: Geoengineering Sector | B70: 0 | C70: 0 | D70: 0 | E70: 0 | F70: 0 | G70: 0 | H70: 0 | I70: 0 | J70: 0 | K70: 0 | L70: 0 | M70: 0 | N70: 0 | O70: 0 | P70: 0 | Q70: 0 | R70: 0 | S70: 0 | T70: 0 | U70: 0 | V70: 0 | W70: 0 | X70: 0 | Y70: 0 | Z70: 0 | AA70: 0 | AB70: 0 | AC70: 0 | AD70: 0 | AE70: 0
A71: Biofuel Diesel
A72: Year | B72: 2021 | C72: 2022 | D72: 2023 | E72: 2024 | F72: 2025 | G72: 2026 | H72: 2027 | I72: 2028 | J72: 2029 | K72: 2030 | L72: 2031 | M72: 2032 | N72: 2033 | O72: 2034 | P72: 2035 | Q72: 2036 | R72: 2037 | S72: 2038 | T72: 2039 | U72: 2040 | V72: 2041 | W72: 2042 | X72: 2043 | Y72: 2044 | Z72: 2045 | AA72: 2046 | AB72: 2047 | AC72: 2048 | AD72: 2049 | AE72: 2050 | AF72: 2051 | AG72: 2052 | AH72: 2053 | AI72: 2054 | AJ72: 2055 | AK72: 2056 | AL72: 2057 | AM72: 2058 | AN72: 2059 | AO72: 2060 | AP72: 2061 | AQ72: 2062 | AR72: 2063 | AS72: 2064 | AT72: 2065 | AU72: 2066 | AV72: 2067 | AW72: 2068 | AX72: 2069 | AY72: 2070
A73: Transportation Sector | B73: 1.8434124e-05 | C73: 1.8434124e-05 | D73: 1.9099273e-05 | E73: 1.8434124e-05 | F73: 1.8537784e-05 | G73: 1.8822848e-05 | H73: 1.8935145e-05 | I73: 1.9272039e-05 | J73: 1.9392975e-05 | K73: 1.9747145e-05 | L73: 1.9790337e-05 | M73: 2.0101315e-05 | N73: 2.028272e-05 | O73: 2.0705996e-05 | P73: 2.093923e-05 | Q73: 2.109472e-05 | R73: 2.1431613e-05 | S73: 2.1604379e-05 | T73: 2.1794422e-05 | U73: 2.2019017e-05 | V73: 2.2165868e-05 | W73: 2.2355911e-05 | X73: 2.2545953e-05 | Y73: 2.2545953e-05 | Z73: 2.2692804e-05 | AA73: 2.3029698e-05 | AB73: 2.3167911e-05 | AC73: 2.3349315e-05 | AD73: 2.3668932e-05 | AE73: 2.367757e-05
A74: Electricity Sector | B74: 1.8434124e-05 | C74: 1.8434124e-05 | D74: 1.8944501e-05 | E74: 1.8434124e-05 | F74: 1.779399e-05 | G74: 1.7300914e-05 | H74: 1.6721334e-05 | I74: 1.6366665e-05 | J74: 1.5795735e-05 | K74: 1.5986045e-05 | L74: 1.5942793e-05 | M74: 1.6202306e-05 | N74: 1.6366665e-05 | O74: 1.645317e-05 | P74: 1.6608878e-05 | Q74: 1.6738635e-05 | R74: 1.7058702e-05 | S74: 1.7274963e-05 | T74: 1.7482574e-05 | U74: 1.7724787e-05 | V74: 1.7845893e-05 | W74: 1.7932398e-05 | X74: 1.8140009e-05 | Y74: 1.8191911e-05 | Z74: 1.8364921e-05 | AA74: 1.8693638e-05 | AB74: 1.8823395e-05 | AC74: 1.8987754e-05 | AD74: 1.9333772e-05 | AE74: 1.9411626e-05
A75: Residential Buildings Sector | B75: 1.2438195e-05 | C75: 1.2438195e-05 | D75: 1.2782727e-05 | E75: 1.2438195e-05 | F75: 1.26309e-05 | G75: 1.2969592e-05 | H75: 1.3203174e-05 | I75: 1.3588582e-05 | J75: 1.3845522e-05 | K75: 1.4055745e-05 | L75: 1.4073263e-05 | M75: 1.4271807e-05 | N75: 1.4388598e-05 | O75: 1.4458672e-05 | P75: 1.4616339e-05 | Q75: 1.4715611e-05 | R75: 1.4902476e-05 | S75: 1.5030946e-05 | T75: 1.5153576e-05 | U75: 1.5293725e-05 | V75: 1.5387157e-05 | W75: 1.5509787e-05 | X75: 1.5638257e-05 | Y75: 1.5644096e-05 | Z75: 1.5755047e-05 | AA75: 1.597111e-05 | AB75: 1.6064542e-05 | AC75: 1.6181333e-05 | AD75: 1.6385716e-05 | AE75: 1.6414914e-05
A76: Commercial Buildings Sector | B76: 1.8434124e-05 | C76: 1.8434124e-05 | D76: 1.894283e-05 | E76: 1.8434124e-05 | F76: 1.7873686e-05 | G76: 1.7520178e-05 | H76: 1.7020094e-05 | I76: 1.6735564e-05 | J76: 1.6244102e-05 | K76: 1.6571743e-05 | L76: 1.6606232e-05 | M76: 1.6899384e-05 | N76: 1.7080449e-05 | O76: 1.7442579e-05 | P76: 1.7675376e-05 | Q76: 1.7821953e-05 | R76: 1.8158216e-05 | S76: 1.8339281e-05 | T76: 1.8528968e-05 | U76: 1.8753143e-05 | V76: 1.8882475e-05 | W76: 1.906354e-05 | X76: 1.9270471e-05 | Y76: 1.9279094e-05 | Z76: 1.9451536e-05 | AA76: 1.9770555e-05 | AB76: 1.9917131e-05 | AC76: 2.0089574e-05 | AD76: 2.0408593e-05 | AE76: 2.0451704e-05
A77: Industry Sector | B77: 1.8434124e-05 | C77: 1.8434124e-05 | D77: 1.8944741e-05 | E77: 1.8434124e-05 | F77: 1.7897544e-05 | G77: 1.7560018e-05 | H77: 1.706671e-05 | I77: 1.6807075e-05 | J77: 1.6313767e-05 | K77: 1.6659948e-05 | L77: 1.6703221e-05 | M77: 1.7006129e-05 | N77: 1.7187874e-05 | O77: 1.7300382e-05 | P77: 1.7534054e-05 | Q77: 1.7689836e-05 | R77: 1.8001398e-05 | S77: 1.8183143e-05 | T77: 1.8382197e-05 | U77: 1.8607215e-05 | V77: 1.8737032e-05 | W77: 1.8927432e-05 | X77: 1.9126486e-05 | Y77: 1.9143795e-05 | Z77: 1.9316885e-05 | AA77: 1.9637102e-05 | AB77: 1.9792884e-05 | AC77: 1.9965974e-05 | AD77: 2.0294846e-05 | AE77: 2.0329464e-05
A78: District Heating Sector | B78: 1.8434124e-05 | C78: 1.8434124e-05 | D78: 1.8944741e-05 | E78: 1.8434124e-05 | F78: 1.7897544e-05 | G78: 1.7560018e-05 | H78: 1.706671e-05 | I78: 1.6807075e-05 | J78: 1.6313767e-05 | K78: 1.6659948e-05 | L78: 1.6703221e-05 | M78: 1.7006129e-05 | N78: 1.7187874e-05 | O78: 1.7300382e-05 | P78: 1.7534054e-05 | Q78: 1.7689836e-05 | R78: 1.8001398e-05 | S78: 1.8183143e-05 | T78: 1.8382197e-05 | U78: 1.8607215e-05 | V78: 1.8737032e-05 | W78: 1.8927432e-05 | X78: 1.9126486e-05 | Y78: 1.9143795e-05 | Z78: 1.9316885e-05 | AA78: 1.9637102e-05 | AB78: 1.9792884e-05 | AC78: 1.9965974e-05 | AD78: 2.0294846e-05 | AE78: 2.0329464e-05
A79: LULUCF Sector | B79: 0 | C79: 0 | D79: 0 | E79: 0 | F79: 0 | G79: 0 | H79: 0 | I79: 0 | J79: 0 | K79: 0 | L79: 0 | M79: 0 | N79: 0 | O79: 0 | P79: 0 | Q79: 0 | R79: 0 | S79: 0 | T79: 0 | U79: 0 | V79: 0 | W79: 0 | X79: 0 | Y79: 0 | Z79: 0 | AA79: 0 | AB79: 0 | AC79: 0 | AD79: 0 | AE79: 0
A80: Geoengineering Sector | B80: 1.8434124e-05 | C80: 1.8434124e-05 | D80: 1.8944741e-05 | E80: 1.8434124e-05 | F80: 1.7897544e-05 | G80: 1.7560018e-05 | H80: 1.706671e-05 | I80: 1.6807075e-05 | J80: 1.6313767e-05 | K80: 1.6659948e-05 | L80: 1.6703221e-05 | M80: 1.7006129e-05 | N80: 1.7187874e-05 | O80: 1.7300382e-05 | P80: 1.7534054e-05 | Q80: 1.7689836e-05 | R80: 1.8001398e-05 | S80: 1.8183143e-05 | T80: 1.8382197e-05 | U80: 1.8607215e-05 | V80: 1.8737032e-05 | W80: 1.8927432e-05 | X80: 1.9126486e-05 | Y80: 1.9143795e-05 | Z80: 1.9316885e-05 | AA80: 1.9637102e-05 | AB80: 1.9792884e-05 | AC80: 1.9965974e-05 | AD80: 2.0294846e-05 | AE80: 2.0329464e-05
A81: Jet Fuel
A82: Year | B82: 2021 | C82: 2022 | D82: 2023 | E82: 2024 | F82: 2025 | G82: 2026 | H82: 2027 | I82: 2028 | J82: 2029 | K82: 2030 | L82: 2031 | M82: 2032 | N82: 2033 | O82: 2034 | P82: 2035 | Q82: 2036 | R82: 2037 | S82: 2038 | T82: 2039 | U82: 2040 | V82: 2041 | W82: 2042 | X82: 2043 | Y82: 2044 | Z82: 2045 | AA82: 2046 | AB82: 2047 | AC82: 2048 | AD82: 2049 | AE82: 2050 | AF82: 2051 | AG82: 2052 | AH82: 2053 | AI82: 2054 | AJ82: 2055 | AK82: 2056 | AL82: 2057 | AM82: 2058 | AN82: 2059 | AO82: 2060 | AP82: 2061 | AQ82: 2062 | AR82: 2063 | AS82: 2064 | AT82: 2065 | AU82: 2066 | AV82: 2067 | AW82: 2068 | AX82: 2069 | AY82: 2070
A83: Transportation Sector | B83: 2.1019815e-05 | C83: 2.1019815e-05 | D83: 2.1778262e-05 | E83: 2.1019815e-05 | F83: 2.1138015e-05 | G83: 2.1463063e-05 | H83: 2.1591113e-05 | I83: 2.1975261e-05 | J83: 2.2113161e-05 | K83: 2.2517009e-05 | L83: 2.2566259e-05 | M83: 2.2920857e-05 | N83: 2.3127706e-05 | O83: 2.3610355e-05 | P83: 2.3876303e-05 | Q83: 2.4053603e-05 | R83: 2.4437751e-05 | S83: 2.463475e-05 | T83: 2.485145e-05 | U83: 2.5107548e-05 | V83: 2.5274998e-05 | W83: 2.5491697e-05 | X83: 2.5708396e-05 | Y83: 2.5708396e-05 | Z83: 2.5875845e-05 | AA83: 2.6259994e-05 | AB83: 2.6417593e-05 | AC83: 2.6624442e-05 | AD83: 2.6988891e-05 | AE83: 2.6998741e-05
A84: Electricity Sector | B84: 0 | C84: 0 | D84: 0 | E84: 0 | F84: 0 | G84: 0 | H84: 0 | I84: 0 | J84: 0 | K84: 0 | L84: 0 | M84: 0 | N84: 0 | O84: 0 | P84: 0 | Q84: 0 | R84: 0 | S84: 0 | T84: 0 | U84: 0 | V84: 0 | W84: 0 | X84: 0 | Y84: 0 | Z84: 0 | AA84: 0 | AB84: 0 | AC84: 0 | AD84: 0 | AE84: 0
A85: Residential Buildings Sector | B85: 1.0801857e-05 | C85: 1.0801857e-05 | D85: 1.1101064e-05 | E85: 1.0801857e-05 | F85: 1.096921e-05 | G85: 1.1263345e-05 | H85: 1.1466197e-05 | I85: 1.1800902e-05 | J85: 1.2024039e-05 | K85: 1.2206606e-05 | L85: 1.222182e-05 | M85: 1.2394244e-05 | N85: 1.249567e-05 | O85: 1.2556525e-05 | P85: 1.269345e-05 | Q85: 1.2779662e-05 | R85: 1.2941944e-05 | S85: 1.3053512e-05 | T85: 1.3160009e-05 | U85: 1.328172e-05 | V85: 1.3362861e-05 | W85: 1.3469358e-05 | X85: 1.3580927e-05 | Y85: 1.3585998e-05 | Z85: 1.3682353e-05 | AA85: 1.3869991e-05 | AB85: 1.3951131e-05 | AC85: 1.4052557e-05 | AD85: 1.4230053e-05 | AE85: 1.4255409e-05
A86: Commercial Buildings Sector | B86: 1.0801857e-05 | C86: 1.0801857e-05 | D86: 1.1099944e-05 | E86: 1.0801857e-05 | F86: 1.0473457e-05 | G86: 1.0266312e-05 | H86: 9.9732772e-06 | I86: 9.8065507e-06 | J86: 9.5185685e-06 | K86: 9.7105566e-06 | L86: 9.7307659e-06 | M86: 9.9025447e-06 | N86: 1.0008643e-05 | O86: 1.0220841e-05 | P86: 1.0357253e-05 | Q86: 1.0443143e-05 | R86: 1.0640183e-05 | S86: 1.0746282e-05 | T86: 1.0857433e-05 | U86: 1.0988793e-05 | V86: 1.1064578e-05 | W86: 1.1170677e-05 | X86: 1.1291932e-05 | Y86: 1.1296985e-05 | Z86: 1.1398031e-05 | AA86: 1.1584967e-05 | AB86: 1.1670856e-05 | AC86: 1.1771903e-05 | AD86: 1.1958838e-05 | AE86: 1.19841e-05
A87: Industry Sector | B87: 0 | C87: 0 | D87: 0 | E87: 0 | F87: 0 | G87: 0 | H87: 0 | I87: 0 | J87: 0 | K87: 0 | L87: 0 | M87: 0 | N87: 0 | O87: 0 | P87: 0 | Q87: 0 | R87: 0 | S87: 0 | T87: 0 | U87: 0 | V87: 0 | W87: 0 | X87: 0 | Y87: 0 | Z87: 0 | AA87: 0 | AB87: 0 | AC87: 0 | AD87: 0 | AE87: 0
A88: District Heating Sector | B88: 0 | C88: 0 | D88: 0 | E88: 0 | F88: 0 | G88: 0 | H88: 0 | I88: 0 | J88: 0 | K88: 0 | L88: 0 | M88: 0 | N88: 0 | O88: 0 | P88: 0 | Q88: 0 | R88: 0 | S88: 0 | T88: 0 | U88: 0 | V88: 0 | W88: 0 | X88: 0 | Y88: 0 | Z88: 0 | AA88: 0 | AB88: 0 | AC88: 0 | AD88: 0 | AE88: 0
A89: LULUCF Sector | B89: 0 | C89: 0 | D89: 0 | E89: 0 | F89: 0 | G89: 0 | H89: 0 | I89: 0 | J89: 0 | K89: 0 | L89: 0 | M89: 0 | N89: 0 | O89: 0 | P89: 0 | Q89: 0 | R89: 0 | S89: 0 | T89: 0 | U89: 0 | V89: 0 | W89: 0 | X89: 0 | Y89: 0 | Z89: 0 | AA89: 0 | AB89: 0 | AC89: 0 | AD89: 0 | AE89: 0
A90: Geoengineering Sector | B90: 0 | C90: 0 | D90: 0 | E90: 0 | F90: 0 | G90: 0 | H90: 0 | I90: 0 | J90: 0 | K90: 0 | L90: 0 | M90: 0 | N90: 0 | O90: 0 | P90: 0 | Q90: 0 | R90: 0 | S90: 0 | T90: 0 | U90: 0 | V90: 0 | W90: 0 | X90: 0 | Y90: 0 | Z90: 0 | AA90: 0 | AB90: 0 | AC90: 0 | AD90: 0 | AE90: 0
A91: Lignite
A92: Year | B92: 2021 | C92: 2022 | D92: 2023 | E92: 2024 | F92: 2025 | G92: 2026 | H92: 2027 | I92: 2028 | J92: 2029 | K92: 2030 | L92: 2031 | M92: 2032 | N92: 2033 | O92: 2034 | P92: 2035 | Q92: 2036 | R92: 2037 | S92: 2038 | T92: 2039 | U92: 2040 | V92: 2041 | W92: 2042 | X92: 2043 | Y92: 2044 | Z92: 2045 | AA92: 2046 | AB92: 2047 | AC92: 2048 | AD92: 2049 | AE92: 2050 | AF92: 2051 | AG92: 2052 | AH92: 2053 | AI92: 2054 | AJ92: 2055 | AK92: 2056 | AL92: 2057 | AM92: 2058 | AN92: 2059 | AO92: 2060 | AP92: 2061 | AQ92: 2062 | AR92: 2063 | AS92: 2064 | AT92: 2065 | AU92: 2066 | AV92: 2067 | AW92: 2068 | AX92: 2069 | AY92: 2070
A93: Transportation Sector | B93: 0 | C93: 0 | D93: 0 | E93: 0 | F93: 0 | G93: 0 | H93: 0 | I93: 0 | J93: 0 | K93: 0 | L93: 0 | M93: 0 | N93: 0 | O93: 0 | P93: 0 | Q93: 0 | R93: 0 | S93: 0 | T93: 0 | U93: 0 | V93: 0 | W93: 0 | X93: 0 | Y93: 0 | Z93: 0 | AA93: 0 | AB93: 0 | AC93: 0 | AD93: 0 | AE93: 0
A94: Electricity Sector | B94: 1.5214646e-06 | C94: 1.5214646e-06 | D94: 1.5140788e-06 | E94: 1.5214646e-06 | F94: 1.4993073e-06 | G94: 1.4771501e-06 | H94: 1.4623785e-06 | I94: 1.4549928e-06 | J94: 1.4402213e-06 | K94: 1.447607e-06 | L94: 1.4549928e-06 | M94: 1.447607e-06 | N94: 1.447607e-06 | O94: 1.447607e-06 | P94: 1.4402213e-06 | Q94: 1.4402213e-06 | R94: 1.447607e-06 | S94: 1.447607e-06 | T94: 1.4402213e-06 | U94: 1.4402213e-06 | V94: 1.447607e-06 | W94: 1.447607e-06 | X94: 1.4402213e-06 | Y94: 1.4402213e-06 | Z94: 1.4402213e-06 | AA94: 1.4402213e-06 | AB94: 1.4402213e-06 | AC94: 1.4402213e-06 | AD94: 1.4402213e-06 | AE94: 1.4402213e-06
A95: Residential Buildings Sector | B95: 0 | C95: 0 | D95: 0 | E95: 0 | F95: 0 | G95: 0 | H95: 0 | I95: 0 | J95: 0 | K95: 0 | L95: 0 | M95: 0 | N95: 0 | O95: 0 | P95: 0 | Q95: 0 | R95: 0 | S95: 0 | T95: 0 | U95: 0 | V95: 0 | W95: 0 | X95: 0 | Y95: 0 | Z95: 0 | AA95: 0 | AB95: 0 | AC95: 0 | AD95: 0 | AE95: 0
A96: Commercial Buildings Sector | B96: 0 | C96: 0 | D96: 0 | E96: 0 | F96: 0 | G96: 0 | H96: 0 | I96: 0 | J96: 0 | K96: 0 | L96: 0 | M96: 0 | N96: 0 | O96: 0 | P96: 0 | Q96: 0 | R96: 0 | S96: 0 | T96: 0 | U96: 0 | V96: 0 | W96: 0 | X96: 0 | Y96: 0 | Z96: 0 | AA96: 0 | AB96: 0 | AC96: 0 | AD96: 0 | AE96: 0
A97: Industry Sector | B97: 1.5214646e-06 | C97: 1.5214646e-06 | D97: 1.5141848e-06 | E97: 1.5214646e-06 | F97: 1.5069051e-06 | G97: 1.4850659e-06 | H97: 1.4777861e-06 | I97: 1.4705064e-06 | J97: 1.4632267e-06 | K97: 1.4705064e-06 | L97: 1.4777861e-06 | M97: 1.4632267e-06 | N97: 1.4705064e-06 | O97: 1.4705064e-06 | P97: 1.4632267e-06 | Q97: 1.4632267e-06 | R97: 1.4705064e-06 | S97: 1.4705064e-06 | T97: 1.4632267e-06 | U97: 1.4632267e-06 | V97: 1.4705064e-06 | W97: 1.4705064e-06 | X97: 1.4705064e-06 | Y97: 1.4632267e-06 | Z97: 1.4632267e-06 | AA97: 1.4705064e-06 | AB97: 1.4705064e-06 | AC97: 1.4705064e-06 | AD97: 1.4705064e-06 | AE97: 1.4705064e-06
A98: District Heating Sector | B98: 1.5214646e-06 | C98: 1.5214646e-06 | D98: 1.5141848e-06 | E98: 1.5214646e-06 | F98: 1.5069051e-06 | G98: 1.4850659e-06 | H98: 1.4777861e-06 | I98: 1.4705064e-06 | J98: 1.4632267e-06 | K98: 1.4705064e-06 | L98: 1.4777861e-06 | M98: 1.4632267e-06 | N98: 1.4705064e-06 | O98: 1.4705064e-06 | P98: 1.4632267e-06 | Q98: 1.4632267e-06 | R98: 1.4705064e-06 | S98: 1.4705064e-06 | T98: 1.4632267e-06 | U98: 1.4632267e-06 | V98: 1.4705064e-06 | W98: 1.4705064e-06 | X98: 1.4705064e-06 | Y98: 1.4632267e-06 | Z98: 1.4632267e-06 | AA98: 1.4705064e-06 | AB98: 1.4705064e-06 | AC98: 1.4705064e-06 | AD98: 1.4705064e-06 | AE98: 1.4705064e-06
A99: LULUCF Sector | B99: 0 | C99: 0 | D99: 0 | E99: 0 | F99: 0 | G99: 0 | H99: 0 | I99: 0 | J99: 0 | K99: 0 | L99: 0 | M99: 0 | N99: 0 | O99: 0 | P99: 0 | Q99: 0 | R99: 0 | S99: 0 | T99: 0 | U99: 0 | V99: 0 | W99: 0 | X99: 0 | Y99: 0 | Z99: 0 | AA99: 0 | AB99: 0 | AC99: 0 | AD99: 0 | AE99: 0
A100: Geoengineering Sector | B100: 1.5214646e-06 | C100: 1.5214646e-06 | D100: 1.5141848e-06 | E100: 1.5214646e-06 | F100: 1.5069051e-06 | G100: 1.4850659e-06 | H100: 1.4777861e-06 | I100: 1.4705064e-06 | J100: 1.4632267e-06 | K100: 1.4705064e-06 | L100: 1.4777861e-06 | M100: 1.4632267e-06 | N100: 1.4705064e-06 | O100: 1.4705064e-06 | P100: 1.4632267e-06 | Q100: 1.4632267e-06 | R100: 1.4705064e-06 | S100: 1.4705064e-06 | T100: 1.4632267e-06 | U100: 1.4632267e-06 | V100: 1.4705064e-06 | W100: 1.4705064e-06 | X100: 1.4705064e-06 | Y100: 1.4632267e-06 | Z100: 1.4632267e-06 | AA100: 1.4705064e-06 | AB100: 1.4705064e-06 | AC100: 1.4705064e-06 | AD100: 1.4705064e-06 | AE100: 1.4705064e-06
...

Sheet Fuel Taxes
A1: Hard Coal
A2: Year | B2: 2021 | C2: 2022 | D2: 2023 | E2: 2024 | F2: 2025 | G2: 2026 | H2: 2027 | I2: 2028 | J2: 2029 | K2: 2030 | L2: 2031 | M2: 2032 | N2: 2033 | O2: 2034 | P2: 2035 | Q2: 2036 | R2: 2037 | S2: 2038 | T2: 2039 | U2: 2040 | V2: 2041 | W2: 2042 | X2: 2043 | Y2: 2044 | Z2: 2045 | AA2: 2046 | AB2: 2047 | AC2: 2048 | AD2: 2049 | AE2: 2050 | AF2: 2051 | AG2: 2052 | AH2: 2053 | AI2: 2054 | AJ2: 2055 | AK2: 2056 | AL2: 2057 | AM2: 2058 | AN2: 2059 | AO2: 2060 | AP2: 2061 | AQ2: 2062 | AR2: 2063 | AS2: 2064 | AT2: 2065 | AU2: 2066 | AV2: 2067 | AW2: 2068 | AX2: 2069 | AY2: 2070
A3: Transportation Sector | B3: 0 | C3: 0 | D3: 0 | E3: 0 | F3: 0 | G3: 0 | H3: 0 | I3: 0 | J3: 0 | K3: 0 | L3: 0 | M3: 0 | N3: 0 | O3: 0 | P3: 0 | Q3: 0 | R3: 0 | S3: 0 | T3: 0 | U3: 0 | V3: 0 | W3: 0 | X3: 0 | Y3: 0 | Z3: 0 | AA3: 0 | AB3: 0 | AC3: 0 | AD3: 0 | AE3: 0
A4: Electricity Sector | B4: 4.4933639e-07 | C4: 4.4933639e-07 | D4: 4.4715515e-07 | E4: 4.4933639e-07 | F4: 4.4279266e-07 | G4: 4.3624893e-07 | H4: 4.3188644e-07 | I4: 4.2970519e-07 | J4: 4.253427e-07 | K4: 4.2752395e-07 | L4: 4.2970519e-07 | M4: 4.2752395e-07 | N4: 4.2752395e-07 | O4: 4.2752395e-07 | P4: 4.253427e-07 | Q4: 4.253427e-07 | R4: 4.2752395e-07 | S4: 4.2752395e-07 | T4: 4.253427e-07 | U4: 4.253427e-07 | V4: 4.2752395e-07 | W4: 4.2752395e-07 | X4: 4.253427e-07 | Y4: 4.253427e-07 | Z4: 4.253427e-07 | AA4: 4.253427e-07 | AB4: 4.253427e-07 | AC4: 4.253427e-07 | AD4: 4.253427e-07 | AE4: 4.253427e-07
A5: Residential Buildings Sector | B5: 0 | C5: 0 | D5: 0 | E5: 0 | F5: 0 | G5: 0 | H5: 0 | I5: 0 | J5: 0 | K5: 0 | L5: 0 | M5: 0 | N5: 0 | O5: 0 | P5: 0 | Q5: 0 | R5: 0 | S5: 0 | T5: 0 | U5: 0 | V5: 0 | W5: 0 | X5: 0 | Y5: 0 | Z5: 0 | AA5: 0 | AB5: 0 | AC5: 0 | AD5: 0 | AE5: 0
A6: Commercial Buildings Sector | B6: 0 | C6: 0 | D6: 0 | E6: 0 | F6: 0 | G6: 0 | H6: 0 | I6: 0 | J6: 0 | K6: 0 | L6: 0 | M6: 0 | N6: 0 | O6: 0 | P6: 0 | Q6: 0 | R6: 0 | S6: 0 | T6: 0 | U6: 0 | V6: 0 | W6: 0 | X6: 0 | Y6: 0 | Z6: 0 | AA6: 0 | AB6: 0 | AC6: 0 | AD6: 0 | AE6: 0
A7: Industry Sector | B7: 5.3898368e-07 | C7: 5.3898368e-07 | D7: 5.3898368e-07 | E7: 5.3898368e-07 | F7: 5.4520272e-07 | G7: 5.4520272e-07 | H7: 5.4520272e-07 | I7: 5.4727574e-07 | J7: 5.4934875e-07 | K7: 5.5142176e-07 | L7: 5.5556779e-07 | M7: 5.5556779e-07 | N7: 5.5764081e-07 | O7: 5.5971382e-07 | P7: 5.6178683e-07 | Q7: 5.6178683e-07 | R7: 5.6385985e-07 | S7: 5.6385985e-07 | T7: 5.6593286e-07 | U7: 5.6593286e-07 | V7: 5.6800588e-07 | W7: 5.7007889e-07 | X7: 5.7215191e-07 | Y7: 5.7422492e-07 | Z7: 5.7629793e-07 | AA7: 5.7837095e-07 | AB7: 5.8044396e-07 | AC7: 5.8251698e-07 | AD7: 5.8458999e-07 | AE7: 5.86663e-07
A8: District Heating Sector | B8: 5.3898368e-07 | C8: 5.3898368e-07 | D8: 5.3898368e-07 | E8: 5.3898368e-07 | F8: 5.4520272e-07 | G8: 5.4520272e-07 | H8: 5.4520272e-07 | I8: 5.4727574e-07 | J8: 5.4934875e-07 | K8: 5.5142176e-07 | L8: 5.5556779e-07 | M8: 5.5556779e-07 | N8: 5.5764081e-07 | O8: 5.5971382e-07 | P8: 5.6178683e-07 | Q8: 5.6178683e-07 | R8: 5.6385985e-07 | S8: 5.6385985e-07 | T8: 5.6593286e-07 | U8: 5.6593286e-07 | V8: 5.6800588e-07 | W8: 5.7007889e-07 | X8: 5.7215191e-07 | Y8: 5.7422492e-07 | Z8: 5.7629793e-07 | AA8: 5.7837095e-07 | AB8: 5.8044396e-07 | AC8: 5.8251698e-07 | AD8: 5.8458999e-07 | AE8: 5.86663e-07
A9: LULUCF Sector | B9: 0 | C9: 0 | D9: 0 | E9: 0 | F9: 0 | G9: 0 | H9: 0 | I9: 0 | J9: 0 | K9: 0 | L9: 0 | M9: 0 | N9: 0 | O9: 0 | P9: 0 | Q9: 0 | R9: 0 | S9: 0 | T9: 0 | U9: 0 | V9: 0 | W9: 0 | X9: 0 | Y9: 0 | Z9: 0 | AA9: 0 | AB9: 0 | AC9: 0 | AD9: 0 | AE9: 0
A10: Geoengineering Sector | B10: 5.3898368e-07 | C10: 5.3898368e-07 | D10: 5.3898368e-07 | E10: 5.3898368e-07 | F10: 5.4520272e-07 | G10: 5.4520272e-07 | H10: 5.4520272e-07 | I10: 5.4727574e-07 | J10: 5.4934875e-07 | K10: 5.5142176e-07 | L10: 5.5556779e-07 | M10: 5.5556779e-07 | N10: 5.5764081e-07 | O10: 5.5971382e-07 | P10: 5.6178683e-07 | Q10: 5.6178683e-07 | R10: 5.6385985e-07 | S10: 5.6385985e-07 | T10: 5.6593286e-07 | U10: 5.6593286e-07 | V10: 5.6800588e-07 | W10: 5.7007889e-07 | X10: 5.7215191e-07 | Y10: 5.7422492e-07 | Z10: 5.7629793e-07 | AA10: 5.7837095e-07 | AB10: 5.8044396e-07 | AC10: 5.8251698e-07 | AD10: 5.8458999e-07 | AE10: 5.86663e-07
A11: Natural Gas
A12: Year | B12: 2021 | C12: 2022 | D12: 2023 | E12: 2024 | F12: 2025 | G12: 2026 | H12: 2027 | I12: 2028 | J12: 2029 | K12: 2030 | L12: 2031 | M12: 2032 | N12: 2033 | O12: 2034 | P12: 2035 | Q12: 2036 | R12: 2037 | S12: 2038 | T12: 2039 | U12: 2040 | V12: 2041 | W12: 2042 | X12: 2043 | Y12: 2044 | Z12: 2045 | AA12: 2046 | AB12: 2047 | AC12: 2048 | AD12: 2049 | AE12: 2050 | AF12: 2051 | AG12: 2052 | AH12: 2053 | AI12: 2054 | AJ12: 2055 | AK12: 2056 | AL12: 2057 | AM12: 2058 | AN12: 2059 | AO12: 2060 | AP12: 2061 | AQ12: 2062 | AR12: 2063 | AS12: 2064 | AT12: 2065 | AU12: 2066 | AV12: 2067 | AW12: 2068 | AX12: 2069 | AY12: 2070
A13: Transportation Sector | B13: 1.4019128e-06 | C13: 1.4019128e-06 | D13: 1.4019128e-06 | E13: 1.4019128e-06 | F13: 2.1035625e-06 | G13: 2.1883324e-06 | H13: 2.0300189e-06 | I13: 1.9007603e-06 | J13: 1.9540371e-06 | K13: 2.0245964e-06 | L13: 2.0638152e-06 | M13: 2.1542939e-06 | N13: 2.232393e-06 | O13: 2.2685685e-06 | P13: 2.2784251e-06 | Q13: 2.3222225e-06 | R13: 2.3657539e-06 | S13: 2.3859909e-06 | T13: 2.3966134e-06 | U13: 2.3997469e-06 | V13: 2.3936433e-06 | W13: 2.4081748e-06 | X13: 2.4085927e-06 | Y13: 2.4078444e-06 | Z13: 2.4076884e-06 | AA13: 2.3939187e-06 | AB13: 2.3782645e-06 | AC13: 2.3756987e-06 | AD13: 2.3796538e-06 | AE13: 2.3886821e-06
A14: Electricity Sector | B14: 8.5053632e-07 | C14: 8.5053632e-07 | D14: 8.5053632e-07 | E14: 8.5053632e-07 | F14: 1.2762251e-06 | G14: 1.3276548e-06 | H14: 1.2316064e-06 | I14: 1.1531856e-06 | J14: 1.1855085e-06 | K14: 1.2283166e-06 | L14: 1.2521106e-06 | M14: 1.3070037e-06 | N14: 1.3543862e-06 | O14: 1.3763338e-06 | P14: 1.3823137e-06 | Q14: 1.4088855e-06 | R14: 1.4352959e-06 | S14: 1.4475736e-06 | T14: 1.4540182e-06 | U14: 1.4559193e-06 | V14: 1.4522163e-06 | W14: 1.4610325e-06 | X14: 1.4612861e-06 | Y14: 1.4608321e-06 | Z14: 1.4607374e-06 | AA14: 1.4523834e-06 | AB14: 1.442886e-06 | AC14: 1.4413294e-06 | AD14: 1.4437289e-06 | AE14: 1.4492063e-06
A15: Residential Buildings Sector | B15: 1.4019128e-06 | C15: 1.4019128e-06 | D15: 1.4019128e-06 | E15: 1.4019128e-06 | F15: 1.4019128e-06 | G15: 1.4019128e-06 | H15: 1.4019128e-06 | I15: 1.4019128e-06 | J15: 1.4019128e-06 | K15: 1.4019128e-06 | L15: 1.4019128e-06 | M15: 1.4019128e-06 | N15: 1.4019128e-06 | O15: 1.4019128e-06 | P15: 1.4019128e-06 | Q15: 1.4019128e-06 | R15: 1.4019128e-06 | S15: 1.4019128e-06 | T15: 1.4019128e-06 | U15: 1.4019128e-06 | V15: 1.4019128e-06 | W15: 1.4019128e-06 | X15: 1.4019128e-06 | Y15: 1.4019128e-06 | Z15: 1.4019128e-06 | AA15: 1.4019128e-06 | AB15: 1.4019128e-06 | AC15: 1.4019128e-06 | AD15: 1.4019128e-06 | AE15: 1.4019128e-06
A16: Commercial Buildings Sector | B16: 1.4019128e-06 | C16: 1.4019128e-06 | D16: 1.4019128e-06 | E16: 1.4019128e-06 | F16: 1.4019128e-06 | G16: 1.4019128e-06 | H16: 1.4019128e-06 | I16: 1.4019128e-06 | J16: 1.4019128e-06 | K16: 1.4019128e-06 | L16: 1.4019128e-06 | M16: 1.4019128e-06 | N16: 1.4019128e-06 | O16: 1.4019128e-06 | P16: 1.4019128e-06 | Q16: 1.4019128e-06 | R16: 1.4019128e-06 | S16: 1.4019128e-06 | T16: 1.4019128e-06 | U16: 1.4019128e-06 | V16: 1.4019128e-06 | W16: 1.4019128e-06 | X16: 1.4019128e-06 | Y16: 1.4019128e-06 | Z16: 1.4019128e-06 | AA16: 1.4019128e-06 | AB16: 1.4019128e-06 | AC16: 1.4019128e-06 | AD16: 1.4019128e-06 | AE16: 1.4019128e-06
A17: Industry Sector | B17: 1.4019128e-06 | C17: 1.4019128e-06 | D17: 1.4019128e-06 | E17: 1.4019128e-06 | F17: 1.4019128e-06 | G17: 1.4019128e-06 | H17: 1.4019128e-06 | I17: 1.4019128e-06 | J17: 1.4019128e-06 | K17: 1.4019128e-06 | L17: 1.4019128e-06 | M17: 1.4019128e-06 | N17: 1.4019128e-06 | O17: 1.4019128e-06 | P17: 1.4019128e-06 | Q17: 1.4019128e-06 | R17: 1.4019128e-06 | S17: 1.4019128e-06 | T17: 1.4019128e-06 | U17: 1.4019128e-06 | V17: 1.4019128e-06 | W17: 1.4019128e-06 | X17: 1.4019128e-06 | Y17: 1.4019128e-06 | Z17: 1.4019128e-06 | AA17: 1.4019128e-06 | AB17: 1.4019128e-06 | AC17: 1.4019128e-06 | AD17: 1.4019128e-06 | AE17: 1.4019128e-06
A18: District Heating Sector | B18: 1.4019128e-06 | C18: 1.4019128e-06 | D18: 1.4019128e-06 | E18: 1.4019128e-06 | F18: 1.4019128e-06 | G18: 1.4019128e-06 | H18: 1.4019128e-06 | I18: 1.4019128e-06 | J18: 1.4019128e-06 | K18: 1.4019128e-06 | L18: 1.4019128e-06 | M18: 1.4019128e-06 | N18: 1.4019128e-06 | O18: 1.4019128e-06 | P18: 1.4019128e-06 | Q18: 1.4019128e-06 | R18: 1.4019128e-06 | S18: 1.4019128e-06 | T18: 1.4019128e-06 | U18: 1.4019128e-06 | V18: 1.4019128e-06 | W18: 1.4019128e-06 | X18: 1.4019128e-06 | Y18: 1.4019128e-06 | Z18: 1.4019128e-06 | AA18: 1.4019128e-06 | AB18: 1.4019128e-06 | AC18: 1.4019128e-06 | AD18: 1.4019128e-06 | AE18: 1.4019128e-06
A19: LULUCF Sector | B19: 1.4019128e-06 | C19: 1.4019128e-06 | D19: 1.4019128e-06 | E19: 1.4019128e-06 | F19: 1.4019128e-06 | G19: 1.4019128e-06 | H19: 1.4019128e-06 | I19: 1.4019128e-06 | J19: 1.4019128e-06 | K19: 1.4019128e-06 | L19: 1.4019128e-06 | M19: 1.4019128e-06 | N19: 1.4019128e-06 | O19: 1.4019128e-06 | P19: 1.4019128e-06 | Q19: 1.4019128e-06 | R19: 1.4019128e-06 | S19: 1.4019128e-06 | T19: 1.4019128e-06 | U19: 1.4019128e-06 | V19: 1.4019128e-06 | W19: 1.4019128e-06 | X19: 1.4019128e-06 | Y19: 1.4019128e-06 | Z19: 1.4019128e-06 | AA19: 1.4019128e-06 | AB19: 1.4019128e-06 | AC19: 1.4019128e-06 | AD19: 1.4019128e-06 | AE19: 1.4019128e-06
A20: Geoengineering Sector | B20: 1.4019128e-06 | C20: 1.4019128e-06 | D20: 1.4019128e-06 | E20: 1.4019128e-06 | F20: 1.4019128e-06 | G20: 1.4019128e-06 | H20: 1.4019128e-06 | I20: 1.4019128e-06 | J20: 1.4019128e-06 | K20: 1.4019128e-06 | L20: 1.4019128e-06 | M20: 1.4019128e-06 | N20: 1.4019128e-06 | O20: 1.4019128e-06 | P20: 1.4019128e-06 | Q20: 1.4019128e-06 | R20: 1.4019128e-06 | S20: 1.4019128e-06 | T20: 1.4019128e-06 | U20: 1.4019128e-06 | V20: 1.4019128e-06 | W20: 1.4019128e-06 | X20: 1.4019128e-06 | Y20: 1.4019128e-06 | Z20: 1.4019128e-06 | AA20: 1.4019128e-06 | AB20: 1.4019128e-06 | AC20: 1.4019128e-06 | AD20: 1.4019128e-06 | AE20: 1.4019128e-06
A21: Nuclear
A22: Year | B22: 2021 | C22: 2022 | D22: 2023 | E22: 2024 | F22: 2025 | G22: 2026 | H22: 2027 | I22: 2028 | J22: 2029 | K22: 2030 | L22: 2031 | M22: 2032 | N22: 2033 | O22: 2034 | P22: 2035 | Q22: 2036 | R22: 2037 | S22: 2038 | T22: 2039 | U22: 2040 | V22: 2041 | W22: 2042 | X22: 2043 | Y22: 2044 | Z22: 2045 | AA22: 2046 | AB22: 2047 | AC22: 2048 | AD22: 2049 | AE22: 2050 | AF22: 2051 | AG22: 2052 | AH22: 2053 | AI22: 2054 | AJ22: 2055 | AK22: 2056 | AL22: 2057 | AM22: 2058 | AN22: 2059 | AO22: 2060 | AP22: 2061 | AQ22: 2062 | AR22: 2063 | AS22: 2064 | AT22: 2065 | AU22: 2066 | AV22: 2067 | AW22: 2068 | AX22: 2069 | AY22: 2070
A23: Transportation Sector | B23: 0 | C23: 0 | D23: 0 | E23: 0 | F23: 0 | G23: 0 | H23: 0 | I23: 0 | J23: 0 | K23: 0 | L23: 0 | M23: 0 | N23: 0 | O23: 0 | P23: 0 | Q23: 0 | R23: 0 | S23: 0 | T23: 0 | U23: 0 | V23: 0 | W23: 0 | X23: 0 | Y23: 0 | Z23: 0 | AA23: 0 | AB23: 0 | AC23: 0 | AD23: 0 | AE23: 0 | AF23: 0
A24: Electricity Sector | B24: 0 | C24: 0 | D24: 0 | E24: 0 | F24: 0 | G24: 0 | H24: 0 | I24: 0 | J24: 0 | K24: 0 | L24: 0 | M24: 0 | N24: 0 | O24: 0 | P24: 0 | Q24: 0 | R24: 0 | S24: 0 | T24: 0 | U24: 0 | V24: 0 | W24: 0 | X24: 0 | Y24: 0 | Z24: 0 | AA24: 0 | AB24: 0 | AC24: 0 | AD24: 0 | AE24: 0 | AF24: 0
A25: Residential Buildings Sector | B25: 0 | C25: 0 | D25: 0 | E25: 0 | F25: 0 | G25: 0 | H25: 0 | I25: 0 | J25: 0 | K25: 0 | L25: 0 | M25: 0 | N25: 0 | O25: 0 | P25: 0 | Q25: 0 | R25: 0 | S25: 0 | T25: 0 | U25: 0 | V25: 0 | W25: 0 | X25: 0 | Y25: 0 | Z25: 0 | AA25: 0 | AB25: 0 | AC25: 0 | AD25: 0 | AE25: 0 | AF25: 0
A26: Commercial Buildings Sector | B26: 0 | C26: 0 | D26: 0 | E26: 0 | F26: 0 | G26: 0 | H26: 0 | I26: 0 | J26: 0 | K26: 0 | L26: 0 | M26: 0 | N26: 0 | O26: 0 | P26: 0 | Q26: 0 | R26: 0 | S26: 0 | T26: 0 | U26: 0 | V26: 0 | W26: 0 | X26: 0 | Y26: 0 | Z26: 0 | AA26: 0 | AB26: 0 | AC26: 0 | AD26: 0 | AE26: 0 | AF26: 0
A27: Industry Sector | B27: 0 | C27: 0 | D27: 0 | E27: 0 | F27: 0 | G27: 0 | H27: 0 | I27: 0 | J27: 0 | K27: 0 | L27: 0 | M27: 0 | N27: 0 | O27: 0 | P27: 0 | Q27: 0 | R27: 0 | S27: 0 | T27: 0 | U27: 0 | V27: 0 | W27: 0 | X27: 0 | Y27: 0 | Z27: 0 | AA27: 0 | AB27: 0 | AC27: 0 | AD27: 0 | AE27: 0 | AF27: 0
A28: District Heating Sector | B28: 0 | C28: 0 | D28: 0 | E28: 0 | F28: 0 | G28: 0 | H28: 0 | I28: 0 | J28: 0 | K28: 0 | L28: 0 | M28: 0 | N28: 0 | O28: 0 | P28: 0 | Q28: 0 | R28: 0 | S28: 0 | T28: 0 | U28: 0 | V28: 0 | W28: 0 | X28: 0 | Y28: 0 | Z28: 0 | AA28: 0 | AB28: 0 | AC28: 0 | AD28: 0 | AE28: 0 | AF28: 0
A29: LULUCF Sector | B29: 0 | C29: 0 | D29: 0 | E29: 0 | F29: 0 | G29: 0 | H29: 0 | I29: 0 | J29: 0 | K29: 0 | L29: 0 | M29: 0 | N29: 0 | O29: 0 | P29: 0 | Q29: 0 | R29: 0 | S29: 0 | T29: 0 | U29: 0 | V29: 0 | W29: 0 | X29: 0 | Y29: 0 | Z29: 0 | AA29: 0 | AB29: 0 | AC29: 0 | AD29: 0 | AE29: 0 | AF29: 0
A30: Geoengineering Sector | B30: 0 | C30: 0 | D30: 0 | E30: 0 | F30: 0 | G30: 0 | H30: 0 | I30: 0 | J30: 0 | K30: 0 | L30: 0 | M30: 0 | N30: 0 | O30: 0 | P30: 0 | Q30: 0 | R30: 0 | S30: 0 | T30: 0 | U30: 0 | V30: 0 | W30: 0 | X30: 0 | Y30: 0 | Z30: 0 | AA30: 0 | AB30: 0 | AC30: 0 | AD30: 0 | AE30: 0 | AF30: 0
A31: Biomass
A32: Year | B32: 2021 | C32: 2022 | D32: 2023 | E32: 2024 | F32: 2025 | G32: 2026 | H32: 2027 | I32: 2028 | J32: 2029 | K32: 2030 | L32: 2031 | M32: 2032 | N32: 2033 | O32: 2034 | P32: 2035 | Q32: 2036 | R32: 2037 | S32: 2038 | T32: 2039 | U32: 2040 | V32: 2041 | W32: 2042 | X32: 2043 | Y32: 2044 | Z32: 2045 | AA32: 2046 | AB32: 2047 | AC32: 2048 | AD32: 2049 | AE32: 2050 | AF32: 2051 | AG32: 2052 | AH32: 2053 | AI32: 2054 | AJ32: 2055 | AK32: 2056 | AL32: 2057 | AM32: 2058 | AN32: 2059 | AO32: 2060 | AP32: 2061 | AQ32: 2062 | AR32: 2063 | AS32: 2064 | AT32: 2065 | AU32: 2066 | AV32: 2067 | AW32: 2068 | AX32: 2069 | AY32: 2070
A33: Transportation Sector | B33: 0 | C33: 0 | D33: 0 | E33: 0 | F33: 0 | G33: 0 | H33: 0 | I33: 0 | J33: 0 | K33: 0 | L33: 0 | M33: 0 | N33: 0 | O33: 0 | P33: 0 | Q33: 0 | R33: 0 | S33: 0 | T33: 0 | U33: 0 | V33: 0 | W33: 0 | X33: 0 | Y33: 0 | Z33: 0 | AA33: 0 | AB33: 0 | AC33: 0 | AD33: 0 | AE33: 0 | AF33: 0
A34: Electricity Sector | B34: 1.1988347e-07 | C34: 1.1988347e-07 | D34: 1.1988347e-07 | E34: 1.1988347e-07 | F34: 1.1988347e-07 | G34: 1.1988347e-07 | H34: 1.1988347e-07 | I34: 1.1988347e-07 | J34: 1.1988347e-07 | K34: 1.1988347e-07 | L34: 1.1988347e-07 | M34: 1.1988347e-07 | N34: 1.1988347e-07 | O34: 1.1988347e-07 | P34: 1.1988347e-07 | Q34: 1.1988347e-07 | R34: 1.1988347e-07 | S34: 1.1988347e-07 | T34: 1.1988347e-07 | U34: 1.1988347e-07 | V34: 1.1988347e-07 | W34: 1.1988347e-07 | X34: 1.1988347e-07 | Y34: 1.1988347e-07 | Z34: 1.1988347e-07 | AA34: 1.1988347e-07 | AB34: 1.1988347e-07 | AC34: 1.1988347e-07 | AD34: 1.1988347e-07 | AE34: 1.1988347e-07 | AF34: 1.61119e-07
A35: Residential Buildings Sector | B35: 1.1988347e-07 | C35: 1.1988347e-07 | D35: 1.1988347e-07 | E35: 1.1988347e-07 | F35: 1.1988347e-07 | G35: 1.1988347e-07 | H35: 1.1988347e-07 | I35: 1.1988347e-07 | J35: 1.1988347e-07 | K35: 1.1988347e-07 | L35: 1.1988347e-07 | M35: 1.1988347e-07 | N35: 1.1988347e-07 | O35: 1.1988347e-07 | P35: 1.1988347e-07 | Q35: 1.1988347e-07 | R35: 1.1988347e-07 | S35: 1.1988347e-07 | T35: 1.1988347e-07 | U35: 1.1988347e-07 | V35: 1.1988347e-07 | W35: 1.1988347e-07 | X35: 1.1988347e-07 | Y35: 1.1988347e-07 | Z35: 1.1988347e-07 | AA35: 1.1988347e-07 | AB35: 1.1988347e-07 | AC35: 1.1988347e-07 | AD35: 1.1988347e-07 | AE35: 1.1988347e-07 | AF35: 1.61119e-07
A36: Commercial Buildings Sector | B36: 1.1988347e-07 | C36: 1.1988347e-07 | D36: 1.1988347e-07 | E36: 1.1988347e-07 | F36: 1.1988347e-07 | G36: 1.1988347e-07 | H36: 1.1988347e-07 | I36: 1.1988347e-07 | J36: 1.1988347e-07 | K36: 1.1988347e-07 | L36: 1.1988347e-07 | M36: 1.1988347e-07 | N36: 1.1988347e-07 | O36: 1.1988347e-07 | P36: 1.1988347e-07 | Q36: 1.1988347e-07 | R36: 1.1988347e-07 | S36: 1.1988347e-07 | T36: 1.1988347e-07 | U36: 1.1988347e-07 | V36: 1.1988347e-07 | W36: 1.1988347e-07 | X36: 1.1988347e-07 | Y36: 1.1988347e-07 | Z36: 1.1988347e-07 | AA36: 1.1988347e-07 | AB36: 1.1988347e-07 | AC36: 1.1988347e-07 | AD36: 1.1988347e-07 | AE36: 1.1988347e-07 | AF36: 1.61119e-07
A37: Industry Sector | B37: 1.1988347e-07 | C37: 1.1988347e-07 | D37: 1.1988347e-07 | E37: 1.1988347e-07 | F37: 1.1988347e-07 | G37: 1.1988347e-07 | H37: 1.1988347e-07 | I37: 1.1988347e-07 | J37: 1.1988347e-07 | K37: 1.1988347e-07 | L37: 1.1988347e-07 | M37: 1.1988347e-07 | N37: 1.1988347e-07 | O37: 1.1988347e-07 | P37: 1.1988347e-07 | Q37: 1.1988347e-07 | R37: 1.1988347e-07 | S37: 1.1988347e-07 | T37: 1.1988347e-07 | U37: 1.1988347e-07 | V37: 1.1988347e-07 | W37: 1.1988347e-07 | X37: 1.1988347e-07 | Y37: 1.1988347e-07 | Z37: 1.1988347e-07 | AA37: 1.1988347e-07 | AB37: 1.1988347e-07 | AC37: 1.1988347e-07 | AD37: 1.1988347e-07 | AE37: 1.1988347e-07 | AF37: 1.61119e-07
A38: District Heating Sector | B38: 1.1988347e-07 | C38: 1.1988347e-07 | D38: 1.1988347e-07 | E38: 1.1988347e-07 | F38: 1.1988347e-07 | G38: 1.1988347e-07 | H38: 1.1988347e-07 | I38: 1.1988347e-07 | J38: 1.1988347e-07 | K38: 1.1988347e-07 | L38: 1.1988347e-07 | M38: 1.1988347e-07 | N38: 1.1988347e-07 | O38: 1.1988347e-07 | P38: 1.1988347e-07 | Q38: 1.1988347e-07 | R38: 1.1988347e-07 | S38: 1.1988347e-07 | T38: 1.1988347e-07 | U38: 1.1988347e-07 | V38: 1.1988347e-07 | W38: 1.1988347e-07 | X38: 1.1988347e-07 | Y38: 1.1988347e-07 | Z38: 1.1988347e-07 | AA38: 1.1988347e-07 | AB38: 1.1988347e-07 | AC38: 1.1988347e-07 | AD38: 1.1988347e-07 | AE38: 1.1988347e-07 | AF38: 0
A39: LULUCF Sector | B39: 0 | C39: 0 | D39: 0 | E39: 0 | F39: 0 | G39: 0 | H39: 0 | I39: 0 | J39: 0 | K39: 0 | L39: 0 | M39: 0 | N39: 0 | O39: 0 | P39: 0 | Q39: 0 | R39: 0 | S39: 0 | T39: 0 | U39: 0 | V39: 0 | W39: 0 | X39: 0 | Y39: 0 | Z39: 0 | AA39: 0 | AB39: 0 | AC39: 0 | AD39: 0 | AE39: 0 | AF39: 0
A40: Geoengineering Sector | B40: 1.1988347e-07 | C40: 1.1988347e-07 | D40: 1.1988347e-07 | E40: 1.1988347e-07 | F40: 1.1988347e-07 | G40: 1.1988347e-07 | H40: 1.1988347e-07 | I40: 1.1988347e-07 | J40: 1.1988347e-07 | K40: 1.1988347e-07 | L40: 1.1988347e-07 | M40: 1.1988347e-07 | N40: 1.1988347e-07 | O40: 1.1988347e-07 | P40: 1.1988347e-07 | Q40: 1.1988347e-07 | R40: 1.1988347e-07 | S40: 1.1988347e-07 | T40: 1.1988347e-07 | U40: 1.1988347e-07 | V40: 1.1988347e-07 | W40: 1.1988347e-07 | X40: 1.1988347e-07 | Y40: 1.1988347e-07 | Z40: 1.1988347e-07 | AA40: 1.1988347e-07 | AB40: 1.1988347e-07 | AC40: 1.1988347e-07 | AD40: 1.1988347e-07 | AE40: 1.1988347e-07 | AF40: 1.61119e-07
A41: Petroleum Gasoline
A42: Year | B42: 2021 | C42: 2022 | D42: 2023 | E42: 2024 | F42: 2025 | G42: 2026 | H42: 2027 | I42: 2028 | J42: 2029 | K42: 2030 | L42: 2031 | M42: 2032 | N42: 2033 | O42: 2034 | P42: 2035 | Q42: 2036 | R42: 2037 | S42: 2038 | T42: 2039 | U42: 2040 | V42: 2041 | W42: 2042 | X42: 2043 | Y42: 2044 | Z42: 2045 | AA42: 2046 | AB42: 2047 | AC42: 2048 | AD42: 2049 | AE42: 2050 | AF42: 2051 | AG42: 2052 | AH42: 2053 | AI42: 2054 | AJ42: 2055 | AK42: 2056 | AL42: 2057 | AM42: 2058 | AN42: 2059 | AO42: 2060 | AP42: 2061 | AQ42: 2062 | AR42: 2063 | AS42: 2064 | AT42: 2065 | AU42: 2066 | AV42: 2067 | AW42: 2068 | AX42: 2069 | AY42: 2070
A43: Transportation Sector | B43: 1.2351958e-05 | C43: 1.2351958e-05 | D43: 1.2475759e-05 | E43: 1.2351958e-05 | F43: 1.236884e-05 | G43: 1.236884e-05 | H43: 1.2318194e-05 | I43: 1.2155002e-05 | J43: 1.2295684e-05 | K43: 1.2396976e-05 | L43: 1.2548914e-05 | M43: 1.2610814e-05 | N43: 1.2779634e-05 | O43: 1.3173546e-05 | P43: 1.3263583e-05 | Q43: 1.3381756e-05 | R43: 1.3618104e-05 | S43: 1.3837569e-05 | T43: 1.3983879e-05 | U43: 1.4152699e-05 | V43: 1.419209e-05 | W43: 1.4349655e-05 | X43: 1.4540983e-05 | Y43: 1.4591629e-05 | Z43: 1.4698548e-05 | AA43: 1.4923641e-05 | AB43: 1.5047442e-05 | AC43: 1.5165615e-05 | AD43: 1.5356944e-05 | AE43: 1.540759e-05
A44: Electricity Sector | B44: 0 | C44: 0 | D44: 0 | E44: 0 | F44: 0 | G44: 0 | H44: 0 | I44: 0 | J44: 0 | K44: 0 | L44: 0 | M44: 0 | N44: 0 | O44: 0 | P44: 0 | Q44: 0 | R44: 0 | S44: 0 | T44: 0 | U44: 0 | V44: 0 | W44: 0 | X44: 0 | Y44: 0 | Z44: 0 | AA44: 0 | AB44: 0 | AC44: 0 | AD44: 0 | AE44: 0
A45: Residential Buildings Sector | B45: 0 | C45: 0 | D45: 0 | E45: 0 | F45: 0 | G45: 0 | H45: 0 | I45: 0 | J45: 0 | K45: 0 | L45: 0 | M45: 0 | N45: 0 | O45: 0 | P45: 0 | Q45: 0 | R45: 0 | S45: 0 | T45: 0 | U45: 0 | V45: 0 | W45: 0 | X45: 0 | Y45: 0 | Z45: 0 | AA45: 0 | AB45: 0 | AC45: 0 | AD45: 0 | AE45: 0
A46: Commercial Buildings Sector | B46: 0 | C46: 0 | D46: 0 | E46: 0 | F46: 0 | G46: 0 | H46: 0 | I46: 0 | J46: 0 | K46: 0 | L46: 0 | M46: 0 | N46: 0 | O46: 0 | P46: 0 | Q46: 0 | R46: 0 | S46: 0 | T46: 0 | U46: 0 | V46: 0 | W46: 0 | X46: 0 | Y46: 0 | Z46: 0 | AA46: 0 | AB46: 0 | AC46: 0 | AD46: 0 | AE46: 0
A47: Industry Sector | B47: 0 | C47: 0 | D47: 0 | E47: 0 | F47: 0 | G47: 0 | H47: 0 | I47: 0 | J47: 0 | K47: 0 | L47: 0 | M47: 0 | N47: 0 | O47: 0 | P47: 0 | Q47: 0 | R47: 0 | S47: 0 | T47: 0 | U47: 0 | V47: 0 | W47: 0 | X47: 0 | Y47: 0 | Z47: 0 | AA47: 0 | AB47: 0 | AC47: 0 | AD47: 0 | AE47: 0
A48: District Heating Sector | B48: 0 | C48: 0 | D48: 0 | E48: 0 | F48: 0 | G48: 0 | H48: 0 | I48: 0 | J48: 0 | K48: 0 | L48: 0 | M48: 0 | N48: 0 | O48: 0 | P48: 0 | Q48: 0 | R48: 0 | S48: 0 | T48: 0 | U48: 0 | V48: 0 | W48: 0 | X48: 0 | Y48: 0 | Z48: 0 | AA48: 0 | AB48: 0 | AC48: 0 | AD48: 0 | AE48: 0
A49: LULUCF Sector | B49: 0 | C49: 0 | D49: 0 | E49: 0 | F49: 0 | G49: 0 | H49: 0 | I49: 0 | J49: 0 | K49: 0 | L49: 0 | M49: 0 | N49: 0 | O49: 0 | P49: 0 | Q49: 0 | R49: 0 | S49: 0 | T49: 0 | U49: 0 | V49: 0 | W49: 0 | X49: 0 | Y49: 0 | Z49: 0 | AA49: 0 | AB49: 0 | AC49: 0 | AD49: 0 | AE49: 0
A50: Geoengineering Sector | B50: 0 | C50: 0 | D50: 0 | E50: 0 | F50: 0 | G50: 0 | H50: 0 | I50: 0 | J50: 0 | K50: 0 | L50: 0 | M50: 0 | N50: 0 | O50: 0 | P50: 0 | Q50: 0 | R50: 0 | S50: 0 | T50: 0 | U50: 0 | V50: 0 | W50: 0 | X50: 0 | Y50: 0 | Z50: 0 | AA50: 0 | AB50: 0 | AC50: 0 | AD50: 0 | AE50: 0
A51: Petroleum Diesel
A52: Year | B52: 2021 | C52: 2022 | D52: 2023 | E52: 2024 | F52: 2025 | G52: 2026 | H52: 2027 | I52: 2028 | J52: 2029 | K52: 2030 | L52: 2031 | M52: 2032 | N52: 2033 | O52: 2034 | P52: 2035 | Q52: 2036 | R52: 2037 | S52: 2038 | T52: 2039 | U52: 2040 | V52: 2041 | W52: 2042 | X52: 2043 | Y52: 2044 | Z52: 2045 | AA52: 2046 | AB52: 2047 | AC52: 2048 | AD52: 2049 | AE52: 2050 | AF52: 2051 | AG52: 2052 | AH52: 2053 | AI52: 2054 | AJ52: 2055 | AK52: 2056 | AL52: 2057 | AM52: 2058 | AN52: 2059 | AO52: 2060 | AP52: 2061 | AQ52: 2062 | AR52: 2063 | AS52: 2064 | AT52: 2065 | AU52: 2066 | AV52: 2067 | AW52: 2068 | AX52: 2069 | AY52: 2070
A53: Transportation Sector | B53: 8.2905591e-06 | C53: 8.2905591e-06 | D53: 8.589703e-06 | E53: 8.2905591e-06 | F53: 8.337179e-06 | G53: 8.4653835e-06 | H53: 8.5158883e-06 | I53: 8.6674027e-06 | J53: 8.7217925e-06 | K53: 8.8810769e-06 | L53: 8.9005019e-06 | M53: 9.0403613e-06 | N53: 9.121946e-06 | O53: 9.3123103e-06 | P53: 9.4172049e-06 | Q53: 9.4871347e-06 | R53: 9.6386491e-06 | S53: 9.7163488e-06 | T53: 9.8018185e-06 | U53: 9.9028281e-06 | V53: 9.9688729e-06 | W53: 1.0054343e-05 | X53: 1.0139812e-05 | Y53: 1.0139812e-05 | Z53: 1.0205857e-05 | AA53: 1.0357371e-05 | AB53: 1.0419531e-05 | AC53: 1.0501116e-05 | AD53: 1.064486e-05 | AE53: 1.0648745e-05
A54: Electricity Sector | B54: 8.2905591e-06 | C54: 8.2905591e-06 | D54: 8.520096e-06 | E54: 8.2905591e-06 | F54: 8.0026655e-06 | G54: 7.7809096e-06 | H54: 7.5202491e-06 | I54: 7.3607404e-06 | J54: 7.1039704e-06 | K54: 7.1895604e-06 | L54: 7.1701082e-06 | M54: 7.2868218e-06 | N54: 7.3607404e-06 | O54: 7.399645e-06 | P54: 7.4696732e-06 | Q54: 7.52803e-06 | R54: 7.6719768e-06 | S54: 7.7692382e-06 | T54: 7.8626091e-06 | U54: 7.9715418e-06 | V54: 8.0260082e-06 | W54: 8.0649128e-06 | X54: 8.1582837e-06 | Y54: 8.1816264e-06 | Z54: 8.2594355e-06 | AA54: 8.4072728e-06 | AB54: 8.4656296e-06 | AC54: 8.5395482e-06 | AD54: 8.6951664e-06 | AE54: 8.7301805e-06
A55: Residential Buildings Sector | B55: 5.5939513e-06 | C55: 5.5939513e-06 | D55: 5.7489011e-06 | E55: 5.5939513e-06 | F55: 5.6806182e-06 | G55: 5.8329417e-06 | H55: 5.9379924e-06 | I55: 6.1113261e-06 | J55: 6.2268819e-06 | K55: 6.3214276e-06 | L55: 6.3293064e-06 | M55: 6.4185995e-06 | N55: 6.4711249e-06 | O55: 6.5026401e-06 | P55: 6.5735494e-06 | Q55: 6.6181959e-06 | R55: 6.7022365e-06 | S55: 6.7600144e-06 | T55: 6.815166e-06 | U55: 6.8781965e-06 | V55: 6.9202168e-06 | W55: 6.9753684e-06 | X55: 7.0331463e-06 | Y55: 7.0357726e-06 | Z55: 7.0856717e-06 | AA55: 7.1828436e-06 | AB55: 7.2248639e-06 | AC55: 7.2773892e-06 | AD55: 7.3693086e-06 | AE55: 7.38244e-06
A56: Commercial Buildings Sector | B56: 8.2905591e-06 | C56: 8.2905591e-06 | D56: 8.5193444e-06 | E56: 8.2905591e-06 | F56: 8.0385075e-06 | G56: 7.8795211e-06 | H56: 7.6546135e-06 | I56: 7.5266489e-06 | J56: 7.305619e-06 | K56: 7.4529722e-06 | L56: 7.4684831e-06 | M56: 7.6003255e-06 | N56: 7.6817576e-06 | O56: 7.8446217e-06 | P56: 7.94932e-06 | Q56: 8.0152412e-06 | R56: 8.1664722e-06 | S56: 8.2479042e-06 | T56: 8.333214e-06 | U56: 8.4340347e-06 | V56: 8.4922004e-06 | W56: 8.5736325e-06 | X56: 8.6666977e-06 | Y56: 8.6705754e-06 | Z56: 8.7481298e-06 | AA56: 8.8916053e-06 | AB56: 8.9575265e-06 | AC56: 9.0350808e-06 | AD56: 9.1785563e-06 | AE56: 9.1979449e-06
A57: Industry Sector | B57: 8.2905591e-06 | C57: 8.2905591e-06 | D57: 8.5202037e-06 | E57: 8.2905591e-06 | F57: 8.0492377e-06 | G57: 7.8974387e-06 | H57: 7.6755787e-06 | I57: 7.5588103e-06 | J57: 7.3369502e-06 | K57: 7.4926415e-06 | L57: 7.5121029e-06 | M57: 7.6483327e-06 | N57: 7.7300706e-06 | O57: 7.7806703e-06 | P57: 7.8857619e-06 | Q57: 7.9558229e-06 | R57: 8.0959451e-06 | S57: 8.177683e-06 | T57: 8.2672054e-06 | U57: 8.3684048e-06 | V57: 8.426789e-06 | W57: 8.5124192e-06 | X57: 8.6019416e-06 | Y57: 8.6097262e-06 | Z57: 8.6875718e-06 | AA57: 8.8315862e-06 | AB57: 8.9016473e-06 | AC57: 8.9794929e-06 | AD57: 9.1273996e-06 | AE57: 9.1429687e-06
A58: District Heating Sector | B58: 8.2905591e-06 | C58: 8.2905591e-06 | D58: 8.5202037e-06 | E58: 8.2905591e-06 | F58: 8.0492377e-06 | G58: 7.8974387e-06 | H58: 7.6755787e-06 | I58: 7.5588103e-06 | J58: 7.3369502e-06 | K58: 7.4926415e-06 | L58: 7.5121029e-06 | M58: 7.6483327e-06 | N58: 7.7300706e-06 | O58: 7.7806703e-06 | P58: 7.8857619e-06 | Q58: 7.9558229e-06 | R58: 8.0959451e-06 | S58: 8.177683e-06 | T58: 8.2672054e-06 | U58: 8.3684048e-06 | V58: 8.426789e-06 | W58: 8.5124192e-06 | X58: 8.6019416e-06 | Y58: 8.6097262e-06 | Z58: 8.6875718e-06 | AA58: 8.8315862e-06 | AB58: 8.9016473e-06 | AC58: 8.9794929e-06 | AD58: 9.1273996e-06 | AE58: 9.1429687e-06
A59: LULUCF Sector | B59: 0 | C59: 0 | D59: 0 | E59: 0 | F59: 0 | G59: 0 | H59: 0 | I59: 0 | J59: 0 | K59: 0 | L59: 0 | M59: 0 | N59: 0 | O59: 0 | P59: 0 | Q59: 0 | R59: 0 | S59: 0 | T59: 0 | U59: 0 | V59: 0 | W59: 0 | X59: 0 | Y59: 0 | Z59: 0 | AA59: 0 | AB59: 0 | AC59: 0 | AD59: 0 | AE59: 0
A60: Geoengineering Sector | B60: 8.2905591e-06 | C60: 8.2905591e-06 | D60: 8.5202037e-06 | E60: 8.2905591e-06 | F60: 8.0492377e-06 | G60: 7.8974387e-06 | H60: 7.6755787e-06 | I60: 7.5588103e-06 | J60: 7.3369502e-06 | K60: 7.4926415e-06 | L60: 7.5121029e-06 | M60: 7.6483327e-06 | N60: 7.7300706e-06 | O60: 7.7806703e-06 | P60: 7.8857619e-06 | Q60: 7.9558229e-06 | R60: 8.0959451e-06 | S60: 8.177683e-06 | T60: 8.2672054e-06 | U60: 8.3684048e-06 | V60: 8.426789e-06 | W60: 8.5124192e-06 | X60: 8.6019416e-06 | Y60: 8.6097262e-06 | Z60: 8.6875718e-06 | AA60: 8.8315862e-06 | AB60: 8.9016473e-06 | AC60: 8.9794929e-06 | AD60: 9.1273996e-06 | AE60: 9.1429687e-06
A61: Biofuel Gasoline
A62: Year | B62: 2021 | C62: 2022 | D62: 2023 | E62: 2024 | F62: 2025 | G62: 2026 | H62: 2027 | I62: 2028 | J62: 2029 | K62: 2030 | L62: 2031 | M62: 2032 | N62: 2033 | O62: 2034 | P62: 2035 | Q62: 2036 | R62: 2037 | S62: 2038 | T62: 2039 | U62: 2040 | V62: 2041 | W62: 2042 | X62: 2043 | Y62: 2044 | Z62: 2045 | AA62: 2046 | AB62: 2047 | AC62: 2048 | AD62: 2049 | AE62: 2050 | AF62: 2051 | AG62: 2052 | AH62: 2053 | AI62: 2054 | AJ62: 2055 | AK62: 2056 | AL62: 2057 | AM62: 2058 | AN62: 2059 | AO62: 2060 | AP62: 2061 | AQ62: 2062 | AR62: 2063 | AS62: 2064 | AT62: 2065 | AU62: 2066 | AV62: 2067 | AW62: 2068 | AX62: 2069 | AY62: 2070
A63: Transportation Sector | B63: 1.2489405e-06 | C63: 1.2489405e-06 | D63: 1.2643977e-06 | E63: 1.2489405e-06 | F63: 1.5410813e-06 | G63: 1.4648259e-06 | H63: 1.4746154e-06 | I63: 1.469463e-06 | J63: 1.4354572e-06 | K63: 1.4395791e-06 | L63: 1.4509144e-06 | M63: 1.4648259e-06 | N63: 1.4792526e-06 | O63: 1.5488099e-06 | P63: 1.5658128e-06 | Q63: 1.5740566e-06 | R63: 1.6080624e-06 | S63: 1.6333092e-06 | T63: 1.688955e-06 | U63: 1.6827722e-06 | V63: 1.6915312e-06 | W63: 1.7399637e-06 | X63: 1.7914877e-06 | Y63: 1.8347678e-06 | Z63: 1.8507402e-06 | AA63: 1.9311176e-06 | AB63: 1.9548186e-06 | AC63: 1.9759434e-06 | AD63: 1.9975835e-06 | AE63: 2.0228302e-06
A64: Electricity Sector | B64: 0 | C64: 0 | D64: 0 | E64: 0 | F64: 0 | G64: 0 | H64: 0 | I64: 0 | J64: 0 | K64: 0 | L64: 0 | M64: 0 | N64: 0 | O64: 0 | P64: 0 | Q64: 0 | R64: 0 | S64: 0 | T64: 0 | U64: 0 | V64: 0 | W64: 0 | X64: 0 | Y64: 0 | Z64: 0 | AA64: 0 | AB64: 0 | AC64: 0 | AD64: 0 | AE64: 0
A65: Residential Buildings Sector | B65: 0 | C65: 0 | D65: 0 | E65: 0 | F65: 0 | G65: 0 | H65: 0 | I65: 0 | J65: 0 | K65: 0 | L65: 0 | M65: 0 | N65: 0 | O65: 0 | P65: 0 | Q65: 0 | R65: 0 | S65: 0 | T65: 0 | U65: 0 | V65: 0 | W65: 0 | X65: 0 | Y65: 0 | Z65: 0 | AA65: 0 | AB65: 0 | AC65: 0 | AD65: 0 | AE65: 0
A66: Commercial Buildings Sector | B66: 0 | C66: 0 | D66: 0 | E66: 0 | F66: 0 | G66: 0 | H66: 0 | I66: 0 | J66: 0 | K66: 0 | L66: 0 | M66: 0 | N66: 0 | O66: 0 | P66: 0 | Q66: 0 | R66: 0 | S66: 0 | T66: 0 | U66: 0 | V66: 0 | W66: 0 | X66: 0 | Y66: 0 | Z66: 0 | AA66: 0 | AB66: 0 | AC66: 0 | AD66: 0 | AE66: 0
A67: Industry Sector | B67: 0 | C67: 0 | D67: 0 | E67: 0 | F67: 0 | G67: 0 | H67: 0 | I67: 0 | J67: 0 | K67: 0 | L67: 0 | M67: 0 | N67: 0 | O67: 0 | P67: 0 | Q67: 0 | R67: 0 | S67: 0 | T67: 0 | U67: 0 | V67: 0 | W67: 0 | X67: 0 | Y67: 0 | Z67: 0 | AA67: 0 | AB67: 0 | AC67: 0 | AD67: 0 | AE67: 0
A68: District Heating Sector | B68: 0 | C68: 0 | D68: 0 | E68: 0 | F68: 0 | G68: 0 | H68: 0 | I68: 0 | J68: 0 | K68: 0 | L68: 0 | M68: 0 | N68: 0 | O68: 0 | P68: 0 | Q68: 0 | R68: 0 | S68: 0 | T68: 0 | U68: 0 | V68: 0 | W68: 0 | X68: 0 | Y68: 0 | Z68: 0 | AA68: 0 | AB68: 0 | AC68: 0 | AD68: 0 | AE68: 0
A69: LULUCF Sector | B69: 0 | C69: 0 | D69: 0 | E69: 0 | F69: 0 | G69: 0 | H69: 0 | I69: 0 | J69: 0 | K69: 0 | L69: 0 | M69: 0 | N69: 0 | O69: 0 | P69: 0 | Q69: 0 | R69: 0 | S69: 0 | T69: 0 | U69: 0 | V69: 0 | W69: 0 | X69: 0 | Y69: 0 | Z69: 0 | AA69: 0 | AB69: 0 | AC69: 0 | AD69: 0 | AE69: 0
A70: Geoengineering Sector | B70: 0 | C70: 0 | D70: 0 | E70: 0 | F70: 0 | G70: 0 | H70: 0 | I70: 0 | J70: 0 | K70: 0 | L70: 0 | M70: 0 | N70: 0 | O70: 0 | P70: 0 | Q70: 0 | R70: 0 | S70: 0 | T70: 0 | U70: 0 | V70: 0 | W70: 0 | X70: 0 | Y70: 0 | Z70: 0 | AA70: 0 | AB70: 0 | AC70: 0 | AD70: 0 | AE70: 0
A71: Biofuel Diesel
A72: Year | B72: 2021 | C72: 2022 | D72: 2023 | E72: 2024 | F72: 2025 | G72: 2026 | H72: 2027 | I72: 2028 | J72: 2029 | K72: 2030 | L72: 2031 | M72: 2032 | N72: 2033 | O72: 2034 | P72: 2035 | Q72: 2036 | R72: 2037 | S72: 2038 | T72: 2039 | U72: 2040 | V72: 2041 | W72: 2042 | X72: 2043 | Y72: 2044 | Z72: 2045 | AA72: 2046 | AB72: 2047 | AC72: 2048 | AD72: 2049 | AE72: 2050 | AF72: 2051 | AG72: 2052 | AH72: 2053 | AI72: 2054 | AJ72: 2055 | AK72: 2056 | AL72: 2057 | AM72: 2058 | AN72: 2059 | AO72: 2060 | AP72: 2061 | AQ72: 2062 | AR72: 2063 | AS72: 2064 | AT72: 2065 | AU72: 2066 | AV72: 2067 | AW72: 2068 | AX72: 2069 | AY72: 2070
A73: Transportation Sector | B73: 9.7021707e-07 | C73: 9.7021707e-07 | D73: 1.0052249e-06 | E73: 9.7021707e-07 | F73: 9.7567283e-07 | G73: 9.9067619e-07 | H73: 9.965866e-07 | I73: 1.0143178e-06 | J73: 1.0206829e-06 | K73: 1.0393234e-06 | L73: 1.0415967e-06 | M73: 1.057964e-06 | N73: 1.0675116e-06 | O73: 1.0897893e-06 | P73: 1.1020647e-06 | Q73: 1.1102484e-06 | R73: 1.1279796e-06 | S73: 1.1370726e-06 | T73: 1.1470748e-06 | U73: 1.1588956e-06 | V73: 1.1666246e-06 | W73: 1.1766269e-06 | X73: 1.1866291e-06 | Y73: 1.1866291e-06 | Z73: 1.1943581e-06 | AA73: 1.2120894e-06 | AB73: 1.2193637e-06 | AC73: 1.2289113e-06 | AD73: 1.2457333e-06 | AE73: 1.2461879e-06
A74: Electricity Sector | B74: 9.7021707e-07 | C74: 9.7021707e-07 | D74: 9.9707901e-07 | E74: 9.7021707e-07 | F74: 9.3652581e-07 | G74: 9.1057444e-07 | H74: 8.800702e-07 | I74: 8.6140342e-07 | J74: 8.3135447e-07 | K74: 8.4137078e-07 | L74: 8.3909435e-07 | M74: 8.5275296e-07 | N74: 8.6140342e-07 | O74: 8.6595629e-07 | P74: 8.7415146e-07 | Q74: 8.8098077e-07 | R74: 8.978264e-07 | S74: 9.0920858e-07 | T74: 9.2013547e-07 | U74: 9.3288352e-07 | V74: 9.3925754e-07 | W74: 9.4381041e-07 | X74: 9.547373e-07 | Y74: 9.5746903e-07 | Z74: 9.6657477e-07 | AA74: 9.8387568e-07 | AB74: 9.9070499e-07 | AC74: 9.9935545e-07 | AD74: 1.0175669e-06 | AE74: 1.0216645e-06
A75: Residential Buildings Sector | B75: 6.5464186e-07 | C75: 6.5464186e-07 | D75: 6.7277513e-07 | E75: 6.5464186e-07 | F75: 6.647842e-07 | G75: 6.8261012e-07 | H75: 6.9490387e-07 | I75: 7.1518855e-07 | J75: 7.2871166e-07 | K75: 7.3977603e-07 | L75: 7.4069806e-07 | M75: 7.5114775e-07 | N75: 7.5729462e-07 | O75: 7.6098274e-07 | P75: 7.6928102e-07 | Q75: 7.7450586e-07 | R75: 7.8434085e-07 | S75: 7.9110241e-07 | T75: 7.9755663e-07 | U75: 8.0493288e-07 | V75: 8.0985037e-07 | W75: 8.1630459e-07 | X75: 8.2306615e-07 | Y75: 8.2337349e-07 | Z75: 8.2921302e-07 | AA75: 8.4058473e-07 | AB75: 8.4550223e-07 | AC75: 8.516491e-07 | AD75: 8.6240613e-07 | AE75: 8.6394285e-07
A76: Commercial Buildings Sector | B76: 9.7021707e-07 | C76: 9.7021707e-07 | D76: 9.9699107e-07 | E76: 9.7021707e-07 | F76: 9.4072029e-07 | G76: 9.2211463e-07 | H76: 8.9579443e-07 | I76: 8.8081914e-07 | J76: 8.5495274e-07 | K76: 8.7219701e-07 | L76: 8.7401219e-07 | M76: 8.8944128e-07 | N76: 8.9897101e-07 | O76: 9.1803046e-07 | P76: 9.3028297e-07 | Q76: 9.3799751e-07 | R76: 9.5569558e-07 | S76: 9.6522531e-07 | T76: 9.7520883e-07 | U76: 9.8700754e-07 | V76: 9.9381449e-07 | W76: 1.0033442e-06 | X76: 1.0142353e-06 | Y76: 1.0146891e-06 | Z76: 1.0237651e-06 | AA76: 1.0405555e-06 | AB76: 1.0482701e-06 | AC76: 1.057346e-06 | AD76: 1.0741365e-06 | AE76: 1.0764055e-06
A77: Industry Sector | B77: 9.7021707e-07 | C77: 9.7021707e-07 | D77: 9.9709162e-07 | E77: 9.7021707e-07 | F77: 9.4197601e-07 | G77: 9.2421147e-07 | H77: 8.9824791e-07 | I77: 8.8458289e-07 | J77: 8.5861933e-07 | K77: 8.7683937e-07 | L77: 8.7911687e-07 | M77: 8.9505941e-07 | N77: 9.0462493e-07 | O77: 9.1054644e-07 | P77: 9.2284497e-07 | Q77: 9.3104398e-07 | R77: 9.4744202e-07 | S77: 9.5700754e-07 | T77: 9.6748406e-07 | U77: 9.7932709e-07 | V77: 9.861596e-07 | W77: 9.9618062e-07 | X77: 1.0066571e-06 | Y77: 1.0075681e-06 | Z77: 1.0166782e-06 | AA77: 1.0335317e-06 | AB77: 1.0417307e-06 | AC77: 1.0508407e-06 | AD77: 1.0681498e-06 | AE77: 1.0699718e-06
A78: District Heating Sector | B78: 9.7021707e-07 | C78: 9.7021707e-07 | D78: 9.9709162e-07 | E78: 9.7021707e-07 | F78: 9.4197601e-07 | G78: 9.2421147e-07 | H78: 8.9824791e-07 | I78: 8.8458289e-07 | J78: 8.5861933e-07 | K78: 8.7683937e-07 | L78: 8.7911687e-07 | M78: 8.9505941e-07 | N78: 9.0462493e-07 | O78: 9.1054644e-07 | P78: 9.2284497e-07 | Q78: 9.3104398e-07 | R78: 9.4744202e-07 | S78: 9.5700754e-07 | T78: 9.6748406e-07 | U78: 9.7932709e-07 | V78: 9.861596e-07 | W78: 9.9618062e-07 | X78: 1.0066571e-06 | Y78: 1.0075681e-06 | Z78: 1.0166782e-06 | AA78: 1.0335317e-06 | AB78: 1.0417307e-06 | AC78: 1.0508407e-06 | AD78: 1.0681498e-06 | AE78: 1.0699718e-06
A79: LULUCF Sector | B79: 0 | C79: 0 | D79: 0 | E79: 0 | F79: 0 | G79: 0 | H79: 0 | I79: 0 | J79: 0 | K79: 0 | L79: 0 | M79: 0 | N79: 0 | O79: 0 | P79: 0 | Q79: 0 | R79: 0 | S79: 0 | T79: 0 | U79: 0 | V79: 0 | W79: 0 | X79: 0 | Y79: 0 | Z79: 0 | AA79: 0 | AB79: 0 | AC79: 0 | AD79: 0 | AE79: 0
A80: Geoengineering Sector | B80: 9.7021707e-07 | C80: 9.7021707e-07 | D80: 9.9709162e-07 | E80: 9.7021707e-07 | F80: 9.4197601e-07 | G80: 9.2421147e-07 | H80: 8.9824791e-07 | I80: 8.8458289e-07 | J80: 8.5861933e-07 | K80: 8.7683937e-07 | L80: 8.7911687e-07 | M80: 8.9505941e-07 | N80: 9.0462493e-07 | O80: 9.1054644e-07 | P80: 9.2284497e-07 | Q80: 9.3104398e-07 | R80: 9.4744202e-07 | S80: 9.5700754e-07 | T80: 9.6748406e-07 | U80: 9.7932709e-07 | V80: 9.861596e-07 | W80: 9.9618062e-07 | X80: 1.0066571e-06 | Y80: 1.0075681e-06 | Z80: 1.0166782e-06 | AA80: 1.0335317e-06 | AB80: 1.0417307e-06 | AC80: 1.0508407e-06 | AD80: 1.0681498e-06 | AE80: 1.0699718e-06
A81: Jet Fuel
A82: Year | B82: 2021 | C82: 2022 | D82: 2023 | E82: 2024 | F82: 2025 | G82: 2026 | H82: 2027 | I82: 2028 | J82: 2029 | K82: 2030 | L82: 2031 | M82: 2032 | N82: 2033 | O82: 2034 | P82: 2035 | Q82: 2036 | R82: 2037 | S82: 2038 | T82: 2039 | U82: 2040 | V82: 2041 | W82: 2042 | X82: 2043 | Y82: 2044 | Z82: 2045 | AA82: 2046 | AB82: 2047 | AC82: 2048 | AD82: 2049 | AE82: 2050 | AF82: 2051 | AG82: 2052 | AH82: 2053 | AI82: 2054 | AJ82: 2055 | AK82: 2056 | AL82: 2057 | AM82: 2058 | AN82: 2059 | AO82: 2060 | AP82: 2061 | AQ82: 2062 | AR82: 2063 | AS82: 2064 | AT82: 2065 | AU82: 2066 | AV82: 2067 | AW82: 2068 | AX82: 2069 | AY82: 2070
A83: Transportation Sector | B83: 4.4581194e-06 | C83: 4.4581194e-06 | D83: 4.6189793e-06 | E83: 4.4581194e-06 | F83: 4.4831884e-06 | G83: 4.5521284e-06 | H83: 4.5792866e-06 | I83: 4.6607611e-06 | J83: 4.6900084e-06 | K83: 4.7756611e-06 | L83: 4.7861066e-06 | M83: 4.8613138e-06 | N83: 4.9051847e-06 | O83: 5.0075502e-06 | P83: 5.0639556e-06 | Q83: 5.1015593e-06 | R83: 5.1830338e-06 | S83: 5.2248156e-06 | T83: 5.2707756e-06 | U83: 5.325092e-06 | V83: 5.3606065e-06 | W83: 5.4065665e-06 | X83: 5.4525265e-06 | Y83: 5.4525265e-06 | Z83: 5.488041e-06 | AA83: 5.5695156e-06 | AB83: 5.602941e-06 | AC83: 5.6468119e-06 | AD83: 5.7241083e-06 | AE83: 5.7261974e-06
A84: Electricity Sector | B84: 0 | C84: 0 | D84: 0 | E84: 0 | F84: 0 | G84: 0 | H84: 0 | I84: 0 | J84: 0 | K84: 0 | L84: 0 | M84: 0 | N84: 0 | O84: 0 | P84: 0 | Q84: 0 | R84: 0 | S84: 0 | T84: 0 | U84: 0 | V84: 0 | W84: 0 | X84: 0 | Y84: 0 | Z84: 0 | AA84: 0 | AB84: 0 | AC84: 0 | AD84: 0 | AE84: 0
A85: Residential Buildings Sector | B85: 2.2909797e-06 | C85: 2.2909797e-06 | D85: 2.3544388e-06 | E85: 2.2909797e-06 | F85: 2.3264738e-06 | G85: 2.3888573e-06 | H85: 2.4318803e-06 | I85: 2.5028684e-06 | J85: 2.5501939e-06 | K85: 2.5889146e-06 | L85: 2.5921414e-06 | M85: 2.628711e-06 | N85: 2.6502225e-06 | O85: 2.6631295e-06 | P85: 2.6921701e-06 | Q85: 2.7104549e-06 | R85: 2.7448733e-06 | S85: 2.768536e-06 | T85: 2.7911232e-06 | U85: 2.816937e-06 | V85: 2.8341463e-06 | W85: 2.8567334e-06 | X85: 2.8803961e-06 | Y85: 2.8814717e-06 | Z85: 2.9019076e-06 | AA85: 2.941704e-06 | AB85: 2.9589132e-06 | AC85: 2.9804248e-06 | AD85: 3.01807e-06 | AE85: 3.0234479e-06
A86: Commercial Buildings Sector | B86: 2.2909797e-06 | C86: 2.2909797e-06 | D86: 2.3542013e-06 | E86: 2.2909797e-06 | F86: 2.2213288e-06 | G86: 2.1773951e-06 | H86: 2.1152451e-06 | I86: 2.0798838e-06 | J86: 2.0188053e-06 | K86: 2.0595243e-06 | L86: 2.0638105e-06 | M86: 2.1002433e-06 | N86: 2.1227459e-06 | O86: 2.1677512e-06 | P86: 2.1966831e-06 | Q86: 2.2148995e-06 | R86: 2.25669e-06 | S86: 2.2791926e-06 | T86: 2.3027668e-06 | U86: 2.3306272e-06 | V86: 2.3467005e-06 | W86: 2.3692031e-06 | X86: 2.3949203e-06 | Y86: 2.3959919e-06 | Z86: 2.4174229e-06 | AA86: 2.4570704e-06 | AB86: 2.4752868e-06 | AC86: 2.4967178e-06 | AD86: 2.5363653e-06 | AE86: 2.5417231e-06
A87: Industry Sector | B87: 0 | C87: 0 | D87: 0 | E87: 0 | F87: 0 | G87: 0 | H87: 0 | I87: 0 | J87: 0 | K87: 0 | L87: 0 | M87: 0 | N87: 0 | O87: 0 | P87: 0 | Q87: 0 | R87: 0 | S87: 0 | T87: 0 | U87: 0 | V87: 0 | W87: 0 | X87: 0 | Y87: 0 | Z87: 0 | AA87: 0 | AB87: 0 | AC87: 0 | AD87: 0 | AE87: 0
A88: District Heating Sector | B88: 0 | C88: 0 | D88: 0 | E88: 0 | F88: 0 | G88: 0 | H88: 0 | I88: 0 | J88: 0 | K88: 0 | L88: 0 | M88: 0 | N88: 0 | O88: 0 | P88: 0 | Q88: 0 | R88: 0 | S88: 0 | T88: 0 | U88: 0 | V88: 0 | W88: 0 | X88: 0 | Y88: 0 | Z88: 0 | AA88: 0 | AB88: 0 | AC88: 0 | AD88: 0 | AE88: 0
A89: LULUCF Sector | B89: 0 | C89: 0 | D89: 0 | E89: 0 | F89: 0 | G89: 0 | H89: 0 | I89: 0 | J89: 0 | K89: 0 | L89: 0 | M89: 0 | N89: 0 | O89: 0 | P89: 0 | Q89: 0 | R89: 0 | S89: 0 | T89: 0 | U89: 0 | V89: 0 | W89: 0 | X89: 0 | Y89: 0 | Z89: 0 | AA89: 0 | AB89: 0 | AC89: 0 | AD89: 0 | AE89: 0
A90: Geoengineering Sector | B90: 0 | C90: 0 | D90: 0 | E90: 0 | F90: 0 | G90: 0 | H90: 0 | I90: 0 | J90: 0 | K90: 0 | L90: 0 | M90: 0 | N90: 0 | O90: 0 | P90: 0 | Q90: 0 | R90: 0 | S90: 0 | T90: 0 | U90: 0 | V90: 0 | W90: 0 | X90: 0 | Y90: 0 | Z90: 0 | AA90: 0 | AB90: 0 | AC90: 0 | AD90: 0 | AE90: 0
A91: Lignite
A92: Year | B92: 2021 | C92: 2022 | D92: 2023 | E92: 2024 | F92: 2025 | G92: 2026 | H92: 2027 | I92: 2028 | J92: 2029 | K92: 2030 | L92: 2031 | M92: 2032 | N92: 2033 | O92: 2034 | P92: 2035 | Q92: 2036 | R92: 2037 | S92: 2038 | T92: 2039 | U92: 2040 | V92: 2041 | W92: 2042 | X92: 2043 | Y92: 2044 | Z92: 2045 | AA92: 2046 | AB92: 2047 | AC92: 2048 | AD92: 2049 | AE92: 2050 | AF92: 2051 | AG92: 2052 | AH92: 2053 | AI92: 2054 | AJ92: 2055 | AK92: 2056 | AL92: 2057 | AM92: 2058 | AN92: 2059 | AO92: 2060 | AP92: 2061 | AQ92: 2062 | AR92: 2063 | AS92: 2064 | AT92: 2065 | AU92: 2066 | AV92: 2067 | AW92: 2068 | AX92: 2069 | AY92: 2070
A93: Transportation Sector | B93: 0 | C93: 0 | D93: 0 | E93: 0 | F93: 0 | G93: 0 | H93: 0 | I93: 0 | J93: 0 | K93: 0 | L93: 0 | M93: 0 | N93: 0 | O93: 0 | P93: 0 | Q93: 0 | R93: 0 | S93: 0 | T93: 0 | U93: 0 | V93: 0 | W93: 0 | X93: 0 | Y93: 0 | Z93: 0 | AA93: 0 | AB93: 0 | AC93: 0 | AD93: 0 | AE93: 0
A94: Electricity Sector | B94: 3.691346e-07 | C94: 3.691346e-07 | D94: 3.6734269e-07 | E94: 3.691346e-07 | F94: 3.6375886e-07 | G94: 3.5838311e-07 | H94: 3.5479928e-07 | I94: 3.5300736e-07 | J94: 3.4942353e-07 | K94: 3.5121545e-07 | L94: 3.5300736e-07 | M94: 3.5121545e-07 | N94: 3.5121545e-07 | O94: 3.5121545e-07 | P94: 3.4942353e-07 | Q94: 3.4942353e-07 | R94: 3.5121545e-07 | S94: 3.5121545e-07 | T94: 3.4942353e-07 | U94: 3.4942353e-07 | V94: 3.5121545e-07 | W94: 3.5121545e-07 | X94: 3.4942353e-07 | Y94: 3.4942353e-07 | Z94: 3.4942353e-07 | AA94: 3.4942353e-07 | AB94: 3.4942353e-07 | AC94: 3.4942353e-07 | AD94: 3.4942353e-07 | AE94: 3.4942353e-07
A95: Residential Buildings Sector | B95: 0 | C95: 0 | D95: 0 | E95: 0 | F95: 0 | G95: 0 | H95: 0 | I95: 0 | J95: 0 | K95: 0 | L95: 0 | M95: 0 | N95: 0 | O95: 0 | P95: 0 | Q95: 0 | R95: 0 | S95: 0 | T95: 0 | U95: 0 | V95: 0 | W95: 0 | X95: 0 | Y95: 0 | Z95: 0 | AA95: 0 | AB95: 0 | AC95: 0 | AD95: 0 | AE95: 0
A96: Commercial Buildings Sector | B96: 0 | C96: 0 | D96: 0 | E96: 0 | F96: 0 | G96: 0 | H96: 0 | I96: 0 | J96: 0 | K96: 0 | L96: 0 | M96: 0 | N96: 0 | O96: 0 | P96: 0 | Q96: 0 | R96: 0 | S96: 0 | T96: 0 | U96: 0 | V96: 0 | W96: 0 | X96: 0 | Y96: 0 | Z96: 0 | AA96: 0 | AB96: 0 | AC96: 0 | AD96: 0 | AE96: 0
A97: Industry Sector | B97: 3.691346e-07 | C97: 3.691346e-07 | D97: 3.6736841e-07 | E97: 3.691346e-07 | F97: 3.6560221e-07 | G97: 3.6030363e-07 | H97: 3.5853744e-07 | I97: 3.5677124e-07 | J97: 3.5500505e-07 | K97: 3.5677124e-07 | L97: 3.5853744e-07 | M97: 3.5500505e-07 | N97: 3.5677124e-07 | O97: 3.5677124e-07 | P97: 3.5500505e-07 | Q97: 3.5500505e-07 | R97: 3.5677124e-07 | S97: 3.5677124e-07 | T97: 3.5500505e-07 | U97: 3.5500505e-07 | V97: 3.5677124e-07 | W97: 3.5677124e-07 | X97: 3.5677124e-07 | Y97: 3.5500505e-07 | Z97: 3.5500505e-07 | AA97: 3.5677124e-07 | AB97: 3.5677124e-07 | AC97: 3.5677124e-07 | AD97: 3.5677124e-07 | AE97: 3.5677124e-07
A98: District Heating Sector | B98: 3.691346e-07 | C98: 3.691346e-07 | D98: 3.6736841e-07 | E98: 3.691346e-07 | F98: 3.6560221e-07 | G98: 3.6030363e-07 | H98: 3.5853744e-07 | I98: 3.5677124e-07 | J98: 3.5500505e-07 | K98: 3.5677124e-07 | L98: 3.5853744e-07 | M98: 3.5500505e-07 | N98: 3.5677124e-07 | O98: 3.5677124e-07 | P98: 3.5500505e-07 | Q98: 3.5500505e-07 | R98: 3.5677124e-07 | S98: 3.5677124e-07 | T98: 3.5500505e-07 | U98: 3.5500505e-07 | V98: 3.5677124e-07 | W98: 3.5677124e-07 | X98: 3.5677124e-07 | Y98: 3.5500505e-07 | Z98: 3.5500505e-07 | AA98: 3.5677124e-07 | AB98: 3.5677124e-07 | AC98: 3.5677124e-07 | AD98: 3.5677124e-07 | AE98: 3.5677124e-07
A99: LULUCF Sector | B99: 0 | C99: 0 | D99: 0 | E99: 0 | F99: 0 | G99: 0 | H99: 0 | I99: 0 | J99: 0 | K99: 0 | L99: 0 | M99: 0 | N99: 0 | O99: 0 | P99: 0 | Q99: 0 | R99: 0 | S99: 0 | T99: 0 | U99: 0 | V99: 0 | W99: 0 | X99: 0 | Y99: 0 | Z99: 0 | AA99: 0 | AB99: 0 | AC99: 0 | AD99: 0 | AE99: 0
A100: Geoengineering Sector | B100: 3.691346e-07 | C100: 3.691346e-07 | D100: 3.6736841e-07 | E100: 3.691346e-07 | F100: 3.6560221e-07 | G100: 3.6030363e-07 | H100: 3.5853744e-07 | I100: 3.5677124e-07 | J100: 3.5500505e-07 | K100: 3.5677124e-07 | L100: 3.5853744e-07 | M100: 3.5500505e-07 | N100: 3.5677124e-07 | O100: 3.5677124e-07 | P100: 3.5500505e-07 | Q100: 3.5500505e-07 | R100: 3.5677124e-07 | S100: 3.5677124e-07 | T100: 3.5500505e-07 | U100: 3.5500505e-07 | V100: 3.5677124e-07 | W100: 3.5677124e-07 | X100: 3.5677124e-07 | Y100: 3.5500505e-07 | Z100: 3.5500505e-07 | AA100: 3.5677124e-07 | AB100: 3.5677124e-07 | AC100: 3.5677124e-07 | AD100: 3.5677124e-07 | AE100: 3.5677124e-07
...

Sheet BAU Fuel Use by Sector
A1: Time (Time) | B1: 2019 | C1: 2020 | D1: 2021 | E1: 2022 | F1: 2023 | G1: 2024 | H1: 2025 | I1: 2026 | J1: 2027 | K1: 2028 | L1: 2029 | M1: 2030 | N1: 2031 | O1: 2032 | P1: 2033 | Q1: 2034 | R1: 2035 | S1: 2036 | T1: 2037 | U1: 2038 | V1: 2039 | W1: 2040 | X1: 2041 | Y1: 2042 | Z1: 2043 | AA1: 2044 | AB1: 2045 | AC1: 2046 | AD1: 2047 | AE1: 2048 | AF1: 2049 | AG1: 2050 | AJ1: Fuel Use by Sector (EPS output)
A2: Electricity Fuel Use[hard coal es,preexisting retiring] : MostRecentRun | B2: 8.92256e+15 | C2: 7.88532e+15 | D2: 7.7882e+15 | E2: 7.52135e+15 | F2: 7.95155e+15 | G2: 7.95539e+15 | H2: 7.68633e+15 | I2: 7.46396e+15 | J2: 7.22597e+15 | K2: 7.24423e+15 | L2: 7.33847e+15 | M2: 7.42837e+15 | N2: 7.49012e+15 | O2: 7.55634e+15 | P2: 7.67564e+15 | Q2: 7.68061e+15 | R2: 7.68299e+15 | S2: 7.68551e+15 | T2: 7.6898e+15 | U2: 7.694e+15 | V2: 7.69217e+15 | W2: 7.69031e+15 | X2: 7.69113e+15 | Y2: 7.69319e+15 | Z2: 7.70783e+15 | AA2: 7.7063e+15 | AB2: 7.70536e+15 | AC2: 7.70438e+15 | AD2: 7.70048e+15 | AE2: 7.70102e+15 | AF2: 7.69612e+15 | AG2: 7.69603e+15 | AL2: electricity (energy carrier) | AM2: hard coal | AN2: natural gas | AO2: nuclear | AP2: hydro (is not a fuel) | AQ2: wind (is not a fuel) | AR2: solar (is not a fuel) | AS2: biomass | AT2: petroleum gasoline | AU2: petroleum diesel | AV2: biofuel gasoline | AW2: biofuel diesel | AX2: jet fuel | AY2: heat (energy carrier) | AZ2: geothermal (is not a fuel) | BA2: lignite | BB2: crude oil | BC2: heavy fuel oil | BD2: LPG propane or butane | BE2: municipal solid waste | BF2: hydrogen
A3: Electricity Fuel Use[hard coal es,preexisting nonretiring] : MostRecentRun | B3: 0 | C3: 1214330000000 | D3: 2127600000000 | E3: 3456580000000 | F3: 4799370000000 | G3: 6377620000000 | H3: 7795670000000 | I3: 9029970000000 | J3: 10188600000000 | K3: 11271000000000 | L3: 12607600000000 | M3: 14045000000000 | N3: 15505400000000 | O3: 16940800000000 | P3: 18382100000000 | Q3: 19960700000000 | R3: 21302700000000 | S3: 22639200000000 | T3: 23977200000000 | U3: 25321400000000 | V3: 26666000000000 | W3: 27992500000000 | X3: 29318900000000 | Y3: 30654100000000 | Z3: 31993300000000 | AA3: 33379900000000 | AB3: 34708600000000 | AC3: 36039100000000 | AD3: 37369100000000 | AE3: 38686200000000 | AF3: 40021900000000 | AG3: 41332700000000 | AJ3: Transportation | AL3: =SUMIFS($B:$B,$A:$A,"*"&$AJ3&"*",$A:$A,"*"&AL$2&"*") -> 0 | AM3: =SUMIFS($B:$B,$A:$A,"*"&$AJ3&"*",$A:$A,"*"&AM$2&"*") -> 0 | AN3: =SUMIFS($B:$B,$A:$A,"*"&$AJ3&"*",$A:$A,"*"&AN$2&"*") -> 63901931000000 | AO3: =SUMIFS($B:$B,$A:$A,"*"&$AJ3&"*",$A:$A,"*"&AO$2&"*") -> 0 | AP3: =SUMIFS($B:$B,$A:$A,"*"&$AJ3&"*",$A:$A,"*"&AP$2&"*") -> 0 | AQ3: =SUMIFS($B:$B,$A:$A,"*"&$AJ3&"*",$A:$A,"*"&AQ$2&"*") -> 0 | AR3: =SUMIFS($B:$B,$A:$A,"*"&$AJ3&"*",$A:$A,"*"&AR$2&"*") -> 0 | AS3: =SUMIFS($B:$B,$A:$A,"*"&$AJ3&"*",$A:$A,"*"&AS$2&"*") -> 0 | ... BF3: =SUMIFS($B:$B,$A:$A,"*"&$AJ3&"*",$A:$A,"*"&BF$2&"*") -> 0
A4: Electricity Fuel Use[hard coal es,newly built] : MostRecentRun | B4: 458263000000000 | C4: 926831000000000 | D4: 1.42466e+15 | E4: 1.90961e+15 | F4: 1.99038e+15 | G4: 2.13042e+15 | H4: 2.30779e+15 | I4: 2.39389e+15 | J4: 2.46368e+15 | K4: 2.50908e+15 | L4: 2.53894e+15 | M4: 2.56805e+15 | N4: 2.59257e+15 | O4: 2.60371e+15 | P4: 2.6226e+15 | Q4: 2.62467e+15 | R4: 2.62595e+15 | S4: 2.62746e+15 | T4: 2.62943e+15 | U4: 2.63119e+15 | V4: 2.63186e+15 | W4: 2.63273e+15 | X4: 2.63408e+15 | Y4: 2.63543e+15 | Z4: 2.63867e+15 | AA4: 2.63964e+15 | AB4: 2.64065e+15 | AC4: 2.64165e+15 | AD4: 2.64222e+15 | AE4: 2.64343e+15 | AF4: 2.64387e+15 | AG4: 2.64498e+15 | AJ4: Electricity Fuel Use | AL4: =SUMIFS($B:$B,$A:$A,"*"&$AJ4&"*",$A:$A,"*"&AL$2&"*") -> 0 | AM4: =SUMIFS($B:$B,$A:$A,"*"&$AJ4&"*",$A:$A,"*"&AM$2&"*") -> 9.380823e+15 | AN4: =SUMIFS($B:$B,$A:$A,"*"&$AJ4&"*",$A:$A,"*"&AN$2&"*") -> 10131100000000 | AO4: =SUMIFS($B:$B,$A:$A,"*"&$AJ4&"*",$A:$A,"*"&AO$2&"*") -> 374046000000000 | AP4: =SUMIFS($B:$B,$A:$A,"*"&$AJ4&"*",$A:$A,"*"&AP$2&"*") -> 0 | AQ4: =SUMIFS($B:$B,$A:$A,"*"&$AJ4&"*",$A:$A,"*"&AQ$2&"*") -> 0 | AR4: =SUMIFS($B:$B,$A:$A,"*"&$AJ4&"*",$A:$A,"*"&AR$2&"*") -> 0 | AS4: =SUMIFS($B:$B,$A:$A,"*"&$AJ4&"*",$A:$A,"*"&AS$2&"*") -> 329559200000000 | ... BF4: =SUMIFS($B:$B,$A:$A,"*"&$AJ4&"*",$A:$A,"*"&BF$2&"*") -> 0
A5: Electricity Fuel Use[natural gas nonpeaker es,preexisting retiring] : MostRecentRun | B5: 6862060000000 | C5: 5896660000000 | D5: 1024690000000 | E5: 832984000000 | F5: 1186790000000 | G5: 1572800000000 | H5: 1345120000000 | I5: 1198960000000 | J5: 1132950000000 | K5: 951551000000 | L5: 851117000000 | M5: 817195000000 | N5: 798843000000 | O5: 756020000000 | P5: 737866000000 | Q5: 716643000000 | R5: 692968000000 | S5: 689989000000 | T5: 709375000000 | U5: 694973000000 | V5: 681592000000 | W5: 681915000000 | X5: 687612000000 | Y5: 695791000000 | Z5: 713659000000 | AA5: 715959000000 | AB5: 711507000000 | AC5: 701876000000 | AD5: 683395000000 | AE5: 651757000000 | AF5: 616570000000 | AG5: 594184000000 | AJ5: Building Components Energy Use | AK5: residential | AL5: =SUMIFS($B:$B,$A:$A,"*"&$AJ5&"*",$A:$A,"*"&AL$2&"*") -> 0 | AM5: =SUMIFS($B:$B,$A:$A,"*"&$AJ5&"*",$A:$A,"*"&AM$2&"*") -> 0 | AN5: =SUMIFS($B:$B,$A:$A,"*"&$AJ5&"*",$A:$A,"*"&AN$2&"*") -> 151951000000000 | AO5: =SUMIFS($B:$B,$A:$A,"*"&$AJ5&"*",$A:$A,"*"&AO$2&"*") -> 0 | AP5: =SUMIFS($B:$B,$A:$A,"*"&$AJ5&"*",$A:$A,"*"&AP$2&"*") -> 0 | AQ5: =SUMIFS($B:$B,$A:$A,"*"&$AJ5&"*",$A:$A,"*"&AQ$2&"*") -> 0 | AR5: =SUMIFS($B:$B,$A:$A,"*"&$AJ5&"*",$A:$A,"*"&AR$2&"*") -> 0 | AS5: =SUMIFS($B:$B,$A:$A,"*"&$AJ5&"*",$A:$A,"*"&AS$2&"*") -> 3.42302e+15 | ... BF5: =SUMIFS($B:$B,$A:$A,"*"&$AJ5&"*",$A:$A,"*"&BF$2&"*") -> 0
A6: Electricity Fuel Use[natural gas nonpeaker es,preexisting nonretiring] : MostRecentRun | B6: 0 | C6: 0 | D6: 0 | E6: 0 | F6: 0 | G6: 0 | H6: 0 | I6: 0 | J6: 0 | K6: 0 | L6: 0 | M6: 0 | N6: 0 | O6: 0 | P6: 0 | Q6: 0 | R6: 0 | S6: 0 | T6: 0 | U6: 0 | V6: 0 | W6: 0 | X6: 0 | Y6: 0 | Z6: 0 | AA6: 0 | AB6: 0 | AC6: 0 | AD6: 0 | AE6: 0 | AF6: 0 | AG6: 0 | AJ6: Building Components Energy Use | AK6: commercial | AL6: =SUMIFS($B:$B,$A:$A,"*"&$AJ6&"*",$A:$A,"*"&AL$2&"*") -> 0 | AM6: =SUMIFS($B:$B,$A:$A,"*"&$AJ6&"*",$A:$A,"*"&AM$2&"*") -> 0 | AN6: =SUMIFS($B:$B,$A:$A,"*"&$AJ6&"*",$A:$A,"*"&AN$2&"*") -> 151951000000000 | AO6: =SUMIFS($B:$B,$A:$A,"*"&$AJ6&"*",$A:$A,"*"&AO$2&"*") -> 0 | AP6: =SUMIFS($B:$B,$A:$A,"*"&$AJ6&"*",$A:$A,"*"&AP$2&"*") -> 0 | AQ6: =SUMIFS($B:$B,$A:$A,"*"&$AJ6&"*",$A:$A,"*"&AQ$2&"*") -> 0 | AR6: =SUMIFS($B:$B,$A:$A,"*"&$AJ6&"*",$A:$A,"*"&AR$2&"*") -> 0 | AS6: =SUMIFS($B:$B,$A:$A,"*"&$AJ6&"*",$A:$A,"*"&AS$2&"*") -> 3.42302e+15 | ... BF6: =SUMIFS($B:$B,$A:$A,"*"&$AJ6&"*",$A:$A,"*"&BF$2&"*") -> 0
A7: Electricity Fuel Use[natural gas nonpeaker es,newly built] : MostRecentRun | B7: 0 | C7: 0 | D7: 0 | E7: 0 | F7: 0 | G7: 0 | H7: 0 | I7: 0 | J7: 0 | K7: 0 | L7: 0 | M7: 0 | N7: 0 | O7: 0 | P7: 0 | Q7: 0 | R7: 0 | S7: 0 | T7: 0 | U7: 0 | V7: 0 | W7: 0 | X7: 0 | Y7: 0 | Z7: 0 | AA7: 0 | AB7: 0 | AC7: 0 | AD7: 0 | AE7: 0 | AF7: 0 | AG7: 0 | AJ7: Industrial Fuel Use | AL7: =SUMIFS($B:$B,$A:$A,"*"&$AJ7&"*",$A:$A,"*"&AL$2&"*") -> 0 | AM7: =SUMIFS($B:$B,$A:$A,"*"&$AJ7&"*",$A:$A,"*"&AM$2&"*") -> 5.9230872e+15 | AN7: =SUMIFS($B:$B,$A:$A,"*"&$AJ7&"*",$A:$A,"*"&AN$2&"*") -> 1.3596751e+16 | AO7: =SUMIFS($B:$B,$A:$A,"*"&$AJ7&"*",$A:$A,"*"&AO$2&"*") -> 0 | AP7: =SUMIFS($B:$B,$A:$A,"*"&$AJ7&"*",$A:$A,"*"&AP$2&"*") -> 0 | AQ7: =SUMIFS($B:$B,$A:$A,"*"&$AJ7&"*",$A:$A,"*"&AQ$2&"*") -> 0 | AR7: =SUMIFS($B:$B,$A:$A,"*"&$AJ7&"*",$A:$A,"*"&AR$2&"*") -> 0 | AS7: =SUMIFS($B:$B,$A:$A,"*"&$AJ7&"*",$A:$A,"*"&AS$2&"*") -> 2.12e+15 | ... BF7: =SUMIFS($B:$B,$A:$A,"*"&$AJ7&"*",$A:$A,"*"&BF$2&"*") -> 0
A8: Electricity Fuel Use[nuclear es,preexisting retiring] : MostRecentRun | B8: 374046000000000 | C8: 374046000000000 | D8: 374046000000000 | E8: 374046000000000 | F8: 374046000000000 | G8: 374046000000000 | H8: 374046000000000 | I8: 374046000000000 | J8: 374046000000000 | K8: 374046000000000 | L8: 374046000000000 | M8: 374046000000000 | N8: 374046000000000 | O8: 374046000000000 | P8: 374046000000000 | Q8: 374046000000000 | R8: 374046000000000 | S8: 374046000000000 | T8: 374046000000000 | U8: 374046000000000 | V8: 374046000000000 | W8: 374046000000000 | X8: 374046000000000 | Y8: 374046000000000 | Z8: 374046000000000 | AA8: 374046000000000 | AB8: 374046000000000 | AC8: 374046000000000 | AD8: 374046000000000 | AE8: 374046000000000 | AF8: 374046000000000 | AG8: 374046000000000
A9: Electricity Fuel Use[nuclear es,preexisting nonretiring] : MostRecentRun | B9: 0 | C9: 0 | D9: 0 | E9: 0 | F9: 0 | G9: 0 | H9: 0 | I9: 0 | J9: 0 | K9: 0 | L9: 0 | M9: 0 | N9: 0 | O9: 0 | P9: 0 | Q9: 0 | R9: 0 | S9: 0 | T9: 0 | U9: 0 | V9: 0 | W9: 0 | X9: 0 | Y9: 0 | Z9: 0 | AA9: 0 | AB9: 0 | AC9: 0 | AD9: 0 | AE9: 0 | AF9: 0 | AG9: 0
A10: Electricity Fuel Use[nuclear es,newly built] : MostRecentRun | B10: 0 | C10: 28096900000000 | D10: 57218700000000 | E10: 87365300000000 | F10: 147957000000000 | G10: 240831000000000 | H10: 367395000000000 | I10: 466930000000000 | J10: 569539000000000 | K10: 578763000000000 | L10: 587217000000000 | M10: 596441000000000 | N10: 639312000000000 | O10: 683208000000000 | P10: 683208000000000 | Q10: 683208000000000 | R10: 683208000000000 | S10: 683208000000000 | T10: 683208000000000 | U10: 683208000000000 | V10: 683208000000000 | W10: 683208000000000 | X10: 683208000000000 | Y10: 683208000000000 | Z10: 683208000000000 | AA10: 683208000000000 | AB10: 683208000000000 | AC10: 683208000000000 | AD10: 683208000000000 | AE10: 683208000000000 | AF10: 683208000000000 | AG10: 683208000000000
A11: Electricity Fuel Use[hydro es,preexisting retiring] : MostRecentRun | B11: 0 | C11: 0 | D11: 0 | E11: 0 | F11: 0 | G11: 0 | H11: 0 | I11: 0 | J11: 0 | K11: 0 | L11: 0 | M11: 0 | N11: 0 | O11: 0 | P11: 0 | Q11: 0 | R11: 0 | S11: 0 | T11: 0 | U11: 0 | V11: 0 | W11: 0 | X11: 0 | Y11: 0 | Z11: 0 | AA11: 0 | AB11: 0 | AC11: 0 | AD11: 0 | AE11: 0 | AF11: 0 | AG11: 0
A12: Electricity Fuel Use[hydro es,preexisting nonretiring] : MostRecentRun | B12: 0 | C12: 0 | D12: 0 | E12: 0 | F12: 0 | G12: 0 | H12: 0 | I12: 0 | J12: 0 | K12: 0 | L12: 0 | M12: 0 | N12: 0 | O12: 0 | P12: 0 | Q12: 0 | R12: 0 | S12: 0 | T12: 0 | U12: 0 | V12: 0 | W12: 0 | X12: 0 | Y12: 0 | Z12: 0 | AA12: 0 | AB12: 0 | AC12: 0 | AD12: 0 | AE12: 0 | AF12: 0 | AG12: 0
A13: Electricity Fuel Use[hydro es,newly built] : MostRecentRun | B13: 0 | C13: 0 | D13: 0 | E13: 0 | F13: 0 | G13: 0 | H13: 0 | I13: 0 | J13: 0 | K13: 0 | L13: 0 | M13: 0 | N13: 0 | O13: 0 | P13: 0 | Q13: 0 | R13: 0 | S13: 0 | T13: 0 | U13: 0 | V13: 0 | W13: 0 | X13: 0 | Y13: 0 | Z13: 0 | AA13: 0 | AB13: 0 | AC13: 0 | AD13: 0 | AE13: 0 | AF13: 0 | AG13: 0
A14: Electricity Fuel Use[onshore wind es,preexisting retiring] : MostRecentRun | B14: 0 | C14: 0 | D14: 0 | E14: 0 | F14: 0 | G14: 0 | H14: 0 | I14: 0 | J14: 0 | K14: 0 | L14: 0 | M14: 0 | N14: 0 | O14: 0 | P14: 0 | Q14: 0 | R14: 0 | S14: 0 | T14: 0 | U14: 0 | V14: 0 | W14: 0 | X14: 0 | Y14: 0 | Z14: 0 | AA14: 0 | AB14: 0 | AC14: 0 | AD14: 0 | AE14: 0 | AF14: 0 | AG14: 0
A15: Electricity Fuel Use[onshore wind es,preexisting nonretiring] : MostRecentRun | B15: 0 | C15: 0 | D15: 0 | E15: 0 | F15: 0 | G15: 0 | H15: 0 | I15: 0 | J15: 0 | K15: 0 | L15: 0 | M15: 0 | N15: 0 | O15: 0 | P15: 0 | Q15: 0 | R15: 0 | S15: 0 | T15: 0 | U15: 0 | V15: 0 | W15: 0 | X15: 0 | Y15: 0 | Z15: 0 | AA15: 0 | AB15: 0 | AC15: 0 | AD15: 0 | AE15: 0 | AF15: 0 | AG15: 0
A16: Electricity Fuel Use[onshore wind es,newly built] : MostRecentRun | B16: 0 | C16: 0 | D16: 0 | E16: 0 | F16: 0 | G16: 0 | H16: 0 | I16: 0 | J16: 0 | K16: 0 | L16: 0 | M16: 0 | N16: 0 | O16: 0 | P16: 0 | Q16: 0 | R16: 0 | S16: 0 | T16: 0 | U16: 0 | V16: 0 | W16: 0 | X16: 0 | Y16: 0 | Z16: 0 | AA16: 0 | AB16: 0 | AC16: 0 | AD16: 0 | AE16: 0 | AF16: 0 | AG16: 0
A17: Electricity Fuel Use[solar PV es,preexisting retiring] : MostRecentRun | B17: 0 | C17: 0 | D17: 0 | E17: 0 | F17: 0 | G17: 0 | H17: 0 | I17: 0 | J17: 0 | K17: 0 | L17: 0 | M17: 0 | N17: 0 | O17: 0 | P17: 0 | Q17: 0 | R17: 0 | S17: 0 | T17: 0 | U17: 0 | V17: 0 | W17: 0 | X17: 0 | Y17: 0 | Z17: 0 | AA17: 0 | AB17: 0 | AC17: 0 | AD17: 0 | AE17: 0 | AF17: 0 | AG17: 0
A18: Electricity Fuel Use[solar PV es,preexisting nonretiring] : MostRecentRun | B18: 0 | C18: 0 | D18: 0 | E18: 0 | F18: 0 | G18: 0 | H18: 0 | I18: 0 | J18: 0 | K18: 0 | L18: 0 | M18: 0 | N18: 0 | O18: 0 | P18: 0 | Q18: 0 | R18: 0 | S18: 0 | T18: 0 | U18: 0 | V18: 0 | W18: 0 | X18: 0 | Y18: 0 | Z18: 0 | AA18: 0 | AB18: 0 | AC18: 0 | AD18: 0 | AE18: 0 | AF18: 0 | AG18: 0
A19: Electricity Fuel Use[solar PV es,newly built] : MostRecentRun | B19: 0 | C19: 0 | D19: 0 | E19: 0 | F19: 0 | G19: 0 | H19: 0 | I19: 0 | J19: 0 | K19: 0 | L19: 0 | M19: 0 | N19: 0 | O19: 0 | P19: 0 | Q19: 0 | R19: 0 | S19: 0 | T19: 0 | U19: 0 | V19: 0 | W19: 0 | X19: 0 | Y19: 0 | Z19: 0 | AA19: 0 | AB19: 0 | AC19: 0 | AD19: 0 | AE19: 0 | AF19: 0 | AG19: 0
... A1156: Building Components Energy Use[commercial,hydrogen bf,other component] : MostRecentRun | B1156: 0 | C1156: 0 | D1156: 0 | E1156: 0 | F1156: 0 | G1156: 0 | H1156: 0 | I1156: 0 | J1156: 0 | K1156: 0 | L1156: 0 | M1156: 0 | N1156: 0 | O1156: 0 | P1156: 0 | Q1156: 0 | R1156: 0 | S1156: 0 | T1156: 0 | U1156: 0 | V1156: 0 | W1156: 0 | X1156: 0 | Y1156: 0 | Z1156: 0 | AA1156: 0 | AB1156: 0 | AC1156: 0 | AD1156: 0 | AE1156: 0 | AF1156: 0 | AG1156: 0

Sheet Fuel Price Data
A1: Hard Coal
A2: Year | B2: 2021 | C2: 2022 | D2: 2023 | E2: 2024 | F2: 2025 | G2: 2026 | H2: 2027 | I2: 2028 | J2: 2029 | K2: 2030 | L2: 2031 | M2: 2032 | N2: 2033 | O2: 2034 | P2: 2035 | Q2: 2036 | R2: 2037 | S2: 2038 | T2: 2039 | U2: 2040 | V2: 2041 | W2: 2042 | X2: 2043 | Y2: 2044 | Z2: 2045 | AA2: 2046 | AB2: 2047 | AC2: 2048 | AD2: 2049 | AE2: 2050 | AF2: 2051 | AG2: 2052 | AH2: 2053 | AI2: 2054 | AJ2: 2055 | AK2: 2056 | AL2: 2057 | AM2: 2058 | AN2: 2059 | AO2: 2060 | AP2: 2061 | AQ2: 2062 | AR2: 2063 | AS2: 2064 | AT2: 2065 | AU2: 2066 | AV2: 2067 | AW2: 2068 | AX2: 2069 | AY2: 2070
A3: Transportation Sector | B3: ='Pretax Fuel Prices'!B3+'Fuel Taxes'!B3 -> 0 | C3: ='Pretax Fuel Prices'!C3+'Fuel Taxes'!C3 -> 0 | D3: ='Pretax Fuel Prices'!D3+'Fuel Taxes'!D3 -> 0 | E3: ='Pretax Fuel Prices'!E3+'Fuel Taxes'!E3 -> 0 | F3: ='Pretax Fuel Prices'!F3+'Fuel Taxes'!F3 -> 0 | G3: ='Pretax Fuel Prices'!G3+'Fuel Taxes'!G3 -> 0 | H3: ='Pretax Fuel Prices'!H3+'Fuel Taxes'!H3 -> 0 | I3: ='Pretax Fuel Prices'!I3+'Fuel Taxes'!I3 -> 0 | ... AI3: ='Pretax Fuel Prices'!AI3+'Fuel Taxes'!AI3 -> 0
A4: Electricity Sector | B4: ='Pretax Fuel Prices'!B4+'Fuel Taxes'!B4 -> 1.9762037e-06 | C4: ='Pretax Fuel Prices'!C4+'Fuel Taxes'!C4 -> 1.9762037e-06 | D4: ='Pretax Fuel Prices'!D4+'Fuel Taxes'!D4 -> 1.9666104e-06 | E4: ='Pretax Fuel Prices'!E4+'Fuel Taxes'!E4 -> 1.9762037e-06 | F4: ='Pretax Fuel Prices'!F4+'Fuel Taxes'!F4 -> 1.947424e-06 | G4: ='Pretax Fuel Prices'!G4+'Fuel Taxes'!G4 -> 1.9186443e-06 | H4: ='Pretax Fuel Prices'!H4+'Fuel Taxes'!H4 -> 1.8994579e-06 | I4: ='Pretax Fuel Prices'!I4+'Fuel Taxes'!I4 -> 1.8898647e-06 | ... AI4: ='Pretax Fuel Prices'!AI4+'Fuel Taxes'!AI4 -> 0
A5: Residential Buildings Sector | B5: ='Pretax Fuel Prices'!B5+'Fuel Taxes'!B5 -> 0 | C5: ='Pretax Fuel Prices'!C5+'Fuel Taxes'!C5 -> 0 | D5: ='Pretax Fuel Prices'!D5+'Fuel Taxes'!D5 -> 0 | E5: ='Pretax Fuel Prices'!E5+'Fuel Taxes'!E5 -> 0 | F5: ='Pretax Fuel Prices'!F5+'Fuel Taxes'!F5 -> 0 | G5: ='Pretax Fuel Prices'!G5+'Fuel Taxes'!G5 -> 0 | H5: ='Pretax Fuel Prices'!H5+'Fuel Taxes'!H5 -> 0 | I5: ='Pretax Fuel Prices'!I5+'Fuel Taxes'!I5 -> 0 | ... AI5: ='Pretax Fuel Prices'!AI5+'Fuel Taxes'!AI5 -> 0
A6: Commercial Buildings Sector | B6: ='Pretax Fuel Prices'!B6+'Fuel Taxes'!B6 -> 0 | C6: ='Pretax Fuel Prices'!C6+'Fuel Taxes'!C6 -> 0 | D6: ='Pretax Fuel Prices'!D6+'Fuel Taxes'!D6 -> 0 | E6: ='Pretax Fuel Prices'!E6+'Fuel Taxes'!E6 -> 0 | F6: ='Pretax Fuel Prices'!F6+'Fuel Taxes'!F6 -> 0 | G6: ='Pretax Fuel Prices'!G6+'Fuel Taxes'!G6 -> 0 | H6: ='Pretax Fuel Prices'!H6+'Fuel Taxes'!H6 -> 0 | I6: ='Pretax Fuel Prices'!I6+'Fuel Taxes'!I6 -> 0 | ... AI6: ='Pretax Fuel Prices'!AI6+'Fuel Taxes'!AI6 -> 0
A7: Industry Sector | B7: ='Pretax Fuel Prices'!B7+'Fuel Taxes'!B7 -> 2.3704768e-06 | C7: ='Pretax Fuel Prices'!C7+'Fuel Taxes'!C7 -> 2.3704768e-06 | D7: ='Pretax Fuel Prices'!D7+'Fuel Taxes'!D7 -> 2.3704768e-06 | E7: ='Pretax Fuel Prices'!E7+'Fuel Taxes'!E7 -> 2.3704768e-06 | F7: ='Pretax Fuel Prices'!F7+'Fuel Taxes'!F7 -> 2.3978285e-06 | G7: ='Pretax Fuel Prices'!G7+'Fuel Taxes'!G7 -> 2.3978285e-06 | H7: ='Pretax Fuel Prices'!H7+'Fuel Taxes'!H7 -> 2.3978285e-06 | I7: ='Pretax Fuel Prices'!I7+'Fuel Taxes'!I7 -> 2.4069457e-06 | ... AI7: ='Pretax Fuel Prices'!AI7+'Fuel Taxes'!AI7 -> 0
A8: District Heating Sector | B8: ='Pretax Fuel Prices'!B8+'Fuel Taxes'!B8 -> 2.3704768e-06 | C8: ='Pretax Fuel Prices'!C8+'Fuel Taxes'!C8 -> 2.3704768e-06 | D8: ='Pretax Fuel Prices'!D8+'Fuel Taxes'!D8 -> 2.3704768e-06 | E8: ='Pretax Fuel Prices'!E8+'Fuel Taxes'!E8 -> 2.3704768e-06 | F8: ='Pretax Fuel Prices'!F8+'Fuel Taxes'!F8 -> 2.3978285e-06 | G8: ='Pretax Fuel Prices'!G8+'Fuel Taxes'!G8 -> 2.3978285e-06 | H8: ='Pretax Fuel Prices'!H8+'Fuel Taxes'!H8 -> 2.3978285e-06 | I8: ='Pretax Fuel Prices'!I8+'Fuel Taxes'!I8 -> 2.4069457e-06 | ... AI8: ='Pretax Fuel Prices'!AI8+'Fuel Taxes'!AI8 -> 0
A9: LULUCF Sector | B9: ='Pretax Fuel Prices'!B9+'Fuel Taxes'!B9 -> 0 | C9: ='Pretax Fuel Prices'!C9+'Fuel Taxes'!C9 -> 0 | D9: ='Pretax Fuel Prices'!D9+'Fuel Taxes'!D9 -> 0 | E9: ='Pretax Fuel Prices'!E9+'Fuel Taxes'!E9 -> 0 | F9: ='Pretax Fuel Prices'!F9+'Fuel Taxes'!F9 -> 0 | G9: ='Pretax Fuel Prices'!G9+'Fuel Taxes'!G9 -> 0 | H9: ='Pretax Fuel Prices'!H9+'Fuel Taxes'!H9 -> 0 | I9: ='Pretax Fuel Prices'!I9+'Fuel Taxes'!I9 -> 0 | ... AI9: ='Pretax Fuel Prices'!AI9+'Fuel Taxes'!AI9 -> 0
A10: Geoengineering Sector | B10: ='Pretax Fuel Prices'!B10+'Fuel Taxes'!B10 -> 2.3704768e-06 | C10: ='Pretax Fuel Prices'!C10+'Fuel Taxes'!C10 -> 2.3704768e-06 | D10: ='Pretax Fuel Prices'!D10+'Fuel Taxes'!D10 -> 2.3704768e-06 | E10: ='Pretax Fuel Prices'!E10+'Fuel Taxes'!E10 -> 2.3704768e-06 | F10: ='Pretax Fuel Prices'!F10+'Fuel Taxes'!F10 -> 2.3978285e-06 | G10: ='Pretax Fuel Prices'!G10+'Fuel Taxes'!G10 -> 2.3978285e-06 | H10: ='Pretax Fuel Prices'!H10+'Fuel Taxes'!H10 -> 2.3978285e-06 | I10: ='Pretax Fuel Prices'!I10+'Fuel Taxes'!I10 -> 2.4069457e-06 | ... AI10: ='Pretax Fuel Prices'!AI10+'Fuel Taxes'!AI10 -> 0
A11: Natural Gas
A12: Year | B12: 2021 | C12: 2022 | D12: 2023 | E12: 2024 | F12: 2025 | G12: 2026 | H12: 2027 | I12: 2028 | J12: 2029 | K12: 2030 | L12: 2031 | M12: 2032 | N12: 2033 | O12: 2034 | P12: 2035 | Q12: 2036 | R12: 2037 | S12: 2038 | T12: 2039 | U12: 2040 | V12: 2041 | W12: 2042 | X12: 2043 | Y12: 2044 | Z12: 2045 | AA12: 2046 | AB12: 2047 | AC12: 2048 | AD12: 2049 | AE12: 2050 | AF12: 2051 | AG12: 2052 | AH12: 2053 | AI12: 2054 | AJ12: 2055 | AK12: 2056 | AL12: 2057 | AM12: 2058 | AN12: 2059 | AO12: 2060 | AP12: 2061 | AQ12: 2062 | AR12: 2063 | AS12: 2064 | AT12: 2065 | AU12: 2066 | AV12: 2067 | AW12: 2068 | AX12: 2069 | AY12: 2070
A13: Transportation Sector | B13: ='Pretax Fuel Prices'!B13+'Fuel Taxes'!B13 -> 1.0776658e-05 | C13: ='Pretax Fuel Prices'!C13+'Fuel Taxes'!C13 -> 1.0776658e-05 | D13: ='Pretax Fuel Prices'!D13+'Fuel Taxes'!D13 -> 1.0776658e-05 | E13: ='Pretax Fuel Prices'!E13+'Fuel Taxes'!E13 -> 1.0776658e-05 | F13: ='Pretax Fuel Prices'!F13+'Fuel Taxes'!F13 -> 1.6170316e-05 | G13: ='Pretax Fuel Prices'!G13+'Fuel Taxes'!G13 -> 1.6821952e-05 | H13: ='Pretax Fuel Prices'!H13+'Fuel Taxes'!H13 -> 1.5604979e-05 | I13: ='Pretax Fuel Prices'!I13+'Fuel Taxes'!I13 -> 1.4611354e-05 | ... AI13: ='Pretax Fuel Prices'!AI13+'Fuel Taxes'!AI13 -> 0
A14: Electricity Sector | B14: ='Pretax Fuel Prices'!B14+'Fuel Taxes'!B14 -> 6.5381663e-06 | C14: ='Pretax Fuel Prices'!C14+'Fuel Taxes'!C14 -> 6.5381663e-06 | D14: ='Pretax Fuel Prices'!D14+'Fuel Taxes'!D14 -> 6.5381663e-06 | E14: ='Pretax Fuel Prices'!E14+'Fuel Taxes'!E14 -> 6.5381663e-06 | F14: ='Pretax Fuel Prices'!F14+'Fuel Taxes'!F14 -> 9.810483e-06 | G14: ='Pretax Fuel Prices'!G14+'Fuel Taxes'!G14 -> 1.0205828e-05 | H14: ='Pretax Fuel Prices'!H14+'Fuel Taxes'!H14 -> 9.4674943e-06 | I14: ='Pretax Fuel Prices'!I14+'Fuel Taxes'!I14 -> 8.864665e-06 | ... AI14: ='Pretax Fuel Prices'!AI14+'Fuel Taxes'!AI14 -> 0
A15: Residential Buildings Sector | B15: ='Pretax Fuel Prices'!B15+'Fuel Taxes'!B15 -> 1.0776658e-05 | C15: ='Pretax Fuel Prices'!C15+'Fuel Taxes'!C15 -> 1.0776658e-05 | D15: ='Pretax Fuel Prices'!D15+'Fuel Taxes'!D15 -> 1.0776658e-05 | E15: ='Pretax Fuel Prices'!E15+'Fuel Taxes'!E15 -> 1.0776658e-05 | F15: ='Pretax Fuel Prices'!F15+'Fuel Taxes'!F15 -> 1.0776658e-05 | G15: ='Pretax Fuel Prices'!G15+'Fuel Taxes'!G15 -> 1.0776658e-05 | H15: ='Pretax Fuel Prices'!H15+'Fuel Taxes'!H15 -> 1.0776658e-05 | I15: ='Pretax Fuel Prices'!I15+'Fuel Taxes'!I15 -> 1.0776658e-05 | ... AI15: ='Pretax Fuel Prices'!AI15+'Fuel Taxes'!AI15 -> 0
A16: Commercial Buildings Sector | B16: ='Pretax Fuel Prices'!B16+'Fuel Taxes'!B16 -> 1.0776658e-05 | C16: ='Pretax Fuel Prices'!C16+'Fuel Taxes'!C16 -> 1.0776658e-05 | D16: ='Pretax Fuel Prices'!D16+'Fuel Taxes'!D16 -> 1.0776658e-05 | E16: ='Pretax Fuel Prices'!E16+'Fuel Taxes'!E16 -> 1.0776658e-05 | F16: ='Pretax Fuel Prices'!F16+'Fuel Taxes'!F16 -> 1.0776658e-05 | G16: ='Pretax Fuel Prices'!G16+'Fuel Taxes'!G16 -> 1.0776658e-05 | H16: ='Pretax Fuel Prices'!H16+'Fuel Taxes'!H16 -> 1.0776658e-05 | I16: ='Pretax Fuel Prices'!I16+'Fuel Taxes'!I16 -> 1.0776658e-05 | ... AI16: ='Pretax Fuel Prices'!AI16+'Fuel Taxes'!AI16 -> 0
A17: Industry Sector | B17: ='Pretax Fuel Prices'!B17+'Fuel Taxes'!B17 -> 1.0776658e-05 | C17: ='Pretax Fuel Prices'!C17+'Fuel Taxes'!C17 -> 1.0776658e-05 | D17: ='Pretax Fuel Prices'!D17+'Fuel Taxes'!D17 -> 1.0776658e-05 | E17: ='Pretax Fuel Prices'!E17+'Fuel Taxes'!E17 -> 1.0776658e-05 | F17: ='Pretax Fuel Prices'!F17+'Fuel Taxes'!F17 -> 1.0776658e-05 | G17: ='Pretax Fuel Prices'!G17+'Fuel Taxes'!G17 -> 1.0776658e-05 | H17: ='Pretax Fuel Prices'!H17+'Fuel Taxes'!H17 -> 1.0776658e-05 | I17: ='Pretax Fuel Prices'!I17+'Fuel Taxes'!I17 -> 1.0776658e-05 | ... AI17: ='Pretax Fuel Prices'!AI17+'Fuel Taxes'!AI17 -> 0
A18: District Heating Sector | B18: ='Pretax Fuel Prices'!B18+'Fuel Taxes'!B18 -> 1.0776658e-05 | C18: ='Pretax Fuel Prices'!C18+'Fuel Taxes'!C18 -> 1.0776658e-05 | D18: ='Pretax Fuel Prices'!D18+'Fuel Taxes'!D18 -> 1.0776658e-05 | E18: ='Pretax Fuel Prices'!E18+'Fuel Taxes'!E18 -> 1.0776658e-05 | F18: ='Pretax Fuel Prices'!F18+'Fuel Taxes'!F18 -> 1.0776658e-05 | G18: ='Pretax Fuel Prices'!G18+'Fuel Taxes'!G18 -> 1.0776658e-05 | H18: ='Pretax Fuel Prices'!H18+'Fuel Taxes'!H18 -> 1.0776658e-05 | I18: ='Pretax Fuel Prices'!I18+'Fuel Taxes'!I18 -> 1.0776658e-05 | ... AI18: ='Pretax Fuel Prices'!AI18+'Fuel Taxes'!AI18 -> 0
A19: LULUCF Sector | B19: ='Pretax Fuel Prices'!B19+'Fuel Taxes'!B19 -> 1.0776658e-05 | C19: ='Pretax Fuel Prices'!C19+'Fuel Taxes'!C19 -> 1.0776658e-05 | D19: ='Pretax Fuel Prices'!D19+'Fuel Taxes'!D19 -> 1.0776658e-05 | E19: ='Pretax Fuel Prices'!E19+'Fuel Taxes'!E19 -> 1.0776658e-05 | F19: ='Pretax Fuel Prices'!F19+'Fuel Taxes'!F19 -> 1.0776658e-05 | G19: ='Pretax Fuel Prices'!G19+'Fuel Taxes'!G19 -> 1.0776658e-05 | H19: ='Pretax Fuel Prices'!H19+'Fuel Taxes'!H19 -> 1.0776658e-05 | I19: ='Pretax Fuel Prices'!I19+'Fuel Taxes'!I19 -> 1.0776658e-05 | ... AI19: ='Pretax Fuel Prices'!AI19+'Fuel Taxes'!AI19 -> 0
A20: Geoengineering Sector | B20: ='Pretax Fuel Prices'!B20+'Fuel Taxes'!B20 -> 1.0776658e-05 | C20: ='Pretax Fuel Prices'!C20+'Fuel Taxes'!C20 -> 1.0776658e-05 | D20: ='Pretax Fuel Prices'!D20+'Fuel Taxes'!D20 -> 1.0776658e-05 | E20: ='Pretax Fuel Prices'!E20+'Fuel Taxes'!E20 -> 1.0776658e-05 | F20: ='Pretax Fuel Prices'!F20+'Fuel Taxes'!F20 -> 1.0776658e-05 | G20: ='Pretax Fuel Prices'!G20+'Fuel Taxes'!G20 -> 1.0776658e-05 | H20: ='Pretax Fuel Prices'!H20+'Fuel Taxes'!H20 -> 1.0776658e-05 | I20: ='Pretax Fuel Prices'!I20+'Fuel Taxes'!I20 -> 1.0776658e-05 | ... AI20: ='Pretax Fuel Prices'!AI20+'Fuel Taxes'!AI20 -> 0
A21: Nuclear
A22: Year | B22: 2021 | C22: 2022 | D22: 2023 | E22: 2024 | F22: 2025 | G22: 2026 | H22: 2027 | I22: 2028 | J22: 2029 | K22: 2030 | L22: 2031 | M22: 2032 | N22: 2033 | O22: 2034 | P22: 2035 | Q22: 2036 | R22: 2037 | S22: 2038 | T22: 2039 | U22: 2040 | V22: 2041 | W22: 2042 | X22: 2043 | Y22: 2044 | Z22: 2045 | AA22: 2046 | AB22: 2047 | AC22: 2048 | AD22: 2049 | AE22: 2050 | AF22: 2051 | AG22: 2052 | AH22: 2053 | AI22: 2054 | AJ22: 2055 | AK22: 2056 | AL22: 2057 | AM22: 2058 | AN22: 2059 | AO22: 2060 | AP22: 2061 | AQ22: 2062 | AR22: 2063 | AS22: 2064 | AT22: 2065 | AU22: 2066 | AV22: 2067 | AW22: 2068 | AX22: 2069 | AY22: 2070
A23: Transportation Sector | B23: ='Pretax Fuel Prices'!B23+'Fuel Taxes'!B23 -> 0 | C23: ='Pretax Fuel Prices'!C23+'Fuel Taxes'!C23 -> 0 | D23: ='Pretax Fuel Prices'!D23+'Fuel Taxes'!D23 -> 0 | E23: ='Pretax Fuel Prices'!E23+'Fuel Taxes'!E23 -> 0 | F23: ='Pretax Fuel Prices'!F23+'Fuel Taxes'!F23 -> 0 | G23: ='Pretax Fuel Prices'!G23+'Fuel Taxes'!G23 -> 0 | H23: ='Pretax Fuel Prices'!H23+'Fuel Taxes'!H23 -> 0 | I23: ='Pretax Fuel Prices'!I23+'Fuel Taxes'!I23 -> 0 | ... AI23: ='Pretax Fuel Prices'!AI23+'Fuel Taxes'!AI23 -> 0
A24: Electricity Sector | B24: ='Pretax Fuel Prices'!B24+'Fuel Taxes'!B24 -> 7.4e-07 | C24: ='Pretax Fuel Prices'!C24+'Fuel Taxes'!C24 -> 7.4e-07 | D24: ='Pretax Fuel Prices'!D24+'Fuel Taxes'!D24 -> 7.4e-07 | E24: ='Pretax Fuel Prices'!E24+'Fuel Taxes'!E24 -> 7.4e-07 | F24: ='Pretax Fuel Prices'!F24+'Fuel Taxes'!F24 -> 7.4e-07 | G24: ='Pretax Fuel Prices'!G24+'Fuel Taxes'!G24 -> 7.4e-07 | H24: ='Pretax Fuel Prices'!H24+'Fuel Taxes'!H24 -> 7.4e-07 | I24: ='Pretax Fuel Prices'!I24+'Fuel Taxes'!I24 -> 7.4e-07 | ... AI24: ='Pretax Fuel Prices'!AI24+'Fuel Taxes'!AI24 -> 0
A25: Residential Buildings Sector | B25: ='Pretax Fuel Prices'!B25+'Fuel Taxes'!B25 -> 0 | C25: ='Pretax Fuel Prices'!C25+'Fuel Taxes'!C25 -> 0 | D25: ='Pretax Fuel Prices'!D25+'Fuel Taxes'!D25 -> 0 | E25: ='Pretax Fuel Prices'!E25+'Fuel Taxes'!E25 -> 0 | F25: ='Pretax Fuel Prices'!F25+'Fuel Taxes'!F25 -> 0 | G25: ='Pretax Fuel Prices'!G25+'Fuel Taxes'!G25 -> 0 | H25: ='Pretax Fuel Prices'!H25+'Fuel Taxes'!H25 -> 0 | I25: ='Pretax Fuel Prices'!I25+'Fuel Taxes'!I25 -> 0 | ... AI25: ='Pretax Fuel Prices'!AI25+'Fuel Taxes'!AI25 -> 0
A26: Commercial Buildings Sector | B26: ='Pretax Fuel Prices'!B26+'Fuel Taxes'!B26 -> 0 | C26: ='Pretax Fuel Prices'!C26+'Fuel Taxes'!C26 -> 0 | D26: ='Pretax Fuel Prices'!D26+'Fuel Taxes'!D26 -> 0 | E26: ='Pretax Fuel Prices'!E26+'Fuel Taxes'!E26 -> 0 | F26: ='Pretax Fuel Prices'!F26+'Fuel Taxes'!F26 -> 0 | G26: ='Pretax Fuel Prices'!G26+'Fuel Taxes'!G26 -> 0 | H26: ='Pretax Fuel Prices'!H26+'Fuel Taxes'!H26 -> 0 | I26: ='Pretax Fuel Prices'!I26+'Fuel Taxes'!I26 -> 0 | ... AI26: ='Pretax Fuel Prices'!AI26+'Fuel Taxes'!AI26 -> 0
A27: Industry Sector | B27: ='Pretax Fuel Prices'!B27+'Fuel Taxes'!B27 -> 0 | C27: ='Pretax Fuel Prices'!C27+'Fuel Taxes'!C27 -> 0 | D27: ='Pretax Fuel Prices'!D27+'Fuel Taxes'!D27 -> 0 | E27: ='Pretax Fuel Prices'!E27+'Fuel Taxes'!E27 -> 0 | F27: ='Pretax Fuel Prices'!F27+'Fuel Taxes'!F27 -> 0 | G27: ='Pretax Fuel Prices'!G27+'Fuel Taxes'!G27 -> 0 | H27: ='Pretax Fuel Prices'!H27+'Fuel Taxes'!H27 -> 0 | I27: ='Pretax Fuel Prices'!I27+'Fuel Taxes'!I27 -> 0 | ... AI27: ='Pretax Fuel Prices'!AI27+'Fuel Taxes'!AI27 -> 0
A28: District Heating Sector | B28: ='Pretax Fuel Prices'!B28+'Fuel Taxes'!B28 -> 0 | C28: ='Pretax Fuel Prices'!C28+'Fuel Taxes'!C28 -> 0 | D28: ='Pretax Fuel Prices'!D28+'Fuel Taxes'!D28 -> 0 | E28: ='Pretax Fuel Prices'!E28+'Fuel Taxes'!E28 -> 0 | F28: ='Pretax Fuel Prices'!F28+'Fuel Taxes'!F28 -> 0 | G28: ='Pretax Fuel Prices'!G28+'Fuel Taxes'!G28 -> 0 | H28: ='Pretax Fuel Prices'!H28+'Fuel Taxes'!H28 -> 0 | I28: ='Pretax Fuel Prices'!I28+'Fuel Taxes'!I28 -> 0 | ... AI28: ='Pretax Fuel Prices'!AI28+'Fuel Taxes'!AI28 -> 0
A29: LULUCF Sector | B29: ='Pretax Fuel Prices'!B29+'Fuel Taxes'!B29 -> 0 | C29: ='Pretax Fuel Prices'!C29+'Fuel Taxes'!C29 -> 0 | D29: ='Pretax Fuel Prices'!D29+'Fuel Taxes'!D29 -> 0 | E29: ='Pretax Fuel Prices'!E29+'Fuel Taxes'!E29 -> 0 | F29: ='Pretax Fuel Prices'!F29+'Fuel Taxes'!F29 -> 0 | G29: ='Pretax Fuel Prices'!G29+'Fuel Taxes'!G29 -> 0 | H29: ='Pretax Fuel Prices'!H29+'Fuel Taxes'!H29 -> 0 | I29: ='Pretax Fuel Prices'!I29+'Fuel Taxes'!I29 -> 0 | ... AI29: ='Pretax Fuel Prices'!AI29+'Fuel Taxes'!AI29 -> 0
A30: Geoengineering Sector | B30: ='Pretax Fuel Prices'!B30+'Fuel Taxes'!B30 -> 0 | C30: ='Pretax Fuel Prices'!C30+'Fuel Taxes'!C30 -> 0 | D30: ='Pretax Fuel Prices'!D30+'Fuel Taxes'!D30 -> 0 | E30: ='Pretax Fuel Prices'!E30+'Fuel Taxes'!E30 -> 0 | F30: ='Pretax Fuel Prices'!F30+'Fuel Taxes'!F30 -> 0 | G30: ='Pretax Fuel Prices'!G30+'Fuel Taxes'!G30 -> 0 | H30: ='Pretax Fuel Prices'!H30+'Fuel Taxes'!H30 -> 0 | I30: ='Pretax Fuel Prices'!I30+'Fuel Taxes'!I30 -> 0 | ... AI30: ='Pretax Fuel Prices'!AI30+'Fuel Taxes'!AI30 -> 0
A31: Biomass
A32: Year | B32: 2021 | C32: 2022 | D32: 2023 | E32: 2024 | F32: 2025 | G32: 2026 | H32: 2027 | I32: 2028 | J32: 2029 | K32: 2030 | L32: 2031 | M32: 2032 | N32: 2033 | O32: 2034 | P32: 2035 | Q32: 2036 | R32: 2037 | S32: 2038 | T32: 2039 | U32: 2040 | V32: 2041 | W32: 2042 | X32: 2043 | Y32: 2044 | Z32: 2045 | AA32: 2046 | AB32: 2047 | AC32: 2048 | AD32: 2049 | AE32: 2050 | AF32: 2051 | AG32: 2052 | AH32: 2053 | AI32: 2054 | AJ32: 2055 | AK32: 2056 | AL32: 2057 | AM32: 2058 | AN32: 2059 | AO32: 2060 | AP32: 2061 | AQ32: 2062 | AR32: 2063 | AS32: 2064 | AT32: 2065 | AU32: 2066 | AV32: 2067 | AW32: 2068 | AX32: 2069 | AY32: 2070
A33: Transportation Sector | B33: ='Pretax Fuel Prices'!B33+'Fuel Taxes'!B33 -> 0 | C33: ='Pretax Fuel Prices'!C33+'Fuel Taxes'!C33 -> 0 | D33: ='Pretax Fuel Prices'!D33+'Fuel Taxes'!D33 -> 0 | E33: ='Pretax Fuel Prices'!E33+'Fuel Taxes'!E33 -> 0 | F33: ='Pretax Fuel Prices'!F33+'Fuel Taxes'!F33 -> 0 | G33: ='Pretax Fuel Prices'!G33+'Fuel Taxes'!G33 -> 0 | H33: ='Pretax Fuel Prices'!H33+'Fuel Taxes'!H33 -> 0 | I33: ='Pretax Fuel Prices'!I33+'Fuel Taxes'!I33 -> 0 | ... AI33: ='Pretax Fuel Prices'!AI33+'Fuel Taxes'!AI33 -> 0
A34: Electricity Sector | B34: ='Pretax Fuel Prices'!B34+'Fuel Taxes'!B34 -> 2.3976694e-06 | C34: ='Pretax Fuel Prices'!C34+'Fuel Taxes'!C34 -> 2.3976694e-06 | D34: ='Pretax Fuel Prices'!D34+'Fuel Taxes'!D34 -> 2.3976694e-06 | E34: ='Pretax Fuel Prices'!E34+'Fuel Taxes'!E34 -> 2.3976694e-06 | F34: ='Pretax Fuel Prices'!F34+'Fuel Taxes'!F34 -> 2.3976694e-06 | G34: ='Pretax Fuel Prices'!G34+'Fuel Taxes'!G34 -> 2.3976694e-06 | H34: ='Pretax Fuel Prices'!H34+'Fuel Taxes'!H34 -> 2.3976694e-06 | I34: ='Pretax Fuel Prices'!I34+'Fuel Taxes'!I34 -> 2.3976694e-06 | ... AI34: ='Pretax Fuel Prices'!AI34+'Fuel Taxes'!AI34 -> 0
A35: Residential Buildings Sector | B35: ='Pretax Fuel Prices'!B35+'Fuel Taxes'!B35 -> 2.3976694e-06 | C35: ='Pretax Fuel Prices'!C35+'Fuel Taxes'!C35 -> 2.3976694e-06 | D35: ='Pretax Fuel Prices'!D35+'Fuel Taxes'!D35 -> 2.3976694e-06 | E35: ='Pretax Fuel Prices'!E35+'Fuel Taxes'!E35 -> 2.3976694e-06 | F35: ='Pretax Fuel Prices'!F35+'Fuel Taxes'!F35 -> 2.3976694e-06 | G35: ='Pretax Fuel Prices'!G35+'Fuel Taxes'!G35 -> 2.3976694e-06 | H35: ='Pretax Fuel Prices'!H35+'Fuel Taxes'!H35 -> 2.3976694e-06 | I35: ='Pretax Fuel Prices'!I35+'Fuel Taxes'!I35 -> 2.3976694e-06 | ... AI35: ='Pretax Fuel Prices'!AI35+'Fuel Taxes'!AI35 -> 0
A36: Commercial Buildings Sector | B36: ='Pretax Fuel Prices'!B36+'Fuel Taxes'!B36 -> 2.3976694e-06 | C36: ='Pretax Fuel Prices'!C36+'Fuel Taxes'!C36 -> 2.3976694e-06 | D36: ='Pretax Fuel Prices'!D36+'Fuel Taxes'!D36 -> 2.3976694e-06 | E36: ='Pretax Fuel Prices'!E36+'Fuel Taxes'!E36 -> 2.3976694e-06 | F36: ='Pretax Fuel Prices'!F36+'Fuel Taxes'!F36 -> 2.3976694e-06 | G36: ='Pretax Fuel Prices'!G36+'Fuel Taxes'!G36 -> 2.3976694e-06 | H36: ='Pretax Fuel Prices'!H36+'Fuel Taxes'!H36 -> 2.3976694e-06 | I36: ='Pretax Fuel Prices'!I36+'Fuel Taxes'!I36 -> 2.3976694e-06 | ... AI36: ='Pretax Fuel Prices'!AI36+'Fuel Taxes'!AI36 -> 0
A37: Industry Sector | B37: ='Pretax Fuel Prices'!B37+'Fuel Taxes'!B37 -> 2.3976694e-06 | C37: ='Pretax Fuel Prices'!C37+'Fuel Taxes'!C37 -> 2.3976694e-06 | D37: ='Pretax Fuel Prices'!D37+'Fuel Taxes'!D37 -> 2.3976694e-06 | E37: ='Pretax Fuel Prices'!E37+'Fuel Taxes'!E37 -> 2.3976694e-06 | F37: ='Pretax Fuel Prices'!F37+'Fuel Taxes'!F37 -> 2.3976694e-06 | G37: ='Pretax Fuel Prices'!G37+'Fuel Taxes'!G37 -> 2.3976694e-06 | H37: ='Pretax Fuel Prices'!H37+'Fuel Taxes'!H37 -> 2.3976694e-06 | I37: ='Pretax Fuel Prices'!I37+'Fuel Taxes'!I37 -> 2.3976694e-06 | ... AI37: ='Pretax Fuel Prices'!AI37+'Fuel Taxes'!AI37 -> 0
A38: District Heating Sector | B38: ='Pretax Fuel Prices'!B38+'Fuel Taxes'!B38 -> 2.3976694e-06 | C38: ='Pretax Fuel Prices'!C38+'Fuel Taxes'!C38 -> 2.3976694e-06 | D38: ='Pretax Fuel Prices'!D38+'Fuel Taxes'!D38 -> 2.3976694e-06 | E38: ='Pretax Fuel Prices'!E38+'Fuel Taxes'!E38 -> 2.3976694e-06 | F38: ='Pretax Fuel Prices'!F38+'Fuel Taxes'!F38 -> 2.3976694e-06 | G38: ='Pretax Fuel Prices'!G38+'Fuel Taxes'!G38 -> 2.3976694e-06 | H38: ='Pretax Fuel Prices'!H38+'Fuel Taxes'!H38 -> 2.3976694e-06 | I38: ='Pretax Fuel Prices'!I38+'Fuel Taxes'!I38 -> 2.3976694e-06 | ... AI38: ='Pretax Fuel Prices'!AI38+'Fuel Taxes'!AI38 -> 0
A39: LULUCF Sector | B39: ='Pretax Fuel Prices'!B39+'Fuel Taxes'!B39 -> 0 | C39: ='Pretax Fuel Prices'!C39+'Fuel Taxes'!C39 -> 0 | D39: ='Pretax Fuel Prices'!D39+'Fuel Taxes'!D39 -> 0 | E39: ='Pretax Fuel Prices'!E39+'Fuel Taxes'!E39 -> 0 | F39: ='Pretax Fuel Prices'!F39+'Fuel Taxes'!F39 -> 0 | G39: ='Pretax Fuel Prices'!G39+'Fuel Taxes'!G39 -> 0 | H39: ='Pretax Fuel Prices'!H39+'Fuel Taxes'!H39 -> 0 | I39: ='Pretax Fuel Prices'!I39+'Fuel Taxes'!I39 -> 0 | ... AI39: ='Pretax Fuel Prices'!AI39+'Fuel Taxes'!AI39 -> 0
A40: Geoengineering Sector | B40: ='Pretax Fuel Prices'!B40+'Fuel Taxes'!B40 -> 2.3976694e-06 | C40: ='Pretax Fuel Prices'!C40+'Fuel Taxes'!C40 -> 2.3976694e-06 | D40: ='Pretax Fuel Prices'!D40+'Fuel Taxes'!D40 -> 2.3976694e-06 | E40: ='Pretax Fuel Prices'!E40+'Fuel Taxes'!E40 -> 2.3976694e-06 | F40: ='Pretax Fuel Prices'!F40+'Fuel Taxes'!F40 -> 2.3976694e-06 | G40: ='Pretax Fuel Prices'!G40+'Fuel Taxes'!G40 -> 2.3976694e-06 | H40: ='Pretax Fuel Prices'!H40+'Fuel Taxes'!H40 -> 2.3976694e-06 | I40: ='Pretax Fuel Prices'!I40+'Fuel Taxes'!I40 -> 2.3976694e-06 | ... AI40: ='Pretax Fuel Prices'!AI40+'Fuel Taxes'!AI40 -> 0
A41: Petroleum Gasoline
A42: Year | B42: 2021 | C42: 2022 | D42: 2023 | E42: 2024 | F42: 2025 | G42: 2026 | H42: 2027 | I42: 2028 | J42: 2029 | K42: 2030 | L42: 2031 | M42: 2032 | N42: 2033 | O42: 2034 | P42: 2035 | Q42: 2036 | R42: 2037 | S42: 2038 | T42: 2039 | U42: 2040 | V42: 2041 | W42: 2042 | X42: 2043 | Y42: 2044 | Z42: 2045 | AA42: 2046 | AB42: 2047 | AC42: 2048 | AD42: 2049 | AE42: 2050 | AF42: 2051 | AG42: 2052 | AH42: 2053 | AI42: 2054 | AJ42: 2055 | AK42: 2056 | AL42: 2057 | AM42: 2058 | AN42: 2059 | AO42: 2060 | AP42: 2061 | AQ42: 2062 | AR42: 2063 | AS42: 2064 | AT42: 2065 | AU42: 2066 | AV42: 2067 | AW42: 2068 | AX42: 2069 | AY42: 2070
A43: Transportation Sector | B43: ='Pretax Fuel Prices'!B43+'Fuel Taxes'!B43 -> 2.497881e-05 | C43: ='Pretax Fuel Prices'!C43+'Fuel Taxes'!C43 -> 2.497881e-05 | D43: ='Pretax Fuel Prices'!D43+'Fuel Taxes'!D43 -> 2.5229167e-05 | E43: ='Pretax Fuel Prices'!E43+'Fuel Taxes'!E43 -> 2.497881e-05 | F43: ='Pretax Fuel Prices'!F43+'Fuel Taxes'!F43 -> 2.501295e-05 | G43: ='Pretax Fuel Prices'!G43+'Fuel Taxes'!G43 -> 2.501295e-05 | H43: ='Pretax Fuel Prices'!H43+'Fuel Taxes'!H43 -> 2.4910531e-05 | I43: ='Pretax Fuel Prices'!I43+'Fuel Taxes'!I43 -> 2.4580515e-05 | ... AI43: ='Pretax Fuel Prices'!AI43+'Fuel Taxes'!AI43 -> 0
A44: Electricity Sector | B44: ='Pretax Fuel Prices'!B44+'Fuel Taxes'!B44 -> 0 | C44: ='Pretax Fuel Prices'!C44+'Fuel Taxes'!C44 -> 0 | D44: ='Pretax Fuel Prices'!D44+'Fuel Taxes'!D44 -> 0 | E44: ='Pretax Fuel Prices'!E44+'Fuel Taxes'!E44 -> 0 | F44: ='Pretax Fuel Prices'!F44+'Fuel Taxes'!F44 -> 0 | G44: ='Pretax Fuel Prices'!G44+'Fuel Taxes'!G44 -> 0 | H44: ='Pretax Fuel Prices'!H44+'Fuel Taxes'!H44 -> 0 | I44: ='Pretax Fuel Prices'!I44+'Fuel Taxes'!I44 -> 0 | ... AI44: ='Pretax Fuel Prices'!AI44+'Fuel Taxes'!AI44 -> 0
A45: Residential Buildings Sector | B45: ='Pretax Fuel Prices'!B45+'Fuel Taxes'!B45 -> 0 | C45: ='Pretax Fuel Prices'!C45+'Fuel Taxes'!C45 -> 0 | D45: ='Pretax Fuel Prices'!D45+'Fuel Taxes'!D45 -> 0 | E45: ='Pretax Fuel Prices'!E45+'Fuel Taxes'!E45 -> 0 | F45: ='Pretax Fuel Prices'!F45+'Fuel Taxes'!F45 -> 0 | G45: ='Pretax Fuel Prices'!G45+'Fuel Taxes'!G45 -> 0 | H45: ='Pretax Fuel Prices'!H45+'Fuel Taxes'!H45 -> 0 | I45: ='Pretax Fuel Prices'!I45+'Fuel Taxes'!I45 -> 0 | ... AI45: ='Pretax Fuel Prices'!AI45+'Fuel Taxes'!AI45 -> 0
A46: Commercial Buildings Sector | B46: ='Pretax Fuel Prices'!B46+'Fuel Taxes'!B46 -> 0 | C46: ='Pretax Fuel Prices'!C46+'Fuel Taxes'!C46 -> 0 | D46: ='Pretax Fuel Prices'!D46+'Fuel Taxes'!D46 -> 0 | E46: ='Pretax Fuel Prices'!E46+'Fuel Taxes'!E46 -> 0 | F46: ='Pretax Fuel Prices'!F46+'Fuel Taxes'!F46 -> 0 | G46: ='Pretax Fuel Prices'!G46+'Fuel Taxes'!G46 -> 0 | H46: ='Pretax Fuel Prices'!H46+'Fuel Taxes'!H46 -> 0 | I46: ='Pretax Fuel Prices'!I46+'Fuel Taxes'!I46 -> 0 | ... AI46: ='Pretax Fuel Prices'!AI46+'Fuel Taxes'!AI46 -> 0
A47: Industry Sector | B47: ='Pretax Fuel Prices'!B47+'Fuel Taxes'!B47 -> 0 | C47: ='Pretax Fuel Prices'!C47+'Fuel Taxes'!C47 -> 0 | D47: ='Pretax Fuel Prices'!D47+'Fuel Taxes'!D47 -> 0 | E47: ='Pretax Fuel Prices'!E47+'Fuel Taxes'!E47 -> 0 | F47: ='Pretax Fuel Prices'!F47+'Fuel Taxes'!F47 -> 0 | G47: ='Pretax Fuel Prices'!G47+'Fuel Taxes'!G47 -> 0 | H47: ='Pretax Fuel Prices'!H47+'Fuel Taxes'!H47 -> 0 | I47: ='Pretax Fuel Prices'!I47+'Fuel Taxes'!I47 -> 0 | ... AI47: ='Pretax Fuel Prices'!AI47+'Fuel Taxes'!AI47 -> 0
A48: District Heating Sector | B48: ='Pretax Fuel Prices'!B48+'Fuel Taxes'!B48 -> 0 | C48: ='Pretax Fuel Prices'!C48+'Fuel Taxes'!C48 -> 0 | D48: ='Pretax Fuel Prices'!D48+'Fuel Taxes'!D48 -> 0 | E48: ='Pretax Fuel Prices'!E48+'Fuel Taxes'!E48 -> 0 | F48: ='Pretax Fuel Prices'!F48+'Fuel Taxes'!F48 -> 0 | G48: ='Pretax Fuel Prices'!G48+'Fuel Taxes'!G48 -> 0 | H48: ='Pretax Fuel Prices'!H48+'Fuel Taxes'!H48 -> 0 | I48: ='Pretax Fuel Prices'!I48+'Fuel Taxes'!I48 -> 0 | ... AI48: ='Pretax Fuel Prices'!AI48+'Fuel Taxes'!AI48 -> 0
A49: LULUCF Sector | B49: ='Pretax Fuel Prices'!B49+'Fuel Taxes'!B49 -> 0 | C49: ='Pretax Fuel Prices'!C49+'Fuel Taxes'!C49 -> 0 | D49: ='Pretax Fuel Prices'!D49+'Fuel Taxes'!D49 -> 0 | E49: ='Pretax Fuel Prices'!E49+'Fuel Taxes'!E49 -> 0 | F49: ='Pretax Fuel Prices'!F49+'Fuel Taxes'!F49 -> 0 | G49: ='Pretax Fuel Prices'!G49+'Fuel Taxes'!G49 -> 0 | H49: ='Pretax Fuel Prices'!H49+'Fuel Taxes'!H49 -> 0 | I49: ='Pretax Fuel Prices'!I49+'Fuel Taxes'!I49 -> 0 | ... AI49: ='Pretax Fuel Prices'!AI49+'Fuel Taxes'!AI49 -> 0
A50: Geoengineering Sector | B50: ='Pretax Fuel Prices'!B50+'Fuel Taxes'!B50 -> 0 | C50: ='Pretax Fuel Prices'!C50+'Fuel Taxes'!C50 -> 0 | D50: ='Pretax Fuel Prices'!D50+'Fuel Taxes'!D50 -> 0 | E50: ='Pretax Fuel Prices'!E50+'Fuel Taxes'!E50 -> 0 | F50: ='Pretax Fuel Prices'!F50+'Fuel Taxes'!F50 -> 0 | G50: ='Pretax Fuel Prices'!G50+'Fuel Taxes'!G50 -> 0 | H50: ='Pretax Fuel Prices'!H50+'Fuel Taxes'!H50 -> 0 | I50: ='Pretax Fuel Prices'!I50+'Fuel Taxes'!I50 -> 0 | ... AI50: ='Pretax Fuel Prices'!AI50+'Fuel Taxes'!AI50 -> 0
A51: Petroleum Diesel
A52: Year | B52: 2021 | C52: 2022 | D52: 2023 | E52: 2024 | F52: 2025 | G52: 2026 | H52: 2027 | I52: 2028 | J52: 2029 | K52: 2030 | L52: 2031 | M52: 2032 | N52: 2033 | O52: 2034 | P52: 2035 | Q52: 2036 | R52: 2037 | S52: 2038 | T52: 2039 | U52: 2040 | V52: 2041 | W52: 2042 | X52: 2043 | Y52: 2044 | Z52: 2045 | AA52: 2046 | AB52: 2047 | AC52: 2048 | AD52: 2049 | AE52: 2050 | AF52: 2051 | AG52: 2052 | AH52: 2053 | AI52: 2054 | AJ52: 2055 | AK52: 2056 | AL52: 2057 | AM52: 2058 | AN52: 2059 | AO52: 2060 | AP52: 2061 | AQ52: 2062 | AR52: 2063 | AS52: 2064 | AT52: 2065 | AU52: 2066 | AV52: 2067 | AW52: 2068 | AX52: 2069 | AY52: 2070
A53: Transportation Sector | B53: ='Pretax Fuel Prices'!B53+'Fuel Taxes'!B53 -> 1.9404341e-05 | C53: ='Pretax Fuel Prices'!B53+'Fuel Taxes'!C53 -> 1.9404341e-05 | D53: ='Pretax Fuel Prices'!C53+'Fuel Taxes'!D53 -> 1.9703485e-05 | E53: ='Pretax Fuel Prices'!D53+'Fuel Taxes'!E53 -> 1.9805354e-05 | F53: ='Pretax Fuel Prices'!E53+'Fuel Taxes'!F53 -> 1.9450961e-05 | G53: ='Pretax Fuel Prices'!F53+'Fuel Taxes'!G53 -> 1.9641661e-05 | H53: ='Pretax Fuel Prices'!G53+'Fuel Taxes'!H53 -> 1.9864029e-05 | I53: ='Pretax Fuel Prices'!H53+'Fuel Taxes'!I53 -> 2.0083247e-05 | J53: ='Pretax Fuel Prices'!I53+'Fuel Taxes'!J53 -> 2.0340747e-05 | ... AI53: ='Pretax Fuel Prices'!AH53+'Fuel Taxes'!AI53 -> 0
A54: Electricity Sector | B54: ='Pretax Fuel Prices'!B54+'Fuel Taxes'!B54 -> 1.9404341e-05 | C54: ='Pretax Fuel Prices'!B54+'Fuel Taxes'!C54 -> 1.9404341e-05 | D54: ='Pretax Fuel Prices'!C54+'Fuel Taxes'!D54 -> 1.9633878e-05 | E54: ='Pretax Fuel Prices'!D54+'Fuel Taxes'!E54 -> 1.9712043e-05 | F54: ='Pretax Fuel Prices'!E54+'Fuel Taxes'!F54 -> 1.9116448e-05 | G54: ='Pretax Fuel Prices'!F54+'Fuel Taxes'!G54 -> 1.850876e-05 | H54: ='Pretax Fuel Prices'!G54+'Fuel Taxes'!H54 -> 1.7950828e-05 | I54: ='Pretax Fuel Prices'!H54+'Fuel Taxes'!I54 -> 1.7441895e-05 | J54: ='Pretax Fuel Prices'!I54+'Fuel Taxes'!J54 -> 1.6971298e-05 | ... AI54: ='Pretax Fuel Prices'!AH54+'Fuel Taxes'!AI54 -> 0
A55: Residential Buildings Sector | B55: ='Pretax Fuel Prices'!B55+'Fuel Taxes'!B55 -> 1.3092837e-05 | C55: ='Pretax Fuel Prices'!B55+'Fuel Taxes'!C55 -> 1.3092837e-05 | D55: ='Pretax Fuel Prices'!C55+'Fuel Taxes'!D55 -> 1.3247787e-05 | E55: ='Pretax Fuel Prices'!D55+'Fuel Taxes'!E55 -> 1.3300553e-05 | F55: ='Pretax Fuel Prices'!E55+'Fuel Taxes'!F55 -> 1.3179504e-05 | G55: ='Pretax Fuel Prices'!F55+'Fuel Taxes'!G55 -> 1.3448007e-05 | H55: ='Pretax Fuel Prices'!G55+'Fuel Taxes'!H55 -> 1.3757253e-05 | I55: ='Pretax Fuel Prices'!H55+'Fuel Taxes'!I55 -> 1.4071411e-05 | J55: ='Pretax Fuel Prices'!I55+'Fuel Taxes'!J55 -> 1.4419327e-05 | ... AI55: ='Pretax Fuel Prices'!AH55+'Fuel Taxes'!AI55 -> 0
A56: Commercial Buildings Sector | B56: ='Pretax Fuel Prices'!B56+'Fuel Taxes'!B56 -> 1.9404341e-05 | C56: ='Pretax Fuel Prices'!B56+'Fuel Taxes'!C56 -> 1.9404341e-05 | D56: ='Pretax Fuel Prices'!C56+'Fuel Taxes'!D56 -> 1.9633127e-05 | E56: ='Pretax Fuel Prices'!D56+'Fuel Taxes'!E56 -> 1.9711036e-05 | F56: ='Pretax Fuel Prices'!E56+'Fuel Taxes'!F56 -> 1.915229e-05 | G56: ='Pretax Fuel Prices'!F56+'Fuel Taxes'!G56 -> 1.8655419e-05 | H56: ='Pretax Fuel Prices'!G56+'Fuel Taxes'!H56 -> 1.8217385e-05 | I56: ='Pretax Fuel Prices'!H56+'Fuel Taxes'!I56 -> 1.7787924e-05 | J56: ='Pretax Fuel Prices'!I56+'Fuel Taxes'!J56 -> 1.7395353e-05 | ... AI56: ='Pretax Fuel Prices'!AH56+'Fuel Taxes'!AI56 -> 0
A57: Industry Sector | B57: ='Pretax Fuel Prices'!B57+'Fuel Taxes'!B57 -> 1.9404341e-05 | C57: ='Pretax Fuel Prices'!B57+'Fuel Taxes'!C57 -> 1.9404341e-05 | D57: ='Pretax Fuel Prices'!C57+'Fuel Taxes'!D57 -> 1.9633986e-05 | E57: ='Pretax Fuel Prices'!D57+'Fuel Taxes'!E57 -> 1.9712188e-05 | F57: ='Pretax Fuel Prices'!E57+'Fuel Taxes'!F57 -> 1.916302e-05 | G57: ='Pretax Fuel Prices'!F57+'Fuel Taxes'!G57 -> 1.8687721e-05 | H57: ='Pretax Fuel Prices'!G57+'Fuel Taxes'!H57 -> 1.8262369e-05 | I57: ='Pretax Fuel Prices'!H57+'Fuel Taxes'!I57 -> 1.784819e-05 | J57: ='Pretax Fuel Prices'!I57+'Fuel Taxes'!J57 -> 1.7469798e-05 | ... AI57: ='Pretax Fuel Prices'!AH57+'Fuel Taxes'!AI57 -> 0
A58: District Heating Sector | B58: ='Pretax Fuel Prices'!B58+'Fuel Taxes'!B58 -> 1.9404341e-05 | C58: ='Pretax Fuel Prices'!B58+'Fuel Taxes'!C58 -> 1.9404341e-05 | D58: ='Pretax Fuel Prices'!C58+'Fuel Taxes'!D58 -> 1.9633986e-05 | E58: ='Pretax Fuel Prices'!D58+'Fuel Taxes'!E58 -> 1.9712188e-05 | F58: ='Pretax Fuel Prices'!E58+'Fuel Taxes'!F58 -> 1.916302e-05 | G58: ='Pretax Fuel Prices'!F58+'Fuel Taxes'!G58 -> 1.8687721e-05 | H58: ='Pretax Fuel Prices'!G58+'Fuel Taxes'!H58 -> 1.8262369e-05 | I58: ='Pretax Fuel Prices'!H58+'Fuel Taxes'!I58 -> 1.784819e-05 | J58: ='Pretax Fuel Prices'!I58+'Fuel Taxes'!J58 -> 1.7469798e-05 | ... AI58: ='Pretax Fuel Prices'!AH58+'Fuel Taxes'!AI58 -> 0
A59: LULUCF Sector | B59: ='Pretax Fuel Prices'!B59+'Fuel Taxes'!B59 -> 0 | C59: ='Pretax Fuel Prices'!B59+'Fuel Taxes'!C59 -> 0 | D59: ='Pretax Fuel Prices'!C59+'Fuel Taxes'!D59 -> 0 | E59: ='Pretax Fuel Prices'!D59+'Fuel Taxes'!E59 -> 0 | F59: ='Pretax Fuel Prices'!E59+'Fuel Taxes'!F59 -> 0 | G59: ='Pretax Fuel Prices'!F59+'Fuel Taxes'!G59 -> 0 | H59: ='Pretax Fuel Prices'!G59+'Fuel Taxes'!H59 -> 0 | I59: ='Pretax Fuel Prices'!H59+'Fuel Taxes'!I59 -> 0 | J59: ='Pretax Fuel Prices'!I59+'Fuel Taxes'!J59 -> 0 | ... AI59: ='Pretax Fuel Prices'!AH59+'Fuel Taxes'!AI59 -> 0
A60: Geoengineering Sector | B60: ='Pretax Fuel Prices'!B60+'Fuel Taxes'!B60 -> 1.9404341e-05 | C60: ='Pretax Fuel Prices'!B60+'Fuel Taxes'!C60 -> 1.9404341e-05 | D60: ='Pretax Fuel Prices'!C60+'Fuel Taxes'!D60 -> 1.9633986e-05 | E60: ='Pretax Fuel Prices'!D60+'Fuel Taxes'!E60 -> 1.9712188e-05 | F60: ='Pretax Fuel Prices'!E60+'Fuel Taxes'!F60 -> 1.916302e-05 | G60: ='Pretax Fuel Prices'!F60+'Fuel Taxes'!G60 -> 1.8687721e-05 | H60: ='Pretax Fuel Prices'!G60+'Fuel Taxes'!H60 -> 1.8262369e-05 | I60: ='Pretax Fuel Prices'!H60+'Fuel Taxes'!I60 -> 1.784819e-05 | J60: ='Pretax Fuel Prices'!I60+'Fuel Taxes'!J60 -> 1.7469798e-05 | ... AI60: ='Pretax Fuel Prices'!AH60+'Fuel Taxes'!AI60 -> 0
A61: Biofuel Gasoline
A62: Year | B62: 2021 | C62: 2022 | D62: 2023 | E62: 2024 | F62: 2025 | G62: 2026 | H62: 2027 | I62: 2028 | J62: 2029 | K62: 2030 | L62: 2031 | M62: 2032 | N62: 2033 | O62: 2034 | P62: 2035 | Q62: 2036 | R62: 2037 | S62: 2038 | T62: 2039 | U62: 2040 | V62: 2041 | W62: 2042 | X62: 2043 | Y62: 2044 | Z62: 2045 | AA62: 2046 | AB62: 2047 | AC62: 2048 | AD62: 2049 | AE62: 2050 | AF62: 2051 | AG62: 2052 | AH62: 2053 | AI62: 2054 | AJ62: 2055 | AK62: 2056 | AL62: 2057 | AM62: 2058 | AN62: 2059 | AO62: 2060 | AP62: 2061 | AQ62: 2062 | AR62: 2063 | AS62: 2064 | AT62: 2065 | AU62: 2066 | AV62: 2067 | AW62: 2068 | AX62: 2069 | AY62: 2070
A63: Transportation Sector | B63: ='Pretax Fuel Prices'!B63+'Fuel Taxes'!B63 -> 2.497881e-05 | C63: ='Pretax Fuel Prices'!C63+'Fuel Taxes'!C63 -> 2.497881e-05 | D63: ='Pretax Fuel Prices'!D63+'Fuel Taxes'!D63 -> 2.5287954e-05 | E63: ='Pretax Fuel Prices'!E63+'Fuel Taxes'!E63 -> 2.497881e-05 | F63: ='Pretax Fuel Prices'!F63+'Fuel Taxes'!F63 -> 3.0821626e-05 | G63: ='Pretax Fuel Prices'!G63+'Fuel Taxes'!G63 -> 2.9296517e-05 | H63: ='Pretax Fuel Prices'!H63+'Fuel Taxes'!H63 -> 2.9492308e-05 | I63: ='Pretax Fuel Prices'!I63+'Fuel Taxes'!I63 -> 2.938926e-05 | ... AI63: ='Pretax Fuel Prices'!AI63+'Fuel Taxes'!AI63 -> 0
A64: Electricity Sector | B64: ='Pretax Fuel Prices'!B64+'Fuel Taxes'!B64 -> 0 | C64: ='Pretax Fuel Prices'!C64+'Fuel Taxes'!C64 -> 0 | D64: ='Pretax Fuel Prices'!D64+'Fuel Taxes'!D64 -> 0 | E64: ='Pretax Fuel Prices'!E64+'Fuel Taxes'!E64 -> 0 | F64: ='Pretax Fuel Prices'!F64+'Fuel Taxes'!F64 -> 0 | G64: ='Pretax Fuel Prices'!G64+'Fuel Taxes'!G64 -> 0 | H64: ='Pretax Fuel Prices'!H64+'Fuel Taxes'!H64 -> 0 | I64: ='Pretax Fuel Prices'!I64+'Fuel Taxes'!I64 -> 0 | ... AI64: ='Pretax Fuel Prices'!AI64+'Fuel Taxes'!AI64 -> 0
A65: Residential Buildings Sector | B65: ='Pretax Fuel Prices'!B65+'Fuel Taxes'!B65 -> 0 | C65: ='Pretax Fuel Prices'!C65+'Fuel Taxes'!C65 -> 0 | D65: ='Pretax Fuel Prices'!D65+'Fuel Taxes'!D65 -> 0 | E65: ='Pretax Fuel Prices'!E65+'Fuel Taxes'!E65 -> 0 | F65: ='Pretax Fuel Prices'!F65+'Fuel Taxes'!F65 -> 0 | G65: ='Pretax Fuel Prices'!G65+'Fuel Taxes'!G65 -> 0 | H65: ='Pretax Fuel Prices'!H65+'Fuel Taxes'!H65 -> 0 | I65: ='Pretax Fuel Prices'!I65+'Fuel Taxes'!I65 -> 0 | ... AI65: ='Pretax Fuel Prices'!AI65+'Fuel Taxes'!AI65 -> 0
A66: Commercial Buildings Sector | B66: ='Pretax Fuel Prices'!B66+'Fuel Taxes'!B66 -> 0 | C66: ='Pretax Fuel Prices'!C66+'Fuel Taxes'!C66 -> 0 | D66: ='Pretax Fuel Prices'!D66+'Fuel Taxes'!D66 -> 0 | E66: ='Pretax Fuel Prices'!E66+'Fuel Taxes'!E66 -> 0 | F66: ='Pretax Fuel Prices'!F66+'Fuel Taxes'!F66 -> 0 | G66: ='Pretax Fuel Prices'!G66+'Fuel Taxes'!G66 -> 0 | H66: ='Pretax Fuel Prices'!H66+'Fuel Taxes'!H66 -> 0 | I66: ='Pretax Fuel Prices'!I66+'Fuel Taxes'!I66 -> 0 | ... AI66: ='Pretax Fuel Prices'!AI66+'Fuel Taxes'!AI66 -> 0
A67: Industry Sector | B67: ='Pretax Fuel Prices'!B67+'Fuel Taxes'!B67 -> 0 | C67: ='Pretax Fuel Prices'!C67+'Fuel Taxes'!C67 -> 0 | D67: ='Pretax Fuel Prices'!D67+'Fuel Taxes'!D67 -> 0 | E67: ='Pretax Fuel Prices'!E67+'Fuel Taxes'!E67 -> 0 | F67: ='Pretax Fuel Prices'!F67+'Fuel Taxes'!F67 -> 0 | G67: ='Pretax Fuel Prices'!G67+'Fuel Taxes'!G67 -> 0 | H67: ='Pretax Fuel Prices'!H67+'Fuel Taxes'!H67 -> 0 | I67: ='Pretax Fuel Prices'!I67+'Fuel Taxes'!I67 -> 0 | ... AI67: ='Pretax Fuel Prices'!AI67+'Fuel Taxes'!AI67 -> 0
A68: District Heating Sector | B68: ='Pretax Fuel Prices'!B68+'Fuel Taxes'!B68 -> 0 | C68: ='Pretax Fuel Prices'!C68+'Fuel Taxes'!C68 -> 0 | D68: ='Pretax Fuel Prices'!D68+'Fuel Taxes'!D68 -> 0 | E68: ='Pretax Fuel Prices'!E68+'Fuel Taxes'!E68 -> 0 | F68: ='Pretax Fuel Prices'!F68+'Fuel Taxes'!F68 -> 0 | G68: ='Pretax Fuel Prices'!G68+'Fuel Taxes'!G68 -> 0 | H68: ='Pretax Fuel Prices'!H68+'Fuel Taxes'!H68 -> 0 | I68: ='Pretax Fuel Prices'!I68+'Fuel Taxes'!I68 -> 0 | ... AI68: ='Pretax Fuel Prices'!AI68+'Fuel Taxes'!AI68 -> 0
A69: LULUCF Sector | B69: ='Pretax Fuel Prices'!B69+'Fuel Taxes'!B69 -> 0 | C69: ='Pretax Fuel Prices'!C69+'Fuel Taxes'!C69 -> 0 | D69: ='Pretax Fuel Prices'!D69+'Fuel Taxes'!D69 -> 0 | E69: ='Pretax Fuel Prices'!E69+'Fuel Taxes'!E69 -> 0 | F69: ='Pretax Fuel Prices'!F69+'Fuel Taxes'!F69 -> 0 | G69: ='Pretax Fuel Prices'!G69+'Fuel Taxes'!G69 -> 0 | H69: ='Pretax Fuel Prices'!H69+'Fuel Taxes'!H69 -> 0 | I69: ='Pretax Fuel Prices'!I69+'Fuel Taxes'!I69 -> 0 | ... AI69: ='Pretax Fuel Prices'!AI69+'Fuel Taxes'!AI69 -> 0
A70: Geoengineering Sector | B70: ='Pretax Fuel Prices'!B70+'Fuel Taxes'!B70 -> 0 | C70: ='Pretax Fuel Prices'!C70+'Fuel Taxes'!C70 -> 0 | D70: ='Pretax Fuel Prices'!D70+'Fuel Taxes'!D70 -> 0 | E70: ='Pretax Fuel Prices'!E70+'Fuel Taxes'!E70 -> 0 | F70: ='Pretax Fuel Prices'!F70+'Fuel Taxes'!F70 -> 0 | G70: ='Pretax Fuel Prices'!G70+'Fuel Taxes'!G70 -> 0 | H70: ='Pretax Fuel Prices'!H70+'Fuel Taxes'!H70 -> 0 | I70: ='Pretax Fuel Prices'!I70+'Fuel Taxes'!I70 -> 0 | ... AI70: ='Pretax Fuel Prices'!AI70+'Fuel Taxes'!AI70 -> 0
A71: Biofuel Diesel
A72: Year | B72: 2021 | C72: 2022 | D72: 2023 | E72: 2024 | F72: 2025 | G72: 2026 | H72: 2027 | I72: 2028 | J72: 2029 | K72: 2030 | L72: 2031 | M72: 2032 | N72: 2033 | O72: 2034 | P72: 2035 | Q72: 2036 | R72: 2037 | S72: 2038 | T72: 2039 | U72: 2040 | V72: 2041 | W72: 2042 | X72: 2043 | Y72: 2044 | Z72: 2045 | AA72: 2046 | AB72: 2047 | AC72: 2048 | AD72: 2049 | AE72: 2050 | AF72: 2051 | AG72: 2052 | AH72: 2053 | AI72: 2054 | AJ72: 2055 | AK72: 2056 | AL72: 2057 | AM72: 2058 | AN72: 2059 | AO72: 2060 | AP72: 2061 | AQ72: 2062 | AR72: 2063 | AS72: 2064 | AT72: 2065 | AU72: 2066 | AV72: 2067 | AW72: 2068 | AX72: 2069 | AY72: 2070
A73: Transportation Sector | B73: ='Pretax Fuel Prices'!B73+'Fuel Taxes'!B73 -> 1.9404341e-05 | C73: ='Pretax Fuel Prices'!C73+'Fuel Taxes'!C73 -> 1.9404341e-05 | D73: ='Pretax Fuel Prices'!D73+'Fuel Taxes'!D73 -> 2.0104498e-05 | E73: ='Pretax Fuel Prices'!E73+'Fuel Taxes'!E73 -> 1.9404341e-05 | F73: ='Pretax Fuel Prices'!F73+'Fuel Taxes'!F73 -> 1.9513457e-05 | G73: ='Pretax Fuel Prices'!G73+'Fuel Taxes'!G73 -> 1.9813524e-05 | H73: ='Pretax Fuel Prices'!H73+'Fuel Taxes'!H73 -> 1.9931732e-05 | I73: ='Pretax Fuel Prices'!I73+'Fuel Taxes'!I73 -> 2.0286357e-05 | ... AI73: ='Pretax Fuel Prices'!AI73+'Fuel Taxes'!AI73 -> 0
A74: Electricity Sector | B74: ='Pretax Fuel Prices'!B74+'Fuel Taxes'!B74 -> 1.9404341e-05 | C74: ='Pretax Fuel Prices'!C74+'Fuel Taxes'!C74 -> 1.9404341e-05 | D74: ='Pretax Fuel Prices'!D74+'Fuel Taxes'!D74 -> 1.994158e-05 | E74: ='Pretax Fuel Prices'!E74+'Fuel Taxes'!E74 -> 1.9404341e-05 | F74: ='Pretax Fuel Prices'!F74+'Fuel Taxes'!F74 -> 1.8730516e-05 | G74: ='Pretax Fuel Prices'!G74+'Fuel Taxes'!G74 -> 1.8211489e-05 | H74: ='Pretax Fuel Prices'!H74+'Fuel Taxes'!H74 -> 1.7601404e-05 | I74: ='Pretax Fuel Prices'!I74+'Fuel Taxes'!I74 -> 1.7228068e-05 | ... AI74: ='Pretax Fuel Prices'!AI74+'Fuel Taxes'!AI74 -> 0
A75: Residential Buildings Sector | B75: ='Pretax Fuel Prices'!B75+'Fuel Taxes'!B75 -> 1.3092837e-05 | C75: ='Pretax Fuel Prices'!C75+'Fuel Taxes'!C75 -> 1.3092837e-05 | D75: ='Pretax Fuel Prices'!D75+'Fuel Taxes'!D75 -> 1.3455503e-05 | E75: ='Pretax Fuel Prices'!E75+'Fuel Taxes'!E75 -> 1.3092837e-05 | F75: ='Pretax Fuel Prices'!F75+'Fuel Taxes'!F75 -> 1.3295684e-05 | G75: ='Pretax Fuel Prices'!G75+'Fuel Taxes'!G75 -> 1.3652202e-05 | H75: ='Pretax Fuel Prices'!H75+'Fuel Taxes'!H75 -> 1.3898077e-05 | I75: ='Pretax Fuel Prices'!I75+'Fuel Taxes'!I75 -> 1.4303771e-05 | ... AI75: ='Pretax Fuel Prices'!AI75+'Fuel Taxes'!AI75 -> 0
A76: Commercial Buildings Sector | B76: ='Pretax Fuel Prices'!B76+'Fuel Taxes'!B76 -> 1.9404341e-05 | C76: ='Pretax Fuel Prices'!C76+'Fuel Taxes'!C76 -> 1.9404341e-05 | D76: ='Pretax Fuel Prices'!D76+'Fuel Taxes'!D76 -> 1.9939821e-05 | E76: ='Pretax Fuel Prices'!E76+'Fuel Taxes'!E76 -> 1.9404341e-05 | F76: ='Pretax Fuel Prices'!F76+'Fuel Taxes'!F76 -> 1.8814406e-05 | G76: ='Pretax Fuel Prices'!G76+'Fuel Taxes'!G76 -> 1.8442293e-05 | H76: ='Pretax Fuel Prices'!H76+'Fuel Taxes'!H76 -> 1.7915889e-05 | I76: ='Pretax Fuel Prices'!I76+'Fuel Taxes'!I76 -> 1.7616383e-05 | ... AI76: ='Pretax Fuel Prices'!AI76+'Fuel Taxes'!AI76 -> 0
A77: Industry Sector | B77: ='Pretax Fuel Prices'!B77+'Fuel Taxes'!B77 -> 1.9404341e-05 | C77: ='Pretax Fuel Prices'!C77+'Fuel Taxes'!C77 -> 1.9404341e-05 | D77: ='Pretax Fuel Prices'!D77+'Fuel Taxes'!D77 -> 1.9941832e-05 | E77: ='Pretax Fuel Prices'!E77+'Fuel Taxes'!E77 -> 1.9404341e-05 | F77: ='Pretax Fuel Prices'!F77+'Fuel Taxes'!F77 -> 1.883952e-05 | G77: ='Pretax Fuel Prices'!G77+'Fuel Taxes'!G77 -> 1.8484229e-05 | H77: ='Pretax Fuel Prices'!H77+'Fuel Taxes'!H77 -> 1.7964958e-05 | I77: ='Pretax Fuel Prices'!I77+'Fuel Taxes'!I77 -> 1.7691658e-05 | ... AI77: ='Pretax Fuel Prices'!AI77+'Fuel Taxes'!AI77 -> 0
A78: District Heating Sector | B78: ='Pretax Fuel Prices'!B78+'Fuel Taxes'!B78 -> 1.9404341e-05 | C78: ='Pretax Fuel Prices'!C78+'Fuel Taxes'!C78 -> 1.9404341e-05 | D78: ='Pretax Fuel Prices'!D78+'Fuel Taxes'!D78 -> 1.9941832e-05 | E78: ='Pretax Fuel Prices'!E78+'Fuel Taxes'!E78 -> 1.9404341e-05 | F78: ='Pretax Fuel Prices'!F78+'Fuel Taxes'!F78 -> 1.883952e-05 | G78: ='Pretax Fuel Prices'!G78+'Fuel Taxes'!G78 -> 1.8484229e-05 | H78: ='Pretax Fuel Prices'!H78+'Fuel Taxes'!H78 -> 1.7964958e-05 | I78: ='Pretax Fuel Prices'!I78+'Fuel Taxes'!I78 -> 1.7691658e-05 | ... AI78: ='Pretax Fuel Prices'!AI78+'Fuel Taxes'!AI78 -> 0
A79: LULUCF Sector | B79: ='Pretax Fuel Prices'!B79+'Fuel Taxes'!B79 -> 0 | C79: ='Pretax Fuel Prices'!C79+'Fuel Taxes'!C79 -> 0 | D79: ='Pretax Fuel Prices'!D79+'Fuel Taxes'!D79 -> 0 | E79: ='Pretax Fuel Prices'!E79+'Fuel Taxes'!E79 -> 0 | F79: ='Pretax Fuel Prices'!F79+'Fuel Taxes'!F79 -> 0 | G79: ='Pretax Fuel Prices'!G79+'Fuel Taxes'!G79 -> 0 | H79: ='Pretax Fuel Prices'!H79+'Fuel Taxes'!H79 -> 0 | I79: ='Pretax Fuel Prices'!I79+'Fuel Taxes'!I79 -> 0 | ... AI79: ='Pretax Fuel Prices'!AI79+'Fuel Taxes'!AI79 -> 0
A80: Geoengineering Sector | B80: ='Pretax Fuel Prices'!B80+'Fuel Taxes'!B80 -> 1.9404341e-05 | C80: ='Pretax Fuel Prices'!C80+'Fuel Taxes'!C80 -> 1.9404341e-05 | D80: ='Pretax Fuel Prices'!D80+'Fuel Taxes'!D80 -> 1.9941832e-05 | E80: ='Pretax Fuel Prices'!E80+'Fuel Taxes'!E80 -> 1.9404341e-05 | F80: ='Pretax Fuel Prices'!F80+'Fuel Taxes'!F80 -> 1.883952e-05 | G80: ='Pretax Fuel Prices'!G80+'Fuel Taxes'!G80 -> 1.8484229e-05 | H80: ='Pretax Fuel Prices'!H80+'Fuel Taxes'!H80 -> 1.7964958e-05 | I80: ='Pretax Fuel Prices'!I80+'Fuel Taxes'!I80 -> 1.7691658e-05 | ... AI80: ='Pretax Fuel Prices'!AI80+'Fuel Taxes'!AI80 -> 0
A81: Jet Fuel
A82: Year | B82: 2021 | C82: 2022 | D82: 2023 | E82: 2024 | F82: 2025 | G82: 2026 | H82: 2027 | I82: 2028 | J82: 2029 | K82: 2030 | L82: 2031 | M82: 2032 | N82: 2033 | O82: 2034 | P82: 2035 | Q82: 2036 | R82: 2037 | S82: 2038 | T82: 2039 | U82: 2040 | V82: 2041 | W82: 2042 | X82: 2043 | Y82: 2044 | Z82: 2045 | AA82: 2046 | AB82: 2047 | AC82: 2048 | AD82: 2049 | AE82: 2050 | AF82: 2051 | AG82: 2052 | AH82: 2053 | AI82: 2054 | AJ82: 2055 | AK82: 2056 | AL82: 2057 | AM82: 2058 | AN82: 2059 | AO82: 2060 | AP82: 2061 | AQ82: 2062 | AR82: 2063 | AS82: 2064 | AT82: 2065 | AU82: 2066 | AV82: 2067 | AW82: 2068 | AX82: 2069 | AY82: 2070
A83: Transportation Sector | B83: ='Pretax Fuel Prices'!B83+'Fuel Taxes'!B83 -> 2.5477934e-05 | C83: ='Pretax Fuel Prices'!C83+'Fuel Taxes'!C83 -> 2.5477934e-05 | D83: ='Pretax Fuel Prices'!D83+'Fuel Taxes'!D83 -> 2.6397241e-05 | E83: ='Pretax Fuel Prices'!E83+'Fuel Taxes'!E83 -> 2.5477934e-05 | F83: ='Pretax Fuel Prices'!F83+'Fuel Taxes'!F83 -> 2.5621203e-05 | G83: ='Pretax Fuel Prices'!G83+'Fuel Taxes'!G83 -> 2.6015192e-05 | H83: ='Pretax Fuel Prices'!H83+'Fuel Taxes'!H83 -> 2.6170399e-05 | I83: ='Pretax Fuel Prices'!I83+'Fuel Taxes'!I83 -> 2.6636022e-05 | ... AI83: ='Pretax Fuel Prices'!AI83+'Fuel Taxes'!AI83 -> 0
A84: Electricity Sector | B84: ='Pretax Fuel Prices'!B84+'Fuel Taxes'!B84 -> 0 | C84: ='Pretax Fuel Prices'!C84+'Fuel Taxes'!C84 -> 0 | D84: ='Pretax Fuel Prices'!D84+'Fuel Taxes'!D84 -> 0 | E84: ='Pretax Fuel Prices'!E84+'Fuel Taxes'!E84 -> 0 | F84: ='Pretax Fuel Prices'!F84+'Fuel Taxes'!F84 -> 0 | G84: ='Pretax Fuel Prices'!G84+'Fuel Taxes'!G84 -> 0 | H84: ='Pretax Fuel Prices'!H84+'Fuel Taxes'!H84 -> 0 | I84: ='Pretax Fuel Prices'!I84+'Fuel Taxes'!I84 -> 0 | ... AI84: ='Pretax Fuel Prices'!AI84+'Fuel Taxes'!AI84 -> 0
A85: Residential Buildings Sector | B85: ='Pretax Fuel Prices'!B85+'Fuel Taxes'!B85 -> 1.3092837e-05 | C85: ='Pretax Fuel Prices'!C85+'Fuel Taxes'!C85 -> 1.3092837e-05 | D85: ='Pretax Fuel Prices'!D85+'Fuel Taxes'!D85 -> 1.3455503e-05 | E85: ='Pretax Fuel Prices'!E85+'Fuel Taxes'!E85 -> 1.3092837e-05 | F85: ='Pretax Fuel Prices'!F85+'Fuel Taxes'!F85 -> 1.3295684e-05 | G85: ='Pretax Fuel Prices'!G85+'Fuel Taxes'!G85 -> 1.3652202e-05 | H85: ='Pretax Fuel Prices'!H85+'Fuel Taxes'!H85 -> 1.3898077e-05 | I85: ='Pretax Fuel Prices'!I85+'Fuel Taxes'!I85 -> 1.4303771e-05 | ... AI85: ='Pretax Fuel Prices'!AI85+'Fuel Taxes'!AI85 -> 0
